Workbook

Sheet Fund I RYG
B2: Fund I Portfolio Health
B3: Company | C3: Initial Inv. Date | D3: Initial Inv. Series | E3: Current Inv. Series | F3: Last Valuation | G3: SV Holding Value | H3: FD% | I3: $ Invested | J3: % of Invested Cost | K3: Current Market Value | L3: Portfolio Value | M3: MOIC | N3: 2025E Rev | O3: 2024A Rev | P3: 2025E ARR | Q3: 2024 ARR | R3: Rev/ARR Growth YoY | S3: Rev Multiple | T3: Q2 Status | U3: Current Q3 Status | V3: Rationale | W3: Fundraising/Current Runway | X3: Other key highlights
B4: Spring | C4: 43244 | D4: Seed | E4: E | F4: 3300000000 | G4: 3300000000 | H4: 0.0087 | I4: 1449990.3 | J4: =I4/$I$25 -> 0.095270258 | K4: 28841289 | L4: =K4/$K$25 -> 0.31465487 | M4: =K4/I4 -> 19.890677 | N4: No FS | O4: No FS | P4: 750000000 | Q4: No FS | R4: No data | S4: - | T4: 1 | U4: 1 | V4: Continues to beat plan and is approaching profitability | W4: Potential IPO Candidate | X4: In Oct 2025, released the “VERA‑MH” initiative, described as the first open-source evaluation framework for validating AI in mental-health care
B5: Rightway Health | C5: 43768 | D5: A | E5: C | F5: 625000000 | G5: 625000000 | H5: 0.0215 | I5: 999998.47 | J5: =I5/$I$25 -> 0.065703964 | K5: 13426663 | L5: =K5/$K$25 -> 0.14648322 | M5: =K5/I5 -> 13.426684 | N5: 45000000 | O5: 25972982 | P5: 83000000 | Q5: 49300395 | R5: =N5/O5-1 -> 0.73256964 | S5: =F5/N5 -> 13.888889 | T5: 1 | U5: 1 | V5: ARR is projected to to grow to $132M or by 60% by H12026. Strong retention and growth metrics | W5: 36 months | X5: Rebranded logo & reported: ~113% revenue retention, >97% client retention, and year-over-year member growth of 100%+ in 2025
B6: Human Interest | C6: 43670 | D6: B | E6: D | F6: 3000000000 | G6: 3000000000 | H6: 0.0041973601 | I6: 1090002.1 | J6: =I6/$I$25 -> 0.071617565 | K6: 10700000 | L6: =K6/$K$25 -> 0.11673567 | M6: =K6/I6 -> 9.8164952 | N6: =108402000/3*4 -> 144536000 | O6: 105094000 | P6: 161840913 | Q6: 119029044 | R6: =N6/O6-1 -> 0.37530211 | S6: =F6/N6 -> 20.756075 | T6: 1 | U6: 1 | V6: Strong revenue growth, working with 37% of all new 401(k) plans. Recent regulatory push to bring alternatives into plans. Q3 ARR at ~$162M
B7: Multiverse | C7: 43395 | D7: Seed | E7: D | F7: 1700000000 | G7: 1700000000 | H7: 0.0055 | I7: 834995.61 | J7: =I7/$I$25 -> 0.054862605 | K7: 9377802.2 | L7: =K7/$K$25 -> 0.10231065 | M7: =K7/I7 -> 11.23096 | N7: 100000000 | O7: No FS | P7: No data | Q7: No FS | R7: No data | S7: =+G7/N7 -> 17 | T7: 1 | U7: 1 | V7: AI retraining and upskilling providing tailwind, will finish Q4 with just over $70m of bookings, exceeding $62m forecast. Reported revenue was over $100m. Finished the year with Q4 growth YoY at 100%​, GM in Q4 reached 84%, +8pp YoY. Added > 250 new logos to customer list, launched in US, $38M Revenue in Q3 | W7: 44 months
B8: Rula | C8: 43719 | D8: Seed | E8: C | F8: 1250000000 | G8: 1250000000 | H8: 0.0055704752 | I8: 496199.35 | J8: =I8/$I$25 -> 0.032602314 | K8: 6277910.6 | L8: =K8/$K$25 -> 0.068491223 | M8: =K8/I8 -> 12.651993 | N8: 236000000 | O8: 121610000 | P8: 786000000 | R8: =N8/O8-1 -> 0.94062988 | S8: =F8/N8 -> 5.2966102 | T8: 1 | U8: 1 | V8: Forecasting ~2x y/y growth with revenue run rate above $200M by year end
B9: Carrot | C9: 43333 | D9: Seed | E9: D | F9: 600000000 | G9: 600000000 | H9: 0.0094339757 | I9: 999996.37 | J9: =I9/$I$25 -> 0.065703826 | K9: 5663568.2 | L9: =K9/$K$25 -> 0.061788824 | M9: =K9/I9 -> 5.6635888 | N9: No FS | O9: No FS | P9: No FS | Q9: No FS | R9: N/A | S9: - | T9: 1 | U9: 1 | V9: Scaling well with significant partnerships helping cover over 17,000 providers nationwide, expanded its U.S provider network significantly: adding ~4,200 new clinics/providers across all 50 states
B10: Pelago | C10: 43558 | D10: Seed | E10: C | F10: 365000000 | G10: 365000000 | H10: 0.01145385 | I10: 549993.11 | J10: =I10/$I$25 -> 0.036136783 | K10: 4289097.2 | L10: =K10/$K$25 -> 0.046793516 | M10: =K10/I10 -> 7.7984561 | N10: =15400000+5750000 -> 21150000 | O10: 22182779 | P10: 20000000 | Q10: 15029622 | R10: =N10/O10-1 -> -0.046557692 | S10: =F10/N10 -> 17.257683 | T10: 1 | U10: 0 | V10: Revenue is down slightly, sig decrease in 2025 ARR but forecasted ARR $10M in H1 2026 | W10: 13 months
B11: Galileo | C11: 43866 | D11: B | E11: C | F11: 361500000 | G11: 361500000 | H11: 0.0077 | I11: =1499992.69+252000 -> 1751992.7 | J11: =I11/$I$25 -> 0.11511304 | K11: 4040579.9 | L11: =K11/$K$25 -> 0.044082223 | M11: =K11/I11 -> 2.3062767 | N11: 47000000 | O11: 39582208 | P11: 20150000 | Q11: 6021046 | R11: =N11/O11-1 -> 0.18740218 | S11: =F11/N11 -> 7.6914894 | T11: -1 | U11: 0 | V11: Completed recap in Q3, completing transition away from shared savings to FFS / Capitated, $16M loan from SVB | W11: Budget in flux | X11: Barbara Wachsman joined the Galileo team as Head of Employer Strategy.
B12: XP | C12: 43817 | D12: Seed | E12: B | F12: 120000000 | G12: 120000000 | H12: 0.016510945 | I12: 800000 | J12: =I12/$I$25 -> 0.052563251 | K12: 1981323 | L12: =K12/$K$25 -> 0.021615987 | M12: =K12/I12 -> 2.4766537 | N12: =8889758+3653000 -> 12542758 | O12: 9100316 | P12: 13806000 | Q12: 11207000 | R12: =N12/O12-1 -> 0.37827719 | S12: =F12/N12 -> 9.5672738 | T12: 1 | U12: 0 | V12: Slight ARR growth in Q3/25 with the launch of a few smaller clients, followed by material growth in Q4/25 . Based upon the implemented expense reductions, included a substantial reduction of our staff, we expect to reach breakeven without the need for external capital | W12: - | X12: how is enterprise adoption panning out?, Ameriflex partnership?
B13: Fountain | C13: 43789 | D13: B | E13: C | F13: 860000000 | G13: 860000000 | H13: 0.0019508497 | I13: 499996.82 | J13: =I13/$I$25 -> 0.032851823 | K13: 1772396.1 | L13: =K13/$K$25 -> 0.01933662 | M13: =K13/I13 -> 3.5448147 | N13: =24222597+8497000 -> 32719597 | O13: 36517866 | P13: 33851000 | Q13: 31676017 | R13: =N13/O13-1 -> -0.10401125 | S13: =F13/N13 -> 26.283942 | T13: 0 | U13: 0 | V13: Revenue is down, ARR forecasts revised down from ~41M to $34M | W13: 34 months | X13: Announced its “Agentic-First Frontline Operating System” at HR Tech 2025 featuring a 12-product suite spanning hiring, onboarding, shift-management, referrals, communications and compliance.
B14: Karat | C14: 43592 | D14: B | E14: C | F14: 1111200000 | G14: Pref Stack - $168.8M | H14: 0.004707841 | I14: 999994.83 | J14: =I14/$I$25 -> 0.065703724 | K14: 999994.83 | L14: =K14/$K$25 -> 0.010909819 | M14: =K14/I14 -> 1 | N14: =16734498+6826439 -> 23560937 | O14: 16800000 | R14: =N14/O14-1 -> 0.40243673 | S14: =F14/N14 -> 47.16281 | T14: 0 | U14: 0 | V14: Holding at preference stack, modest growth (1.4x) but 2+ years of runway. | W14: 24 months | X14: Acquired Byteboard in early 2025, skill based technical assessment company, how is this acq progressing? New add on services?
B15: Ladder | C15: 43866 | D15: C | E15: D | F15: 330000000 | G15: 330000000 | H15: 0.0024800544 | I15: 749994.59 | J15: =I15/$I$25 -> 0.049277693 | K15: 759917.21 | L15: =K15/$K$25 -> 0.0082906021 | M15: =K15/I15 -> 1.0132302 | N15: =26013880*2 -> 52027760 | O15: 49313412 | P15: No forecasts provided | R15: =N15/O15-1 -> 0.055042794 | S15: =F15/N15 -> 6.3427678 | T15: 0 | U15: 0 | V15: Recapitalized business, at $50M revenue run rate
B16: Brightside Benefit | C16: 43775 | D16: A | E16: B | F16: 170000000 | G16: 170000000 | H16: 0.0011185071 | I16: 499999.53 | J16: =I16/$I$25 -> 0.032852001 | K16: 438844.21 | L16: =K16/$K$25 -> 0.0047877357 | M16: =K16/I16 -> 0.87768924 | N16: 29602894 | O16: 19460502 | P16: 32000000 | Q16: 31348884 | R16: =N16/O16-1 -> 0.52117833 | S16: =F16/N16 -> 5.7426818 | T16: 0 | U16: 0 | V16: Closed a round and scaled to $30M ARR with major partnerships
B17: Charthop | C17: 43740 | D17: Seed | E17: C | F17: 270000000 | G17: Pref Stack - $75M | H17: 0.0082354955 | I17: 1200001.7 | J17: =I17/$I$25 -> 0.078844987 | K17: 1200001.7 | L17: =K17/$K$25 -> 0.013091869 | M17: =K17/I17 -> 1 | N17: 8668373 | O17: 7936982 | P17: 8074878 | Q17: 9445102 | R17: =N17/O17-1 -> 0.092149762 | S17: =F17/N17 -> 31.147714 | T17: -1 | U17: -1 | V17: Revenue forecast is up ~9%, signed new business with Kraken, ~1.5 yrs of runway, holding at preference stack, forecasting ~12M by end of 2026. ARR up 7% YOY | W17: 16 months | X17: introduced ChartHop AI, a new capability that merges people data with business metrics and overlays role-based security controls, new VP of sales hired, feedback from HR Tech?
B18: Terminal | C18: 43727 | D18: B | E18: B | F18: 137000000 | G18: 0 | H18: 0.0041771259 | I18: 599999.73 | J18: =I18/$I$25 -> 0.039422421 | K18: 0 | L18: =K18/$K$25 -> 0 | M18: =K18/I18 -> 0 | N18: 47509757 | O18: 47067203 | P18: 49275176 | Q18: 41384666 | R18: =N18/O18-1 -> 0.0094025982 | S18: =F18/N18 -> 2.8836182 | T18: -1 | U18: -1 | V18: Cash flow positive mid-next year, revenue is flat
B19: Hone | C19: 43262 | D19: Seed | E19: B | F19: 126200000 | G19: 126200000 | H19: 0.013943702 | I19: 682666.27 | J19: =I19/$I$25 -> 0.044853948 | K19: 1756737.3 | L19: =K19/$K$25 -> 0.019165785 | M19: =K19/I19 -> 2.5733472 | N19: 7921721 | O19: 7590763 | P19: 8554337 | Q19: 7118996 | R19: =N19/O19-1 -> 0.043600097 | S19: =F19/N19 -> 15.930882 | T19: 0 | U19: -1 | V19: Revenue is flat, opportunity to reinvigorate growth via AI automation? 8 month runway left | W19: <1 year | X19: Hone has rolled out an AI Coach feature to reinforce skills “in the flow of work” alongside live classes.
B20: Hatch | C20: 43665 | D20: Seed | E20: Seed | F20: 25000000 | G20: 25000000 | H20: 0.0058239338 | I20: 258903.8 | J20: =I20/$I$25 -> 0.017011032 | K20: 133950.81 | L20: =K20/$K$25 -> 0.0014613866 | M20: =K20/I20 -> 0.51737674 | N20: 2974911 | O20: 760642 | P20: 1219314 | Q20: 848711 | R20: =N20/O20-1 -> 2.9110528 | S20: =F20/N20 -> 8.4036127 | T20: 0 | U20: -1 | V20: Strong rev growth, ARR seems stalled ~$1M, not much info
B21: Cleo | C21: 43328 | D21: A | E21: C | F21: 231000000 | G21: 0 | H21: 0.0016734774 | I21: 100000 | J21: =I21/$I$25 -> 0.0065704064 | K21: 0 | L21: =K21/$K$25 -> 0 | M21: =K21/I21 -> 0 | N21: No FS | O21: No FS | P21: No data | Q21: No FS | R21: No data | T21: -1 | U21: -1 | V21: N/A - proactive write-off
B22: Enrich | C22: 43829 | D22: Seed | E22: Seed | F22: 11000000 | G22: 0 | H22: 0.038095113 | I22: 399999.44 | J22: =I22/$I$25 -> 0.026281589 | K22: 0 | L22: =K22/$K$25 -> 0 | M22: =K22/I22 -> 0 | N22: 1038000 | O22: 622163 | Q22: 608121 | R22: =N22/O22-1 -> 0.66837308 | S22: =F22/N22 -> 10.597303 | T22: -1 | U22: -1 | V22: N/A - proactive write-off | W22: 30 months
B23: Vetty | C23: 43857 | D23: Seed | E23: A | F23: 13000000 | G23: 0 | H23: N/A | I23: 255034 | J23: =I23/$I$25 -> 0.01675677 | K23: 0 | L23: =K23/$K$25 -> 0 | M23: =K23/I23 -> 0 | N23: =7588530+3119277 -> 10707807 | O23: 10000000 | P23: 12477107 | Q23: 12000000 | R23: =N23/O23-1 -> 0.0707807 | S23: =F23/N23 -> 1.2140675 | T23: -1 | U23: -1 | V23: N/A - proactive write-off, ARR revised down from $14M to $12M, 4 months of runway | W23: 4 months
I25: =SUM(I4:I23) -> 15219759 | K25: =SUM(K4:K23) -> 91660075 | S25: =AVERAGE(S10:S18) -> 17.119998

Sheet Fund I Inv Char
M1: 21000000
B2: Fund I Current Investment Characteristics
B3: Company | C3: Series | D3: FD% | E3: Initial Cost | F3: Last Valuation | G3: Holding Value | H3: Potential Post Money | I3: $ Invested | J3: Current Market Value | K3: New Mark | L3: Multiple | N3: 2025 E Revenue/ARR | O3: Holding Value Implied Mult. | P3: EV at 10x | Q3: 10x EV> Holding Value | R3: 10x EV? Total Raised | S3: Raised to Date | V3: Additional Value | W3: Expected Gross MOIC | X3: Additional TVPI
B4: Spring | C4: E | D4: 0.0087 | E4: 23000000 | F4: 3300000000 | G4: 3300000000 | I4: 1449990.3 | J4: 28841289 | L4: =J4/I4 -> 19.890677 | M4: 2225.9968 | S4: $467M
B5: Rightway Health | C5: C | D5: 0.0215 | E5: 35000000 | F5: 625000000 | G5: 625000000 | H5: =ROUND(34.5/18.79*G5,-6) -> 1148000000 | I5: 999998.47 | J5: 13426663 | K5: =H5*D5 -> 24682000 | L5: =J5/I5 -> 13.426684 | M5: 12548.721 | V5: =K5-J5 -> 11255337 | W5: =K5/I5 -> 24.682038 | X5: =V5/20730000 -> 0.5429492
B6: Multiverse | C6: D | D6: 0.0055 | E6: 26000000 | F6: 1700000000 | G6: 1700000000 | I6: 834995.61 | J6: 9377802.2 | L6: =J6/I6 -> 11.23096 | M6: 1506.0563 | N6: 10554783 | O6: 11.956665 | P6: 105547830 | Q6: No | S6: $415M
B7: Rula | C7: C | D7: 0.0055704752 | E7: 12000000 | F7: 1250000000 | G7: 1250000000 | I7: 496199.35 | J7: 6277910.6 | L7: =J7/I7 -> 12.651993 | M7: 2153.0683 | Y7: 10x net revenue for a competitor
B8: Carrot | C8: D | D8: 0.0094339757 | E8: 10000000 | F8: 600000000 | G8: 600000000 | I8: 999996.37 | J8: 5663568.2 | L8: =J8/I8 -> 5.6635888 | M8: 3901.7482
B9: Human Interest | C9: F | D9: 0.0041973601 | E9: 37000000 | F9: 1250000000 | G9: 1250000000 | H9: 3000000000 | I9: 1090002.1 | J9: 5589792.5 | K9: 10743747 | L9: =J9/I9 -> 5.1282403 | M9: 1833.4447 | N9: 20000000 | O9: 18.25 | P9: 200000000 | Q9: No | S9: $700M | V9: =K9-J9 -> 5153954.5 | W9: =K9/I9 -> 9.85663 | X9: =V9/20730000 -> 0.24862299
B10: Pelago | C10: C | D10: 0.01145385 | E10: 18000000 | F10: 365000000 | G10: 365000000 | I10: 549993.11 | J10: 4289097.2 | L10: =J10/I10 -> 7.7984561 | M10: 4460.6435 | N10: 21900000 | O10: 50.739726 | P10: 219000000 | Q10: No
B11: Galileo | C11: C | D11: 0.0064925049 | E11: 106000000 | F11: 600000000 | G11: 361500000 | I11: =1499992.69+252000 -> 1751992.7 | J11: 2656434 | L11: =J11/I11 -> 1.5162358 | M11: 3605.8102 | N11: 2111099 | O11: 11.842173 | P11: 21110990 | Q11: No
B12: XP | C12: B | D12: 0.016510945 | E12: 12000000 | F12: 120000000 | G12: 120000000 | I12: 800000 | J12: 1981323 | L12: =J12/I12 -> 2.4766537 | M12: 3769.8759
B13: Fountain | C13: C | D13: 0.0019508497 | E13: 79000000 | F13: 860000000 | G13: 860000000 | I13: 499996.82 | J13: 1772396.1 | L13: =J13/I13 -> 3.5448147 | M13: 2132.4175 | N13: 21000000 | O13: 15.952381 | P13: 210000000 | Q13: No
B14: Hone | C14: B | D14: 0.013943702 | E14: 8000000 | F14: 126200000 | G14: 126200000 | I14: 682666.27 | J14: 1756737.3 | L14: =J14/I14 -> 2.5733472 | M14: 5027.3802 | N14: 41337300 | O14: 3.3141981 | P14: 413373000 | Q14: Yes
B15: Charthop | C15: C | D15: 0.0082354955 | E15: 25000000 | F15: 270000000 | G15: Preference Stack - $74M | I15: 1200001.7 | J15: 1200001.7 | L15: =J15/I15 -> 1 | M15: 2549.9376 | N15: 9744878 | O15: 27.706863 | P15: 97448780 | Q15: No
B16: Karat | C16: C | D16: 0.004707841 | E16: 138000000 | F16: 1111200000 | G16: Preference Stack - $170M | I16: 999994.83 | J16: 999994.83 | L16: =J16/I16 -> 1 | M16: 965.57517 | N16: 70638024 | O16: 8.8479259 | P16: 706380240 | Q16: Yes
B17: Ladder | C17: D | D17: 0.0024800544 | E17: 234000000 | F17: 330000000 | G17: 330000000 | I17: 749994.59 | J17: 759917.21 | L17: =J17/I17 -> 1.0132302 | M17: 18775.026 | N17: 37421387 | O17: 4.5428567 | P17: 3.7421387e+08 | Q17: Yes
B18: Brightside Benefit | C18: B | D18: 0.0011185071 | E18: 135000000 | F18: 170000000 | G18: 170000000 | I18: 499999.53 | J18: 438844.21 | L18: =J18/I18 -> 0.87768924 | M18: 10764.54 | N18: 50000000 | O18: 17.2 | P18: 500000000 | Q18: No
B19: Hatch | C19: Seed | D19: 0.0058239338 | E19: 25000000 | F19: 25000000 | G19: 25000000 | I19: 258903.8 | J19: 133950.81 | L19: =J19/I19 -> 0.51737674 | M19: 1271.8836
B20: Cleo | C20: C | D20: 0.0016734774 | E20: 33000000 | F20: 231000000 | G20: 0 | I20: 100000 | J20: 0 | L20: =J20/I20 -> 0 | M20: 551.25181
B21: Terminal | C21: B | D21: 0.0041771259 | E21: 137000000 | F21: 137000000 | G21: 0 | I21: 599999.73 | J21: 0 | L21: =J21/I21 -> 0 | M21: #VALUE!
B22: Enrich | C22: Seed | D22: 0.038095113 | E22: 11000000 | F22: 11000000 | G22: 0 | I22: 399999.44 | J22: 0 | L22: =J22/I22 -> 0 | M22: 8467.5563
B23: Vetty | C23: A | D23: N/A | E23: 13000000 | F23: 13000000 | G23: 0 | I23: 255034 | J23: 0 | L23: =J23/I23 -> 0 | M23: 3234.4989 | N23: 28530046 | O23: 21.03046 | P23: 285300460 | Q23: No
I25: =SUM(I4:I23) -> 15219759 | J25: =SUM(J4:J23) -> 85165722 | L25: =J25/I25 -> 5.595734 | V25: =SUM(V4:V23) -> 16409291 | X25: =V25/20730000 -> 0.79157218
B27: *excludes investments that have been completely w/o /realized or are public

Sheet Fund II RYG
B2: Fund II Portfolio Health
B3: Company | C3: Initial Inv. Date | D3: Initial Inv. Series | E3: Current Inv. Series | F3: Last Valuation | G3: SV Holding Value | H3: FD % | I3: $ Invested | K3: Current Market Value | L3: Portfolio Value | M3: MOIC | N3: 2025E Rev | O3: 2024A Rev | P3: 2025E ARR | Q3: 2024 ARR | R3: Rev/ARR Growth YoY | S3: Rev Multiple | T3: Q2 Status | U3: Current Q3 Status | V3: Rationale | W3: Fundraising/Current Runway | X3: Other key highlights
B4: Midi | C4: 44455 | D4: Seed | E4: D | F4: 1150000000 | G4: =F4 -> 1150000000 | H4: =VLOOKUP(B4,Sheet1!$K$4:$N$32,4,0) -> 0.0483 | I4: 5531507 | J4: =I4/$I$32 -> 0.093436992 | K4: =24143029.3692*1.995 -> 48165344 | L4: =K4/$K$32 -> 0.33444623 | M4: =K4/I4 -> 8.7074542 | N4: =190000000 -> 190000000 | O4: 37586650 | P4: 129267358 | Q4: 58853221 | R4: =N4/O4-1 -> 4.0549863 | S4: =F4/N4 -> 6.0526316 | T4: 1 | U4: 1 | V4: Beating and raising, ~$190M in revenue growing ~5x y/y
B5: Rula | C5: 44265 | D5: A | E5: C | F5: 1250000000 | G5: =F5 -> 1250000000 | H5: =VLOOKUP(B5,Sheet1!$K$4:$N$32,4,0) -> 0.019806577 | I5: 4500000 | J5: =I5/$I$32 -> 0.076013004 | K5: 25285301 | L5: =K5/$K$32 -> 0.17557382 | M5: =K5/I5 -> 5.6189558 | N5: 236000000 | O5: 121610000 | P5: 786000000 | R5: =N5/O5-1 -> 0.94062988 | S5: =F5/N5 -> 5.2966102 | T5: 1 | U5: 1 | V5: Forecasting 2x y/y growth with revenue run rate above $200M by year end
B6: Remote | C6: 44398 | D6: B | E6: D | F6: 3000000000 | G6: =F6 -> 3000000000 | H6: =VLOOKUP(B6,Sheet1!$K$4:$N$32,4,0) -> 0.003599981 | I6: 4781446 | J6: =I6/$I$32 -> 0.080767127 | K6: 10354762 | L6: =K6/$K$32 -> 0.071900472 | M6: =K6/I6 -> 2.165613 | N6: No FS | O6: No FS | P6: 350000000 | Q6: No FS | R6: - | S6: =F6/P6 -> 8.5714286 | T6: 1 | U6: 1 | V6: Forecasting to accelerate above $350M ARR, continued tailwinds from global workforce | X6: Launched AI powered workflows - next gen payroll
B7: Ashby | C7: 44599 | D7: B | E7: C | F7: 500000000 | G7: =F7 -> 500000000 | H7: =VLOOKUP(B7,Sheet1!$K$4:$N$32,4,0) -> 0.020715715 | I7: 5000000 | J7: =I7/$I$32 -> 0.084458893 | K7: 10135319 | L7: =K7/$K$32 -> 0.070376727 | M7: =K7/I7 -> 2.0270638 | N7: =16207350+10621813 -> 26829163 | O7: 14028342 | P7: 47144781 | Q7: 21606717 | R7: =N7/O7-1 -> 0.91249707 | S7: =F7/N7 -> 18.636437 | T7: 1 | U7: 1 | V7: Closed a $50M Series D at a ~2x step-up from previous round, strong growth
B8: Liftoff | C8: 45064 | D8: Seed | E8: Seed | F8: 39000000 | G8: =F8 -> 39000000 | H8: =VLOOKUP(B8,Sheet1!$K$4:$N$32,4,0) -> 0.05 | I8: 886565.66 | J8: =I8/$I$32 -> 0.014975671 | K8: 1896344.2 | L8: =K8/$K$32 -> 0.013167666 | M8: =K8/I8 -> 2.1389777 | N8: 14000 | O8: 12600 | P8: No data | Q8: No data | R8: =N8/O8-1 -> 0.11111111 | S8: N/A | T8: 1 | U8: 1 | V8: Came out of stealth in Oct 25, good organic growth, no real monetization yet, positive for now but will need to watch the story unfold from here | W8: 30 months
B9: Brightline | C9: 44047 | D9: A | E9: C | F9: 705200000 | G9: =F9 -> 705200000 | H9: =VLOOKUP(B9,Sheet1!$K$4:$N$32,4,0) -> 0.0060300575 | I9: 1499987 | J9: =I9/$I$32 -> 0.025337449 | K9: 4521963.7 | L9: =K9/$K$32 -> 0.031399209 | M9: =K9/I9 -> 3.0146685 | N9: 46580844 | O9: 52238905 | P9: No data | Q9: No data | R9: =N9/O9-1 -> -0.10831125 | S9: =F9/N9 -> 15.139271 | T9: 1 | U9: 0 | V9: Revenue is down slightly yoy, profitable this year. Focusing on delivering care in person, opened 3rd clinic in NY, leadership change, revenue growth -ve, have they de-risked the hybrid model yet? Can it grow and scale? Valuation multiple seems high given the fact pattern | X9: The company expanded its leadership team (operations, product & engineering) in support of its hybrid care strategy and deeper insurer partnerships
B10: CoverGo | C10: 44621 | D10: A | E10: A | F10: 43000000 | G10: =F10 -> 43000000 | H10: =VLOOKUP(B10,Sheet1!$K$4:$N$32,4,0) -> 0.093023256 | I10: 4000000 | J10: =I10/$I$32 -> 0.067567115 | K10: 5294506.9 | L10: =K10/$K$32 -> 0.036763526 | M10: =K10/I10 -> 1.3236267 | N10: =4476975+2898051+3272929 -> 10647955 | O10: 7131378 | P10: 7994010 | Q10: 4957248 | R10: =N10/O10-1 -> 0.49311325 | S10: =F10/N10 -> 4.0383341 | T10: 0 | U10: 0 | V10: Reaccelerated growth, forecasting 2x y/y growth and close to breakeven, yellow for now, will see how the raise goes | W10: 6 months, starting B raise in Q4/Q1'26
B11: Cocoon | C11: 44232 | D11: Seed | E11: A | F11: 1.6250158e+08 | G11: Pref Stack - $26M | H11: =VLOOKUP(B11,Sheet1!$K$4:$N$32,4,0) -> 0.027242491 | I11: 4224996.6 | J11: =I11/$I$32 -> 0.071367707 | K11: 4224996.6 | L11: =K11/$K$32 -> 0.029337155 | M11: =K11/I11 -> 1 | N11: =4118018+2153019 -> 6271037 | O11: 4222643 | P11: 9626246 | Q11: 5424822 | R11: =N11/O11-1 -> 0.4850976 | S11: =F11/N11 -> 25.913032 | T11: 0 | U11: 0 | V11: Contracted ARR at ~$10M, strong product expansion and channel traction with Gurdian/Sedgewick moving into enterprises, moved into variable hourly workers market (increased TAM?). Increased distribution scale + partner validation should move this into green? Rev multiple seems high | W11: 8 months | X11: Gaurdian PEO Distribution - massive channel and disty partnership, will reduce CAC, Enterprise with Sedgewick, SMB/PEO Market capture with Gaurdian, HCM partnerships with workday, adp, paychex
B12: Gable | C12: 44848 | D12: A | E12: A | F12: 50000000 | G12: =F12 -> 50000000 | H12: =VLOOKUP(B12,Sheet1!$K$4:$N$32,4,0) -> 0.08 | I12: 4000000 | J12: =I12/$I$32 -> 0.067567115 | K12: 4000000 | L12: =K12/$K$32 -> 0.027774844 | M12: =K12/I12 -> 1 | N12: 5591913 | O12: 1865748 | P12: =2184011+1284518 -> 3468529 | Q12: 1423910 | R12: =N12/O12-1 -> 1.9971427 | S12: =F12/N12 -> 8.9414839 | T12: 0 | U12: 0 | V12: Forecasting $7.8M ARR by end of Q1'26. Sep run rate at $3.6M. Raised internal bridge round, forecasting ~3x growth and scale appropriate for Series B. Reduced burn, have reduced costs and improved EBITDA. Rev multiple seems high, would want to keep this at yellow. | W12: 13 months
B13: Mosey | C13: 44707 | D13: A | E13: A | F13: 88000000 | G13: =F13 -> 88000000 | H13: =VLOOKUP(B13,Sheet1!$K$4:$N$32,4,0) -> 0.045455 | I13: 3999998.9 | J13: =I13/$I$32 -> 0.067567096 | K13: 3999998.9 | L13: =K13/$K$32 -> 0.027774836 | M13: =K13/I13 -> 1 | N13: =685409*2 -> 1370818 | O13: 938232 | P13: 1481268 | Q13: 1057993 | R13: =N13/O13-1 -> 0.46106507 | S13: =F13/N13 -> 64.195247 | T13: 0 | U13: 0 | V13: Revenue growing ~46% y/y and significant integrations into payroll providers, val multiple too high | W13: 24 months
B14: Nayya | C14: 44344 | D14: B | E14: C | F14: 4.8781374e+08 | G14: =F14 -> 4.8781374e+08 | H14: =VLOOKUP(B14,Sheet1!$K$4:$N$32,4,0) -> 0.0076636442 | I14: 2699987.1 | J14: =I14/$I$32 -> 0.045607585 | K14: 3853385.4 | L14: =K14/$K$32 -> 0.026756794 | M14: =K14/I14 -> 1.4271866 | N14: =19723132+8128680 -> 27851812 | O14: 16056400 | P14: 35344400 | Q14: 28364777 | R14: =N14/O14-1 -> 0.7346237 | S14: =F14/N14 -> 17.514614 | T14: 1 | U14: 0 | V14: Reduced ARR forecast by 20%, reduced growth <2x, strong partnerships are encouraging but needs to convert to ARR contribution and signed deployments. Would suggest yellow. | W14: 17 months | X14: Contract with Google, Acquired Northstar (financial wellness company), Strada announces “exclusive” Nayya partnership at Workday Rising
B15: Origin | C15: 44307 | D15: A | E15: B | F15: 401250000 | G15: Pref Stack - $136.5M | H15: =VLOOKUP(B15,Sheet1!$K$4:$N$32,4,0) -> 0.027099272 | I15: 3699992.1 | J15: =I15/$I$32 -> 0.062499448 | K15: 3699992.1 | L15: =K15/$K$32 -> 0.025691676 | M15: =K15/I15 -> 1 | N15: =5525377*2 -> 11050754 | O15: No data yet | P15: 15000000 | Q15: 9910000 | T15: 0 | U15: 0 | V15: Wrote down to preference stack, undergoing pivot away from B2B model | W15: 19 months
B16: ianacare | C16: 44547 | D16: A | E16: A | F16: 60000000 | G16: =F16 -> 60000000 | H16: =VLOOKUP(B16,Sheet1!$K$4:$N$32,4,0) -> 0.01664562 | I16: 2999984.9 | J16: =I16/$I$32 -> 0.05067508 | K16: 2999984.9 | L16: =K16/$K$32 -> 0.020831028 | M16: =K16/I16 -> 1 | N16: =1614535+380000 -> 1994535 | O16: 1044591 | P16: 2000000 | Q16: 246432 | R16: =N16/O16-1 -> 0.90939325 | S16: =F16/N16 -> 30.0822 | T16: 0 | U16: 0 | V16: Regulatory tailwinds from GUIDE program driving growth as company shifts away from employer. Expect GUIDE revenue to ramp from 6 digit ARR to 7 digit ARR in the next 6-9 months. They revised 2025E ARR projectons down by 25% but expect visibility into GUIDE related ARR to dramatically increase over next 12 months. | W16: 12 months
B17: Delfina | C17: 44621 | D17: Seed | E17: A | F17: 50000000 | G17: =F17 -> 50000000 | H17: =VLOOKUP(B17,Sheet1!$K$4:$N$32,4,0) -> 0.041920188 | I17: 1549999.9 | J17: =I17/$I$32 -> 0.026182256 | K17: 2097344.6 | L17: =K17/$K$32 -> 0.014563355 | M17: =K17/I17 -> 1.3531256 | N17: 2266666 | O17: 1333980 | P17: No FS | Q17: No FS | R17: =N17/O17-1 -> 0.6991754 | S17: =F17/N17 -> 22.05883 | T17: 0 | U17: 0 | V17: Didn't provide revenue projections but taking a hit due to Medicaid budget cuts. Actuals down from projections
B18: Galileo | C18: 44232 | D18: C | E18: C | F18: 361500000 | G18: 361500000 | H18: =VLOOKUP(B18,Sheet1!$K$4:$N$32,4,0) -> 0.0041856851 | I18: 2163902 | J18: =I18/$I$32 -> 0.036552154 | K18: 1724879 | L18: =K18/$K$32 -> 0.011977061 | M18: =K18/I18 -> 0.79711512 | N18: =19556915+10625000 -> 30181915 | O18: 39582208 | P18: 20150000 | Q18: 6021046 | R18: =N18/O18-1 -> -0.23748784 | S18: =F18/N18 -> 11.977371 | T18: -1 | U18: 0 | V18: Completed recap in Q3, completing transition away from shared savings to FFS / Capitated | X18: Galileo Launches First Fully Bilingual Health Care Platform Delivering 24/7 Primary and Multi-Specialty Care
B19: Pinwheel | C19: 44105 | D19: A | E19: B | F19: 4.965001e+08 | G19: Pref Stack - $78M | H19: =VLOOKUP(B19,Sheet1!$K$4:$N$32,4,0) -> 0.0057927248 | I19: 1453156.1 | J19: =I19/$I$32 -> 0.024546391 | K19: 1453156.1 | L19: =K19/$K$32 -> 0.010090296 | M19: =K19/I19 -> 1 | N19: =8180288+3100000 -> 11280288 | O19: 8972963 | P19: 13000000 | Q19: 9916578 | R19: =N19/O19-1 -> 0.25714193 | S19: =F19/N19 -> 44.014843 | T19: 0 | U19: 0 | V19: 30 months of runway, undergoing CEO change, written-down to cost in Q3 | W19: 30 months
B20: Formally | C20: 45006 | D20: Seed | E20: Seed | F20: 25000000 | G20: =F20 -> 25000000 | H20: =VLOOKUP(B20,Sheet1!$K$4:$N$32,4,0) -> 0.04 | I20: 1000000 | J20: =I20/$I$32 -> 0.016891779 | K20: 1000000 | L20: =K20/$K$32 -> 0.006943711 | M20: =K20/I20 -> 1 | N20: No FS | O20: No FS | P20: No FS | Q20: No FS | T20: 0 | U20: 0 | V20: Legal AI is driving renewed interest and company continues to sell well into legal firms
B21: a.team | C21: 44567 | D21: A | E21: A | F21: 325000000 | G21: =F21 -> 325000000 | H21: =VLOOKUP(B21,Sheet1!$K$4:$N$32,4,0) -> 0.0030769253 | I21: 999998.86 | J21: =I21/$I$32 -> 0.016891759 | K21: 999998.86 | L21: =K21/$K$32 -> 0.0069437031 | M21: =K21/I21 -> 1 | N21: No FS | O21: No FS | P21: No FS | Q21: No FS | T21: 0 | U21: 0 | V21: Over 2 years of runway, $10M+ ARR
B22: Finch | C22: 44435 | D22: A | E22: B | F22: 200000000 | G22: =F22 -> 200000000 | H22: =VLOOKUP(B22,Sheet1!$K$4:$N$32,4,0) -> 0.0032205422 | I22: 500003.42 | J22: =I22/$I$32 -> 0.0084459471 | K22: 740862.12 | L22: =K22/$K$32 -> 0.0051443324 | M22: =K22/I22 -> 1.4817141 | N22: =2000000*4 -> 8000000 | O22: 6847796 | P22: 7893656 | Q22: 8900000 | R22: =N22/O22-1 -> 0.1682591 | S22: =F22/N22 -> 25 | T22: 1 | U22: 0 | V22: HR Tech API, Modest growth in Rev, ARR is down ~10% when compared to product traction (seems substantial), high growth margins ~80%, val multiples seem high when compared to industry (peaking at ~20x), retention/churn metrics and high val multiple would suggest yellow (high yellow - cautious but positive) | W22: 34 months | X22: Connected to over 220+ systems, ~80% U.S. employer coverage, 52,000+ employers
B23: Patch | C23: 44879 | D23: Seed | E23: Seed | F23: 8000000 | G23: Acq | H23: Acq | I23: 411246 | J23: =I23/$I$32 -> 0.0069466764 | K23: 586415 | L23: =K23/$K$32 -> 0.0040718963 | M23: =K23/I23 -> 1.425947 | N23: No FS | O23: No FS | P23: No FS | Q23: No FS | T23: 1 | U23: 0 | V23: Acquired by Wellthy, our share is valued at ~600k. No access to FI
B24: Rightfoot | C24: 44175 | D24: Seed | E24: A | F24: 55000000 | G24: 0 | H24: =VLOOKUP(B24,Sheet1!$K$4:$N$32,4,0) -> 0.012564741 | I24: 399999.32 | J24: =I24/$I$32 -> 0.0067567 | K24: 0 | L24: =K24/$K$32 -> 0 | M24: =K24/I24 -> 0 | T24: 0 | U24: 0 | V24: Showing signs of significant growth after undergoing pivot, monitoring to write back up to cost
B25: Vivante | C25: 44552 | D25: A | E25: B | F25: 84077296 | G25: =F25 -> 84077296 | H25: =VLOOKUP(B25,Sheet1!$K$4:$N$32,4,0) -> 0.037179658 | I25: 2204142.3 | J25: =I25/$I$32 -> 0.037231884 | K25: 3130662 | L25: =K25/$K$32 -> 0.021738412 | M25: =K25/I25 -> 1.4203538 | N25: 15200000 | O25: 17400000 | R25: =N25/O25-1 -> -0.12643678 | S25: =F25/N25 -> 5.531401 | T25: 1 | U25: -1 | V25: Down round, strucured pay to play with punitive provisions
B26: Violet | C26: 44722 | D26: Seed | E26: Seed | F26: 22000000 | G26: =F26 -> 22000000 | H26: =VLOOKUP(B26,Sheet1!$K$4:$N$32,4,0) -> 0.12409 | I26: 2599995.3 | J26: =I26/$I$32 -> 0.043918545 | K26: 2599995.3 | L26: =K26/$K$32 -> 0.018053616 | M26: =K26/I26 -> 1 | N26: 1870752 | P26: 2500000 | Q26: 1624000 | R26: =P26/Q26-1 -> 0.53940887 | S26: =F26/P26 -> 8.8 | T26: 0 | U26: -1 | V26: Modest growth yoy (1.53x) Actively pursuing M&A, UCare contract cancelled as Medicaid related churn coming to fruition, $2.7M ARR Churn (230k/month) | W26: Cash & AR: $592k ($395k cash + $197k AR) Additional guaranteed Rev til EOM Jan: $287k Total: $879k Burn: $230k / month = 3.82 months cash out date
B27: Bravely | C27: 44379 | D27: A | E27: A | F27: 67500000 | G27: =F27 -> 67500000 | H27: =VLOOKUP(B27,Sheet1!$K$4:$N$32,4,0) -> 0.018518542 | I27: 1249999.6 | J27: =I27/$I$32 -> 0.021114716 | K27: 1249999.6 | L27: =K27/$K$32 -> 0.0086796356 | M27: =K27/I27 -> 1 | N27: No FS | O27: No FS | P27: No FS | Q27: No FS | R27: N/A | S27: N/A | T27: -1 | U27: -1 | V27: Looking to capture AI tailwinds with a $5M+ install base
B28: Murmur | C28: 44098 | D28: Seed | E28: Seed | F28: 28000000 | G28: 0 | H28: =VLOOKUP(B28,Sheet1!$K$4:$N$32,4,0) -> 0.064069691 | I28: 1574998 | J28: =I28/$I$32 -> 0.026604518 | K28: 0 | L28: =K28/$K$32 -> 0 | M28: =K28/I28 -> 0 | N28: N/A | O28: N/A | P28: N/A | Q28: N/A | R28: N/A | S28: N/A | T28: -1 | U28: -1 | V28: N/A - shutdown
B29: Cleo | C29: 44155 | D29: B | E29: C | F29: 231000000 | G29: 0 | H29: =VLOOKUP(B29,Sheet1!$K$4:$N$32,4,0) -> 0.0040460588 | I29: 599997.84 | J29: =I29/$I$32 -> 0.010135031 | K29: 0 | L29: =K29/$K$32 -> 0 | M29: =K29/I29 -> 0 | N29: No FS | O29: No FS | P29: No FS | Q29: No FS | R29: N/A | S29: N/A | T29: -1 | U29: -1 | V29: N/A - proactive write-off
B30: Praisidio | C30: 44370 | D30: Seed | E30: Seed | F30: 20000000 | G30: 0 | H30: =VLOOKUP(B30,Sheet1!$K$4:$N$32,4,0) -> 0.01 | I30: 200000 | J30: =I30/$I$32 -> 0.0033783557 | K30: 0 | L30: =K30/$K$32 -> 0 | M30: =K30/I30 -> 0 | N30: No FS | O30: No FS | P30: No FS | Q30: No FS | R30: N/A | S30: N/A | T30: -1 | U30: -1 | V30: N/A - proactive write-off
I32: =SUM(I5:I31) -> 59200397 | K32: =SUM(K4:K31) -> 1.4401521e+08
M36: =SUM(K4:K7) -> 93940725
M37: =SUM(I4:I7) -> 19812953
M38: =M36/M37 -> 4.7413793
M47: =141/5.75% -> 2452.1739

Sheet Sheet1
N1: Updated as of 9.30 | V1: =74*10^6 -> 74000000
B2: Initial Investment Characteristics | K2: Current Investment Characteristics | AM2: VOTING - "overall" by IC member | AU2: Avg Vote - by category | AY2: *Missing Vote | AZ2: Double-check | BD2: Scorecards - by category
B3: Company | C3: Date | D3: Series | E3: Sector | F3: $ Invested | G3: VC Syndicate | H3: FD% | I3: Avg. Cost | K3: Company | L3: Series | M3: $ Invested | N3: FD% | O3: Initital Cost | P3: Avg. Cost | Q3: Last Valuation | R3: Holding Value | S3: $ Invested | T3: Market Value | U3: Multiple | V3: RTF | X3: 44285 | Y3: 44469 | Z3: 44742 | AA3: 44926 | AB3: 45107 | AC3: 45291 | AD3: 45473 | AE3: 45565 | AF3: 45657 | AG3: 45838 | AH3: 45930 | AI3: Rationale | AM3: ABG | AN3: CBOU | AO3: Colin | AP3: Greg | AQ3: Robby | AS3: Overall | AT3: Team | AU3: Tech | AV3: TAM | AW3: Timing | AX3: Terms | BB3: Lead | BC3: Qual. Total | BD3: Quant. Total | BE3: Deal Terms | BF3: Total | BG3: Notes
B4: Brightline | C4: =INDEX('[1]Statement of Investments'!$C$5:$C$220,MATCH('[1]Investment Characteristics'!$B4,'[1]Statement of Investments'!$B$5:$B$220,0)) -> 44047 | D4: A | E4: Healthtech | F4: =INDEX('[1]Statement of Investments'!$L$5:$L$220,MATCH('[1]Investment Characteristics'!$B4,'[1]Statement of Investments'!$B$5:$B$220,0)) -> 499998.47 | G4: GV, Oak HC/FT, Threshold | H4: 0.006249969 | I4: 80000000 | K4: =B4 -> Brightline | L4: C | M4: =INDEX('[1]Statement of Investments'!$L$5:$L$220,MATCH('[1]Investment Characteristics'!$K4,'[1]Statement of Investments'!$E$5:$E$220,0)) -> 1499987 | N4: 0.0060300575 | O4: =I4 -> 80000000 | P4: =IFERROR(ROUND(S4/N4,-5),0) -> 248800000 | Q4: 757442906 | R4: =+Q4 -> 757442906 | S4: =INDEX('[1]Statement of Investments'!$L$5:$L$220,MATCH(B4,'[1]Statement of Investments'!$E$5:$E$220,0)) -> 1499987 | T4: =INDEX('[1]Statement of Investments'!$O$5:$O$220,MATCH(B4,'[1]Statement of Investments'!$E$5:$E$220,0)) -> 4521963.7 | U4: =T4/S4 -> 3.0146685 | V4: =+$V$1/N4/10^6 -> 12271.857 | X4: 0 | Y4: 0 | Z4: -1 | AA4: 0 | AB4: 0 | AC4: 1 | AD4: 1 | AE4: 1 | AF4: 1 | AI4: Grew 7x y/y - forecasting minimal growth as company shifts towards profitability | AM4: 2 | AN4: 1 | AO4: 2 | AP4: 1 | AQ4: 2 | AS4: 1.6 | AT4: 1.8 | AU4: 0.6 | AV4: 2 | AW4: 2 | AX4: 0.2 | BB4: ABG | BC4: 49.8 | BD4: 6.5 | BE4: 7 | BF4: 63.3
B5: Murmur | C5: =INDEX('[1]Statement of Investments'!$C$5:$C$220,MATCH('[1]Investment Characteristics'!$B5,'[1]Statement of Investments'!$B$5:$B$220,0)) -> 44098 | D5: Seed | E5: Workforce | F5: =INDEX('[1]Statement of Investments'!$L$5:$L$220,MATCH('[1]Investment Characteristics'!$B5,'[1]Statement of Investments'!$B$5:$B$220,0)) -> 225000 | G5: Lerer Hippeau, Human Ventures | H5: 0.026471511 | I5: =IFERROR(ROUND(F5/H5,-5),0) -> 8500000 | K5: Murmur | L5: Seed | M5: =INDEX('[1]Statement of Investments'!$L$5:$L$220,MATCH('[1]Investment Characteristics'!$K5,'[1]Statement of Investments'!$E$5:$E$220,0)) -> 1574998 | N5: 0.064069691 | O5: =I5 -> 8500000 | P5: =IFERROR(ROUND(S5/N5,-5),0) -> 24600000 | Q5: =28*10^6 -> 28000000 | R5: 0 | S5: =INDEX('[1]Statement of Investments'!$L$5:$L$220,MATCH(B5,'[1]Statement of Investments'!$E$5:$E$220,0)) -> 1574998 | T5: =INDEX('[1]Statement of Investments'!$O$5:$O$220,MATCH(B5,'[1]Statement of Investments'!$E$5:$E$220,0)) -> 0 | U5: =T5/S5 -> 0 | V5: =+$V$1/N5/10^6 -> 1154.9923 | X5: 0 | Y5: 0 | Z5: 1 | AA5: 0 | AB5: 0 | AC5: 1 | AD5: 0 | AE5: 0 | AF5: -1 | AG5: -1 | AH5: -1 | AI5: Pivoting product, plenty of runway but looking for PMF but likely writeoff in Q1 | AM5: 1 | AN5: 1 | AO5: 1 | AP5: 1 | AQ5: 1 | AS5: 1 | AT5: 1.3 | AU5: 0.7 | AV5: 1.7 | AW5: 2 | AX5: 2 | BB5: ABG | BC5: 44 | BD5: 8 | BE5: 9 | BF5: 61
B6: Pinwheel | C6: =INDEX('[1]Statement of Investments'!$C$5:$C$220,MATCH('[1]Investment Characteristics'!$B6,'[1]Statement of Investments'!$B$5:$B$220,0)) -> 44105 | D6: A | E6: Financial | F6: =INDEX('[1]Statement of Investments'!$L$5:$L$220,MATCH('[1]Investment Characteristics'!$B6,'[1]Statement of Investments'!$B$5:$B$220,0)) -> 499997.04 | G6: Coatue, First Round, Upfront | H6: 0.005 | I6: =IFERROR(ROUND(F6/H6,-5),0) -> 100000000 | K6: Pinwheel | L6: B | M6: =INDEX('[1]Statement of Investments'!$L$5:$L$220,MATCH('[1]Investment Characteristics'!$K6,'[1]Statement of Investments'!$E$5:$E$220,0)) -> 1453156.1 | N6: 0.0057927248 | O6: =I6 -> 100000000 | P6: =IFERROR(ROUND(S6/N6,-5),0) -> 250900000 | Q6: 5.0637434e+08 | R6: Pref Stack - $78M | S6: =INDEX('[1]Statement of Investments'!$L$5:$L$220,MATCH(B6,'[1]Statement of Investments'!$E$5:$E$220,0)) -> 1453156.1 | T6: =INDEX('[1]Statement of Investments'!$O$5:$O$220,MATCH(B6,'[1]Statement of Investments'!$E$5:$E$220,0)) -> 1453156.1 | U6: =T6/S6 -> 1 | V6: =+$V$1/N6/10^6 -> 12774.644 | X6: 0 | Y6: 1 | Z6: 1 | AA6: 1 | AB6: 0 | AC6: 0 | AD6: 0 | AE6: 0 | AF6: 0 | AI6: Growth has slowed but plenty of runway and increasing profitability | AM6: 2 | AN6: 1 | AO6: 1 | AP6: 1 | AQ6: 1 | AS6: 1.2 | AT6: 1 | AU6: 0.6 | AV6: 2 | AW6: 1.8 | AX6: 0.2 | BB6: RP/ABG | BC6: 46.5 | BD6: 10.5 | BE6: 7 | BF6: 64
B7: Cleo | C7: =INDEX('[1]Statement of Investments'!$C$5:$C$220,MATCH('[1]Investment Characteristics'!$B7,'[1]Statement of Investments'!$B$5:$B$220,0)) -> 44155 | D7: B | E7: Healthtech | F7: =INDEX('[1]Statement of Investments'!$L$5:$L$220,MATCH('[1]Investment Characteristics'!$B7,'[1]Statement of Investments'!$B$5:$B$220,0)) -> 599997.84 | G7: Felicis, Forerunner, Greylock | H7: =F7/115000000 -> 0.0052173725 | I7: =IFERROR(ROUND(F7/H7,-5),0) -> 115000000 | K7: Cleo | L7: C | M7: =INDEX('[1]Statement of Investments'!$L$5:$L$220,MATCH('[1]Investment Characteristics'!$K7,'[1]Statement of Investments'!$E$5:$E$220,0)) -> 599997.84 | N7: 0.0040460588 | O7: =I7 -> 115000000 | P7: =IFERROR(ROUND(S7/N7,-5),0) -> 148300000 | Q7: 231000000 | R7: 0 | S7: =INDEX('[1]Statement of Investments'!$L$5:$L$220,MATCH(B7,'[1]Statement of Investments'!$E$5:$E$220,0)) -> 599997.84 | T7: =INDEX('[1]Statement of Investments'!$O$5:$O$220,MATCH(B7,'[1]Statement of Investments'!$E$5:$E$220,0)) -> 0 | U7: =T7/S7 -> 0 | V7: =+$V$1/N7/10^6 -> 18289.403 | X7: 1 | Y7: 1 | Z7: 1 | AA7: 0 | AB7: -1 | AC7: 0 | AD7: -1 | AE7: -1 | AF7: -1 | AG7: -1 | AH7: -1 | AI7: No financials provided, investment already written off | AM7: 1 | AN7: 2 | AO7: 1 | AP7: 1 | AQ7: 2 | AS7: 1.4 | AT7: 1.4 | AU7: 1 | AV7: 1.2 | AW7: 2 | AX7: 1.8 | BB7: RP | BC7: 35.3 | BD7: 12 | BE7: 7 | BF7: 54.3
B8: Rightfoot | C8: =INDEX('[1]Statement of Investments'!$C$5:$C$220,MATCH('[1]Investment Characteristics'!$B8,'[1]Statement of Investments'!$B$5:$B$220,0)) -> 44175 | D8: Seed | E8: Financial | F8: =INDEX('[1]Statement of Investments'!$L$5:$L$220,MATCH('[1]Investment Characteristics'!$B8,'[1]Statement of Investments'!$B$5:$B$220,0)) -> 399999.32 | G8: Bain Capital, LSVP | H8: 0.02 | I8: =IFERROR(ROUND(F8/H8,-5),0) -> 20000000 | K8: Rightfoot | L8: A | M8: =INDEX('[1]Statement of Investments'!$L$5:$L$220,MATCH('[1]Investment Characteristics'!$K8,'[1]Statement of Investments'!$E$5:$E$220,0)) -> 399999.32 | N8: 0.012564741 | O8: =I8 -> 20000000 | P8: =IFERROR(ROUND(S8/N8,-5),0) -> 31800000 | Q8: =55*10^6 -> 55000000 | R8: 0 | S8: =INDEX('[1]Statement of Investments'!$L$5:$L$220,MATCH(B8,'[1]Statement of Investments'!$E$5:$E$220,0)) -> 399999.32 | T8: =INDEX('[1]Statement of Investments'!$O$5:$O$220,MATCH(B8,'[1]Statement of Investments'!$E$5:$E$220,0)) -> 0 | U8: =T8/S8 -> 0 | V8: =+$V$1/N8/10^6 -> 5889.4968 | X8: 0 | Y8: 0 | Z8: 1 | AA8: 0 | AB8: 0 | AC8: -1 | AD8: -1 | AE8: -1 | AF8: -1 | AG8: -1 | AH8: -1 | AI8: Written off - company has runway but looking for PMF | AM8: 1 | AN8: 2 | AO8: 1 | AP8: 1 | AQ8: 1 | AS8: 1.2 | AT8: 1.2 | AU8: 1.4 | AV8: 1 | AW8: 1.6 | AX8: 1.8 | BB8: CH | BC8: 41 | BD8: 9.8 | BE8: 4 | BF8: 54.8
B9: Mathison | C9: =INDEX('[1]Statement of Investments'!$C$5:$C$220,MATCH('[1]Investment Characteristics'!$B9,'[1]Statement of Investments'!$B$5:$B$220,0)) -> 44176 | D9: Seed | E9: Workforce | F9: =INDEX('[1]Statement of Investments'!$L$5:$L$220,MATCH('[1]Investment Characteristics'!$B9,'[1]Statement of Investments'!$B$5:$B$220,0)) -> 299999.56 | G9: Bain Capital | H9: 0.020000165 | I9: =IFERROR(ROUND(F9/H9,-5),0) -> 15000000 | K9: Mathison | L9: Acq. | M9: =INDEX('[1]Statement of Investments'!$L$5:$L$220,MATCH('[1]Investment Characteristics'!$K9,'[1]Statement of Investments'!$E$5:$E$220,0)) -> 2049994.2 | N9: 0.04 | O9: =I9 -> 15000000 | P9: =IFERROR(ROUND(S9/N9,-5),0) -> 51200000 | Q9: 70000000 | R9: =+Q9 -> 70000000 | S9: =INDEX('[1]Statement of Investments'!$L$5:$L$220,MATCH(B9,'[1]Statement of Investments'!$E$5:$E$220,0)) -> 2049994.2 | T9: =INDEX('[1]Statement of Investments'!$O$5:$O$220,MATCH(B9,'[1]Statement of Investments'!$E$5:$E$220,0)) -> 272298.82 | U9: =T9/S9 -> 0.13282907 | V9: =+$V$1/N9/10^6 -> 1850 | X9: 1 | Y9: 1 | Z9: 1 | AA9: -1 | AB9: -1 | AC9: -1 | AM9: 2 | AN9: 2 | AO9: 2 | AP9: 1 | AQ9: 1 | AS9: 1.6 | AT9: 0.8 | AU9: 1 | AV9: 1.2 | AW9: 2 | AX9: 1.8 | BB9: ABG | BC9: 46 | BD9: 15 | BE9: 4 | BF9: 65
B10: Galileo | C10: =INDEX('[1]Statement of Investments'!$C$5:$C$220,MATCH('[1]Investment Characteristics'!$B10,'[1]Statement of Investments'!$B$5:$B$220,0)) -> 44232 | D10: C | E10: Healthtech | F10: =INDEX('[1]Statement of Investments'!$L$5:$L$220,MATCH('[1]Investment Characteristics'!$B10,'[1]Statement of Investments'!$B$5:$B$220,0)) -> 1999999.2 | G10: Foresite Capital, Oak HC/FT, 8VC | H10: 0.0050633027 | I10: =IFERROR(ROUND(F10/H10,-5),0) -> 395000000 | K10: Galileo | L10: C | M10: =INDEX('[1]Statement of Investments'!$L$5:$L$220,MATCH('[1]Investment Characteristics'!$K10,'[1]Statement of Investments'!$E$5:$E$220,0)) -> 2163901.7 | N10: 0.0041856851 | O10: =I10 -> 395000000 | P10: =IFERROR(ROUND(S10/N10,-5),0) -> 517000000 | Q10: =600*10^6 -> 600000000 | R10: =+Q10 -> 600000000 | S10: =INDEX('[1]Statement of Investments'!$L$5:$L$220,MATCH(B10,'[1]Statement of Investments'!$E$5:$E$220,0)) -> 2163901.7 | T10: =INDEX('[1]Statement of Investments'!$O$5:$O$220,MATCH(B10,'[1]Statement of Investments'!$E$5:$E$220,0)) -> 1724878.8 | U10: =T10/S10 -> 0.79711515 | V10: =+$V$1/N10/10^6 -> 17679.304 | X10: 1 | Y10: 0 | Z10: 0 | AA10: 2 | AB10: 0 | AC10: -1 | AD10: -1 | AE10: -1 | AF10: -1 | AI10: Revenue doubled in 2024 and forecasted to grow 1.5x+ in 2025, north of $50M. High burn, currently fundraising | AM10: 1 | AN10: 1 | AO10: 1 | AP10: 2 | AQ10: 2 | AS10: 1.4 | AT10: 2 | AU10: 1.2 | AV10: 2 | AW10: 1.8 | AX10: -0.4 | BB10: GG | BC10: 45.5 | BD10: 10.5 | BE10: 7 | BF10: 63
B11: Cocoon | C11: =INDEX('[1]Statement of Investments'!$C$5:$C$220,MATCH('[1]Investment Characteristics'!$B11,'[1]Statement of Investments'!$B$5:$B$220,0)) -> 44232 | D11: Seed | E11: Workforce | F11: =INDEX('[1]Statement of Investments'!$L$5:$L$220,MATCH('[1]Investment Characteristics'!$B11,'[1]Statement of Investments'!$B$5:$B$220,0)) -> 224999.42 | G11: Index Ventures, XYZ Capital | H11: 0.0073744678 | I11: =IFERROR(ROUND(F11/H11,-5),0) -> 30500000 | K11: Cocoon | L11: A | M11: =INDEX('[1]Statement of Investments'!$L$5:$L$220,MATCH('[1]Investment Characteristics'!$K11,'[1]Statement of Investments'!$E$5:$E$220,0)) -> 4224996.6 | N11: 0.027242491 | O11: =I11 -> 30500000 | P11: =IFERROR(ROUND(S11/N11,-5),0) -> 155100000 | Q11: 1.6250158e+08 | R11: Pref Stack - $26M | S11: =INDEX('[1]Statement of Investments'!$L$5:$L$220,MATCH(B11,'[1]Statement of Investments'!$E$5:$E$220,0)) -> 4224996.6 | T11: =INDEX('[1]Statement of Investments'!$O$5:$O$220,MATCH(B11,'[1]Statement of Investments'!$E$5:$E$220,0)) -> 4224996.6 | U11: =T11/S11 -> 1 | V11: =+$V$1/N11/10^6 -> 2716.3448 | X11: 1 | Y11: 1 | Z11: 1 | AA11: 1 | AB11: 1 | AC11: 1 | AD11: 0 | AE11: 0 | AF11: 0 | AI11: Written to preference stack, ARR forecasting to grow ~2x but lower runway | AM11: 1 | AN11: 1 | AO11: 1 | AQ11: 1 | AS11: 1 | AT11: 1.5 | AU11: 0.8 | AV11: 1.5 | AW11: 1.5 | AX11: 1 | BB11: RP | BC11: 48.5 | BD11: 11.3 | BF11: 59.8
B12: Rula | C12: =INDEX('[1]Statement of Investments'!$C$5:$C$220,MATCH('[1]Investment Characteristics'!$B12,'[1]Statement of Investments'!$B$5:$B$220,0)) -> 44265 | D12: A | E12: Healthtech | F12: =INDEX('[1]Statement of Investments'!$L$5:$L$220,MATCH('[1]Investment Characteristics'!$B12,'[1]Statement of Investments'!$B$5:$B$220,0)) -> 1500000 | G12: Wing Ventures, Upfront Ventures | H12: 0.023774266 | I12: =IFERROR(ROUND(F12/H12,-5),0) -> 63100000 | K12: Rula | L12: C | M12: =INDEX('[1]Statement of Investments'!$L$5:$L$220,MATCH('[1]Investment Characteristics'!$K12,'[1]Statement of Investments'!$E$5:$E$220,0)) -> 4500000 | N12: 0.019806577 | O12: =I12 -> 63100000 | P12: =IFERROR(ROUND(S12/N12,-5),0) -> 227200000 | Q12: 1250000000 | R12: =+Q12 -> 1250000000 | S12: =INDEX('[1]Statement of Investments'!$L$5:$L$220,MATCH(B12,'[1]Statement of Investments'!$E$5:$E$220,0)) -> 4500000 | T12: =INDEX('[1]Statement of Investments'!$O$5:$O$220,MATCH(B12,'[1]Statement of Investments'!$E$5:$E$220,0)) -> 25285301 | U12: =T12/S12 -> 5.6189558 | V12: =+$V$1/N12/10^6 -> 3736.1327 | X12: 1 | Y12: 1 | Z12: 1 | AA12: 1 | AB12: 1 | AC12: 1 | AD12: 1 | AE12: 1 | AF12: 1 | AI12: Closed 2024 north of $100M in revenue, forecasting 2x+ growth in 2025 | AM12: 1 | AN12: 1 | AP12: 1 | AQ12: 2 | AS12: 1.3 | AT12: 1.3 | AU12: 0 | AV12: 1.5 | AW12: 2 | AX12: 1 | BB12: RP | BC12: 45.5 | BD12: 10 | BE12: 7 | BF12: 62.5
B13: Origin | C13: =INDEX('[1]Statement of Investments'!$C$5:$C$220,MATCH('[1]Investment Characteristics'!$B13,'[1]Statement of Investments'!$B$5:$B$220,0)) -> 44307 | D13: A | E13: Financial | F13: =INDEX('[1]Statement of Investments'!$L$5:$L$220,MATCH('[1]Investment Characteristics'!$B13,'[1]Statement of Investments'!$B$5:$B$220,0)) -> 1699997.1 | G13: Felicis, 01 Advisors, General Catalyst | H13: 0.013599977 | I13: =IFERROR(ROUND(F13/H13,-5),0) -> 125000000 | K13: Origin | L13: B | M13: =INDEX('[1]Statement of Investments'!$L$5:$L$220,MATCH('[1]Investment Characteristics'!$K13,'[1]Statement of Investments'!$E$5:$E$220,0)) -> 3699992.1 | N13: 0.027099272 | O13: =I13 -> 125000000 | P13: =IFERROR(ROUND(S13/N13,-5),0) -> 136500000 | Q13: 401250000 | R13: =P13 -> 136500000 | S13: =INDEX('[1]Statement of Investments'!$L$5:$L$220,MATCH(B13,'[1]Statement of Investments'!$E$5:$E$220,0)) -> 3699992.1 | T13: =INDEX('[1]Statement of Investments'!$O$5:$O$220,MATCH(B13,'[1]Statement of Investments'!$E$5:$E$220,0)) -> 3699992.1 | U13: =T13/S13 -> 1 | V13: =+$V$1/N13/10^6 -> 2730.7007 | X13: 1 | Y13: 1 | Z13: 1 | AA13: 0 | AB13: 0 | AC13: 0 | AD13: 0 | AE13: 0 | AF13: 0 | AI13: Slowing growth as the company pivots to a D2C model, 2+ years of runway | AM13: 1 | AN13: 2 | AQ13: 2 | AS13: 1.7 | AT13: 2 | AU13: 1 | AV13: 1.7 | AW13: 1.3 | AX13: 1 | BB13: CH/RP | BC13: 50.5 | BD13: 8 | BE13: 6.5 | BF13: 65
B14: Nayya | C14: =INDEX('[1]Statement of Investments'!$C$5:$C$220,MATCH('[1]Investment Characteristics'!$B14,'[1]Statement of Investments'!$B$5:$B$220,0)) -> 44344 | D14: B | E14: Healthtech | F14: =INDEX('[1]Statement of Investments'!$L$5:$L$220,MATCH('[1]Investment Characteristics'!$B14,'[1]Statement of Investments'!$B$5:$B$220,0)) -> 500000 | G14: Felicis, Iconiq, SVB Capital | H14: 0.002173913 | I14: =IFERROR(ROUND(F14/H14,-5),0) -> 230000000 | K14: Nayya | L14: C | M14: =INDEX('[1]Statement of Investments'!$L$5:$L$220,MATCH('[1]Investment Characteristics'!$K14,'[1]Statement of Investments'!$E$5:$E$220,0)) -> 2699987.1 | N14: 0.0076636442 | O14: =I14 -> 230000000 | P14: =IFERROR(ROUND(S14/N14,-5),0) -> 352300000 | Q14: 5.049535e+08 | R14: =+Q14 -> 5.049535e+08 | S14: =INDEX('[1]Statement of Investments'!$L$5:$L$220,MATCH(B14,'[1]Statement of Investments'!$E$5:$E$220,0)) -> 2699987.1 | T14: =INDEX('[1]Statement of Investments'!$O$5:$O$220,MATCH(B14,'[1]Statement of Investments'!$E$5:$E$220,0)) -> 3853385.4 | U14: =T14/S14 -> 1.4271866 | V14: =+$V$1/N14/10^6 -> 9655.9806 | X14: 1 | Y14: 1 | Z14: 0 | AA14: 0 | AB14: 0 | AC14: 1 | AD14: 1 | AE14: 1 | AF14: 1 | AI14: Revenue forecasted to 2x y/y with significant ramp from partnership distribution | AM14: 1 | AN14: 1 | AP14: 1 | AQ14: 1 | AS14: 1 | AT14: 1 | AU14: 1.5 | AV14: 1.8 | AW14: 1.5 | AX14: 0.3 | BB14: RP | BC14: 47.5 | BF14: 47.5
B15: Praisidio | C15: =INDEX('[1]Statement of Investments'!$C$5:$C$220,MATCH('[1]Investment Characteristics'!$B15,'[1]Statement of Investments'!$B$5:$B$220,0)) -> 44370 | D15: Seed | E15: Workforce | F15: =INDEX('[1]Statement of Investments'!$L$5:$L$220,MATCH('[1]Investment Characteristics'!$B15,'[1]Statement of Investments'!$B$5:$B$220,0)) -> 200000 | G15: Signal Fire, Storm Ventures | H15: 0.01 | I15: =IFERROR(ROUND(F15/H15,-5),0) -> 20000000 | K15: Praisidio | L15: Seed | M15: =INDEX('[1]Statement of Investments'!$L$5:$L$220,MATCH('[1]Investment Characteristics'!$K15,'[1]Statement of Investments'!$E$5:$E$220,0)) -> 200000 | N15: 0.01 | O15: =I15 -> 20000000 | P15: =IFERROR(ROUND(S15/N15,-5),0) -> 20000000 | Q15: 20000000 | R15: 0 | S15: =INDEX('[1]Statement of Investments'!$L$5:$L$220,MATCH(B15,'[1]Statement of Investments'!$E$5:$E$220,0)) -> 200000 | T15: =INDEX('[1]Statement of Investments'!$O$5:$O$220,MATCH(B15,'[1]Statement of Investments'!$E$5:$E$220,0)) -> 0 | U15: =T15/S15 -> 0 | V15: =+$V$1/N15/10^6 -> 7400 | X15: 1 | Y15: 1 | Z15: 0 | AA15: 0 | AB15: 0 | AC15: 0 | AD15: 0 | AE15: 0 | AF15: -1 | AG15: -1 | AH15: -1 | AI15: Written down to 0 | AM15: 2 | AN15: 2 | AP15: 1 | AQ15: 1 | AS15: 1.5 | AT15: 1.5 | AU15: 1 | AV15: 1 | AW15: 2 | AX15: 1.8 | BB15: ABG | BC15: 46.5 | BD15: 13 | BE15: 9 | BF15: 68.5
B16: Bravely | C16: =INDEX('[1]Statement of Investments'!$C$5:$C$220,MATCH('[1]Investment Characteristics'!$B16,'[1]Statement of Investments'!$B$5:$B$220,0)) -> 44379 | D16: A | E16: Workforce | F16: =INDEX('[1]Statement of Investments'!$L$5:$L$220,MATCH('[1]Investment Characteristics'!$B16,'[1]Statement of Investments'!$B$5:$B$220,0)) -> 1249999.6 | G16: Telescope Partners, Primary Venture Partners | H16: 0.018518542 | I16: =IFERROR(ROUND(F16/H16,-5),0) -> 67500000 | K16: Bravely | L16: A | M16: =INDEX('[1]Statement of Investments'!$L$5:$L$220,MATCH('[1]Investment Characteristics'!$K16,'[1]Statement of Investments'!$E$5:$E$220,0)) -> 1249999.6 | N16: 0.018518542 | O16: =I16 -> 67500000 | P16: =IFERROR(ROUND(S16/N16,-5),0) -> 67500000 | Q16: 67500000 | R16: =+Q16 -> 67500000 | S16: =INDEX('[1]Statement of Investments'!$L$5:$L$220,MATCH(B16,'[1]Statement of Investments'!$E$5:$E$220,0)) -> 1249999.6 | T16: =INDEX('[1]Statement of Investments'!$O$5:$O$220,MATCH(B16,'[1]Statement of Investments'!$E$5:$E$220,0)) -> 1249999.6 | U16: =T16/S16 -> 1 | V16: =+$V$1/N16/10^6 -> 3995.995 | X16: 1 | Y16: 1 | Z16: 0 | AA16: -1 | AB16: -1 | AC16: -1 | AD16: -1 | AE16: -1 | AF16: -1 | AI16: Close to breakeven with significant runway as the company looks to reinvigorate growth | AM16: 2 | AN16: 1 | AO16: 1 | AP16: 1 | AQ16: 1 | AS16: 1.2 | AT16: 1.2 | AU16: 0.4 | AV16: 1.4 | AW16: 2 | AX16: 1.6 | BB16: ABG | BC16: 45 | BD16: 13.5 | BF16: 58.5 | BG16: No scorecard, pulled from Investment Diligence
B17: Remote | C17: =INDEX('[1]Statement of Investments'!$C$5:$C$220,MATCH('[1]Investment Characteristics'!$B17,'[1]Statement of Investments'!$B$5:$B$220,0)) -> 44398 | D17: B | E17: Workforce | F17: =INDEX('[1]Statement of Investments'!$L$5:$L$220,MATCH('[1]Investment Characteristics'!$B17,'[1]Statement of Investments'!$B$5:$B$220,0)) -> 3999979.6 | G17: Accel, General Catalyst, Index, Sequoia | H17: 0.0039999789 | I17: =IFERROR(ROUND(F17/H17,-5),0) -> 1000000000 | K17: Remote | L17: C | M17: =INDEX('[1]Statement of Investments'!$L$5:$L$220,MATCH('[1]Investment Characteristics'!$K17,'[1]Statement of Investments'!$E$5:$E$220,0)) -> 4781446 | N17: 0.003599981 | O17: =I17 -> 1000000000 | P17: =IFERROR(ROUND(S17/N17,-5),0) -> 1328200000 | Q17: 3000000000 | R17: =+Q17 -> 3000000000 | S17: =INDEX('[1]Statement of Investments'!$L$5:$L$220,MATCH(B17,'[1]Statement of Investments'!$E$5:$E$220,0)) -> 4781446 | T17: =INDEX('[1]Statement of Investments'!$O$5:$O$220,MATCH(B17,'[1]Statement of Investments'!$E$5:$E$220,0)) -> 10354762 | U17: =T17/S17 -> 2.165613 | V17: =+$V$1/N17/10^6 -> 20555.664 | X17: 1 | Y17: 1 | Z17: 0 | AA17: 0 | AB17: 1 | AC17: 1 | AD17: 1 | AE17: 1 | AF17: 1 | AI17: Lower visibility into financial figures, but strong ecosystem feedback and ramp from employer channel | AM17: 2 | AN17: 1 | AP17: 1 | AQ17: 2 | AS17: 1.5 | AT17: 2 | AU17: 1.8 | AV17: 2 | AW17: 1.8 | AX17: 0.3 | BB17: RP | BC17: 52.5 | BD17: 14.3 | BF17: 66.8
B18: Finch | C18: =INDEX('[1]Statement of Investments'!$C$5:$C$220,MATCH('[1]Investment Characteristics'!$B18,'[1]Statement of Investments'!$B$5:$B$220,0)) -> 44435 | D18: A | E18: Financial | F18: =INDEX('[1]Statement of Investments'!$L$5:$L$220,MATCH('[1]Investment Characteristics'!$B18,'[1]Statement of Investments'!$B$5:$B$220,0)) -> 500003.42 | G18: Menlo, General Catalyst, Box Group | H18: 0.0043467434 | I18: =IFERROR(ROUND(F18/H18,-5),0) -> 115000000 | K18: Finch | L18: B | M18: =INDEX('[1]Statement of Investments'!$L$5:$L$220,MATCH('[1]Investment Characteristics'!$K18,'[1]Statement of Investments'!$E$5:$E$220,0)) -> 500003.42 | N18: 0.0032205422 | O18: =I18 -> 115000000 | P18: =IFERROR(ROUND(S18/N18,-5),0) -> 155300000 | Q18: 230000392 | R18: =+Q18 -> 230000392 | S18: =INDEX('[1]Statement of Investments'!$L$5:$L$220,MATCH(B18,'[1]Statement of Investments'!$E$5:$E$220,0)) -> 500003.42 | T18: =INDEX('[1]Statement of Investments'!$O$5:$O$220,MATCH(B18,'[1]Statement of Investments'!$E$5:$E$220,0)) -> 740862.12 | U18: =T18/S18 -> 1.4817141 | V18: =+$V$1/N18/10^6 -> 22977.498 | X18: 1 | Y18: 1 | Z18: 1 | AA18: 1 | AB18: 1 | AC18: 1 | AD18: 1 | AE18: 1 | AF18: 1 | AI18: 3 years of runway, forecasting 1.5x y/y growth and deepening key distribution partnerships | AM18: 1 | AN18: 1 | AQ18: 1 | AS18: 1 | AT18: 1 | AU18: 1.7 | AV18: 1.3 | AW18: 1.7 | AX18: 0.3 | BB18: RP | BC18: 46.5 | BD18: 14 | BE18: 2 | BF18: 62.5
B19: Midi | C19: =INDEX('[1]Statement of Investments'!$C$5:$C$220,MATCH('[1]Investment Characteristics'!$B19,'[1]Statement of Investments'!$B$5:$B$220,0)) -> 44455 | D19: Seed | E19: Healthtech | F19: =INDEX('[1]Statement of Investments'!$L$5:$L$220,MATCH('[1]Investment Characteristics'!$B19,'[1]Statement of Investments'!$B$5:$B$220,0)) -> 510137 | G19: Icon Ventures | H19: =F19/10000000 -> 0.0510137 | I19: =IFERROR(ROUND(F19/H19,-5),0) -> 10000000 | K19: Midi | L19: D | M19: =INDEX('[1]Statement of Investments'!$L$5:$L$220,MATCH('[1]Investment Characteristics'!$K19,'[1]Statement of Investments'!$E$5:$E$220,0)) -> 5531507 | N19: 0.0483 | O19: =I19 -> 10000000 | P19: =IFERROR(ROUND(S19/N19,-5),0) -> 114500000 | Q19: 1150000000 | R19: =+Q19 -> 1150000000 | S19: =INDEX('[1]Statement of Investments'!$L$5:$L$220,MATCH(B19,'[1]Statement of Investments'!$E$5:$E$220,0)) -> 5531507 | T19: =INDEX('[1]Statement of Investments'!$O$5:$O$220,MATCH(B19,'[1]Statement of Investments'!$E$5:$E$220,0)) -> 48185999 | U19: =T19/S19 -> 8.7111883 | V19: =+$V$1/N19/10^6 -> 1532.0911 | X19: 1 | Y19: 1 | Z19: 1 | AA19: 1 | AB19: 1 | AC19: 1 | AD19: 1 | AE19: 1 | AF19: 1 | AG19: 1 | AH19: 1 | AI19: Forecasting to reach $100M+ of net revenue in 2025, expecting to close new round of financing at markup | AM19: 2 | AN19: 2 | AO19: 1 | AP19: 1 | AQ19: 1 | AS19: 1.4 | AT19: 1.6 | AU19: 0.2 | AV19: 1.8 | AW19: 1.4 | AX19: 1.8 | BB19: ABG | BC19: 41.5 | BD19: 8 | BF19: 49.5 | BG19: No scorecard, pulled from Investment Diligence
B20: ianacare | C20: =INDEX('[1]Statement of Investments'!$C$5:$C$220,MATCH('[1]Investment Characteristics'!$B20,'[1]Statement of Investments'!$B$5:$B$220,0)) -> 44547 | D20: A | E20: Healthtech | F20: =INDEX('[1]Statement of Investments'!$L$5:$L$220,MATCH('[1]Investment Characteristics'!$B20,'[1]Statement of Investments'!$B$5:$B$220,0)) -> 999984.87 | G20: Greycroft, 8VC | H20: 0.016666456 | I20: =IFERROR(ROUND(F20/H20,-5),0) -> 60000000 | K20: ianacare | L20: A | M20: =INDEX('[1]Statement of Investments'!$L$5:$L$220,MATCH('[1]Investment Characteristics'!$K20,'[1]Statement of Investments'!$E$5:$E$220,0)) -> 2999984.9 | N20: 0.01664562 | O20: =I20 -> 60000000 | P20: =+O20 -> 60000000 | Q20: =P20 -> 60000000 | R20: =+Q20 -> 60000000 | S20: =INDEX('[1]Statement of Investments'!$L$5:$L$220,MATCH(B20,'[1]Statement of Investments'!$E$5:$E$220,0)) -> 2999984.9 | T20: =INDEX('[1]Statement of Investments'!$O$5:$O$220,MATCH(B20,'[1]Statement of Investments'!$E$5:$E$220,0)) -> 2999984.9 | U20: =T20/S20 -> 1 | V20: =+$V$1/N20/10^6 -> 4445.6139 | Y20: 1 | Z20: 1 | AA20: 1 | AB20: 1 | AC20: 0 | AD20: -1 | AE20: -1 | AF20: 0 | AI20: Potential new channel through GUIDE CMS reimbursement is accelerating growth and Elevance expanding partnership | AM20: 2 | AN20: 1 | AO20: 2 | AP20: 1 | AQ20: 1 | AS20: 1.4 | AT20: 2 | AU20: 1.4 | AV20: 1 | AW20: 1.8 | AX20: 1 | BB20: ABG | BC20: 47.8 | BD20: 15 | BF20: 62.8
B21: Vivante | C21: =INDEX('[1]Statement of Investments'!$C$5:$C$220,MATCH('[1]Investment Characteristics'!$B21,'[1]Statement of Investments'!$B$5:$B$220,0)) -> 44552 | D21: A | E21: Healthtech | F21: =INDEX('[1]Statement of Investments'!$L$5:$L$220,MATCH('[1]Investment Characteristics'!$B21,'[1]Statement of Investments'!$B$5:$B$220,0)) -> 999999 | G21: 7Wire, NFP | H21: 0.045928552 | I21: =IFERROR(ROUND(F21/H21,-5),0) -> 21800000 | K21: Vivante | L21: B | M21: =INDEX('[1]Statement of Investments'!$L$5:$L$220,MATCH('[1]Investment Characteristics'!$K21,'[1]Statement of Investments'!$E$5:$E$220,0)) -> 2204142.3 | N21: 0.037179658 | O21: =I21 -> 21800000 | P21: =IFERROR(ROUND(S21/N21,-5),0) -> 59300000 | Q21: 84077296 | R21: =+Q21 -> 84077296 | S21: =INDEX('[1]Statement of Investments'!$L$5:$L$220,MATCH(B21,'[1]Statement of Investments'!$E$5:$E$220,0)) -> 2204142.3 | T21: =INDEX('[1]Statement of Investments'!$O$5:$O$220,MATCH(B21,'[1]Statement of Investments'!$E$5:$E$220,0)) -> 3130662 | U21: =T21/S21 -> 1.4203538 | V21: =+$V$1/N21/10^6 -> 1990.3357 | Y21: 1 | Z21: 1 | AA21: -1 | AB21: 1 | AC21: 1 | AD21: 1 | AE21: 1 | AF21: 1 | AI21: Steady 1.5x y/y growth last year, forecasted into 2025 - currently fundraising | AM21: 1 | AN21: 2 | AP21: 1 | AQ21: 2 | AS21: 1.5 | AT21: 1.3 | AU21: 1 | AV21: 1.8 | AW21: 1.5 | AX21: 2 | BB21: RP | BC21: 49.5 | BF21: 49.5
B22: a.team | C22: =INDEX('[1]Statement of Investments'!$C$5:$C$220,MATCH('[1]Investment Characteristics'!$B22,'[1]Statement of Investments'!$B$5:$B$220,0)) -> 44567 | D22: A | E22: Workforce | F22: =INDEX('[1]Statement of Investments'!$L$5:$L$220,MATCH('[1]Investment Characteristics'!$B22,'[1]Statement of Investments'!$B$5:$B$220,0)) -> 999998.86 | G22: Spruce, Tiger, Insight, BoxGroup | H22: 0.003076922 | I22: =IFERROR(ROUND(F22/H22,-5),0) -> 325000000 | K22: a.team | L22: A | M22: =INDEX('[1]Statement of Investments'!$L$5:$L$220,MATCH('[1]Investment Characteristics'!$K22,'[1]Statement of Investments'!$E$5:$E$220,0)) -> 999998.86 | N22: 0.0030769253 | O22: =I22 -> 325000000 | P22: =IFERROR(ROUND(S22/N22,-5),0) -> 325000000 | Q22: =P22 -> 325000000 | R22: =+Q22 -> 325000000 | S22: =INDEX('[1]Statement of Investments'!$L$5:$L$220,MATCH(B22,'[1]Statement of Investments'!$E$5:$E$220,0)) -> 999998.86 | T22: =INDEX('[1]Statement of Investments'!$O$5:$O$220,MATCH(B22,'[1]Statement of Investments'!$E$5:$E$220,0)) -> 999998.86 | U22: =T22/S22 -> 1 | V22: =+$V$1/N22/10^6 -> 24049.983 | Y22: 1 | Z22: 1 | AA22: 1 | AB22: 0 | AC22: 1 | AD22: 0 | AE22: 0 | AF22: 0 | AI22: runway++ | AY22: Double-check | BB22: ABG | BC22: 51.5 | BD22: 17.8 | BF22: 69.3
B23: CoverGo | C23: =INDEX('[1]Statement of Investments'!$C$5:$C$220,MATCH('[1]Investment Characteristics'!$B23,'[1]Statement of Investments'!$B$5:$B$220,0)) -> 44621 | D23: A | E23: Financial | F23: =INDEX('[1]Statement of Investments'!$L$5:$L$220,MATCH('[1]Investment Characteristics'!$B23,'[1]Statement of Investments'!$B$5:$B$220,0)) -> 2000000 | G23: N/A | H23: =(F23+2*10^6)/I23 -> 0.093023256 | I23: 43000000 | K23: CoverGo | L23: A | M23: =INDEX('[1]Statement of Investments'!$L$5:$L$220,MATCH('[1]Investment Characteristics'!$K23,'[1]Statement of Investments'!$E$5:$E$220,0)) -> 4000000 | N23: 0.093023256 | O23: =I23 -> 43000000 | P23: =O23 -> 43000000 | Q23: =P23 -> 43000000 | R23: =+Q23 -> 43000000 | S23: =INDEX('[1]Statement of Investments'!$L$5:$L$220,MATCH(B23,'[1]Statement of Investments'!$E$5:$E$220,0)) -> 4000000 | T23: =INDEX('[1]Statement of Investments'!$O$5:$O$220,MATCH(B23,'[1]Statement of Investments'!$E$5:$E$220,0)) -> 5294506.9 | U23: =T23/S23 -> 1.3236267 | V23: =+$V$1/N23/10^6 -> 795.5 | Y23: 1 | Z23: 1 | AA23: 1 | AB23: 1 | AC23: 1 | AD23: 0 | AE23: 0 | AF23: 0 | AH23: 0 | AI23: 5 new clients and managed to grow ARR by 26% (from US$5M in Dec 24 to US$6.3M in Jun 25) and reached US$4.4M in revenue in H1 2025 | AJ23: • Series B is planned to start in Oct 2025 with target closing in Q1 2026. In the meantime, we have identified an additional financing option to fulfill working capital needs as planned. | AM23: 1 | AN23: 2 | AQ23: 2 | AS23: 1.7 | AT23: 1 | AU23: 2 | AV23: 1.3 | AW23: 1.7 | AX23: 2 | BB23: CH | BC23: 45.5 | BD23: 14.8 | BE23: 3.5 | BF23: 63.8
B24: Delfina | C24: =INDEX('[1]Statement of Investments'!$C$5:$C$220,MATCH('[1]Investment Characteristics'!$B24,'[1]Statement of Investments'!$B$5:$B$220,0)) -> 44621 | D24: Seed | E24: Healthtech | F24: =INDEX('[1]Statement of Investments'!$L$5:$L$220,MATCH('[1]Investment Characteristics'!$B24,'[1]Statement of Investments'!$B$5:$B$220,0)) -> 800000 | G24: Story Ventures | H24: =F24/I24 -> 0.053333333 | I24: =15*10^6 -> 15000000 | K24: Delfina | L24: Seed | M24: =INDEX('[1]Statement of Investments'!$L$5:$L$220,MATCH('[1]Investment Characteristics'!$K24,'[1]Statement of Investments'!$E$5:$E$220,0)) -> 1549999.9 | N24: 0.041920188 | O24: =I24 -> 15000000 | P24: =O24 -> 15000000 | Q24: 52000000 | R24: =+Q24 -> 52000000 | S24: =INDEX('[1]Statement of Investments'!$L$5:$L$220,MATCH(B24,'[1]Statement of Investments'!$E$5:$E$220,0)) -> 1549999.9 | T24: =INDEX('[1]Statement of Investments'!$O$5:$O$220,MATCH(B24,'[1]Statement of Investments'!$E$5:$E$220,0)) -> 2097344.6 | U24: =T24/S24 -> 1.3531256 | V24: =+$V$1/N24/10^6 -> 1765.2593 | Z24: 1 | AA24: 1 | AB24: 1 | AC24: 1 | AD24: 0 | AE24: 0 | AF24: 1 | AI24: Closed a Series A led by USVP, potential for explosive growth through key | AM24: 2 | AN24: 2 | AO24: 2 | AP24: 1 | AQ24: 2 | AS24: 1.8 | AT24: 1.8 | AU24: 1.2 | AV24: 1.4 | AW24: 1.4 | AX24: 2 | BB24: RP | BC24: 45 | BD24: 9.5 | BF24: 54.5
B25: Ashby | C25: =INDEX('[1]Statement of Investments'!$C$5:$C$220,MATCH('[1]Investment Characteristics'!$B25,'[1]Statement of Investments'!$B$5:$B$220,0)) -> 44599 | D25: B | E25: Workforce | F25: =INDEX('[1]Statement of Investments'!$L$5:$L$220,MATCH('[1]Investment Characteristics'!$B25,'[1]Statement of Investments'!$B$5:$B$220,0)) -> 3000000 | G25: F-Prime, Elad Gil | H25: =F25/I25 -> 0.017142857 | I25: 175000000 | K25: Ashby | L25: C | M25: =INDEX('[1]Statement of Investments'!$L$5:$L$220,MATCH('[1]Investment Characteristics'!$K25,'[1]Statement of Investments'!$E$5:$E$220,0)) -> 5000000 | N25: 0.020715715 | O25: =I25 -> 175000000 | P25: =O25 -> 175000000 | Q25: 500000000 | R25: =+Q25 -> 500000000 | S25: =INDEX('[1]Statement of Investments'!$L$5:$L$220,MATCH(B25,'[1]Statement of Investments'!$E$5:$E$220,0)) -> 5000000 | T25: =INDEX('[1]Statement of Investments'!$O$5:$O$220,MATCH(B25,'[1]Statement of Investments'!$E$5:$E$220,0)) -> 10135319 | U25: =T25/S25 -> 2.0270638 | V25: =+$V$1/N25/10^6 -> 3572.1674 | Y25: 1 | Z25: 1 | AA25: 1 | AB25: 1 | AC25: 1 | AD25: 1 | AE25: 1 | AF25: 1 | AI25: Accelerating revenue growth, approaching significant scale, likely a GOF II target | AM25: 1 | AN25: 1 | AP25: 2 | AQ25: 2 | AS25: 1.5 | AT25: 1 | AU25: 1.5 | AV25: 1.5 | AW25: 1.3 | AX25: 0.8 | BB25: RP | BC25: 53.3 | BD25: 13 | BF25: 66.3 | BG25: No scorecard, pulled from Investment Diligence
B26: Mosey | C26: =INDEX('[1]Statement of Investments'!$C$5:$C$220,MATCH('[1]Investment Characteristics'!$B26,'[1]Statement of Investments'!$B$5:$B$220,0)) -> 44707 | D26: A | E26: Workforce | F26: =INDEX('[1]Statement of Investments'!$L$5:$L$220,MATCH('[1]Investment Characteristics'!$B26,'[1]Statement of Investments'!$B$5:$B$220,0)) -> 3999998.9 | G26: Canaan | H26: 0.045455 | I26: 88000000 | K26: Mosey | L26: A | M26: =INDEX('[1]Statement of Investments'!$L$5:$L$220,MATCH('[1]Investment Characteristics'!$K26,'[1]Statement of Investments'!$E$5:$E$220,0)) -> 3999998.9 | N26: 0.045455 | O26: =I26 -> 88000000 | P26: =O26 -> 88000000 | Q26: =P26 -> 88000000 | R26: =+Q26 -> 88000000 | S26: =INDEX('[1]Statement of Investments'!$L$5:$L$220,MATCH(B26,'[1]Statement of Investments'!$E$5:$E$220,0)) -> 3999998.9 | T26: =INDEX('[1]Statement of Investments'!$O$5:$O$220,MATCH(B26,'[1]Statement of Investments'!$E$5:$E$220,0)) -> 3999998.9 | U26: =T26/S26 -> 1 | V26: =+$V$1/N26/10^6 -> 1627.9837 | Z26: 1 | AA26: 1 | AB26: 1 | AC26: 0 | AD26: 0 | AE26: 0 | AF26: 0 | AI26: Growth has been steady but not accelerating - potential channel opportunities to drive signficant expansion | AM26: 2 | AN26: 1 | AO26: 2 | AP26: 2 | AQ26: 2 | AS26: 1.8 | AT26: 1.8 | AU26: 1.4 | AV26: 1.8 | AW26: 2 | AX26: 0.6 | BB26: RP | BC26: 45.5 | BF26: 45.5
B27: Violet | C27: =INDEX('[1]Statement of Investments'!$C$5:$C$220,MATCH('[1]Investment Characteristics'!$B27,'[1]Statement of Investments'!$B$5:$B$220,0)) -> 44722 | D27: Seed | E27: Healthtech | F27: =INDEX('[1]Statement of Investments'!$L$5:$L$220,MATCH('[1]Investment Characteristics'!$B27,'[1]Statement of Investments'!$B$5:$B$220,0)) -> 2599995.3 | G27: The Venture Collective, Northwell | H27: =F27/I27 -> 0.1181816 | I27: =22*10^6 -> 22000000 | K27: Violet | L27: Seed | M27: =INDEX('[1]Statement of Investments'!$L$5:$L$220,MATCH('[1]Investment Characteristics'!$K27,'[1]Statement of Investments'!$E$5:$E$220,0)) -> 2599995.3 | N27: 0.12409 | O27: =I27 -> 22000000 | P27: =O27 -> 22000000 | Q27: =P27 -> 22000000 | R27: =+Q27 -> 22000000 | S27: =INDEX('[1]Statement of Investments'!$L$5:$L$220,MATCH(B27,'[1]Statement of Investments'!$E$5:$E$220,0)) -> 2599995.3 | T27: =INDEX('[1]Statement of Investments'!$O$5:$O$220,MATCH(B27,'[1]Statement of Investments'!$E$5:$E$220,0)) -> 2599995.3 | U27: =T27/S27 -> 1 | V27: =+$V$1/N27/10^6 -> 596.34137 | Z27: 1 | AA27: 0 | AB27: 0 | AC27: 1 | AD27: 0 | AE27: 0 | AF27: 1 | AI27: Successful Series Seed Extension with growing traction with health plans, strong renewals | AM27: 2 | AN27: 2 | AO27: 2 | AP27: 2 | AQ27: 2 | AS27: 2 | AT27: 1.2 | AU27: 0.8 | AV27: 1.2 | AW27: 2 | AX27: 2 | BB27: ABG | BC27: 37 | BF27: 37
B28: Gable | C28: =INDEX('[1]Statement of Investments'!$C$5:$C$220,MATCH('[1]Investment Characteristics'!$B28,'[1]Statement of Investments'!$B$5:$B$220,0)) -> 44848 | D28: A | E28: Workforce | F28: =INDEX('[1]Statement of Investments'!$L$5:$L$220,MATCH('[1]Investment Characteristics'!$B28,'[1]Statement of Investments'!$B$5:$B$220,0)) -> 4000000 | G28: Foundation Capital | H28: 0.08 | I28: =F28/H28 -> 50000000 | K28: Gable | L28: A | M28: =INDEX('[1]Statement of Investments'!$L$5:$L$220,MATCH('[1]Investment Characteristics'!$K28,'[1]Statement of Investments'!$E$5:$E$220,0)) -> 4000000 | N28: 0.08 | O28: =I28 -> 50000000 | P28: =O28 -> 50000000 | Q28: =P28 -> 50000000 | R28: =+Q28 -> 50000000 | S28: =INDEX('[1]Statement of Investments'!$L$5:$L$220,MATCH(B28,'[1]Statement of Investments'!$E$5:$E$220,0)) -> 4000000 | T28: =INDEX('[1]Statement of Investments'!$O$5:$O$220,MATCH(B28,'[1]Statement of Investments'!$E$5:$E$220,0)) -> 4000000 | U28: =T28/S28 -> 1 | V28: =+$V$1/N28/10^6 -> 925 | AA28: 1 | AB28: 0 | AC28: 0 | AD28: 0 | AE28: 0 | AF28: 1 | AI28: Showing signs of PMF and repeatable buying motion - forecasting to 5x revenue and expand ACV | AM28: 1 | AN28: 2 | AO28: 2 | AP28: 2 | AQ28: 2 | BB28: RP/CT | BC28: 49 | BD28: 14 | BF28: 63
A29: Wellthy Merger | B29: Patch Caregiving | C29: =INDEX('[1]Statement of Investments'!$C$5:$C$220,MATCH('[1]Investment Characteristics'!$B29,'[1]Statement of Investments'!$B$5:$B$220,0)) -> 44879 | D29: Seed | E29: Workforce | F29: =INDEX('[1]Statement of Investments'!$L$5:$L$220,MATCH('[1]Investment Characteristics'!$B29,'[1]Statement of Investments'!$B$5:$B$220,0))+'[1]Statement of Investments'!L204 -> 499999.85 | G29: AlleyCorp | H29: =F29/I29 -> 0.062499981 | I29: =8*10^6 -> 8000000 | K29: Patch Caregiving | L29: Acq. | M29: =INDEX('[1]Statement of Investments'!$L$79:$L$220,MATCH('[1]Investment Characteristics'!$K29,'[1]Statement of Investments'!$E$79:$E$220,0)) -> 411245.85 | N29: 0.0018 | O29: =I29 -> 8000000 | P29: =O29 -> 8000000 | Q29: =P29 -> 8000000 | R29: =+Q29 -> 8000000 | S29: =INDEX('[1]Statement of Investments'!$L$79:$L$220,MATCH(B29,'[1]Statement of Investments'!$E$79:$E$220,0)) -> 411245.85 | T29: =INDEX('[1]Statement of Investments'!$O$79:$O$220,MATCH(B29,'[1]Statement of Investments'!$E$79:$E$220,0)) -> 586415.29 | U29: =T29/S29 -> 1.4259482 | V29: =+$V$1/N29/10^6 -> 41111.111 | AA29: 1 | AB29: 1 | AC29: 1 | AD29: 1 | AE29: 1 | AF29: 1 | AI29: Continuing to build deep relationship with UPS and expand into hospital systems. Profitable | AM29: 1 | AN29: 2 | AO29: 2 | AP29: 1 | AQ29: 2 | BB29: RP/CT | BC29: 45.5 | BD29: 15 | BF29: 60.5
B30: Formally | C30: =INDEX('[1]Statement of Investments'!$C$5:$C$220,MATCH('[1]Investment Characteristics'!$B30,'[1]Statement of Investments'!$B$5:$B$220,0)) -> 45006 | D30: Seed | E30: Workforce | F30: =INDEX('[1]Statement of Investments'!$L$5:$L$220,MATCH('[1]Investment Characteristics'!$B30,'[1]Statement of Investments'!$B$5:$B$220,0)) -> 1000000 | G30: Bessemer | H30: =F30/I30 -> 0.04 | I30: =25*10^6 -> 25000000 | K30: Formally | L30: Seed | M30: =INDEX('[1]Statement of Investments'!$L$5:$L$220,MATCH('[1]Investment Characteristics'!$K30,'[1]Statement of Investments'!$E$5:$E$220,0)) -> 1000000 | N30: 0.04 | O30: =I30 -> 25000000 | P30: =O30 -> 25000000 | Q30: =P30 -> 25000000 | R30: =+Q30 -> 25000000 | S30: =INDEX('[1]Statement of Investments'!$L$5:$L$220,MATCH(B30,'[1]Statement of Investments'!$E$5:$E$220,0)) -> 1000000 | T30: =INDEX('[1]Statement of Investments'!$O$5:$O$220,MATCH(B30,'[1]Statement of Investments'!$E$5:$E$220,0)) -> 1000000 | U30: =T30/S30 -> 1 | V30: =+$V$1/N30/10^6 -> 1850 | AB30: 1 | AC30: 1 | AD30: 0 | AE30: 0 | AF30: 0 | AI30: Legal AI is a natural expansion outside of core immigation workflow | AM30: 1* | AN30: 1 | AO30: 2 | AP30: 0 | AQ30: 2 | AS30: 1.2 | AT30: 1 | AU30: 0.6 | AV30: 0.4 | AW30: 1.4 | AX30: 0 | BB30: ABG | BC30: 41.5
B31: Liftoff | C31: =INDEX('[1]Statement of Investments'!$C$5:$C$220,MATCH('[1]Investment Characteristics'!$B31,'[1]Statement of Investments'!$B$5:$B$220,0)) -> 45064 | D31: Seed | E31: Workforce | F31: =INDEX('[1]Statement of Investments'!$L$5:$L$220,MATCH('[1]Investment Characteristics'!$B31,'[1]Statement of Investments'!$B$5:$B$220,0)) -> 500000 | G31: Torch Capital, Kleiner Perkins Spark Fund | H31: =F31/I31 -> 0.05 | I31: =10*10^6 -> 10000000 | K31: Liftoff | L31: Seed | M31: =INDEX('[1]Statement of Investments'!$L$5:$L$220,MATCH('[1]Investment Characteristics'!$K31,'[1]Statement of Investments'!$E$5:$E$220,0)) -> 886565.66 | N31: 0.05 | O31: =I31 -> 10000000 | P31: =O31 -> 10000000 | Q31: =39*10^6 -> 39000000 | R31: =+Q31 -> 39000000 | S31: =INDEX('[1]Statement of Investments'!$L$5:$L$220,MATCH(B31,'[1]Statement of Investments'!$E$5:$E$220,0)) -> 886565.66 | T31: =INDEX('[1]Statement of Investments'!$O$5:$O$220,MATCH(B31,'[1]Statement of Investments'!$E$5:$E$220,0)) -> 1896344.2 | U31: =T31/S31 -> 2.1389777 | V31: =+$V$1/N31/10^6 -> 1480 | AB31: 1 | AC31: 1 | AD31: 1 | AE31: 1 | AF31: 1 | AI31: Closed Series A in Q3 at a ~3x step-up, product showing strong virality | AM31: 2 | AN31: 1 | AO31: 1 | AP31: 1 | AQ31: 1 | AS31: 1.2 | AT31: 1.6 | AU31: 0.8 | AV31: 1.8 | AW31: 1 | AX31: 1.6 | BB31: ABG | BC31: 38 | BF31: 41.5
B32: Easop | C32: =INDEX('[1]Statement of Investments'!$C$5:$C$220,MATCH('[1]Investment Characteristics'!$B32,'[1]Statement of Investments'!$B$5:$B$220,0)) -> 45065 | D32: Seed | E32: Workforce | F32: 1000000 | G32: Partech Ventures, Boldstart Ventures | H32: =F32/I32 -> 0.066666667 | I32: =15*10^6 -> 15000000 | K32: Easop | L32: Acq. | M32: =+F32 -> 1000000 | N32: 0.066666667 | O32: =I32 -> 15000000 | P32: =O32 -> 15000000 | Q32: =P32 -> 15000000 | R32: =+Q32 -> 15000000 | S32: =+M32 -> 1000000 | T32: =+'[1]Statement of Investments'!O7+'[1]Statement of Investments'!O143 -> 1068916.9 | U32: =T32/S32 -> 1.0689169 | V32: =+$V$1/N32/10^6 -> 1110 | AB32: 1 | AC32: 1 | AM32: 1 | AN32: 1 | AO32: 2 | AP32: 2 | AQ32: 2 | AS32: 1.6 | AT32: 1 | AU32: 0.6 | AV32: 0.6 | AW32: 1.6 | AX32: 1.6 | BB32: CT | BC32: 47 | BF32: 47
B34: Average | F34: =AVERAGE(F4:F33) -> 1286554.6 | H34: =AVERAGE(H4:H33) -> 0.031544087 | I34: =AVERAGE(I4:I33) -> 1.1215172e+08 | K34: Average | M34: =AVERAGE(M4:M33) -> 2337306.8 | N34: =AVERAGE(N4:N33) -> 0.031817691 | O34: =AVERAGE(O4:O33) -> 1.1215172e+08 | P34: =AVERAGE(P4:P33) -> 1.6291379e+08 | Q34: =AVERAGE(Q4:Q33) -> 3.5672759e+08 | S34: =AVERAGE(S4:S33) -> 2337306.8 | T34: =AVERAGE(T4:T33) -> 5013002.8
B35: Median | F35: =MEDIAN(F4:F33) -> 999984.87 | H35: =MEDIAN(H4:H33) -> 0.02 | I35: =MEDIAN(I4:I33) -> 50000000 | K35: Median | M35: =MEDIAN(M4:M33) -> 2049994.2 | N35: =MEDIAN(N4:N33) -> 0.020715715 | O35: =MEDIAN(O4:O33) -> 50000000 | P35: =MEDIAN(P4:P33) -> 67500000 | Q35: =MEDIAN(Q4:Q33) -> 84077296 | S35: =MEDIAN(S4:S33) -> 2049994.2 | T35: =MEDIAN(T4:T33) -> 2097344.6
B36: Dollar Weighted | H36: =SUMPRODUCT(H$4:H$33,$F$4:$F$33)/SUM($F$4:$F$33) -> 0.039869451 | I36: =SUMPRODUCT(I$4:I$33,$F$4:$F$33)/SUM($F$4:$F$33) -> 1.9381834e+08 | K36: Dollar Weighted | N36: =SUMPRODUCT(N$4:N$33,$S$4:$S$33)/SUM($S$4:$S$33) -> 0.036956969 | O36: =SUMPRODUCT(O$4:O$33,$F$4:$F$33)/SUM($F$4:$F$33) -> 1.9381834e+08 | P36: =SUMPRODUCT(P$4:P$33,$S$4:$S$33)/SUM($S$4:$S$33) -> 2.1765835e+08 | Q36: =SUMPRODUCT(Q$4:Q$33,$S$4:$S$33)/SUM($S$4:$S$33) -> 5.5644685e+08
B41: Fund II Sector Summary
C42: Workforce | D42: Healthtech | E42: Financial | F42: Total
B43: Deals:
B44: # of Deals | C44: =COUNTIF($E$4:$E$35,C$42) -> 14 | D44: =COUNTIF($E$4:$E$35,D$42) -> 10 | E44: =COUNTIF($E$4:$E$35,E$42) -> 5 | F44: =SUM(C44:E44) -> 29
B45: % of Deals | C45: =C44/$F$44 -> 0.48275862 | D45: =D44/$F$44 -> 0.34482759 | E45: =E44/$F$44 -> 0.17241379 | F45: =F44/$F$44 -> 1
B46: Invested Capital:
B47: Initial Investment | C47: =SUMIF($E$4:$E$35,C$42,$F$4:$F$35) -> 21199976 | D47: =SUMIF($E$4:$E$35,D$42,$F$4:$F$35) -> 11010112 | E47: =SUMIF($E$4:$E$35,E$42,$F$4:$F$35) -> 5099996.9 | F47: =SUM(C47:E47) -> 37310084
B48: % of Invested Cap | C48: =C47/$F$47 -> 0.56821034 | D48: =D47/$F$47 -> 0.29509747 | E48: =E47/$F$47 -> 0.13669218 | F48: =F47/$F$47 -> 1
B49: Current Investment | C49: =SUMIF($E$4:$E$35,C$42,$M$4:$M$35) -> 31379244 | D49: =SUMIF($E$4:$E$35,D$42,$M$4:$M$35) -> 26349503 | E49: =SUMIF($E$4:$E$35,E$42,$M$4:$M$35) -> 10053151 | F49: =SUM(C49:E49) -> 67781898
B50: % of Invested Cap | C50: =C49/$F$49 -> 0.46294431 | D50: =D49/$F$49 -> 0.38873953 | E50: =E49/$F$49 -> 0.14831616 | F50: =F49/$F$49 -> 1
B51: Current Mark
B52: Total Value | C52: =SUMIF($E$4:$E$35,C$42,$T$4:$T$35) -> 39789050 | D52: =SUMIF($E$4:$E$35,D$42,$T$4:$T$35) -> 94399515 | E52: =SUMIF($E$4:$E$35,E$42,$T$4:$T$35) -> 11188517 | F52: =SUM(C52:E52) -> 1.4537708e+08
B53: MOIC | C53: =C52/C49 -> 1.2680054 | D53: =D52/D49 -> 3.5825918 | E53: =E52/E49 -> 1.1129364 | F53: =F52/F49 -> 2.1447774
B54: Average Investment:
B55: Initial Avg. Inv. | C55: =AVERAGEIF($E$4:$E$35,C$42,$F$4:$F$35) -> 1514284 | D55: =AVERAGEIF($E$4:$E$35,D$42,$F$4:$F$35) -> 1101011.2 | E55: =AVERAGEIF($E$4:$E$35,E$42,$F$4:$F$35) -> 1019999.4 | F55: =F34 -> 1286554.6
B56: Current Avg. Inv. | C56: =AVERAGEIF($E$4:$E$35,C$42,$M$4:$M$35) -> 2241374.5 | D56: =AVERAGEIF($E$4:$E$35,D$42,$M$4:$M$35) -> 2634950.3 | E56: =AVERAGEIF($E$4:$E$35,E$42,$M$4:$M$35) -> 2010630.2 | F56: =M34 -> 2337306.8
B57: Average Cost:
B58: Initial Avg. Cost | C58: =AVERAGEIF($E$4:$E$35,C$42,$I$4:$I$35) -> 131250000 | D58: =AVERAGEIF($E$4:$E$35,D$42,$I$4:$I$35) -> 101190000 | E58: =AVERAGEIF($E$4:$E$35,E$42,$I$4:$I$35) -> 80600000 | F58: =I34 -> 1.1215172e+08
B59: Current Avg. Inv. | C59: =AVERAGEIF($E$4:$E$35,C$42,$P$4:$P$35) -> 1.6732857e+08 | D59: =AVERAGEIF($E$4:$E$35,D$42,$P$4:$P$35) -> 176440000 | E59: =AVERAGEIF($E$4:$E$35,E$42,$P$4:$P$35) -> 123500000 | F59: =P34 -> 1.6291379e+08
B60: Round
B61: Seed | C61: =COUNTIFS($D$4:$D$35,$B61,$E$4:$E$35,C$42) -> 8 | D61: =COUNTIFS($D$4:$D$35,$B61,$E$4:$E$35,D$42) -> 3 | E61: =COUNTIFS($D$4:$D$35,$B61,$E$4:$E$35,E$42) -> 1 | F61: =SUM(C61:E61) -> 12
B62: A | C62: =COUNTIFS($D$4:$D$35,$B62,$E$4:$E$35,C$42) -> 4 | D62: =COUNTIFS($D$4:$D$35,$B62,$E$4:$E$35,D$42) -> 4 | E62: =COUNTIFS($D$4:$D$35,$B62,$E$4:$E$35,E$42) -> 4 | F62: =SUM(C62:E62) -> 12
B63: B+ | C63: =COUNTIFS($D$4:$D$35,"B",$E$4:$E$35,C$42)+COUNTIFS($D$4:$D$35,"C",$E$4:$E$35,C$42) -> 2 | D63: =COUNTIFS($D$4:$D$35,"B",$E$4:$E$35,D$42)+COUNTIFS($D$4:$D$35,"C",$E$4:$E$35,D$42) -> 3 | E63: =COUNTIFS($D$4:$D$35,"B",$E$4:$E$35,E$42)+COUNTIFS($D$4:$D$35,"C",$E$4:$E$35,E$42) -> 0 | F63: =SUM(C63:E63) -> 5
B66: Fund II Stage Summary
C67: Seed | D67: A | E67: B | F67: Total
B68: Average Investment:
B69: Initial Avg. Inv. | C69: =AVERAGEIF($D$4:$D$33,C$67,$F$4:$F$33) -> 688344.2 | D69: =AVERAGEIF($D$4:$D$33,D$67,$F$4:$F$33) -> 1579164.8 | E69: =AVERAGEIFS($F$4:$F$33,$D$4:$D$33,"<>Seed",$D$4:$D$33,"<>A") -> 2019995.3 | F69: =F34 -> 1286554.6
B70: Current Avg. Inv. | C70: =AVERAGEIF($D$4:$D$33,C$67,$M$4:$M$33) -> 1785775.1 | D70: =AVERAGEIF($D$4:$D$33,D$67,$M$4:$M$33) -> 2592271.9 | E70: =AVERAGEIFS($M$4:$M$33,$D$4:$D$33,"<>Seed",$D$4:$D$33,"<>A") -> 3049066.5 | F70: =M34 -> 2337306.8
B71: Deals
B72: # of Deals | C72: =COUNTIF($D$4:$D$35,C$67) -> 12 | D72: =COUNTIF($D$4:$D$35,D$67) -> 12 | E72: =COUNTIF($D$4:$D$33,"B")+COUNTIF($D$4:$D$33,"C") -> 5 | F72: =SUM(C72:E72) -> 29
B73: % of Deals | C73: =C72/$F$72 -> 0.4137931 | D73: =D72/$F$72 -> 0.4137931 | E73: =E72/$F$72 -> 0.17241379 | F73: =F72/$F$72 -> 1
B74: # of Deals | C74: =COUNTIF($L$4:$L$35,C$67) -> 6 | D74: =COUNTIF($L$4:$L$35,D$67) -> 8 | E74: =F72-SUM(C74:D74) -> 15 | F74: =SUM(C74:E74) -> 29
B75: % of Deals | C75: =C74/$F$72 -> 0.20689655 | D75: =D74/$F$72 -> 0.27586207 | E75: =E74/$F$72 -> 0.51724138 | F75: =F74/$F$72 -> 1
B76: Valuation
B77: Initial Avg. Cost | C77: =AVERAGEIF($D$4:$D$33,C$67,$I$4:$I$33) -> 16583333 | D77: =AVERAGEIF($D$4:$D$33,D$67,$I$4:$I$33) -> 94866667 | E77: =AVERAGEIFS($I$4:$I$33,$D$4:$D$33,"<>Seed",$D$4:$D$33,"<>A") -> 383000000 | F77: =I34 -> 1.1215172e+08
B78: Initial Median Cost | C78: {=MEDIAN(IF($D$4:$D$33=C67,$I$4:$I$33))} -> 15000000 | D78: {=MEDIAN(IF($D$4:$D$33=D67,$I$4:$I$33))} -> 73750000 | E78: =MEDIAN(I7,I10,I14,I25,I17) -> 230000000 | F78: =I35 -> 50000000
B79: Ownership
B80: Initial Avg. FD% | C80: =AVERAGEIF($D$4:$D$33,C$67,$H$4:$H$33) -> 0.043795119 | D80: =AVERAGEIF($D$4:$D$33,D$67,$H$4:$H$33) -> 0.02963664 | E80: =AVERAGEIFS($H$4:$H$33,$D$4:$D$33,"<>Seed",$D$4:$D$33,"<>A") -> 0.0067194849 | F80: =H34 -> 0.031544087
B81: Initial Median FD% | C81: {=MEDIAN(IF($D$4:$D$33=C$67,$H$4:$H$33))} -> 0.045 | D81: {=MEDIAN(IF($D$4:$D$33=D$67,$H$4:$H$33))} -> 0.017592499 | E81: =MEDIAN(H25,H17,H14,H10,H7) -> 0.0050633027 | F81: =H35 -> 0.02
B82: Invested Capital:
B83: Initial Investment | C83: =SUMIF($D$4:$D$33,C$67,$F$4:$F$33) -> 8260130.4 | D83: =SUMIF($D$4:$D$33,D$67,$F$4:$F$33) -> 18949977 | E83: =SUMIF($D$4:$D$33,"B",$F$4:$F$33)+F10 -> 10099977 | F83: =SUM(C83:E83) -> 37310084
C84: =C83/$F$83 -> 0.22139136 | D84: =D83/$F$83 -> 0.50790497 | E84: =E83/$F$83 -> 0.27070367
B85: Current Investment | C85: =SUMIF($L$4:$L$33,C$67,$M$4:$M$33) -> 7811558.8 | D85: =SUMIF($L$4:$L$33,D$67,$M$4:$M$33) -> 21874978 | E85: =SUM(M4:M30)-SUM(C85:D85) -> 36208795 | F85: =SUM(C85:E85) -> 65895332
C86: =C85/$F$85 -> 0.11854495 | D86: =D85/$F$85 -> 0.33196552 | E86: =E85/$F$85 -> 0.54948953
C94: `

Sheet Fund II Inv Char
B2: Fund II Current Investment Characteristics
B3: Company | C3: Series | D3: FD% | E3: Initial Cost | F3: Last Valuation | G3: Holding Value | H3: Potential Company Value | I3: $ Invested | J3: Market Value | K3: Potential SV Market Value | L3: Multiple | N3: Additional Value | O3: Expected Gross MOIC | P3: Additional TVPI
B4: Rula | C4: C | D4: 0.0207 | E4: 63100000 | F4: 1250000000 | G4: 1250000000 | I4: 4500000 | J4: 25285301 | L4: 5.6189558
B5: Midi | C5: C | D5: 0.0483 | E5: 10000000 | F5: 500000000 | G5: 500000000 | H5: 1150000000 | I5: 5531507 | J5: 24143029 | K5: =H5*D5 -> 55545000 | L5: 4.3646387 | N5: =K5-J5 -> 31401971 | O5: =K5/I5 -> 10.041567 | P5: =N5/73293334 -> 0.42844238
B6: Remote | C6: C | D6: 0.003599981 | E6: 1000000000 | F6: 3000000000 | G6: 3000000000 | I6: 4781446 | J6: 10354762 | L6: 2.165613
B7: Ashby | C7: C | D7: 0.0203 | E7: 175000000 | F7: 500000000 | G7: 500000000 | I7: 5000000 | J7: 10135319 | L7: 2.0270638
B8: CoverGo | C8: A | D8: 0.093023256 | E8: 43000000 | F8: 43000000 | G8: 43000000 | I8: 4000000 | J8: 5294506.9 | L8: 1.3236267
B9: Brightline | C9: C | D9: 0.0060300575 | E9: 80000000 | F9: 705200000 | G9: 705200000 | I9: 1499987 | J9: 4521963.7 | K9: =H9*D9 -> 0 | L9: 3.0146685
B10: Cocoon | C10: A | D10: 0.02785117 | E10: 30500000 | F10: 1.6250158e+08 | G10: Preference Stack ($26M) | I10: 4224996.6 | J10: 4224996.6 | L10: 1
B11: Gable | C11: A | D11: 0.08 | E11: 50000000 | F11: 50000000 | G11: 50000000 | I11: 4000000 | J11: 4000000 | L11: 1
B12: Mosey | C12: A | D12: 0.045455 | E12: 88000000 | F12: 88000000 | G12: 88000000 | I12: 3999998.9 | J12: 3999998.9 | L12: 1
B13: Nayya | C13: C | D13: 0.0076636442 | E13: 230000000 | F13: 4.8781374e+08 | G13: 4.8781374e+08 | I13: 2699987.1 | J13: 3853385.4 | L13: 1.4271866
B14: Origin | C14: B | D14: 0.027099272 | E14: 125000000 | F14: 401250000 | G14: Preference Stack ($76M) | I14: 3699992.1 | J14: 3699992.1 | L14: 1
B15: Vivante | C15: B | D15: 0.037179658 | E15: 21800000 | F15: 84077296 | G15: 84077296 | I15: 2204142.3 | J15: 3130662 | L15: 1.4203538
B16: Pinwheel | C16: B | D16: 0.0057927248 | E16: 100000000 | F16: 4.965001e+08 | G16: 4.965001e+08 | I16: 1453156.1 | J16: 3035952.2 | L16: 2.0892128
B17: ianacare | C17: A | D17: 0.01664562 | E17: 60000000 | F17: 60000000 | G17: 60000000 | I17: 2999984.9 | J17: 2999984.9 | L17: 1
B18: Galileo | C18: C | D18: 0.0041856851 | E18: 395000000 | F18: 600000000 | G18: 600000000 | I18: 1999999.2 | J18: 2604941.4 | L18: 1.3024712
B19: Violet | C19: Seed | D19: 0.1181816 | E19: 22000000 | F19: 22000000 | G19: 22000000 | I19: 2599995.3 | J19: 2599995.3 | L19: 1
B20: Delfina | C20: A | D20: 0.052614847 | E20: 15000000 | F20: 50000000 | G20: 50000000 | I20: 1549999.9 | J20: 2097344.6 | L20: 1.3531256
B21: Liftoff | C21: Seed | D21: 0.05 | E21: 10000000 | F21: 39000000 | G21: 39000000 | I21: 886565.66 | J21: 1896344.2 | L21: 2.1389777
B22: Murmur | C22: Seed | D22: 0.064069691 | E22: 8500000 | F22: 28000000 | G22: 28000000 | I22: 1574998 | J22: 1574998 | L22: 1
B23: Bravely | C23: A | D23: 0.018518542 | E23: 67500000 | F23: 67500000 | G23: 67500000 | I23: 1249999.6 | J23: 1249999.6 | L23: 1
B24: Formally | C24: Seed | D24: 0.04 | E24: 25000000 | F24: 25000000 | G24: 25000000 | I24: 1000000 | J24: 1000000 | L24: 1
B25: a.team | C25: A | D25: 0.0030769253 | E25: 325000000 | F25: 325000000 | G25: 325000000 | I25: 999998.86 | J25: 999998.86 | L25: 1
B26: Finch | C26: B | D26: 0.0032205422 | E26: 115000000 | F26: 200000000 | G26: 200000000 | I26: 500003.42 | J26: 740862.12 | L26: 1.4817141
... B30: Praisidio | C30: Seed | D30: 0.01 | E30: 20000000 | F30: 20000000 | G30: 0 | I30: 200000 | J30: 0 | L30: 0

Sheet GOF I Inv Char
B2: GOF I Current Investment Characteristics
B3: Company | C3: Series | D3: FD% | E3: Initital Cost | F3: Last Valuation | G3: Holding Value | H3: $ Invested | I3: Market Value | J3: Multiple
B4: Spring | C4: E | D4: 0.0014999963 | E4: 2000000000 | F4: 3300000000 | G4: 3300000000 | H4: 2999992.2 | I4: 4435508.1 | J4: 1.4785065
B5: Fountain | C5: D | D5: 0.0045216718 | E5: 435000000 | F5: 860000000 | G5: 860000000 | H5: 2999981.3 | I5: 3888643 | J5: 1.2962224
B6: Carrot | C6: D | D6: 0.0048507273 | E6: 260000000 | F6: 600000000 | G6: 600000000 | H6: 2200002.1 | I6: 2911244.8 | J6: 1.3232918
B7: Rula | C7: C | D7: 0.0028 | E7: 5.3571371e+08 | F7: 1250000000 | G7: 1250000000 | H7: 1499998.4 | I7: 2848531.5 | J7: 1.899023
B8: Karat | C8: C | D8: 0.0013498793 | E8: 1111200000 | F8: 1111200000 | G8: Preference Stack ($170M) | H8: 1499987.1 | I8: 1499987.1 | J8: 1
B9: Hone | C9: B | D9: 0.0079223739 | E9: 1.262245e+08 | F9: 126200000 | G9: 126200000 | H9: 999997.7 | I9: 999997.7 | J9: 1
B10: Rightway | C10: C | D10: 0.00090906625 | E10: 1100000000 | F10: 625000000 | G10: 625000000 | H10: 1499959.4 | I10: 982749.23 | J10: 0.65518391
B11: Ladder | C11: D | D11: 0.0024242189 | E11: 825000000 | F11: =+G11 -> 330000000 | G11: 330000000 | H11: 1999984.6 | I11: 742808.52 | J11: 0.37140712
B12: Charthop | C12: B | D12: 0.0013 | E12: 335000000 | F12: 270000000 | G12: Preference Stack ($74M) | H12: 499999.98 | I12: 499999.98 | J12: 1

Sheet Fund III RYG
U1: =15*13% -> 1.95
B2: Fund III Portfolio Health
B3: Company | C3: Initial Inv. Date | D3: Initial Inv. Series | E3: Current Inv. Series | F3: Last Valuation | G3: SV Holding Value | H3: FD % | I3: $ Invested | J3: Market Value | K3: Portfolio Value | L3: MOIC | M3: 2025E Rev | N3: 2024A Rev | O3: 2025E ARR | P3: 2024 ARR | Q3: Rev/ARR Growth YoY | R3: Rev Multiple | S3: Q2 Status | T3: Current Q3 Status | U3: Rationale | V3: Fundraising/Current Runway | W3: Other key highlights
B4: Stepful | C4: 45183 | D4: A | E4: B | F4: 261500000 | G4: 261500000 | H4: =VLOOKUP(B4,Sheet2!$K$4:$M$45,3,0) -> 0.052805468 | I4: 7878030.5 | J4: 13609280 | K4: =J4/$J$31 -> 0.15273568 | L4: =J4/I4 -> 1.7274977 | M4: =38827962+12014384 -> 50842346 | N4: 19914254 | O4: 55600000 | P4: No data | Q4: =M4/N4-1 -> 1.553063 | R4: =F4/M4 -> 5.1433504 | S4: 1 | T4: 1 | U4: Growing 2.5x+ y/y, yoy bookings at 2X, expanding helthcare education offerings and new B2B partnerships with Trilogy an Norther Light | V4: $35M cash on hand, ~$1M monthly burn, ~3 years of runway | W4: Stepful - B2B for nursing classes Charge Double of what they charge consumers Raise > $700M Q1 of next year - plan
B5: OneImaging | C5: 45665 | D5: Seed | E5: A | F5: 250000000 | G5: 250000000 | H5: =VLOOKUP(B5,Sheet2!$K$4:$M$45,3,0) -> 0.05994 | I5: 3999990.6 | J5: 14640883 | K5: =J5/$J$31 -> 0.16431327 | L5: =J5/I5 -> 3.6602292 | M5: =1248270+2594222 -> 3842492 | N5: 32237 | O5: 16422582 | P5: 77000 | Q5: =M5/N5-1 -> 118.19509 | R5: =F5/O5 -> 15.222941 | S5: 1 | T5: 1 | U5: Closed $30M Series A at ~12x step-up from seed round we co-led, projecting >10x revenue growth by Q3 2026 | V5: 28 months
B6: Thatch | C6: 45513 | D6: A | E6: B | F6: 450000000 | G6: 450000000 | H6: =VLOOKUP(B6,Sheet2!$K$4:$M$45,3,0) -> 0.032141794 | I6: 4040625.2 | J6: 10304094 | K6: =J6/$J$31 -> 0.11564189 | L6: =J6/I6 -> 2.5501238 | M6: =3989264+1534539 -> 5523803 | N6: 1534539 | O6: 15178908 | P6: 1534539 | Q6: =M6/N6-1 -> 2.5996498 | R6: =F6/O6 -> 29.646401 | S6: 1 | T6: 1 | U6: Closed Series B at 2.5x step-up, on target to grow ~15x this year, Revenue for Qtr to 9/30 ahead of Plan by ~10%, forecasting 3x ARR growth by EOY | V6: 21 months
B7: Salsa | C7: 45747 | D7: Seed | E7: A | F7: 70000000 | G7: 70000000 | H7: =VLOOKUP(B7,Sheet2!$K$4:$M$45,3,0) -> 0.084687403 | I7: 5499997.9 | J7: 5912934 | K7: =J7/$J$31 -> 0.06636031 | L7: =J7/I7 -> 1.0750793 | M7: No FS | N7: No FS | O7: No FS | P7: No FS | Q7: N/A | R7: - | S7: 1 | T7: 1 | U7: Closed Series A from Altos Ventures earlier this year, embedded solutions beginning to ramp, well capitalized | V7: 19 months | W7: Salsa announced a partnership with Easyteam (“embedded workforce + payroll solution for hourly teams”) enabling platforms to launch payroll + workforce management together for hourly/shift-based sectors.
B8: Onboarded | C8: 45824 | D8: A | E8: A | F8: 57500000 | G8: 57500000 | H8: =VLOOKUP(B8,Sheet2!$K$4:$M$45,3,0) -> 0.086956522 | I8: 5000000 | J8: 5000000 | K8: =J8/$J$31 -> 0.056114536 | L8: =J8/I8 -> 1 | M8: =400578+1450000 -> 1850578 | N8: No data | O8: 2500000 | Q8: N/A | R8: =F8/M8 -> 31.071373 | S8: 1 | T8: 1 | U8: Fundraising | V8: 47 months
B9: Sully.AI | C9: 45670 | D9: A | E9: A | F9: 75000000 | G9: 75000000 | H9: =VLOOKUP(B9,Sheet2!$K$4:$M$45,3,0) -> 0.053333327 | I9: 3999999.5 | J9: 3999999.5 | K9: =J9/$J$31 -> 0.044891623 | L9: =J9/I9 -> 1 | M9: =1131704+1691892 -> 2823596 | N9: 0 | O9: 4218948 | P9: 0 | Q9: N/A | R9: =F9/O9 -> 17.776943 | S9: 1 | T9: 1 | U9: Raising at $200M SAFE cap, projecting 7x growth in revenue | V9: 17 months
B10: Athena.AI | C10: 45778 | D10: Seed | E10: Seed | F10: 35000000 | G10: 35000000 | H10: =VLOOKUP(B10,Sheet2!$K$4:$M$45,3,0) -> 0.09 | I10: 3150000 | J10: 3150000 | K10: =J10/$J$31 -> 0.035352158 | L10: =J10/I10 -> 1 | O10: 1700000 | Q10: N/A | R10: =F10/O10 -> 20.588235 | S10: 1 | T10: 1 | U10: Recent Investment
B11: Solara | C11: 45329 | D11: Seed | E11: A | F11: 14500000 | G11: 14500000 | H11: =VLOOKUP(B11,Sheet2!$K$4:$M$45,3,0) -> 0.13793102 | I11: 1999999.8 | J11: 1999999.8 | K11: =J11/$J$31 -> 0.022445812 | L11: =J11/I11 -> 1 | M11: 500000 | N11: 0 | Q11: N/A | R11: =F11/M11 -> 29 | S11: 1 | T11: 1 | U11: Raising Series A at $40-42.5M Post Money - tight cash runway, projecting $2.4M in revenue by end of 2026, adding 2 Sales FTE and 1 acct management FTE. ACV growth. This is only providor revenue not payor included. Raising between $17.5-$20M (oversubscribed) - | V11: 5 months | W11: CMO left, flat ACV for their systems ($200k) for pilots, single program, multi program or platform, expand beyond PEPM, examples like EPIC -? Working on a big deal with Aetna/CVS. Aetna deal - complement EAP program 3,000 employees - sees opp in pharmacy channels. Platform with usage is their pricing model. Track end user engagement and provider engagement, Violet eg - contracted revenue wont continue to grow
B12: Wagmo | C12: 45209 | D12: A | E12: A | F12: 78500000 | G12: 78500000 | H12: =VLOOKUP(B12,Sheet2!$K$4:$M$45,3,0) -> 0.03180843 | I12: 1499998 | J12: 1499998 | K12: =J12/$J$31 -> 0.016834339 | L12: =J12/I12 -> 1 | M12: =5886387+4236328+4496818 -> 14619533 | N12: 12254470 | O12: 22155060 | P12: 12254470 | Q12: =M12/N12-1 -> 0.19299594 | R12: =F12/M12 -> 5.3695286 | S12: 1 | T12: 1 | U12: Channel partnership with ADP ramping B2B business, ending year $20M+ ARR | V12: 33 months
B13: Take2 AI | C13: 45376 | D13: Seed | E13: Seed | F13: 10000000 | G13: 10000000 | H13: =VLOOKUP(B13,Sheet2!$K$4:$M$45,3,0) -> 0.07 | I13: 700000 | J13: 700000 | K13: =J13/$J$31 -> 0.007856035 | L13: =J13/I13 -> 1 | M13: =88943+130000+250000 -> 468943 | N13: - | O13: 1186000 | P13: - | Q13: N/A | R13: =F13/M13 -> 21.324553 | S13: 1 | T13: 1 | U13: Found key ICP with healthcare customers, raised $2M note at higher-valuation, Raising an A right now | V13: 26 months runway right now. Current bank bank balance of $3.4M and monthly burn in Q2 of $134k
B14: Kubera | C14: 45274 | D14: Seed | E14: Seed | F14: 30000000 | G14: 30000000 | H14: =VLOOKUP(B14,Sheet2!$K$4:$M$45,3,0) -> 0.033713855 | I14: 528083 | J14: 1011413 | K14: =J14/$J$31 -> 0.011350994 | L14: =J14/I14 -> 1.9152539 | M14: =68250+150000 -> 218250 | Q14: N/A | R14: =F14/M14 -> 137.45704 | S14: 1 | T14: 1 | U14: Signed a pilot partner for $500k TCV; converted all 3 pilot customers, raised Seed at $30M in Q3
B15: Clasp | C15: 45807 | D15: Seed - SVA | E15: Seed | F15: 35000000 | G15: 35000000 | H15: =VLOOKUP(B15,Sheet2!$K$4:$M$45,3,0) -> 0.0071428571 | I15: 250000 | J15: 250000 | K15: =J15/$J$31 -> 0.0028057268 | L15: =J15/I15 -> 1 | O15: 1100000 | Q15: N/A | R15: =F15/O15 -> 31.818182 | S15: 1 | T15: 1 | U15: Allstate scaled Clasp to 30+ agents, added 112 new companies, and adopted Clasp’s COBRA integration (via Anuvi) with HSA next; Remote’s integration is on track with an early go-live and a $150K ACV upsell; Deel’s $2.2M RFP is nearing completion to make Clasp their core BenAdmin platform; and open enrollment season is progressing strongly with 56 completions and 200+ upcoming. | V15: 21 months
B16: Outro Health | C16: 45806 | D16: Seed - SVA | E16: Seed | F16: 10000000 | G16: 10000000 | H16: =VLOOKUP(B16,Sheet2!$K$4:$M$45,3,0) -> 0.025 | I16: 250000 | J16: 250000 | K16: =J16/$J$31 -> 0.0028057268 | L16: =J16/I16 -> 1 | O16: 500000 | P16: 150000 | Q16: N/A | R16: =F16/O16 -> 20 | S16: 1 | T16: 1 | U16: $500K ARR, 157 active patients by 9/30, 48% QoQ. | W16: Launched insurance-based plans (5 patients onboarded), and strong 62% retention; heading into Q4, they’re starting a Seed Round, hiring marketing and ops leads, targeting 250 patients, and expanding into MI, PA, and NJ.
B17: Sunny Health | C17: 45806 | D17: Seed - SVA | E17: Seed | F17: 16000000 | G17: 16000000 | H17: =VLOOKUP(B17,Sheet2!$K$4:$M$45,3,0) -> 0.003125 | I17: 50000 | J17: 50000 | K17: =J17/$J$31 -> 0.00056114536 | L17: =J17/I17 -> 1 | M17: Pre-revenue | N17: Pre-revenue | O17: Pre-revenue | P17: Pre-revenue | Q17: N/A | R17: N/A | S17: 1 | T17: 1 | U17: Pre-Revenue
B18: Trial Library | C18: 45869 | D18: Seed | E18: Seed | F18: 60000000 | G18: 60000000 | H18: =VLOOKUP(B18,Sheet2!$K$4:$M$45,3,0) -> 0.060720105 | I18: 1999997 | J18: 1999997 | K18: =J18/$J$31 -> 0.022445781 | L18: =J18/I18 -> 1 | M18: 3172038 | O18: 8462310 | P18: 0 | Q18: N/A | R18: =F18/O18 -> 7.0902626 | S18: - | T18: 1 | U18: 2x revenue growth Q/Q, Expect to be cash flow positive in Q4, Rev run rate forecasted to hit $8.4M
B19: Tezi | C19: 45877 | D19: A | E19: A | F19: 50000000 | G19: 50000000 | H19: =VLOOKUP(B19,Sheet2!$K$4:$M$45,3,0) -> 0.033333283 | I19: 2999998 | J19: 2999998 | K19: =J19/$J$31 -> 0.033668699 | L19: =J19/I19 -> 1 | O19: 450000 | Q19: N/A | R19: =F19/O19 -> 111.11111 | S19: - | T19: 1 | U19: Forecasting flat growth as they pivot from SLG to PLG, followed by reacceleration. Not yet in the market with the new PLG product, so not yet ready to predict when growth accelerates. Provided conservative forecasts for now. planned Eng hiring to accelerate product development so burn is high right now. Will need to see how the pivot pans out, since its a recent investment will leave at green | V19: 23 months
B20: Andel | C20: 45924 | D20: Seed - SVA | E20: Seed | F20: 22500000 | G20: 22500000 | H20: =VLOOKUP(B20,Sheet2!$K$4:$M$45,3,0) -> 0.011111111 | I20: 250000 | J20: 250000 | K20: =J20/$J$31 -> 0.0028057268 | L20: =J20/I20 -> 1 | M20: Pre-revenue | N20: Pre-revenue | O20: Pre-revenue | P20: Pre-revenue | Q20: N/A | R20: N/A | S20: - | T20: 1 | U20: Recent Investment | V20: 14 months
B21: Second Door | C21: 45924 | D21: Seed - SVA | E21: Seed | F21: 14000000 | G21: 14000000 | H21: =VLOOKUP(B21,Sheet2!$K$4:$M$45,3,0) -> 0.017857143 | I21: 250000 | J21: 250000 | K21: =J21/$J$31 -> 0.0028057268 | L21: =J21/I21 -> 1 | M21: Pre-revenue | N21: Pre-revenue | O21: Pre-revenue | P21: Pre-revenue | Q21: N/A | R21: N/A | S21: - | T21: 1 | U21: Recent Investment
B22: TrueClaim | C22: 45924 | D22: Seed - SVA | E22: Seed | F22: 24000000 | G22: 24000000 | H22: =VLOOKUP(B22,Sheet2!$K$4:$M$45,3,0) -> 0.010416667 | I22: 250000 | J22: 250000 | K22: =J22/$J$31 -> 0.0028057268 | L22: =J22/I22 -> 1 | M22: Pre-revenue | N22: Pre-revenue | O22: Pre-revenue | P22: Pre-revenue | Q22: N/A | R22: N/A | S22: - | T22: 1 | U22: Recent Investment
B23: Techwolf | C23: 45467 | D23: B | E23: B | F23: 141000000 | G23: 141000000 | H23: =VLOOKUP(B23,Sheet2!$K$4:$M$45,3,0) -> 0.035210817 | I23: 5037377 | J23: 5037377 | K23: =J23/$J$31 -> 0.056534015 | L23: =J23/I23 -> 1 | M23: =3254786+2037894+2178612 -> 7471292 | N23: 6597644 | O23: 9181066 | P23: 6270535 | Q23: =M23/N23-1 -> 0.13241818 | R23: =F23/M23 -> 18.872238 | S23: 0 | T23: 1 | U23: Continuing to sign channel partnerships. Techwolf - signing bigger contracts, employers are leaning back in, on target to double this year and double next year Rev = $7M this year Double that next year 14M* 10x | V23: 12 months | W23: Workday is a customer—announced it will roll out TechWolf across Workday’s own 20k+ employees
B24: Summer | C24: 45209 | D24: A | E24: A | F24: 40166216 | G24: 40166216 | H24: =VLOOKUP(B24,Sheet2!$K$4:$M$45,3,0) -> 0.11734531 | I24: 3250000 | J24: 3250000 | K24: =J24/$J$31 -> 0.036474448 | L24: =J24/I24 -> 1 | M24: =1309991+858000+1195000 -> 3362991 | N24: 1556905 | Q24: =M24/N24-1 -> 1.1600489 | R24: =F24/M24 -> 11.943599 | S24: 0 | T24: 0 | U24: Signed NY City to $40M TCV contract, recap business allowed for increased ownership but revised revenue down so keeping as yellow
B25: PenguinAI | C25: 45821 | D25: A | E25: A | F25: 165000000 | G25: 165000000 | H25: =VLOOKUP(B25,Sheet2!$K$4:$M$45,3,0) -> 0.02527 | I25: 4000000 | J25: 4000000 | K25: =J25/$J$31 -> 0.044891629 | L25: =J25/I25 -> 1 | O25: 173000 | P25: 275500 | Q25: N/A | R25: - | S25: 1 | T25: 0 | U25: Forecasting ~$6.2M ARR by end of Q2'26. Pushed revenue projections out by a year. | V25: sufficient runway
B26: Laguna Health | C26: 45021 | D26: A | E26: A | F26: 53000000 | G26: 53000000 | H26: =VLOOKUP(B26,Sheet2!$K$4:$M$45,3,0) -> 0.077934988 | I26: 4999999.7 | J26: 4999999.7 | K26: =J26/$J$31 -> 0.056114533 | L26: =J26/I26 -> 1 | M26: =945907+629000 -> 1574907 | N26: 60382 | O26: 2386000 | Q26: =M26/N26-1 -> 25.082392 | R26: =F26/M26 -> 33.652781 | S26: 0 | T26: 0 | U26: Partnership with Highmark showing land and expand promise, need to raise EOY | V26: 5 months
B27: Multimodal | C27: 45614 | D27: Seed | E27: Seed | F27: 30000000 | G27: 30000000 | H27: =VLOOKUP(B27,Sheet2!$K$4:$M$45,3,0) -> 0.066666667 | I27: 2000000 | J27: 2000000 | K27: =J27/$J$31 -> 0.022445814 | L27: =J27/I27 -> 1 | M27: =205000+300000+450000 -> 955000 | N27: 1060690 | Q27: =M27/N27-1 -> -0.099642685 | R27: =F27/M27 -> 31.413613 | S27: 1 | T27: 0 | U27: Revenue dropped ~$600K in Q1–Q2 due to churn from two clients - a PE portfolio company exiting investments and a struggling startup - but the shift to larger enterprise deals has lengthened sales cycles, with current POC momentum expected to drive strong revenue growth in H2 2025 and into 2026. | V27: 21 months
B28: ExceedsAI | C28: 45666 | D28: Seed | E28: Seed | F28: 15000000 | G28: 15000000 | H28: =VLOOKUP(B28,Sheet2!$K$4:$M$45,3,0) -> 0.079166656 | I28: 1187499.8 | J28: 1187499.8 | K28: =J28/$J$31 -> 0.013327201 | L28: =J28/I28 -> 1 | M28: 30000 | N28: 0 | O28: 60000 | P28: 0 | Q28: N/A | R28: - | S28: 0 | T28: 0 | U28: Refining product and ICP with >1 year runway. $30,000 YTD Rev. No revenue in Q3. Revising forecasts in January with more actuals given pivot. | V28: 11 months
B29: Hireguide | C29: 45351 | D29: Seed | E29: Seed | F29: 32000000 | G29: 5000000 | H29: =VLOOKUP(B29,Sheet2!$K$4:$M$45,3,0) -> 0.09375 | I29: 3000000 | J29: 500000 | K29: =J29/$J$31 -> 0.0056114536 | L29: =J29/I29 -> 0.16666667 | M29: =128598+35000 -> 163598 | N29: 131353 | O29: 35000 | Q29: =M29/N29-1 -> 0.24548354 | R29: =F29/M29 -> 195.60141 | S29: -1 | T29: -1 | U29: In acquisition conversations with ATS and HCM providers, retiring existing Hireguide revenue to focus 100% on the pivot toward the AI Interviewer, Q2 2026 includes a new sales channel (Partner channel) which we're planning to open in April 2026 | V29: 6 months
I31: =SUM(I4:I29) -> 68071596 | J31: =SUM(J4:J29) -> 89103472
B32: *Carefam and Helm are Q4 Investments

Sheet Sheet2
M1: Reviewed 9/11 | X1: =143*10^6 -> 143000000
B2: Core Initial Investment Characteristics | K2: Current Investment Characteristics
B3: Company | C3: Date | D3: Series | E3: Sector | F3: $ Invested | G3: VC Syndicate | H3: FD% | I3: Avg. Cost | K3: Company | L3: Series | M3: FD% | N3: Initital Cost | O3: Avg. Cost | P3: Last Valuation | Q3: Holding Value | R3: $ Invested | S3: Follow -On Investment | T3: Market Value | U3: Multiple | V3: Lead | W3: Allocation | X3: RTF | Y3: Board Seat | AA3: 45107 | AB3: 45473 | AC3: 45565 | AD3: 45657 | AE3: 45838 | AH3: Rationale
B4: Laguna Health | C4: =INDEX('[2]Statement of Investments'!$C$5:$C$204,MATCH('[2]Investment Characteristics'!$B4,'[2]Statement of Investments'!$B$5:$B$204,0)) -> 45021 | D4: A | E4: Healthtech | F4: =INDEX('[2]Statement of Investments'!$L$5:$L$204,MATCH('[2]Investment Characteristics'!$B4,'[2]Statement of Investments'!$B$5:$B$204,0)) -> 3999999.7 | G4: HC9, Pitango | H4: 0.07547 | I4: =IFERROR(ROUND(F4/H4,-5),0) -> 53000000 | K4: =B4 -> Laguna Health | L4: A | M4: 0.077934988 | N4: =I4 -> 53000000 | O4: =IFERROR(ROUND(R4/M4,-5),0) -> 64200000 | P4: =N4 -> 53000000 | Q4: =+P4 -> 53000000 | R4: =INDEX('[2]Statement of Investments'!$L$5:$L$204,MATCH(B4,'[2]Statement of Investments'!$E$5:$E$204,0)) -> 4999999.7 | S4: =R4-F4 -> 1000000 | T4: =INDEX('[2]Statement of Investments'!$O$5:$O$204,MATCH(B4,'[2]Statement of Investments'!$E$5:$E$204,0)) -> 4999999.7 | U4: =T4/R4 -> 1 | V4: RP | W4: GG | X4: =+$X$1/M4/10^6 -> 1834.8627 | AA4: 1 | AB4: 1 | AC4: 0 | AD4: 0
B5: Stepful | C5: =INDEX('[2]Statement of Investments'!$C$5:$C$204,MATCH('[2]Investment Characteristics'!$B5,'[2]Statement of Investments'!$B$5:$B$204,0)) -> 45183 | D5: A | E5: Workforce | F5: =INDEX('[2]Statement of Investments'!$L$5:$L$204,MATCH('[2]Investment Characteristics'!$B5,'[2]Statement of Investments'!$B$5:$B$204,0)) -> 3999995.7 | G5: Reach, Alleycorp, YC | H5: 0.043589887 | I5: =IFERROR(ROUND(F5/H5,-5),0) -> 91800000 | K5: =B5 -> Stepful | L5: B | M5: 0.052805468 | N5: =I5 -> 91800000 | O5: =IFERROR(ROUND(R5/M5,-5),0) -> 149200000 | P5: 261500000 | Q5: =+P5 -> 261500000 | R5: =INDEX('[2]Statement of Investments'!$L$5:$L$204,MATCH(B5,'[2]Statement of Investments'!$E$5:$E$204,0)) -> 7878030.5 | S5: =R5-F5 -> 3878034.7 | T5: =INDEX('[2]Statement of Investments'!$O$5:$O$204,MATCH(B5,'[2]Statement of Investments'!$E$5:$E$204,0)) -> 13609280 | U5: =T5/R5 -> 1.7274977 | V5: ABG | W5: ABG | X5: =+$X$1/M5/10^6 -> 2708.0529 | AA5: - | AB5: 1 | AC5: 1 | AD5: 1
B6: Summer | C6: =INDEX('[2]Statement of Investments'!$C$5:$C$204,MATCH('[2]Investment Characteristics'!$B6,'[2]Statement of Investments'!$B$5:$B$204,0)) -> 45209 | D6: Seed | E6: Financial | F6: =INDEX('[2]Statement of Investments'!$L$5:$L$204,MATCH('[2]Investment Characteristics'!$B6,'[2]Statement of Investments'!$B$5:$B$204,0)) -> 3250000 | G6: GC, QED, Flourish, Rebalance | H6: =+F6/I6 -> 0.092857143 | I6: =35*10^6 -> 35000000 | K6: =B6 -> Summer | L6: A | M6: 0.11734531 | N6: =I6 -> 35000000 | O6: =IFERROR(ROUND(R6/M6,-5),0) -> 27700000 | P6: 41544018 | Q6: 41544018 | R6: =INDEX('[2]Statement of Investments'!$L$5:$L$204,MATCH(B6,'[2]Statement of Investments'!$E$5:$E$204,0)) -> 3250000 | S6: =R6-F6 -> 0 | T6: =INDEX('[2]Statement of Investments'!$O$5:$O$204,MATCH(B6,'[2]Statement of Investments'!$E$5:$E$204,0)) -> 3250000 | U6: =T6/R6 -> 1 | V6: RP | W6: RP | X6: =+$X$1/M6/10^6 -> 1218.6256 | AA6: - | AB6: 1 | AC6: 0 | AD6: -1
B7: Kubera | C7: =INDEX('[2]Statement of Investments'!$C$5:$C$204,MATCH('[2]Investment Characteristics'!$B7,'[2]Statement of Investments'!$B$5:$B$204,0)) -> 45274 | D7: Seed | E7: Healthtech | F7: =INDEX('[2]Statement of Investments'!$L$5:$L$204,MATCH('[2]Investment Characteristics'!$B7,'[2]Statement of Investments'!$B$5:$B$204,0)) -> 399999.2 | G7: Upfront Ventures | H7: =+F7/I7 -> 0.033333267 | I7: =12*10^6 -> 12000000 | K7: =B7 -> Kubera | L7: Seed | M7: 0.033713855 | N7: =I7 -> 12000000 | O7: =IFERROR(ROUND(R7/M7,-5),0) -> 15700000 | P7: 30000000 | Q7: =+P7 -> 30000000 | R7: =INDEX('[2]Statement of Investments'!$L$5:$L$204,MATCH(B7,'[2]Statement of Investments'!$E$5:$E$204,0)) -> 528082.67 | S7: =R7-F7 -> 128083.47 | T7: =INDEX('[2]Statement of Investments'!$O$5:$O$204,MATCH(B7,'[2]Statement of Investments'!$E$5:$E$204,0)) -> 1011413.2 | U7: =T7/R7 -> 1.9152554 | V7: RP | W7: RP | X7: =+$X$1/M7/10^6 -> 4241.5796 | AA7: - | AB7: 1 | AC7: 1 | AD7: 0
B8: Wagmo | C8: =INDEX('[2]Statement of Investments'!$C$5:$C$204,MATCH('[2]Investment Characteristics'!$B8,'[2]Statement of Investments'!$B$5:$B$204,0)) -> 45209 | D8: A | E8: Financial | F8: =INDEX('[2]Statement of Investments'!$L$5:$L$204,MATCH('[2]Investment Characteristics'!$B8,'[2]Statement of Investments'!$B$5:$B$204,0)) -> 1499998 | G8: Revolution, MS&AD | H8: 0.0191 | I8: =IFERROR(ROUND(F8/H8,-5),0) -> 78500000 | K8: =B8 -> Wagmo | L8: A | M8: 0.03180843 | N8: =I8 -> 78500000 | O8: =IFERROR(ROUND(R8/M8,-5),0) -> 47200000 | P8: =N8 -> 78500000 | Q8: =+P8 -> 78500000 | R8: =INDEX('[2]Statement of Investments'!$L$5:$L$204,MATCH(B8,'[2]Statement of Investments'!$E$5:$E$204,0)) -> 1499998 | S8: =R8-F8 -> 0 | T8: =INDEX('[2]Statement of Investments'!$O$5:$O$204,MATCH(B8,'[2]Statement of Investments'!$E$5:$E$204,0)) -> 1499998 | U8: =T8/R8 -> 1 | V8: RP | W8: CH | X8: =+$X$1/M8/10^6 -> 4495.6636 | AA8: - | AB8: 1 | AC8: 0 | AD8: 1
B9: Salsa | C9: =INDEX('[2]Statement of Investments'!$C$5:$C$204,MATCH('[2]Investment Characteristics'!$B9,'[2]Statement of Investments'!$B$5:$B$204,0)) -> 45329 | D9: Seed | E9: Financial | F9: =INDEX('[2]Statement of Investments'!$L$5:$L$204,MATCH('[2]Investment Characteristics'!$B9,'[2]Statement of Investments'!$B$5:$B$204,0)) -> 2500000 | G9: BTV, Greycroft | H9: =+F9/I9 -> 0.056818182 | I9: =44*10^6 -> 44000000 | K9: =B9 -> Salsa | L9: A | M9: 0.084687403 | N9: =I9 -> 44000000 | O9: =IFERROR(ROUND(R9/M9,-5),0) -> 64900000 | P9: =70*10^6 -> 70000000 | Q9: =+P9 -> 70000000 | R9: =INDEX('[2]Statement of Investments'!$L$5:$L$204,MATCH(B9,'[2]Statement of Investments'!$E$5:$E$204,0)) -> 5499997.9 | S9: =R9-F9 -> 2999997.9 | T9: =INDEX('[2]Statement of Investments'!$O$5:$O$204,MATCH(B9,'[2]Statement of Investments'!$E$5:$E$204,0)) -> 5912934 | U9: =T9/R9 -> 1.0750793 | V9: RP | W9: CH | X9: =+$X$1/M9/10^6 -> 1688.5628 | AA9: - | AB9: 1 | AC9: 1 | AD9: 1
B10: Solara | C10: =INDEX('[2]Statement of Investments'!$C$5:$C$204,MATCH('[2]Investment Characteristics'!$B10,'[2]Statement of Investments'!$B$5:$B$204,0)) -> 45329 | D10: Seed | E10: Healthtech | F10: =INDEX('[2]Statement of Investments'!$L$5:$L$204,MATCH('[2]Investment Characteristics'!$B10,'[2]Statement of Investments'!$B$5:$B$204,0)) -> 1999999.8 | G10: Define Ventures | H10: =+F10/I10 -> 0.13793102 | I10: 14500000 | K10: =B10 -> Solara | L10: Seed | M10: 0.13793102 | N10: =I10 -> 14500000 | O10: =IFERROR(ROUND(R10/M10,-5),0) -> 14500000 | P10: =N10 -> 14500000 | Q10: =+P10 -> 14500000 | R10: =INDEX('[2]Statement of Investments'!$L$5:$L$204,MATCH(B10,'[2]Statement of Investments'!$E$5:$E$204,0)) -> 1999999.8 | S10: =R10-F10 -> 0 | T10: =INDEX('[2]Statement of Investments'!$O$5:$O$204,MATCH(B10,'[2]Statement of Investments'!$E$5:$E$204,0)) -> 1999999.8 | U10: =T10/R10 -> 1 | V10: RP | W10: GG | X10: =+$X$1/M10/10^6 -> 1036.7501 | AA10: - | AB10: 1 | AC10: 1 | AD10: 1
B11: Hireguide | C11: =INDEX('[2]Statement of Investments'!$C$5:$C$204,MATCH('[2]Investment Characteristics'!$B11,'[2]Statement of Investments'!$B$5:$B$204,0)) -> 45351 | D11: Seed | E11: Workforce | F11: =INDEX('[2]Statement of Investments'!$L$5:$L$204,MATCH('[2]Investment Characteristics'!$B11,'[2]Statement of Investments'!$B$5:$B$204,0)) -> 3000000 | G11: Wing, NEA, GGV | H11: =+F11/I11 -> 0.09375 | I11: =32*10^6 -> 32000000 | K11: =B11 -> Hireguide | L11: Seed | M11: 0.09375 | N11: =I11 -> 32000000 | O11: =IFERROR(ROUND(R11/M11,-5),0) -> 32000000 | P11: =N11 -> 32000000 | Q11: =+P11 -> 32000000 | R11: =INDEX('[2]Statement of Investments'!$L$5:$L$204,MATCH(B11,'[2]Statement of Investments'!$E$5:$E$204,0)) -> 3000000 | S11: =R11-F11 -> 0 | T11: =INDEX('[2]Statement of Investments'!$O$5:$O$204,MATCH(B11,'[2]Statement of Investments'!$E$5:$E$204,0)) -> 500000 | U11: =T11/R11 -> 0.16666667 | V11: CT | W11: RP | X11: =+$X$1/M11/10^6 -> 1525.3333 | AA11: - | AC11: 1 | AD11: 0
B12: Take2 AI | C12: =INDEX('[2]Statement of Investments'!$C$5:$C$204,MATCH('[2]Investment Characteristics'!$B12,'[2]Statement of Investments'!$B$5:$B$204,0)) -> 45376 | D12: Seed | E12: Workforce | F12: =INDEX('[2]Statement of Investments'!$L$5:$L$204,MATCH('[2]Investment Characteristics'!$B12,'[2]Statement of Investments'!$B$5:$B$204,0)) -> 700000 | G12: Reach Capital | H12: =+F12/I12 -> 0.07 | I12: 10000000 | K12: =B12 -> Take2 AI | L12: Seed | M12: 0.07 | N12: =I12 -> 10000000 | O12: =IFERROR(ROUND(R12/M12,-5),0) -> 10000000 | P12: =N12 -> 10000000 | Q12: =+P12 -> 10000000 | R12: =INDEX('[2]Statement of Investments'!$L$5:$L$204,MATCH(B12,'[2]Statement of Investments'!$E$5:$E$204,0)) -> 700000 | S12: =R12-F12 -> 0 | T12: =INDEX('[2]Statement of Investments'!$O$5:$O$204,MATCH(B12,'[2]Statement of Investments'!$E$5:$E$204,0)) -> 700000 | U12: =T12/R12 -> 1 | V12: ABG | W12: ABG | X12: =+$X$1/M12/10^6 -> 2042.8571 | AA12: - | AC12: 1 | AD12: 0
B13: Techwolf | C13: =INDEX('[2]Statement of Investments'!$C$5:$C$204,MATCH('[2]Investment Characteristics'!$B13,'[2]Statement of Investments'!$B$5:$B$204,0)) -> 45467 | D13: B | E13: Workforce | F13: =INDEX('[2]Statement of Investments'!$L$5:$L$204,MATCH('[2]Investment Characteristics'!$B13,'[2]Statement of Investments'!$B$5:$B$204,0)) -> 5037377 | G13: Felix Capital, Stride VC | H13: =+F13/I13 -> 0.035726078 | I13: =141*10^6 -> 141000000 | K13: =B13 -> Techwolf | L13: B | M13: 0.035210817 | N13: =I13 -> 141000000 | O13: =IFERROR(ROUND(R13/M13,-5),0) -> 143100000 | P13: =N13 -> 141000000 | Q13: =+P13 -> 141000000 | R13: =INDEX('[2]Statement of Investments'!$L$5:$L$204,MATCH(B13,'[2]Statement of Investments'!$E$5:$E$204,0)) -> 5037377 | S13: =R13-F13 -> 0 | T13: =INDEX('[2]Statement of Investments'!$O$5:$O$204,MATCH(B13,'[2]Statement of Investments'!$E$5:$E$204,0)) -> 5037377 | U13: =T13/R13 -> 1 | V13: ABG | W13: ABG | X13: =+$X$1/M13/10^6 -> 4061.252 | AD13: 1
B14: Thatch | C14: =INDEX('[2]Statement of Investments'!$C$5:$C$204,MATCH('[2]Investment Characteristics'!$B14,'[2]Statement of Investments'!$B$5:$B$204,0)) -> 45513 | D14: A | E14: Healthtech | F14: =INDEX('[2]Statement of Investments'!$L$5:$L$204,MATCH('[2]Investment Characteristics'!$B14,'[2]Statement of Investments'!$B$5:$B$204,0)) -> 1509998.6 | G14: Index, GV, GC, a16z | H14: 0.029703718 | I14: =F14/H14 -> 50835341 | K14: =B14 -> Thatch | L14: B | M14: 0.032141794 | N14: =I14 -> 50835341 | O14: =IFERROR(ROUND(R14/M14,-5),0) -> 125700000 | P14: =450*10^6 -> 450000000 | Q14: =450*10^6 -> 450000000 | R14: =INDEX('[2]Statement of Investments'!$L$5:$L$204,MATCH(B14,'[2]Statement of Investments'!$E$5:$E$204,0)) -> 4040625.2 | S14: =R14-F14 -> 2530626.5 | T14: =INDEX('[2]Statement of Investments'!$O$5:$O$204,MATCH(B14,'[2]Statement of Investments'!$E$5:$E$204,0)) -> 10304094 | U14: =T14/R14 -> 2.5501238 | V14: RP | W14: GG | X14: =+$X$1/M14/10^6 -> 4449.0361 | AD14: 1
B15: Multimodal | C15: =INDEX('[2]Statement of Investments'!$C$5:$C$204,MATCH('[2]Investment Characteristics'!$B15,'[2]Statement of Investments'!$B$5:$B$204,0)) -> 45614 | D15: Seed | E15: Financial | F15: =INDEX('[2]Statement of Investments'!$L$5:$L$204,MATCH('[2]Investment Characteristics'!$B15,'[2]Statement of Investments'!$B$5:$B$204,0)) -> 2000000 | H15: =+F15/I15 -> 0.066666667 | I15: =30*10^6 -> 30000000 | K15: =B15 -> Multimodal | L15: Seed | M15: 0.066666667 | N15: =I15 -> 30000000 | O15: =IFERROR(ROUND(R15/M15,-5),0) -> 30000000 | P15: =N15 -> 30000000 | Q15: =+P15 -> 30000000 | R15: =INDEX('[2]Statement of Investments'!$L$5:$L$204,MATCH(B15,'[2]Statement of Investments'!$E$5:$E$204,0)) -> 2000000 | S15: =R15-F15 -> 0 | T15: =INDEX('[2]Statement of Investments'!$O$5:$O$204,MATCH(B15,'[2]Statement of Investments'!$E$5:$E$204,0)) -> 2000000 | U15: =T15/R15 -> 1 | V15: CH | W15: CH | X15: =+$X$1/M15/10^6 -> 2145 | AD15: 1
B16: OneImaging | C16: =INDEX('[2]Statement of Investments'!$C$5:$C$204,MATCH('[2]Investment Characteristics'!$B16,'[2]Statement of Investments'!$B$5:$B$204,0)) -> 45665 | D16: Seed | E16: Healthtech | F16: =INDEX('[2]Statement of Investments'!$L$5:$L$204,MATCH('[2]Investment Characteristics'!$B16,'[2]Statement of Investments'!$B$5:$B$204,0)) -> 1000000 | G16: Aquiline, Six Thirty, Vy Capital | H16: =+F16/I16 -> 0.055555556 | I16: =18*10^6 -> 18000000 | K16: =B16 -> OneImaging | L16: A | M16: 0.05994 | N16: =I16 -> 18000000 | O16: =IFERROR(ROUND(R16/M16,-5),0) -> 66700000 | P16: 250000000 | Q16: =+P16 -> 250000000 | R16: =INDEX('[2]Statement of Investments'!$L$5:$L$204,MATCH(B16,'[2]Statement of Investments'!$E$5:$E$204,0)) -> 4000000 | S16: =R16-F16 -> 3000000 | T16: =INDEX('[2]Statement of Investments'!$O$5:$O$204,MATCH(B16,'[2]Statement of Investments'!$E$5:$E$204,0)) -> 14640928 | U16: =T16/R16 -> 3.660232 | V16: CT | W16: RP | X16: =+$X$1/M16/10^6 -> 2385.7191 | AD16: 1
B17: ExceedsAI | C17: =INDEX('[2]Statement of Investments'!$C$5:$C$204,MATCH('[2]Investment Characteristics'!$B17,'[2]Statement of Investments'!$B$5:$B$204,0)) -> 45666 | D17: Seed | E17: Workforce | F17: =INDEX('[2]Statement of Investments'!$L$5:$L$204,MATCH('[2]Investment Characteristics'!$B17,'[2]Statement of Investments'!$B$5:$B$204,0)) -> 1187499.8 | G17: Venrock | H17: =+F17/I17 -> 0.079166656 | I17: =15*10^6 -> 15000000 | K17: =B17 -> ExceedsAI | L17: Seed | M17: 0.079166656 | N17: =I17 -> 15000000 | O17: =IFERROR(ROUND(R17/M17,-5),0) -> 15000000 | P17: =N17 -> 15000000 | Q17: =+P17 -> 15000000 | R17: =INDEX('[2]Statement of Investments'!$L$5:$L$204,MATCH(B17,'[2]Statement of Investments'!$E$5:$E$204,0)) -> 1187499.8 | S17: =R17-F17 -> 0 | T17: =INDEX('[2]Statement of Investments'!$O$5:$O$204,MATCH(B17,'[2]Statement of Investments'!$E$5:$E$204,0)) -> 1187499.8 | U17: =T17/R17 -> 1 | V17: ABG | W17: ABG | X17: =+$X$1/M17/10^6 -> 1806.316 | AD17: 1
B18: Sully.AI | C18: =INDEX('[2]Statement of Investments'!$C$5:$C$204,MATCH('[2]Investment Characteristics'!$B18,'[2]Statement of Investments'!$B$5:$B$204,0)) -> 45666 | D18: A | E18: Healthtech | F18: =INDEX('[2]Statement of Investments'!$L$5:$L$204,MATCH('[2]Investment Characteristics'!$B18,'[2]Statement of Investments'!$B$5:$B$204,0)) -> 3999999.5 | G18: Amity Ventures | H18: =+F18/I18 -> 0.053333327 | I18: =75*10^6 -> 75000000 | K18: =B18 -> Sully.AI | L18: A | M18: 0.053333327 | N18: =I18 -> 75000000 | O18: =IFERROR(ROUND(R18/M18,-5),0) -> 75000000 | P18: =N18 -> 75000000 | Q18: =+P18 -> 75000000 | R18: =INDEX('[2]Statement of Investments'!$L$5:$L$204,MATCH(B18,'[2]Statement of Investments'!$E$5:$E$204,0)) -> 3999999.5 | S18: =R18-F18 -> 0 | T18: =INDEX('[2]Statement of Investments'!$O$5:$O$204,MATCH(B18,'[2]Statement of Investments'!$E$5:$E$204,0)) -> 3999999.5 | U18: =T18/R18 -> 1 | V18: ABG | W18: ABG | X18: =+$X$1/M18/10^6 -> 2681.2503 | AD18: 1
B19: Athena.AI | C19: =INDEX('[2]Statement of Investments'!$C$5:$C$204,MATCH('[2]Investment Characteristics'!$B19,'[2]Statement of Investments'!$B$5:$B$204,0)) -> 45778 | D19: Seed | E19: Workforce | F19: =INDEX('[2]Statement of Investments'!$L$5:$L$204,MATCH('[2]Investment Characteristics'!$B19,'[2]Statement of Investments'!$B$5:$B$204,0)) -> 3150000 | G19: Village Global | H19: =+F19/I19 -> 0.09 | I19: =35*10^6 -> 35000000 | K19: =B19 -> Athena.AI | L19: Seed | M19: 0.09 | N19: =I19 -> 35000000 | O19: =IFERROR(ROUND(R19/M19,-5),0) -> 35000000 | P19: =N19 -> 35000000 | Q19: =+P19 -> 35000000 | R19: =INDEX('[2]Statement of Investments'!$L$5:$L$204,MATCH(B19,'[2]Statement of Investments'!$E$5:$E$204,0)) -> 3150000 | S19: =R19-F19 -> 0 | T19: =INDEX('[2]Statement of Investments'!$O$5:$O$204,MATCH(B19,'[2]Statement of Investments'!$E$5:$E$204,0)) -> 3150000 | U19: =T19/R19 -> 1 | V19: RP | W19: RP | X19: =+$X$1/M19/10^6 -> 1588.8889
B20: Onboarded | C20: =INDEX('[2]Statement of Investments'!$C$5:$C$204,MATCH('[2]Investment Characteristics'!$B20,'[2]Statement of Investments'!$B$5:$B$204,0)) -> 45824 | D20: A | E20: Workforce | F20: =INDEX('[2]Statement of Investments'!$L$5:$L$204,MATCH('[2]Investment Characteristics'!$B20,'[2]Statement of Investments'!$B$5:$B$204,0)) -> 5000000 | G20: SV, Resolute | H20: =+F20/I20 -> 0.086956522 | I20: =57.5*10^6 -> 57500000 | K20: =B20 -> Onboarded | L20: A | M20: 0.086956522 | N20: =I20 -> 57500000 | O20: =IFERROR(ROUND(R20/M20,-5),0) -> 57500000 | P20: =N20 -> 57500000 | Q20: =+P20 -> 57500000 | R20: =INDEX('[2]Statement of Investments'!$L$5:$L$204,MATCH(B20,'[2]Statement of Investments'!$E$5:$E$204,0)) -> 5000000 | S20: =R20-F20 -> 0 | T20: =INDEX('[2]Statement of Investments'!$O$5:$O$204,MATCH(B20,'[2]Statement of Investments'!$E$5:$E$204,0)) -> 5000000 | U20: =T20/R20 -> 1 | V20: CT | W20: GG | X20: =+$X$1/M20/10^6 -> 1644.5
B21: PenguinAI | C21: =INDEX('[2]Statement of Investments'!$C$5:$C$204,MATCH('[2]Investment Characteristics'!$B21,'[2]Statement of Investments'!$B$5:$B$204,0)) -> 45821 | D21: A | E21: Healthtech | F21: =INDEX('[2]Statement of Investments'!$L$5:$L$204,MATCH('[2]Investment Characteristics'!$B21,'[2]Statement of Investments'!$B$5:$B$204,0)) -> 4000000 | G21: GreyCroft, UPMC | H21: =+F21/I21 -> 0.024242424 | I21: =165*10^6 -> 165000000 | K21: =B21 -> PenguinAI | L21: A | M21: 0.02527 | N21: =I21 -> 165000000 | O21: =IFERROR(ROUND(R21/M21,-5),0) -> 158300000 | P21: =N21 -> 165000000 | Q21: =+P21 -> 165000000 | R21: =INDEX('[2]Statement of Investments'!$L$5:$L$204,MATCH(B21,'[2]Statement of Investments'!$E$5:$E$204,0)) -> 4000000 | S21: =R21-F21 -> 0 | T21: =INDEX('[2]Statement of Investments'!$O$5:$O$204,MATCH(B21,'[2]Statement of Investments'!$E$5:$E$204,0)) -> 4000000 | U21: =T21/R21 -> 1 | V21: GG | W21: GG | X21: =+$X$1/M21/10^6 -> 5658.8841
B22: Tezi | C22: =INDEX('[2]Statement of Investments'!$C$5:$C$204,MATCH('[2]Investment Characteristics'!$B22,'[2]Statement of Investments'!$B$5:$B$204,0)) -> 45869 | D22: Seed | E22: Workforce | F22: =INDEX('[2]Statement of Investments'!$L$5:$L$204,MATCH('[2]Investment Characteristics'!$B22,'[2]Statement of Investments'!$B$5:$B$204,0)) -> 1999997 | G22: 8VC, Audacious | H22: =F22/I22 -> 0.033333283 | I22: 60000000 | K22: =B22 -> Tezi | L22: Seed | M22: 0.033333283 | N22: =I22 -> 60000000 | O22: =IFERROR(ROUND(R22/M22,-5),0) -> 60000000 | P22: =N22 -> 60000000 | Q22: =+P22 -> 60000000 | R22: =INDEX('[2]Statement of Investments'!$L$5:$L$204,MATCH(B22,'[2]Statement of Investments'!$E$5:$E$204,0)) -> 1999997 | S22: =R22-F22 -> 0 | T22: =INDEX('[2]Statement of Investments'!$O$5:$O$204,MATCH(B22,'[2]Statement of Investments'!$E$5:$E$204,0)) -> 1999997 | U22: =T22/R22 -> 1 | V22: RP | W22: RP | X22: =+$X$1/M22/10^6 -> 4290.0064
B23: Trial Library | C23: =INDEX('[2]Statement of Investments'!$C$5:$C$204,MATCH('[2]Investment Characteristics'!$B23,'[2]Statement of Investments'!$B$5:$B$204,0)) -> 45877 | D23: A | E23: Healthtech | F23: =INDEX('[2]Statement of Investments'!$L$5:$L$204,MATCH('[2]Investment Characteristics'!$B23,'[2]Statement of Investments'!$B$5:$B$204,0)) -> 2999998 | G23: Lux, Next Ventures | H23: =F23/I23 -> 0.05999996 | I23: =50*10^6 -> 50000000 | K23: =B23 -> Trial Library | L23: A | M23: 0.060720105 | N23: =I23 -> 50000000 | O23: =IFERROR(ROUND(R23/M23,-5),0) -> 49400000 | P23: =N23 -> 50000000 | Q23: =+P23 -> 50000000 | R23: =INDEX('[2]Statement of Investments'!$L$5:$L$204,MATCH(B23,'[2]Statement of Investments'!$E$5:$E$204,0)) -> 2999998 | S23: =R23-F23 -> 0 | T23: =INDEX('[2]Statement of Investments'!$O$5:$O$204,MATCH(B23,'[2]Statement of Investments'!$E$5:$E$204,0)) -> 2999998 | U23: =T23/R23 -> 1 | V23: ABG | W23: GG
B24: Carefam | C24: 45949 | D24: A | E24: Healthtech | F24: =2.64*10^6 -> 2640000 | G24: Pitango Ventures | H24: 0.0702 | I24: =37*10^6 -> 37000000 | K24: Carefam | L24: A | M24: 0.0702 | N24: =I24 -> 37000000 | O24: =N24 -> 37000000 | P24: =O24 -> 37000000 | Q24: =P24 -> 37000000 | R24: =F24 -> 2640000 | S24: 0 | T24: =R24 -> 2640000 | U24: =T24/R24 -> 1 | V24: ABG | W24: ABG
B25: Helm | C25: 45958 | D25: A | E25: Healthtech | F25: 3000000 | G25: .406 Ventures, Springtide | H25: =+F25/I25 -> 0.066666667 | I25: 45000000 | K25: =+B25 -> Helm | L25: A | M25: 0.066666667 | N25: =I25 -> 45000000 | O25: =N25 -> 45000000 | P25: =O25 -> 45000000 | Q25: =P25 -> 45000000 | R25: =F25 -> 3000000 | S25: =R25-F25 -> 0 | T25: =R25 -> 3000000 | U25: =T25/R25 -> 1 | V25: CT | W25: GG
B32: Average | F32: =AVERAGE(F4:F31) -> 2676130.1 | H32: =AVERAGE(H4:H31) -> 0.062472743 | I32: =AVERAGE(I4:I31) -> 52278879 | K32: Average | M32: =AVERAGE(M4:M31) -> 0.06634465 | N32: =AVERAGE(N4:N31) -> 52278879 | O32: =AVERAGE(O4:O31) -> 60140909 | P32: =AVERAGE(P4:P31) -> 90979274 | R32: =AVERAGE(R4:R31) -> 3291436.6 | T32: =AVERAGE(T4:T31) -> 4247432.6
B33: Median | F33: =MEDIAN(F4:F31) -> 2819999 | H33: =MEDIAN(H4:H31) -> 0.063333313 | I33: =MEDIAN(I4:I31) -> 44500000 | K33: Median | M33: =MEDIAN(M4:M31) -> 0.066666667 | N33: =MEDIAN(N4:N31) -> 44500000 | O33: =MEDIAN(O4:O31) -> 48300000 | P33: =MEDIAN(P4:P31) -> 51500000 | R33: =MEDIAN(R4:R31) -> 3075000 | T33: =MEDIAN(T4:T31) -> 3075000
B34: Dollar Weighted | H34: =SUMPRODUCT(H$4:H$31,$F$4:$F$31)/SUM($F$4:$F$31) -> 0.06346449 | I34: =SUMPRODUCT(I$4:I$31,$F$4:$F$31)/SUM($F$4:$F$31) -> 64556806 | K34: Dollar Weighted | M34: =SUMPRODUCT(M$4:M$31,$R$4:$R$31)/SUM($R$4:$R$31) -> 0.065813435 | N34: =SUMPRODUCT(N$4:N$31,$R$4:$R$31)/SUM($R$4:$R$31) -> 62503225 | O34: =SUMPRODUCT(O$4:O$31,$R$4:$R$31)/SUM($R$4:$R$31) -> 76778649 | P34: =SUMPRODUCT(P$4:P$31,$R$4:$R$31)/SUM($R$4:$R$31) -> 1.1845489e+08
B38: SVA Initial Investment Characteristics | K38: Current Investment Characteristics
B39: Company | C39: Date | D39: Series | E39: Sector | F39: $ Invested | G39: VC Syndicate | H39: FD% | I39: Avg. Cost | K39: Company | L39: Series | M39: FD% | N39: Initital Cost | O39: Avg. Cost | P39: Last Valuation | Q39: Holding Value | R39: $ Invested | S39: Follow -On Investment | T39: Market Value | U39: Multiple | V39: Lead | W39: Allocation | X39: RTF
B40: Clasp | C40: =INDEX('[2]Statement of Investments'!$C$5:$C$204,MATCH('[2]Investment Characteristics'!$B40,'[2]Statement of Investments'!$B$5:$B$204,0)) -> 45807 | D40: Seed - SVA | E40: Workforce | F40: =INDEX('[2]Statement of Investments'!$L$5:$L$204,MATCH('[2]Investment Characteristics'!$B40,'[2]Statement of Investments'!$B$5:$B$204,0)) -> 250000 | G40: SV | H40: =F40/I40 -> 0.0071428571 | I40: 35000000 | K40: =B40 -> Clasp | L40: Seed | M40: 0.0071428571 | N40: =I40 -> 35000000 | O40: =IFERROR(ROUND(R40/M40,-5),0) -> 35000000 | P40: =N40 -> 35000000 | Q40: =+P40 -> 35000000 | R40: =INDEX('[2]Statement of Investments'!$L$5:$L$204,MATCH(B40,'[2]Statement of Investments'!$E$5:$E$204,0)) -> 250000 | T40: =INDEX('[2]Statement of Investments'!$O$5:$O$204,MATCH(B40,'[2]Statement of Investments'!$E$5:$E$204,0)) -> 250000 | U40: =T40/R40 -> 1 | W40: CH | X40: =+$X$1/M40/10^6 -> 20020
B41: Sunny Health | C41: =INDEX('[2]Statement of Investments'!$C$5:$C$204,MATCH('[2]Investment Characteristics'!$B41,'[2]Statement of Investments'!$B$5:$B$204,0)) -> 45806 | D41: Seed - SVA | E41: Healthtech | F41: =INDEX('[2]Statement of Investments'!$L$5:$L$204,MATCH('[2]Investment Characteristics'!$B41,'[2]Statement of Investments'!$B$5:$B$204,0)) -> 50000 | G41: SV | H41: =F41/I41 -> 0.003125 | I41: 16000000 | K41: =B41 -> Sunny Health | L41: Seed | M41: 0.003125 | N41: =I41 -> 16000000 | O41: =IFERROR(ROUND(R41/M41,-5),0) -> 16000000 | P41: =N41 -> 16000000 | Q41: =+P41 -> 16000000 | R41: =INDEX('[2]Statement of Investments'!$L$5:$L$204,MATCH(B41,'[2]Statement of Investments'!$E$5:$E$204,0)) -> 50000 | T41: =INDEX('[2]Statement of Investments'!$O$5:$O$204,MATCH(B41,'[2]Statement of Investments'!$E$5:$E$204,0)) -> 50000 | U41: =T41/R41 -> 1 | W41: RP | X41: =+$X$1/M41/10^6 -> 45760
B42: Outro Health | C42: =INDEX('[2]Statement of Investments'!$C$5:$C$204,MATCH('[2]Investment Characteristics'!$B42,'[2]Statement of Investments'!$B$5:$B$204,0)) -> 45806 | D42: Seed - SVA | E42: Healthtech | F42: =INDEX('[2]Statement of Investments'!$L$5:$L$204,MATCH('[2]Investment Characteristics'!$B42,'[2]Statement of Investments'!$B$5:$B$204,0)) -> 250000 | G42: SV | H42: =F42/I42 -> 0.025 | I42: 10000000 | K42: =B42 -> Outro Health | L42: Seed | M42: 0.025 | N42: =I42 -> 10000000 | O42: =IFERROR(ROUND(R42/M42,-5),0) -> 10000000 | P42: =N42 -> 10000000 | Q42: =+P42 -> 10000000 | R42: =INDEX('[2]Statement of Investments'!$L$5:$L$204,MATCH(B42,'[2]Statement of Investments'!$E$5:$E$204,0)) -> 250000 | T42: =INDEX('[2]Statement of Investments'!$O$5:$O$204,MATCH(B42,'[2]Statement of Investments'!$E$5:$E$204,0)) -> 250000 | U42: =T42/R42 -> 1 | W42: ABG | X42: =+$X$1/M42/10^6 -> 5720
B43: TrueClaim | C43: =INDEX('[2]Statement of Investments'!$C$5:$C$204,MATCH('[2]Investment Characteristics'!$B43,'[2]Statement of Investments'!$B$5:$B$204,0)) -> 45924 | D43: Seed - SVA | E43: Healthtech | F43: =INDEX('[2]Statement of Investments'!$L$5:$L$204,MATCH('[2]Investment Characteristics'!$B43,'[2]Statement of Investments'!$B$5:$B$204,0)) -> 250000 | G43: SV | H43: =F43/I43 -> 0.010416667 | I43: 24000000 | K43: TrueClaim | L43: Seed | M43: 0.010416667 | N43: =I43 -> 24000000 | O43: =IFERROR(ROUND(R43/M43,-5),0) -> 24000000 | P43: =N43 -> 24000000 | Q43: =+P43 -> 24000000 | R43: =INDEX('[2]Statement of Investments'!$L$5:$L$204,MATCH(B43,'[2]Statement of Investments'!$E$5:$E$204,0)) -> 250000 | T43: =INDEX('[2]Statement of Investments'!$O$5:$O$204,MATCH(B43,'[2]Statement of Investments'!$E$5:$E$204,0)) -> 250000 | U43: =T43/R43 -> 1 | X43: =+$X$1/M43/10^6 -> 13728
B44: Andel | C44: =INDEX('[2]Statement of Investments'!$C$5:$C$204,MATCH('[2]Investment Characteristics'!$B44,'[2]Statement of Investments'!$B$5:$B$204,0)) -> 45924 | D44: Seed - SVA | E44: Healthtech | F44: =INDEX('[2]Statement of Investments'!$L$5:$L$204,MATCH('[2]Investment Characteristics'!$B44,'[2]Statement of Investments'!$B$5:$B$204,0)) -> 250000 | G44: SV | H44: =F44/I44 -> 0.011111111 | I44: 22500000 | K44: Andel | L44: Seed | M44: 0.011111111 | N44: =I44 -> 22500000 | O44: =IFERROR(ROUND(R44/M44,-5),0) -> 22500000 | P44: =N44 -> 22500000 | Q44: =+P44 -> 22500000 | R44: =INDEX('[2]Statement of Investments'!$L$5:$L$204,MATCH(B44,'[2]Statement of Investments'!$E$5:$E$204,0)) -> 250000 | T44: =INDEX('[2]Statement of Investments'!$O$5:$O$204,MATCH(B44,'[2]Statement of Investments'!$E$5:$E$204,0)) -> 250000 | U44: =T44/R44 -> 1 | X44: =+$X$1/M44/10^6 -> 12870
B45: Second Door | C45: =INDEX('[2]Statement of Investments'!$C$5:$C$204,MATCH('[2]Investment Characteristics'!$B45,'[2]Statement of Investments'!$B$5:$B$204,0)) -> 45924 | D45: Seed - SVA | E45: Healthtech | F45: =INDEX('[2]Statement of Investments'!$L$5:$L$204,MATCH('[2]Investment Characteristics'!$B45,'[2]Statement of Investments'!$B$5:$B$204,0)) -> 250000 | G45: SV | H45: =F45/I45 -> 0.017857143 | I45: 14000000 | K45: Second Door | L45: Seed | M45: 0.017857143 | N45: =I45 -> 14000000 | O45: =IFERROR(ROUND(R45/M45,-5),0) -> 14000000 | P45: =N45 -> 14000000 | Q45: =+P45 -> 14000000 | R45: =INDEX('[2]Statement of Investments'!$L$5:$L$204,MATCH(B45,'[2]Statement of Investments'!$E$5:$E$204,0)) -> 250000 | T45: =INDEX('[2]Statement of Investments'!$O$5:$O$204,MATCH(B45,'[2]Statement of Investments'!$E$5:$E$204,0)) -> 250000 | U45: =T45/R45 -> 1 | X45: =+$X$1/M45/10^6 -> 8008
B54: Fund III Sector Summary
C55: Workforce | D55: Healthtech | E55: Financial | F55: Total
B56: Deals:
B57: # of Deals | C57: =COUNTIF($E$4:$E$42,C$55) -> 9 | D57: =COUNTIF($E$4:$E$42,D$55) -> 12 | E57: =COUNTIF($E$4:$E$33,E$55) -> 4 | F57: =SUM(C57:E57) -> 25
B58: % of Deals | C58: =C57/$F$57 -> 0.36 | D58: =D57/$F$57 -> 0.48 | E58: =E57/$F$57 -> 0.16 | F58: =F57/$F$57 -> 1
B60: Initial Investment | C60: =SUMIF($E$4:$E$33,C$55,$F$4:$F$33) -> 24074870 | D60: =SUMIF($E$4:$E$33,D$55,$F$4:$F$33) -> 25549995 | E60: =SUMIF($E$4:$E$33,E$55,$F$4:$F$33) -> 9249998 | F60: =SUM(C60:E60) -> 58874862
B61: % of Invested Cap | C61: =C60/$F$60 -> 0.40891594 | D61: =D60/$F$60 -> 0.4339712 | E61: =E60/$F$60 -> 0.15711286 | F61: =F60/$F$60 -> 1
B62: Current Investment | C62: =SUMIF($E$4:$E$30,C$55,$R$4:$R$30) -> 27952904 | D62: =SUMIF($E$4:$E$30,D$55,$R$4:$R$30) -> 32208705 | E62: =SUMIF($E$4:$E$29,E$55,$R$4:$R$29) -> 12249996 | F62: =SUM(C62:E62) -> 72411605
B63: % of Invested Cap | C63: =C62/$F$62 -> 0.38602796 | D63: =D62/$F$62 -> 0.44480032 | E63: =E62/$F$62 -> 0.16917172 | F63: =F62/$F$62 -> 1
B64: Current Mark
B65: Total Value | C65: =SUMIF($E$4:$E$33,C$55,$T$4:$T$33) -> 31184153 | D65: =SUMIF($E$4:$E$33,D$55,$T$4:$T$33) -> 49596433 | E65: =SUMIF($E$4:$E$33,E$55,$T$4:$T$33) -> 12662932 | F65: =SUM(C65:E65) -> 93443518
B66: MOIC | C66: =C65/C62 -> 1.1155962 | D66: =D65/D62 -> 1.5398456 | E66: =E65/E62 -> 1.0337091 | F66: =F65/F62 -> 1.2904495
B67: Average Investment:
B68: Initial Avg. Inv. | C68: =AVERAGEIF($E$4:$E$33,C$55,$F$4:$F$33) -> 3009358.7 | D68: =AVERAGEIF($E$4:$E$33,D$55,$F$4:$F$33) -> 2554999.5 | E68: =AVERAGEIF($E$4:$E$33,E$55,$F$4:$F$33) -> 2312499.5 | F68: =F32 -> 2676130.1
B69: Current Avg. Inv. | C69: =AVERAGEIF($E$4:$E$31,C$55,$R$4:$R$31) -> 3494113 | D69: =AVERAGEIF($E$4:$E$31,D$55,$R$4:$R$31) -> 3220870.5 | E69: =AVERAGEIF($E$4:$E$31,E$55,$R$4:$R$31) -> 3062499 | F69: =R32 -> 3291436.6
B70: Average Cost:
B71: Initial Avg. Cost | C71: =AVERAGEIF($E$4:$E$33,C$55,$I$4:$I$33) -> 55287500 | D71: =AVERAGEIF($E$4:$E$33,D$55,$I$4:$I$33) -> 52033534 | E71: =AVERAGEIF($E$4:$E$33,E$55,$I$4:$I$33) -> 46875000 | F71: =I32 -> 52278879
B72: Current Avg. Inv. | C72: =AVERAGEIF($E$4:$E$33,C$55,$O$4:$O$33) -> 62725000 | D72: =AVERAGEIF($E$4:$E$33,D$55,$O$4:$O$33) -> 65150000 | E72: =AVERAGEIF($E$4:$E$33,E$55,$O$4:$O$33) -> 42450000 | F72: =O32 -> 60140909
B73: Round
B74: Seed | C74: =COUNTIFS($D$4:$D$33,$B74,$E$4:$E$33,C$55) -> 5 | D74: =COUNTIFS($D$4:$D$33,$B74,$E$4:$E$33,D$55) -> 3 | E74: =COUNTIFS($D$4:$D$33,$B74,$E$4:$E$33,E$55) -> 3 | F74: =SUM(C74:E74) -> 11
B75: A | C75: =COUNTIFS($D$4:$D$33,$B75,$E$4:$E$33,C$55) -> 2 | D75: =COUNTIFS($D$4:$D$33,$B75,$E$4:$E$33,D$55) -> 7 | E75: =COUNTIFS($D$4:$D$33,$B75,$E$4:$E$33,E$55) -> 1 | F75: =SUM(C75:E75) -> 10
B76: B+ | C76: =COUNTIFS($D$4:$D$33,"B",$E$4:$E$33,C$55)+COUNTIFS($D$4:$D$33,"C",$E$4:$E$33,C$55) -> 1 | D76: =COUNTIFS($D$4:$D$33,"B",$E$4:$E$33,D$55)+COUNTIFS($D$4:$D$33,"C",$E$4:$E$33,D$55) -> 0 | E76: =COUNTIFS($D$4:$D$33,"B",$E$4:$E$33,E$55)+COUNTIFS($D$4:$D$33,"C",$E$4:$E$33,E$55) -> 0 | F76: =SUM(C76:E76) -> 1
B79: Fund III Stage Summary
C80: Seed | D80: A | E80: B | F80: Total
B81: Average Investment:
B82: Initial Avg. Inv. | C82: =AVERAGEIF($D$4:$D$31,C$80,$F$4:$F$31) -> 1926136 | D82: =AVERAGEIF($D$4:$D$31,D$80,$F$4:$F$31) -> 3264999 | E82: =AVERAGEIFS($F$4:$F$31,$D$4:$D$31,"<>Seed",$D$4:$D$31,"<>A") -> 5037377 | F82: =F32 -> 2676130.1
B83: Current Avg. Inv. | C83: =AVERAGEIF($D$4:$D$31,C$80,$R$4:$R$31) -> 2483234.3 | D83: =AVERAGEIF($D$4:$D$31,D$80,$R$4:$R$31) -> 4005865.1 | E83: =AVERAGEIF($D$4:$D$31,E$80,$R$4:$R$31) -> 5037377 | F83: =R32 -> 3291436.6
B84: Deals
B85: Initial # of Deals | C85: =COUNTIF($D$4:$D$33,C$80) -> 11 | D85: =COUNTIF($D$4:$D$33,D$80) -> 10 | E85: =COUNTIF($D$4:$D$31,"B")+COUNTIF($D$4:$D$31,"C") -> 1 | F85: =SUM(C85:E85) -> 22
B86: % of Deals | C86: =C85/$F$85 -> 0.5 | D86: =D85/$F$85 -> 0.45454545 | E86: =E85/$F$85 -> 0.045454545 | F86: =F85/$F$85 -> 1
B87: Current # of Deals | C87: =COUNTIF($L$4:$L$33,C$80) -> 8 | D87: =COUNTIF($L$4:$L$33,D$80) -> 11 | E87: =F85-SUM(C87:D87) -> 3 | F87: =SUM(C87:E87) -> 22
B88: % of Deals | C88: =C87/$F$87 -> 0.36363636 | D88: =D87/$F$87 -> 0.5 | E88: =E87/$F$87 -> 0.13636364 | F88: =F87/$F$85 -> 1
B89: Valuation
B90: Initial Avg. Cost | C90: =AVERAGEIF($D$4:$D$31,C$80,$I$4:$I$31) -> 27772727 | D90: =AVERAGEIF($D$4:$D$31,D$80,$I$4:$I$31) -> 70363534 | E90: =AVERAGEIFS($I$4:$I$31,$D$4:$D$31,"<>Seed",$D$4:$D$31,"<>A") -> 141000000 | F90: =I32 -> 52278879 | H90: =1/11 -> 0.090909091 | I90: Series B #
B91: Initial Median Cost | C91: {=MEDIAN(IF($D$4:$D$31=C80,$I$4:$I$31))} -> 30000000 | D91: {=MEDIAN(IF($D$4:$D$31=D80,$I$4:$I$31))} -> 55250000 | E91: =MEDIAN(I13) -> 141000000 | F91: =I33 -> 44500000 | H91: =6/11 -> 0.54545455 | I91: Series A #
B92: Ownership | H92: =4/11 -> 0.36363636 | I92: Seed #
B93: Initial Avg. FD% | C93: =AVERAGEIF($D$4:$D$31,C$80,$H$4:$H$31) -> 0.073582888 | D93: =AVERAGEIF($D$4:$D$31,D$80,$H$4:$H$31) -> 0.05292625 | E93: =AVERAGEIFS($H$4:$H$31,$D$4:$D$31,"<>Seed",$D$4:$D$31,"<>A") -> 0.035726078 | F93: =H32 -> 0.062472743
B94: Initial Median FD% | C94: {=MEDIAN(IF($D$4:$D$31=C$80,$H$4:$H$31))} -> 0.07 | D94: {=MEDIAN(IF($D$4:$D$31=D$80,$H$4:$H$31))} -> 0.056666643 | E94: =MEDIAN(H13) -> 0.035726078 | F94: =H33 -> 0.063333313 | H94: =5/30.3 -> 0.1650165 | I94: Series B $
B95: Invested Capital: | H95: =16.7/30.3 -> 0.55115512 | I95: Series A $
B96: Initial Investment | C96: =SUMIF($D$4:$D$31,C$80,$F$4:$F$31) -> 21187496 | D96: =SUMIF($D$4:$D$31,D$80,$F$4:$F$31) -> 32649990 | E96: =SUMIF($D$4:$D$31,"B",$F$4:$F$31) -> 5037377 | F96: =SUM(C96:E96) -> 58874862 | H96: =8.6/30.3 -> 0.28382838 | I96: Seed $
C97: =C96/$F$96 -> 0.35987338 | D97: =D96/$F$96 -> 0.55456588 | E97: =E96/$F$96 -> 0.085560744
B98: Current Investment | C98: =SUMIF($L$4:$L$31,C$80,$R$4:$R$31) -> 14565579 | D98: =SUMIF($L$4:$L$31,D$80,$R$4:$R$31) -> 40889993 | E98: =SUMIF($L$4:$L$31,E$80,$R$4:$R$31) -> 16956033 | F98: =SUM(C98:E98) -> 72411605 | H98: =11.4/30.3 -> 0.37623762 | I98: Fintech $
C99: =C98/$F$98 -> 0.20114979 | D99: =D98/$F$98 -> 0.5646884 | E99: =E98/$F$98 -> 0.23416181 | H99: =11.2/30.3 -> 0.36963696 | I99: Healthcare $
B100: Current Valuation:
B101: Valuation | C101: =SUMIF($D$4:$D$31,C$80,$T$4:$T$31) -> 36352772 | D101: =SUMIF($D$4:$D$31,D$80,$T$4:$T$31) -> 52053369 | E101: =SUMIF($D$4:$D$31,E$80,$T$4:$T$31) -> 5037377 | F101: =SUM(C101:E101) -> 93443518
B102: Current MOIC | C102: =C101/C98 -> 2.4958 | D102: =D101/D98 -> 1.27301 | E102: =E101/E98 -> 0.29708465 | F102: =F101/F98 -> 1.2904495
B103: Avg step up | C103: =C101/F101 -> 0.38903471 | D103: =D101/F101 -> 0.55705703 | E103: =E101/F101 -> 0.053908255 | H103: =7.7/30.3 -> 0.25412541 | I103: Workforce $
C105: =SUMIF($D$4:$D$31,C$80,$R$4:$R$31) -> 27315577 | D105: =SUMIF($D$4:$D$31,D$80,$R$4:$R$31) -> 40058651 | E105: =SUMIF($D$4:$D$31,E$80,$R$4:$R$31)+R10 -> 7037376.8 | F105: =SUM(C105:E105) -> 74411605
C106: =C105/$F$105 -> 0.3670876 | D106: =D105/$F$105 -> 0.53833876 | E106: =E105/$F$105 -> 0.094573646
F108: =2/50 -> 0.04
C110: `

Sheet GOF I RYG
B2: GOF I Portfolio Health
B3: Company | C3: Initial Inv. Date | D3: Initial Inv. Series | E3: Current Inv. Series | F3: Last Valuation | G3: SV Holding Value | H3: FD% | I3: $ Invested | K3: Current Market Value | L3: Portfolio Value | M3: MOIC | N3: 2025E Rev | O3: 2024A Rev | P3: 2025E ARR | Q3: 2024 ARR | R3: Rev/ARR Growth YoY | S3: Rev Multiple | T3: Q2 Status | U3: Current Q3 Status | V3: Rationale | W3: Fundraising/Current Runway | X3: Other key highlights
B4: Spring | E4: E | F4: 3300000000 | G4: 3300000000 | H4: =VLOOKUP(B4,Sheet3!$A$3:$D$13,4,0) -> 0.0013440277 | I4: 2999992.2 | K4: 4435508.1 | L4: =K4/$K$14 -> 0.25402464 | M4: =K4/I4 -> 1.4785065 | N4: No FS | O4: No FS | P4: 750000000 | Q4: No FS | R4: N/A | S4: - | T4: 1 | U4: 1 | V4: Continues to beat plan and is approaching profitability | W4: Potential IPO Candidate | X4: In Oct 2025, released the “VERA‑MH” initiative, described as the first open-source evaluation framework for validating AI in mental-health care
B5: Carrot | E5: D | F5: 600000000 | G5: 600000000 | H5: =VLOOKUP(B5,Sheet3!$A$3:$D$13,4,0) -> 0.0048507273 | I5: 2200002.1 | K5: 2911244.8 | L5: =K5/$K$14 -> 0.16672901 | M5: =K5/I5 -> 1.3232918 | N5: No FS | O5: No FS | P5: No FS | Q5: No FS | R5: N/A | S5: - | T5: 1 | U5: 1 | V5: Scaling well with significant partnerships helping cover over 17,000 providers nationwide, expanded its U.S provider network significantly: adding ~4,200 new clinics/providers across all 50 states
B6: Rula | E6: C | F6: 1250000000 | G6: 1250000000 | H6: =VLOOKUP(B6,Sheet3!$A$3:$D$13,4,0) -> 0.0023371701 | I6: 1499998.4 | K6: 1499998.4 | L6: =K6/$K$14 -> 0.085905952 | M6: =K6/I6 -> 1 | N6: 236000000 | O6: 121610000 | P6: 786000000 | R6: =N6/O6-1 -> 0.94062988 | S6: =F6/N6 -> 5.2966102 | T6: 1 | U6: 1 | V6: Forecasting ~2x y/y growth with revenue run rate above $200M by year end
B7: Rightway | E7: C | F7: 625000000 | G7: 625000000 | H7: =VLOOKUP(B7,Sheet3!$A$3:$D$13,4,0) -> 0.0015768049 | I7: 1499959.3 | K7: 982749.22 | L7: =K7/$K$14 -> 0.056282732 | M7: =K7/I7 -> 0.65518392 | N7: 45000000 | O7: 25972982 | P7: 83000000 | Q7: 49300395 | R7: =N7/O7-1 -> 0.73256964 | S7: =F7/N7 -> 13.888889 | T7: 1 | U7: 1 | V7: ARR is projected to to grow to $132M or by 60% by H12026. Strong retention and growth metrics | W7: 36 months | X7: Rebranded logo & reported: ~113% revenue retention, >97% client retention, and year-over-year member growth of 100%+ in 2025
B8: Fountain | E8: C | F8: 860000000 | G8: 860000000 | H8: =VLOOKUP(B8,Sheet3!$A$3:$D$13,4,0) -> 0.0045216718 | I8: 2999981.3 | K8: 3888643 | L8: =K8/$K$14 -> 0.22270529 | M8: =K8/I8 -> 1.2962224 | N8: =24222597+8497000 -> 32719597 | O8: 36517866 | P8: 33851000 | Q8: 31676017 | R8: =N8/O8-1 -> -0.10401125 | S8: =F8/N8 -> 26.283942 | T8: 0 | U8: 0 | V8: Revenue is down, ARR forecasts revised down from ~41M to $34M | W8: 34 months | X8: Announced its “Agentic-First Frontline Operating System” at HR Tech 2025 featuring a 12-product suite spanning hiring, onboarding, shift-management, referrals, communications and compliance.
B9: Karat | E9: C | F9: 1111200000 | G9: Pref Stack - $168.8M | H9: =VLOOKUP(B9,Sheet3!$A$3:$D$13,4,0) -> 0.0013500458 | I9: 1499987.1 | K9: 1499987.1 | L9: =K9/$K$14 -> 0.085905306 | M9: =K9/I9 -> 1 | N9: =16734498+6826439 -> 23560937 | O9: 16800000 | R9: =N9/O9-1 -> 0.40243673 | S9: =F9/N9 -> 47.16281 | T9: 0 | U9: 0 | V9: Holding at preference stack, modest growth (1.4x) but 2+ years of runway. | W9: 24 months | X9: Acquired Byteboard in early 2025, skill based technical assessment company, how is this acq progressing? New add on services?
B10: Ladder | E10: D | F10: 330000000 | G10: 330000000 | H10: =VLOOKUP(B10,Sheet3!$A$3:$D$13,4,0) -> 0.0024242189 | I10: 1999984.6 | K10: 742808.52 | L10: =K10/$K$14 -> 0.042541161 | M10: =K10/I10 -> 0.37140712 | N10: =26013880*2 -> 52027760 | O10: 49313412 | P10: No forecasts provided | R10: =N10/O10-1 -> 0.055042794 | S10: =F10/N10 -> 6.3427678 | T10: 0 | U10: 0 | V10: Recapitalized business, at $50M revenue run rate
B11: Charthop | E11: C | F11: 270000000 | G11: Pref Stack - $75M | H11: =VLOOKUP(B11,Sheet3!$A$3:$D$13,4,0) -> 0.0012472782 | I11: 499999.98 | K11: 499999.98 | L11: =K11/$K$14 -> 0.028635347 | M11: =K11/I11 -> 1 | N11: 8668373 | O11: 7936982 | P11: 8074878 | Q11: 9445102 | R11: =N11/O11-1 -> 0.092149762 | S11: =F11/N11 -> 31.147714 | T11: -1 | U11: -1 | V11: Revenue forecast is up ~9%, signed new business with Kraken, ~1.5 yrs of runway, holding at preference stack, forecasting ~12M by end of 2026. ARR up 7% YOY | W11: 16 months | X11: introduced ChartHop AI, a new capability that merges people data with business metrics and overlays role-based security controls, new VP of sales hired, feedback from HR Tech?
B12: Hone | E12: B | F12: 126200000 | G12: 126200000 | H12: =VLOOKUP(B12,Sheet3!$A$3:$D$13,4,0) -> 0.0079223739 | I12: 999997.7 | K12: 999997.7 | L12: =K12/$K$14 -> 0.057270564 | M12: =K12/I12 -> 1 | N12: 7921721 | O12: 7590763 | P12: 8554337 | Q12: 7118996 | R12: =N12/O12-1 -> 0.043600097 | S12: =F12/N12 -> 15.930882 | T12: 0 | U12: -1 | V12: Revenue is flat, opportunity to reinvigorate growth via AI automation? 8 month runway left | W12: <1 year | X12: Hone has rolled out an AI Coach feature to reinforce skills “in the flow of work” alongside live classes.
I14: =SUM(I4:I12) -> 16199903 | K14: =SUM(K4:K12) -> 17460937
T17: 7
T18: 6

Sheet Sheet3
A1: Current Investment Characteristics
A2: Company | B2: Series | C2: $ Invested | D2: FD%
A3: Charthop | B3: C | C3: 499999.98 | D3: 0.0012472782
A4: Carrot | B4: D | C4: 2200002.1 | D4: 0.0048507273
A5: Ladder | B5: D | C5: 1999984.6 | D5: 0.0024242189
A6: Fountain | B6: D | C6: 2999981.3 | D6: 0.0045216718
A7: Spring | B7: E | C7: 2999992.2 | D7: 0.0013440277
A8: Karat | B8: C | C8: 1499987.1 | D8: 0.0013500458
A9: Rightway | B9: D | C9: 1499959.4 | D9: 0.0015768049
A10: Level | B10: B | C10: 499995.2 | D10: 0.00055555022
A11: Rula | B11: C | C11: 1499998.4 | D11: 0.0023371701
A12: Hone | B12: B | C12: 999997.7 | D12: 0.0079223739

Sheet Fund III Inv Char
B2: Fund III Current Investment Characteristics
B3: Company | C3: Series | D3: FD% | E3: Initital Cost | F3: Last Valuation | G3: Holding Value | H3: $ Invested | I3: Market Value | J3: Multiple
B4: Stepful | C4: B | D4: 0.0528 | E4: 91800000 | F4: 261500000 | G4: 261500000 | H4: 7878030.5 | I4: 13609280 | J4: 1.7274977
B5: OneImaging | C5: A | D5: 0.055555556 | E5: 18000000 | F5: 250000000 | G5: 250000000 | H5: 1000000 | I5: 11640892 | J5: 11.640892
B6: Thatch | C6: B | D6: 0.034148619 | E6: 135000000 | F6: 450000000 | G6: 450000000 | H6: 4040625.2 | I6: 10304094 | J6: 2.5501238
B7: Salsa | C7: A | D7: 0.0847 | E7: 44000000 | F7: 70000000 | G7: 70000000 | H7: 5499997.9 | I7: 5912934 | J7: 1.0750793
B8: Techwolf | C8: B | D8: 0.035726078 | E8: 141000000 | F8: 141000000 | G8: 141000000 | H8: 5037377 | I8: 5037377 | J8: 1
B9: Onboarded | C9: A | D9: 0.086956522 | E9: 57500000 | F9: 57500000 | G9: 57500000 | H9: 5000000 | I9: 5000000 | J9: 1
B10: Laguna Health | C10: A | D10: 0.07547 | E10: 53000000 | F10: 53000000 | G10: 53000000 | H10: 4999999.7 | I10: 4999999.7 | J10: 1
B11: PenguinAI | C11: A | D11: 0.024242424 | E11: 165000000 | F11: 165000000 | G11: 165000000 | H11: 4000000 | I11: 4000000 | J11: 1
B12: Sully.AI | C12: A | D12: 0.053333327 | E12: 75000000 | F12: 75000000 | G12: 75000000 | H12: 3999999.5 | I12: 3999999.5 | J12: 1
B13: Summer | C13: A | D13: 0.11 | E13: 35000000 | F13: 40166216 | G13: 40166216 | H13: 3250000 | I13: 3250000 | J13: 1
B14: Athena.AI | C14: Seed | D14: 0.09 | E14: 35000000 | F14: 35000000 | G14: 35000000 | H14: 3150000 | I14: 3150000 | J14: 1
B15: Hireguide | C15: Seed | D15: 0.09375 | E15: 32000000 | F15: 32000000 | G15: 32000000 | H15: 3000000 | I15: 3000000 | J15: 1
... B24: Sunny Health | C24: Seed - SVA | D24: 0.003125 | E24: 16000000 | F24: 16000000 | G24: 16000000 | H24: 50000 | I24: 50000 | J24: 1

Sheet GOF II Inv Char
B2: GOF II Current Investment Characteristics
B3: Company | C3: Series | D3: FD% | E3: Initital Cost | F3: Last Valuation | G3: Holding Value | H3: $ Invested | I3: Market Value | J3: Multiple | L3: =I4*2.3 -> 16197612
B4: Midi | C4: C | D4: 0.01397 | E4: 310000000 | F4: 500000000 | G4: 500000000 | H4: 5999997.9 | I4: 7042439.9 | J4: 1.1737404 | K4: 1150000000 | L4: =K4*D4 -> 16065500 | M4: =L4/H4 -> 2.6775843 | N4: =L4-I4 -> 9023060.1 | O4: =N4/35000000 -> 0.25780172 | P4: =L4/H4 -> 2.6775843
B5: Empathy | C5: C | D5: 0.006 | E5: 500000000 | F5: 500000000 | G5: 500000000 | H5: 3000000 | I5: 3000000 | J5: 1 | K5: =K4/G4 -> 2.3 | L5: =I5 -> 3000000
B6: CertifyOS | C6: B | D6: 0.011111111 | E6: 270000000 | F6: 270000000 | G6: 270000000 | H6: 3000000 | I6: 3000000 | J6: 1 | K6: =K5*H4 -> 13799995 | L6: =I6 -> 3000000
B7: Rightway | C7: D | D7: 0.0051723813 | E7: 580000000 | F7: 625000000 | G7: 625000000 | H7: 2999981.2 | I7: 2999981.2 | J7: 1 | K7: =K4/F4 -> 2.3 | L7: =I7 -> 2999981.2
B8: Nayya | C8: C | D8: 0.0075757333 | E8: 330000000 | F8: 330000000 | G8: 330000000 | H8: 2499992 | I8: 2499992 | J8: 1 | L8: =I8 -> 2499992
B9: XP Health | C9: B | D9: 0.0083 | E9: 1.2048189e+08 | F9: 1.2048189e+08 | G9: 1.2048189e+08 | H9: 999999.66 | I9: 999999.66 | J9: 1 | L9: =I9 -> 999999.66
H10: =SUM(H4:H9) -> 18499971 | I10: =SUM(I4:I9) -> 19542413 | J10: =I10/H10 -> 1.0563483 | L10: =SUM(L4:L9) -> 28565473 | M10: =L10/H10 -> 1.5440821
O11: =0.94+O4 -> 1.1978017

Sheet Sheet5
B2: Goal | C2: Status | D2: Commentary
A3: 1 | B3: Early DPI by EOY '24 | C3: 0.1x | D3: Achieved 0.12x DPI in 2024 through Rula distribution
A4: 2 | B4: 0.5x DPI by EOY '25 | C4: 0.5x | D4: Distributed an additional $8M in Q1'25, achieving 0.5x DPI
A5: 3 | B5: 1.0x DPI by Q2'26 | C5: 0.5x | D5: Active secondary conversations, line of sight to 1.0x DPI
F9: Fund | G9: Vintage | H9: Status | I9: Strategy
F10: Core Fund I | G10: 2018 | H10: Harvest | I10: Actively looking for secondary opportunities to facilitate DPI
F11: Core Fund II | G11: 2020 | H11: Recycle | I11: Early liquidity an opportunity to recycle into additional opportunities
F12: Core Fund III | G12: 2023 | H12: Deploy | I12: Currently deploying; any liquidity viewed as recycle opportunity
F13: GOF I | G13: 2021 | H13: Harvest | I13: Expect companies to compound before eyeing liquidity
F14: GOF II | G14: 2024 | H14: Deploy | I14: Currently deploying; any liquidity viewed as recycle opportunity
C35: 45682 | D35: 45713 | E35: 45741 | F35: 45772 | G35: 45802 | H35: 45833 | I35: 45863 | J35: 45894 | K35: 45925
B36: Net Revenue | C36: 3.5 | D36: 3.5 | E36: 3.8 | F36: 4.2 | G36: 4.8 | H36: 4.6 | I36: 4.3 | J36: 4.7 | K36: 3.5
B37: Total Costs | C37: 3.9 | D37: 4.3 | E37: 4.4 | F37: 4.5 | G37: 5 | H37: 4.3 | I37: 5.3 | J37: 5.4 | K37: 5.7
B38: Net Income | C38: -0.4 | D38: -0.8 | E38: -0.6 | F38: -0.3 | G38: -0.1 | H38: 0.2 | I38: -1.1 | J38: -0.7 | K38: -2.2 | L38: =AVERAGE(C38:K38) -> -0.66666667
L39: =L38*12 -> -8
L40: =35/8 -> 4.375

Sheet exit outlook
C1: Fund I | D1: 20700000
C2: Fund II | D2: 74000000
B4: Company | C4: Fund | D4: Holding Value | E4: Traction (1) | F4: Fund Position FMV | G4: DPI at Current FMV | H4: Outlook
B5: Spring | C5: Fund I | D5: ='Fund I Inv Char'!G4 -> 3300000000 | E5: 500000000 | F5: ='Fund I Inv Char'!J4 -> 28841289 | G5: =F5/D1 -> 1.393299 | H5: Strong IPO candidate
B6: Rightway | C6: Fund I | D6: ='Fund I Inv Char'!G5 -> 625000000 | E6: 80000000 | F6: ='Fund I Inv Char'!J5 -> 13426663 | G6: =F6/D1 -> 0.64863107 | H6: Potential to sell warrants (50% of position) into a new round 1H'26
B7: Rula | C7: Fund I | D7: ='Fund I Inv Char'!G7 -> 1250000000 | E7: 225000000 | F7: ='Fund I Inv Char'!J7 -> 6277910.6 | G7: =F7/D1 -> 0.30328071 | H7: Active secondary market, interest at a premium to last round
B8: Human Interest | C8: Fund I | D8: ='Fund I Inv Char'!G9 -> 1250000000 | E8: 145000000 | F8: ='Fund I Inv Char'!J9 -> 5589792.5 | G8: =F8/D1 -> 0.27003828
B9: Carrot | C9: Fund I | D9: ='Fund I Inv Char'!G8 -> 600000000 | E9: 100000000 | F9: ='Fund I Inv Char'!J8 -> 5663568.2 | G9: =F9/D1 -> 0.27360233
B10: Rula | C10: Fund II | D10: ='Fund II Inv Char'!G4 -> 1250000000 | E10: 225000000 | F10: ='Fund II Inv Char'!J4 -> 25285301 | G10: =F10/D2 -> 0.34169326 | H10: Active secondary market, interest at a premium to last round
B11: Midi | C11: Fund II | D11: ='Fund II Inv Char'!G5 -> 500000000 | E11: 125000000 | F11: ='Fund II Inv Char'!J5 -> 24143029 | G11: =F11/D2 -> 0.32625715 | H11: Expect new round at mark-up in 2H'25 / 1H'26
B12: Remote | C12: Fund II | D12: ='Fund II Inv Char'!G6 -> 3000000000 | E12: 355000000 | F12: ='Fund II Inv Char'!J6 -> 10354762 | G12: =F12/D2 -> 0.13992921 | H12: Potential secondary candidate as they raise again

Sheet GOF II RYG
B2: GOF II Portfolio Health
B3: Company | C3: Initial Inv. Date | D3: Initial Inv. Series | E3: Current Inv. Series | F3: SV Holding Value | G3: Invested Cost | H3: FMV | I3: Portfolio Value | J3: MOIC | K3: 2025E Rev | L3: 2024A Rev | M3: 2025E ARR | N3: 2024 ARR | O3: Rev/ARR Growth YoY | P3: Rev Multiple | Q3: Prev. Status | R3: Current Q3 Status | S3: Rationale
B4: Midi | C4: 45358 | D4: B | E4: D | F4: ='Fund II RYG'!G4 -> 1150000000 | G4: 5999998 | H4: 14050000 | I4: =H4/$H$11 -> 0.5268065 | J4: =H4/G4 -> 2.3416674 | K4: =190000000 -> 190000000 | L4: 37586650 | M4: 129267358 | N4: 58853221 | O4: =K4/L4-1 -> 4.0549863 | P4: =F4/K4 -> 6.0526316 | Q4: 1 | R4: 1 | S4: Beating and raising, will scale north of $100M revenue growing ~3x y/y
B5: Empathy | C5: 45767 | D5: C | E5: C | F5: 500000000 | G5: 3000000 | H5: 3000000 | I5: =H5/$H$11 -> 0.11248537 | J5: =H5/G5 -> 1 | K5: =7410000+12028000 -> 19438000 | M5: 40000000 | P5: =F5/K5 -> 25.722811 | Q5: 1 | R5: 1 | S5: Recent investment
B6: CertifyOS | C6: 45800 | D6: B | E6: B | F6: 270000000 | G6: 3000000 | H6: 3000000 | I6: =H6/$H$11 -> 0.11248537 | J6: =H6/G6 -> 1 | K6: 16000000 | M6: 17000000 | P6: =F6/K6 -> 16.875 | Q6: 1 | R6: 1 | S6: Recent investment
B7: Rightway | C7: 45376 | D7: D | E7: D | F7: ='Fund I RYG'!G5 -> 625000000 | G7: 2999981 | H7: 2999981 | I7: =H7/$H$11 -> 0.11248466 | J7: =H7/G7 -> 1 | K7: 45000000 | L7: 25972982 | M7: 83000000 | N7: 49300395 | O7: =K7/L7-1 -> 0.73256964 | P7: =F7/K7 -> 13.888889 | Q7: 1 | R7: 1 | S7: Transparent PBM solution driving 2x y/y growth
B8: Nayya | C8: 45666 | D8: C | E8: C | F8: ='Fund II RYG'!G14 -> 4.8781374e+08 | G8: 2499992 | H8: 2620153 | I8: =H8/$H$11 -> 0.098242963 | J8: =H8/G8 -> 1.0480646 | K8: =19723132+8128680 -> 27851812 | L8: 16056400 | M8: 35344400 | N8: 28364777 | O8: =K8/L8-1 -> 0.7346237 | P8: =F8/K8 -> 17.514614 | Q8: 1 | R8: 0 | S8: Over 2x y/y growth, expecting to raise in 2H'25 with partnerships ramping well
B9: XP Health | C9: 45450 | D9: B | E9: B | F9: ='Fund I RYG'!G12 -> 120000000 | G9: 1000000 | H9: 1000000 | I9: =H9/$H$11 -> 0.037495125 | J9: =H9/G9 -> 1 | K9: =5958042*2 -> 11916084 | L9: 9100316 | M9: 12400000 | N9: 11207000 | O9: =K9/L9-1 -> 0.30941431 | P9: =F9/K9 -> 10.070422 | Q9: 1 | R9: 0 | S9: On track to double this year, closing a strategic round with employer momentum
H11: =SUM(H4:H9) -> 26670134
