Workbook

Sheet Fund Dashboard
B2: SemperVirens Fund II Summary
C3: ="As of "&TEXT('Statement of Investments'!$C$1,"mm/dd/yyyy") -> As of 12/31/2025 | F3: ="As of "&TEXT('Statement of Investments'!$C$1,"mm/dd/yyyy") -> As of 12/31/2025
B5: Fund Capital: | E5: Quarterly Invested Capital:
B6: Committed Capital | C6: 20730000 | E6: New Investments | F6: =SUMIF('Investment Rollover'!$C$4:$C$31,"=0",'Investment Rollover'!$D$4:$D$31) -> 5749995
B7: Capital Called | C7: =-SUM(#REF!) -> #REF! | E7: Follow-Ons | F7: =SUMIF('Investment Rollover'!$C$4:$C$31,">0",'Investment Rollover'!$D$4:$D$31) -> 5680282.5
B8: Percent Called | C8: =C7/C6 -> #REF! | E8: Total New Investments | F8: =SUM(F6:F7) -> 11430277
B10: Investment Summary: | E10: Pro-Forma Net Peformance:
B11: Invested Capital | C11: ='Investment Performance Summary'!E41 -> 70623804 | E11: Contributions | F11: =-#REF! -> #REF!
B12: Total Value | C12: ='Investment Performance Summary'!H41 -> 92399729 | E12: Distributions | F12: =#REF! -> #REF!
B13: MOIC | C13: =C12/C11 -> 1.3083369 | E13: NAV | F13: =#REF! -> #REF!
B14: Gross IRR | C14: ='Investment Performance Summary'!J41 -> 0.23573356 | E14: TVPI | F14: =(F13+F12)/F11 -> #REF!
E15: DPI | F15: =F12/F11 -> #REF!
E16: Net IRR | F16: =#REF! -> #REF!

Sheet Investment Performance Summary
B2: SemperVirens Fund III Investment Summary | K2: Markup
B4: ="As of "&TEXT('Statement of Investments'!$C$1,"mm/dd/yyyy") -> As of 12/31/2025 | C4: Initial Inv. | D4: Initial Exit | E4: Dollars | F4: Unrealized | G4: Realized | H4: Total | I4: Gross | J4: Gross
B5: Company | C5: Date | D5: Date | E5: Invested | F5: Value | G5: Value | H5: Value | I5: Multiple | J5: IRR
B7: Unrealized Portfolio
B9: Laguna Health | C9: =INDEX('Statement of Investments'!$C$5:$C$205,MATCH('Investment Performance Summary'!$B9,'Statement of Investments'!$B$5:$B$205,0)) -> 45021 | D9: - | E9: =INDEX('Statement of Investments'!$L$5:$L$205,MATCH($B9,'Statement of Investments'!$E$5:$E$205,0)) -> 4999999.7 | F9: =INDEX('Statement of Investments'!$O$5:$O$205,MATCH($B9,'Statement of Investments'!$E$5:$E$205,0)) -> 4999999.7 | G9: 0 | H9: =F9+G9 -> 4999999.7 | I9: =H9/E9 -> 1 | J9: =INDEX('Statement of Investments'!$R$5:$R$205,MATCH($B9,'Statement of Investments'!$E$5:$E$205,0)) -> 2.9802322e-09 | K9: N
B10: Stepful | C10: =INDEX('Statement of Investments'!$C$5:$C$205,MATCH('Investment Performance Summary'!$B10,'Statement of Investments'!$B$5:$B$205,0)) -> 45183 | D10: - | E10: =INDEX('Statement of Investments'!$L$5:$L$205,MATCH($B10,'Statement of Investments'!$E$5:$E$205,0)) -> 7878030.5 | F10: =INDEX('Statement of Investments'!$O$5:$O$205,MATCH($B10,'Statement of Investments'!$E$5:$E$205,0)) -> 13609280 | G10: 0 | H10: =F10+G10 -> 13609280 | I10: =H10/E10 -> 1.7274977 | J10: =INDEX('Statement of Investments'!$R$5:$R$205,MATCH($B10,'Statement of Investments'!$E$5:$E$205,0)) -> 0.38251794 | K10: Y
B11: Summer | C11: =INDEX('Statement of Investments'!$C$5:$C$205,MATCH('Investment Performance Summary'!$B11,'Statement of Investments'!$B$5:$B$205,0)) -> 45209 | D11: - | E11: =INDEX('Statement of Investments'!$L$5:$L$205,MATCH($B11,'Statement of Investments'!$E$5:$E$205,0)) -> 3250000 | F11: =INDEX('Statement of Investments'!$O$5:$O$205,MATCH($B11,'Statement of Investments'!$E$5:$E$205,0)) -> 3250000 | G11: 0 | H11: =F11+G11 -> 3250000 | I11: =H11/E11 -> 1 | J11: =INDEX('Statement of Investments'!$R$5:$R$205,MATCH($B11,'Statement of Investments'!$E$5:$E$205,0)) -> 4.8828125e-09 | K11: N
B12: Wagmo | C12: =INDEX('Statement of Investments'!$C$5:$C$205,MATCH('Investment Performance Summary'!$B12,'Statement of Investments'!$B$5:$B$205,0)) -> 45209 | D12: - | E12: =INDEX('Statement of Investments'!$L$5:$L$205,MATCH($B12,'Statement of Investments'!$E$5:$E$205,0)) -> 1499998 | F12: =INDEX('Statement of Investments'!$O$5:$O$205,MATCH($B12,'Statement of Investments'!$E$5:$E$205,0)) -> 1499998 | G12: 0 | H12: =F12+G12 -> 1499998 | I12: =H12/E12 -> 1 | J12: =INDEX('Statement of Investments'!$R$5:$R$205,MATCH($B12,'Statement of Investments'!$E$5:$E$205,0)) -> 4.8828125e-09 | K12: N
B13: Kubera | C13: =INDEX('Statement of Investments'!$C$5:$C$205,MATCH('Investment Performance Summary'!$B13,'Statement of Investments'!$B$5:$B$205,0)) -> 45274 | D13: - | E13: =INDEX('Statement of Investments'!$L$5:$L$205,MATCH($B13,'Statement of Investments'!$E$5:$E$205,0)) -> 528082.67 | F13: =INDEX('Statement of Investments'!$O$5:$O$205,MATCH($B13,'Statement of Investments'!$E$5:$E$205,0)) -> 1011413.2 | G13: 0 | H13: =F13+G13 -> 1011413.2 | I13: =H13/E13 -> 1.9152554 | J13: =INDEX('Statement of Investments'!$R$5:$R$205,MATCH($B13,'Statement of Investments'!$E$5:$E$205,0)) -> 0.46074747 | K13: N
B14: Solara | C14: =INDEX('Statement of Investments'!$C$5:$C$205,MATCH('Investment Performance Summary'!$B14,'Statement of Investments'!$B$5:$B$205,0)) -> 45329 | D14: - | E14: =INDEX('Statement of Investments'!$L$5:$L$205,MATCH($B14,'Statement of Investments'!$E$5:$E$205,0)) -> 4552198.8 | F14: =INDEX('Statement of Investments'!$O$5:$O$205,MATCH($B14,'Statement of Investments'!$E$5:$E$205,0)) -> 5296211.2 | G14: 0 | H14: =F14+G14 -> 5296211.2 | I14: =H14/E14 -> 1.1634402 | J14: =INDEX('Statement of Investments'!$R$5:$R$205,MATCH($B14,'Statement of Investments'!$E$5:$E$205,0)) -> 0.17761299 | K14: N
B15: Salsa | C15: =INDEX('Statement of Investments'!$C$5:$C$205,MATCH('Investment Performance Summary'!$B15,'Statement of Investments'!$B$5:$B$205,0)) -> 45329 | D15: - | E15: =INDEX('Statement of Investments'!$L$5:$L$205,MATCH($B15,'Statement of Investments'!$E$5:$E$205,0)) -> 5499997.9 | F15: =INDEX('Statement of Investments'!$O$5:$O$205,MATCH($B15,'Statement of Investments'!$E$5:$E$205,0)) -> 5912934 | G15: 0 | H15: =F15+G15 -> 5912934 | I15: =H15/E15 -> 1.0750793 | J15: =INDEX('Statement of Investments'!$R$5:$R$205,MATCH($B15,'Statement of Investments'!$E$5:$E$205,0)) -> 0.058040698 | K15: Y
B16: Hireguide | C16: =INDEX('Statement of Investments'!$C$5:$C$205,MATCH('Investment Performance Summary'!$B16,'Statement of Investments'!$B$5:$B$205,0)) -> 45351 | D16: - | E16: =INDEX('Statement of Investments'!$L$5:$L$205,MATCH($B16,'Statement of Investments'!$E$5:$E$205,0)) -> 3000000 | F16: =INDEX('Statement of Investments'!$O$5:$O$205,MATCH($B16,'Statement of Investments'!$E$5:$E$205,0)) -> 500000 | G16: 0 | H16: =F16+G16 -> 500000 | I16: =H16/E16 -> 0.16666667 | J16: =INDEX('Statement of Investments'!$R$5:$R$205,MATCH($B16,'Statement of Investments'!$E$5:$E$205,0)) -> -0.62267676 | K16: N
B17: Take2 AI | C17: =INDEX('Statement of Investments'!$C$5:$C$205,MATCH('Investment Performance Summary'!$B17,'Statement of Investments'!$B$5:$B$205,0)) -> 45376 | D17: - | E17: =INDEX('Statement of Investments'!$L$5:$L$205,MATCH($B17,'Statement of Investments'!$E$5:$E$205,0)) -> 700000 | F17: =INDEX('Statement of Investments'!$O$5:$O$205,MATCH($B17,'Statement of Investments'!$E$5:$E$205,0)) -> 700000 | G17: 0 | H17: =F17+G17 -> 700000 | I17: =H17/E17 -> 1 | J17: =INDEX('Statement of Investments'!$R$5:$R$205,MATCH($B17,'Statement of Investments'!$E$5:$E$205,0)) -> 4.8828125e-09 | K17: N
B18: Techwolf | C18: =INDEX('Statement of Investments'!$C$5:$C$205,MATCH('Investment Performance Summary'!$B18,'Statement of Investments'!$B$5:$B$205,0)) -> 45467 | D18: - | E18: =INDEX('Statement of Investments'!$L$5:$L$205,MATCH($B18,'Statement of Investments'!$E$5:$E$205,0)) -> 5037377 | F18: =INDEX('Statement of Investments'!$O$5:$O$205,MATCH($B18,'Statement of Investments'!$E$5:$E$205,0)) -> 5037377 | G18: 0 | H18: =F18+G18 -> 5037377 | I18: =H18/E18 -> 1 | J18: =INDEX('Statement of Investments'!$R$5:$R$205,MATCH($B18,'Statement of Investments'!$E$5:$E$205,0)) -> 4.8828125e-09 | K18: N
B19: Thatch | C19: =INDEX('Statement of Investments'!$C$5:$C$205,MATCH('Investment Performance Summary'!$B19,'Statement of Investments'!$B$5:$B$205,0)) -> 45513 | D19: - | E19: =INDEX('Statement of Investments'!$L$5:$L$205,MATCH($B19,'Statement of Investments'!$E$5:$E$205,0)) -> 4040625.2 | F19: =INDEX('Statement of Investments'!$O$5:$O$205,MATCH($B19,'Statement of Investments'!$E$5:$E$205,0)) -> 10304094 | G19: 0 | H19: =F19+G19 -> 10304094 | I19: =H19/E19 -> 2.5501238 | J19: =INDEX('Statement of Investments'!$R$5:$R$205,MATCH($B19,'Statement of Investments'!$E$5:$E$205,0)) -> 1.4000929 | K19: Y
B20: Multimodal | C20: =INDEX('Statement of Investments'!$C$5:$C$205,MATCH('Investment Performance Summary'!$B20,'Statement of Investments'!$B$5:$B$205,0)) -> 45614 | D20: - | E20: =INDEX('Statement of Investments'!$L$5:$L$205,MATCH($B20,'Statement of Investments'!$E$5:$E$205,0)) -> 2000000 | F20: =INDEX('Statement of Investments'!$O$5:$O$205,MATCH($B20,'Statement of Investments'!$E$5:$E$205,0)) -> 2000000 | G20: 0 | H20: =F20+G20 -> 2000000 | I20: =H20/E20 -> 1 | J20: =INDEX('Statement of Investments'!$R$5:$R$205,MATCH($B20,'Statement of Investments'!$E$5:$E$205,0)) -> 4.8828125e-09 | K20: N
... B23: Sully.AI | C23: =INDEX('Statement of Investments'!$C$5:$C$205,MATCH('Investment Performance Summary'!$B23,'Statement of Investments'!$B$5:$B$205,0)) -> 45666 | D23: - | E23: =INDEX('Statement of Investments'!$L$5:$L$205,MATCH($B23,'Statement of Investments'!$E$5:$E$205,0)) -> 3999999.5 | F23: =INDEX('Statement of Investments'!$O$5:$O$205,MATCH($B23,'Statement of Investments'!$E$5:$E$205,0)) -> 3999999.5 | G23: 0 | H23: =F23+G23 -> 3999999.5 | I23: =H23/E23 -> 1 | J23: =INDEX('Statement of Investments'!$R$5:$R$205,MATCH($B23,'Statement of Investments'!$E$5:$E$205,0)) -> -4.8828125e-09 | K23: N
B24: Athena.AI | C24: =INDEX('Statement of Investments'!$C$5:$C$205,MATCH('Investment Performance Summary'!$B24,'Statement of Investments'!$B$5:$B$205,0)) -> 45778 | D24: - | E24: =INDEX('Statement of Investments'!$L$5:$L$205,MATCH($B24,'Statement of Investments'!$E$5:$E$205,0)) -> 3150000 | F24: =INDEX('Statement of Investments'!$O$5:$O$205,MATCH($B24,'Statement of Investments'!$E$5:$E$205,0)) -> 3150000 | G24: 0 | H24: =F24+G24 -> 3150000 | I24: =H24/E24 -> 1 | J24: =INDEX('Statement of Investments'!$R$5:$R$205,MATCH($B24,'Statement of Investments'!$E$5:$E$205,0)) -> 4.8828125e-09
B25: Onboarded | C25: =INDEX('Statement of Investments'!$C$5:$C$205,MATCH('Investment Performance Summary'!$B25,'Statement of Investments'!$B$5:$B$205,0)) -> 45824 | D25: - | E25: =INDEX('Statement of Investments'!$L$5:$L$205,MATCH($B25,'Statement of Investments'!$E$5:$E$205,0)) -> 5000000 | F25: =INDEX('Statement of Investments'!$O$5:$O$205,MATCH($B25,'Statement of Investments'!$E$5:$E$205,0)) -> 5000000 | G25: 0 | H25: =F25+G25 -> 5000000 | I25: =H25/E25 -> 1 | J25: =INDEX('Statement of Investments'!$R$5:$R$205,MATCH($B25,'Statement of Investments'!$E$5:$E$205,0)) -> 4.8828125e-09
B26: PenguinAI | C26: =INDEX('Statement of Investments'!$C$5:$C$205,MATCH('Investment Performance Summary'!$B26,'Statement of Investments'!$B$5:$B$205,0)) -> 45821 | D26: - | E26: =INDEX('Statement of Investments'!$L$5:$L$205,MATCH($B26,'Statement of Investments'!$E$5:$E$205,0)) -> 4000000 | F26: =INDEX('Statement of Investments'!$O$5:$O$205,MATCH($B26,'Statement of Investments'!$E$5:$E$205,0)) -> 4000000 | G26: 0 | H26: =F26+G26 -> 4000000 | I26: =H26/E26 -> 1 | J26: =INDEX('Statement of Investments'!$R$5:$R$205,MATCH($B26,'Statement of Investments'!$E$5:$E$205,0)) -> 4.8828125e-09
B27: Clasp | C27: =INDEX('Statement of Investments'!$C$5:$C$205,MATCH('Investment Performance Summary'!$B27,'Statement of Investments'!$B$5:$B$205,0)) -> 45807 | D27: - | E27: =INDEX('Statement of Investments'!$L$5:$L$205,MATCH($B27,'Statement of Investments'!$E$5:$E$205,0)) -> 250000 | F27: =INDEX('Statement of Investments'!$O$5:$O$205,MATCH($B27,'Statement of Investments'!$E$5:$E$205,0)) -> 250000 | G27: 0 | H27: =F27+G27 -> 250000 | I27: =H27/E27 -> 1 | J27: =INDEX('Statement of Investments'!$R$5:$R$205,MATCH($B27,'Statement of Investments'!$E$5:$E$205,0)) -> 4.8828125e-09
B28: Sunny Health | C28: =INDEX('Statement of Investments'!$C$5:$C$205,MATCH('Investment Performance Summary'!$B28,'Statement of Investments'!$B$5:$B$205,0)) -> 45806 | D28: - | E28: =INDEX('Statement of Investments'!$L$5:$L$205,MATCH($B28,'Statement of Investments'!$E$5:$E$205,0)) -> 50000 | F28: =INDEX('Statement of Investments'!$O$5:$O$205,MATCH($B28,'Statement of Investments'!$E$5:$E$205,0)) -> 50000 | G28: 0 | H28: =F28+G28 -> 50000 | I28: =H28/E28 -> 1 | J28: =INDEX('Statement of Investments'!$R$5:$R$205,MATCH($B28,'Statement of Investments'!$E$5:$E$205,0)) -> 4.8828125e-09
B29: Outro Health | C29: =INDEX('Statement of Investments'!$C$5:$C$205,MATCH('Investment Performance Summary'!$B29,'Statement of Investments'!$B$5:$B$205,0)) -> 45806 | D29: - | E29: =INDEX('Statement of Investments'!$L$5:$L$205,MATCH($B29,'Statement of Investments'!$E$5:$E$205,0)) -> 250000 | F29: =INDEX('Statement of Investments'!$O$5:$O$205,MATCH($B29,'Statement of Investments'!$E$5:$E$205,0)) -> 250000 | G29: 0 | H29: =F29+G29 -> 250000 | I29: =H29/E29 -> 1 | J29: =INDEX('Statement of Investments'!$R$5:$R$205,MATCH($B29,'Statement of Investments'!$E$5:$E$205,0)) -> 4.8828125e-09
B30: Tezi | C30: =INDEX('Statement of Investments'!$C$5:$C$205,MATCH('Investment Performance Summary'!$B30,'Statement of Investments'!$B$5:$B$205,0)) -> 45869 | D30: - | E30: =INDEX('Statement of Investments'!$L$5:$L$205,MATCH($B30,'Statement of Investments'!$E$5:$E$205,0)) -> 1999997 | F30: =INDEX('Statement of Investments'!$O$5:$O$205,MATCH($B30,'Statement of Investments'!$E$5:$E$205,0)) -> 1999997 | G30: 0 | H30: =F30+G30 -> 1999997 | I30: =H30/E30 -> 1 | J30: =INDEX('Statement of Investments'!$R$5:$R$205,MATCH($B30,'Statement of Investments'!$E$5:$E$205,0)) -> 4.8828125e-09
B31: Trial Library | C31: =INDEX('Statement of Investments'!$C$5:$C$205,MATCH('Investment Performance Summary'!$B31,'Statement of Investments'!$B$5:$B$205,0)) -> 45877 | D31: - | E31: =INDEX('Statement of Investments'!$L$5:$L$205,MATCH($B31,'Statement of Investments'!$E$5:$E$205,0)) -> 2999998 | F31: =INDEX('Statement of Investments'!$O$5:$O$205,MATCH($B31,'Statement of Investments'!$E$5:$E$205,0)) -> 2999998 | G31: 0 | H31: =F31+G31 -> 2999998 | I31: =H31/E31 -> 1 | J31: =INDEX('Statement of Investments'!$R$5:$R$205,MATCH($B31,'Statement of Investments'!$E$5:$E$205,0)) -> 4.8828125e-09
B32: TrueClaim | C32: =INDEX('Statement of Investments'!$C$5:$C$205,MATCH('Investment Performance Summary'!$B32,'Statement of Investments'!$B$5:$B$205,0)) -> 45924 | E32: =INDEX('Statement of Investments'!$L$5:$L$205,MATCH($B32,'Statement of Investments'!$E$5:$E$205,0)) -> 250000 | F32: =INDEX('Statement of Investments'!$O$5:$O$205,MATCH($B32,'Statement of Investments'!$E$5:$E$205,0)) -> 250000 | G32: 0 | H32: =F32+G32 -> 250000 | I32: =H32/E32 -> 1 | J32: =INDEX('Statement of Investments'!$R$5:$R$205,MATCH($B32,'Statement of Investments'!$E$5:$E$205,0)) -> 4.8828125e-09
B33: Andel | C33: =INDEX('Statement of Investments'!$C$5:$C$205,MATCH('Investment Performance Summary'!$B33,'Statement of Investments'!$B$5:$B$205,0)) -> 45924 | E33: =INDEX('Statement of Investments'!$L$5:$L$205,MATCH($B33,'Statement of Investments'!$E$5:$E$205,0)) -> 250000 | F33: =INDEX('Statement of Investments'!$O$5:$O$205,MATCH($B33,'Statement of Investments'!$E$5:$E$205,0)) -> 250000 | G33: 0 | H33: =F33+G33 -> 250000 | I33: =H33/E33 -> 1 | J33: =INDEX('Statement of Investments'!$R$5:$R$205,MATCH($B33,'Statement of Investments'!$E$5:$E$205,0)) -> 4.8828125e-09
B34: Second Door | C34: =INDEX('Statement of Investments'!$C$5:$C$205,MATCH('Investment Performance Summary'!$B34,'Statement of Investments'!$B$5:$B$205,0)) -> 45924 | E34: =INDEX('Statement of Investments'!$L$5:$L$205,MATCH($B34,'Statement of Investments'!$E$5:$E$205,0)) -> 250000 | F34: =INDEX('Statement of Investments'!$O$5:$O$205,MATCH($B34,'Statement of Investments'!$E$5:$E$205,0)) -> 250000 | G34: 0 | H34: =F34+G34 -> 250000 | I34: =H34/E34 -> 1 | J34: =INDEX('Statement of Investments'!$R$5:$R$205,MATCH($B34,'Statement of Investments'!$E$5:$E$205,0)) -> 4.8828125e-09
B39: Total Unrealized Portfolio | E39: =SUM(E9:E38) -> 70623804 | F39: =SUM(F9:F38) -> 92399729 | G39: =SUM(G9:G38) -> 0 | H39: =SUM(H9:H38) -> 92399729 | I39: =H39/E39 -> 1.3083369 | J39: ='Statement of Investments'!R203 -> 0.23849095
B41: Total Portfolio | E41: =E39 -> 70623804 | F41: =F39 -> 92399729 | G41: =G39 -> 0 | H41: =H39 -> 92399729 | I41: =H41/E41 -> 1.3083369 | J41: ='Statement of Investments'!R205 -> 0.23573356
B44: =3/50 -> 0.06

Sheet Supporting Worksheets -->

Sheet Sheet2
B3: Exit Value | C3: Proceeds | D3: Deal MOIC | E3: Fund MOIC | F3: % of Fund Returned
B4: $200 M | C4: $7 M | D4: 3.33 | E4: 0.05 | F4: 0.05 | G4: =D4*1.43% -> 0.047619
B5: $500 M | C5: $17 M | D5: 8.33 | E5: 0.12 | F5: 0.12 | G5: =D5*1.43% -> 0.119119
B6: $1,000 M | C6: $33 M | D6: 16.65 | E6: 0.24 | F6: 0.23
B7: $4,300 M | C7: $143 M | D7: 71.6 | E7: 1.02 | F7: 1
C9: 2000000

Sheet Statement of Investments
A1: 46022 | B1: As of | C1: =IF(TODAY()<$A$1,TODAY(),A1) -> 46022
C2: Investment | D2: Liquidity | K2: Original Cost | N2: Current Value | Q2: Gross
C3: Date | D3: Date | F3: Security | G3: Stock Certificates | I3: Shares | K3: Per Share | L3: Total Dollars | N3: Per Share | O3: Total Dollars | Q3: MOIC | R3: IRR
S4: 43101 | T4: -0.1
A5: REALIZED
B77: Total Realized Portfolio | L77: =SUM(L5:L76) -> 0 | O77: =SUM(O5:O76) -> 0 | Q77: =IFERROR(O77/L77,0) -> 0 | R77: 0
A79: UNREALIZED
S80: 43101 | T80: -0.1
B81: Laguna Health | C81: 45021 | F81: Series A Preferred Stock | I81: 2487562 | K81: =L81/I81 -> 1.608 | L81: 3999999.7 | N81: =K81 -> 1.608 | O81: =I81*N81 -> 3999999.7 | S81: =IFERROR(C81,0) -> 45021 | T81: =-L81 -> -3999999.7
C82: 45723 | F82: SAFE | L82: 1000000 | O82: =+L82 -> 1000000 | S82: =IFERROR(C82,0) -> 45723 | T82: =-L82 -> -1000000
E84: =B81 -> Laguna Health | F84: Total | L84: =SUM(L81:L83) -> 4999999.7 | O84: =SUM(O81:O83) -> 4999999.7 | Q84: =O84/L84 -> 1 | R84: =XIRR(T81:T84,S81:S84,) -> 2.9802322e-09 | S84: =$C$1 -> 46022 | T84: =O84 -> 4999999.7
B86: Stepful | C86: 45183 | F86: Series A Preferred Stock | I86: 578611 | K86: =+L86/I86 -> 6.9131 | L86: 3999995.7 | N86: =K87 -> 16.818285 | O86: =I86*N86 -> 9731244.8 | S86: =IFERROR(C86,0) -> 45183 | T86: =-L86 -> -3999995.7
C87: 45590 | F87: Series B Preferred Stock | I87: 123625 | K87: =L87/I87 -> 16.818285 | L87: 2079160.5 | N87: =N86 -> 16.818285 | O87: =I87*N87 -> 2079160.5 | S87: =IFERROR(C87,0) -> 45590 | T87: =-L87 -> -2079160.5
C88: 45828 | F88: Common Stock | I88: 118816 | K88: =L88/I88 -> 15.14 | L88: 1798874.2 | N88: =K88 -> 15.14 | O88: =I88*N88 -> 1798874.2 | S88: =IFERROR(C88,0) -> 45828 | T88: =-L88 -> -1798874.2
E90: =B86 -> Stepful | F90: Total | I90: =SUM(I86:I89) -> 821052 | L90: =SUM(L86:L88) -> 7878030.5 | O90: =SUM(O86:O89) -> 13609280 | Q90: =O90/L90 -> 1.7274977 | R90: =XIRR(T86:T90,S86:S90,0) -> 0.38251794 | S90: =$C$1 -> 46022 | T90: =O90 -> 13609280
B92: Summer | C92: 45209 | F92: Series A - II Preferred | I92: 2471857 | K92: =L92/I92 -> 1.314801 | L92: =2250000+1000000 -> 3250000 | N92: 0 | O92: =L92 -> 3250000 | S92: =IFERROR(C92,0) -> 45209 | T92: =-L92 -> -3250000
C93: 45756 | F93: Common Stock Warrants | I93: 1235928 | O93: =N93*I93 -> 0 | S93: =IFERROR(C93,0) -> 45756 | T93: =-L93 -> 0
E95: =B92 -> Summer | F95: Total | L95: =SUM(L92:L94) -> 3250000 | O95: =SUM(O92:O94) -> 3250000 | Q95: =O95/L95 -> 1 | R95: =XIRR(T92:T95,S92:S95,0) -> 4.8828125e-09 | S95: =$C$1 -> 46022 | T95: =O95 -> 3250000
B97: Wagmo | C97: 45209 | F97: Series A-1 Preferred Stock | I97: 499599.67 | K97: 3.0024 | L97: 1499998 | N97: 3.0024 | O97: =+L97 -> 1499998 | S97: =IFERROR(C97,0) -> 45209 | T97: =-L97 -> -1499998
F98: Series A-1 Warrants | I98: 99920 | N98: =N97-K97 -> 0 | O98: =+L98 -> 0
E100: =B97 -> Wagmo | F100: Total | L100: =SUM(L97:L99) -> 1499998 | O100: =SUM(O97:O99) -> 1499998 | Q100: =O100/L100 -> 1 | R100: =XIRR(T97:T100,S97:S100,0) -> 4.8828125e-09 | S100: =$C$1 -> 46022 | T100: =O100 -> 1499998
B102: Kubera | C102: 45274 | F102: Series Seed Preferred Stock | I102: 447777 | K102: =+L102/I102 -> 0.89330001 | L102: 399999.2 | N102: =N103 -> 1.9727001 | O102: =+I102*N102 -> 883329.72 | S102: =IFERROR(C102,0) -> 45274 | T102: =-L102 -> -399999.2
C103: 45924 | F103: Series Seed-1 Preferred Stock | I103: 64928 | K103: =+L103/I103 -> 1.9727001 | L103: 128083.47 | N103: =K103 -> 1.9727001 | O103: =+I103*N103 -> 128083.47 | S103: =IFERROR(C103,0) -> 45924 | T103: =-L103 -> -128083.47
E104: =B102 -> Kubera | F104: Total | L104: =SUM(L102:L103) -> 528082.67 | O104: =SUM(O102:O103) -> 1011413.2 | Q104: =O104/L104 -> 1.9152554 | R104: =XIRR(T102:T104,S102:S104,0) -> 0.46074747 | S104: =$C$1 -> 46022 | T104: =O104 -> 1011413.2
B106: Salsa | C106: 45329 | F106: Series A-1 Preferred Stock | I106: =832084+11634 -> 843718 | K106: =L106/I106 -> 2.9630753 | L106: =2.5*10^6 -> 2500000 | N106: =K107 -> 3.4524997 | O106: =I106*N106 -> 2912936.2 | S106: =IFERROR(C106,0) -> 45329 | T106: =-L106 -> -2500000
C107: 45747 | F107: Series A Preferred Stock | I107: =856953+11982 -> 868935 | K107: =L107/I107 -> 3.4524997 | L107: =2958599.41+41398.45 -> 2999997.9 | N107: =K107 -> 3.4524997 | O107: =I107*N107 -> 2999997.9 | S107: =IFERROR(C107,0) -> 45747 | T107: =-L107 -> -2999997.9
E109: =B106 -> Salsa | F109: Total | L109: =SUM(L106:L108) -> 5499997.9 | O109: =SUM(O106:O108) -> 5912934 | Q109: =O109/L109 -> 1.0750793 | R109: =XIRR(T106:T109,S106:S109,0) -> 0.058040698 | S109: =$C$1 -> 46022 | T109: =O109 -> 5912934
B111: Solara | C111: 45329 | F111: Series Seed Preferred Stock | I111: 2041441 | K111: =L111/I111 -> 0.9797 | L111: 1999999.8 | N111: 1.3442 | O111: =+I111*N111 -> 2744105 | S111: =IFERROR(C111,0) -> 45329 | T111: =-L111 -> -1999999.8
C112: 46008 | F112: Series A Preferred Stock | I112: 1898606 | K112: =L112/I112 -> 1.3442489 | L112: =2552199 -> 2552199 | N112: 1.3442 | O112: =N112*I112 -> 2552106.2 | S112: =IFERROR(C112,0) -> 46008 | T112: =-L112 -> -2552199
E114: =B111 -> Solara | F114: Total | L114: =SUM(L111:L113) -> 4552198.8 | O114: =SUM(O111:O113) -> 5296211.2 | Q114: =O114/L114 -> 1.1634402 | R114: =XIRR(T111:T114,S111:S114,0) -> 0.17761299 | S114: =$C$1 -> 46022 | T114: =O114 -> 5296211.2
B116: Hireguide | C116: 45351 | F116: SAFE Note | I116: 0 | K116: 0 | L116: =3*10^6 -> 3000000 | N116: 0 | O116: =500000 -> 500000 | S116: =IFERROR(C116,0) -> 45351 | T116: =-L116 -> -3000000
E118: =B116 -> Hireguide | F118: Total | L118: =SUM(L116:L117) -> 3000000 | O118: =SUM(O116:O117) -> 500000 | Q118: =O118/L118 -> 0.16666667 | R118: =XIRR(T116:T118,S116:S118,0) -> -0.62267676 | S118: =$C$1 -> 46022 | T118: =O118 -> 500000
B120: Take2 AI | C120: 45376 | F120: SAFE Note | I120: 0 | K120: 0 | L120: =700000 -> 700000 | N120: 0 | O120: =L120 -> 700000 | S120: =IFERROR(C120,0) -> 45376 | T120: =-L120 -> -700000
E122: =B120 -> Take2 AI | F122: Total | L122: =SUM(L120:L121) -> 700000 | O122: =SUM(O120:O121) -> 700000 | Q122: =O122/L122 -> 1 | R122: =XIRR(T120:T122,S120:S122,0) -> 4.8828125e-09 | S122: =$C$1 -> 46022 | T122: =O122 -> 700000
B124: Techwolf | C124: 45467 | F124: Series B Preferred Stock | I124: 112815 | L124: 5037377 | O124: =+L124 -> 5037377 | S124: =IFERROR(C124,0) -> 45467 | T124: =-L124 -> -5037377
E126: =B124 -> Techwolf | F126: Total | L126: =SUM(L124:L125) -> 5037377 | O126: =SUM(O124:O125) -> 5037377 | Q126: =O126/L126 -> 1 | R126: =XIRR(T124:T126,S124:S126,0) -> 4.8828125e-09 | S126: =$C$1 -> 46022 | T126: =O126 -> 5037377
B128: Thatch | C128: 45513 | F128: Series A Preferred Stock | I128: 309845 | K128: 4.8734 | L128: 1509998.6 | N128: =+K131 -> 12.3072 | O128: =I128*N128 -> 3813324.4 | S128: =IFERROR(C128,0) -> 45513 | T128: =-L128 -> -1509998.6
C129: 45525 | F129: Series Seed Preferred Stock - Secondary Purchase | I129: =L129/K129 -> 26806.002 | K129: 4.8734 | L129: =129067.13+1569.24 -> 130636.37 | N129: =N128 -> 12.3072 | O129: =I129*N129 -> 329906.83 | S129: =IFERROR(C129,0) -> 45525 | T129: =-L129 -> -130636.37
C130: 45508 | F130: Series A Warrants | I130: 512988.88 | K130: 0 | L130: 0 | N130: =O130/I130 -> 7.3312759 | O130: 3760863 | S130: =IFERROR(C130,0) -> 45508 | T130: =-L130 -> 0 | U130: =+I130*K129 -> 2500000
C131: 45737 | F131: Series B Preferred Stock | I131: =191302+3705 -> 195007 | K131: =+L131/I131 -> 12.3072 | L131: =2354391.98+45598.18 -> 2399990.2 | N131: =+K131 -> 12.3072 | O131: =2.4*10^6 -> 2400000 | S131: =IFERROR(C131,0) -> 45737 | T131: =-L131 -> -2399990.2
E133: =B128 -> Thatch | F133: Total | I133: =SUM(I128:I132) -> 1044646.9 | L133: =SUM(L128:L132) -> 4040625.2 | O133: =SUM(O128:O132) -> 10304094 | Q133: =O133/L133 -> 2.5501238 | R133: =XIRR(T128:T133,S128:S133,0) -> 1.4000929 | S133: =$C$1 -> 46022 | T133: =O133 -> 10304094
B135: MultiModal | C135: 45614 | F135: SAFE | L135: =2*10^6 -> 2000000 | O135: =L135 -> 2000000 | S135: =IFERROR(C135,0) -> 45614 | T135: =-L135 -> -2000000
E137: =B135 -> MultiModal | F137: Total | L137: =SUM(L135:L136) -> 2000000 | O137: =SUM(O135:O136) -> 2000000 | Q137: =O137/L137 -> 1 | R137: =XIRR(T135:T137,S135:S137,0) -> 4.8828125e-09 | S137: =$C$1 -> 46022 | T137: =O137 -> 2000000
B139: OneImaging | C139: 45665 | F139: Series A-2 Preferred (SAFE Conversion) | I139: 1337434 | K139: =L139/I139 -> 0.74770045 | L139: 1000000 | N139: =K140 -> 8.7039272 | O139: =N139*I139 -> 11640928 | S139: =IFERROR(C139,0) -> 45665 | T139: =-L139 -> -1000000
C140: 45860 | F140: Series A Preferred Stock | I140: 344672 | K140: =L140/I140 -> 8.7039272 | L140: 3000000 | N140: =K140 -> 8.7039272 | O140: =I140*N140 -> 3000000 | S140: =IFERROR(C140,0) -> 45860 | T140: =-L140 -> -3000000
E141: =B139 -> OneImaging | F141: Total | L141: =SUM(L139:L140) -> 4000000 | O141: =O139+O140 -> 14640928 | Q141: =O141/L141 -> 3.660232 | R141: =XIRR(T139:T141,S139:S141,0) -> 6.5936678 | S141: =$C$1 -> 46022 | T141: =O141 -> 14640928
B143: ExceedsAI | C143: 45666 | F143: Series Seed Preferred Stock | I143: 2032694 | K143: =L143/I143 -> 0.5842 | L143: 1187499.8 | N143: =+K143 -> 0.5842 | O143: =+L143 -> 1187499.8 | S143: =IFERROR(C143,0) -> 45666 | T143: =-L143 -> -1187499.8
E145: =B143 -> ExceedsAI | F145: Total | L145: =SUM(L143:L144) -> 1187499.8 | O145: =SUM(O143:O144) -> 1187499.8 | Q145: =O145/L145 -> 1 | R145: =XIRR(T143:T145,S143:S145,0) -> 4.8828125e-09 | S145: =$C$1 -> 46022 | T145: =O145 -> 1187499.8
B147: Sully.AI | C147: 45666 | F147: Series A Preferred Stock | I147: 2478468 | K147: =+L147/I147 -> 1.6139 | L147: 3999999.5 | N147: =K147 -> 1.6139 | O147: =+I147*N147 -> 3999999.5 | S147: =IFERROR(C147,0) -> 45666 | T147: =-L147 -> -3999999.5
E149: =B147 -> Sully.AI | F149: Total | L149: =SUM(L147:L148) -> 3999999.5 | O149: =SUM(O147:O148) -> 3999999.5 | Q149: =O149/L149 -> 1 | R149: =XIRR(T147:T149,S147:S149,0) -> -4.8828125e-09 | S149: =$C$1 -> 46022 | T149: =O149 -> 3999999.5
B151: Athena.AI | C151: 45778 | F151: Series Seed Preferred Stock | I151: 1103249 | K151: =+L151/I151 -> 2.8552031 | L151: =3150000 -> 3150000 | N151: =K151 -> 2.8552031 | O151: =I151*N151 -> 3150000 | S151: =IFERROR(C151,0) -> 45778 | T151: =-L151 -> -3150000
K152: =L152/I152 -> #DIV/0!
E153: =B151 -> Athena.AI | F153: Total | L153: =SUM(L151:L152) -> 3150000 | O153: =SUM(O151:O152) -> 3150000 | Q153: =O153/L153 -> 1 | R153: =XIRR(T151:T153,S151:S153,0) -> 4.8828125e-09 | S153: =$C$1 -> 46022 | T153: =O153 -> 3150000
B155: Onboarded | C155: 45824 | F155: Series A-1 Preferred Stock | I155: 3663808 | K155: =+L155/I155 -> 1.3647003 | L155: =5*10^6 -> 5000000 | N155: =K155 -> 1.3647003 | O155: =L155 -> 5000000 | S155: =IFERROR(C155,0) -> 45824 | T155: =-L155 -> -5000000
K156: =L156/I156 -> #DIV/0!
E157: =B155 -> Onboarded | F157: Total | L157: =SUM(L155:L156) -> 5000000 | O157: =SUM(O155:O156) -> 5000000 | Q157: =O157/L157 -> 1 | R157: =XIRR(T155:T157,S155:S157,0) -> 4.8828125e-09 | S157: =$C$1 -> 46022 | T157: =O157 -> 5000000
B159: PenguinAI | C159: 45821 | F159: Series A Preferred Stock | I159: 573523 | K159: =+L159/I159 -> 6.9744369 | L159: =4*10^6 -> 4000000 | N159: =+K159 -> 6.9744369 | O159: =L159 -> 4000000 | S159: =IFERROR(C159,0) -> 45821 | T159: =-L159 -> -4000000
E161: =B159 -> PenguinAI | F161: Total | L161: =SUM(L159:L160) -> 4000000 | O161: =SUM(O159:O160) -> 4000000 | Q161: =O161/L161 -> 1 | R161: =XIRR(T159:T161,S159:S161,0) -> 4.8828125e-09 | S161: =$C$1 -> 46022 | T161: =O161 -> 4000000
B163: Clasp | C163: 45807 | F163: SAFE Note | L163: 250000 | O163: 250000 | S163: =IFERROR(C163,0) -> 45807 | T163: =-L163 -> -250000
E165: =B163 -> Clasp | F165: Total | L165: =SUM(L163:L164) -> 250000 | O165: =SUM(O163:O164) -> 250000 | Q165: =O165/L165 -> 1 | R165: =XIRR(T163:T165,S163:S165,0) -> 4.8828125e-09 | S165: =$C$1 -> 46022 | T165: =O165 -> 250000
B167: Sunny Health | C167: 45806 | F167: SAFE Note | L167: 50000 | O167: 50000 | S167: =IFERROR(C167,0) -> 45806 | T167: =-L167 -> -50000
E169: =B167 -> Sunny Health | F169: Total | L169: =SUM(L167:L168) -> 50000 | O169: =SUM(O167:O168) -> 50000 | Q169: =O169/L169 -> 1 | R169: =XIRR(T167:T169,S167:S169,0) -> 4.8828125e-09 | S169: =$C$1 -> 46022 | T169: =O169 -> 50000
B171: Outro Health | C171: 45806 | F171: SAFE Note | L171: 250000 | O171: =L171 -> 250000 | S171: =IFERROR(C171,0) -> 45806 | T171: =-L171 -> -250000
E172: =B171 -> Outro Health | F172: Total | L172: =SUM(L170:L171) -> 250000 | O172: =SUM(O170:O171) -> 250000 | Q172: =O172/L172 -> 1 | R172: =XIRR(T170:T172,S170:S172,0) -> 4.8828125e-09 | S172: =$C$1 -> 46022 | T172: =O172 -> 250000
B174: Tezi | C174: 45869 | F174: Series Seed-1 Preferred Stock | I174: 598999 | K174: =L174/I174 -> 3.3388987 | L174: 1999997 | N174: =O174/I174 -> 3.3388987 | O174: =L174 -> 1999997 | S174: =IFERROR(C174,0) -> 45869 | T174: =-L174 -> -1999997
C176: 45864 | F176: Series Seed-1 Warrant | I176: =299500+89850 -> 389350 | K176: 0 | N176: =O176/I176 -> 0 | O176: 0 | S176: =IFERROR(C176,0) -> 45864 | T176: =-L176 -> 0
E177: =B174 -> Tezi | F177: Total | I177: =I174+I176 -> 988349 | L177: =SUM(L174:L175) -> 1999997 | O177: =SUM(O174:O175) -> 1999997 | Q177: =O177/L177 -> 1 | R177: =XIRR(T174:T177,S174:S177,0) -> 4.8828125e-09 | S177: =$C$1 -> 46022 | T177: =O177 -> 1999997
B179: Trial Library | C179: 45877 | F179: Series A Preferred Stock | I179: 1302798 | K179: =L179/I179 -> 2.3027346 | L179: 2999998 | N179: =O179/I179 -> 2.3027346 | O179: 2999998 | S179: =IFERROR(C179,0) -> 45877 | T179: =-L179 -> -2999998
E181: =B179 -> Trial Library | F181: Total | L181: =SUM(L179:L180) -> 2999998 | O181: =SUM(O179:O180) -> 2999998 | Q181: =O181/L181 -> 1 | R181: =XIRR(T179:T181,S179:S181,0) -> 4.8828125e-09 | S181: =$C$1 -> 46022 | T181: =O181 -> 2999998
B183: TrueClaim | C183: 45924 | F183: SAFE Note | L183: 250000 | O183: =L183 -> 250000 | S183: =IFERROR(C183,0) -> 45924 | T183: =-L183 -> -250000
E185: =B183 -> TrueClaim | F185: Total | L185: =SUM(L183:L184) -> 250000 | O185: =SUM(O183:O184) -> 250000 | Q185: =O185/L185 -> 1 | R185: =XIRR(T183:T185,S183:S185,0) -> 4.8828125e-09 | S185: =$C$1 -> 46022 | T185: =O185 -> 250000
B187: Andel | C187: 45924 | F187: SAFE Note | L187: 250000 | O187: =L187 -> 250000 | S187: =IFERROR(C187,0) -> 45924 | T187: =-L187 -> -250000
E189: =B187 -> Andel | F189: Total | L189: =SUM(L187:L188) -> 250000 | O189: =SUM(O187:O188) -> 250000 | Q189: =O189/L189 -> 1 | R189: =XIRR(T187:T189,S187:S189,0) -> 4.8828125e-09 | S189: =$C$1 -> 46022 | T189: =O189 -> 250000
B191: Second Door | C191: 45924 | F191: SAFE Note | L191: 250000 | O191: =L191 -> 250000 | S191: =IFERROR(C191,0) -> 45924 | T191: =-L191 -> -250000
E193: =B191 -> Second Door | F193: Total | L193: =SUM(L191:L192) -> 250000 | O193: =SUM(O191:O192) -> 250000 | Q193: =O193/L193 -> 1 | R193: =XIRR(T191:T193,S191:S193,0) -> 4.8828125e-09 | S193: =$C$1 -> 46022 | T193: =O193 -> 250000
B195: Carefam | C195: 45949 | F195: Series A Preferred Stock | L195: =2604553.72+36445.83 -> 2640999.6 | O195: =L195 -> 2640999.6 | S195: =IFERROR(C195,0) -> 45949 | T195: =-L195 -> -2640999.6
E196: =B195 -> Carefam | F196: Total | L196: =SUM(L195:L195) -> 2640999.6 | O196: =SUM(O195:O195) -> 2640999.6 | Q196: =O196/L196 -> 1 | R196: =XIRR(T195:T196,S195:S196,0) -> 4.8828125e-09 | S196: =$C$1 -> 46022 | T196: =O196 -> 2640999.6
B198: Helm | C198: 45958 | L198: 3000000 | O198: =L198 -> 3000000 | S198: =IFERROR(C198,0) -> 45958 | T198: =-L198 -> -3000000
E200: =B198 -> Helm | F200: Total | L200: =SUM(L198:L199) -> 3000000 | O200: =SUM(O198:O199) -> 3000000 | Q200: =O200/L200 -> 1 | R200: =XIRR(T198:T200,S198:S200,0) -> 4.8828125e-09 | S200: =$C$1 -> 46022 | T200: =O200 -> 3000000
B203: Total Unrealized Portfolio | L203: =SUMIF($F$80:$F$202,"Total",L80:L202) -> 76264804 | O203: =SUMIF($F$80:$F$202,"Total",O80:O202) -> 98040729 | Q203: =O203/L203 -> 1.2855305 | R203: =XIRR(T80:T182,S80:S182,) -> 0.23849095
B205: Total Portfolio | L205: =L203+L77 -> 76264804 | O205: =O203+O77 -> 98040729 | Q205: =O205/L205 -> 1.2855305 | R205: =XIRR(T4:T202,S4:S202) -> 0.23573356

Sheet Investment Characteristics
Q1: =Q8*N8 -> 1499860.1 | Y1: =143*10^6 -> 143000000
B2: Core Initial Investment Characteristics | K2: Current Investment Characteristics
B3: Company | C3: Date | D3: Series | E3: Sector | F3: $ Invested | G3: VC Syndicate | H3: FD% | I3: Avg. Cost | K3: Company | L3: Series | M3: FD% Actual | N3: With warrants fully vested | O3: Initital Cost | P3: Avg. Cost | Q3: Last Valuation | R3: Holding Value | S3: $ Invested | T3: Follow -On Investment | U3: Market Value | V3: Multiple | W3: Lead | X3: Allocation | Y3: RTF | Z3: Board Seat | AB3: 45107 | AC3: 45473 | AD3: 45565 | AE3: 45657 | AF3: 45838 | AG3: 45930 | AI3: Rationale
A4: x | B4: Laguna Health | C4: =INDEX('Statement of Investments'!$C$5:$C$205,MATCH('Investment Characteristics'!$B4,'Statement of Investments'!$B$5:$B$205,0)) -> 45021 | D4: A | E4: Healthtech | F4: =INDEX('Statement of Investments'!$L$5:$L$205,MATCH('Investment Characteristics'!$B4,'Statement of Investments'!$B$5:$B$205,0)) -> 3999999.7 | G4: HC9, Pitango | H4: 0.07547 | I4: =IFERROR(ROUND(F4/H4,-5),0) -> 53000000 | K4: =B4 -> Laguna Health | L4: A | M4: 0.077934988 | N4: =M4 -> 0.077934988 | O4: =I4 -> 53000000 | P4: =IFERROR(ROUND(S4/M4,-5),0) -> 64200000 | Q4: =O4 -> 53000000 | R4: =+Q4 -> 53000000 | S4: =INDEX('Statement of Investments'!$L$5:$L$205,MATCH(B4,'Statement of Investments'!$E$5:$E$205,0)) -> 4999999.7 | T4: =S4-F4 -> 1000000 | U4: =INDEX('Statement of Investments'!$O$5:$O$205,MATCH(B4,'Statement of Investments'!$E$5:$E$205,0)) -> 4999999.7 | V4: =U4/S4 -> 1 | W4: RP | X4: GG | Y4: =+$Y$1/M4/10^6 -> 1834.8627 | AB4: 1 | AC4: 1 | AD4: 0 | AE4: 0
A5: x | B5: Stepful | C5: =INDEX('Statement of Investments'!$C$5:$C$205,MATCH('Investment Characteristics'!$B5,'Statement of Investments'!$B$5:$B$205,0)) -> 45183 | D5: A | E5: Workforce | F5: =INDEX('Statement of Investments'!$L$5:$L$205,MATCH('Investment Characteristics'!$B5,'Statement of Investments'!$B$5:$B$205,0)) -> 3999995.7 | G5: Reach, Alleycorp, YC | H5: 0.043589887 | I5: =IFERROR(ROUND(F5/H5,-5),0) -> 91800000 | K5: =B5 -> Stepful | L5: B | M5: 0.052805468 | N5: =M5 -> 0.052805468 | O5: =I5 -> 91800000 | P5: =IFERROR(ROUND(S5/M5,-5),0) -> 149200000 | Q5: 261500000 | R5: =+Q5 -> 261500000 | S5: =INDEX('Statement of Investments'!$L$5:$L$205,MATCH(B5,'Statement of Investments'!$E$5:$E$205,0)) -> 7878030.5 | T5: =S5-F5 -> 3878034.7 | U5: =INDEX('Statement of Investments'!$O$5:$O$205,MATCH(B5,'Statement of Investments'!$E$5:$E$205,0)) -> 13609280 | V5: =U5/S5 -> 1.7274977 | W5: ABG | X5: ABG | Y5: =+$Y$1/M5/10^6 -> 2708.0529 | AB5: - | AC5: 1 | AD5: 1 | AE5: 1
B6: Summer | C6: =INDEX('Statement of Investments'!$C$5:$C$205,MATCH('Investment Characteristics'!$B6,'Statement of Investments'!$B$5:$B$205,0)) -> 45209 | D6: Seed | E6: Financial | F6: =INDEX('Statement of Investments'!$L$5:$L$205,MATCH('Investment Characteristics'!$B6,'Statement of Investments'!$B$5:$B$205,0)) -> 3250000 | G6: GC, QED, Flourish, Rebalance | H6: =+F6/I6 -> 0.092857143 | I6: =35*10^6 -> 35000000 | K6: =B6 -> Summer | L6: A | M6: 0.11734531 | N6: =M6 -> 0.11734531 | O6: =I6 -> 35000000 | P6: =IFERROR(ROUND(S6/M6,-5),0) -> 27700000 | Q6: 41544018 | R6: 41544018 | S6: =INDEX('Statement of Investments'!$L$5:$L$205,MATCH(B6,'Statement of Investments'!$E$5:$E$205,0)) -> 3250000 | T6: =S6-F6 -> 0 | U6: =INDEX('Statement of Investments'!$O$5:$O$205,MATCH(B6,'Statement of Investments'!$E$5:$E$205,0)) -> 3250000 | V6: =U6/S6 -> 1 | W6: RP | X6: RP | Y6: =+$Y$1/M6/10^6 -> 1218.6256 | AB6: - | AC6: 1 | AD6: 0 | AE6: -1
B7: Kubera | C7: =INDEX('Statement of Investments'!$C$5:$C$205,MATCH('Investment Characteristics'!$B7,'Statement of Investments'!$B$5:$B$205,0)) -> 45274 | D7: Seed | E7: Healthtech | F7: =INDEX('Statement of Investments'!$L$5:$L$205,MATCH('Investment Characteristics'!$B7,'Statement of Investments'!$B$5:$B$205,0)) -> 399999.2 | G7: Upfront Ventures | H7: =+F7/I7 -> 0.033333267 | I7: =12*10^6 -> 12000000 | K7: =B7 -> Kubera | L7: Seed | M7: 0.033713855 | N7: =M7 -> 0.033713855 | O7: =I7 -> 12000000 | P7: =IFERROR(ROUND(S7/M7,-5),0) -> 15700000 | Q7: 30000000 | R7: =+Q7 -> 30000000 | S7: =INDEX('Statement of Investments'!$L$5:$L$205,MATCH(B7,'Statement of Investments'!$E$5:$E$205,0)) -> 528082.67 | T7: =S7-F7 -> 128083.47 | U7: =INDEX('Statement of Investments'!$O$5:$O$205,MATCH(B7,'Statement of Investments'!$E$5:$E$205,0)) -> 1011413.2 | V7: =U7/S7 -> 1.9152554 | W7: RP | X7: RP | Y7: =+$Y$1/M7/10^6 -> 4241.5796 | AB7: - | AC7: 1 | AD7: 1 | AE7: 0
B8: Wagmo | C8: =INDEX('Statement of Investments'!$C$5:$C$205,MATCH('Investment Characteristics'!$B8,'Statement of Investments'!$B$5:$B$205,0)) -> 45209 | D8: A | E8: Financial | F8: =INDEX('Statement of Investments'!$L$5:$L$205,MATCH('Investment Characteristics'!$B8,'Statement of Investments'!$B$5:$B$205,0)) -> 1499998 | G8: Revolution, MS&AD | H8: 0.03180843 | I8: =IFERROR(ROUND(F8/H8,-5),0) -> 47200000 | K8: =B8 -> Wagmo | L8: A | M8: =(133226+499600+0.75*199840)/26203667 -> 0.029870094 | N8: =(133226+499600+199840)/26203667 -> 0.031776698 | O8: =I8 -> 47200000 | P8: =IFERROR(ROUND(S8/M8,-5),0) -> 50200000 | Q8: =O8 -> 47200000 | R8: =+Q8 -> 47200000 | S8: =INDEX('Statement of Investments'!$L$5:$L$205,MATCH(B8,'Statement of Investments'!$E$5:$E$205,0)) -> 1499998 | T8: =S8-F8 -> 0 | U8: =INDEX('Statement of Investments'!$O$5:$O$205,MATCH(B8,'Statement of Investments'!$E$5:$E$205,0)) -> 1499998 | V8: =U8/S8 -> 1 | W8: RP | X8: CH | Y8: =+$Y$1/M8/10^6 -> 4787.397 | AB8: - | AC8: 1 | AD8: 0 | AE8: 1
B9: Salsa | C9: =INDEX('Statement of Investments'!$C$5:$C$205,MATCH('Investment Characteristics'!$B9,'Statement of Investments'!$B$5:$B$205,0)) -> 45329 | D9: Seed | E9: Financial | F9: =INDEX('Statement of Investments'!$L$5:$L$205,MATCH('Investment Characteristics'!$B9,'Statement of Investments'!$B$5:$B$205,0)) -> 2500000 | G9: BTV, Greycroft | H9: =+F9/I9 -> 0.056818182 | I9: =44*10^6 -> 44000000 | K9: =B9 -> Salsa | L9: A | M9: 0.084687403 | N9: =M9 -> 0.084687403 | O9: =I9 -> 44000000 | P9: =IFERROR(ROUND(S9/M9,-5),0) -> 64900000 | Q9: =70*10^6 -> 70000000 | R9: =+Q9 -> 70000000 | S9: =INDEX('Statement of Investments'!$L$5:$L$205,MATCH(B9,'Statement of Investments'!$E$5:$E$205,0)) -> 5499997.9 | T9: =S9-F9 -> 2999997.9 | U9: =INDEX('Statement of Investments'!$O$5:$O$205,MATCH(B9,'Statement of Investments'!$E$5:$E$205,0)) -> 5912934 | V9: =U9/S9 -> 1.0750793 | W9: RP | X9: CH | Y9: =+$Y$1/M9/10^6 -> 1688.5628 | AB9: - | AC9: 1 | AD9: 1 | AE9: 1
A10: x | B10: Solara | C10: =INDEX('Statement of Investments'!$C$5:$C$205,MATCH('Investment Characteristics'!$B10,'Statement of Investments'!$B$5:$B$205,0)) -> 45329 | D10: Seed | E10: Healthtech | F10: =INDEX('Statement of Investments'!$L$5:$L$205,MATCH('Investment Characteristics'!$B10,'Statement of Investments'!$B$5:$B$205,0)) -> 1999999.8 | G10: Define Ventures, USVP | H10: =+F10/I10 -> 0.13793102 | I10: 14500000 | K10: =B10 -> Solara | L10: Seed | M10: 0.1309 | N10: =M10 -> 0.1309 | O10: =I10 -> 14500000 | P10: =IFERROR(ROUND(S10/M10,-5),0) -> 34800000 | Q10: =40000000 -> 40000000 | R10: =+Q10 -> 40000000 | S10: =INDEX('Statement of Investments'!$L$5:$L$205,MATCH(B10,'Statement of Investments'!$E$5:$E$205,0)) -> 4552198.8 | T10: =S10-F10 -> 2552199 | U10: =INDEX('Statement of Investments'!$O$5:$O$205,MATCH(B10,'Statement of Investments'!$E$5:$E$205,0)) -> 5296211.2 | V10: =U10/S10 -> 1.1634402 | W10: RP | X10: GG | Y10: =+$Y$1/M10/10^6 -> 1092.437 | AB10: - | AC10: 1 | AD10: 1 | AE10: 1
A11: x | B11: Hireguide | C11: =INDEX('Statement of Investments'!$C$5:$C$205,MATCH('Investment Characteristics'!$B11,'Statement of Investments'!$B$5:$B$205,0)) -> 45351 | D11: Seed | E11: Workforce | F11: =INDEX('Statement of Investments'!$L$5:$L$205,MATCH('Investment Characteristics'!$B11,'Statement of Investments'!$B$5:$B$205,0)) -> 3000000 | G11: Wing, NEA, GGV | H11: =+F11/I11 -> 0.09375 | I11: =32*10^6 -> 32000000 | K11: =B11 -> Hireguide | L11: Seed | M11: 0.09375 | N11: =M11 -> 0.09375 | O11: =I11 -> 32000000 | P11: =IFERROR(ROUND(S11/M11,-5),0) -> 32000000 | Q11: =O11 -> 32000000 | R11: =+Q11 -> 32000000 | S11: =INDEX('Statement of Investments'!$L$5:$L$205,MATCH(B11,'Statement of Investments'!$E$5:$E$205,0)) -> 3000000 | T11: =S11-F11 -> 0 | U11: =INDEX('Statement of Investments'!$O$5:$O$205,MATCH(B11,'Statement of Investments'!$E$5:$E$205,0)) -> 500000 | V11: =U11/S11 -> 0.16666667 | W11: CT | X11: RP | Y11: =+$Y$1/M11/10^6 -> 1525.3333 | AB11: - | AD11: 1 | AE11: 0
B12: Take2 AI | C12: =INDEX('Statement of Investments'!$C$5:$C$205,MATCH('Investment Characteristics'!$B12,'Statement of Investments'!$B$5:$B$205,0)) -> 45376 | D12: Seed | E12: Workforce | F12: =INDEX('Statement of Investments'!$L$5:$L$205,MATCH('Investment Characteristics'!$B12,'Statement of Investments'!$B$5:$B$205,0)) -> 700000 | G12: Reach Capital | H12: =+F12/I12 -> 0.07 | I12: 10000000 | K12: =B12 -> Take2 AI | L12: Seed | M12: 0.07 | N12: =M12 -> 0.07 | O12: =I12 -> 10000000 | P12: =IFERROR(ROUND(S12/M12,-5),0) -> 10000000 | Q12: =O12 -> 10000000 | R12: =+Q12 -> 10000000 | S12: =INDEX('Statement of Investments'!$L$5:$L$205,MATCH(B12,'Statement of Investments'!$E$5:$E$205,0)) -> 700000 | T12: =S12-F12 -> 0 | U12: =INDEX('Statement of Investments'!$O$5:$O$205,MATCH(B12,'Statement of Investments'!$E$5:$E$205,0)) -> 700000 | V12: =U12/S12 -> 1 | W12: ABG | X12: ABG | Y12: =+$Y$1/M12/10^6 -> 2042.8571 | AB12: - | AD12: 1 | AE12: 0
B13: Techwolf | C13: =INDEX('Statement of Investments'!$C$5:$C$205,MATCH('Investment Characteristics'!$B13,'Statement of Investments'!$B$5:$B$205,0)) -> 45467 | D13: B | E13: Workforce | F13: =INDEX('Statement of Investments'!$L$5:$L$205,MATCH('Investment Characteristics'!$B13,'Statement of Investments'!$B$5:$B$205,0)) -> 5037377 | G13: Felix Capital, Stride VC | H13: =+F13/I13 -> 0.035726078 | I13: =141*10^6 -> 141000000 | K13: =B13 -> Techwolf | L13: B | M13: 0.035210817 | N13: =M13 -> 0.035210817 | O13: =I13 -> 141000000 | P13: =IFERROR(ROUND(S13/M13,-5),0) -> 143100000 | Q13: =O13 -> 141000000 | R13: =+Q13 -> 141000000 | S13: =INDEX('Statement of Investments'!$L$5:$L$205,MATCH(B13,'Statement of Investments'!$E$5:$E$205,0)) -> 5037377 | T13: =S13-F13 -> 0 | U13: =INDEX('Statement of Investments'!$O$5:$O$205,MATCH(B13,'Statement of Investments'!$E$5:$E$205,0)) -> 5037377 | V13: =U13/S13 -> 1 | W13: ABG | X13: ABG | Y13: =+$Y$1/M13/10^6 -> 4061.252 | AE13: 1
B14: Thatch | C14: =INDEX('Statement of Investments'!$C$5:$C$205,MATCH('Investment Characteristics'!$B14,'Statement of Investments'!$B$5:$B$205,0)) -> 45513 | D14: A | E14: Healthtech | F14: =INDEX('Statement of Investments'!$L$5:$L$205,MATCH('Investment Characteristics'!$B14,'Statement of Investments'!$B$5:$B$205,0)) -> 1509998.6 | G14: Index, GV, GC, a16z | H14: 0.029703718 | I14: =F14/H14 -> 50835341 | K14: =B14 -> Thatch | L14: B | M14: 0.032141794 | N14: =M14 -> 0.032141794 | O14: =I14 -> 50835341 | P14: =IFERROR(ROUND(S14/M14,-5),0) -> 125700000 | Q14: =450*10^6 -> 450000000 | R14: =450*10^6 -> 450000000 | S14: =INDEX('Statement of Investments'!$L$5:$L$205,MATCH(B14,'Statement of Investments'!$E$5:$E$205,0)) -> 4040625.2 | T14: =S14-F14 -> 2530626.5 | U14: =INDEX('Statement of Investments'!$O$5:$O$205,MATCH(B14,'Statement of Investments'!$E$5:$E$205,0)) -> 10304094 | V14: =U14/S14 -> 2.5501238 | W14: RP | X14: GG | Y14: =+$Y$1/M14/10^6 -> 4449.0361 | AE14: 1
A15: x | B15: Multimodal | C15: =INDEX('Statement of Investments'!$C$5:$C$205,MATCH('Investment Characteristics'!$B15,'Statement of Investments'!$B$5:$B$205,0)) -> 45614 | D15: Seed | E15: Financial | F15: =INDEX('Statement of Investments'!$L$5:$L$205,MATCH('Investment Characteristics'!$B15,'Statement of Investments'!$B$5:$B$205,0)) -> 2000000 | H15: =+F15/I15 -> 0.066666667 | I15: =30*10^6 -> 30000000 | K15: =B15 -> Multimodal | L15: Seed | M15: 0.066666667 | N15: =M15 -> 0.066666667 | O15: =I15 -> 30000000 | P15: =IFERROR(ROUND(S15/M15,-5),0) -> 30000000 | Q15: =O15 -> 30000000 | R15: =+Q15 -> 30000000 | S15: =INDEX('Statement of Investments'!$L$5:$L$205,MATCH(B15,'Statement of Investments'!$E$5:$E$205,0)) -> 2000000 | T15: =S15-F15 -> 0 | U15: =INDEX('Statement of Investments'!$O$5:$O$205,MATCH(B15,'Statement of Investments'!$E$5:$E$205,0)) -> 2000000 | V15: =U15/S15 -> 1 | W15: CH | X15: CH | Y15: =+$Y$1/M15/10^6 -> 2145 | AE15: 1
A16: x | B16: OneImaging | C16: =INDEX('Statement of Investments'!$C$5:$C$205,MATCH('Investment Characteristics'!$B16,'Statement of Investments'!$B$5:$B$205,0)) -> 45665 | D16: Seed | E16: Healthtech | F16: =INDEX('Statement of Investments'!$L$5:$L$205,MATCH('Investment Characteristics'!$B16,'Statement of Investments'!$B$5:$B$205,0)) -> 1000000 | G16: Aquiline, Six Thirty, Vy Capital | H16: =+F16/I16 -> 0.055555556 | I16: =18*10^6 -> 18000000 | K16: =B16 -> OneImaging | L16: A | M16: 0.05994 | N16: =M16 -> 0.05994 | O16: =I16 -> 18000000 | P16: =IFERROR(ROUND(S16/M16,-5),0) -> 66700000 | Q16: 250000000 | R16: =+Q16 -> 250000000 | S16: =INDEX('Statement of Investments'!$L$5:$L$205,MATCH(B16,'Statement of Investments'!$E$5:$E$205,0)) -> 4000000 | T16: =S16-F16 -> 3000000 | U16: =INDEX('Statement of Investments'!$O$5:$O$205,MATCH(B16,'Statement of Investments'!$E$5:$E$205,0)) -> 14640928 | V16: =U16/S16 -> 3.660232 | W16: CT | X16: RP | Y16: =+$Y$1/M16/10^6 -> 2385.7191 | AE16: 1
B17: ExceedsAI | C17: =INDEX('Statement of Investments'!$C$5:$C$205,MATCH('Investment Characteristics'!$B17,'Statement of Investments'!$B$5:$B$205,0)) -> 45666 | D17: Seed | E17: Workforce | F17: =INDEX('Statement of Investments'!$L$5:$L$205,MATCH('Investment Characteristics'!$B17,'Statement of Investments'!$B$5:$B$205,0)) -> 1187499.8 | G17: Venrock | H17: =+F17/I17 -> 0.079166656 | I17: =15*10^6 -> 15000000 | K17: =B17 -> ExceedsAI | L17: Seed | M17: 0.079166656 | N17: =M17 -> 0.079166656 | O17: =I17 -> 15000000 | P17: =IFERROR(ROUND(S17/M17,-5),0) -> 15000000 | Q17: =O17 -> 15000000 | R17: =+Q17 -> 15000000 | S17: =INDEX('Statement of Investments'!$L$5:$L$205,MATCH(B17,'Statement of Investments'!$E$5:$E$205,0)) -> 1187499.8 | T17: =S17-F17 -> 0 | U17: =INDEX('Statement of Investments'!$O$5:$O$205,MATCH(B17,'Statement of Investments'!$E$5:$E$205,0)) -> 1187499.8 | V17: =U17/S17 -> 1 | W17: ABG | X17: ABG | Y17: =+$Y$1/M17/10^6 -> 1806.316 | AE17: 1
B18: Sully.AI | C18: =INDEX('Statement of Investments'!$C$5:$C$205,MATCH('Investment Characteristics'!$B18,'Statement of Investments'!$B$5:$B$205,0)) -> 45666 | D18: A | E18: Healthtech | F18: =INDEX('Statement of Investments'!$L$5:$L$205,MATCH('Investment Characteristics'!$B18,'Statement of Investments'!$B$5:$B$205,0)) -> 3999999.5 | G18: Amity Ventures | H18: =+F18/I18 -> 0.053333327 | I18: =75*10^6 -> 75000000 | K18: =B18 -> Sully.AI | L18: A | M18: 0.053333327 | N18: =M18 -> 0.053333327 | O18: =I18 -> 75000000 | P18: =IFERROR(ROUND(S18/M18,-5),0) -> 75000000 | Q18: =O18 -> 75000000 | R18: =+Q18 -> 75000000 | S18: =INDEX('Statement of Investments'!$L$5:$L$205,MATCH(B18,'Statement of Investments'!$E$5:$E$205,0)) -> 3999999.5 | T18: =S18-F18 -> 0 | U18: =INDEX('Statement of Investments'!$O$5:$O$205,MATCH(B18,'Statement of Investments'!$E$5:$E$205,0)) -> 3999999.5 | V18: =U18/S18 -> 1 | W18: ABG | X18: ABG | Y18: =+$Y$1/M18/10^6 -> 2681.2503 | AE18: 1
A19: x | B19: Athena.AI | C19: =INDEX('Statement of Investments'!$C$5:$C$205,MATCH('Investment Characteristics'!$B19,'Statement of Investments'!$B$5:$B$205,0)) -> 45778 | D19: Seed | E19: Workforce | F19: =INDEX('Statement of Investments'!$L$5:$L$205,MATCH('Investment Characteristics'!$B19,'Statement of Investments'!$B$5:$B$205,0)) -> 3150000 | G19: Village Global | H19: =+F19/I19 -> 0.09 | I19: =35*10^6 -> 35000000 | K19: =B19 -> Athena.AI | L19: Seed | M19: 0.09 | N19: =M19 -> 0.09 | O19: =I19 -> 35000000 | P19: =IFERROR(ROUND(S19/M19,-5),0) -> 35000000 | Q19: =O19 -> 35000000 | R19: =+Q19 -> 35000000 | S19: =INDEX('Statement of Investments'!$L$5:$L$205,MATCH(B19,'Statement of Investments'!$E$5:$E$205,0)) -> 3150000 | T19: =S19-F19 -> 0 | U19: =INDEX('Statement of Investments'!$O$5:$O$205,MATCH(B19,'Statement of Investments'!$E$5:$E$205,0)) -> 3150000 | V19: =U19/S19 -> 1 | W19: RP | X19: RP | Y19: =+$Y$1/M19/10^6 -> 1588.8889
A20: x | B20: Onboarded | C20: =INDEX('Statement of Investments'!$C$5:$C$205,MATCH('Investment Characteristics'!$B20,'Statement of Investments'!$B$5:$B$205,0)) -> 45824 | D20: A | E20: Workforce | F20: =INDEX('Statement of Investments'!$L$5:$L$205,MATCH('Investment Characteristics'!$B20,'Statement of Investments'!$B$5:$B$205,0)) -> 5000000 | G20: SV, Resolute | H20: =+F20/I20 -> 0.086956522 | I20: =57.5*10^6 -> 57500000 | K20: =B20 -> Onboarded | L20: A | M20: 0.086956522 | N20: =M20 -> 0.086956522 | O20: =I20 -> 57500000 | P20: =IFERROR(ROUND(S20/M20,-5),0) -> 57500000 | Q20: =O20 -> 57500000 | R20: =+Q20 -> 57500000 | S20: =INDEX('Statement of Investments'!$L$5:$L$205,MATCH(B20,'Statement of Investments'!$E$5:$E$205,0)) -> 5000000 | T20: =S20-F20 -> 0 | U20: =INDEX('Statement of Investments'!$O$5:$O$205,MATCH(B20,'Statement of Investments'!$E$5:$E$205,0)) -> 5000000 | V20: =U20/S20 -> 1 | W20: CT | X20: GG | Y20: =+$Y$1/M20/10^6 -> 1644.5
B21: PenguinAI | C21: =INDEX('Statement of Investments'!$C$5:$C$205,MATCH('Investment Characteristics'!$B21,'Statement of Investments'!$B$5:$B$205,0)) -> 45821 | D21: A | E21: Healthtech | F21: =INDEX('Statement of Investments'!$L$5:$L$205,MATCH('Investment Characteristics'!$B21,'Statement of Investments'!$B$5:$B$205,0)) -> 4000000 | G21: GreyCroft, UPMC | H21: =+F21/I21 -> 0.024242424 | I21: =165*10^6 -> 165000000 | K21: =B21 -> PenguinAI | L21: A | M21: 0.02527 | N21: =M21 -> 0.02527 | O21: =I21 -> 165000000 | P21: =IFERROR(ROUND(S21/M21,-5),0) -> 158300000 | Q21: =O21 -> 165000000 | R21: =+Q21 -> 165000000 | S21: =INDEX('Statement of Investments'!$L$5:$L$205,MATCH(B21,'Statement of Investments'!$E$5:$E$205,0)) -> 4000000 | T21: =S21-F21 -> 0 | U21: =INDEX('Statement of Investments'!$O$5:$O$205,MATCH(B21,'Statement of Investments'!$E$5:$E$205,0)) -> 4000000 | V21: =U21/S21 -> 1 | W21: GG | X21: GG | Y21: =+$Y$1/M21/10^6 -> 5658.8841
B22: Tezi | C22: =INDEX('Statement of Investments'!$C$5:$C$205,MATCH('Investment Characteristics'!$B22,'Statement of Investments'!$B$5:$B$205,0)) -> 45869 | D22: Seed | E22: Workforce | F22: =INDEX('Statement of Investments'!$L$5:$L$205,MATCH('Investment Characteristics'!$B22,'Statement of Investments'!$B$5:$B$205,0)) -> 1999997 | G22: 8VC, Audacious | H22: =F22/I22 -> 0.033333283 | I22: 60000000 | K22: =B22 -> Tezi | L22: Seed | M22: 0.033333283 | N22: =M22+((389350+(500000/(0.8*3.34)))/17969903) -> 0.065413353 | O22: =I22 -> 60000000 | P22: =IFERROR(ROUND(S22/M22,-5),0) -> 60000000 | Q22: =O22 -> 60000000 | R22: =+Q22 -> 60000000 | S22: =INDEX('Statement of Investments'!$L$5:$L$205,MATCH(B22,'Statement of Investments'!$E$5:$E$205,0)) -> 1999997 | T22: =S22-F22 -> 0 | U22: =INDEX('Statement of Investments'!$O$5:$O$205,MATCH(B22,'Statement of Investments'!$E$5:$E$205,0)) -> 1999997 | V22: =U22/S22 -> 1 | W22: RP | X22: RP | Y22: =+$Y$1/M22/10^6 -> 4290.0064
A23: x | B23: Trial Library | C23: =INDEX('Statement of Investments'!$C$5:$C$205,MATCH('Investment Characteristics'!$B23,'Statement of Investments'!$B$5:$B$205,0)) -> 45877 | D23: A | E23: Healthtech | F23: =INDEX('Statement of Investments'!$L$5:$L$205,MATCH('Investment Characteristics'!$B23,'Statement of Investments'!$B$5:$B$205,0)) -> 2999998 | G23: Lux, Next Ventures | H23: =F23/I23 -> 0.05999996 | I23: =50*10^6 -> 50000000 | K23: =B23 -> Trial Library | L23: A | M23: 0.060720105 | N23: =M23 -> 0.060720105 | O23: =I23 -> 50000000 | P23: =IFERROR(ROUND(S23/M23,-5),0) -> 49400000 | Q23: =O23 -> 50000000 | R23: =+Q23 -> 50000000 | S23: =INDEX('Statement of Investments'!$L$5:$L$205,MATCH(B23,'Statement of Investments'!$E$5:$E$205,0)) -> 2999998 | T23: =S23-F23 -> 0 | U23: =INDEX('Statement of Investments'!$O$5:$O$205,MATCH(B23,'Statement of Investments'!$E$5:$E$205,0)) -> 2999998 | V23: =U23/S23 -> 1 | W23: ABG | X23: GG
B24: Carefam | C24: 45949 | D24: A | E24: Workforce | F24: =2.64*10^6 -> 2640000 | G24: Pitango Ventures | H24: 0.0702 | I24: =37*10^6 -> 37000000 | K24: Carefam | L24: A | M24: 0.0702 | N24: =M24 -> 0.0702 | O24: =I24 -> 37000000 | P24: =IFERROR(ROUND(S24/M24,-5),0) -> 37600000 | Q24: =P24 -> 37600000 | R24: =Q24 -> 37600000 | S24: =F24 -> 2640000 | T24: 0 | U24: =S24 -> 2640000 | V24: =U24/S24 -> 1 | W24: ABG | X24: ABG
A25: x | B25: Helm | C25: 45958 | D25: A | E25: Financial | F25: 3000000 | G25: .406 Ventures, Springtide | H25: =6.66666666666667%+(0.5/45) -> 0.077777778 | I25: =F25/H25 -> 38571429 | K25: =+B25 -> Helm | L25: A | M25: =H25 -> 0.077777778 | N25: 0.1 | O25: =I25 -> 38571429 | P25: =IFERROR(ROUND(S25/M25,-5),0) -> 38600000 | Q25: =45*10^6 -> 45000000 | R25: =45*10^6 -> 45000000 | S25: =F25 -> 3000000 | T25: =S25-F25 -> 0 | U25: =S25 -> 3000000 | V25: =U25/S25 -> 1 | W25: CT | X25: GG
B26: Multiply | D26: A | E26: Financial | F26: 4000000 | G26: SV | H26: =4/120 -> 0.033333333 | I26: =+F26/H26 -> 120000000 | K26: Multiply | L26: A | M26: =H26 -> 0.033333333 | N26: =M26+(4/120) -> 0.066666667 | O26: =I26 -> 120000000 | P26: =IFERROR(ROUND(S26/M26,-5),0) -> 120000000 | Q26: 120000000 | R26: =Q26 -> 120000000 | S26: 4000000 | T26: 0 | U26: =S26 -> 4000000 | V26: =U26/S26 -> 1
B32: Average | F32: =AVERAGE(F4:F31) -> 2733689.7 | H32: =AVERAGE(H4:H31) -> 0.062241445 | I32: =AVERAGE(I4:I31) -> 53582903 | K32: Average | M32: =AVERAGE(M4:M31) -> 0.065002496 | N32: =AVERAGE(N4:N31) -> 0.068895636 | O32: =AVERAGE(O4:O31) -> 53582903 | P32: =AVERAGE(P4:P31) -> 63504348 | Q32: =AVERAGE(Q4:Q31) -> 92014957 | S32: =AVERAGE(S4:S31) -> 3433208.9 | U32: =AVERAGE(U4:U31) -> 4379988.2
B33: Median | F33: =MEDIAN(F4:F31) -> 2999998 | H33: =MEDIAN(H4:H31) -> 0.05999996 | I33: =MEDIAN(I4:I31) -> 44000000 | K33: Median | M33: =MEDIAN(M4:M31) -> 0.066666667 | N33: =MEDIAN(N4:N31) -> 0.066666667 | O33: =MEDIAN(O4:O31) -> 44000000 | P33: =MEDIAN(P4:P31) -> 50200000 | Q33: =MEDIAN(Q4:Q31) -> 50000000 | S33: =MEDIAN(S4:S31) -> 3250000 | U33: =MEDIAN(U4:U31) -> 3250000
B34: Dollar Weighted | H34: =SUMPRODUCT(H$4:H$31,$F$4:$F$31)/SUM($F$4:$F$31) -> 0.062380931 | I34: =SUMPRODUCT(I$4:I$31,$F$4:$F$31)/SUM($F$4:$F$31) -> 67030563 | K34: Dollar Weighted | M34: =SUMPRODUCT(M$4:M$31,$S$4:$S$31)/SUM($S$4:$S$31) -> 0.066479022 | N34: =SUMPRODUCT(N$4:N$31,$S$4:$S$31)/SUM($S$4:$S$31) -> 0.06986057 | O34: =SUMPRODUCT(O$4:O$31,$S$4:$S$31)/SUM($S$4:$S$31) -> 63025460 | P34: =SUMPRODUCT(P$4:P$31,$S$4:$S$31)/SUM($S$4:$S$31) -> 77959336 | Q34: =SUMPRODUCT(Q$4:Q$31,$S$4:$S$31)/SUM($S$4:$S$31) -> 1.1606876e+08
B38: SVA Initial Investment Characteristics | K38: Current Investment Characteristics
B39: Company | C39: Date | D39: Series | E39: Sector | F39: $ Invested | G39: VC Syndicate | H39: FD% | I39: Avg. Cost | K39: Company | L39: Series | M39: FD% | O39: Initital Cost | P39: Avg. Cost | Q39: Last Valuation | R39: Holding Value | S39: $ Invested | T39: Follow -On Investment | U39: Market Value | V39: Multiple | W39: Lead | X39: Allocation | Y39: RTF
B40: Clasp | C40: =INDEX('Statement of Investments'!$C$5:$C$205,MATCH('Investment Characteristics'!$B40,'Statement of Investments'!$B$5:$B$205,0)) -> 45807 | D40: Seed - SVA | E40: Workforce | F40: =INDEX('Statement of Investments'!$L$5:$L$205,MATCH('Investment Characteristics'!$B40,'Statement of Investments'!$B$5:$B$205,0)) -> 250000 | G40: SV | H40: =F40/I40 -> 0.0071428571 | I40: 35000000 | K40: =B40 -> Clasp | L40: Seed | M40: 0.0071428571 | O40: =I40 -> 35000000 | P40: =IFERROR(ROUND(S40/M40,-5),0) -> 35000000 | Q40: =O40 -> 35000000 | R40: =+Q40 -> 35000000 | S40: =INDEX('Statement of Investments'!$L$5:$L$205,MATCH(B40,'Statement of Investments'!$E$5:$E$205,0)) -> 250000 | U40: =INDEX('Statement of Investments'!$O$5:$O$205,MATCH(B40,'Statement of Investments'!$E$5:$E$205,0)) -> 250000 | V40: =U40/S40 -> 1 | X40: CH | Y40: =+$Y$1/M40/10^6 -> 20020
B41: Sunny Health | C41: =INDEX('Statement of Investments'!$C$5:$C$205,MATCH('Investment Characteristics'!$B41,'Statement of Investments'!$B$5:$B$205,0)) -> 45806 | D41: Seed - SVA | E41: Healthtech | F41: =INDEX('Statement of Investments'!$L$5:$L$205,MATCH('Investment Characteristics'!$B41,'Statement of Investments'!$B$5:$B$205,0)) -> 50000 | G41: SV | H41: =F41/I41 -> 0.003125 | I41: 16000000 | K41: =B41 -> Sunny Health | L41: Seed | M41: 0.003125 | O41: =I41 -> 16000000 | P41: =IFERROR(ROUND(S41/M41,-5),0) -> 16000000 | Q41: =O41 -> 16000000 | R41: =+Q41 -> 16000000 | S41: =INDEX('Statement of Investments'!$L$5:$L$205,MATCH(B41,'Statement of Investments'!$E$5:$E$205,0)) -> 50000 | U41: =INDEX('Statement of Investments'!$O$5:$O$205,MATCH(B41,'Statement of Investments'!$E$5:$E$205,0)) -> 50000 | V41: =U41/S41 -> 1 | X41: RP | Y41: =+$Y$1/M41/10^6 -> 45760
B42: Outro Health | C42: =INDEX('Statement of Investments'!$C$5:$C$205,MATCH('Investment Characteristics'!$B42,'Statement of Investments'!$B$5:$B$205,0)) -> 45806 | D42: Seed - SVA | E42: Healthtech | F42: =INDEX('Statement of Investments'!$L$5:$L$205,MATCH('Investment Characteristics'!$B42,'Statement of Investments'!$B$5:$B$205,0)) -> 250000 | G42: SV | H42: =F42/I42 -> 0.025 | I42: 10000000 | K42: =B42 -> Outro Health | L42: Seed | M42: 0.025 | O42: =I42 -> 10000000 | P42: =IFERROR(ROUND(S42/M42,-5),0) -> 10000000 | Q42: =O42 -> 10000000 | R42: =+Q42 -> 10000000 | S42: =INDEX('Statement of Investments'!$L$5:$L$205,MATCH(B42,'Statement of Investments'!$E$5:$E$205,0)) -> 250000 | U42: =INDEX('Statement of Investments'!$O$5:$O$205,MATCH(B42,'Statement of Investments'!$E$5:$E$205,0)) -> 250000 | V42: =U42/S42 -> 1 | X42: ABG | Y42: =+$Y$1/M42/10^6 -> 5720
B43: TrueClaim | C43: =INDEX('Statement of Investments'!$C$5:$C$205,MATCH('Investment Characteristics'!$B43,'Statement of Investments'!$B$5:$B$205,0)) -> 45924 | D43: Seed - SVA | E43: Healthtech | F43: =INDEX('Statement of Investments'!$L$5:$L$205,MATCH('Investment Characteristics'!$B43,'Statement of Investments'!$B$5:$B$205,0)) -> 250000 | G43: SV | H43: =F43/I43 -> 0.010416667 | I43: 24000000 | K43: TrueClaim | L43: Seed | M43: 0.010416667 | O43: =I43 -> 24000000 | P43: =IFERROR(ROUND(S43/M43,-5),0) -> 24000000 | Q43: =O43 -> 24000000 | R43: =+Q43 -> 24000000 | S43: =INDEX('Statement of Investments'!$L$5:$L$205,MATCH(B43,'Statement of Investments'!$E$5:$E$205,0)) -> 250000 | U43: =INDEX('Statement of Investments'!$O$5:$O$205,MATCH(B43,'Statement of Investments'!$E$5:$E$205,0)) -> 250000 | V43: =U43/S43 -> 1 | Y43: =+$Y$1/M43/10^6 -> 13728
B44: Andel | C44: =INDEX('Statement of Investments'!$C$5:$C$205,MATCH('Investment Characteristics'!$B44,'Statement of Investments'!$B$5:$B$205,0)) -> 45924 | D44: Seed - SVA | E44: Healthtech | F44: =INDEX('Statement of Investments'!$L$5:$L$205,MATCH('Investment Characteristics'!$B44,'Statement of Investments'!$B$5:$B$205,0)) -> 250000 | G44: SV | H44: =F44/I44 -> 0.011111111 | I44: 22500000 | K44: Andel | L44: Seed | M44: 0.011111111 | O44: =I44 -> 22500000 | P44: =IFERROR(ROUND(S44/M44,-5),0) -> 22500000 | Q44: =O44 -> 22500000 | R44: =+Q44 -> 22500000 | S44: =INDEX('Statement of Investments'!$L$5:$L$205,MATCH(B44,'Statement of Investments'!$E$5:$E$205,0)) -> 250000 | U44: =INDEX('Statement of Investments'!$O$5:$O$205,MATCH(B44,'Statement of Investments'!$E$5:$E$205,0)) -> 250000 | V44: =U44/S44 -> 1 | Y44: =+$Y$1/M44/10^6 -> 12870
B45: Second Door | C45: =INDEX('Statement of Investments'!$C$5:$C$205,MATCH('Investment Characteristics'!$B45,'Statement of Investments'!$B$5:$B$205,0)) -> 45924 | D45: Seed - SVA | E45: Healthtech | F45: =INDEX('Statement of Investments'!$L$5:$L$205,MATCH('Investment Characteristics'!$B45,'Statement of Investments'!$B$5:$B$205,0)) -> 250000 | G45: SV | H45: =F45/I45 -> 0.017857143 | I45: 14000000 | K45: Second Door | L45: Seed | M45: 0.017857143 | O45: =I45 -> 14000000 | P45: =IFERROR(ROUND(S45/M45,-5),0) -> 14000000 | Q45: =O45 -> 14000000 | R45: =+Q45 -> 14000000 | S45: =INDEX('Statement of Investments'!$L$5:$L$205,MATCH(B45,'Statement of Investments'!$E$5:$E$205,0)) -> 250000 | U45: =INDEX('Statement of Investments'!$O$5:$O$205,MATCH(B45,'Statement of Investments'!$E$5:$E$205,0)) -> 250000 | V45: =U45/S45 -> 1 | Y45: =+$Y$1/M45/10^6 -> 8008
P51: =5/80 -> 0.0625
P52: =1780000/3 -> 593333.33
P53: =4000000/P52 -> 6.741573
B54: Fund III Sector Summary | O54: =4/120 -> 0.033333333
C55: Workforce | D55: Healthtech | E55: Financial | F55: Total | O55: =O54*5000000 -> 166666.67
B56: Deals:
B57: # of Deals | C57: =COUNTIF($E$4:$E$42,C$55) -> 10 | D57: =COUNTIF($E$4:$E$42,D$55) -> 10 | E57: =COUNTIF($E$4:$E$33,E$55) -> 6 | F57: =SUM(C57:E57) -> 26
B58: % of Deals | C58: =C57/$F$57 -> 0.38461538 | D58: =D57/$F$57 -> 0.38461538 | E58: =E57/$F$57 -> 0.23076923 | F58: =F57/$F$57 -> 1
B60: Initial Investment | C60: =SUMIF($E$4:$E$33,C$55,$F$4:$F$33) -> 26714870 | D60: =SUMIF($E$4:$E$33,D$55,$F$4:$F$33) -> 19909995 | E60: =SUMIF($E$4:$E$33,E$55,$F$4:$F$33) -> 16249998 | F60: =SUM(C60:E60) -> 62874862
B61: % of Invested Cap | C61: =C60/$F$60 -> 0.42488951 | D61: =D60/$F$60 -> 0.31666065 | E61: =E60/$F$60 -> 0.25844984 | F61: =F60/$F$60 -> 1
B62: Current Investment | C62: =SUMIF($E$4:$E$30,C$55,$S$4:$S$30) -> 30592904 | D62: =SUMIF($E$4:$E$30,D$55,$S$4:$S$30) -> 29120904 | E62: =SUMIF($E$4:$E$29,E$55,$S$4:$S$29) -> 19249996 | F62: =SUM(C62:E62) -> 78963804
B63: % of Invested Cap | C63: =C62/$F$62 -> 0.38742946 | D63: =D62/$F$62 -> 0.36878801 | E63: =E62/$F$62 -> 0.24378253 | F63: =F62/$F$62 -> 1
B64: Current Mark
B65: Total Value | C65: =SUMIF($E$4:$E$33,C$55,$U$4:$U$33) -> 33824153 | D65: =SUMIF($E$4:$E$33,D$55,$U$4:$U$33) -> 47252644 | E65: =SUMIF($E$4:$E$33,E$55,$U$4:$U$33) -> 19662932 | F65: =SUM(C65:E65) -> 1.0073973e+08
B66: MOIC | C66: =C65/C62 -> 1.1056209 | D66: =D65/D62 -> 1.6226366 | E66: =E65/E62 -> 1.0214512 | F66: =F65/F62 -> 1.275771
B67: Average Investment:
B68: Initial Avg. Inv. | C68: =AVERAGEIF($E$4:$E$33,C$55,$F$4:$F$33) -> 2968318.8 | D68: =AVERAGEIF($E$4:$E$33,D$55,$F$4:$F$33) -> 2488749.3 | E68: =AVERAGEIF($E$4:$E$33,E$55,$F$4:$F$33) -> 2708333 | F68: =F32 -> 2733689.7
B69: Current Avg. Inv. | C69: =AVERAGEIF($E$4:$E$31,C$55,$S$4:$S$31) -> 3399211.6 | D69: =AVERAGEIF($E$4:$E$31,D$55,$S$4:$S$31) -> 3640113 | E69: =AVERAGEIF($E$4:$E$31,E$55,$S$4:$S$31) -> 3208332.6 | F69: =S32 -> 3433208.9
B70: Average Cost:
B71: Initial Avg. Cost | C71: =AVERAGEIF($E$4:$E$33,C$55,$I$4:$I$33) -> 53255556 | D71: =AVERAGEIF($E$4:$E$33,D$55,$I$4:$I$33) -> 54791918 | E71: =AVERAGEIF($E$4:$E$33,E$55,$I$4:$I$33) -> 52461905 | F71: =I32 -> 53582903
B72: Current Avg. Inv. | C72: =AVERAGEIF($E$4:$E$33,C$55,$P$4:$P$33) -> 59933333 | D72: =AVERAGEIF($E$4:$E$33,D$55,$P$4:$P$33) -> 73725000 | E72: =AVERAGEIF($E$4:$E$33,E$55,$P$4:$P$33) -> 55233333 | F72: =P32 -> 63504348
B73: Round
B74: Seed | C74: =COUNTIFS($D$4:$D$33,$B74,$E$4:$E$33,C$55) -> 5 | D74: =COUNTIFS($D$4:$D$33,$B74,$E$4:$E$33,D$55) -> 3 | E74: =COUNTIFS($D$4:$D$33,$B74,$E$4:$E$33,E$55) -> 3 | F74: =SUM(C74:E74) -> 11
B75: A | C75: =COUNTIFS($D$4:$D$33,$B75,$E$4:$E$33,C$55) -> 3 | D75: =COUNTIFS($D$4:$D$33,$B75,$E$4:$E$33,D$55) -> 5 | E75: =COUNTIFS($D$4:$D$33,$B75,$E$4:$E$33,E$55) -> 3 | F75: =SUM(C75:E75) -> 11
B76: B+ | C76: =COUNTIFS($D$4:$D$33,"B",$E$4:$E$33,C$55)+COUNTIFS($D$4:$D$33,"C",$E$4:$E$33,C$55) -> 1 | D76: =COUNTIFS($D$4:$D$33,"B",$E$4:$E$33,D$55)+COUNTIFS($D$4:$D$33,"C",$E$4:$E$33,D$55) -> 0 | E76: =COUNTIFS($D$4:$D$33,"B",$E$4:$E$33,E$55)+COUNTIFS($D$4:$D$33,"C",$E$4:$E$33,E$55) -> 0 | F76: =SUM(C76:E76) -> 1
B79: Fund III Stage Summary
C80: Seed | D80: A | E80: B | F80: Total
B81: Average Investment:
B82: Initial Avg. Inv. | C82: =AVERAGEIF($D$4:$D$31,C$80,$F$4:$F$31) -> 1926136 | D82: =AVERAGEIF($D$4:$D$31,D$80,$F$4:$F$31) -> 3331817.2 | E82: =AVERAGEIFS($F$4:$F$31,$D$4:$D$31,"<>Seed",$D$4:$D$31,"<>A") -> 5037377 | F82: =F32 -> 2733689.7
B83: Current Avg. Inv. | C83: =AVERAGEIF($D$4:$D$31,C$80,$S$4:$S$31) -> 2715252.4 | D83: =AVERAGEIF($D$4:$D$31,D$80,$S$4:$S$31) -> 4005331.9 | E83: =AVERAGEIF($D$4:$D$31,E$80,$S$4:$S$31) -> 5037377 | F83: =S32 -> 3433208.9
B84: Deals
B85: Initial # of Deals | C85: =COUNTIF($D$4:$D$33,C$80) -> 11 | D85: =COUNTIF($D$4:$D$33,D$80) -> 11 | E85: =COUNTIF($D$4:$D$31,"B")+COUNTIF($D$4:$D$31,"C") -> 1 | F85: =SUM(C85:E85) -> 23
B86: % of Deals | C86: =C85/$F$85 -> 0.47826087 | D86: =D85/$F$85 -> 0.47826087 | E86: =E85/$F$85 -> 0.043478261 | F86: =F85/$F$85 -> 1
B87: Current # of Deals | C87: =COUNTIF($L$4:$L$33,C$80) -> 8 | D87: =COUNTIF($L$4:$L$33,D$80) -> 12 | E87: =F85-SUM(C87:D87) -> 3 | F87: =SUM(C87:E87) -> 23
B88: % of Deals | C88: =C87/$F$87 -> 0.34782609 | D88: =D87/$F$87 -> 0.52173913 | E88: =E87/$F$87 -> 0.13043478 | F88: =F87/$F$85 -> 1
B89: Valuation
B90: Initial Avg. Cost | C90: =AVERAGEIF($D$4:$D$31,C$80,$I$4:$I$31) -> 27772727 | D90: =AVERAGEIF($D$4:$D$31,D$80,$I$4:$I$31) -> 71446070 | E90: =AVERAGEIFS($I$4:$I$31,$D$4:$D$31,"<>Seed",$D$4:$D$31,"<>A") -> 141000000 | F90: =I32 -> 53582903 | H90: =1/11 -> 0.090909091 | I90: Series B #
B91: Initial Median Cost | C91: {=MEDIAN(IF($D$4:$D$31=C80,$I$4:$I$31))} -> 30000000 | D91: {=MEDIAN(IF($D$4:$D$31=D80,$I$4:$I$31))} -> 53000000 | E91: =MEDIAN(I13) -> 141000000 | F91: =I33 -> 44000000 | H91: =6/11 -> 0.54545455 | I91: Series A #
B92: Ownership | H92: =4/11 -> 0.36363636 | I92: Seed #
B93: Initial Avg. FD% | C93: =AVERAGEIF($D$4:$D$31,C$80,$H$4:$H$31) -> 0.073582888 | D93: =AVERAGEIF($D$4:$D$31,D$80,$H$4:$H$31) -> 0.053310489 | E93: =AVERAGEIFS($H$4:$H$31,$D$4:$D$31,"<>Seed",$D$4:$D$31,"<>A") -> 0.035726078 | F93: =H32 -> 0.062241445
B94: Initial Median FD% | C94: {=MEDIAN(IF($D$4:$D$31=C$80,$H$4:$H$31))} -> 0.07 | D94: {=MEDIAN(IF($D$4:$D$31=D$80,$H$4:$H$31))} -> 0.053333327 | E94: =MEDIAN(H13) -> 0.035726078 | F94: =H33 -> 0.05999996 | H94: =5/30.3 -> 0.1650165 | I94: Series B $
B95: Invested Capital: | H95: =16.7/30.3 -> 0.55115512 | I95: Series A $
B96: Initial Investment | C96: =SUMIF($D$4:$D$31,C$80,$F$4:$F$31) -> 21187496 | D96: =SUMIF($D$4:$D$31,D$80,$F$4:$F$31) -> 36649990 | E96: =SUMIF($D$4:$D$31,"B",$F$4:$F$31) -> 5037377 | F96: =SUM(C96:E96) -> 62874862 | H96: =8.6/30.3 -> 0.28382838 | I96: Seed $
C97: =C96/$F$96 -> 0.3369788 | D97: =D96/$F$96 -> 0.58290369 | E97: =E96/$F$96 -> 0.080117503
B98: Current Investment | C98: =SUMIF($L$4:$L$31,C$80,$S$4:$S$31) -> 17117778 | D98: =SUMIF($L$4:$L$31,D$80,$S$4:$S$31) -> 44889993 | E98: =SUMIF($L$4:$L$31,E$80,$S$4:$S$31) -> 16956033 | F98: =SUM(C98:E98) -> 78963804 | H98: =11.4/30.3 -> 0.37623762 | I98: Fintech $
C99: =C98/$F$98 -> 0.21678006 | D99: =D98/$F$98 -> 0.56848823 | E99: =E98/$F$98 -> 0.21473171 | H99: =11.2/30.3 -> 0.36963696 | I99: Healthcare $
B100: Current Valuation:
B101: Valuation | C101: =SUMIF($D$4:$D$31,C$80,$U$4:$U$31) -> 39648983 | D101: =SUMIF($D$4:$D$31,D$80,$U$4:$U$31) -> 56053369 | E101: =SUMIF($D$4:$D$31,E$80,$U$4:$U$31) -> 5037377 | F101: =SUM(C101:E101) -> 1.0073973e+08
B102: Current MOIC | C102: =C101/C98 -> 2.3162459 | D102: =D101/D98 -> 1.2486829 | E102: =E101/E98 -> 0.29708465 | F102: =F101/F98 -> 1.275771
B103: Avg step up | C103: =C101/F101 -> 0.39357842 | D103: =D101/F101 -> 0.5564177 | E103: =E101/F101 -> 0.050003877 | H103: =7.7/30.3 -> 0.25412541 | I103: Workforce $
C105: =SUMIF($D$4:$D$31,C$80,$S$4:$S$31) -> 29867776 | D105: =SUMIF($D$4:$D$31,D$80,$S$4:$S$31) -> 44058651 | E105: =SUMIF($D$4:$D$31,E$80,$S$4:$S$31)+S10 -> 9589575.8 | F105: =SUM(C105:E105) -> 83516003
C106: =C105/$F$105 -> 0.35762938 | D106: =D105/$F$105 -> 0.52754741 | E106: =E105/$F$105 -> 0.11482321
F108: =2/50 -> 0.04
C110: `

Sheet Portfolio Construction
D1: =20600000 -> 20600000 | F1: 73000000
D2: Fund I | F2: Fund II | G2: % change
B3: Seed | C3: # of Deals | D3: 14 | F3: ='Investment Characteristics'!C85 -> 11 | G3: =F3/D3-1 -> -0.21428571
C4: % of Portfolio | D4: =D3/$D$30 -> 0.5 | F4: =F3/$F$30 -> 0.47826087 | G4: =F4/D4-1 -> -0.043478261
C5: Avg. Initital Inv. | D5: 258412.48 | F5: ='Investment Characteristics'!C82 -> 1926136 | G5: =F5/D5-1 -> 6.4537266
C6: Inv. % of Fund Size | D6: =D5/$D$1 -> 0.012544295 | F6: =F5/$F$1 -> 0.026385424 | G6: =F6/D6-1 -> 1.1033804
C7: Median FD% | D7: 0.0104 | F7: ='Investment Characteristics'!C94 -> 0.07 | G7: =F7/D7-1 -> 5.7307692
C8: Avg. FD% | D8: 0.014 | F8: ='Investment Characteristics'!C93 -> 0.073582888 | G8: =F8/D8-1 -> 4.2559206
C9: Median Valuation | D9: 16000000 | F9: ='Investment Characteristics'!C91 -> 30000000 | G9: =F9/D9-1 -> 0.875
C10: Avg. Valuation | D10: 16642857 | F10: ='Investment Characteristics'!C90 -> 27772727 | G10: =F10/D10-1 -> 0.66874756
B12: A | C12: # of Deals | D12: 7 | F12: ='Investment Characteristics'!D85 -> 11 | G12: =F12/D12-1 -> 0.57142857
C13: % of Portfolio | D13: =D12/$D$30 -> 0.25 | F13: =F12/$F$30 -> 0.47826087 | G13: =F13/D13-1 -> 0.91304348
C14: Avg. Initital Inv. | D14: 492857.33 | F14: ='Investment Characteristics'!D82 -> 3331817.2 | G14: =F14/D14-1 -> 5.7602064
C15: Inv. % of Fund Size | D15: =D14/D1 -> 0.023925113 | F15: =F14/F1 -> 0.045641332 | G15: =F15/D15-1 -> 0.90767467
C16: Median FD% | D16: 0.0079999296 | F16: ='Investment Characteristics'!D94 -> 0.053333327 | G16: =F16/D16-1 -> 5.6667245
C17: Avg. FD% | D17: 0.0084 | F17: ='Investment Characteristics'!D93 -> 0.053310489 | G17: =F17/D17-1 -> 5.3464868
C18: Median Valuation | D18: 39000000 | F18: ='Investment Characteristics'!D91 -> 53000000 | G18: =F18/D18-1 -> 0.35897436
C19: Avg. Valuation | D19: 62571429 | F19: ='Investment Characteristics'!D90 -> 71446070 | G19: =F19/D19-1 -> 0.14183217
B21: B+ | C21: # of Deals | D21: 7 | F21: ='Investment Characteristics'!E85 -> 1 | G21: =F21/D21-1 -> -0.85714286
C22: % of Portfolio | D22: =D21/$D$30 -> 0.25 | F22: =F21/$F$30 -> 0.043478261 | G22: =F22/D22-1 -> -0.82608696
C23: Avg. Initital Inv. | D23: 611474.83 | F23: ='Investment Characteristics'!E82 -> 5037377 | G23: =F23/D23-1 -> 7.2380775
C24: Inv. % of Fund Size | D24: =D23/D1 -> 0.029683244 | F24: =F23/F1 -> 0.069005164 | G24: =F24/D24-1 -> 1.3247178
C25: Median FD% | D25: 0.004370656 | F25: ='Investment Characteristics'!E94 -> 0.035726078 | G25: =F25/D25-1 -> 7.1740768
C26: Avg. FD% | D26: 0.005 | F26: ='Investment Characteristics'!E93 -> 0.035726078 | G26: =F26/D26-1 -> 6.1452156
C27: Median Valuation | D27: 137000000 | F27: ='Investment Characteristics'!E91 -> 141000000 | G27: =F27/D27-1 -> 0.02919708
C28: Avg. Valuation | D28: 1.4014286e+08 | F28: ='Investment Characteristics'!E90 -> 141000000 | G28: =F28/D28-1 -> 0.006116208
B30: Total | C30: # of Deals | D30: 28 | F30: ='Investment Characteristics'!F85 -> 23 | G30: =F30/D30-1 -> -0.17857143
C31: Avg. Initital Inv. | D31: 405289.28 | F31: ='Investment Characteristics'!F82 -> 2733689.7 | G31: =F31/D31-1 -> 5.7450333
C32: Inv. % of Fund Size | D32: =D31/D1 -> 0.019674237 | F32: =F31/F1 -> 0.037447804 | G32: =F32/D32-1 -> 0.90339295
C33: Median FD% | D33: 0.0071 | F33: ='Investment Characteristics'!H33 -> 0.05999996 | G33: =F33/D33-1 -> 7.4506986
C34: Avg. FD% | D34: 0.0091946146 | F34: ='Investment Characteristics'!H32 -> 0.062241445 | G34: =F34/D34-1 -> 5.769337
C35: Median Valuation | D35: 25500000 | F35: ='Investment Characteristics'!I33 -> 44000000 | G35: =F35/D35-1 -> 0.7254902
C36: Avg. Valuation | D36: 59000000 | F36: ='Investment Characteristics'!I32 -> 53582903 | G36: =F36/D36-1 -> -0.091815203

Sheet Investment Rollover
B2: Cost | H2: Carrying Value
B3: Company | C3: 6/30/2025 | D3: Additions | E3: Dispositions | F3: 9/30/2025 | H3: Company | I3: =C3 -> 6/30/2025 | J3: Additions | K3: Dispositions | L3: Net Writeup | M3: =F3 -> 9/30/2025 | N3: MOIC
B4: Laguna Health | C4: 4999999.7 | D4: =IF(F4>C4,F4-C4,0) -> 0 | E4: =IF(F4<C4,F4-C4,0) -> 0 | F4: =INDEX('Statement of Investments'!$L$5:$L$205,MATCH('Investment Rollover'!$B4,'Statement of Investments'!$E$5:$E$205,0)) -> 4999999.7 | H4: =B4 -> Laguna Health | I4: 4999999.7 | J4: =D4 -> 0 | K4: =E4 -> 0 | L4: =M4-SUM(I4:K4) -> 0 | M4: =INDEX('Statement of Investments'!$O$5:$O$205,MATCH('Investment Rollover'!$H4,'Statement of Investments'!$E$5:$E$205,0)) -> 4999999.7 | N4: =M4/F4 -> 1
B5: Stepful | C5: 7878030.5 | D5: =IF(F5>C5,F5-C5,0) -> 0 | E5: =IF(F5<C5,F5-C5,0) -> 0 | F5: =INDEX('Statement of Investments'!$L$5:$L$205,MATCH('Investment Rollover'!$B5,'Statement of Investments'!$E$5:$E$205,0)) -> 7878030.5 | H5: =B5 -> Stepful | I5: 13609280 | J5: =D5 -> 0 | K5: =E5 -> 0 | L5: =M5-SUM(I5:K5) -> 0 | M5: =INDEX('Statement of Investments'!$O$5:$O$205,MATCH('Investment Rollover'!$H5,'Statement of Investments'!$E$5:$E$205,0)) -> 13609280 | N5: =M5/F5 -> 1.7274977
B6: Summer | C6: 3250000 | D6: =IF(F6>C6,F6-C6,0) -> 0 | E6: =IF(F6<C6,F6-C6,0) -> 0 | F6: =INDEX('Statement of Investments'!$L$5:$L$205,MATCH('Investment Rollover'!$B6,'Statement of Investments'!$E$5:$E$205,0)) -> 3250000 | H6: =B6 -> Summer | I6: 3250000 | J6: =D6 -> 0 | K6: =E6 -> 0 | L6: =M6-SUM(I6:K6) -> 0 | M6: =INDEX('Statement of Investments'!$O$5:$O$205,MATCH('Investment Rollover'!$H6,'Statement of Investments'!$E$5:$E$205,0)) -> 3250000 | N6: =M6/F6 -> 1
B7: Wagmo | C7: 1499998 | D7: =IF(F7>C7,F7-C7,0) -> 0 | E7: =IF(F7<C7,F7-C7,0) -> 0 | F7: =INDEX('Statement of Investments'!$L$5:$L$205,MATCH('Investment Rollover'!$B7,'Statement of Investments'!$E$5:$E$205,0)) -> 1499998 | H7: =B7 -> Wagmo | I7: 1499998 | J7: =D7 -> 0 | K7: =E7 -> 0 | L7: =M7-SUM(I7:K7) -> 0 | M7: =INDEX('Statement of Investments'!$O$5:$O$205,MATCH('Investment Rollover'!$H7,'Statement of Investments'!$E$5:$E$205,0)) -> 1499998 | N7: =M7/F7 -> 1
B8: Kubera | C8: 399999.2 | D8: =IF(F8>C8,F8-C8,0) -> 128083.47 | E8: =IF(F8<C8,F8-C8,0) -> 0 | F8: =INDEX('Statement of Investments'!$L$5:$L$205,MATCH('Investment Rollover'!$B8,'Statement of Investments'!$E$5:$E$205,0)) -> 528082.67 | H8: =B8 -> Kubera | I8: 399999.2 | J8: =D8 -> 128083.47 | K8: =E8 -> 0 | L8: =M8-SUM(I8:K8) -> 483330.52 | M8: =INDEX('Statement of Investments'!$O$5:$O$205,MATCH('Investment Rollover'!$H8,'Statement of Investments'!$E$5:$E$205,0)) -> 1011413.2 | N8: =M8/F8 -> 1.9152554
B9: Salsa | C9: 5499997.9 | D9: =IF(F9>C9,F9-C9,0) -> 0 | E9: =IF(F9<C9,F9-C9,0) -> 0 | F9: =INDEX('Statement of Investments'!$L$5:$L$205,MATCH('Investment Rollover'!$B9,'Statement of Investments'!$E$5:$E$205,0)) -> 5499997.9 | H9: =B9 -> Salsa | I9: 5499997.9 | J9: =D9 -> 0 | K9: =E9 -> 0 | L9: =M9-SUM(I9:K9) -> 412936.17 | M9: =INDEX('Statement of Investments'!$O$5:$O$205,MATCH('Investment Rollover'!$H9,'Statement of Investments'!$E$5:$E$205,0)) -> 5912934 | N9: =M9/F9 -> 1.0750793
B10: Solara | C10: 1999999.8 | D10: =IF(F10>C10,F10-C10,0) -> 2552199 | E10: =IF(F10<C10,F10-C10,0) -> 0 | F10: =INDEX('Statement of Investments'!$L$5:$L$205,MATCH('Investment Rollover'!$B10,'Statement of Investments'!$E$5:$E$205,0)) -> 4552198.8 | H10: =B10 -> Solara | I10: 1999999.8 | J10: =D10 -> 2552199 | K10: =E10 -> 0 | L10: =M10-SUM(I10:K10) -> 744012.43 | M10: =INDEX('Statement of Investments'!$O$5:$O$205,MATCH('Investment Rollover'!$H10,'Statement of Investments'!$E$5:$E$205,0)) -> 5296211.2 | N10: =M10/F10 -> 1.1634402
B11: Hireguide | C11: 3000000 | D11: =IF(F11>C11,F11-C11,0) -> 0 | E11: =IF(F11<C11,F11-C11,0) -> 0 | F11: =INDEX('Statement of Investments'!$L$5:$L$205,MATCH('Investment Rollover'!$B11,'Statement of Investments'!$E$5:$E$205,0)) -> 3000000 | H11: =B11 -> Hireguide | I11: 3000000 | J11: =D11 -> 0 | K11: =E11 -> 0 | L11: =M11-SUM(I11:K11) -> -2500000 | M11: =INDEX('Statement of Investments'!$O$5:$O$205,MATCH('Investment Rollover'!$H11,'Statement of Investments'!$E$5:$E$205,0)) -> 500000 | N11: =M11/F11 -> 0.16666667
B12: Take2 AI | C12: 700000 | D12: =IF(F12>C12,F12-C12,0) -> 0 | E12: =IF(F12<C12,F12-C12,0) -> 0 | F12: =INDEX('Statement of Investments'!$L$5:$L$205,MATCH('Investment Rollover'!$B12,'Statement of Investments'!$E$5:$E$205,0)) -> 700000 | H12: =B12 -> Take2 AI | I12: 700000 | J12: =D12 -> 0 | K12: =E12 -> 0 | L12: =M12-SUM(I12:K12) -> 0 | M12: =INDEX('Statement of Investments'!$O$5:$O$205,MATCH('Investment Rollover'!$H12,'Statement of Investments'!$E$5:$E$205,0)) -> 700000 | N12: =M12/F12 -> 1
B13: Techwolf | C13: 5037377 | D13: =IF(F13>C13,F13-C13,0) -> 0 | E13: =IF(F13<C13,F13-C13,0) -> 0 | F13: =INDEX('Statement of Investments'!$L$5:$L$205,MATCH('Investment Rollover'!$B13,'Statement of Investments'!$E$5:$E$205,0)) -> 5037377 | H13: =B13 -> Techwolf | I13: 5037377 | J13: =D13 -> 0 | K13: =E13 -> 0 | L13: =M13-SUM(I13:K13) -> 0 | M13: =INDEX('Statement of Investments'!$O$5:$O$205,MATCH('Investment Rollover'!$H13,'Statement of Investments'!$E$5:$E$205,0)) -> 5037377 | N13: =M13/F13 -> 1
B14: Thatch | C14: 4040625.2 | D14: =IF(F14>C14,F14-C14,0) -> 0 | E14: =IF(F14<C14,F14-C14,0) -> 0 | F14: =INDEX('Statement of Investments'!$L$5:$L$205,MATCH('Investment Rollover'!$B14,'Statement of Investments'!$E$5:$E$205,0)) -> 4040625.2 | H14: =B14 -> Thatch | I14: 10304094 | J14: =D14 -> 0 | K14: =E14 -> 0 | L14: =M14-SUM(I14:K14) -> 0 | M14: =INDEX('Statement of Investments'!$O$5:$O$205,MATCH('Investment Rollover'!$H14,'Statement of Investments'!$E$5:$E$205,0)) -> 10304094 | N14: =M14/F14 -> 2.5501238
B15: Multimodal | C15: 2000000 | D15: =IF(F15>C15,F15-C15,0) -> 0 | E15: =IF(F15<C15,F15-C15,0) -> 0 | F15: =INDEX('Statement of Investments'!$L$5:$L$205,MATCH('Investment Rollover'!$B15,'Statement of Investments'!$E$5:$E$205,0)) -> 2000000 | H15: =B15 -> Multimodal | I15: 2000000 | J15: =D15 -> 0 | K15: =E15 -> 0 | L15: =M15-SUM(I15:K15) -> 0 | M15: =INDEX('Statement of Investments'!$O$5:$O$205,MATCH('Investment Rollover'!$H15,'Statement of Investments'!$E$5:$E$205,0)) -> 2000000 | N15: =M15/F15 -> 1
B16: OneImaging | C16: 1000000 | D16: =IF(F16>C16,F16-C16,0) -> 3000000 | E16: =IF(F16<C16,F16-C16,0) -> 0 | F16: =INDEX('Statement of Investments'!$L$5:$L$205,MATCH('Investment Rollover'!$B16,'Statement of Investments'!$E$5:$E$205,0)) -> 4000000 | H16: =B16 -> OneImaging | I16: =11640891.7926+36 -> 11640928 | J16: =D16 -> 3000000 | K16: =E16 -> 0 | L16: =M16-SUM(I16:K16) -> 0.39419788 | M16: =INDEX('Statement of Investments'!$O$5:$O$205,MATCH('Investment Rollover'!$H16,'Statement of Investments'!$E$5:$E$205,0)) -> 14640928 | N16: =M16/F16 -> 3.660232
B17: ExceedsAI | C17: 1187499.8 | D17: =IF(F17>C17,F17-C17,0) -> 0 | E17: =IF(F17<C17,F17-C17,0) -> 0 | F17: =INDEX('Statement of Investments'!$L$5:$L$205,MATCH('Investment Rollover'!$B17,'Statement of Investments'!$E$5:$E$205,0)) -> 1187499.8 | H17: =B17 -> ExceedsAI | I17: 1187499.8 | J17: =D17 -> 0 | K17: =E17 -> 0 | L17: =M17-SUM(I17:K17) -> 0 | M17: =INDEX('Statement of Investments'!$O$5:$O$205,MATCH('Investment Rollover'!$H17,'Statement of Investments'!$E$5:$E$205,0)) -> 1187499.8 | N17: =M17/F17 -> 1
B18: Sully.AI | C18: 3999999.5 | D18: =IF(F18>C18,F18-C18,0) -> 0 | E18: =IF(F18<C18,F18-C18,0) -> 0 | F18: =INDEX('Statement of Investments'!$L$5:$L$205,MATCH('Investment Rollover'!$B18,'Statement of Investments'!$E$5:$E$205,0)) -> 3999999.5 | H18: =B18 -> Sully.AI | I18: 3999999.5 | J18: =D18 -> 0 | K18: =E18 -> 0 | L18: =M18-SUM(I18:K18) -> 0 | M18: =INDEX('Statement of Investments'!$O$5:$O$205,MATCH('Investment Rollover'!$H18,'Statement of Investments'!$E$5:$E$205,0)) -> 3999999.5 | N18: =M18/F18 -> 1
B19: Athena.AI | C19: 3150000 | D19: =IF(F19>C19,F19-C19,0) -> 0 | E19: =IF(F19<C19,F19-C19,0) -> 0 | F19: =INDEX('Statement of Investments'!$L$5:$L$205,MATCH('Investment Rollover'!$B19,'Statement of Investments'!$E$5:$E$205,0)) -> 3150000 | H19: Athena.AI | I19: 3150000 | J19: =D19 -> 0 | K19: =E19 -> 0 | L19: =M19-SUM(I19:K19) -> 0 | M19: =INDEX('Statement of Investments'!$O$5:$O$205,MATCH('Investment Rollover'!$H19,'Statement of Investments'!$E$5:$E$205,0)) -> 3150000 | N19: =M19/F19 -> 1
B20: Onboarded | C20: 5000000 | D20: =IF(F20>C20,F20-C20,0) -> 0 | E20: =IF(F20<C20,F20-C20,0) -> 0 | F20: =INDEX('Statement of Investments'!$L$5:$L$205,MATCH('Investment Rollover'!$B20,'Statement of Investments'!$E$5:$E$205,0)) -> 5000000 | H20: Onboarded | I20: 5000000 | J20: =D20 -> 0 | K20: =E20 -> 0 | L20: =M20-SUM(I20:K20) -> 0 | M20: =INDEX('Statement of Investments'!$O$5:$O$205,MATCH('Investment Rollover'!$H20,'Statement of Investments'!$E$5:$E$205,0)) -> 5000000 | N20: =M20/F20 -> 1
B21: PenguinAI | C21: 4000000 | D21: =IF(F21>C21,F21-C21,0) -> 0 | E21: =IF(F21<C21,F21-C21,0) -> 0 | F21: =INDEX('Statement of Investments'!$L$5:$L$205,MATCH('Investment Rollover'!$B21,'Statement of Investments'!$E$5:$E$205,0)) -> 4000000 | H21: PenguinAI | I21: 4000000 | J21: =D21 -> 0 | K21: =E21 -> 0 | L21: =M21-SUM(I21:K21) -> 0 | M21: =INDEX('Statement of Investments'!$O$5:$O$205,MATCH('Investment Rollover'!$H21,'Statement of Investments'!$E$5:$E$205,0)) -> 4000000 | N21: =M21/F21 -> 1
B22: Clasp | C22: 250000 | D22: =IF(F22>C22,F22-C22,0) -> 0 | E22: =IF(F22<C22,F22-C22,0) -> 0 | F22: =INDEX('Statement of Investments'!$L$5:$L$205,MATCH('Investment Rollover'!$B22,'Statement of Investments'!$E$5:$E$205,0)) -> 250000 | H22: Clasp | I22: 250000 | J22: =D22 -> 0 | K22: =E22 -> 0 | L22: =M22-SUM(I22:K22) -> 0 | M22: =INDEX('Statement of Investments'!$O$5:$O$205,MATCH('Investment Rollover'!$H22,'Statement of Investments'!$E$5:$E$205,0)) -> 250000 | N22: =M22/F22 -> 1
B23: Sunny Health | C23: 50000 | D23: =IF(F23>C23,F23-C23,0) -> 0 | E23: =IF(F23<C23,F23-C23,0) -> 0 | F23: =INDEX('Statement of Investments'!$L$5:$L$205,MATCH('Investment Rollover'!$B23,'Statement of Investments'!$E$5:$E$205,0)) -> 50000 | H23: Sunny Health | I23: 50000 | J23: =D23 -> 0 | K23: =E23 -> 0 | L23: =M23-SUM(I23:K23) -> 0 | M23: =INDEX('Statement of Investments'!$O$5:$O$205,MATCH('Investment Rollover'!$H23,'Statement of Investments'!$E$5:$E$205,0)) -> 50000 | N23: =M23/F23 -> 1
B24: Outro Health | C24: 250000 | D24: =IF(F24>C24,F24-C24,0) -> 0 | E24: =IF(F24<C24,F24-C24,0) -> 0 | F24: =INDEX('Statement of Investments'!$L$5:$L$205,MATCH('Investment Rollover'!$B24,'Statement of Investments'!$E$5:$E$205,0)) -> 250000 | H24: Outro Health | I24: 250000 | J24: =D24 -> 0 | K24: =E24 -> 0 | L24: =M24-SUM(I24:K24) -> 0 | M24: =INDEX('Statement of Investments'!$O$5:$O$205,MATCH('Investment Rollover'!$H24,'Statement of Investments'!$E$5:$E$205,0)) -> 250000 | N24: =M24/F24 -> 1
B25: Tezi | C25: 0 | D25: =IF(F25>C25,F25-C25,0) -> 1999997 | E25: =IF(F25<C25,F25-C25,0) -> 0 | F25: =INDEX('Statement of Investments'!$L$5:$L$205,MATCH('Investment Rollover'!$B25,'Statement of Investments'!$E$5:$E$205,0)) -> 1999997 | H25: Tezi | I25: 0 | J25: =D25 -> 1999997 | K25: =E25 -> 0 | L25: =M25-SUM(I25:K25) -> 0 | M25: =INDEX('Statement of Investments'!$O$5:$O$205,MATCH('Investment Rollover'!$H25,'Statement of Investments'!$E$5:$E$205,0)) -> 1999997 | N25: =M25/F25 -> 1
B26: Trial Library | C26: 0 | D26: =IF(F26>C26,F26-C26,0) -> 2999998 | E26: =IF(F26<C26,F26-C26,0) -> 0 | F26: =INDEX('Statement of Investments'!$L$5:$L$205,MATCH('Investment Rollover'!$B26,'Statement of Investments'!$E$5:$E$205,0)) -> 2999998 | H26: Trial Library | I26: 0 | J26: =D26 -> 2999998 | K26: =E26 -> 0 | L26: =M26-SUM(I26:K26) -> 0 | M26: =INDEX('Statement of Investments'!$O$5:$O$205,MATCH('Investment Rollover'!$H26,'Statement of Investments'!$E$5:$E$205,0)) -> 2999998 | N26: =M26/F26 -> 1
B27: TrueClaim | C27: 0 | D27: =IF(F27>C27,F27-C27,0) -> 250000 | E27: =IF(F27<C27,F27-C27,0) -> 0 | F27: =INDEX('Statement of Investments'!$L$5:$L$205,MATCH('Investment Rollover'!$B27,'Statement of Investments'!$E$5:$E$205,0)) -> 250000 | H27: TrueClaim | I27: 0 | J27: =D27 -> 250000 | K27: =E27 -> 0 | L27: =M27-SUM(I27:K27) -> 0 | M27: =INDEX('Statement of Investments'!$O$5:$O$205,MATCH('Investment Rollover'!$H27,'Statement of Investments'!$E$5:$E$205,0)) -> 250000 | N27: =M27/F27 -> 1
B28: Andel | C28: 0 | D28: =IF(F28>C28,F28-C28,0) -> 250000 | E28: =IF(F28<C28,F28-C28,0) -> 0 | F28: =INDEX('Statement of Investments'!$L$5:$L$205,MATCH('Investment Rollover'!$B28,'Statement of Investments'!$E$5:$E$205,0)) -> 250000 | H28: Andel | I28: 0 | J28: =D28 -> 250000 | K28: =E28 -> 0 | L28: =M28-SUM(I28:K28) -> 0 | M28: =INDEX('Statement of Investments'!$O$5:$O$205,MATCH('Investment Rollover'!$H28,'Statement of Investments'!$E$5:$E$205,0)) -> 250000 | N28: =M28/F28 -> 1
B29: Second Door | C29: 0 | D29: =IF(F29>C29,F29-C29,0) -> 250000 | E29: =IF(F29<C29,F29-C29,0) -> 0 | F29: =INDEX('Statement of Investments'!$L$5:$L$205,MATCH('Investment Rollover'!$B29,'Statement of Investments'!$E$5:$E$205,0)) -> 250000 | H29: Second Door | I29: 0 | J29: =D29 -> 250000 | K29: =E29 -> 0 | L29: =M29-SUM(I29:K29) -> 0 | M29: =INDEX('Statement of Investments'!$O$5:$O$205,MATCH('Investment Rollover'!$H29,'Statement of Investments'!$E$5:$E$205,0)) -> 250000 | N29: =M29/F29 -> 1
B32: Unrealized Total | C32: =SUM(C4:C31) -> 59193527 | D32: =SUM(D4:D31) -> 11430277 | E32: =SUM(E4:E31) -> 0 | F32: =SUM(F4:F31) -> 70623804 | H32: Unrealized Total | I32: =SUM(I4:I31) -> 81829172 | J32: =SUM(J4:J31) -> 11430277 | K32: =SUM(K4:K31) -> 0 | L32: =SUM(L4:L31) -> -859720.49 | M32: =SUM(M4:M31) -> 92399729 | N32: =M32/F32 -> 1.3083369
E37: =8/30 -> 0.26666667

Sheet Reserves (2)
B2: Total Fund | C2: Amount | D2: Reserve ratio | E2: % of Inv. Cap | F2: % of Total Fund
B3: Initial Invested | C3: =+H35 -> 39365504 | D3: =+C3/$C$5 -> 0.51576964 | E3: =+C3/$E$6 -> 0.34652732 | F3: =+C3/$F$6 -> 0.27722186 | T3: Partner Allocation
B4: Follow-On + Reserve | C4: =+I35+N35 -> 36958305 | D4: =+C4/$C$5 -> 0.48423036 | E4: =+C4/$E$6 -> 0.32533719 | F4: =+C4/$F$6 -> 0.26026976 | T4: Total
B5: Inv. and Reserved | C5: =+O35 -> 76323809 | D5: =SUM(D3:D4) -> 1 | E5: =+C5/$E$6 -> 0.67186452 | F5: =+C5/$F$6 -> 0.53749161 | U5: Target | V5: Actual | W5: Remaining | X5: %
E6: =+F6*0.8 -> 113600000 | F6: =142*10^6 -> 142000000 | T6: Invested | U6: =70*10^6 -> 70000000 | V6: =+SUM('Reserves (2)'!H35) -> 39365504 | W6: =U6-V6 -> 30634496 | X6: =+V6/U6 -> 0.56236434
N7: Partner Input | Q7: Partner Input | T7: Reserved | U7: =45*10^6 -> 45000000 | V7: =+SUM('Reserves (2)'!I35,'Reserves (2)'!N35) -> 36958305 | W7: =U7-V7 -> 8041694.8 | X7: =+V7/U7 -> 0.82129567
L8: Pro Rata Calc | T8: Total | U8: =SUM(U6:U7) -> 115000000 | V8: =SUM(V6:V7) -> 76323809 | W8: =U8-V8 -> 38676191 | X8: =+V8/U8 -> 0.6636853
H9: Initial | J9: Total | Q9: Timing of | T9: Companies | U9: =+U16+U24+U32+U40 -> 28 | V9: =+V16+V24+V32+V40 -> 16 | W9: =+U9-V9 -> 12 | X9: =+V9/U9 -> 0.57142857
B10: Company | C10: Owner | D10: Current Stage | E10: Ownership | F10: Last Valuation | H10: $ Invested | I10: Follow-Ons | J10: Invested | L10: Round Size | M10: Implied Pro-rata | N10: Reserves | O10: Inv. and Reserved | Q10: Next Round | R10: Last Updated
B11: Laguna Health | C11: =INDEX('Investment Characteristics'!$X$4:$X$31,MATCH('Reserves (2)'!$B11,'Investment Characteristics'!$K$4:$K$31,0)) -> GG | D11: =INDEX('Investment Characteristics'!$L$4:$L$31,MATCH('Reserves (2)'!$B11,'Investment Characteristics'!$K$4:$K$31,0)) -> A | E11: =INDEX('Investment Characteristics'!$M$4:$M$31,MATCH('Reserves (2)'!$B11,'Investment Characteristics'!$K$4:$K$31,0)) -> 0.077934988 | F11: =INDEX('Investment Characteristics'!$Q$4:$Q$31,MATCH('Reserves (2)'!$B11,'Investment Characteristics'!$K$4:$K$31,0)) -> 53000000 | H11: =INDEX('Investment Characteristics'!$F$4:$F$33,MATCH('Reserves (2)'!$B11,'Investment Characteristics'!$B$4:$B$33,0)) -> 3999999.7 | I11: =J11-H11 -> 1000000 | J11: =INDEX('Investment Characteristics'!$S$4:$S$33,MATCH('Reserves (2)'!$B11,'Investment Characteristics'!$B$4:$B$33,0)) -> 4999999.7 | L11: =25*10^6 -> 25000000 | M11: =+L11*E11 -> 1948374.7 | N11: =1*10^6 -> 1000000 | O11: =N11+J11 -> 5999999.7 | Q11: Q4'25 | R11: 45686 | T11: GG
B12: Stepful | C12: =INDEX('Investment Characteristics'!$X$4:$X$31,MATCH('Reserves (2)'!$B12,'Investment Characteristics'!$K$4:$K$31,0)) -> ABG | D12: =INDEX('Investment Characteristics'!$L$4:$L$31,MATCH('Reserves (2)'!$B12,'Investment Characteristics'!$K$4:$K$31,0)) -> B | E12: =INDEX('Investment Characteristics'!$M$4:$M$31,MATCH('Reserves (2)'!$B12,'Investment Characteristics'!$K$4:$K$31,0)) -> 0.052805468 | F12: =INDEX('Investment Characteristics'!$Q$4:$Q$31,MATCH('Reserves (2)'!$B12,'Investment Characteristics'!$K$4:$K$31,0)) -> 261500000 | H12: =INDEX('Investment Characteristics'!$F$4:$F$33,MATCH('Reserves (2)'!$B12,'Investment Characteristics'!$B$4:$B$33,0)) -> 3999995.7 | I12: =J12-H12 -> 3878034.7 | J12: =INDEX('Investment Characteristics'!$S$4:$S$33,MATCH('Reserves (2)'!$B12,'Investment Characteristics'!$B$4:$B$33,0)) -> 7878030.5 | L12: =50*10^6 -> 50000000 | M12: =+L12*E12 -> 2640273.4 | N12: 1000000 | O12: =N12+J12 -> 8878030.5 | Q12: Q1'26 | R12: 45686 | U12: Target | V12: Actual | W12: Remaining | X12: %
B13: Summer | C13: =INDEX('Investment Characteristics'!$X$4:$X$31,MATCH('Reserves (2)'!$B13,'Investment Characteristics'!$K$4:$K$31,0)) -> RP | D13: =INDEX('Investment Characteristics'!$L$4:$L$31,MATCH('Reserves (2)'!$B13,'Investment Characteristics'!$K$4:$K$31,0)) -> A | E13: =INDEX('Investment Characteristics'!$M$4:$M$31,MATCH('Reserves (2)'!$B13,'Investment Characteristics'!$K$4:$K$31,0)) -> 0.11734531 | F13: =INDEX('Investment Characteristics'!$Q$4:$Q$31,MATCH('Reserves (2)'!$B13,'Investment Characteristics'!$K$4:$K$31,0)) -> 41544018 | H13: =INDEX('Investment Characteristics'!$F$4:$F$33,MATCH('Reserves (2)'!$B13,'Investment Characteristics'!$B$4:$B$33,0)) -> 3250000 | I13: =J13-H13 -> 0 | J13: =INDEX('Investment Characteristics'!$S$4:$S$33,MATCH('Reserves (2)'!$B13,'Investment Characteristics'!$B$4:$B$33,0)) -> 3250000 | L13: =20*10^6 -> 20000000 | M13: =+L13*E13 -> 2346906.2 | N13: 1000000 | O13: =N13+J13 -> 4250000 | Q13: Q4'25 | T13: Invested | U13: =20*10^6 -> 20000000 | V13: =+SUMIF('Reserves (2)'!$C$11:$C$34,'Reserves (2)'!T11,'Reserves (2)'!$H$11:$H$34) -> 7640634.5 | W13: =U13-V13 -> 12359366 | X13: =+V13/U13 -> 0.38203172
B14: Wagmo | C14: =INDEX('Investment Characteristics'!$X$4:$X$31,MATCH('Reserves (2)'!$B14,'Investment Characteristics'!$K$4:$K$31,0)) -> CH | D14: =INDEX('Investment Characteristics'!$L$4:$L$31,MATCH('Reserves (2)'!$B14,'Investment Characteristics'!$K$4:$K$31,0)) -> A | E14: =INDEX('Investment Characteristics'!$M$4:$M$31,MATCH('Reserves (2)'!$B14,'Investment Characteristics'!$K$4:$K$31,0)) -> 0.029870094 | F14: =INDEX('Investment Characteristics'!$Q$4:$Q$31,MATCH('Reserves (2)'!$B14,'Investment Characteristics'!$K$4:$K$31,0)) -> 47200000 | H14: =INDEX('Investment Characteristics'!$F$4:$F$33,MATCH('Reserves (2)'!$B14,'Investment Characteristics'!$B$4:$B$33,0)) -> 1499998 | I14: =J14-H14 -> 0 | J14: =INDEX('Investment Characteristics'!$S$4:$S$33,MATCH('Reserves (2)'!$B14,'Investment Characteristics'!$B$4:$B$33,0)) -> 1499998 | L14: 6000000 | M14: =+L14*E14 -> 179220.56 | N14: 500000 | O14: =N14+J14 -> 1999998 | Q14: Q1'25 | R14: 45686 | T14: Reserved | U14: =13*10^6 -> 13000000 | V14: =+SUMIF('Reserves (2)'!$C$11:$C$34,'Reserves (2)'!T11,'Reserves (2)'!$I$11:$I$34)+SUMIF('Reserves (2)'!$C$11:$C$34,'Reserves (2)'!T11,'Reserves (2)'!$N$11:$N$34) -> 9452189.2 | W14: =U14-V14 -> 3547810.8 | X14: =+V14/U14 -> 0.72709147
B15: Kubera | C15: =INDEX('Investment Characteristics'!$X$4:$X$31,MATCH('Reserves (2)'!$B15,'Investment Characteristics'!$K$4:$K$31,0)) -> RP | D15: =INDEX('Investment Characteristics'!$L$4:$L$31,MATCH('Reserves (2)'!$B15,'Investment Characteristics'!$K$4:$K$31,0)) -> Seed | E15: =INDEX('Investment Characteristics'!$M$4:$M$31,MATCH('Reserves (2)'!$B15,'Investment Characteristics'!$K$4:$K$31,0)) -> 0.033713855 | F15: =INDEX('Investment Characteristics'!$Q$4:$Q$31,MATCH('Reserves (2)'!$B15,'Investment Characteristics'!$K$4:$K$31,0)) -> 30000000 | H15: =INDEX('Investment Characteristics'!$F$4:$F$33,MATCH('Reserves (2)'!$B15,'Investment Characteristics'!$B$4:$B$33,0)) -> 399999.2 | I15: =J15-H15 -> 128083.47 | J15: =INDEX('Investment Characteristics'!$S$4:$S$33,MATCH('Reserves (2)'!$B15,'Investment Characteristics'!$B$4:$B$33,0)) -> 528082.67 | L15: =10*10^6 -> 10000000 | M15: =+L15*E15 -> 337138.55 | N15: 1500000 | O15: =N15+J15 -> 2028082.7 | Q15: need update | T15: Total | U15: =SUM(U13:U14) -> 33000000 | V15: =SUM(V13:V14) -> 17092824 | W15: =U15-V15 -> 15907176 | X15: =+V15/U15 -> 0.51796435
B16: Salsa | C16: =INDEX('Investment Characteristics'!$X$4:$X$31,MATCH('Reserves (2)'!$B16,'Investment Characteristics'!$K$4:$K$31,0)) -> CH | D16: =INDEX('Investment Characteristics'!$L$4:$L$31,MATCH('Reserves (2)'!$B16,'Investment Characteristics'!$K$4:$K$31,0)) -> A | E16: =INDEX('Investment Characteristics'!$M$4:$M$31,MATCH('Reserves (2)'!$B16,'Investment Characteristics'!$K$4:$K$31,0)) -> 0.084687403 | F16: =INDEX('Investment Characteristics'!$Q$4:$Q$31,MATCH('Reserves (2)'!$B16,'Investment Characteristics'!$K$4:$K$31,0)) -> 70000000 | H16: =INDEX('Investment Characteristics'!$F$4:$F$33,MATCH('Reserves (2)'!$B16,'Investment Characteristics'!$B$4:$B$33,0)) -> 2500000 | I16: =J16-H16 -> 2999997.9 | J16: =INDEX('Investment Characteristics'!$S$4:$S$33,MATCH('Reserves (2)'!$B16,'Investment Characteristics'!$B$4:$B$33,0)) -> 5499997.9 | L16: 12000000 | M16: =+L16*E16 -> 1016248.8 | N16: =1*10^6 -> 1000000 | O16: =N16+J16 -> 6499997.9 | Q16: Q1'26 | R16: 45730 | T16: Companies | U16: 8 | V16: =+COUNTIF('Reserves (2)'!$C$11:$C$34,'Reserves (2)'!T11) -> 3 | W16: =+U16-V16 -> 5 | X16: =+V16/U16 -> 0.375
B17: Solara | C17: =INDEX('Investment Characteristics'!$X$4:$X$31,MATCH('Reserves (2)'!$B17,'Investment Characteristics'!$K$4:$K$31,0)) -> GG | D17: =INDEX('Investment Characteristics'!$L$4:$L$31,MATCH('Reserves (2)'!$B17,'Investment Characteristics'!$K$4:$K$31,0)) -> Seed | E17: =INDEX('Investment Characteristics'!$M$4:$M$31,MATCH('Reserves (2)'!$B17,'Investment Characteristics'!$K$4:$K$31,0)) -> 0.1309 | F17: =INDEX('Investment Characteristics'!$Q$4:$Q$31,MATCH('Reserves (2)'!$B17,'Investment Characteristics'!$K$4:$K$31,0)) -> 40000000 | H17: =INDEX('Investment Characteristics'!$F$4:$F$33,MATCH('Reserves (2)'!$B17,'Investment Characteristics'!$B$4:$B$33,0)) -> 1999999.8 | I17: =J17-H17 -> 2552199 | J17: =INDEX('Investment Characteristics'!$S$4:$S$33,MATCH('Reserves (2)'!$B17,'Investment Characteristics'!$B$4:$B$33,0)) -> 4552198.8 | L17: =20*10^6 -> 20000000 | M17: =+L17*E17 -> 2618000 | N17: 2500000 | O17: =N17+J17 -> 7052198.8 | Q17: Q2'26 | R17: 45686 | T17: Ownership | U17: 0.07 | V17: =+AVERAGEIF('Reserves (2)'!$C$11:$C$34,'Reserves (2)'!T11,'Reserves (2)'!$E$11:$E$34) -> 0.080325594
B18: Hireguide | C18: =INDEX('Investment Characteristics'!$X$4:$X$31,MATCH('Reserves (2)'!$B18,'Investment Characteristics'!$K$4:$K$31,0)) -> RP | D18: =INDEX('Investment Characteristics'!$L$4:$L$31,MATCH('Reserves (2)'!$B18,'Investment Characteristics'!$K$4:$K$31,0)) -> Seed | E18: =INDEX('Investment Characteristics'!$M$4:$M$31,MATCH('Reserves (2)'!$B18,'Investment Characteristics'!$K$4:$K$31,0)) -> 0.09375 | F18: =INDEX('Investment Characteristics'!$Q$4:$Q$31,MATCH('Reserves (2)'!$B18,'Investment Characteristics'!$K$4:$K$31,0)) -> 32000000 | H18: =INDEX('Investment Characteristics'!$F$4:$F$33,MATCH('Reserves (2)'!$B18,'Investment Characteristics'!$B$4:$B$33,0)) -> 3000000 | I18: =J18-H18 -> 0 | J18: =INDEX('Investment Characteristics'!$S$4:$S$33,MATCH('Reserves (2)'!$B18,'Investment Characteristics'!$B$4:$B$33,0)) -> 3000000 | L18: =15*10^6 -> 15000000 | M18: =+L18*E18 -> 1406250 | N18: =0.5*10^6 -> 500000 | O18: =N18+J18 -> 3500000 | Q18: Q2'25 | R18: 45688
B19: Take2 AI | C19: =INDEX('Investment Characteristics'!$X$4:$X$31,MATCH('Reserves (2)'!$B19,'Investment Characteristics'!$K$4:$K$31,0)) -> ABG | D19: =INDEX('Investment Characteristics'!$L$4:$L$31,MATCH('Reserves (2)'!$B19,'Investment Characteristics'!$K$4:$K$31,0)) -> Seed | E19: =INDEX('Investment Characteristics'!$M$4:$M$31,MATCH('Reserves (2)'!$B19,'Investment Characteristics'!$K$4:$K$31,0)) -> 0.07 | F19: =INDEX('Investment Characteristics'!$Q$4:$Q$31,MATCH('Reserves (2)'!$B19,'Investment Characteristics'!$K$4:$K$31,0)) -> 10000000 | H19: =INDEX('Investment Characteristics'!$F$4:$F$33,MATCH('Reserves (2)'!$B19,'Investment Characteristics'!$B$4:$B$33,0)) -> 700000 | I19: =J19-H19 -> 0 | J19: =INDEX('Investment Characteristics'!$S$4:$S$33,MATCH('Reserves (2)'!$B19,'Investment Characteristics'!$B$4:$B$33,0)) -> 700000 | L19: =5*10^6 -> 5000000 | M19: =+L19*E19 -> 350000 | N19: 0 | O19: =N19+J19 -> 700000 | Q19: Q4'25 | R19: 45686 | T19: ABG
B20: Techwolf | C20: =INDEX('Investment Characteristics'!$X$4:$X$31,MATCH('Reserves (2)'!$B20,'Investment Characteristics'!$K$4:$K$31,0)) -> ABG | D20: =INDEX('Investment Characteristics'!$L$4:$L$31,MATCH('Reserves (2)'!$B20,'Investment Characteristics'!$K$4:$K$31,0)) -> B | E20: =INDEX('Investment Characteristics'!$M$4:$M$31,MATCH('Reserves (2)'!$B20,'Investment Characteristics'!$K$4:$K$31,0)) -> 0.035210817 | F20: =INDEX('Investment Characteristics'!$Q$4:$Q$31,MATCH('Reserves (2)'!$B20,'Investment Characteristics'!$K$4:$K$31,0)) -> 141000000 | H20: =INDEX('Investment Characteristics'!$F$4:$F$33,MATCH('Reserves (2)'!$B20,'Investment Characteristics'!$B$4:$B$33,0)) -> 5037377 | I20: =J20-H20 -> 0 | J20: =INDEX('Investment Characteristics'!$S$4:$S$33,MATCH('Reserves (2)'!$B20,'Investment Characteristics'!$B$4:$B$33,0)) -> 5037377 | L20: =50*10^6 -> 50000000 | M20: =+L20*E20 -> 1760540.9 | N20: 0 | O20: =N20+J20 -> 5037377 | Q20: Q2'26 | R20: 45686 | U20: Target | V20: Actual | W20: Remaining | X20: %
B21: Thatch | C21: =INDEX('Investment Characteristics'!$X$4:$X$31,MATCH('Reserves (2)'!$B21,'Investment Characteristics'!$K$4:$K$31,0)) -> GG | D21: =INDEX('Investment Characteristics'!$L$4:$L$31,MATCH('Reserves (2)'!$B21,'Investment Characteristics'!$K$4:$K$31,0)) -> B | E21: =INDEX('Investment Characteristics'!$M$4:$M$31,MATCH('Reserves (2)'!$B21,'Investment Characteristics'!$K$4:$K$31,0)) -> 0.032141794 | F21: =INDEX('Investment Characteristics'!$Q$4:$Q$31,MATCH('Reserves (2)'!$B21,'Investment Characteristics'!$K$4:$K$31,0)) -> 450000000 | H21: 1640635 | I21: =J21-H21 -> 2399990.2 | J21: =INDEX('Investment Characteristics'!$S$4:$S$33,MATCH('Reserves (2)'!$B21,'Investment Characteristics'!$B$4:$B$33,0)) -> 4040625.2 | L21: =50*10^6 -> 50000000 | M21: =+L21*E21 -> 1607089.7 | N21: 0 | O21: =N21+J21 -> 4040625.2 | Q21: Q1'25 | R21: 45730 | T21: Invested | U21: =20*10^6 -> 20000000 | V21: =+SUMIF('Reserves (2)'!$C$11:$C$34,'Reserves (2)'!T19,'Reserves (2)'!$H$11:$H$34) -> 14924872 | W21: =U21-V21 -> 5075127.9 | X21: =+V21/U21 -> 0.7462436
B22: Multimodal | C22: =INDEX('Investment Characteristics'!$X$4:$X$31,MATCH('Reserves (2)'!$B22,'Investment Characteristics'!$K$4:$K$31,0)) -> CH | D22: =INDEX('Investment Characteristics'!$L$4:$L$31,MATCH('Reserves (2)'!$B22,'Investment Characteristics'!$K$4:$K$31,0)) -> Seed | E22: =INDEX('Investment Characteristics'!$M$4:$M$31,MATCH('Reserves (2)'!$B22,'Investment Characteristics'!$K$4:$K$31,0)) -> 0.066666667 | F22: =INDEX('Investment Characteristics'!$Q$4:$Q$31,MATCH('Reserves (2)'!$B22,'Investment Characteristics'!$K$4:$K$31,0)) -> 30000000 | H22: =INDEX('Investment Characteristics'!$F$4:$F$33,MATCH('Reserves (2)'!$B22,'Investment Characteristics'!$B$4:$B$33,0)) -> 2000000 | I22: =J22-H22 -> 0 | J22: =INDEX('Investment Characteristics'!$S$4:$S$33,MATCH('Reserves (2)'!$B22,'Investment Characteristics'!$B$4:$B$33,0)) -> 2000000 | L22: =15*10^6 -> 15000000 | M22: =+L22*E22 -> 1000000 | N22: 3000000 | O22: =N22+J22 -> 5000000 | Q22: Q3 '25 | R22: 45686 | T22: Reserved | U22: =13*10^6 -> 13000000 | V22: =+SUMIF('Reserves (2)'!$C$11:$C$34,'Reserves (2)'!T19,'Reserves (2)'!$I$11:$I$34)+SUMIF('Reserves (2)'!$C$11:$C$34,'Reserves (2)'!T19,'Reserves (2)'!$N$11:$N$34) -> 9878034.7 | W22: =U22-V22 -> 3121965.3 | X22: =+V22/U22 -> 0.75984883
B23: OneImaging | C23: =INDEX('Investment Characteristics'!$X$4:$X$31,MATCH('Reserves (2)'!$B23,'Investment Characteristics'!$K$4:$K$31,0)) -> RP | D23: =INDEX('Investment Characteristics'!$L$4:$L$31,MATCH('Reserves (2)'!$B23,'Investment Characteristics'!$K$4:$K$31,0)) -> A | E23: =INDEX('Investment Characteristics'!$M$4:$M$31,MATCH('Reserves (2)'!$B23,'Investment Characteristics'!$K$4:$K$31,0)) -> 0.05994 | F23: =INDEX('Investment Characteristics'!$Q$4:$Q$31,MATCH('Reserves (2)'!$B23,'Investment Characteristics'!$K$4:$K$31,0)) -> 250000000 | H23: =INDEX('Investment Characteristics'!$F$4:$F$33,MATCH('Reserves (2)'!$B23,'Investment Characteristics'!$B$4:$B$33,0)) -> 1000000 | I23: =J23-H23 -> 3000000 | J23: =INDEX('Investment Characteristics'!$S$4:$S$33,MATCH('Reserves (2)'!$B23,'Investment Characteristics'!$B$4:$B$33,0)) -> 4000000 | L23: =10*10^6 -> 10000000 | M23: =+L23*E23 -> 599400 | N23: =3*10^6 -> 3000000 | O23: =N23+J23 -> 7000000 | Q23: Q1'26 | R23: 45688 | T23: Total | U23: =SUM(U21:U22) -> 33000000 | V23: =SUM(V21:V22) -> 24802907 | W23: =U23-V23 -> 8197093.2 | X23: =+V23/U23 -> 0.75160324
B24: ExceedsAI | C24: =INDEX('Investment Characteristics'!$X$4:$X$31,MATCH('Reserves (2)'!$B24,'Investment Characteristics'!$K$4:$K$31,0)) -> ABG | D24: Seed | E24: 0.066666667 | F24: =30*10^6 -> 30000000 | H24: =INDEX('Investment Characteristics'!$F$4:$F$33,MATCH('Reserves (2)'!$B24,'Investment Characteristics'!$B$4:$B$33,0)) -> 1187499.8 | I24: =J24-H24 -> 0 | J24: =INDEX('Investment Characteristics'!$S$4:$S$33,MATCH('Reserves (2)'!$B24,'Investment Characteristics'!$B$4:$B$33,0)) -> 1187499.8 | L24: =10*10^6 -> 10000000 | M24: =+L24*E24 -> 666666.67 | N24: 2000000 | O24: =N24+J24 -> 3187499.8 | Q24: Q1'26 | R24: 45686 | T24: Companies | U24: 8 | V24: =+COUNTIF('Reserves (2)'!$C$11:$C$34,'Reserves (2)'!T19) -> 5 | W24: =+U24-V24 -> 3 | X24: =+V24/U24 -> 0.625
B25: Sully.AI | C25: =INDEX('Investment Characteristics'!$X$4:$X$31,MATCH('Reserves (2)'!$B25,'Investment Characteristics'!$K$4:$K$31,0)) -> ABG | D25: =INDEX('Investment Characteristics'!$L$4:$L$31,MATCH('Reserves (2)'!$B25,'Investment Characteristics'!$K$4:$K$31,0)) -> A | E25: =INDEX('Investment Characteristics'!$M$4:$M$31,MATCH('Reserves (2)'!$B25,'Investment Characteristics'!$K$4:$K$31,0)) -> 0.053333327 | F25: =INDEX('Investment Characteristics'!$Q$4:$Q$31,MATCH('Reserves (2)'!$B25,'Investment Characteristics'!$K$4:$K$31,0)) -> 75000000 | H25: =INDEX('Investment Characteristics'!$F$4:$F$33,MATCH('Reserves (2)'!$B25,'Investment Characteristics'!$B$4:$B$33,0)) -> 3999999.5 | I25: =J25-H25 -> 0 | J25: =INDEX('Investment Characteristics'!$S$4:$S$33,MATCH('Reserves (2)'!$B25,'Investment Characteristics'!$B$4:$B$33,0)) -> 3999999.5 | L25: =50*10^6 -> 50000000 | M25: =+L25*E25 -> 2666666.3 | N25: 3000000 | O25: =N25+J25 -> 6999999.5 | Q25: Q4'25 | R25: 45686 | T25: Ownership | U25: 0.07 | V25: =+AVERAGEIF('Reserves (2)'!$C$11:$C$34,'Reserves (2)'!T19,'Reserves (2)'!$E$11:$E$34) -> 0.055603256
B26: Athena.AI | C26: =INDEX('Investment Characteristics'!$X$4:$X$31,MATCH('Reserves (2)'!$B26,'Investment Characteristics'!$K$4:$K$31,0)) -> RP | D26: Seed | E26: =INDEX('Investment Characteristics'!$M$4:$M$31,MATCH('Reserves (2)'!$B26,'Investment Characteristics'!$K$4:$K$31,0)) -> 0.09 | F26: =INDEX('Investment Characteristics'!$Q$4:$Q$31,MATCH('Reserves (2)'!$B26,'Investment Characteristics'!$K$4:$K$31,0)) -> 35000000 | H26: =INDEX('Investment Characteristics'!$F$4:$F$33,MATCH('Reserves (2)'!$B26,'Investment Characteristics'!$B$4:$B$33,0)) -> 3150000 | I26: =J26-H26 -> 0 | J26: =INDEX('Investment Characteristics'!$S$4:$S$33,MATCH('Reserves (2)'!$B26,'Investment Characteristics'!$B$4:$B$33,0)) -> 3150000 | L26: =10*10^6 -> 10000000 | M26: =+L26*E26 -> 900000 | N26: 1000000 | O26: =N26+J26 -> 4150000
T27: RP
U28: Target | V28: Actual | W28: Remaining | X28: %
T29: Invested | U29: =20*10^6 -> 20000000 | V29: =+SUMIF('Reserves (2)'!$C$11:$C$34,'Reserves (2)'!T27,'Reserves (2)'!$H$11:$H$34) -> 10799999 | W29: =U29-V29 -> 9200000.8 | X29: =+V29/U29 -> 0.53999996
T30: Reserved | U30: =13*10^6 -> 13000000 | V30: =+SUMIF('Reserves (2)'!$C$11:$C$34,'Reserves (2)'!T27,'Reserves (2)'!$I$11:$I$34)+SUMIF('Reserves (2)'!$C$11:$C$34,'Reserves (2)'!T27,'Reserves (2)'!$N$11:$N$34) -> 10128083 | W30: =U30-V30 -> 2871916.5 | X30: =+V30/U30 -> 0.77908334
T31: Total | U31: =SUM(U29:U30) -> 33000000 | V31: =SUM(V29:V30) -> 20928083 | W31: =U31-V31 -> 12071917 | X31: =+V31/U31 -> 0.63418432
T32: Companies | U32: 8 | V32: =+COUNTIF('Reserves (2)'!$C$11:$C$34,'Reserves (2)'!T27) -> 5 | W32: =+U32-V32 -> 3 | X32: =+V32/U32 -> 0.625
T33: Ownership | U33: 0.07 | V33: =+AVERAGEIF('Reserves (2)'!$C$11:$C$34,'Reserves (2)'!T27,'Reserves (2)'!$E$11:$E$34) -> 0.078949833
B35: Total | H35: =SUM(H11:H33) -> 39365504 | I35: =SUM(I11:I33) -> 15958305 | J35: =SUM(J11:J33) -> 55323809 | N35: =SUM(N11:N33) -> 21000000 | O35: =SUM(O11:O34) -> 76323809 | T35: CH
U36: Target | V36: Actual | W36: Remaining | X36: %
T37: Invested | U37: =10*10^6 -> 10000000 | V37: =+SUMIF('Reserves (2)'!$C$11:$C$34,'Reserves (2)'!T35,'Reserves (2)'!$H$11:$H$34) -> 5999998 | W37: =U37-V37 -> 4000002 | X37: =+V37/U37 -> 0.5999998
T38: Reserved | U38: =6.5*10^6 -> 6500000 | V38: =+SUMIF('Reserves (2)'!$C$11:$C$34,'Reserves (2)'!T35,'Reserves (2)'!$I$11:$I$34)+SUMIF('Reserves (2)'!$C$11:$C$34,'Reserves (2)'!T35,'Reserves (2)'!$N$11:$N$34) -> 7499997.9 | W38: =U38-V38 -> -999997.86 | X38: =+V38/U38 -> 1.1538458
T39: Total | U39: =SUM(U37:U38) -> 16500000 | V39: =SUM(V37:V38) -> 13499996 | W39: =U39-V39 -> 3000004.1 | X39: =+V39/U39 -> 0.81818157
T40: Companies | U40: 4 | V40: =+COUNTIF('Reserves (2)'!$C$11:$C$34,'Reserves (2)'!T35) -> 3 | W40: =+U40-V40 -> 1 | X40: =+V40/U40 -> 0.75
T41: Ownership | U41: 0.07 | V41: =+AVERAGEIF('Reserves (2)'!$C$11:$C$34,'Reserves (2)'!T35,'Reserves (2)'!$E$11:$E$34) -> 0.060408055

Sheet Allocation Tracking
C1: Partner | D1: Deals Remaining | E1: Capital Remaining | F1: SVA Deals Remaining
C2: ABG | D2: =D34 -> 0.55951929 | E2: =G27 -> 6319950.3 | F2: 1
C3: RP | D3: =D47 -> 0.8461958 | E3: =G40 -> 2834777.5 | F3: 1
C4: GG | D4: =D60 -> 0 | E4: =G53 -> -829964.47 | F4: 1
C5: CH | D5: =D73 -> 1.3226212 | E5: =G66 -> 2381432.7 | F5: 0
C6: Total | D6: =SUM(D2:D5) -> 2.7283363 | E6: =SUM(E2:E5) -> 10706196 | F6: =SUM(F2:F5) -> 3
B8: Core Fund Allocation
C9: Target | D9: Invested | E9: Reserved | F9: Inv.+ Reserved | G9: Remaining | H9: Reallocation to 60/40
B10: Initial | C10: =+'Fund Model'!C40 -> 66702000 | D10: =+D25+D38+D51+D64 -> 63005499 | E10: =+E25+E38+E51+E64 -> 0 | F10: =+SUM(D10:E10) -> 63005499 | G10: =+($C$12-$F$12)*0.6 -> 6423717.6 | H10: =+G12*0.6 -> 6423717.6
B11: Follow-On | C11: =+'Fund Model'!C41 -> 44468000 | D11: =+D26+D39+D52+D65 -> 15958305 | E11: =+E26+E39+E52+E65 -> 21500000 | F11: =+SUM(D11:E11) -> 37458305 | G11: =+($C$12-$F$12)*0.4 -> 4282478.4 | H11: =+G12*0.4 -> 4282478.4
B12: Total | C12: =SUM(C10:C11) -> 111170000 | D12: =SUM(D10:D11) -> 78963804 | E12: =SUM(E10:E11) -> 21500000 | F12: =SUM(F10:F11) -> 1.004638e+08 | G12: =+C12-F12 -> 10706196 | H12: =+H11+H10 -> 10706196
B14: Target KPIs: | C14: Target | D14: Actual
B15: # of Companies | C15: ='Fund Model'!C43 -> 25 | D15: =+D30+D43+D69+D56 -> 23
B16: Avg. Initial Investment | C16: =+'Fund Model'!$I$47 -> 2668080 | D16: =+'Investment Characteristics'!F32 -> 2733689.7
B17: Avg. Initial Ownership | C17: 0.07 | D17: =+'Investment Characteristics'!H32 -> 0.062241445
B18: Avg. Proforma Own (inc warrants) | C18: 0.07 | D18: 0.069
B19: Avg. Entry Valuation | C19: 65000000 | D19: ='Investment Characteristics'!I34 -> 67030563
B20: Deals Remaining | D20: =+D6 -> 2.7283363
B23: ABG
C24: Target | D24: Invested | E24: Reserved | F24: Inv.+ Reserved | G24: Remaining
B25: Initial | C25: =+'Fund Model'!$I$40 -> 19057714 | D25: =SUMIF(Reserves!$C$11:$C$32,'Allocation Tracking'!B23,Reserves!$I$11:$I$32) -> 17564872 | E25: 0 | F25: =+SUM(D25:E25) -> 17564872 | G25: =+C25-F25 -> 1492842.2
B26: Follow-On | C26: =+'Fund Model'!$I$41 -> 12705143 | D26: =SUMIF(Reserves!$C$11:$C$32,'Allocation Tracking'!B23,Reserves!$J$11:$J$32) -> 3878034.7 | E26: =SUMIF(Reserves!$C$11:$C$32,'Allocation Tracking'!B23,Reserves!$O$11:$O$32) -> 4000000 | F26: =+SUM(D26:E26) -> 7878034.7 | G26: =+C26-F26 -> 4827108.1
B27: Total | C27: =SUM(C25:C26) -> 31762857 | D27: =SUM(D25:D26) -> 21442907 | E27: =SUM(E25:E26) -> 4000000 | F27: =SUM(F25:F26) -> 25442907 | G27: =+C27-F27 -> 6319950.3
B29: Target KPIs: | C29: Target | D29: Actual
B30: # of Companies | C30: =+'Fund Model'!$I$43 -> 7.1428571 | D30: =+COUNTIF(Reserves!$C$11:$C$32,'Allocation Tracking'!B23) -> 6
B31: Avg. Initial Investment | C31: =+'Fund Model'!$I$47 -> 2668080 | D31: =+AVERAGEIF(Reserves!$C$11:$C$32,'Allocation Tracking'!B23,Reserves!$I$11:$I$32) -> 2927478.7
B32: Avg. Initial Ownership | C32: 0.07 | D32: =+AVERAGEIF(Reserves!$C$11:$C$32,'Allocation Tracking'!B23,Reserves!$E$11:$E$32) -> 0.060119378
B33: Avg. Entry Valuation | C33: =+C31/C32 -> 38115429 | D33: =+AVERAGEIF(Reserves!$C$11:$C$32,'Allocation Tracking'!B23,Reserves!$F$11:$F$32) -> 61633333
B34: Deals Remaining | D34: =+G25/C31 -> 0.55951929
B36: RP
C37: Target | D37: Invested | E37: Reserved | F37: Inv.+ Reserved | G37: Remaining
B38: Initial | C38: =+'Fund Model'!$I$40 -> 19057714 | D38: =SUMIF(Reserves!$C$11:$C$32,'Allocation Tracking'!B36,Reserves!$I$11:$I$32)+4000000 -> 16799996 | E38: 0 | F38: =+SUM(D38:E38) -> 16799996 | G38: =+C38-F38 -> 2257718.1
B39: Follow-On | C39: =+'Fund Model'!$I$41 -> 12705143 | D39: =SUMIF(Reserves!$C$11:$C$32,'Allocation Tracking'!B36,Reserves!$J$11:$J$32)+1000000 -> 4128083.5 | E39: =SUMIF(Reserves!$C$11:$C$32,'Allocation Tracking'!B36,Reserves!$O$11:$O$32) -> 8000000 | F39: =+SUM(D39:E39) -> 12128083 | G39: =+C39-F39 -> 577059.39
B40: Total | C40: =SUM(C38:C39) -> 31762857 | D40: =SUM(D38:D39) -> 20928080 | E40: =SUM(E38:E39) -> 8000000 | F40: =SUM(F38:F39) -> 28928080 | G40: =+C40-F40 -> 2834777.5
B42: Target KPIs: | C42: Target | D42: Actual
B43: # of Companies | C43: =+'Fund Model'!$I$43 -> 7.1428571 | D43: =+COUNTIF(Reserves!$C$11:$C$32,'Allocation Tracking'!B36)+1 -> 7
B44: Avg. Initial Investment | C44: =+'Fund Model'!$I$47 -> 2668080 | D44: =+AVERAGEIF(Reserves!$C$11:$C$32,'Allocation Tracking'!B36,Reserves!$I$11:$I$32) -> 2133332.7
B45: Avg. Initial Ownership | C45: 0.07 | D45: =+AVERAGEIF(Reserves!$C$11:$C$32,'Allocation Tracking'!B36,Reserves!$E$11:$E$32) -> 0.071347075
B46: Avg. Entry Valuation | C46: =+C44/C45 -> 38115429 | D46: =+AVERAGEIF(Reserves!$C$11:$C$32,'Allocation Tracking'!B36,Reserves!$F$11:$F$32) -> 32000000
B47: Deals Remaining | D47: =+G38/C44 -> 0.8461958
B49: GG
C50: Target | D50: Invested | E50: Reserved | F50: Inv.+ Reserved | G50: Remaining
B51: Initial | C51: =+'Fund Model'!$I$40 -> 19057714 | D51: =SUMIF(Reserves!$C$11:$C$32,'Allocation Tracking'!B49,Reserves!$I$11:$I$32) -> 22640632 | E51: 0 | F51: =+SUM(D51:E51) -> 22640632 | G51: =+C51-F51 -> -3582918.2
B52: Follow-On | C52: =+'Fund Model'!$I$41 -> 12705143 | D52: =SUMIF(Reserves!$C$11:$C$32,'Allocation Tracking'!B49,Reserves!$J$11:$J$32)-1000000 -> 4952189.2 | E52: =SUMIF(Reserves!$C$11:$C$32,'Allocation Tracking'!B49,Reserves!$O$11:$O$32) -> 5000000 | F52: =+SUM(D52:E52) -> 9952189.2 | G52: =+C52-F52 -> 2752953.7
B53: Total | C53: =SUM(C51:C52) -> 31762857 | D53: =SUM(D51:D52) -> 27592822 | E53: =SUM(E51:E52) -> 5000000 | F53: =SUM(F51:F52) -> 32592822 | G53: =+C53-F53 -> -829964.47
B55: Target KPIs: | C55: Target | D55: Actual
B56: # of Companies | C56: =+'Fund Model'!$I$43 -> 7.1428571 | D56: =+COUNTIF(Reserves!$C$11:$C$32,'Allocation Tracking'!B49) -> 7
B57: Avg. Initial Investment | C57: =+'Fund Model'!$I$47 -> 2668080 | D57: =+AVERAGEIF(Reserves!$C$11:$C$32,'Allocation Tracking'!B49,Reserves!$I$11:$I$32) -> 3234376.1
B58: Avg. Initial Ownership | C58: 0.07 | D58: =+AVERAGEIF(Reserves!$C$11:$C$32,'Allocation Tracking'!B49,Reserves!$E$11:$E$32) -> 0.069505234
B59: Avg. Entry Valuation | C59: =+C57/C58 -> 38115429 | D59: =+AVERAGEIF(Reserves!$C$11:$C$32,'Allocation Tracking'!B49,Reserves!$F$11:$F$32) -> 62262192
B60: Deals Remaining | D60: 0
B62: CH
C63: Target | D63: Invested | E63: Reserved | F63: Inv.+ Reserved | G63: Remaining
B64: Initial | C64: =+'Fund Model'!L40 -> 9528857.1 | D64: =SUMIF(Reserves!$C$11:$C$32,'Allocation Tracking'!B62,Reserves!$I$11:$I$32) -> 5999998 | E64: 0 | F64: =+SUM(D64:E64) -> 5999998 | G64: =+C64-F64 -> 3528859.1
B65: Follow-On | C65: =+'Fund Model'!L41 -> 6352571.4 | D65: =SUMIF(Reserves!$C$11:$C$32,'Allocation Tracking'!B62,Reserves!$J$11:$J$32) -> 2999997.9 | E65: =SUMIF(Reserves!$C$11:$C$32,'Allocation Tracking'!B62,Reserves!$O$11:$O$32) -> 4500000 | F65: =+SUM(D65:E65) -> 7499997.9 | G65: =+C65-F65 -> -1147426.4
B66: Total | C66: =SUM(C64:C65) -> 15881429 | D66: =SUM(D64:D65) -> 8999995.9 | E66: =SUM(E64:E65) -> 4500000 | F66: =SUM(F64:F65) -> 13499996 | G66: =+C66-F66 -> 2381432.7
B68: Target KPIs: | C68: Target | D68: Actual
B69: # of Companies | C69: =+'Fund Model'!L43 -> 3.5714286 | D69: =+COUNTIF(Reserves!$C$11:$C$32,'Allocation Tracking'!B62) -> 3
B70: Avg. Initial Investment | C70: =+'Fund Model'!L47 -> 2668080 | D70: =+AVERAGEIF(Reserves!$C$11:$C$32,'Allocation Tracking'!B62,Reserves!$I$11:$I$32) -> 1999999.3
B71: Avg. Initial Ownership | C71: 0.07 | D71: =+AVERAGEIF(Reserves!$C$11:$C$32,'Allocation Tracking'!B62,Reserves!$E$11:$E$32) -> 0.060408055
B72: Avg. Entry Valuation | C72: =+C70/C71 -> 38115429 | D72: =+AVERAGEIF(Reserves!$C$11:$C$32,'Allocation Tracking'!B62,Reserves!$F$11:$F$32) -> 40400000
B73: Deals Remaining | D73: =+G64/C70 -> 1.3226212
B75: SVA
C76: Target | D76: Invested | E76: Reserved | F76: Inv.+ Reserved | G76: Remaining
B77: Initial | C77: =+'Fund Model'!C25 -> 2550000 | D77: =Reserves!K44 -> 1300000 | E77: 0 | F77: =+SUM(D77:E77) -> 1300000 | G77: =+C77-F77 -> 1250000
B78: Graduation | C78: =+'Fund Model'!C30 -> 6000000 | D78: 0 | E78: 0 | F78: =+SUM(D78:E78) -> 0 | G78: =+C78-F78 -> 6000000
B79: Follow-On | C79: =+'Fund Model'!C31 -> 2400000 | D79: =SUMIF(Reserves!$C$11:$C$32,'Allocation Tracking'!B75,Reserves!$J$11:$J$32) -> 0 | E79: =SUMIF(Reserves!$C$11:$C$32,'Allocation Tracking'!B75,Reserves!$O$11:$O$32) -> 0 | F79: =+SUM(D79:E79) -> 0 | G79: =+C79-F79 -> 2400000
B80: Total | C80: =SUM(C77:C79) -> 10950000 | D80: =SUM(D77:D79) -> 1300000 | E80: =SUM(E77:E79) -> 0 | F80: =SUM(F77:F79) -> 1300000 | G80: =+C80-F80 -> 9650000
B82: Target KPIs: | C82: Target | D82: Actual
B83: # of Companies | C83: ='Fund Model'!C23 -> 12 | D83: 3
B84: Graduated Companies | C84: ='Fund Model'!C28 -> 3 | D84: 0
B85: % Graduated | C85: ='Fund Model'!C27 -> 0.25 | D85: 0
B86: Core Initial Check | C86: ='Fund Model'!C29 -> 2000000 | D86: 0
B87: Target Ownership | C87: 0.07 | D87: 0
B88: Deals Remaining | D88: =D83 -> 3

Sheet Vitalis Allocation
C2: Invested | D2: Reserved | E2: Dry Powder | G2: Total | N2: Invested | O2: Reserves | Q2: Dry Powder | S2: Total
E3: Core | F3: SVA | O3: Core | P3: Vitalis | Q3: Core | R3: SVA
B4: ABG | C4: =+'Allocation Tracking'!D27+Reserves!K40+Reserves!K42 -> 21942907 | D4: =+'Allocation Tracking'!E27 -> 4000000 | E4: =+'Allocation Tracking'!G27 -> 6319950.3 | F4: =+'Fund Model'!L30+'Fund Model'!L31 -> 2800000 | G4: =SUM(C4:F4) -> 35062857 | M4: ABG | N4: =+C4 -> 21942907 | O4: =+D4 -> 4000000 | P4: 0 | Q4: =+E4 -> 6319950.3 | R4: =+F4 -> 2800000 | S4: =SUM(N4:R4) -> 35062857
B5: GG | C5: =+'Allocation Tracking'!D53+Reserves!K41 -> 27842822 | D5: =+'Allocation Tracking'!E53 -> 5000000 | E5: 0 | F5: =+F4 -> 2800000 | G5: =SUM(C5:F5) -> 35642822 | M5: GG | N5: =+C5 -> 27842822 | O5: =+D5 -> 5000000 | P5: =6*10^6 -> 6000000 | Q5: =+E5 -> 0 | R5: 0 | S5: =SUM(N5:R5) -> 38842822
B6: RP | C6: =+'Allocation Tracking'!D40+Reserves!K39+Reserves!K43 -> 21228080 | D6: =+'Allocation Tracking'!E40 -> 8000000 | E6: =+'Allocation Tracking'!G40 -> 2834777.5 | F6: =+F5 -> 2800000 | G6: =SUM(C6:F6) -> 34862857 | M6: RP | N6: =+C6 -> 21228080 | O6: =+D6 -> 8000000 | P6: 0 | Q6: =+E6 -> 2834777.5 | R6: =+F6 -> 2800000 | S6: =SUM(N6:R6) -> 34862857
B7: CH | C7: =+'Allocation Tracking'!D66+Reserves!K38 -> 9249995.9 | D7: =+'Allocation Tracking'!E66 -> 4500000 | E7: =+'Allocation Tracking'!G66 -> 2381432.7 | F7: 0 | G7: =SUM(C7:F7) -> 16131429 | M7: CH | N7: =+C7 -> 9249995.9 | O7: =+D7 -> 4500000 | P7: 0 | Q7: 0 | R7: =+F7 -> 0 | S7: =SUM(N7:R7) -> 13749996
B8: Total | C8: =SUM(C4:C7) -> 80263804 | D8: =SUM(D4:D7) -> 21500000 | E8: =SUM(E4:E7) -> 11536160 | F8: =SUM(F4:F7) -> 8400000 | G8: =SUM(G4:G7) -> 1.2169996e+08 | M8: Total | N8: =SUM(N4:N7) -> 80263804 | O8: =SUM(O4:O7) -> 21500000 | P8: =SUM(P4:P7) -> 6000000 | Q8: =SUM(Q4:Q7) -> 9154727.8 | R8: =SUM(R4:R7) -> 5600000 | S8: =SUM(S4:S7) -> 1.2251853e+08
T10: # of Companies
H11: # of Companies | T11: Current | U11: Expected Core | V11: Expected SVA -> Core | W11: Total
H12: Current | I12: Expected Core | J12: Expected SVA -> Core | K12: Total | S12: ABG | T12: =+H13 -> 6 | U12: 7 | V12: 1 | W12: =SUM(U12:V12) -> 8
G13: ABG | H13: =+'Allocation Tracking'!D30 -> 6 | I13: 7 | J13: 1 | K13: =SUM(I13:J13) -> 8 | S13: GG | T13: =+H14 -> 7 | U13: 8 | V13: 0 | W13: =SUM(U13:V13) -> 8
G14: GG | H14: =+'Allocation Tracking'!D56 -> 7 | I14: 7 | J14: 1 | K14: =SUM(I14:J14) -> 8 | S14: RP | T14: =+H15 -> 7 | U14: 8 | V14: 1 | W14: =SUM(U14:V14) -> 9
G15: RP | H15: =+'Allocation Tracking'!D43 -> 7 | I15: 8 | J15: 1 | K15: =SUM(I15:J15) -> 9 | S15: CH | T15: =+H16 -> 3 | U15: 3 | V15: 0 | W15: 3
G16: CH | H16: 3 | I16: 4 | J16: 0 | K16: 4 | S16: Total | T16: =SUM(T12:T15) -> 23 | U16: =SUM(U12:U15) -> 26 | V16: =SUM(V12:V15) -> 2 | W16: =SUM(U16:V16) -> 28
G17: Total | H17: =SUM(H13:H16) -> 23 | I17: =SUM(I13:I16) -> 26 | J17: =SUM(J13:J16) -> 3 | K17: =SUM(I17:J17) -> 29

Sheet Reserves
B2: Total Fund | C2: Amount | D2: Reserve ratio | E2: % of Inv. Cap | F2: % of Total Fund | U2: Current | AB2: Full SVA Allocation
B3: Initial Invested | C3: =+I33 -> 59005499 | D3: =+C3/$C$5 -> 0.61168538 | E3: =+C3/$E$6 -> 0.48317637 | F3: =+C3/$F$6 -> 0.41262587 | U3: Partner Allocation | AB3: Partner Allocation
B4: Follow-On + Reserves | C4: =+J33+O33 -> 37458305 | D4: =+C4/$C$5 -> 0.38831462 | E4: =+C4/$E$6 -> 0.30673358 | F4: =+C4/$F$6 -> 0.26194619 | U4: Total | AB4: Total
B5: Inv. and Reserves | C5: =+P33 -> 96463804 | D5: =SUM(D3:D4) -> 1 | E5: =+C5/$E$6 -> 0.78990996 | F5: =+C5/$F$6 -> 0.67457206 | V5: Target | W5: Actual | X5: Reserved | Y5: Remaining | Z5: % | AC5: Target | AD5: Actual | AE5: Reserved | AF5: Remaining | AG5: %
E6: =+'Fund Model'!C20 -> 122120000 | F6: =143*10^6 -> 143000000 | U6: Invested | V6: =70*10^6-V8 -> 69400000 | W6: =+SUM(Reserves!I33) -> 59005499 | X6: 0 | Y6: =V6-W6-X6 -> 10394501 | Z6: =+W6/V6 -> 0.85022332 | AB6: Invested | AC6: =70*10^6-AC8 -> 69400000 | AD6: =+SUM(Reserves!P33) -> 96463804 | AE6: 0 | AF6: =AC6-AD6-AE6 -> -27063804 | AG6: =+AD6/AC6 -> 1.3899684
O7: Partner Input | R7: Partner Input | U7: Reserved | V7: =45*10^6-V9 -> 39000000 | W7: =+J33 -> 15958305 | X7: =+O33 -> 21500000 | Y7: =V7-W7-X7 -> 1541694.8 | Z7: =+W7/V7 -> 0.40918731 | AB7: Reserved | AC7: =45*10^6-AC9 -> 39000000 | AD7: =+Q33 -> 0 | AE7: =+V33 -> 19850000 | AF7: =AC7-AD7-AE7 -> 19150000 | AG7: =+AD7/AC7 -> 0
M8: Pro Rata Calc | U8: SVA Initial | V8: =12*50000 -> 600000 | W8: 0 | X8: 0 | Y8: =V8-W8-X8 -> 600000 | Z8: =+W8/V8 -> 0 | AB8: SVA Initial | AC8: =12*50000 -> 600000 | AD8: 0 | AE8: 0 | AF8: =AC8-AD8-AE8 -> 600000 | AG8: =+AD8/AC8 -> 0
I9: Initial | K9: Total | R9: Timing of | U9: SVA Reserved | V9: =6*1000000 -> 6000000 | W9: 0 | X9: 0 | Y9: =V9-W9-X9 -> 6000000 | Z9: =+W9/V9 -> 0 | AB9: SVA Reserved | AC9: =6*1000000 -> 6000000 | AD9: 0 | AE9: 0 | AF9: =AC9-AD9-AE9 -> 6000000 | AG9: =+AD9/AC9 -> 0
B10: Company | C10: Owner | D10: Current Stage | E10: Ownership | F10: Initial Valuation | G10: Last Valuation | I10: $ Invested | J10: Follow-Ons | K10: Invested | M10: Round Size | N10: Implied Pro-rata | O10: Reserves | P10: Inv. and Reserved | R10: Next Round | S10: Last Updated | U10: Total | V10: =SUM(V6:V9) -> 115000000 | W10: =SUM(W6:W9) -> 74963804 | X10: =SUM(X6:X9) -> 21500000 | Y10: =SUM(Y6:Y9) -> 18536196 | Z10: =+(W10+X10)/V10 -> 0.83881569 | AB10: Total | AC10: =SUM(AC6:AC9) -> 115000000 | AD10: =SUM(AD6:AD9) -> 96463804 | AE10: =SUM(AE6:AE9) -> 19850000 | AF10: =SUM(AF6:AF9) -> -1313804 | AG10: =+(AD10+AE10)/AC10 -> 1.0114244
B11: Stepful | C11: =INDEX('Investment Characteristics'!$X$4:$X$31,MATCH(Reserves!$B11,'Investment Characteristics'!$K$4:$K$31,0)) -> ABG | D11: =INDEX('Investment Characteristics'!$L$4:$L$31,MATCH(Reserves!$B11,'Investment Characteristics'!$K$4:$K$31,0)) -> B | E11: =INDEX('Investment Characteristics'!$M$4:$M$31,MATCH(Reserves!$B11,'Investment Characteristics'!$K$4:$K$31,0)) -> 0.052805468 | F11: =INDEX('Investment Characteristics'!$O$4:$O$31,MATCH(Reserves!$B11,'Investment Characteristics'!$K$4:$K$31,0)) -> 91800000 | G11: =INDEX('Investment Characteristics'!$Q$4:$Q$31,MATCH(Reserves!$B11,'Investment Characteristics'!$K$4:$K$31,0)) -> 261500000 | I11: =INDEX('Investment Characteristics'!$F$4:$F$33,MATCH(Reserves!$B11,'Investment Characteristics'!$B$4:$B$33,0)) -> 3999995.7 | J11: =K11-I11 -> 3878034.7 | K11: =INDEX('Investment Characteristics'!$S$4:$S$33,MATCH(Reserves!$B11,'Investment Characteristics'!$B$4:$B$33,0)) -> 7878030.5 | M11: =N49 -> 50000000 | N11: =+M11*E11 -> 2640273.4 | O11: 0 | P11: =O11+K11 -> 7878030.5 | R11: Q4'25 | U11: Companies | V11: =+V21+V39+#REF!+V51 -> #REF! | W11: =+W21+W39+#REF!+W51 -> #REF! | Y11: =+V11-W11 -> #REF! | Z11: =+W11/V11 -> #REF! | AB11: Companies | AC11: =+AC21+AC39+#REF!+AC51 -> #REF! | AD11: =+AD21+AD39+#REF!+AD51 -> #REF! | AF11: =+AC11-AD11 -> #REF! | AG11: =+AD11/AC11 -> #REF!
B12: Take2 AI | C12: =INDEX('Investment Characteristics'!$X$4:$X$31,MATCH(Reserves!$B12,'Investment Characteristics'!$K$4:$K$31,0)) -> ABG | D12: =INDEX('Investment Characteristics'!$L$4:$L$31,MATCH(Reserves!$B12,'Investment Characteristics'!$K$4:$K$31,0)) -> Seed | E12: =INDEX('Investment Characteristics'!$M$4:$M$31,MATCH(Reserves!$B12,'Investment Characteristics'!$K$4:$K$31,0)) -> 0.07 | F12: =INDEX('Investment Characteristics'!$O$4:$O$31,MATCH(Reserves!$B12,'Investment Characteristics'!$K$4:$K$31,0)) -> 10000000 | G12: =INDEX('Investment Characteristics'!$Q$4:$Q$31,MATCH(Reserves!$B12,'Investment Characteristics'!$K$4:$K$31,0)) -> 10000000 | I12: =INDEX('Investment Characteristics'!$F$4:$F$33,MATCH(Reserves!$B12,'Investment Characteristics'!$B$4:$B$33,0)) -> 700000 | J12: =K12-I12 -> 0 | K12: =INDEX('Investment Characteristics'!$S$4:$S$33,MATCH(Reserves!$B12,'Investment Characteristics'!$B$4:$B$33,0)) -> 700000 | M12: =N47 -> 20000000 | N12: =+M12*E12 -> 1400000 | O12: =1*10^6 -> 1000000 | P12: =O12+K12 -> 1700000 | R12: Q1'26
B13: Techwolf | C13: =INDEX('Investment Characteristics'!$X$4:$X$31,MATCH(Reserves!$B13,'Investment Characteristics'!$K$4:$K$31,0)) -> ABG | D13: =INDEX('Investment Characteristics'!$L$4:$L$31,MATCH(Reserves!$B13,'Investment Characteristics'!$K$4:$K$31,0)) -> B | E13: =INDEX('Investment Characteristics'!$M$4:$M$31,MATCH(Reserves!$B13,'Investment Characteristics'!$K$4:$K$31,0)) -> 0.035210817 | F13: =INDEX('Investment Characteristics'!$O$4:$O$31,MATCH(Reserves!$B13,'Investment Characteristics'!$K$4:$K$31,0)) -> 141000000 | G13: =INDEX('Investment Characteristics'!$Q$4:$Q$31,MATCH(Reserves!$B13,'Investment Characteristics'!$K$4:$K$31,0)) -> 141000000 | I13: =INDEX('Investment Characteristics'!$F$4:$F$33,MATCH(Reserves!$B13,'Investment Characteristics'!$B$4:$B$33,0)) -> 5037377 | J13: =K13-I13 -> 0 | K13: =INDEX('Investment Characteristics'!$S$4:$S$33,MATCH(Reserves!$B13,'Investment Characteristics'!$B$4:$B$33,0)) -> 5037377 | M13: =N49 -> 50000000 | N13: =+M13*E13 -> 1760540.9 | O13: 0 | P13: =O13+K13 -> 5037377 | R13: Q4'25 | U13: GG | AB13: GG
B14: ExceedsAI | C14: =INDEX('Investment Characteristics'!$X$4:$X$31,MATCH(Reserves!$B14,'Investment Characteristics'!$K$4:$K$31,0)) -> ABG | D14: =INDEX('Investment Characteristics'!$L$4:$L$31,MATCH(Reserves!$B14,'Investment Characteristics'!$K$4:$K$31,0)) -> Seed | E14: =INDEX('Investment Characteristics'!$M$4:$M$31,MATCH(Reserves!$B14,'Investment Characteristics'!$K$4:$K$31,0)) -> 0.079166656 | F14: =INDEX('Investment Characteristics'!$O$4:$O$31,MATCH(Reserves!$B14,'Investment Characteristics'!$K$4:$K$31,0)) -> 15000000 | G14: =INDEX('Investment Characteristics'!$Q$4:$Q$31,MATCH(Reserves!$B14,'Investment Characteristics'!$K$4:$K$31,0)) -> 15000000 | I14: =INDEX('Investment Characteristics'!$F$4:$F$33,MATCH(Reserves!$B14,'Investment Characteristics'!$B$4:$B$33,0)) -> 1187499.8 | J14: =K14-I14 -> 0 | K14: =INDEX('Investment Characteristics'!$S$4:$S$33,MATCH(Reserves!$B14,'Investment Characteristics'!$B$4:$B$33,0)) -> 1187499.8 | M14: =N47 -> 20000000 | N14: =+M14*E14 -> 1583333.1 | O14: 0 | P14: =O14+K14 -> 1187499.8 | R14: Q4'25 | V14: Target | W14: Actual | X14: Reserved | Y14: Remaining | Z14: % | AC14: Target | AD14: Actual | AE14: Reserved | AF14: Remaining | AG14: %
B15: Sully.AI | C15: =INDEX('Investment Characteristics'!$X$4:$X$31,MATCH(Reserves!$B15,'Investment Characteristics'!$K$4:$K$31,0)) -> ABG | D15: =INDEX('Investment Characteristics'!$L$4:$L$31,MATCH(Reserves!$B15,'Investment Characteristics'!$K$4:$K$31,0)) -> A | E15: =INDEX('Investment Characteristics'!$M$4:$M$31,MATCH(Reserves!$B15,'Investment Characteristics'!$K$4:$K$31,0)) -> 0.053333327 | F15: =INDEX('Investment Characteristics'!$O$4:$O$31,MATCH(Reserves!$B15,'Investment Characteristics'!$K$4:$K$31,0)) -> 75000000 | G15: =INDEX('Investment Characteristics'!$Q$4:$Q$31,MATCH(Reserves!$B15,'Investment Characteristics'!$K$4:$K$31,0)) -> 75000000 | I15: =INDEX('Investment Characteristics'!$F$4:$F$33,MATCH(Reserves!$B15,'Investment Characteristics'!$B$4:$B$33,0)) -> 3999999.5 | J15: =K15-I15 -> 0 | K15: =INDEX('Investment Characteristics'!$S$4:$S$33,MATCH(Reserves!$B15,'Investment Characteristics'!$B$4:$B$33,0)) -> 3999999.5 | M15: =20*10^6 -> 20000000 | N15: =+M15*E15 -> 1066666.5 | O15: =1*10^6 -> 1000000 | P15: =O15+K15 -> 4999999.5 | R15: Q1'26 | U15: Invested | V15: =20*10^6-V18 -> 19850000 | W15: =+SUMIF(Reserves!$C$11:$C$32,Reserves!U13,Reserves!$I$11:$I$32) -> 22640632 | X15: 0 | Y15: =V15-W15 -> -2790632.4 | Z15: =+(W15+X15)/V15 -> 1.140586 | AB15: Invested | AC15: =20*10^6-AC18 -> 19850000 | AD15: =+SUMIF(Reserves!$C$11:$C$32,Reserves!AB13,Reserves!$I$11:$I$32) -> 22640632 | AE15: 0 | AF15: =AC15-AD15 -> -2790632.4 | AG15: =+(AD15+AE15)/AC15 -> 1.140586
B16: Carefam | C16: =INDEX('Investment Characteristics'!$X$4:$X$31,MATCH(Reserves!$B16,'Investment Characteristics'!$K$4:$K$31,0)) -> ABG | D16: A | E16: =INDEX('Investment Characteristics'!$M$4:$M$31,MATCH(Reserves!$B16,'Investment Characteristics'!$K$4:$K$31,0)) -> 0.0702 | F16: =INDEX('Investment Characteristics'!$O$4:$O$31,MATCH(Reserves!$B16,'Investment Characteristics'!$K$4:$K$31,0)) -> 37000000 | G16: =INDEX('Investment Characteristics'!$Q$4:$Q$31,MATCH(Reserves!$B16,'Investment Characteristics'!$K$4:$K$31,0)) -> 37600000 | I16: =INDEX('Investment Characteristics'!$F$4:$F$33,MATCH(Reserves!$B16,'Investment Characteristics'!$B$4:$B$33,0)) -> 2640000 | J16: =K16-I16 -> 0 | K16: =INDEX('Investment Characteristics'!$F$4:$F$33,MATCH(Reserves!$B16,'Investment Characteristics'!$B$4:$B$33,0)) -> 2640000 | M16: =N48 -> 30000000 | N16: =+M16*E16 -> 2106000 | O16: 2000000 | P16: =O16+K16 -> 4640000 | R16: Q4'25 | V16: Target | W16: Actual | X16: Reserved | Y16: Remaining | Z16: % | AC16: Target | AD16: Actual | AE16: Reserved | AF16: Remaining | AG16: %
B17: Wagmo | C17: =INDEX('Investment Characteristics'!$X$4:$X$31,MATCH(Reserves!$B17,'Investment Characteristics'!$K$4:$K$31,0)) -> CH | D17: =INDEX('Investment Characteristics'!$L$4:$L$31,MATCH(Reserves!$B17,'Investment Characteristics'!$K$4:$K$31,0)) -> A | E17: =INDEX('Investment Characteristics'!$M$4:$M$31,MATCH(Reserves!$B17,'Investment Characteristics'!$K$4:$K$31,0)) -> 0.029870094 | F17: =INDEX('Investment Characteristics'!$O$4:$O$31,MATCH(Reserves!$B17,'Investment Characteristics'!$K$4:$K$31,0)) -> 47200000 | G17: =INDEX('Investment Characteristics'!$Q$4:$Q$31,MATCH(Reserves!$B17,'Investment Characteristics'!$K$4:$K$31,0)) -> 47200000 | I17: =INDEX('Investment Characteristics'!$F$4:$F$33,MATCH(Reserves!$B17,'Investment Characteristics'!$B$4:$B$33,0)) -> 1499998 | J17: =K17-I17 -> 0 | K17: =INDEX('Investment Characteristics'!$S$4:$S$33,MATCH(Reserves!$B17,'Investment Characteristics'!$B$4:$B$33,0)) -> 1499998 | M17: =N48 -> 30000000 | N17: =+M17*E17 -> 896102.82 | O17: 0 | P17: =O17+K17 -> 1499998 | R17: Q1'26 | U17: Reserved | V17: =13*10^6-V19 -> 11500000 | W17: =+SUMIF(Reserves!$C$11:$C$32,Reserves!U13,Reserves!$J$11:$J$32)-J11 -> 2074154.4 | X17: =+SUMIF(Reserves!$C$11:$C$32,Reserves!U13,Reserves!$O$11:$O$32) -> 5000000 | Y17: =V17-W17-X17 -> 4425845.6 | Z17: =+(W17+X17)/V17 -> 0.61514386 | AB17: Reserved | AC17: =13*10^6-AC19 -> 11500000 | AD17: =+SUMIF(Reserves!$C$11:$C$32,Reserves!AB13,Reserves!$J$11:$J$32)-Q11 -> 5952189.2 | AE17: =+SUMIF(Reserves!$C$11:$C$32,Reserves!AB13,Reserves!$O$11:$O$32) -> 5000000 | AF17: =AC17-AD17-AE17 -> 547810.84 | AG17: =+(AD17+AE17)/AC17 -> 0.95236427
B18: Salsa | C18: =INDEX('Investment Characteristics'!$X$4:$X$31,MATCH(Reserves!$B18,'Investment Characteristics'!$K$4:$K$31,0)) -> CH | D18: =INDEX('Investment Characteristics'!$L$4:$L$31,MATCH(Reserves!$B18,'Investment Characteristics'!$K$4:$K$31,0)) -> A | E18: =INDEX('Investment Characteristics'!$M$4:$M$31,MATCH(Reserves!$B18,'Investment Characteristics'!$K$4:$K$31,0)) -> 0.084687403 | F18: =INDEX('Investment Characteristics'!$O$4:$O$31,MATCH(Reserves!$B18,'Investment Characteristics'!$K$4:$K$31,0)) -> 44000000 | G18: =INDEX('Investment Characteristics'!$Q$4:$Q$31,MATCH(Reserves!$B18,'Investment Characteristics'!$K$4:$K$31,0)) -> 70000000 | I18: =INDEX('Investment Characteristics'!$F$4:$F$33,MATCH(Reserves!$B18,'Investment Characteristics'!$B$4:$B$33,0)) -> 2500000 | J18: =K18-I18 -> 2999997.9 | K18: =INDEX('Investment Characteristics'!$S$4:$S$33,MATCH(Reserves!$B18,'Investment Characteristics'!$B$4:$B$33,0)) -> 5499997.9 | M18: =N48 -> 30000000 | N18: =+M18*E18 -> 2540622.1 | O18: 2500000 | P18: =O18+K18 -> 7999997.9 | R18: Q2'26 | U18: SVA Initial | V18: =3*50000 -> 150000 | W18: 50000 | X18: 0 | Y18: =V18-W18 -> 100000 | Z18: =+(W18+X18)/V18 -> 0.33333333 | AB18: SVA Initial | AC18: =3*50000 -> 150000 | AD18: 50000 | AE18: 0 | AF18: =AC18-AD18 -> 100000 | AG18: =+(AD18+AE18)/AC18 -> 0.33333333
B19: Multimodal | C19: =INDEX('Investment Characteristics'!$X$4:$X$31,MATCH(Reserves!$B19,'Investment Characteristics'!$K$4:$K$31,0)) -> CH | D19: =INDEX('Investment Characteristics'!$L$4:$L$31,MATCH(Reserves!$B19,'Investment Characteristics'!$K$4:$K$31,0)) -> Seed | E19: =INDEX('Investment Characteristics'!$M$4:$M$31,MATCH(Reserves!$B19,'Investment Characteristics'!$K$4:$K$31,0)) -> 0.066666667 | F19: =INDEX('Investment Characteristics'!$O$4:$O$31,MATCH(Reserves!$B19,'Investment Characteristics'!$K$4:$K$31,0)) -> 30000000 | G19: =INDEX('Investment Characteristics'!$Q$4:$Q$31,MATCH(Reserves!$B19,'Investment Characteristics'!$K$4:$K$31,0)) -> 30000000 | I19: =INDEX('Investment Characteristics'!$F$4:$F$33,MATCH(Reserves!$B19,'Investment Characteristics'!$B$4:$B$33,0)) -> 2000000 | J19: =K19-I19 -> 0 | K19: =INDEX('Investment Characteristics'!$S$4:$S$33,MATCH(Reserves!$B19,'Investment Characteristics'!$B$4:$B$33,0)) -> 2000000 | M19: =N47 -> 20000000 | N19: =+M19*E19 -> 1333333.3 | O19: =2*10^6 -> 2000000 | P19: =O19+K19 -> 4000000 | R19: Q2'25 | U19: SVA Reserved | V19: =1.5*1000000 -> 1500000 | W19: 0 | X19: 0 | Y19: =V19-W19 -> 1500000 | Z19: =+(W19+X19)/V19 -> 0 | AB19: SVA Reserved | AC19: =1.5*1000000 -> 1500000 | AD19: 0 | AE19: 0 | AF19: =AC19-AD19 -> 1500000 | AG19: =+(AD19+AE19)/AC19 -> 0
B20: Laguna Health | C20: =INDEX('Investment Characteristics'!$X$4:$X$31,MATCH(Reserves!$B20,'Investment Characteristics'!$K$4:$K$31,0)) -> GG | D20: =INDEX('Investment Characteristics'!$L$4:$L$31,MATCH(Reserves!$B20,'Investment Characteristics'!$K$4:$K$31,0)) -> A | E20: =INDEX('Investment Characteristics'!$M$4:$M$31,MATCH(Reserves!$B20,'Investment Characteristics'!$K$4:$K$31,0)) -> 0.077934988 | F20: =INDEX('Investment Characteristics'!$O$4:$O$31,MATCH(Reserves!$B20,'Investment Characteristics'!$K$4:$K$31,0)) -> 53000000 | G20: =INDEX('Investment Characteristics'!$Q$4:$Q$31,MATCH(Reserves!$B20,'Investment Characteristics'!$K$4:$K$31,0)) -> 53000000 | I20: =INDEX('Investment Characteristics'!$F$4:$F$33,MATCH(Reserves!$B20,'Investment Characteristics'!$B$4:$B$33,0)) -> 3999999.7 | J20: =K20-I20 -> 1000000 | K20: =INDEX('Investment Characteristics'!$S$4:$S$33,MATCH(Reserves!$B20,'Investment Characteristics'!$B$4:$B$33,0)) -> 4999999.7 | M20: =15*10^6 -> 15000000 | N20: =+M20*E20 -> 1169024.8 | O20: 1000000 | P20: =O20+K20 -> 5999999.7 | R20: Q4'25 | U20: Total | V20: =SUM(V15:V19) -> 33000000 | W20: =SUM(W15:W19) -> 24764787 | X20: =SUM(X15:X19) -> 5000000 | Y20: =SUM(Y15:Y19) -> 3235213.1 | Z20: =+(W20+X20)/V20 -> 0.90196324 | AB20: Total | AC20: =SUM(AC15:AC19) -> 33000000 | AD20: =SUM(AD15:AD19) -> 28642822 | AE20: =SUM(AE15:AE19) -> 5000000 | AF20: =SUM(AF15:AF19) -> -642821.61 | AG20: =+(AD20+AE20)/AC20 -> 1.0194794
B21: Solara | C21: =INDEX('Investment Characteristics'!$X$4:$X$31,MATCH(Reserves!$B21,'Investment Characteristics'!$K$4:$K$31,0)) -> GG | D21: =INDEX('Investment Characteristics'!$L$4:$L$31,MATCH(Reserves!$B21,'Investment Characteristics'!$K$4:$K$31,0)) -> Seed | E21: =INDEX('Investment Characteristics'!$M$4:$M$31,MATCH(Reserves!$B21,'Investment Characteristics'!$K$4:$K$31,0)) -> 0.1309 | F21: =INDEX('Investment Characteristics'!$O$4:$O$31,MATCH(Reserves!$B21,'Investment Characteristics'!$K$4:$K$31,0)) -> 14500000 | G21: =INDEX('Investment Characteristics'!$Q$4:$Q$31,MATCH(Reserves!$B21,'Investment Characteristics'!$K$4:$K$31,0)) -> 40000000 | I21: =INDEX('Investment Characteristics'!$F$4:$F$33,MATCH(Reserves!$B21,'Investment Characteristics'!$B$4:$B$33,0)) -> 1999999.8 | J21: =K21-I21 -> 2552199 | K21: =INDEX('Investment Characteristics'!$S$4:$S$33,MATCH(Reserves!$B21,'Investment Characteristics'!$B$4:$B$33,0)) -> 4552198.8 | M21: =15*10^6 -> 15000000 | N21: =+M21*E21 -> 1963500 | O21: 0 | P21: =O21+K21 -> 4552198.8 | R21: Q2'26 | U21: Companies | V21: 8 | W21: =+COUNTIF(Reserves!$C$11:$C$32,Reserves!U13) -> 7 | Y21: =+V21-W21 -> 1 | Z21: =+W21/V21 -> 0.875 | AB21: Companies | AC21: 8 | AD21: =+COUNTIF(Reserves!$C$11:$C$32,Reserves!AB13) -> 7 | AF21: =+AC21-AD21 -> 1 | AG21: =+AD21/AC21 -> 0.875
B22: Thatch | C22: =INDEX('Investment Characteristics'!$X$4:$X$31,MATCH(Reserves!$B22,'Investment Characteristics'!$K$4:$K$31,0)) -> GG | D22: =INDEX('Investment Characteristics'!$L$4:$L$31,MATCH(Reserves!$B22,'Investment Characteristics'!$K$4:$K$31,0)) -> B | E22: =INDEX('Investment Characteristics'!$M$4:$M$31,MATCH(Reserves!$B22,'Investment Characteristics'!$K$4:$K$31,0)) -> 0.032141794 | F22: =INDEX('Investment Characteristics'!$O$4:$O$31,MATCH(Reserves!$B22,'Investment Characteristics'!$K$4:$K$31,0)) -> 50835341 | G22: =INDEX('Investment Characteristics'!$Q$4:$Q$31,MATCH(Reserves!$B22,'Investment Characteristics'!$K$4:$K$31,0)) -> 450000000 | I22: 1640635 | J22: =K22-I22 -> 2399990.2 | K22: =INDEX('Investment Characteristics'!$S$4:$S$33,MATCH(Reserves!$B22,'Investment Characteristics'!$B$4:$B$33,0)) -> 4040625.2 | M22: =N49 -> 50000000 | N22: =+M22*E22 -> 1607089.7 | O22: 0 | P22: =O22+K22 -> 4040625.2 | R22: Q1'25 | U22: Ownership | V22: 0.07 | W22: =+AVERAGEIF(Reserves!$C$11:$C$32,Reserves!U13,Reserves!$E$11:$E$32) -> 0.069505234 | AB22: Ownership | AC22: 0.07 | AD22: =+AVERAGEIF(Reserves!$C$11:$C$32,Reserves!AB13,Reserves!$E$11:$E$32) -> 0.069505234
B23: Onboarded | C23: =INDEX('Investment Characteristics'!$X$4:$X$31,MATCH(Reserves!$B23,'Investment Characteristics'!$K$4:$K$31,0)) -> GG | D23: =INDEX('Investment Characteristics'!$L$4:$L$31,MATCH(Reserves!$B23,'Investment Characteristics'!$K$4:$K$31,0)) -> A | E23: =INDEX('Investment Characteristics'!$M$4:$M$31,MATCH(Reserves!$B23,'Investment Characteristics'!$K$4:$K$31,0)) -> 0.086956522 | F23: =INDEX('Investment Characteristics'!$O$4:$O$31,MATCH(Reserves!$B23,'Investment Characteristics'!$K$4:$K$31,0)) -> 57500000 | G23: =INDEX('Investment Characteristics'!$Q$4:$Q$31,MATCH(Reserves!$B23,'Investment Characteristics'!$K$4:$K$31,0)) -> 57500000 | I23: =INDEX('Investment Characteristics'!$F$4:$F$33,MATCH(Reserves!$B23,'Investment Characteristics'!$B$4:$B$33,0)) -> 5000000 | J23: =K23-I23 -> 0 | K23: =INDEX('Investment Characteristics'!$S$4:$S$33,MATCH(Reserves!$B23,'Investment Characteristics'!$B$4:$B$33,0)) -> 5000000 | M23: =N48 -> 30000000 | N23: =+M23*E23 -> 2608695.7 | O23: 1000000 | P23: =O23+K23 -> 6000000 | R23: Q3 '25
B24: PenguinAI | C24: =INDEX('Investment Characteristics'!$X$4:$X$31,MATCH(Reserves!$B24,'Investment Characteristics'!$K$4:$K$31,0)) -> GG | D24: =INDEX('Investment Characteristics'!$L$4:$L$31,MATCH(Reserves!$B24,'Investment Characteristics'!$K$4:$K$31,0)) -> A | E24: =INDEX('Investment Characteristics'!$M$4:$M$31,MATCH(Reserves!$B24,'Investment Characteristics'!$K$4:$K$31,0)) -> 0.02527 | F24: =INDEX('Investment Characteristics'!$O$4:$O$31,MATCH(Reserves!$B24,'Investment Characteristics'!$K$4:$K$31,0)) -> 165000000 | G24: =INDEX('Investment Characteristics'!$Q$4:$Q$31,MATCH(Reserves!$B24,'Investment Characteristics'!$K$4:$K$31,0)) -> 165000000 | I24: =INDEX('Investment Characteristics'!$F$4:$F$33,MATCH(Reserves!$B24,'Investment Characteristics'!$B$4:$B$33,0)) -> 4000000 | J24: =K24-I24 -> 0 | K24: =INDEX('Investment Characteristics'!$S$4:$S$33,MATCH(Reserves!$B24,'Investment Characteristics'!$B$4:$B$33,0)) -> 4000000 | M24: =N48 -> 30000000 | N24: =+M24*E24 -> 758100 | O24: 0 | P24: =O24+K24 -> 4000000 | R24: Q1'26 | U24: ABG | AB24: ABG
B25: Trial Library | C25: =INDEX('Investment Characteristics'!$X$4:$X$31,MATCH(Reserves!$B25,'Investment Characteristics'!$K$4:$K$31,0)) -> GG | D25: Seed | E25: 0.066666667 | F25: =INDEX('Investment Characteristics'!$O$4:$O$31,MATCH(Reserves!$B25,'Investment Characteristics'!$K$4:$K$31,0)) -> 50000000 | G25: =INDEX('Investment Characteristics'!$Q$4:$Q$31,MATCH(Reserves!$B25,'Investment Characteristics'!$K$4:$K$31,0)) -> 50000000 | I25: =INDEX('Investment Characteristics'!$F$4:$F$33,MATCH(Reserves!$B25,'Investment Characteristics'!$B$4:$B$33,0)) -> 2999998 | J25: =K25-I25 -> 0 | K25: =INDEX('Investment Characteristics'!$S$4:$S$33,MATCH(Reserves!$B25,'Investment Characteristics'!$B$4:$B$33,0)) -> 2999998 | M25: =N47 -> 20000000 | N25: =+M25*E25 -> 1333333.3 | O25: 2000000 | P25: =O25+K25 -> 4999998 | R25: Q1'26 | V25: Target | W25: Actual | X25: Reserved | Y25: Remaining | Z25: % | AC25: Target | AD25: Actual | AE25: Reserved | AF25: Remaining | AG25: %
B26: Helm | C26: GG | D26: A | E26: =3000000/F26 -> 0.066666667 | F26: 45000000 | G26: 45000000 | I26: =INDEX('Investment Characteristics'!$F$4:$F$33,MATCH(Reserves!$B26,'Investment Characteristics'!$B$4:$B$33,0)) -> 3000000 | J26: 0 | K26: =INDEX('Investment Characteristics'!$F$4:$F$33,MATCH(Reserves!$B26,'Investment Characteristics'!$B$4:$B$33,0)) -> 3000000 | M26: =N48 -> 30000000 | N26: =+M26*E26 -> 2000000 | O26: 1000000 | P26: =O26+K26 -> 4000000
B27: Summer | C27: =INDEX('Investment Characteristics'!$X$4:$X$31,MATCH(Reserves!$B27,'Investment Characteristics'!$K$4:$K$31,0)) -> RP | D27: =INDEX('Investment Characteristics'!$L$4:$L$31,MATCH(Reserves!$B27,'Investment Characteristics'!$K$4:$K$31,0)) -> A | E27: =INDEX('Investment Characteristics'!$M$4:$M$31,MATCH(Reserves!$B27,'Investment Characteristics'!$K$4:$K$31,0)) -> 0.11734531 | F27: =INDEX('Investment Characteristics'!$O$4:$O$31,MATCH(Reserves!$B27,'Investment Characteristics'!$K$4:$K$31,0)) -> 35000000 | G27: =INDEX('Investment Characteristics'!$Q$4:$Q$31,MATCH(Reserves!$B27,'Investment Characteristics'!$K$4:$K$31,0)) -> 41544018 | I27: =INDEX('Investment Characteristics'!$F$4:$F$33,MATCH(Reserves!$B27,'Investment Characteristics'!$B$4:$B$33,0)) -> 3250000 | J27: =K27-I27 -> 0 | K27: =INDEX('Investment Characteristics'!$S$4:$S$33,MATCH(Reserves!$B27,'Investment Characteristics'!$B$4:$B$33,0)) -> 3250000 | M27: =N47 -> 20000000 | N27: =+M27*E27 -> 2346906.2 | O27: 0 | P27: =O27+K27 -> 3250000 | R27: Q4'25 | S27: Q3'25 | U27: Invested | V27: =20*10^6-V29 -> 19850000 | W27: =+SUMIF(Reserves!$C$11:$C$32,Reserves!U24,Reserves!$I$11:$I$32) -> 17564872 | X27: 0 | Y27: =V27-W27-X27 -> 2285127.9 | Z27: =+W27/V27 -> 0.8848802 | AB27: Invested | AC27: =20*10^6-AC29 -> 19850000 | AD27: =+SUMIF(Reserves!$C$11:$C$32,Reserves!AB24,Reserves!$I$11:$I$32) -> 17564872 | AE27: 0 | AF27: =AC27-AD27-AE27 -> 2285127.9 | AG27: =+AD27/AC27 -> 0.8848802
B28: Kubera | C28: =INDEX('Investment Characteristics'!$X$4:$X$31,MATCH(Reserves!$B28,'Investment Characteristics'!$K$4:$K$31,0)) -> RP | D28: Seed | E28: =INDEX('Investment Characteristics'!$M$4:$M$31,MATCH(Reserves!$B28,'Investment Characteristics'!$K$4:$K$31,0)) -> 0.033713855 | F28: =INDEX('Investment Characteristics'!$O$4:$O$31,MATCH(Reserves!$B28,'Investment Characteristics'!$K$4:$K$31,0)) -> 12000000 | G28: =INDEX('Investment Characteristics'!$Q$4:$Q$31,MATCH(Reserves!$B28,'Investment Characteristics'!$K$4:$K$31,0)) -> 30000000 | I28: =INDEX('Investment Characteristics'!$F$4:$F$33,MATCH(Reserves!$B28,'Investment Characteristics'!$B$4:$B$33,0)) -> 399999.2 | J28: =K28-I28 -> 128083.47 | K28: =INDEX('Investment Characteristics'!$S$4:$S$33,MATCH(Reserves!$B28,'Investment Characteristics'!$B$4:$B$33,0)) -> 528082.67 | M28: =N47 -> 20000000 | N28: =+M28*E28 -> 674277.1 | O28: 1000000 | P28: =O28+K28 -> 1528082.7 | S28: Q3'25 | U28: Reserved | V28: =13*10^6-V30 -> 11500000 | W28: =+SUMIF(Reserves!$C$11:$C$32,Reserves!U24,Reserves!$J$11:$J$32) -> 3878034.7 | X28: =+SUMIF(Reserves!$C$11:$C$32,Reserves!U24,Reserves!$O$11:$O$32) -> 4000000 | Y28: =V28-W28-X28 -> 3621965.3 | Z28: =+W28/V28 -> 0.33722041 | AB28: Reserved | AC28: =13*10^6-AC30 -> 11500000 | AD28: =+SUMIF(Reserves!$C$11:$C$32,Reserves!AB24,Reserves!$J$11:$J$32) -> 3878034.7 | AE28: =+SUMIF(Reserves!$C$11:$C$32,Reserves!AB24,Reserves!$O$11:$O$32) -> 4000000 | AF28: =AC28-AD28-AE28 -> 3621965.3 | AG28: =+AD28/AC28 -> 0.33722041
B29: Hireguide | C29: =INDEX('Investment Characteristics'!$X$4:$X$31,MATCH(Reserves!$B29,'Investment Characteristics'!$K$4:$K$31,0)) -> RP | D29: =INDEX('Investment Characteristics'!$L$4:$L$31,MATCH(Reserves!$B29,'Investment Characteristics'!$K$4:$K$31,0)) -> Seed | E29: =INDEX('Investment Characteristics'!$M$4:$M$31,MATCH(Reserves!$B29,'Investment Characteristics'!$K$4:$K$31,0)) -> 0.09375 | F29: =INDEX('Investment Characteristics'!$O$4:$O$31,MATCH(Reserves!$B29,'Investment Characteristics'!$K$4:$K$31,0)) -> 32000000 | G29: =INDEX('Investment Characteristics'!$Q$4:$Q$31,MATCH(Reserves!$B29,'Investment Characteristics'!$K$4:$K$31,0)) -> 32000000 | I29: =INDEX('Investment Characteristics'!$F$4:$F$33,MATCH(Reserves!$B29,'Investment Characteristics'!$B$4:$B$33,0)) -> 3000000 | J29: =K29-I29 -> 0 | K29: =INDEX('Investment Characteristics'!$S$4:$S$33,MATCH(Reserves!$B29,'Investment Characteristics'!$B$4:$B$33,0)) -> 3000000 | M29: =N47 -> 20000000 | N29: =+M29*E29 -> 1875000 | O29: 0 | P29: =O29+K29 -> 3000000 | R29: Q4'25 | S29: Q3'25 | U29: SVA Initial | V29: =3*50000 -> 150000 | W29: =+I38 -> 250000 | X29: 0 | Y29: =V29-W29-X29 -> -100000 | Z29: =+W29/V29 -> 1.6666667 | AB29: SVA Initial | AC29: =3*50000 -> 150000 | AD29: 0 | AE29: 0 | AF29: =AC29-AD29-AE29 -> 150000 | AG29: =+AD29/AC29 -> 0
B30: OneImaging | C30: =INDEX('Investment Characteristics'!$X$4:$X$31,MATCH(Reserves!$B30,'Investment Characteristics'!$K$4:$K$31,0)) -> RP | D30: =INDEX('Investment Characteristics'!$L$4:$L$31,MATCH(Reserves!$B30,'Investment Characteristics'!$K$4:$K$31,0)) -> A | E30: =INDEX('Investment Characteristics'!$M$4:$M$31,MATCH(Reserves!$B30,'Investment Characteristics'!$K$4:$K$31,0)) -> 0.05994 | F30: =INDEX('Investment Characteristics'!$O$4:$O$31,MATCH(Reserves!$B30,'Investment Characteristics'!$K$4:$K$31,0)) -> 18000000 | G30: =INDEX('Investment Characteristics'!$Q$4:$Q$31,MATCH(Reserves!$B30,'Investment Characteristics'!$K$4:$K$31,0)) -> 250000000 | I30: =INDEX('Investment Characteristics'!$F$4:$F$33,MATCH(Reserves!$B30,'Investment Characteristics'!$B$4:$B$33,0)) -> 1000000 | J30: =K30-I30 -> 3000000 | K30: =INDEX('Investment Characteristics'!$S$4:$S$33,MATCH(Reserves!$B30,'Investment Characteristics'!$B$4:$B$33,0)) -> 4000000 | M30: =N48 -> 30000000 | N30: =+M30*E30 -> 1798200 | O30: 2000000 | P30: =O30+K30 -> 6000000 | S30: Q3'25 | U30: SVA Reserved | V30: =1.5*1000000 -> 1500000 | W30: 0 | X30: 0 | Y30: =V30-W30-X30 -> 1500000 | Z30: =+W30/V30 -> 0 | AB30: SVA Reserved | AC30: =1.5*1000000 -> 1500000 | AD30: 0 | AE30: 0 | AF30: =AC30-AD30-AE30 -> 1500000 | AG30: =+AD30/AC30 -> 0
B31: Athena.AI | C31: =INDEX('Investment Characteristics'!$X$4:$X$31,MATCH(Reserves!$B31,'Investment Characteristics'!$K$4:$K$31,0)) -> RP | D31: =INDEX('Investment Characteristics'!$L$4:$L$31,MATCH(Reserves!$B31,'Investment Characteristics'!$K$4:$K$31,0)) -> Seed | E31: =INDEX('Investment Characteristics'!$M$4:$M$31,MATCH(Reserves!$B31,'Investment Characteristics'!$K$4:$K$31,0)) -> 0.09 | F31: =INDEX('Investment Characteristics'!$O$4:$O$31,MATCH(Reserves!$B31,'Investment Characteristics'!$K$4:$K$31,0)) -> 35000000 | G31: =INDEX('Investment Characteristics'!$Q$4:$Q$31,MATCH(Reserves!$B31,'Investment Characteristics'!$K$4:$K$31,0)) -> 35000000 | I31: =INDEX('Investment Characteristics'!$F$4:$F$33,MATCH(Reserves!$B31,'Investment Characteristics'!$B$4:$B$33,0)) -> 3150000 | J31: =K31-I31 -> 0 | K31: =INDEX('Investment Characteristics'!$S$4:$S$33,MATCH(Reserves!$B31,'Investment Characteristics'!$B$4:$B$33,0)) -> 3150000 | M31: =N47 -> 20000000 | N31: =+M31*E31 -> 1800000 | O31: =3*10^6 -> 3000000 | P31: =O31+K31 -> 6150000 | S31: Q3'25
B32: Tezi | C32: =INDEX('Investment Characteristics'!$X$4:$X$31,MATCH(Reserves!$B32,'Investment Characteristics'!$K$4:$K$31,0)) -> RP | D32: =INDEX('Investment Characteristics'!$L$4:$L$31,MATCH(Reserves!$B32,'Investment Characteristics'!$K$4:$K$31,0)) -> Seed | E32: =INDEX('Investment Characteristics'!$M$4:$M$31,MATCH(Reserves!$B32,'Investment Characteristics'!$K$4:$K$31,0)) -> 0.033333283 | F32: =INDEX('Investment Characteristics'!$O$4:$O$31,MATCH(Reserves!$B32,'Investment Characteristics'!$K$4:$K$31,0)) -> 60000000 | G32: =INDEX('Investment Characteristics'!$Q$4:$Q$31,MATCH(Reserves!$B32,'Investment Characteristics'!$K$4:$K$31,0)) -> 60000000 | I32: =INDEX('Investment Characteristics'!$F$4:$F$33,MATCH(Reserves!$B32,'Investment Characteristics'!$B$4:$B$33,0)) -> 1999997 | J32: =K32-I32 -> 0 | K32: =INDEX('Investment Characteristics'!$S$4:$S$33,MATCH(Reserves!$B32,'Investment Characteristics'!$B$4:$B$33,0)) -> 1999997 | M32: =N47 -> 20000000 | N32: =+M32*E32 -> 666665.67 | O32: 2000000 | P32: =O32+K32 -> 3999997 | R32: Q4'25 | S32: Q3'25 | U32: RP | AB32: RP
B33: Total | I33: =SUM(I11:I32) -> 59005499 | J33: =SUM(J11:J32) -> 15958305 | K33: =SUM(K11:K32) -> 74963804 | O33: =SUM(O11:O32) -> 21500000 | P33: =SUM(P11:P32) -> 96463804 | U33: Invested | V33: =20*10^6-V36 -> 19850000 | W33: =+SUMIF(Reserves!$C$11:$C$32,Reserves!U32,Reserves!$I$11:$I$32) -> 12799996 | X33: 0 | Y33: =V33-W33-X33 -> 7050003.8 | Z33: =+W33/V33 -> 0.64483608 | AB33: Invested | AC33: =20*10^6-AC36 -> 19850000 | AD33: =+SUMIF(Reserves!$C$11:$C$32,Reserves!AB32,Reserves!$I$11:$I$32) -> 12799996 | AE33: 0 | AF33: =AC33-AD33-AE33 -> 7050003.8 | AG33: =+AD33/AC33 -> 0.64483608
U34: Reserved | V34: =13*10^6-V37 -> 11500000 | W34: =+SUMIF(Reserves!$C$11:$C$32,Reserves!U32,Reserves!$J$11:$J$32)+J11 -> 7006118.2 | X34: =+SUMIF(Reserves!$C$11:$C$32,Reserves!U32,Reserves!$O$11:$O$32) -> 8000000 | Y34: =V34-W34-X34 -> -3506118.2 | Z34: =+W34/V34 -> 0.60922767 | AB34: Reserved | AC34: =13*10^6-AC37 -> 11500000 | AD34: =+SUMIF(Reserves!$C$11:$C$32,Reserves!AB32,Reserves!$J$11:$J$32)+Q11 -> 3128083.5 | AE34: =+SUMIF(Reserves!$C$11:$C$32,Reserves!AB32,Reserves!$O$11:$O$32) -> 8000000 | AF34: =AC34-AD34-AE34 -> 371916.53 | AG34: =+AD34/AC34 -> 0.27200726
I36: Initial | K36: Total | R36: Timing of | U36: SVA Initial | V36: =3*50000 -> 150000 | W36: =+I40 -> 50000 | X36: 0 | Y36: =V36-W36-X36 -> 100000 | Z36: =+W36/V36 -> 0.33333333 | AB36: SVA Initial | AC36: =3*50000 -> 150000 | AD36: 0 | AE36: 0 | AF36: =AC36-AD36-AE36 -> 150000 | AG36: =+AD36/AC36 -> 0
B37: Company | C37: Owner | D37: Current Stage | E37: Ownership | F37: Initial Valuation | G37: Last Valuation | I37: $ Invested | J37: Follow-Ons | K37: Invested | M37: Round Size | N37: Implied Pro-rata | O37: Reserves | P37: Inv. and Reserved | R37: Next Round | S37: Last Updated | U37: SVA Reserved | V37: =1.5*1000000 -> 1500000 | W37: 0 | X37: 0 | Y37: =V37-W37-X37 -> 1500000 | Z37: =+W37/V37 -> 0 | AB37: SVA Reserved | AC37: =1.5*1000000 -> 1500000 | AD37: 0 | AE37: 0 | AF37: =AC37-AD37-AE37 -> 1500000 | AG37: =+AD37/AC37 -> 0
B38: Clasp | C38: SVA - CH | D38: Seed | E38: 0.0071428571 | F38: 35000000 | G38: =F38 -> 35000000 | I38: 250000 | J38: 0 | K38: 250000 | O38: 0 | P38: =O38+K38 -> 250000 | U38: Total | V38: =SUM(V27:V30) -> 33000000 | W38: =SUM(W27:W30) -> 21692907 | X38: =SUM(X27:X30) -> 4000000 | Y38: =SUM(Y27:Y30) -> 7307093.2 | Z38: =+(W38+X38)/V38 -> 0.77857293 | AB38: Total | AC38: =SUM(AC27:AC30) -> 33000000 | AD38: =SUM(AD27:AD30) -> 21442907 | AE38: =SUM(AE27:AE30) -> 4000000 | AF38: =SUM(AF27:AF30) -> 7557093.2 | AG38: =+(AD38+AE38)/AC38 -> 0.77099718
B39: Sunny Health | C39: SVA - RP | D39: Seed | E39: 0.003125 | F39: 16000000 | G39: =F39 -> 16000000 | I39: 250000 | J39: 0 | K39: 50000 | O39: 0 | P39: =O39+K39 -> 50000 | U39: Companies | V39: 8 | W39: =+COUNTIF(Reserves!$C$11:$C$32,Reserves!U24) -> 6 | Y39: =+V39-W39 -> 2 | Z39: =+W39/V39 -> 0.75 | AB39: Companies | AC39: 8 | AD39: =+COUNTIF(Reserves!$C$11:$C$32,Reserves!AB24) -> 6 | AF39: =+AC39-AD39 -> 2 | AG39: =+AD39/AC39 -> 0.75
B40: Outro Health | C40: SVA - ABG | D40: Seed | E40: 0.025 | F40: 10000000 | G40: =F40 -> 10000000 | I40: 50000 | J40: 0 | K40: 250000 | O40: 0 | P40: =O40+K40 -> 250000 | U40: Ownership | V40: 0.07 | W40: =+AVERAGEIF(Reserves!$C$11:$C$32,Reserves!U24,Reserves!$E$11:$E$32) -> 0.060119378 | AB40: Ownership | AC40: 0.07 | AD40: =+AVERAGEIF(Reserves!$C$11:$C$32,Reserves!AB24,Reserves!$E$11:$E$32) -> 0.060119378
B41: TrueClaim | C41: SVA - GG | D41: Seed | E41: 0.010416667 | F41: 24000000 | G41: =+F41 -> 24000000 | K41: 250000 | O41: 0 | P41: =O41+K41 -> 250000
B42: Andel | C42: SVA - ABG | D42: Seed | E42: 0.011111111 | F42: 22500000 | G42: =+F42 -> 22500000 | K42: 250000 | O42: 0 | P42: =O42+K42 -> 250000
B43: Second Door | C43: SVA - RP | D43: Seed | E43: 0.017857143 | F43: 14000000 | G43: =+F43 -> 14000000 | K43: 250000 | O43: 0 | P43: =O43+K43 -> 250000
B44: Total | I44: =SUM(I38:I40) -> 550000 | J44: =SUM(J38:J40) -> 0 | K44: =SUM(K38:K43) -> 1300000 | O44: =SUM(O38:O40) -> 0 | P44: =SUM(P38:P43) -> 1300000
U45: CH | AB45: CH
V46: Target | W46: Actual | X46: Reserved | Y46: Remaining | Z46: % | AC46: Target | AD46: Actual | AE46: Reserved | AF46: Remaining | AG46: %
L47: A | M47: Seed | N47: =20*10^6 -> 20000000 | U47: Invested | V47: =10*10^6-V49 -> 9850000 | W47: =+SUMIF(Reserves!$C$11:$C$32,Reserves!U45,Reserves!$I$11:$I$32) -> 5999998 | X47: 0 | Y47: =V47-W47-X47 -> 3850002 | Z47: =+W47/V47 -> 0.60913686 | AB47: Invested | AC47: =10*10^6-AC49 -> 9850000 | AD47: =+SUMIF(Reserves!$C$11:$C$32,Reserves!AB45,Reserves!$I$11:$I$32) -> 5999998 | AE47: 0 | AF47: =AC47-AD47-AE47 -> 3850002 | AG47: =+AD47/AC47 -> 0.60913686
L48: B | M48: A | N48: =30*10^6 -> 30000000 | U48: Reserved | V48: =6.5*10^6-#REF! -> #REF! | W48: =+SUMIF(Reserves!$C$11:$C$32,Reserves!U45,Reserves!$J$11:$J$32) -> 2999997.9 | X48: =+SUMIF(Reserves!$C$11:$C$32,Reserves!U45,Reserves!$O$11:$O$32) -> 4500000 | Y48: =V48-W48-X48 -> #REF! | Z48: =+W48/V48 -> #REF! | AB48: Reserved | AC48: =6.5*10^6-#REF! -> #REF! | AD48: =+SUMIF(Reserves!$C$11:$C$32,Reserves!AB45,Reserves!$J$11:$J$32) -> 2999997.9 | AE48: =+SUMIF(Reserves!$C$11:$C$32,Reserves!AB45,Reserves!$O$11:$O$32) -> 4500000 | AF48: =AC48-AD48-AE48 -> #REF! | AG48: =+AD48/AC48 -> #REF!
L49: C | M49: B | N49: =50*10^6 -> 50000000 | U49: SVA Initial | V49: =3*50000 -> 150000 | W49: =+I39 -> 250000 | X49: 0 | Y49: =V49-W49-X49 -> -100000 | Z49: =+W49/V49 -> 1.6666667 | AB49: SVA Initial | AC49: =3*50000 -> 150000 | AD49: 0 | AE49: 0 | AF49: =AC49-AD49-AE49 -> 150000 | AG49: =+AD49/AC49 -> 0
I50: =2/70 -> 0.028571429 | U50: Total | V50: =SUM(V47:V49) -> #REF! | W50: =SUM(W47:W49) -> 9249995.9 | X50: =SUM(X47:X49) -> 4500000 | Y50: =SUM(Y47:Y49) -> #REF! | Z50: =+(W50+X50)/V50 -> #REF! | AB50: Total | AC50: =SUM(AC47:AC49) -> #REF! | AD50: =SUM(AD47:AD49) -> 8999995.9 | AE50: =SUM(AE47:AE49) -> 4500000 | AF50: =SUM(AF47:AF49) -> #REF! | AG50: =+(AD50+AE50)/AC50 -> #REF!
I51: =+E12*(0.95) -> 0.0665 | U51: Companies | V51: 4 | W51: =+COUNTIF(Reserves!$C$11:$C$32,Reserves!U45) -> 3 | Y51: =+V51-W51 -> 1 | Z51: =+W51/V51 -> 0.75 | AB51: Companies | AC51: 4 | AD51: =+COUNTIF(Reserves!$C$11:$C$32,Reserves!AB45) -> 3 | AF51: =+AC51-AD51 -> 1 | AG51: =+AD51/AC51 -> 0.75
U52: Ownership | V52: 0.07 | W52: =+AVERAGEIF(Reserves!$C$11:$C$32,Reserves!U45,Reserves!$E$11:$E$32) -> 0.060408055 | AB52: Ownership | AC52: 0.07 | AD52: =+AVERAGEIF(Reserves!$C$11:$C$32,Reserves!AB45,Reserves!$E$11:$E$32) -> 0.060408055

Sheet Exit Forecast
C2: Full Fund | D2: Inv. Capital
B3: Amount | C3: =142*10^6 -> 142000000 | D3: =+L34 -> 52173809
A4: 5 | B4: 5x Gross Target | C4: =+C3*A4 -> 710000000 | D4: =+D3*A4 -> 2.6086904e+08
B5: Current Proj. | C5: =+T34 -> 2.3792672e+08 | D5: =+T34 -> 2.3792672e+08
B6: Surplus/(Shortfall) | C6: =+C5-C4 -> -4.7207328e+08 | D6: =+D5-D4 -> -22942326 | O6: Partner Input
I7: To be updated
L8: Total | M8: Market | O8: 0.25 | P8: 0.5 | Q8: 0.25
B9: Company | C9: Owner | D9: Current Stage | E9: Ownership | F9: Last Valuation | G9: Holding Value | I9: '24A Rev | J9: '25E Rev | L9: Invested | M9: Value | O9: Bear | P9: Base | Q9: Bull | S9: Weighted Exit | T9: Proceeds | U9: MOIC | W9: Last Updated
B10: Laguna Health | C10: =INDEX('Investment Characteristics'!$X$4:$X$31,MATCH('Exit Forecast'!$B10,'Investment Characteristics'!$K$4:$K$31,0)) -> GG | D10: =INDEX('Investment Characteristics'!$L$4:$L$31,MATCH('Exit Forecast'!$B10,'Investment Characteristics'!$K$4:$K$31,0)) -> A | E10: =INDEX('Investment Characteristics'!$M$4:$M$31,MATCH('Exit Forecast'!$B10,'Investment Characteristics'!$K$4:$K$31,0)) -> 0.077934988 | F10: =INDEX('Investment Characteristics'!$Q$4:$Q$31,MATCH('Exit Forecast'!$B10,'Investment Characteristics'!$K$4:$K$31,0)) -> 53000000 | G10: =INDEX('Investment Characteristics'!$R$4:$R$31,MATCH('Exit Forecast'!$B10,'Investment Characteristics'!$K$4:$K$31,0)) -> 53000000 | L10: =INDEX('Investment Characteristics'!$S$4:$S$33,MATCH('Exit Forecast'!$B10,'Investment Characteristics'!$B$4:$B$33,0)) -> 4999999.7 | M10: =INDEX('Investment Characteristics'!$U$4:$U$33,MATCH('Exit Forecast'!$B10,'Investment Characteristics'!$B$4:$B$33,0)) -> 4999999.7 | O10: =+F10 -> 53000000 | P10: 100000000 | Q10: 700000000 | S10: =+IFERROR(O10*$O$8+P10*$P$8+Q10*$Q$8,"") -> 238250000 | T10: =IFERROR(+(S10/G10)*M10,"") -> 22476414 | U10: =IFERROR(T10/M10,"") -> 4.495283
B11: Stepful | C11: =INDEX('Investment Characteristics'!$X$4:$X$31,MATCH('Exit Forecast'!$B11,'Investment Characteristics'!$K$4:$K$31,0)) -> ABG | D11: =INDEX('Investment Characteristics'!$L$4:$L$31,MATCH('Exit Forecast'!$B11,'Investment Characteristics'!$K$4:$K$31,0)) -> B | E11: =INDEX('Investment Characteristics'!$M$4:$M$31,MATCH('Exit Forecast'!$B11,'Investment Characteristics'!$K$4:$K$31,0)) -> 0.052805468 | F11: =INDEX('Investment Characteristics'!$Q$4:$Q$31,MATCH('Exit Forecast'!$B11,'Investment Characteristics'!$K$4:$K$31,0)) -> 261500000 | G11: =INDEX('Investment Characteristics'!$R$4:$R$31,MATCH('Exit Forecast'!$B11,'Investment Characteristics'!$K$4:$K$31,0)) -> 261500000 | L11: =INDEX('Investment Characteristics'!$S$4:$S$33,MATCH('Exit Forecast'!$B11,'Investment Characteristics'!$B$4:$B$33,0)) -> 7878030.5 | M11: =INDEX('Investment Characteristics'!$U$4:$U$33,MATCH('Exit Forecast'!$B11,'Investment Characteristics'!$B$4:$B$33,0)) -> 13609280 | O11: =+F11 -> 261500000 | P11: =750*10^6 -> 750000000 | Q11: =3000*10^6 -> 3000000000 | S11: =+IFERROR(O11*$O$8+P11*$P$8+Q11*$Q$8,"") -> 1190375000 | T11: =IFERROR(+(S11/G11)*M11,"") -> 61950846 | U11: =IFERROR(T11/M11,"") -> 4.5521033
B12: Summer | C12: =INDEX('Investment Characteristics'!$X$4:$X$31,MATCH('Exit Forecast'!$B12,'Investment Characteristics'!$K$4:$K$31,0)) -> RP | D12: =INDEX('Investment Characteristics'!$L$4:$L$31,MATCH('Exit Forecast'!$B12,'Investment Characteristics'!$K$4:$K$31,0)) -> A | E12: =INDEX('Investment Characteristics'!$M$4:$M$31,MATCH('Exit Forecast'!$B12,'Investment Characteristics'!$K$4:$K$31,0)) -> 0.11734531 | F12: =INDEX('Investment Characteristics'!$Q$4:$Q$31,MATCH('Exit Forecast'!$B12,'Investment Characteristics'!$K$4:$K$31,0)) -> 41544018 | G12: =INDEX('Investment Characteristics'!$R$4:$R$31,MATCH('Exit Forecast'!$B12,'Investment Characteristics'!$K$4:$K$31,0)) -> 41544018 | L12: =INDEX('Investment Characteristics'!$S$4:$S$33,MATCH('Exit Forecast'!$B12,'Investment Characteristics'!$B$4:$B$33,0)) -> 3250000 | M12: =INDEX('Investment Characteristics'!$U$4:$U$33,MATCH('Exit Forecast'!$B12,'Investment Characteristics'!$B$4:$B$33,0)) -> 3250000 | O12: 0 | P12: =+G12 -> 41544018 | Q12: 50000000 | S12: =+IFERROR(O12*$O$8+P12*$P$8+Q12*$Q$8,"") -> 33272009 | T12: =IFERROR(+(S12/G12)*M12,"") -> 2602878.5 | U12: =IFERROR(T12/M12,"") -> 0.80088568
B13: Wagmo | C13: =INDEX('Investment Characteristics'!$X$4:$X$31,MATCH('Exit Forecast'!$B13,'Investment Characteristics'!$K$4:$K$31,0)) -> CH | D13: =INDEX('Investment Characteristics'!$L$4:$L$31,MATCH('Exit Forecast'!$B13,'Investment Characteristics'!$K$4:$K$31,0)) -> A | E13: =INDEX('Investment Characteristics'!$M$4:$M$31,MATCH('Exit Forecast'!$B13,'Investment Characteristics'!$K$4:$K$31,0)) -> 0.029870094 | F13: =INDEX('Investment Characteristics'!$Q$4:$Q$31,MATCH('Exit Forecast'!$B13,'Investment Characteristics'!$K$4:$K$31,0)) -> 47200000 | G13: =INDEX('Investment Characteristics'!$R$4:$R$31,MATCH('Exit Forecast'!$B13,'Investment Characteristics'!$K$4:$K$31,0)) -> 47200000 | L13: =INDEX('Investment Characteristics'!$S$4:$S$33,MATCH('Exit Forecast'!$B13,'Investment Characteristics'!$B$4:$B$33,0)) -> 1499998 | M13: =INDEX('Investment Characteristics'!$U$4:$U$33,MATCH('Exit Forecast'!$B13,'Investment Characteristics'!$B$4:$B$33,0)) -> 1499998 | O13: =+F13 -> 47200000 | P13: 300000000 | Q13: 600000000 | S13: =+IFERROR(O13*$O$8+P13*$P$8+Q13*$Q$8,"") -> 311800000 | T13: =IFERROR(+(S13/G13)*M13,"") -> 9908885.4 | U13: =IFERROR(T13/M13,"") -> 6.6059322 | W13: 45686
B14: Kubera | C14: =INDEX('Investment Characteristics'!$X$4:$X$31,MATCH('Exit Forecast'!$B14,'Investment Characteristics'!$K$4:$K$31,0)) -> RP | D14: =INDEX('Investment Characteristics'!$L$4:$L$31,MATCH('Exit Forecast'!$B14,'Investment Characteristics'!$K$4:$K$31,0)) -> Seed | E14: =INDEX('Investment Characteristics'!$M$4:$M$31,MATCH('Exit Forecast'!$B14,'Investment Characteristics'!$K$4:$K$31,0)) -> 0.033713855 | F14: =INDEX('Investment Characteristics'!$Q$4:$Q$31,MATCH('Exit Forecast'!$B14,'Investment Characteristics'!$K$4:$K$31,0)) -> 30000000 | G14: =INDEX('Investment Characteristics'!$R$4:$R$31,MATCH('Exit Forecast'!$B14,'Investment Characteristics'!$K$4:$K$31,0)) -> 30000000 | L14: =INDEX('Investment Characteristics'!$S$4:$S$33,MATCH('Exit Forecast'!$B14,'Investment Characteristics'!$B$4:$B$33,0)) -> 528082.67 | M14: =INDEX('Investment Characteristics'!$U$4:$U$33,MATCH('Exit Forecast'!$B14,'Investment Characteristics'!$B$4:$B$33,0)) -> 1011413.2 | O14: 0 | P14: =+G14 -> 30000000 | Q14: =100*10^6 -> 100000000 | S14: =+IFERROR(O14*$O$8+P14*$P$8+Q14*$Q$8,"") -> 40000000 | T14: =IFERROR(+(S14/G14)*M14,"") -> 1348550.9 | U14: =IFERROR(T14/M14,"") -> 1.3333333
B15: Salsa | C15: =INDEX('Investment Characteristics'!$X$4:$X$31,MATCH('Exit Forecast'!$B15,'Investment Characteristics'!$K$4:$K$31,0)) -> CH | D15: =INDEX('Investment Characteristics'!$L$4:$L$31,MATCH('Exit Forecast'!$B15,'Investment Characteristics'!$K$4:$K$31,0)) -> A | E15: =INDEX('Investment Characteristics'!$M$4:$M$31,MATCH('Exit Forecast'!$B15,'Investment Characteristics'!$K$4:$K$31,0)) -> 0.084687403 | F15: =INDEX('Investment Characteristics'!$Q$4:$Q$31,MATCH('Exit Forecast'!$B15,'Investment Characteristics'!$K$4:$K$31,0)) -> 70000000 | G15: =INDEX('Investment Characteristics'!$R$4:$R$31,MATCH('Exit Forecast'!$B15,'Investment Characteristics'!$K$4:$K$31,0)) -> 70000000 | L15: =INDEX('Investment Characteristics'!$S$4:$S$33,MATCH('Exit Forecast'!$B15,'Investment Characteristics'!$B$4:$B$33,0)) -> 5499997.9 | M15: =INDEX('Investment Characteristics'!$U$4:$U$33,MATCH('Exit Forecast'!$B15,'Investment Characteristics'!$B$4:$B$33,0)) -> 5912934 | O15: =+G15 -> 70000000 | P15: 400000000 | Q15: 800000000 | S15: =+IFERROR(O15*$O$8+P15*$P$8+Q15*$Q$8,"") -> 417500000 | T15: =IFERROR(+(S15/G15)*M15,"") -> 35266428 | U15: =IFERROR(T15/M15,"") -> 5.9642857 | W15: 45686
B16: Solara | C16: =INDEX('Investment Characteristics'!$X$4:$X$31,MATCH('Exit Forecast'!$B16,'Investment Characteristics'!$K$4:$K$31,0)) -> GG | D16: =INDEX('Investment Characteristics'!$L$4:$L$31,MATCH('Exit Forecast'!$B16,'Investment Characteristics'!$K$4:$K$31,0)) -> Seed | E16: =INDEX('Investment Characteristics'!$M$4:$M$31,MATCH('Exit Forecast'!$B16,'Investment Characteristics'!$K$4:$K$31,0)) -> 0.1309 | F16: =INDEX('Investment Characteristics'!$Q$4:$Q$31,MATCH('Exit Forecast'!$B16,'Investment Characteristics'!$K$4:$K$31,0)) -> 40000000 | G16: =INDEX('Investment Characteristics'!$R$4:$R$31,MATCH('Exit Forecast'!$B16,'Investment Characteristics'!$K$4:$K$31,0)) -> 40000000 | L16: =INDEX('Investment Characteristics'!$S$4:$S$33,MATCH('Exit Forecast'!$B16,'Investment Characteristics'!$B$4:$B$33,0)) -> 4552198.8 | M16: =INDEX('Investment Characteristics'!$U$4:$U$33,MATCH('Exit Forecast'!$B16,'Investment Characteristics'!$B$4:$B$33,0)) -> 5296211.2 | O16: =+G16 -> 40000000 | P16: =75*10^6 -> 75000000 | Q16: =250*10^6 -> 250000000 | S16: =+IFERROR(O16*$O$8+P16*$P$8+Q16*$Q$8,"") -> 110000000 | T16: =IFERROR(+(S16/G16)*M16,"") -> 14564581 | U16: =IFERROR(T16/M16,"") -> 2.75
B17: Hireguide | C17: =INDEX('Investment Characteristics'!$X$4:$X$31,MATCH('Exit Forecast'!$B17,'Investment Characteristics'!$K$4:$K$31,0)) -> RP | D17: =INDEX('Investment Characteristics'!$L$4:$L$31,MATCH('Exit Forecast'!$B17,'Investment Characteristics'!$K$4:$K$31,0)) -> Seed | E17: =INDEX('Investment Characteristics'!$M$4:$M$31,MATCH('Exit Forecast'!$B17,'Investment Characteristics'!$K$4:$K$31,0)) -> 0.09375 | F17: =INDEX('Investment Characteristics'!$Q$4:$Q$31,MATCH('Exit Forecast'!$B17,'Investment Characteristics'!$K$4:$K$31,0)) -> 32000000 | G17: =INDEX('Investment Characteristics'!$R$4:$R$31,MATCH('Exit Forecast'!$B17,'Investment Characteristics'!$K$4:$K$31,0)) -> 32000000 | L17: =INDEX('Investment Characteristics'!$S$4:$S$33,MATCH('Exit Forecast'!$B17,'Investment Characteristics'!$B$4:$B$33,0)) -> 3000000 | M17: =INDEX('Investment Characteristics'!$U$4:$U$33,MATCH('Exit Forecast'!$B17,'Investment Characteristics'!$B$4:$B$33,0)) -> 500000 | O17: 0 | P17: =+G17 -> 32000000 | Q17: =100*10^6 -> 100000000 | S17: =+IFERROR(O17*$O$8+P17*$P$8+Q17*$Q$8,"") -> 41000000 | T17: =IFERROR(+(S17/G17)*M17,"") -> 640625 | U17: =IFERROR(T17/M17,"") -> 1.28125
B18: Take2 AI | C18: =INDEX('Investment Characteristics'!$X$4:$X$31,MATCH('Exit Forecast'!$B18,'Investment Characteristics'!$K$4:$K$31,0)) -> ABG | D18: =INDEX('Investment Characteristics'!$L$4:$L$31,MATCH('Exit Forecast'!$B18,'Investment Characteristics'!$K$4:$K$31,0)) -> Seed | E18: =INDEX('Investment Characteristics'!$M$4:$M$31,MATCH('Exit Forecast'!$B18,'Investment Characteristics'!$K$4:$K$31,0)) -> 0.07 | F18: =INDEX('Investment Characteristics'!$Q$4:$Q$31,MATCH('Exit Forecast'!$B18,'Investment Characteristics'!$K$4:$K$31,0)) -> 10000000 | G18: =INDEX('Investment Characteristics'!$R$4:$R$31,MATCH('Exit Forecast'!$B18,'Investment Characteristics'!$K$4:$K$31,0)) -> 10000000 | L18: =INDEX('Investment Characteristics'!$S$4:$S$33,MATCH('Exit Forecast'!$B18,'Investment Characteristics'!$B$4:$B$33,0)) -> 700000 | M18: =INDEX('Investment Characteristics'!$U$4:$U$33,MATCH('Exit Forecast'!$B18,'Investment Characteristics'!$B$4:$B$33,0)) -> 700000 | O18: 0 | P18: =+G18 -> 10000000 | Q18: =65*10^6 -> 65000000 | S18: =+IFERROR(O18*$O$8+P18*$P$8+Q18*$Q$8,"") -> 21250000 | T18: =IFERROR(+(S18/G18)*M18,"") -> 1487500 | U18: =IFERROR(T18/M18,"") -> 2.125
B19: Techwolf | C19: =INDEX('Investment Characteristics'!$X$4:$X$31,MATCH('Exit Forecast'!$B19,'Investment Characteristics'!$K$4:$K$31,0)) -> ABG | D19: =INDEX('Investment Characteristics'!$L$4:$L$31,MATCH('Exit Forecast'!$B19,'Investment Characteristics'!$K$4:$K$31,0)) -> B | E19: =INDEX('Investment Characteristics'!$M$4:$M$31,MATCH('Exit Forecast'!$B19,'Investment Characteristics'!$K$4:$K$31,0)) -> 0.035210817 | F19: =INDEX('Investment Characteristics'!$Q$4:$Q$31,MATCH('Exit Forecast'!$B19,'Investment Characteristics'!$K$4:$K$31,0)) -> 141000000 | G19: =INDEX('Investment Characteristics'!$R$4:$R$31,MATCH('Exit Forecast'!$B19,'Investment Characteristics'!$K$4:$K$31,0)) -> 141000000 | L19: =INDEX('Investment Characteristics'!$S$4:$S$33,MATCH('Exit Forecast'!$B19,'Investment Characteristics'!$B$4:$B$33,0)) -> 5037377 | M19: =INDEX('Investment Characteristics'!$U$4:$U$33,MATCH('Exit Forecast'!$B19,'Investment Characteristics'!$B$4:$B$33,0)) -> 5037377 | O19: =+G19 -> 141000000 | P19: =500*10^6 -> 500000000 | Q19: =750*10^6 -> 750000000 | S19: =+IFERROR(O19*$O$8+P19*$P$8+Q19*$Q$8,"") -> 472750000 | T19: =IFERROR(+(S19/G19)*M19,"") -> 16889503 | U19: =IFERROR(T19/M19,"") -> 3.3528369
B20: Thatch | C20: =INDEX('Investment Characteristics'!$X$4:$X$31,MATCH('Exit Forecast'!$B20,'Investment Characteristics'!$K$4:$K$31,0)) -> GG | D20: =INDEX('Investment Characteristics'!$L$4:$L$31,MATCH('Exit Forecast'!$B20,'Investment Characteristics'!$K$4:$K$31,0)) -> B | E20: =INDEX('Investment Characteristics'!$M$4:$M$31,MATCH('Exit Forecast'!$B20,'Investment Characteristics'!$K$4:$K$31,0)) -> 0.032141794 | F20: =INDEX('Investment Characteristics'!$Q$4:$Q$31,MATCH('Exit Forecast'!$B20,'Investment Characteristics'!$K$4:$K$31,0)) -> 450000000 | G20: =INDEX('Investment Characteristics'!$R$4:$R$31,MATCH('Exit Forecast'!$B20,'Investment Characteristics'!$K$4:$K$31,0)) -> 450000000 | L20: =INDEX('Investment Characteristics'!$S$4:$S$33,MATCH('Exit Forecast'!$B20,'Investment Characteristics'!$B$4:$B$33,0)) -> 4040625.2 | M20: =INDEX('Investment Characteristics'!$U$4:$U$33,MATCH('Exit Forecast'!$B20,'Investment Characteristics'!$B$4:$B$33,0)) -> 10304094 | O20: =+G20 -> 450000000 | P20: =500*10^6 -> 500000000 | Q20: =1500*10^6 -> 1500000000 | S20: =+IFERROR(O20*$O$8+P20*$P$8+Q20*$Q$8,"") -> 737500000 | T20: =IFERROR(+(S20/G20)*M20,"") -> 16887266 | U20: =IFERROR(T20/M20,"") -> 1.6388889
B21: Multimodal | C21: =INDEX('Investment Characteristics'!$X$4:$X$31,MATCH('Exit Forecast'!$B21,'Investment Characteristics'!$K$4:$K$31,0)) -> CH | D21: =INDEX('Investment Characteristics'!$L$4:$L$31,MATCH('Exit Forecast'!$B21,'Investment Characteristics'!$K$4:$K$31,0)) -> Seed | E21: =INDEX('Investment Characteristics'!$M$4:$M$31,MATCH('Exit Forecast'!$B21,'Investment Characteristics'!$K$4:$K$31,0)) -> 0.066666667 | F21: =INDEX('Investment Characteristics'!$Q$4:$Q$31,MATCH('Exit Forecast'!$B21,'Investment Characteristics'!$K$4:$K$31,0)) -> 30000000 | G21: =INDEX('Investment Characteristics'!$R$4:$R$31,MATCH('Exit Forecast'!$B21,'Investment Characteristics'!$K$4:$K$31,0)) -> 30000000 | L21: =INDEX('Investment Characteristics'!$S$4:$S$33,MATCH('Exit Forecast'!$B21,'Investment Characteristics'!$B$4:$B$33,0)) -> 2000000 | M21: =INDEX('Investment Characteristics'!$U$4:$U$33,MATCH('Exit Forecast'!$B21,'Investment Characteristics'!$B$4:$B$33,0)) -> 2000000 | O21: =+G21 -> 30000000 | P21: =100*10^6 -> 100000000 | Q21: =500*10^6 -> 500000000 | S21: =+IFERROR(O21*$O$8+P21*$P$8+Q21*$Q$8,"") -> 182500000 | T21: =IFERROR(+(S21/G21)*M21,"") -> 12166667 | U21: =IFERROR(T21/M21,"") -> 6.0833333 | W21: 45686
B22: OneImaging | C22: =INDEX('Investment Characteristics'!$X$4:$X$31,MATCH('Exit Forecast'!$B22,'Investment Characteristics'!$K$4:$K$31,0)) -> RP | D22: =INDEX('Investment Characteristics'!$L$4:$L$31,MATCH('Exit Forecast'!$B22,'Investment Characteristics'!$K$4:$K$31,0)) -> A | E22: =INDEX('Investment Characteristics'!$M$4:$M$31,MATCH('Exit Forecast'!$B22,'Investment Characteristics'!$K$4:$K$31,0)) -> 0.05994 | F22: =INDEX('Investment Characteristics'!$Q$4:$Q$31,MATCH('Exit Forecast'!$B22,'Investment Characteristics'!$K$4:$K$31,0)) -> 250000000 | G22: =INDEX('Investment Characteristics'!$R$4:$R$31,MATCH('Exit Forecast'!$B22,'Investment Characteristics'!$K$4:$K$31,0)) -> 250000000 | L22: =INDEX('Investment Characteristics'!$S$4:$S$33,MATCH('Exit Forecast'!$B22,'Investment Characteristics'!$B$4:$B$33,0)) -> 4000000 | M22: =INDEX('Investment Characteristics'!$U$4:$U$33,MATCH('Exit Forecast'!$B22,'Investment Characteristics'!$B$4:$B$33,0)) -> 14640928 | O22: 0 | P22: =50*10^6 -> 50000000 | Q22: =300*10^6 -> 300000000 | S22: =+IFERROR(O22*$O$8+P22*$P$8+Q22*$Q$8,"") -> 100000000 | T22: =IFERROR(+(S22/G22)*M22,"") -> 5856371.3 | U22: =IFERROR(T22/M22,"") -> 0.4
B23: ExceedsAI | C23: =INDEX('Investment Characteristics'!$X$4:$X$31,MATCH('Exit Forecast'!$B23,'Investment Characteristics'!$K$4:$K$31,0)) -> ABG | D23: Seed | E23: 0.066666667 | F23: =30*10^6 -> 30000000 | G23: =INDEX('Investment Characteristics'!$R$4:$R$31,MATCH('Exit Forecast'!$B23,'Investment Characteristics'!$K$4:$K$31,0)) -> 15000000 | L23: =INDEX('Investment Characteristics'!$S$4:$S$33,MATCH('Exit Forecast'!$B23,'Investment Characteristics'!$B$4:$B$33,0)) -> 1187499.8 | M23: =INDEX('Investment Characteristics'!$U$4:$U$33,MATCH('Exit Forecast'!$B23,'Investment Characteristics'!$B$4:$B$33,0)) -> 1187499.8 | O23: =+G23 -> 15000000 | P23: =75*10^6 -> 75000000 | Q23: =250*10^6 -> 250000000 | S23: =+IFERROR(O23*$O$8+P23*$P$8+Q23*$Q$8,"") -> 103750000 | T23: =IFERROR(+(S23/G23)*M23,"") -> 8213540.6 | U23: =IFERROR(T23/M23,"") -> 6.9166667
B24: Sully.AI | C24: =INDEX('Investment Characteristics'!$X$4:$X$31,MATCH('Exit Forecast'!$B24,'Investment Characteristics'!$K$4:$K$31,0)) -> ABG | D24: =INDEX('Investment Characteristics'!$L$4:$L$31,MATCH('Exit Forecast'!$B24,'Investment Characteristics'!$K$4:$K$31,0)) -> A | E24: =INDEX('Investment Characteristics'!$M$4:$M$31,MATCH('Exit Forecast'!$B24,'Investment Characteristics'!$K$4:$K$31,0)) -> 0.053333327 | F24: =INDEX('Investment Characteristics'!$Q$4:$Q$31,MATCH('Exit Forecast'!$B24,'Investment Characteristics'!$K$4:$K$31,0)) -> 75000000 | G24: =INDEX('Investment Characteristics'!$R$4:$R$31,MATCH('Exit Forecast'!$B24,'Investment Characteristics'!$K$4:$K$31,0)) -> 75000000 | L24: =INDEX('Investment Characteristics'!$S$4:$S$33,MATCH('Exit Forecast'!$B24,'Investment Characteristics'!$B$4:$B$33,0)) -> 3999999.5 | M24: =INDEX('Investment Characteristics'!$U$4:$U$33,MATCH('Exit Forecast'!$B24,'Investment Characteristics'!$B$4:$B$33,0)) -> 3999999.5 | O24: =+G24 -> 75000000 | P24: =500*10^6 -> 500000000 | Q24: =1000*10^6 -> 1000000000 | S24: =+IFERROR(O24*$O$8+P24*$P$8+Q24*$Q$8,"") -> 518750000 | T24: =IFERROR(+(S24/G24)*M24,"") -> 27666663 | U24: =IFERROR(T24/M24,"") -> 6.9166667
S25: =+IFERROR(O25*$O$8+P25*$P$8+Q25*$Q$8,"") -> 0 | T25: =IFERROR(+(S25/G25)*M25,"") | U25: =IFERROR(T25/M25,"")
S26: =+IFERROR(O26*$O$8+P26*$P$8+Q26*$Q$8,"") -> 0 | T26: =IFERROR(+(S26/G26)*M26,"") | U26: =IFERROR(T26/M26,"")
S27: =+IFERROR(O27*$O$8+P27*$P$8+Q27*$Q$8,"") -> 0 | T27: =IFERROR(+(S27/G27)*M27,"") | U27: =IFERROR(T27/M27,"")
S28: =+IFERROR(O28*$O$8+P28*$P$8+Q28*$Q$8,"") -> 0 | T28: =IFERROR(+(S28/G28)*M28,"") | U28: =IFERROR(T28/M28,"")
S29: =+IFERROR(O29*$O$8+P29*$P$8+Q29*$Q$8,"") -> 0 | T29: =IFERROR(+(S29/G29)*M29,"") | U29: =IFERROR(T29/M29,"")
S30: =+IFERROR(O30*$O$8+P30*$P$8+Q30*$Q$8,"") -> 0 | T30: =IFERROR(+(S30/G30)*M30,"") | U30: =IFERROR(T30/M30,"")
S31: =+IFERROR(O31*$O$8+P31*$P$8+Q31*$Q$8,"") -> 0 | T31: =IFERROR(+(S31/G31)*M31,"") | U31: =IFERROR(T31/M31,"")
S32: =+IFERROR(O32*$O$8+P32*$P$8+Q32*$Q$8,"") -> 0 | T32: =IFERROR(+(S32/G32)*M32,"") | U32: =IFERROR(T32/M32,"")
S33: =+IFERROR(O33*$O$8+P33*$P$8+Q33*$Q$8,"") -> 0 | T33: =IFERROR(+(S33/G33)*M33,"") | U33: =IFERROR(T33/M33,"")
B34: Total | L34: =SUM(L10:L33) -> 52173809 | M34: =SUM(M10:M33) -> 73949734 | T34: =SUM(T10:T33) -> 2.3792672e+08 | U34: =+T34/L34 -> 4.5602712

Sheet Fund Model
B2: Summary Fund Model
C3: Fund III
B4: Fund Size | C4: =142*10^6 -> 142000000
B5: # of Deals | C5: 30
A6: 0.2 | B6: Deals that Matter | C6: 6 | D6: 20% of deals
B7: Avg. Inv. Size | C7: =+C4/C5 -> 4733333.3
B8: Avg. Valuation. | C8: =65*10^6 -> 65000000 | D8: Includes follow-ons
B9: Avg. Ownership | C9: =+C7/C8 -> 0.072820513
B10: Avg. Exit Needed | C10: 1500000000
B11: Avg. Multiple | C11: =+(C10*C9)/C7 -> 23.076923
B12: Total Returns | C12: =+(C11*C7*C6)/(0.8) -> 8.1923077e+08
B13: DPI (Net carry) | C13: =+(C12-(C12-C4)*0.2)/C4 -> 4.8153846
B16: Fund Allocation
B17: Fund Assumptions
B18: Fund Size | C18: =142*10^6 -> 142000000
B19: Fee Pool | C19: =C18*0.02*7 -> 19880000 | D19: 7 years of fees | E19: =C19/C18 -> 0.14
B20: Investable Capital | C20: =C18-C19 -> 122120000
B22: Fund III SVA Assumptions | H22: Fund III SVA Partner Allocation (RP+ABG+GG) | K22: Fund III SVA Partner Allocation (CH)
B23: Companies | C23: 12 | D23: 3 Cohorts, 4 companies | H23: Companies | I23: =ROUNDDOWN(C23/3.5,0) -> 3 | K23: Companies | L23: =ROUNDDOWN(C23/3.5*0.5,0) -> 1
B24: Initial Investment | C24: 250000 | H24: Initial Investment | I24: 250000 | K24: Initial Investment | L24: 250000
B25: Total Initial SVA | C25: =(C23-4)*C24+(550000) -> 2550000 | H25: Total Initial SVA | I25: =I23*I24 -> 750000 | K25: Total Initial SVA | L25: =L23*L24 -> 250000
B27: % Graduate to Core | C27: 0.25 | D27: ~4 per cohort | H27: % Graduate to Core | I27: 0.25 | K27: % Graduate to Core | L27: 0.25
B28: SVA -> Core Companies | C28: =ROUNDUP(C23*C27,0) -> 3 | H28: SVA -> Core Companies | I28: =ROUNDUP(I23*I27,0) -> 1 | K28: SVA -> Core Companies | L28: =ROUNDUP(L23*L27,0) -> 1
B29: Core Inital Check | C29: =2*10^6 -> 2000000 | D29: Target ~7% ownership, avg valuation $30M | H29: Core Inital Check | I29: =+C29 -> 2000000 | K29: Core Inital Check | L29: =+C29 -> 2000000
B30: Total SVA -> Core Checks | C30: =C29*C28 -> 6000000 | H30: Total SVA -> Core Checks | I30: =I29*I28 -> 2000000 | K30: Total SVA -> Core Checks | L30: =L29*L28 -> 2000000
B31: Follow-On Reserves | C31: =C30*0.4 -> 2400000 | D31: 40% Reserve Target | H31: Follow-On Reserves | I31: =I30*0.4 -> 800000 | K31: Follow-On Reserves | L31: =L30*0.4 -> 800000
B33: Total SVA Pool | C33: =C31+C30+C25 -> 10950000 | D33: Initial SVA check, Core check, and reserves | H33: Total SVA Pool | I33: =I31+I30+I25 -> 3550000 | K33: Total SVA Pool | L33: =L31+L30+L25 -> 3050000
B35: Fund III Core Investment | H35: Fund III Core Partner Allocation (RP+ABG+GG) | K35: Fund III Core Partner Allocation (CH)
B36: Investable Capital | C36: =C20 -> 122120000 | H36: Investable Capital | I36: =C36/3.5 -> 34891429 | K36: Investable Capital | L36: =C36/3.5*0.5 -> 17445714
B37: Total SVA Pool | C37: =C33 -> 10950000 | H37: Total SVA Pool | I37: =C37/3.5 -> 3128571.4 | K37: Total SVA Pool | L37: =C37/3.5*0.5 -> 1564285.7
B38: Fund III Investable Capital | C38: =C36-C37 -> 111170000 | H38: Fund III Investable Capital | I38: =I36-I37 -> 31762857 | K38: Fund III Investable Capital | L38: =L36-L37 -> 15881429
A40: 0.6 | B40: Initial Investment | C40: =C38*A40 -> 66702000 | D40: 60% of capital | H40: Initial Investment | I40: =I38*A40 -> 19057714 | K40: Initial Investment | L40: =L38*A40 -> 9528857.1
A41: 0.4 | B41: Follow-On / Reserves | C41: =C38*A41 -> 44468000 | D41: 40% of capital | H41: Follow-On / Reserves | I41: =I38*A41 -> 12705143 | K41: Follow-On / Reserves | L41: =L38*A41 -> 6352571.4
B43: Target Core Companies | C43: 25 | H43: Target Core Companies | I43: =C43/3.5 -> 7.1428571 | K43: Target Core Companies | L43: =C43/3.5*0.5 -> 3.5714286
B44: SVA -> Core Companies | C44: =C28 -> 3 | H44: SVA -> Core Companies | I44: =C44/3.5 -> 0.85714286 | K44: SVA -> Core Companies | L44: =C44/3.5*0.5 -> 0.42857143
B45: Total Portfolio | C45: =SUM(C43:C44) -> 28 | H45: Total Portfolio | I45: =I43+I44 -> 8 | K45: Total Portfolio | L45: =L43+L44 -> 4
B47: Avg. Initial Check | C47: =C40/C43 -> 2668080 | H47: Avg. Initial Check | I47: =I40/I43 -> 2668080 | K47: Avg. Initial Check | L47: =L40/L43 -> 2668080

Sheet Forecast Exits
AC1: Dilution
B2: Power Law KPI | C2: Target | D2: Actual
B3: Average Valuation | C3: =+'Fund Model'!C8 -> 65000000 | D3: =AVERAGE(O64:O86) -> 60936364
B4: Power Law Companies | C4: =+'Fund Model'!C6 -> 6 | D4: =COUNTIF(AB64:AB86,"Y") -> 2
B5: Power Law Hit Rate | C5: =+'Fund Model'!A6 -> 0.2 | D5: =D4/COUNTA(B64:B86) -> 0.090909091
B6: Avg. PL Ownership | C6: =+'Fund Model'!C9 -> 0.072820513 | D6: =AVERAGEIF(AB64:AB86,"Y",E64:E86) -> 0.042473631
B7: Avg. PL Exit | C7: =+'Fund Model'!C10 -> 1500000000 | D7: =AVERAGEIF(AB64:AB86,"Y",V64:V86) -> 1071150000
B8: Avg. PL Proceeds | C8: =+C7*C6 -> 1.0923077e+08 | D8: =AVERAGEIF(AB64:AB86,"Y",X64:X86) -> 43095451
B9: What's Needed
B10: Remaining PL Companes | D10: =C4-D4 -> 4
B11: Ownership of new PL Companies at $1.5bn | D11: =D12/C7 -> 0.094865619
B12: Avg. PL Proceeds Needed | C12: - | D12: =((C4*C8)-SUMIF(AB64:AB86,"Y",X64:X86))/(C4-D4) -> 1.4229843e+08
B14: Full Fund | C14: Full Fund | D14: Inv. Capital | AC14: Seed | AD14: 0.8
B15: Amount | C15: =142*10^6 -> 142000000 | D15: =+F87 -> 76264804 | AC15: A | AD15: 0.85
A16: 6 | B16: 6x Gross Target | C16: =+C15*A16 -> 852000000 | D16: =+D15*A16 -> 4.5758882e+08 | AC16: B | AD16: 0.9
B17: Current Proj. | C17: =X87 -> 3.6283246e+08 | D17: =+X87 -> 3.6283246e+08 | AC17: C | AD17: 0.9
B18: Surplus/(Shortfall) | C18: =+C17-C16 -> -4.8916754e+08 | D18: =+D17-D16 -> -94756364
B19: What's Needed
B20: Current Mult on Inv. Capital | D20: =D17/D15 -> 4.7575348
B21: Mult on New Capital Inv. (incl. follow-on) | D21: =-C18/(C15-D15) -> 7.441486
B23: Partner Allocation:
B24: GG | C24: Full Amount | D24: Inv. Capital
B25: Amount | C25: =+'Allocation Tracking'!C53 -> 31762857 | D25: =+SUMIF($C$64:$C$86,B24,$F$64:$F$86) -> 28592822
A26: =+$A$16 -> 6 | B26: =+B16 -> 6x Gross Target | C26: =+C25*A26 -> 1.9057714e+08 | D26: =+D25*A26 -> 1.7155693e+08
B27: Current Proj. | C27: =+SUMIF($C$64:$C$86,B24,$X$64:$X$86) -> 1.0958591e+08 | D27: =+SUMIF($C$64:$C$86,B24,$X$64:$X$86) -> 1.0958591e+08
B28: Surplus/(Shortfall) | C28: =+C27-C26 -> -80991232 | D28: =+D27-D26 -> -61971019
B29: What's Needed
B30: Current Mult on Inv. Capital | D30: =D27/D25 -> 3.8326372
B31: Mult on New Capital Inv. (incl. follow-on) | D31: =-C28/(C25-D25) -> 25.548998
B33: ABG | C33: Full Amount | D33: Inv. Capital
B34: Amount | C34: =+'Allocation Tracking'!C27 -> 31762857 | D34: =+SUMIF($C$64:$C$86,B33,$F$64:$F$86) -> 21442907
A35: =+$A$16 -> 6 | B35: =+B16 -> 6x Gross Target | C35: =+C34*A35 -> 1.9057714e+08 | D35: =+D34*A35 -> 1.2865744e+08
B36: Current Proj. | C36: =+SUMIF($C$64:$C$86,B33,$X$64:$X$86) -> 1.2609801e+08 | D36: =+SUMIF($C$64:$C$86,B33,$X$64:$X$86) -> 1.2609801e+08
B37: Surplus/(Shortfall) | C37: =+C36-C35 -> -64479130 | D37: =+D36-D35 -> -2559427.9
B38: What's Needed
B39: Current Mult on Inv. Capital | D39: =D36/D34 -> 5.8806399
B40: Mult on New Capital Inv. (incl. follow-on) | D40: =-C37/(C34-D34) -> 6.2480078
B42: RP | C42: Full Amount | D42: Inv. Capital
B43: Amount | C43: =++'Allocation Tracking'!C40 -> 31762857 | D43: =+SUMIF($C$64:$C$86,B42,$F$64:$F$86) -> 15928080
A44: =+$A$16 -> 6 | B44: =+B16 -> 6x Gross Target | C44: =+C43*A44 -> 1.9057714e+08 | D44: =+D43*A44 -> 95568478
B45: Current Proj. | C45: =+SUMIF($C$64:$C$86,B42,$X$64:$X$86) -> 77679417 | D45: =+SUMIF($C$64:$C$86,B42,$X$64:$X$86) -> 77679417
B46: Surplus/(Shortfall) | C46: =+C45-C44 -> -1.1289773e+08 | D46: =+D45-D44 -> -17889061
B47: What's Needed
B48: Current Mult on Inv. Capital | D48: =D45/D43 -> 4.8768853
B49: Mult on New Capital Inv. (incl. follow-on) | D49: =-C46/(C43-D43) -> 7.1297324
B51: CH | C51: Full Amount | D51: Inv. Capital
B52: Amount | C52: =+'Allocation Tracking'!C66 -> 15881429 | D52: =+SUMIF($C$64:$C$86,B51,$F$64:$F$86) -> 8999995.9
A53: =+$A$16 -> 6 | B53: 6x Gross Target | C53: =+C52*A53 -> 95288571 | D53: =+D52*A53 -> 53999975
B54: Current Proj. | C54: =+SUMIF($C$64:$C$86,B51,$X$64:$X$86) -> 49469116 | D54: =+SUMIF($C$64:$C$86,B51,$X$64:$X$86) -> 49469116
B55: Surplus/(Shortfall) | C55: =+C54-C53 -> -45819455 | D55: =+D54-D53 -> -4530859.2
B56: What's Needed
B57: Current Mult on Inv. Capital | D57: =D54/D52 -> 5.496571
B58: Mult on New Capital Inv. (incl. follow-on) | D58: =-C55/(C52-D52) -> 6.658418
B61: Exit Forecast
I62: Revenue | R62: 0.25 | S62: 0.5 | T62: 0.25 | AB62: Power
B63: Company | C63: Owner | D63: Current Stage | E63: Ownership | F63: Total Inv. | G63: Mkt. Value | I63: 2023A | J63: 2024A | K63: 2025E | L63: ARR as of Q2 25 | M63: Y/Y | O63: Avg, Cost | P63: Holding Value | R63: Bear | S63: Base | T63: Bull | V63: Weighted Exit | W63: Exit Ownership | X63: Exit Proceeds | Y63: Exit MOIC | AB63: Law | AC63: Last Updated | AE63: Business Model | AF63: ICP | AG63: Current ACV | AH63: Current Customers | AI63: 2025E Revenue | AJ63: Est Future ACV | AK63: Rev Mult | AL63: Cust to Current Exit | AM63: Current Exit Outcome | AO63: GM% | AP63: CAC | AR63: Suggested Cust Count | AS63: Suggested Exit Outcome | AT63: Commentary
B64: Stepful | C64: =INDEX('Investment Characteristics'!$X$4:$X$31,MATCH(B64,'Investment Characteristics'!$K$4:$K$31,0)) -> ABG | D64: =INDEX('Investment Characteristics'!$L$4:$L$31,MATCH(B64,'Investment Characteristics'!$K$4:$K$31,0)) -> B | E64: =INDEX('Investment Characteristics'!$M$4:$M$31,MATCH(B64,'Investment Characteristics'!$K$4:$K$31,0)) -> 0.052805468 | F64: =INDEX('Investment Characteristics'!$S$4:$S$33,MATCH(B64,'Investment Characteristics'!$B$4:$B$33,0)) -> 7878030.5 | G64: =INDEX('Investment Characteristics'!$U$4:$U$33,MATCH($B64,'Investment Characteristics'!$B$4:$B$33,0)) -> 13609280 | I64: 4362785.5 | J64: 19914254 | K64: 71762828 | L64: 55600000 | M64: =IFERROR(K64/J64-1,"") -> 2.603591 | O64: =INDEX('Investment Characteristics'!$P$4:$P$33,MATCH(B64,'Investment Characteristics'!$B$4:$B$33,0)) -> 149200000 | P64: =INDEX('Investment Characteristics'!$R$4:$R$33,MATCH($B64,'Investment Characteristics'!$B$4:$B$33,0)) -> 261500000 | R64: =+P64*0.8 -> 209200000 | S64: =1*10^9 -> 1000000000 | T64: 3000000000 | V64: =+IFERROR(SUMPRODUCT($R$62:$T$62,R64:T64),"") -> 1302300000 | W64: =+IF(D64="Seed",(E64*$AD$14),IF(D64="A",(E64*$AD$15),IF(D64="B",(E64*$AD$16),(E64*$AD$17)))) -> 0.047524921 | X64: =+V64*W64 -> 61891705 | Y64: =+X64/F64 -> 7.8562409 | AB64: Y | AC64: 45838 | AE64: Fee for Service | AF64: Consumer | AG64: 2000 | AH64: =AI64/AG64 -> 26400 | AI64: =_xlfn.XLOOKUP(B64,'Q2 2025 Financials'!$B$5:$B$47,'Q2 2025 Financials'!$L$5:$L$47, "Not Provided") -> 52800000 | AJ64: 5000 | AK64: =_xlfn.XLOOKUP(B64,'Fund III Multiples'!$B$5:$B$48,'Fund III Multiples'!$P$5:$P$48, "Not Provided") -> 4.6604829 | AL64: =AM64/(AJ64*AK64) -> 55886.913 | AM64: =+V64 -> 1302300000 | AO64: 0.81 | AP64: 428 | AR64: 70000 | AS64: =AR64*AK64*AJ64 -> 1.631169e+09 | AT64: Current courses cost around $2k (re-enrollment lower but also initiation fee); predict could reach up to $15k per course over time
B65: Techwolf | C65: =INDEX('Investment Characteristics'!$X$4:$X$31,MATCH(B65,'Investment Characteristics'!$K$4:$K$31,0)) -> ABG | D65: =INDEX('Investment Characteristics'!$L$4:$L$31,MATCH(B65,'Investment Characteristics'!$K$4:$K$31,0)) -> B | E65: =INDEX('Investment Characteristics'!$M$4:$M$31,MATCH(B65,'Investment Characteristics'!$K$4:$K$31,0)) -> 0.035210817 | F65: =INDEX('Investment Characteristics'!$S$4:$S$33,MATCH(B65,'Investment Characteristics'!$B$4:$B$33,0)) -> 5037377 | G65: =INDEX('Investment Characteristics'!$U$4:$U$33,MATCH(B65,'Investment Characteristics'!$B$4:$B$33,0)) -> 5037377 | I65: 3766390.7 | J65: 6597644 | K65: 8702864 | L65: 7958307 | M65: =IFERROR(K65/J65-1,"") -> 0.31908663 | O65: =INDEX('Investment Characteristics'!$P$4:$P$33,MATCH(B65,'Investment Characteristics'!$B$4:$B$33,0)) -> 143100000 | P65: =INDEX('Investment Characteristics'!$R$4:$R$33,MATCH($B65,'Investment Characteristics'!$B$4:$B$33,0)) -> 141000000 | R65: =70*10^6 -> 70000000 | S65: =+P65 -> 141000000 | T65: 500000000 | V65: =+IFERROR(SUMPRODUCT($R$62:$T$62,R65:T65),"") -> 213000000 | W65: =+IF(D65="Seed",(E65*$AD$14),IF(D65="A",(E65*$AD$15),IF(D65="B",(E65*$AD$16),(E65*$AD$17)))) -> 0.031689735 | X65: =+V65*W65 -> 6749913.6 | Y65: =+X65/F65 -> 1.3399659 | AC65: 45838 | AE65: SaaS | AF65: Enterprise | AG65: 175000 | AH65: =AI65/AG65 -> 42.693097 | AI65: =_xlfn.XLOOKUP(B65,'Q2 2025 Financials'!$B$5:$B$47,'Q2 2025 Financials'!$L$5:$L$47, "Not Provided") -> 7471292 | AJ65: 350000 | AK65: =_xlfn.XLOOKUP(B65,'Fund III Multiples'!$B$5:$B$48,'Fund III Multiples'!$P$5:$P$48, "Not Provided") -> 4.6604829 | AL65: =AM65/(AJ65*AK65) -> 130.5812 | AM65: =+V65 -> 213000000 | AO65: 0.87 | AP65: 170000 | AR65: 250 | AS65: =AR65*AK65*AJ65 -> 4.0779225e+08 | AT65: Starting to sign larger multi-year contracts in the millions
B66: Sully.AI | C66: =INDEX('Investment Characteristics'!$X$4:$X$31,MATCH(B66,'Investment Characteristics'!$K$4:$K$31,0)) -> ABG | D66: =INDEX('Investment Characteristics'!$L$4:$L$31,MATCH(B66,'Investment Characteristics'!$K$4:$K$31,0)) -> A | E66: =INDEX('Investment Characteristics'!$M$4:$M$31,MATCH(B66,'Investment Characteristics'!$K$4:$K$31,0)) -> 0.053333327 | F66: =INDEX('Investment Characteristics'!$S$4:$S$33,MATCH(B66,'Investment Characteristics'!$B$4:$B$33,0)) -> 3999999.5 | G66: =INDEX('Investment Characteristics'!$U$4:$U$33,MATCH(B66,'Investment Characteristics'!$B$4:$B$33,0)) -> 3999999.5 | I66: 0 | J66: 0 | K66: 0 | L66: 1579000 | M66: =IFERROR(K66/J66-1,"") | O66: =INDEX('Investment Characteristics'!$P$4:$P$33,MATCH(B66,'Investment Characteristics'!$B$4:$B$33,0)) -> 75000000 | P66: =INDEX('Investment Characteristics'!$R$4:$R$33,MATCH($B66,'Investment Characteristics'!$B$4:$B$33,0)) -> 75000000 | R66: 75000000 | S66: 500000000 | T66: 1000000000 | V66: =+IFERROR(SUMPRODUCT($R$62:$T$62,R66:T66),"") -> 518750000 | W66: =+IF(D66="Seed",(E66*$AD$14),IF(D66="A",(E66*$AD$15),IF(D66="B",(E66*$AD$16),(E66*$AD$17)))) -> 0.045333328 | X66: =+V66*W66 -> 23516664 | Y66: =+X66/F66 -> 5.8791667 | AC66: 45838 | AE66: Subscription (Per Seat) | AF66: Providers | AG66: 1000 | AH66: =AI66/AG66 -> 2882 | AI66: =_xlfn.XLOOKUP(B66,'Q2 2025 Financials'!$B$5:$B$47,'Q2 2025 Financials'!$L$5:$L$47, "Not Provided") -> 2882000 | AJ66: 2000 | AK66: =_xlfn.XLOOKUP(B66,'Fund III Multiples'!$B$5:$B$48,'Fund III Multiples'!$P$5:$P$48, "Not Provided") -> 8.9817031 | AL66: =AM66/(AJ66*AK66) -> 28878.154 | AM66: =+V66 -> 518750000 | AO66: 0.51 | AP66: 6000 | AR66: =AL66 -> 28878.154 | AS66: =AR66*AK66*AJ66 -> 5.1875e+08 | AT66: Currently charge $99/doctor/month; will upsell as feature rollout continues. Considering cost of medical professionals, could reasonably at least double.
B67: ExceedsAI | C67: =INDEX('Investment Characteristics'!$X$4:$X$31,MATCH(B67,'Investment Characteristics'!$K$4:$K$31,0)) -> ABG | D67: =INDEX('Investment Characteristics'!$L$4:$L$31,MATCH(B67,'Investment Characteristics'!$K$4:$K$31,0)) -> Seed | E67: =INDEX('Investment Characteristics'!$M$4:$M$31,MATCH(B67,'Investment Characteristics'!$K$4:$K$31,0)) -> 0.079166656 | F67: =INDEX('Investment Characteristics'!$S$4:$S$33,MATCH(B67,'Investment Characteristics'!$B$4:$B$33,0)) -> 1187499.8 | G67: =INDEX('Investment Characteristics'!$U$4:$U$33,MATCH(B67,'Investment Characteristics'!$B$4:$B$33,0)) -> 1187499.8 | I67: 0 | J67: 20000 | K67: 237950 | L67: Pending | M67: =IFERROR(K67/J67-1,"") -> 10.8975 | O67: =INDEX('Investment Characteristics'!$P$4:$P$33,MATCH(B67,'Investment Characteristics'!$B$4:$B$33,0)) -> 15000000 | P67: =INDEX('Investment Characteristics'!$R$4:$R$33,MATCH($B67,'Investment Characteristics'!$B$4:$B$33,0)) -> 15000000 | R67: 15000000 | S67: 75000000 | T67: 250000000 | V67: =+IFERROR(SUMPRODUCT($R$62:$T$62,R67:T67),"") -> 103750000 | W67: =+IF(D67="Seed",(E67*$AD$14),IF(D67="A",(E67*$AD$15),IF(D67="B",(E67*$AD$16),(E67*$AD$17)))) -> 0.063333325 | X67: =+V67*W67 -> 6570832.4 | Y67: =+X67/F67 -> 5.5333333 | AC67: 45838 | AE67: Subscription (Per Seat) | AF67: Enterprise | AG67: 200 | AH67: =AI67/AG67 -> 450 | AI67: =_xlfn.XLOOKUP(B67,'Q2 2025 Financials'!$B$5:$B$47,'Q2 2025 Financials'!$L$5:$L$47, "Not Provided") -> 90000 | AJ67: 300 | AK67: =_xlfn.XLOOKUP(B67,'Fund III Multiples'!$B$5:$B$48,'Fund III Multiples'!$P$5:$P$48, "Not Provided") -> 4.6604829 | AL67: =AM67/(AJ67*AK67) -> 74205.472 | AM67: =+V67 -> 103750000 | AO67: 0.57 | AP67: 280 | AR67: 37000 | AS67: =AR67*AK67*AJ67 -> 51731360 | AT67: Intend to charge up to $300 per seat on their enterprise plan; assume current revenue is mix of seats and trial (per month)
B68: Take2 AI | C68: =INDEX('Investment Characteristics'!$X$4:$X$31,MATCH(B68,'Investment Characteristics'!$K$4:$K$31,0)) -> ABG | D68: =INDEX('Investment Characteristics'!$L$4:$L$31,MATCH(B68,'Investment Characteristics'!$K$4:$K$31,0)) -> Seed | E68: =INDEX('Investment Characteristics'!$M$4:$M$31,MATCH(B68,'Investment Characteristics'!$K$4:$K$31,0)) -> 0.07 | F68: =INDEX('Investment Characteristics'!$S$4:$S$33,MATCH(B68,'Investment Characteristics'!$B$4:$B$33,0)) -> 700000 | G68: =INDEX('Investment Characteristics'!$U$4:$U$33,MATCH(B68,'Investment Characteristics'!$B$4:$B$33,0)) -> 700000 | I68: 3000 | J68: 34090 | K68: 777240 | L68: 592000 | M68: =IFERROR(K68/J68-1,"") -> 21.799648 | O68: =INDEX('Investment Characteristics'!$P$4:$P$33,MATCH(B68,'Investment Characteristics'!$B$4:$B$33,0)) -> 10000000 | P68: =INDEX('Investment Characteristics'!$R$4:$R$33,MATCH($B68,'Investment Characteristics'!$B$4:$B$33,0)) -> 10000000 | R68: =+P68 -> 10000000 | S68: 50000000 | T68: 100000000 | V68: =+IFERROR(SUMPRODUCT($R$62:$T$62,R68:T68),"") -> 52500000 | W68: =+IF(D68="Seed",(E68*$AD$14),IF(D68="A",(E68*$AD$15),IF(D68="B",(E68*$AD$16),(E68*$AD$17)))) -> 0.056 | X68: =+V68*W68 -> 2940000 | Y68: =+X68/F68 -> 4.2 | AC68: 45838 | AE68: SaaS | AF68: Enterprise | AG68: 50000 | AH68: =AI68/AG68 -> 9.47032 | AI68: =_xlfn.XLOOKUP(B68,'Q2 2025 Financials'!$B$5:$B$47,'Q2 2025 Financials'!$L$5:$L$47, "Not Provided") -> 473516 | AJ68: 100000 | AK68: =_xlfn.XLOOKUP(B68,'Fund III Multiples'!$B$5:$B$48,'Fund III Multiples'!$P$5:$P$48, "Not Provided") -> 4.6604829 | AL68: =AM68/(AJ68*AK68) -> 112.64927 | AM68: =+V68 -> 52500000 | AO68: 0.45 | AP68: 7200 | AR68: 80 | AS68: =AR68*AK68*AJ68 -> 37283863 | AT68: Highest contract values up to $200k; in this conservative estimate of $150k ACV still think that we could probably assume a higher exit outcome based on # of customers
B69: Carefam | C69: =INDEX('Investment Characteristics'!$X$4:$X$31,MATCH(B69,'Investment Characteristics'!$K$4:$K$31,0)) -> ABG | D69: =INDEX('Investment Characteristics'!$L$4:$L$31,MATCH(B69,'Investment Characteristics'!$K$4:$K$31,0)) -> A | E69: =INDEX('Investment Characteristics'!$M$4:$M$31,MATCH(B69,'Investment Characteristics'!$K$4:$K$31,0)) -> 0.0702 | F69: =INDEX('Investment Characteristics'!$S$4:$S$33,MATCH(B69,'Investment Characteristics'!$B$4:$B$33,0)) -> 2640000 | G69: =INDEX('Investment Characteristics'!$U$4:$U$33,MATCH(B69,'Investment Characteristics'!$B$4:$B$33,0)) -> 2640000 | I69: 0 | J69: 20000 | K69: 237950 | L69: Pending | M69: =IFERROR(K69/J69-1,"") -> 10.8975 | O69: =INDEX('Investment Characteristics'!$P$4:$P$33,MATCH(B69,'Investment Characteristics'!$B$4:$B$33,0)) -> 37600000 | P69: =INDEX('Investment Characteristics'!$R$4:$R$33,MATCH($B69,'Investment Characteristics'!$B$4:$B$33,0)) -> 37600000 | R69: =+P69 -> 37600000 | S69: =300*10^6 -> 300000000 | T69: =1000*10^6 -> 1000000000 | V69: =+IFERROR(SUMPRODUCT($R$62:$T$62,R69:T69),"") -> 409400000 | W69: =+IF(D69="Seed",(E69*$AD$14),IF(D69="A",(E69*$AD$15),IF(D69="B",(E69*$AD$16),(E69*$AD$17)))) -> 0.05967 | X69: =+V69*W69 -> 24428898 | Y69: =+X69/F69 -> 9.2533705 | AC69: 45838 | AE69: SaaS (credit model) | AF69: Providers | AG69: 40000 | AH69: =AI69/AG69 -> 30.15935 | AI69: 1206374 | AJ69: 200000 | AK69: 9 | AL69: =AM69/(AJ69*AK69) -> 227.44444 | AM69: =+V69 -> 409400000 | AO69: 0.54 | AP69: 25 | AR69: =AL69 -> 227.44444 | AS69: =AR69*AK69*AJ69 -> 409400000 | AT69: Currently they are charging by $20-40k credits that are used towards placement fees; starting to shift to pre-paid credit model (aka SaaS).
B70: Salsa | C70: =INDEX('Investment Characteristics'!$X$4:$X$31,MATCH(B70,'Investment Characteristics'!$K$4:$K$31,0)) -> CH | D70: =INDEX('Investment Characteristics'!$L$4:$L$31,MATCH(B70,'Investment Characteristics'!$K$4:$K$31,0)) -> A | E70: =INDEX('Investment Characteristics'!$M$4:$M$31,MATCH(B70,'Investment Characteristics'!$K$4:$K$31,0)) -> 0.084687403 | F70: =INDEX('Investment Characteristics'!$S$4:$S$33,MATCH(B70,'Investment Characteristics'!$B$4:$B$33,0)) -> 5499997.9 | G70: =INDEX('Investment Characteristics'!$U$4:$U$33,MATCH(B70,'Investment Characteristics'!$B$4:$B$33,0)) -> 5912934 | I70: 0 | J70: 0 | K70: 0 | L70: Pending | M70: =IFERROR(K70/J70-1,"") | O70: =INDEX('Investment Characteristics'!$P$4:$P$33,MATCH(B70,'Investment Characteristics'!$B$4:$B$33,0)) -> 64900000 | P70: =INDEX('Investment Characteristics'!$R$4:$R$33,MATCH($B70,'Investment Characteristics'!$B$4:$B$33,0)) -> 70000000 | R70: =+P70*0.8 -> 56000000 | S70: 400000000 | T70: 800000000 | V70: =+IFERROR(SUMPRODUCT($R$62:$T$62,R70:T70),"") -> 414000000 | W70: =+IF(D70="Seed",(E70*$AD$14),IF(D70="A",(E70*$AD$15),IF(D70="B",(E70*$AD$16),(E70*$AD$17)))) -> 0.071984293 | X70: =+V70*W70 -> 29801497 | Y70: =+X70/F70 -> 5.4184562 | AC70: 45930 | AE70: Platform + PEPM | AF70: Enterprise | AG70: 162000 | AH70: =AI70/AG70 -> 0 | AI70: =_xlfn.XLOOKUP(B70,'Q2 2025 Financials'!$B$5:$B$47,'Q2 2025 Financials'!$L$5:$L$47, "Not Provided") -> 0 | AJ70: 250000 | AK70: =_xlfn.XLOOKUP(B70,'Fund III Multiples'!$B$5:$B$48,'Fund III Multiples'!$P$5:$P$48, "Not Provided") -> 6.1639354 | AL70: =AM70/(AJ70*AK70) -> 268.65953 | AM70: =+V70 -> 414000000 | AO70: 0.33 | AP70: 0 | AR70: =AL70 -> 268.65953 | AS70: =AJ70*AK70*AR70 -> 414000000 | AT70: Current is modeled off an example of platform + PEPM for small employer (could be much higher for mid or large), done as customer count not employee
B71: Multimodal | C71: =INDEX('Investment Characteristics'!$X$4:$X$31,MATCH(B71,'Investment Characteristics'!$K$4:$K$31,0)) -> CH | D71: =INDEX('Investment Characteristics'!$L$4:$L$31,MATCH(B71,'Investment Characteristics'!$K$4:$K$31,0)) -> Seed | E71: =INDEX('Investment Characteristics'!$M$4:$M$31,MATCH(B71,'Investment Characteristics'!$K$4:$K$31,0)) -> 0.066666667 | F71: =INDEX('Investment Characteristics'!$S$4:$S$33,MATCH(B71,'Investment Characteristics'!$B$4:$B$33,0)) -> 2000000 | G71: =INDEX('Investment Characteristics'!$U$4:$U$33,MATCH(B71,'Investment Characteristics'!$B$4:$B$33,0)) -> 2000000 | I71: 0 | J71: 1060690 | K71: 3067000 | L71: 500000 | M71: =IFERROR(K71/J71-1,"") -> 1.891514 | O71: =INDEX('Investment Characteristics'!$P$4:$P$33,MATCH(B71,'Investment Characteristics'!$B$4:$B$33,0)) -> 30000000 | P71: =INDEX('Investment Characteristics'!$R$4:$R$33,MATCH($B71,'Investment Characteristics'!$B$4:$B$33,0)) -> 30000000 | R71: =+P71*0.8 -> 24000000 | S71: 50000000 | T71: 500000000 | V71: =+IFERROR(SUMPRODUCT($R$62:$T$62,R71:T71),"") -> 156000000 | W71: =+IF(D71="Seed",(E71*$AD$14),IF(D71="A",(E71*$AD$15),IF(D71="B",(E71*$AD$16),(E71*$AD$17)))) -> 0.053333333 | X71: =+V71*W71 -> 8320000 | Y71: =+X71/F71 -> 4.16 | AC71: 45930 | AE71: SaaS | AF71: Enterprise | AG71: 60000 | AH71: =AI71/AG71 -> 15.916667 | AI71: =_xlfn.XLOOKUP(B71,'Q2 2025 Financials'!$B$5:$B$47,'Q2 2025 Financials'!$L$5:$L$47, "Not Provided") -> 955000 | AJ71: 100000 | AK71: =_xlfn.XLOOKUP(B71,'Fund III Multiples'!$B$5:$B$48,'Fund III Multiples'!$P$5:$P$48, "Not Provided") -> 38.945493 | AL71: =AM71/(AJ71*AK71) -> 40.055983 | AM71: =+V71 -> 156000000 | AO71: 0.85 | AP71: 1500 | AR71: =AL71 -> 40.055983 | AS71: =AJ71*AK71*AR71 -> 156000000 | AT71: Will depend how high they can get enterprise contract values, had some in pipeline up to $1M
B72: Wagmo | C72: =INDEX('Investment Characteristics'!$X$4:$X$31,MATCH(B72,'Investment Characteristics'!$K$4:$K$31,0)) -> CH | D72: =INDEX('Investment Characteristics'!$L$4:$L$31,MATCH(B72,'Investment Characteristics'!$K$4:$K$31,0)) -> A | E72: =INDEX('Investment Characteristics'!$M$4:$M$31,MATCH(B72,'Investment Characteristics'!$K$4:$K$31,0)) -> 0.029870094 | F72: =INDEX('Investment Characteristics'!$S$4:$S$33,MATCH(B72,'Investment Characteristics'!$B$4:$B$33,0)) -> 1499998 | G72: =INDEX('Investment Characteristics'!$U$4:$U$33,MATCH(B72,'Investment Characteristics'!$B$4:$B$33,0)) -> 1499998 | I72: 6046586 | J72: 8661787 | K72: 13728715 | L72: 19,746,623 | M72: =IFERROR(K72/J72-1,"") -> 0.5849749 | O72: =INDEX('Investment Characteristics'!$P$4:$P$33,MATCH(B72,'Investment Characteristics'!$B$4:$B$33,0)) -> 50200000 | P72: =INDEX('Investment Characteristics'!$R$4:$R$33,MATCH($B72,'Investment Characteristics'!$B$4:$B$33,0)) -> 47200000 | R72: =+P72*0.8 -> 37760000 | S72: =500*10^6 -> 500000000 | T72: =750*10^6 -> 750000000 | V72: =+IFERROR(SUMPRODUCT($R$62:$T$62,R72:T72),"") -> 446940000 | W72: =+IF(D72="Seed",(E72*$AD$14),IF(D72="A",(E72*$AD$15),IF(D72="B",(E72*$AD$16),(E72*$AD$17)))) -> 0.02538958 | X72: =+V72*W72 -> 11347619 | Y72: =+X72/F72 -> 7.5650891 | AC72: 45930 | AE72: PEPM | AF72: Enterprise | AG72: 480 | AH72: =AI72/AG72 -> 30457.36 | AI72: =_xlfn.XLOOKUP(B72,'Q2 2025 Financials'!$B$5:$B$47,'Q2 2025 Financials'!$L$5:$L$47, "Not Provided") -> 14619533 | AJ72: 580 | AK72: =_xlfn.XLOOKUP(B72,'Fund III Multiples'!$B$5:$B$48,'Fund III Multiples'!$P$5:$P$48, "Not Provided") -> 7.3362939 | AL72: =AM72/(AJ72*AK72) -> 105037.53 | AM72: =+V72 -> 446940000 | AO72: 0.4 | AP72: 49 | AR72: =AL72 -> 105037.53 | AS72: =AJ72*AK72*AR72 -> 446940000 | AT72: Need to accelerate access to employees (i.e. only 400 plans sold via Sequoia One); including wellness and upsell opportunities, can reach $500+ annually per plan sold; Robby confirmed strong performance recently
