Workbook
Name SummaryCapTableFullyDilutedShares: 'Investment Characteristics'!$D$31

Sheet Fund Dashboard
B2: SemperVirens Fund II Summary
C3: ="As of "&TEXT('Statement of Investments'!$C$1,"mm/dd/yyyy") -> As of 12/31/2025 | F3: ="As of "&TEXT('Statement of Investments'!$C$1,"mm/dd/yyyy") -> As of 12/31/2025
B5: Fund Capital: | E5: Quarterly Invested Capital:
B6: Committed Capital | C6: 20730000 | E6: New Investments | F6: =SUMIF('Investment Rollover'!$C$4:$C$31,"=0",'Investment Rollover'!$D$4:$D$31) -> 0
B7: Capital Called | C7: =-SUM(#REF!) -> #REF! | E7: Follow-Ons | F7: =SUMIF('Investment Rollover'!$C$4:$C$31,">0",'Investment Rollover'!$D$4:$D$31) -> 163902.45
B8: Percent Called | C8: =C7/C6 -> #REF! | E8: Total New Investments | F8: =SUM(F6:F7) -> 163902.45
B10: Investment Summary: | E10: Pro-Forma Net Peformance:
B11: Invested Capital | C11: ='Investment Performance Summary'!E45 -> 67089185 | E11: Contributions | F11: =-#REF! -> #REF!
B12: Total Value | C12: ='Investment Performance Summary'!H45 -> 1.4466024e+08 | E12: Distributions | F12: =#REF! -> #REF!
B13: MOIC | C13: =C12/C11 -> 2.1562379 | E13: NAV | F13: =#REF! -> #REF!
B14: Gross IRR | C14: ='Investment Performance Summary'!J45 -> 0.23819565 | E14: TVPI | F14: =(F13+F12)/F11 -> #REF!
E15: DPI | F15: =F12/F11 -> #REF!
E16: Net IRR | F16: =#REF! -> #REF!

Sheet Investment Performance Summary
B2: SemperVirens Fund II Investment Summary
B4: ="As of "&TEXT('Statement of Investments'!$C$1,"mm/dd/yyyy") -> As of 12/31/2025 | C4: Initial Inv. | D4: Initial Exit | E4: Dollars | F4: Unrealized | G4: Realized | H4: Total | I4: Gross | J4: Gross
B5: Company | C5: Date | D5: Date | E5: Invested | F5: Value | G5: Value | H5: Value | I5: Multiple | J5: IRR
B6: Realized Portfolio
B8: Easop | C8: =INDEX('Statement of Investments'!$C$5:$C$220,MATCH('Investment Performance Summary'!$B8,'Statement of Investments'!$B$5:$B$220,0)) -> 45065 | D8: =INDEX('Statement of Investments'!$D$5:$D$220,MATCH('Investment Performance Summary'!$B8,'Statement of Investments'!$B$5:$B$220,0)) -> 45393 | E8: =INDEX('Statement of Investments'!$L$5:$L$220,MATCH($B8,'Statement of Investments'!$E$5:$E$220,0)) -> 218533.69 | F8: 0 | G8: =INDEX('Statement of Investments'!$O$5:$O$220,MATCH($B8,'Statement of Investments'!$E$5:$E$220,0)) -> 263324.5 | H8: =F8+G8 -> 263324.5 | I8: =H8/E8 -> 1.2049607 | J8: =INDEX('Statement of Investments'!$R$5:$R$220,MATCH($B8,'Statement of Investments'!$E$5:$E$220,0)) -> 0.18573675
B9: Mathison | C9: =INDEX('Statement of Investments'!$C$5:$C$220,MATCH('Investment Performance Summary'!$B9,'Statement of Investments'!$B$5:$B$220,0)) -> 44176 | D9: =INDEX('Statement of Investments'!$D$5:$D$220,MATCH('Investment Performance Summary'!$B9,'Statement of Investments'!$B$5:$B$220,0)) -> 45548 | E9: =INDEX('Statement of Investments'!$L$5:$L$220,MATCH($B9,'Statement of Investments'!$E$5:$E$220,0)) -> 2049994.2 | F9: 0 | G9: =INDEX('Statement of Investments'!$O$5:$O$220,MATCH($B9,'Statement of Investments'!$E$5:$E$220,0)) -> 272298.82 | H9: =F9+G9 -> 272298.82 | I9: =H9/E9 -> 0.13282907 | J9: =INDEX('Statement of Investments'!$R$5:$R$220,MATCH($B9,'Statement of Investments'!$E$5:$E$220,0)) -> -0.38768249
B10: Patch Caregiving | C10: =INDEX('Statement of Investments'!$C$5:$C$220,MATCH('Investment Performance Summary'!$B10,'Statement of Investments'!$B$5:$B$220,0)) -> 44879 | D10: =INDEX('Statement of Investments'!$D$5:$D$220,MATCH('Investment Performance Summary'!$B10,'Statement of Investments'!$B$5:$B$220,0)) -> 45897 | E10: =INDEX('Statement of Investments'!$L$5:$L$220,MATCH($B10,'Statement of Investments'!$E$5:$E$220,0)) -> 88754 | F10: 0 | G10: =INDEX('Statement of Investments'!$O$5:$O$220,MATCH($B10,'Statement of Investments'!$E$5:$E$220,0)) -> 88754 | H10: =F10+G10 -> 88754 | I10: =H10/E10 -> 1 | J10: =INDEX('Statement of Investments'!$R$5:$R$220,MATCH($B10,'Statement of Investments'!$E$5:$E$220,0)) -> 0.26417754
B11: Total Realized Portfolio | E11: =SUM(E6:E10) -> 2357281.9 | F11: =SUM(F6:F10) -> 0 | G11: =SUM(G6:G10) -> 624377.32 | H11: =SUM(H6:H10) -> 624377.32 | I11: =H11/E11 -> 0.26487173 | J11: ='Statement of Investments'!R77 -> -0.29641202
B13: Unrealized Portfolio
B15: Brightline | C15: =INDEX('Statement of Investments'!$C$5:$C$220,MATCH('Investment Performance Summary'!$B15,'Statement of Investments'!$B$5:$B$220,0)) -> 44047 | D15: - | E15: =INDEX('Statement of Investments'!$L$5:$L$220,MATCH($B15,'Statement of Investments'!$E$5:$E$220,0)) -> 1499987 | F15: =INDEX('Statement of Investments'!$O$5:$O$220,MATCH($B15,'Statement of Investments'!$E$5:$E$220,0)) -> 4521963.7 | G15: 0 | H15: =F15+G15 -> 4521963.7 | I15: =H15/E15 -> 3.0146685 | J15: =INDEX('Statement of Investments'!$R$5:$R$220,MATCH($B15,'Statement of Investments'!$E$5:$E$220,0)) -> 0.25233288
B16: Murmur | C16: =INDEX('Statement of Investments'!$C$5:$C$220,MATCH('Investment Performance Summary'!$B16,'Statement of Investments'!$B$5:$B$220,0)) -> 44098 | D16: - | E16: =INDEX('Statement of Investments'!$L$5:$L$220,MATCH($B16,'Statement of Investments'!$E$5:$E$220,0)) -> 1574998 | F16: =INDEX('Statement of Investments'!$O$5:$O$220,MATCH($B16,'Statement of Investments'!$E$5:$E$220,0)) -> 0 | G16: 0 | H16: =F16+G16 -> 0 | I16: =H16/E16 -> 0 | J16: =INDEX('Statement of Investments'!$R$5:$R$220,MATCH($B16,'Statement of Investments'!$E$5:$E$220,0)) -> -1 | K16: x
B17: Pinwheel | C17: =INDEX('Statement of Investments'!$C$5:$C$220,MATCH('Investment Performance Summary'!$B17,'Statement of Investments'!$B$5:$B$220,0)) -> 44105 | D17: - | E17: =INDEX('Statement of Investments'!$L$5:$L$220,MATCH($B17,'Statement of Investments'!$E$5:$E$220,0)) -> 1453156.1 | F17: =INDEX('Statement of Investments'!$O$5:$O$220,MATCH($B17,'Statement of Investments'!$E$5:$E$220,0)) -> 1453156.1 | G17: 0 | H17: =F17+G17 -> 1453156.1 | I17: =H17/E17 -> 1 | J17: =INDEX('Statement of Investments'!$R$5:$R$220,MATCH($B17,'Statement of Investments'!$E$5:$E$220,0)) -> 4.8828125e-09
B18: Cleo | C18: =INDEX('Statement of Investments'!$C$5:$C$220,MATCH('Investment Performance Summary'!$B18,'Statement of Investments'!$B$5:$B$220,0)) -> 44155 | D18: - | E18: =INDEX('Statement of Investments'!$L$5:$L$220,MATCH($B18,'Statement of Investments'!$E$5:$E$220,0)) -> 599997.84 | F18: =INDEX('Statement of Investments'!$O$5:$O$220,MATCH($B18,'Statement of Investments'!$E$5:$E$220,0)) -> 0 | G18: 0 | H18: =F18+G18 -> 0 | I18: =H18/E18 -> 0 | J18: =INDEX('Statement of Investments'!$R$5:$R$220,MATCH($B18,'Statement of Investments'!$E$5:$E$220,0)) -> -1 | K18: x
B19: Rightfoot | C19: =INDEX('Statement of Investments'!$C$5:$C$220,MATCH('Investment Performance Summary'!$B19,'Statement of Investments'!$B$5:$B$220,0)) -> 44175 | D19: - | E19: =INDEX('Statement of Investments'!$L$5:$L$220,MATCH($B19,'Statement of Investments'!$E$5:$E$220,0)) -> 399999.32 | F19: =INDEX('Statement of Investments'!$O$5:$O$220,MATCH($B19,'Statement of Investments'!$E$5:$E$220,0)) -> 0 | G19: 0 | H19: =F19+G19 -> 0 | I19: =H19/E19 -> 0 | J19: -1 | K19: x
B20: Galileo | C20: =INDEX('Statement of Investments'!$C$5:$C$220,MATCH('Investment Performance Summary'!$B20,'Statement of Investments'!$B$5:$B$220,0)) -> 44232 | D20: - | E20: =INDEX('Statement of Investments'!$L$5:$L$220,MATCH($B20,'Statement of Investments'!$E$5:$E$220,0)) -> 2163901.7 | F20: =INDEX('Statement of Investments'!$O$5:$O$220,MATCH($B20,'Statement of Investments'!$E$5:$E$220,0)) -> 1724878.8 | G20: 0 | H20: =F20+G20 -> 1724878.8 | I20: =H20/E20 -> 0.79711515 | J20: =INDEX('Statement of Investments'!$R$5:$R$220,MATCH($B20,'Statement of Investments'!$E$5:$E$220,0)) -> -0.048803942
B21: Cocoon | C21: =INDEX('Statement of Investments'!$C$5:$C$220,MATCH('Investment Performance Summary'!$B21,'Statement of Investments'!$B$5:$B$220,0)) -> 44232 | D21: - | E21: =INDEX('Statement of Investments'!$L$5:$L$220,MATCH($B21,'Statement of Investments'!$E$5:$E$220,0)) -> 4224996.6 | F21: =INDEX('Statement of Investments'!$O$5:$O$220,MATCH($B21,'Statement of Investments'!$E$5:$E$220,0)) -> 4224996.6 | G21: 0 | H21: =F21+G21 -> 4224996.6 | I21: =H21/E21 -> 1 | J21: =INDEX('Statement of Investments'!$R$5:$R$220,MATCH($B21,'Statement of Investments'!$E$5:$E$220,0)) -> 0.31390677
B22: Rula | C22: =INDEX('Statement of Investments'!$C$5:$C$220,MATCH('Investment Performance Summary'!$B22,'Statement of Investments'!$B$5:$B$220,0)) -> 44265 | D22: - | E22: =INDEX('Statement of Investments'!$L$5:$L$220,MATCH($B22,'Statement of Investments'!$E$5:$E$220,0)) -> 4500000 | F22: =INDEX('Statement of Investments'!$O$5:$O$220,MATCH($B22,'Statement of Investments'!$E$5:$E$220,0)) -> 25285301 | G22: 0 | H22: =F22+G22 -> 25285301 | I22: =H22/E22 -> 5.6189558 | J22: =INDEX('Statement of Investments'!$R$5:$R$220,MATCH($B22,'Statement of Investments'!$E$5:$E$220,0)) -> 0.50046626
B23: Origin | C23: =INDEX('Statement of Investments'!$C$5:$C$220,MATCH('Investment Performance Summary'!$B23,'Statement of Investments'!$B$5:$B$220,0)) -> 44307 | D23: - | E23: =INDEX('Statement of Investments'!$L$5:$L$220,MATCH($B23,'Statement of Investments'!$E$5:$E$220,0)) -> 3699992.1 | F23: =INDEX('Statement of Investments'!$O$5:$O$220,MATCH($B23,'Statement of Investments'!$E$5:$E$220,0)) -> 3699992.1 | G23: 0 | H23: =F23+G23 -> 3699992.1 | I23: =H23/E23 -> 1 | J23: =INDEX('Statement of Investments'!$R$5:$R$220,MATCH($B23,'Statement of Investments'!$E$5:$E$220,0)) -> 4.8828125e-09
B24: Nayya | C24: =INDEX('Statement of Investments'!$C$5:$C$220,MATCH('Investment Performance Summary'!$B24,'Statement of Investments'!$B$5:$B$220,0)) -> 44344 | D24: - | E24: =INDEX('Statement of Investments'!$L$5:$L$220,MATCH($B24,'Statement of Investments'!$E$5:$E$220,0)) -> 2699987.1 | F24: =INDEX('Statement of Investments'!$O$5:$O$220,MATCH($B24,'Statement of Investments'!$E$5:$E$220,0)) -> 3853385.4 | G24: 0 | H24: =F24+G24 -> 3853385.4 | I24: =H24/E24 -> 1.4271866 | J24: =INDEX('Statement of Investments'!$R$5:$R$220,MATCH($B24,'Statement of Investments'!$E$5:$E$220,0)) -> 0.09124564
B25: Praisidio | C25: =INDEX('Statement of Investments'!$C$5:$C$220,MATCH('Investment Performance Summary'!$B25,'Statement of Investments'!$B$5:$B$220,0)) -> 44370 | D25: - | E25: =INDEX('Statement of Investments'!$L$5:$L$220,MATCH($B25,'Statement of Investments'!$E$5:$E$220,0)) -> 200000 | F25: =INDEX('Statement of Investments'!$O$5:$O$220,MATCH($B25,'Statement of Investments'!$E$5:$E$220,0)) -> 0 | G25: 0 | H25: =F25+G25 -> 0 | I25: =H25/E25 -> 0 | J25: =INDEX('Statement of Investments'!$R$5:$R$220,MATCH($B25,'Statement of Investments'!$E$5:$E$220,0)) -> -1 | K25: x
B26: Bravely | C26: =INDEX('Statement of Investments'!$C$5:$C$220,MATCH('Investment Performance Summary'!$B26,'Statement of Investments'!$B$5:$B$220,0)) -> 44379 | D26: - | E26: =INDEX('Statement of Investments'!$L$5:$L$220,MATCH($B26,'Statement of Investments'!$E$5:$E$220,0)) -> 1249999.6 | F26: =INDEX('Statement of Investments'!$O$5:$O$220,MATCH($B26,'Statement of Investments'!$E$5:$E$220,0)) -> 1249999.6 | G26: 0 | H26: =F26+G26 -> 1249999.6 | I26: =H26/E26 -> 1 | J26: =INDEX('Statement of Investments'!$R$5:$R$220,MATCH($B26,'Statement of Investments'!$E$5:$E$220,0)) -> 4.8828125e-09
B27: Remote | C27: =INDEX('Statement of Investments'!$C$5:$C$220,MATCH('Investment Performance Summary'!$B27,'Statement of Investments'!$B$5:$B$220,0)) -> 44398 | D27: - | E27: =INDEX('Statement of Investments'!$L$5:$L$220,MATCH($B27,'Statement of Investments'!$E$5:$E$220,0)) -> 4781446 | F27: =INDEX('Statement of Investments'!$O$5:$O$220,MATCH($B27,'Statement of Investments'!$E$5:$E$220,0)) -> 10354762 | G27: 0 | H27: =F27+G27 -> 10354762 | I27: =H27/E27 -> 2.165613 | J27: =INDEX('Statement of Investments'!$R$5:$R$220,MATCH($B27,'Statement of Investments'!$E$5:$E$220,0)) -> 0.20782523
B28: Finch | C28: =INDEX('Statement of Investments'!$C$5:$C$220,MATCH('Investment Performance Summary'!$B28,'Statement of Investments'!$B$5:$B$220,0)) -> 44435 | D28: - | E28: =INDEX('Statement of Investments'!$L$5:$L$220,MATCH($B28,'Statement of Investments'!$E$5:$E$220,0)) -> 500003.42 | F28: =INDEX('Statement of Investments'!$O$5:$O$220,MATCH($B28,'Statement of Investments'!$E$5:$E$220,0)) -> 740862.12 | G28: 0 | H28: =F28+G28 -> 740862.12 | I28: =H28/E28 -> 1.4817141 | J28: =INDEX('Statement of Investments'!$R$5:$R$220,MATCH($B28,'Statement of Investments'!$E$5:$E$220,0)) -> 0.094648638
B29: Midi | C29: =INDEX('Statement of Investments'!$C$5:$C$220,MATCH('Investment Performance Summary'!$B29,'Statement of Investments'!$B$5:$B$220,0)) -> 44455 | D29: - | E29: =INDEX('Statement of Investments'!$L$5:$L$220,MATCH($B29,'Statement of Investments'!$E$5:$E$220,0)) -> 5531507 | F29: =INDEX('Statement of Investments'!$O$5:$O$220,MATCH($B29,'Statement of Investments'!$E$5:$E$220,0)) -> 48185999 | G29: 0 | H29: =F29+G29 -> 48185999 | I29: =H29/E29 -> 8.7111883 | J29: =INDEX('Statement of Investments'!$R$5:$R$220,MATCH($B29,'Statement of Investments'!$E$5:$E$220,0)) -> 0.95959565
B30: ianacare | C30: =INDEX('Statement of Investments'!$C$5:$C$220,MATCH('Investment Performance Summary'!$B30,'Statement of Investments'!$B$5:$B$220,0)) -> 44547 | D30: - | E30: =INDEX('Statement of Investments'!$L$5:$L$220,MATCH($B30,'Statement of Investments'!$E$5:$E$220,0)) -> 2999984.9 | F30: =INDEX('Statement of Investments'!$O$5:$O$220,MATCH($B30,'Statement of Investments'!$E$5:$E$220,0)) -> 2999984.9 | G30: 0 | H30: =F30+G30 -> 2999984.9 | I30: =H30/E30 -> 1 | J30: =INDEX('Statement of Investments'!$R$5:$R$220,MATCH($B30,'Statement of Investments'!$E$5:$E$220,0)) -> 4.8828125e-09
B31: Vivante | C31: =INDEX('Statement of Investments'!$C$5:$C$220,MATCH('Investment Performance Summary'!$B31,'Statement of Investments'!$B$5:$B$220,0)) -> 44552 | D31: - | E31: =INDEX('Statement of Investments'!$L$5:$L$220,MATCH($B31,'Statement of Investments'!$E$5:$E$220,0)) -> 2204142.3 | F31: =INDEX('Statement of Investments'!$O$5:$O$220,MATCH($B31,'Statement of Investments'!$E$5:$E$220,0)) -> 3130662 | G31: 0 | H31: =F31+G31 -> 3130662 | I31: =H31/E31 -> 1.4203538 | J31: =INDEX('Statement of Investments'!$R$5:$R$220,MATCH($B31,'Statement of Investments'!$E$5:$E$220,0)) -> 0.11739947
B32: a.team | C32: =INDEX('Statement of Investments'!$C$5:$C$220,MATCH('Investment Performance Summary'!$B32,'Statement of Investments'!$B$5:$B$220,0)) -> 44567 | D32: - | E32: =INDEX('Statement of Investments'!$L$5:$L$220,MATCH($B32,'Statement of Investments'!$E$5:$E$220,0)) -> 999998.86 | F32: =INDEX('Statement of Investments'!$O$5:$O$220,MATCH($B32,'Statement of Investments'!$E$5:$E$220,0)) -> 999998.86 | G32: 0 | H32: =F32+G32 -> 999998.86 | I32: =H32/E32 -> 1 | J32: =INDEX('Statement of Investments'!$R$5:$R$220,MATCH($B32,'Statement of Investments'!$E$5:$E$220,0)) -> 4.8828125e-09
B33: CoverGo | C33: =INDEX('Statement of Investments'!$C$5:$C$220,MATCH('Investment Performance Summary'!$B33,'Statement of Investments'!$B$5:$B$220,0)) -> 44621 | D33: - | E33: =INDEX('Statement of Investments'!$L$5:$L$220,MATCH($B33,'Statement of Investments'!$E$5:$E$220,0)) -> 4000000 | F33: =INDEX('Statement of Investments'!$O$5:$O$220,MATCH($B33,'Statement of Investments'!$E$5:$E$220,0)) -> 5294506.9 | G33: 0 | H33: =F33+G33 -> 5294506.9 | I33: =H33/E33 -> 1.3236267 | J33: =INDEX('Statement of Investments'!$R$5:$R$220,MATCH($B33,'Statement of Investments'!$E$5:$E$220,0)) -> 0.083919224
B34: Ashby | C34: =INDEX('Statement of Investments'!$C$5:$C$220,MATCH('Investment Performance Summary'!$B34,'Statement of Investments'!$B$5:$B$220,0)) -> 44599 | D34: - | E34: =INDEX('Statement of Investments'!$L$5:$L$220,MATCH($B34,'Statement of Investments'!$E$5:$E$220,0)) -> 5000000 | F34: =INDEX('Statement of Investments'!$O$5:$O$220,MATCH($B34,'Statement of Investments'!$E$5:$E$220,0)) -> 10135319 | G34: 0 | H34: =F34+G34 -> 10135319 | I34: =H34/E34 -> 2.0270638 | J34: =INDEX('Statement of Investments'!$R$5:$R$220,MATCH($B34,'Statement of Investments'!$E$5:$E$220,0)) -> 0.21993771
B35: Delfina | C35: =INDEX('Statement of Investments'!$C$5:$C$220,MATCH('Investment Performance Summary'!$B35,'Statement of Investments'!$B$5:$B$220,0)) -> 44621 | D35: - | E35: =INDEX('Statement of Investments'!$L$5:$L$220,MATCH($B35,'Statement of Investments'!$E$5:$E$220,0)) -> 1549999.9 | F35: =INDEX('Statement of Investments'!$O$5:$O$220,MATCH($B35,'Statement of Investments'!$E$5:$E$220,0)) -> 2097344.6 | G35: 0 | H35: =F35+G35 -> 2097344.6 | I35: =H35/E35 -> 1.3531256 | J35: =INDEX('Statement of Investments'!$R$5:$R$220,MATCH($B35,'Statement of Investments'!$E$5:$E$220,0)) -> 0.11896514
B36: Mosey | C36: =INDEX('Statement of Investments'!$C$5:$C$220,MATCH('Investment Performance Summary'!$B36,'Statement of Investments'!$B$5:$B$220,0)) -> 44707 | D36: - | E36: =INDEX('Statement of Investments'!$L$5:$L$220,MATCH($B36,'Statement of Investments'!$E$5:$E$220,0)) -> 3999998.9 | F36: =INDEX('Statement of Investments'!$O$5:$O$220,MATCH($B36,'Statement of Investments'!$E$5:$E$220,0)) -> 3999998.9 | G36: 0 | H36: =F36+G36 -> 3999998.9 | I36: =H36/E36 -> 1 | J36: =INDEX('Statement of Investments'!$R$5:$R$220,MATCH($B36,'Statement of Investments'!$E$5:$E$220,0)) -> 4.8828125e-09
B37: Violet | C37: =INDEX('Statement of Investments'!$C$5:$C$220,MATCH('Investment Performance Summary'!$B37,'Statement of Investments'!$B$5:$B$220,0)) -> 44722 | D37: - | E37: =INDEX('Statement of Investments'!$L$5:$L$220,MATCH($B37,'Statement of Investments'!$E$5:$E$220,0)) -> 2599995.3 | F37: =INDEX('Statement of Investments'!$O$5:$O$220,MATCH($B37,'Statement of Investments'!$E$5:$E$220,0)) -> 2599995.3 | G37: 0 | H37: =F37+G37 -> 2599995.3 | I37: =H37/E37 -> 1 | J37: =INDEX('Statement of Investments'!$R$5:$R$220,MATCH($B37,'Statement of Investments'!$E$5:$E$220,0)) -> 4.8828125e-09
B38: Gable | C38: =INDEX('Statement of Investments'!$C$5:$C$220,MATCH('Investment Performance Summary'!$B38,'Statement of Investments'!$B$5:$B$220,0)) -> 44848 | D38: - | E38: =INDEX('Statement of Investments'!$L$5:$L$220,MATCH($B38,'Statement of Investments'!$E$5:$E$220,0)) -> 4000000 | F38: =INDEX('Statement of Investments'!$O$5:$O$220,MATCH($B38,'Statement of Investments'!$E$5:$E$220,0)) -> 4000000 | G38: 0 | H38: =F38+G38 -> 4000000 | I38: =H38/E38 -> 1 | J38: =INDEX('Statement of Investments'!$R$5:$R$220,MATCH($B38,'Statement of Investments'!$E$5:$E$220,0)) -> -4.8828125e-09
B39: Patch Caregiving | C39: =INDEX('Statement of Investments'!$C$5:$C$220,MATCH('Investment Performance Summary'!$B39,'Statement of Investments'!$B$5:$B$220,0)) -> 44879 | D39: - | E39: ='Statement of Investments'!L204 -> 411245.85 | F39: ='Statement of Investments'!O204 -> 586415.29 | G39: 0 | H39: =F39+G39 -> 586415.29 | I39: =H39/E39 -> 1.4259482 | J39: =INDEX('Statement of Investments'!$R$5:$R$220,MATCH($B39,'Statement of Investments'!$E$5:$E$220,0)) -> 0.26417754
B40: Formally | C40: =INDEX('Statement of Investments'!$C$5:$C$220,MATCH('Investment Performance Summary'!$B40,'Statement of Investments'!$B$5:$B$220,0)) -> 45006 | D40: - | E40: =INDEX('Statement of Investments'!$L$5:$L$220,MATCH($B40,'Statement of Investments'!$E$5:$E$220,0)) -> 1000000 | F40: =INDEX('Statement of Investments'!$O$5:$O$220,MATCH($B40,'Statement of Investments'!$E$5:$E$220,0)) -> 1000000 | G40: 0 | H40: =F40+G40 -> 1000000 | I40: =H40/E40 -> 1 | J40: =INDEX('Statement of Investments'!$R$5:$R$220,MATCH($B40,'Statement of Investments'!$E$5:$E$220,0)) -> 4.8828125e-09
B41: Liftoff | C41: =INDEX('Statement of Investments'!$C$5:$C$220,MATCH('Investment Performance Summary'!$B41,'Statement of Investments'!$B$5:$B$220,0)) -> 45064 | D41: - | E41: =INDEX('Statement of Investments'!$L$5:$L$220,MATCH($B41,'Statement of Investments'!$E$5:$E$220,0)) -> 886565.66 | F41: =INDEX('Statement of Investments'!$O$5:$O$220,MATCH($B41,'Statement of Investments'!$E$5:$E$220,0)) -> 1896344.2 | G41: 0 | H41: =F41+G41 -> 1896344.2 | I41: =H41/E41 -> 2.1389777 | J41: =INDEX('Statement of Investments'!$R$5:$R$220,MATCH($B41,'Statement of Investments'!$E$5:$E$220,0)) -> 0.42452904
B43: Total Unrealized Portfolio | E43: =SUM(E15:E42) -> 64731903 | F43: =SUM(F15:F42) -> 1.4403587e+08 | G43: =SUM(G15:G42) -> 0 | H43: =SUM(H15:H42) -> 1.4403587e+08 | I43: =H43/E43 -> 2.225114 | J43: ='Statement of Investments'!R218 -> 0.24891897
B45: Total Portfolio | E45: =+E43+E11 -> 67089185 | F45: =+F43+F11 -> 1.4403587e+08 | G45: =+G43+G11 -> 624377.32 | H45: =+H43+H11 -> 1.4466024e+08 | I45: =H45/E45 -> 2.1562379 | J45: ='Statement of Investments'!R220 -> 0.23819565
E49: =E45/73293334 -> 0.9153518 | J49: =SUMIF(K15:K41,"x",E15:E41) -> 2774995.2
J50: =J49/E45 -> 0.041362779

Sheet Supporting Worksheets -->

Sheet Statement of Investments
A1: 46022 | B1: As of | C1: =IF(TODAY()<$A$1,TODAY(),A1) -> 46022
C2: Investment | D2: Liquidity | K2: Original Cost | N2: Current Value | Q2: Gross
C3: Date | D3: Date | F3: Security | G3: Stock Certificates | I3: Shares | K3: Per Share | L3: Total Dollars | N3: Per Share | O3: Total Dollars | Q3: MOIC | R3: IRR
S4: 43101 | T4: -0.1
A5: REALIZED
B7: Easop | C7: 45065 | D7: 45393 | F7: SAFE - Cash proceeds | L7: 218533.69 | O7: =L7 -> 218533.69 | S7: =IFERROR(C7,0) -> 45065 | T7: =-L7 -> -218533.69
C8: 45065 | D8: 45852 | F8: Escrow Cash Proceeds | O8: 44790.81 | S8: =D7 -> 45393 | T8: =O7 -> 218533.69
E9: =B7 -> Easop | F9: Total | L9: =SUM(L7:L8) -> 218533.69 | O9: =SUM(O7:O8) -> 263324.5 | Q9: =O9/L9 -> 1.2049607 | R9: =XIRR(T7:T9,S7:S9,0) -> 0.18573675 | S9: =D8 -> 45852 | T9: =O8 -> 44790.81
B11: Mathison | C11: 44176 | D11: 45548 | F11: Series Seed-2 Preferred Stock | G11: SS2-8 | I11: 329525 | K11: =L11/I11 -> 0.9104 | L11: 299999.56 | N11: 0 | O11: 39848.7 | S11: =IFERROR(C11,0) -> 44176 | T11: =-L11 -> -299999.56
C12: 44470 | D12: 45548 | F12: Series A-1 Preferred Stock | G12: PA-16 | I12: 316902 | K12: =L12/I12 -> 2.3666622 | L12: =0.75*10^6 -> 750000 | N12: 0 | O12: 99621.61 | S12: =IFERROR(C12,0) -> 44470 | T12: =-L12 -> -750000 | U12: Secondary (67,605 shares) | W12: =67605/316902 -> 0.21333094 | X12: =W12*L12 -> 159998.2
D13: 45548 | F13: Common Warrants | I13: 54377 | N13: 0 | O13: =I13*N13 -> 0 | S13: =IFERROR(C13,0) -> 0 | T13: =-L13 -> 0
C14: 44630 | D14: 45548 | F14: Series A Preferred Stock | I14: 338028 | K14: =L14/I14 -> 2.9583189 | L14: 999994.63 | N14: 0 | O14: 132828.51 | S14: =IFERROR(C14,0) -> 44630 | T14: =-L14 -> -999994.63
E16: =B11 -> Mathison | F16: Total | L16: =SUM(L11:L15) -> 2049994.2 | O16: =SUM(O11:O15) -> 272298.82 | Q16: =O16/L16 -> 0.13282907 | R16: =XIRR(T11:T16,S11:S16,-0.1) -> -0.38768249 | S16: =$C$1 -> 46022 | T16: =O16 -> 272298.82
B18: Patch Caregiving | C18: 44879 | D18: 45897 | F18: SAFE - Cash proceeds | L18: 88754 | O18: 88754 | S18: =IFERROR(C18,0) -> 44879 | T18: =-L18 -> -88754 | U18: 675000
S19: =D18 -> 45897 | T19: =O18 -> 88754
B20: (Wellthy Merger) | E20: =B18 -> Patch Caregiving | F20: Total | L20: =SUM(L18:L19) -> 88754 | O20: =SUM(O18:O19) -> 88754 | Q20: =O20/L20 -> 1 | R20: =XIRR(T18:T20,S18:S20,0) -> 0.26417754 | S20: =$C$1 -> 46022 | T20: =O20 -> 88754
B77: Total Realized Portfolio | L77: =SUMIF($F$6:$F$76,"Total",L6:L76) -> 2357281.9 | O77: =SUMIF($F$6:$F$76,"Total",O6:O76) -> 624377.32 | Q77: =IFERROR(O77/L77,0) -> 0.26487173 | R77: =+XIRR(T7:T76,S7:S76,-0.1) -> -0.29641202
A79: UNREALIZED
S80: 43101 | T80: -0.1
B81: Brightline | C81: 44047 | F81: Series A Preferred Stock | G81: PA-3 | I81: =93937*3 -> 281811 | K81: =L81/I81 -> 1.7742333 | L81: 499998.47 | N81: 8.7256 | O81: =$I81*N81 -> 2458970.1 | S81: =IFERROR(C81,0) -> 44047 | T81: =-L81 -> -499998.47
C82: 44333 | F82: Series B Preferred Stock | G82: PB-5 | I82: =78810*3 -> 236430 | K82: =L82/I82 -> 4.2295334 | L82: 999988.57 | N82: =N81 -> 8.7256 | O82: =$I82*N82 -> 2062993.6 | S82: =IFERROR(C82,0) -> 44333 | T82: =-L82 -> -999988.57
E84: =B81 -> Brightline | F84: Total | I84: =I81+I82 -> 518241 | L84: =SUM(L81:L83) -> 1499987 | O84: =SUM(O81:O83) -> 4521963.7 | Q84: =O84/L84 -> 3.0146685 | R84: =XIRR(T81:T84,S81:S84,) -> 0.25233288 | S84: =$C$1 -> 46022 | T84: =O84 -> 4521963.7
B86: Murmur | C86: 44098 | F86: Series Seed Preferred Stock | G86: SSPS-2 | I86: 192884 | K86: =L86/I86 -> 1.1665042 | L86: 225000 | N86: 0 | O86: =$I86*N86 -> 0 | S86: =IFERROR(C86,0) -> 44098 | T86: =-L86 -> -225000
C87: 44406 | F87: Series Seed-1 Preferred Stock | G87: SN-8 | I87: 63431 | K87: =+L87/I87 -> 1.5765162 | L87: 100000 | N87: 0 | O87: =$I87*N87 -> 0 | S87: =IFERROR(C87,0) -> 44406 | T87: =-L87 -> -100000
C88: 44784 | F88: Series Seed-2 Preferred Stock | G88: SN-8 | I88: 589011.99 | K88: =+L88/I88 -> 2.1221945 | L88: 1249998 | N88: 0 | O88: =$I88*N88 -> 0 | S88: =IFERROR(C88,0) -> 44784 | T88: =-L88 -> -1249998
E90: =B86 -> Murmur | F90: Total | I90: =SUM(I86:I88) -> 845326.99 | L90: =SUM(L86:L89) -> 1574998 | O90: =SUM(O86:O89) -> 0 | Q90: =O90/L90 -> 0 | R90: -1 | S90: =$C$1 -> 46022 | T90: =O90 -> 0
B92: Pinwheel | C92: 44105 | F92: Series A Preferred Stock | G92: PA-16 | I92: 118435 | K92: =L92/I92 -> 4.2217 | L92: 499997.04 | N92: =K92 -> 4.2217 | O92: =$I92*N92 -> 499997.04 | S92: =IFERROR(C92,0) -> 44105 | T92: =-L92 -> -499997.04
C93: 44593 | F93: Series B Preferred Stock | G93: PA-16 | I93: 54200 | K93: =L93/I93 -> 17.58596 | L93: 953159.03 | N93: =K93 -> 17.58596 | O93: =$I93*N93 -> 953159.03 | S93: =IFERROR(C93,0) -> 44593 | T93: =-L93 -> -953159.03 | U93: Secondary | X93: =L93 -> 953159.03
E95: =B92 -> Pinwheel | F95: Total | I95: =I92+I93 -> 172635 | L95: =SUM(L92:L94) -> 1453156.1 | O95: =SUM(O92:O94) -> 1453156.1 | Q95: =O95/L95 -> 1 | R95: =XIRR(T92:T95,S92:S95,0) -> 4.8828125e-09 | S95: =$C$1 -> 46022 | T95: =O95 -> 1453156.1
B97: Cleo | C97: 44155 | F97: Series B Preferred Stock | G97: PB-16 | I97: =L97/K97 -> 143061 | K97: 4.194 | L97: 599997.84 | N97: 0 | O97: =I97*N97 -> 0 | S97: =IFERROR(C97,0) -> 44155 | T97: =-L97 -> -599997.84
E99: =B97 -> Cleo | F99: Total | I99: =I97 -> 143061 | L99: =SUM(L97:L98) -> 599997.84 | O99: =SUM(O97:O98) -> 0 | Q99: =O99/L99 -> 0 | R99: -1 | S99: =$C$1 -> 46022 | T99: =O99 -> 0
B101: Rightfoot | C101: 44175 | F101: Series Seed Stock | G101: PS-19 | I101: 372127 | K101: =L101/I101 -> 1.0749 | L101: 399999.32 | N101: 0 | O101: =$I101*N101 -> 0 | S101: =IFERROR(C101,0) -> 44175 | T101: =-L101 -> -399999.32
E103: =B101 -> Rightfoot | F103: Total | I103: =I101 -> 372127 | L103: =SUM(L101:L102) -> 399999.32 | O103: =SUM(O101:O102) -> 0 | Q103: =O103/L103 -> 0 | R103: -1 | S103: =$C$1 -> 46022 | T103: =O103 -> 0
B105: Galileo | C105: 44232 | F105: Series C Preferred Stock | G105: PC-7 | I105: 307749 | K105: =L105/I105 -> 6.4988 | L105: 1999999.2 | N105: =N106 -> 0.45682001 | O105: =$I105*N105 -> 140585.9 | S105: =IFERROR(C105,0) -> 44232 | T105: =-L105 -> -1999999.2
C106: 45849 | F106: Series E-2 Preferred | I106: 358790 | K106: =L106/I106 -> 0.45682001 | L106: 163902.45 | N106: =K106 -> 0.45682001 | O106: =$I106*N106 -> 163902.45 | S106: =IFERROR(C106,0) -> 45849 | T106: =-L106 -> -163902.45 | U106: Warehoused | X106: =L106 -> 163902.45
C107: 45849 | F107: Class A Common Stock Warrants | I107: 3109300 | N107: =N106 -> 0.45682001 | O107: =$I107*N107 -> 1420390.4 | S107: =IFERROR(C107,0) -> 45849 | T107: =-L107 -> 0
E108: =B105 -> Galileo | F108: Total | I108: =SUM(I105:I107) -> 3775839 | L108: =SUM(L105:L106) -> 2163901.7 | O108: =SUM(O105:O107) -> 1724878.8 | Q108: =O108/L108 -> 0.79711515 | R108: =XIRR(T105:T108,S105:S108,0) -> -0.048803942 | S108: =$C$1 -> 46022 | T108: =O108 -> 1724878.8
B110: Cocoon | C110: 44232 | F110: Series Seed Preferred Stock | G110: PS1-2 | I110: 260145 | K110: =L110/I110 -> 0.86490004 | L110: 224999.42 | N110: =+K110 -> 0.86490004 | O110: =$I110*N110 -> 224999.42 | S110: =IFERROR(C110,0) -> 44232 | T110: =-L110 -> -224999.42
C111: 44399 | F111: Series A Preferred Stock | G111: PA-6 | I111: 251971 | K111: =L111/I111 -> 3.9687 | L111: 999997.31 | N111: =+K111 -> 3.9687 | O111: =$I111*N111 -> 999997.31 | S111: =IFERROR(C111,0) -> 44399 | T111: =-L111 -> -999997.31
C112: 44862 | F112: Series A Preferred Stock | I112: =L112/K112 -> 755915 | K112: =N111 -> 3.9687 | L112: 2999999.9 | N112: =+K112 -> 3.9687 | O112: =$I112*N112 -> 2999999.9
E114: =B110 -> Cocoon | F114: Total | I114: =SUM(I110:I112) -> 1268031 | L114: =SUM(L110:L113) -> 4224996.6 | O114: =SUM(O110:O113) -> 4224996.6 | Q114: =O114/L114 -> 1 | R114: =XIRR(T110:T114,S110:S114,0) -> 0.31390677 | S114: =$C$1 -> 46022 | T114: =O114 -> 4224996.6
B116: Rula | C116: 44265 | F116: Series A-1 Preferred Stock | G116: PA1-2 | I116: 3388015 | K116: =L116/I116 -> 0.44273712 | L116: 1500000 | N116: 5.781625 | O116: =I116*N116 -> 19588232 | S116: =IFERROR(C116,0) -> 44265 | T116: =-L116 -> -1500000
C117: 44592 | F117: Series B Preferred Stock | G117: PA-16 | I117: 985375 | K117: =L117/I117 -> 3.0445262 | L117: =3*10^6 -> 3000000 | N117: =N116 -> 5.781625 | O117: =$I117*N117 -> 5697068.7 | S117: =IFERROR(C117,0) -> 44592 | T117: =-L117 -> -3000000
E119: =B116 -> Rula | F119: Total | I119: =I116+I117 -> 4373390 | L119: =SUM(L116:L118) -> 4500000 | O119: =SUM(O116:O118) -> 25285301 | Q119: =O119/L119 -> 5.6189558 | R119: =XIRR(T116:T119,S116:S119,0) -> 0.50046626 | S119: =$C$1 -> 46022 | T119: =O119 -> 25285301 | W119: `
B121: Origin | C121: 44307 | F121: Series A-3 Preferred Stock | G121: PA3-12 | I121: 554377 | K121: =L121/I121 -> 3.0665 | L121: 1699997.1 | N121: =+K121 -> 3.0665 | O121: =$I121*N121 -> 1699997.1 | S121: =IFERROR(C121,0) -> 44307 | T121: =-L121 -> -1699997.1
C122: 44434 | F122: Series B-2 Preferred Stock | G122: PB2-11 | I122: 246129 | K122: =L122/I122 -> 8.1258 | L122: 1999995 | N122: =+K122 -> 8.1258 | O122: =$I122*N122 -> 1999995 | S122: =IFERROR(C122,0) -> 44434 | T122: =-L122 -> -1999995
C123: =C1 -> 46022 | F123: Series A Warrants | I123: =554377 -> 554377 | K123: 0 | L123: 0 | N123: 0 | O123: =$I123*N123 -> 0 | S123: =IFERROR(C123,0) -> 46022 | T123: =-L123 -> 0
E125: =B121 -> Origin | F125: Total | I125: =SUM(I121:I123) -> 1354883 | L125: =SUM(L121:L124) -> 3699992.1 | O125: =SUM(O121:O123) -> 3699992.1 | Q125: =O125/L125 -> 1 | R125: =XIRR(T121:T125,S121:S125,0) -> 4.8828125e-09 | S125: =$C$1 -> 46022 | T125: =O125 -> 3699992.1
B127: Nayya | C127: 44344 | F127: Series C-1 Preferred Stock (converted to C-4 on 1/18/2022) | G127: PC4-1 | I127: 57138 | K127: =L127/I127 -> 8.7507438 | L127: =0.5*10^6 -> 500000 | N127: 16.8251 | O127: =I127*N127 -> 961352.57 | S127: =IFERROR(C127,0) -> 44344 | T127: =-L127 -> -500000
C128: 44524 | F128: Series C-1 Preferred Stock (converted to C-4 on 1/18/2022) | G128: PC4-1 | I128: 85708 | K128: =L128/I128 -> 8.7506417 | L128: 750000 | N128: =N127 -> 16.8251 | O128: =I128*N128 -> 1442045.7 | S128: =IFERROR(C128,0) -> 44524 | T128: =-L128 -> -750000
C129: 44609 | F129: Series C-2 Preferred Stock | G129: PC2-12 | I129: 86180 | K129: =L129/I129 -> 16.8251 | L129: 1449987.1 | N129: =N128 -> 16.8251 | O129: =I129*N129 -> 1449987.1 | S129: =IFERROR(C129,0) -> 44609 | T129: =-L129 -> -1449987.1
E131: =B127 -> Nayya | F131: Total | I131: =SUM(I127:I130) -> 229026 | L131: =SUM(L127:L130) -> 2699987.1 | O131: =SUM(O127:O130) -> 3853385.4 | Q131: =O131/L131 -> 1.4271866 | R131: =XIRR(T127:T131,S127:S131,0) -> 0.09124564 | S131: =$C$1 -> 46022 | T131: =O131 -> 3853385.4 | U131: =O131/O220 -> 0.026637487
B133: Praisidio | C133: 44370 | F133: Series Seed Preferred Stock | G133: PSS-3 | I133: 313612 | K133: =L133/I133 -> 0.6377307 | L133: =0.2*10^6 -> 200000 | N133: 0 | O133: =I133*N133 -> 0 | S133: =IFERROR(C133,0) -> 44370 | T133: =-L133 -> -200000
F134: Series Seed Warrants
E136: =B133 -> Praisidio | F136: Total | L136: =SUM(L133:L135) -> 200000 | O136: =SUM(O133:O135) -> 0 | Q136: =O136/L136 -> 0 | R136: -1 | S136: =$C$1 -> 46022 | T136: =O136 -> 0
B138: Bravely | C138: 44379 | F138: Series A Preferred Stock | G138: PSA-7 | I138: 743260 | K138: =L138/I138 -> 1.6817797 | L138: 1249999.6 | N138: =K138 -> 1.6817797 | O138: =I138*N138 -> 1249999.6 | S138: =IFERROR(C138,0) -> 44379 | T138: =-L138 -> -1249999.6
E140: =B138 -> Bravely | F140: Total | L140: =SUM(L138:L139) -> 1249999.6 | O140: =SUM(O138:O139) -> 1249999.6 | Q140: =O140/L140 -> 1 | R140: =XIRR(T138:T140,S138:S140,0) -> 4.8828125e-09 | S140: =$C$1 -> 46022 | T140: =O140 -> 1249999.6
B142: Remote | C142: 44398 | F142: Series B Preferred Stock | G142: PB-18 | I142: 99181 | K142: =L142/I142 -> 40.3301 | L142: 3999979.6 | N142: 95.82862 | O142: =I142*N142 -> 9504378.4 | S142: =IFERROR(C142,0) -> 44398 | T142: =-L142 -> -3999979.6
C143: 45382 | F143: Common Shares | I143: 8874 | K143: =+L143/I143 -> 88.062464 | L143: 781466.31 | N143: =+N142 -> 95.82862 | O143: =I143*N143 -> 850383.17 | S143: =IFERROR(C143,0) -> 45382 | T143: =-L143 -> -781466.31
E145: =B142 -> Remote | F145: Total | I145: =I142+I143 -> 108055 | L145: =SUM(L142:L144) -> 4781446 | O145: =SUM(O142:O144) -> 10354762 | Q145: =O145/L145 -> 2.165613 | R145: =XIRR(T142:T145,S142:S145,0) -> 0.20782523 | S145: =$C$1 -> 46022 | T145: =O145 -> 10354762
B147: Finch | C147: 44435 | F147: Series A Preferred Stock | G147: PA-4 | I147: 71374 | K147: =L147/I147 -> 7.0054 | L147: 500003.42 | N147: 10.38 | O147: =I147*N147 -> 740862.12 | S147: =IFERROR(C147,0) -> 44435 | T147: =-L147 -> -500003.42
E149: =B147 -> Finch | F149: Total | L149: =SUM(L147:L148) -> 500003.42 | O149: =SUM(O147:O148) -> 740862.12 | Q149: =O149/L149 -> 1.4817141 | R149: =XIRR(T147:T149,S147:S149,0) -> 0.094648638 | S149: =$C$1 -> 46022 | T149: =O149 -> 740862.12
B151: Midi | C151: 44455 | F151: Series Seed-2 Preferred Stock | G151: N/A | I151: 703152 | K151: =L151/I151 -> 0.72550032 | L151: 510137 | N151: =4.899*1.995 -> 9.773505 | O151: =I151*N151 -> 6872259.6 | S151: =IFERROR(C151,0) -> 44455 | T151: =-L151 -> -510137
C152: 44672 | F152: Series Seed-3 Preferred Stock | G152: N/A | I152: 1241334 | K152: =L152/I152 -> 0.82280031 | L152: 1021370 | N152: =N151 -> 9.773505 | O152: =I152*N152 -> 12132184 | S152: =IFERROR(C152,0) -> 44672 | T152: =-L152 -> -1021370
C153: 44841 | F153: Series Seed-1 Preferred Stock | I153: 1367240 | K153: =L153/I153 -> 1.0971007 | L153: =1.5*10^6 -> 1500000 | N153: =N152 -> 9.773505 | O153: =I153*N153 -> 13362727 | S153: =IFERROR(C153,0) -> 44841 | T153: =-L153 -> -1500000
C154: 45107 | F154: Series A Preferred Stock | I154: 1618542 | K154: 1.5446 | L154: 2500000 | N154: =N153 -> 9.773505 | O154: =I154*N154 -> 15818828 | S154: =IFERROR(C154,0) -> 45107 | T154: =-L154 -> -2500000
F155: Series Seed Warrants | S155: =IFERROR(C155,0) -> 0 | T155: =-L155 -> 0
K156: =L156/I156 -> #DIV/0!
E157: =B151 -> Midi | F157: Total | I157: =SUM(I151:I155) -> 4930268 | L157: =SUM(L151:L156) -> 5531507 | O157: =SUM(O151:O156) -> 48185999 | Q157: =O157/L157 -> 8.7111883 | R157: =XIRR(T151:T157,S151:S157,0) -> 0.95959565 | S157: =$C$1 -> 46022 | T157: =O157 -> 48185999
B159: ianacare | C159: 44547 | F159: Series A Preferred Stock | I159: 55297 | K159: =L159/I159 -> 18.08389 | L159: 999984.87 | N159: =K159 -> 18.08389 | O159: =I159*N159 -> 999984.87 | S159: =IFERROR(C159,0) -> 44547 | T159: =-L159 -> -999984.87
C160: 44887 | F160: Convertible Note | L160: =2*10^6 -> 2000000 | O160: =2*10^6 -> 2000000 | S160: =IFERROR(C160,0) -> 44887 | T160: =-L160 -> -2000000
E162: =B159 -> ianacare | F162: Total | L162: =SUM(L159:L161) -> 2999984.9 | O162: =SUM(O159:O161) -> 2999984.9 | Q162: =O162/L162 -> 1 | R162: =XIRR(T159:T162,S159:S162,0) -> 4.8828125e-09 | S162: =$C$1 -> 46022 | T162: =O162 -> 2999984.9
B164: Vivante | C164: 44552 | F164: Series A Preferred Stock | I164: 390000 | K164: =L164/I164 -> 2.5641 | L164: 999999 | N164: =K165 -> 4.9397915 | O164: =I164*N164 -> 1926518.7 | S164: =IFERROR(C164,0) -> 44552 | T164: =-L164 -> -999999
C165: 45156 | F165: Series B Preferred Stock | I165: 243764 | K165: =L165/I165 -> 4.9397915 | L165: 1204143.3 | N165: =K165 -> 4.9397915 | O165: =I165*N165 -> 1204143.3 | S165: =IFERROR(C165,0) -> 45156 | T165: =-L165 -> -1204143.3
E167: =B164 -> Vivante | F167: Total | I167: =I164+I165 -> 633764 | L167: =SUM(L164:L166) -> 2204142.3 | O167: =SUM(O164:O166) -> 3130662 | Q167: =O167/L167 -> 1.4203538 | R167: =XIRR(T164:T167,S164:S167,0) -> 0.11739947 | S167: =$C$1 -> 46022 | T167: =O167 -> 3130662
B169: a.team | C169: 44567 | F169: Series A Preferred Stock | I169: 59467 | K169: =L169/I169 -> 16.81603 | L169: 999998.86 | N169: =K169 -> 16.81603 | O169: =I169*N169 -> 999998.86 | S169: =IFERROR(C169,0) -> 44567 | T169: =-L169 -> -999998.86
E171: =B169 -> a.team | F171: Total | L171: =SUM(L169:L170) -> 999998.86 | O171: =SUM(O169:O170) -> 999998.86 | Q171: =O171/L171 -> 1 | R171: =XIRR(T169:T171,S169:S171,0) -> 4.8828125e-09 | S171: =$C$1 -> 46022 | T171: =O171 -> 999998.86
B173: CoverGo | C173: 44621 | F173: SAFE | I173: =L173/K173 -> 2456.9333 | K173: 814.0229 | L173: =2*10^6 -> 2000000 | N173: 1077.4625 | O173: =I173*N173 -> 2647253.5 | S173: =IFERROR(C173,0) -> 44621 | T173: =-L173 -> -2000000
C174: 44887 | F174: SAFE | I174: =L174/K174 -> 2456.9333 | K174: 814.0229 | L174: =2*10^6 -> 2000000 | N174: 1077.4625 | O174: =I174*N174 -> 2647253.5 | S174: =IFERROR(C174,0) -> 44887 | T174: =-L174 -> -2000000
E176: =B173 -> CoverGo | F176: Total | I176: =I173+I174 -> 4913.8667 | L176: =SUM(L173:L175) -> 4000000 | O176: =SUM(O173:O175) -> 5294506.9 | Q176: =O176/L176 -> 1.3236267 | R176: =XIRR(T173:T176,S173:S176,0) -> 0.083919224 | S176: =$C$1 -> 46022 | T176: =O176 -> 5294506.9
B178: Ashby | C178: 44599 | F178: Series B Preferred Stock | I178: 367035 | K178: =+L178/I178 -> 8.1736074 | L178: =3*10^6 -> 3000000 | N178: =16.21 -> 16.21 | O178: =I178*N178 -> 5949637.4 | S178: =IFERROR(C178,0) -> 44599 | T178: =-L178 -> -3000000
C179: 44931 | F179: Series B Preferred Stock | I179: =L179/K179 -> 244690 | K179: =+K178 -> 8.1736074 | L179: =2*10^6 -> 2000000 | N179: =+N178 -> 16.21 | O179: =I179*N179 -> 3966424.9 | S179: =IFERROR(C179,0) -> 44931 | T179: =-L179 -> -2000000
C180: =+C1 -> 46022 | F180: Series B Warrants | I180: 27283 | N180: =+N179-K179 -> 8.0363926 | O180: =I180*N180 -> 219256.9 | S180: =IFERROR(C180,0) -> 46022 | T180: =-L180 -> 0
E182: =B178 -> Ashby | F182: Total | I182: =SUM(I178:I180) -> 639008 | L182: =SUM(L178:L181) -> 5000000 | O182: =SUM(O178:O181) -> 10135319 | Q182: =O182/L182 -> 2.0270638 | R182: =XIRR(T178:T182,S178:S182,0) -> 0.21993771 | S182: =$C$1 -> 46022 | T182: =O182 -> 10135319
B184: Delfina | C184: 44621 | F184: Series Seed Stock | I184: 1557026 | K184: =+L184/I184 -> 0.51380003 | L184: =0.8*10^6 -> 800000 | N184: =+K186 -> 0.854 | O184: =+I184*N184 -> 1329700.2 | S184: =IFERROR(C184,0) -> 44621 | T184: =-L184 -> -800000
C185: 45314 | F185: SAFE - Conversion Seed 1 | I185: 313401 | K185: =+L185/I185 -> 0.79770007 | L185: 250000 | N185: =+N184 -> 0.854 | O185: =+I185*N185 -> 267644.45 | S185: =IFERROR(C185,0) -> 45314 | T185: =-L185 -> -250000
C186: 45684 | F186: Series A Preferred Stock | I186: 585480 | K186: =+L186/I186 -> 0.854 | L186: 499999.92 | N186: =+N184 -> 0.854 | O186: =+I186*N186 -> 499999.92 | S186: =IFERROR(C186,0) -> 45684 | T186: =-L186 -> -499999.92
E188: =B184 -> Delfina | F188: Total | I188: =SUM(I184:I186) -> 2455907 | L188: =SUM(L184:L187) -> 1549999.9 | O188: =SUM(O184:O187) -> 2097344.6 | Q188: =O188/L188 -> 1.3531256 | R188: =XIRR(T184:T188,S184:S188,0) -> 0.11896514 | S188: =$C$1 -> 46022 | T188: =O188 -> 2097344.6
B190: Mosey | C190: 44707 | F190: Series A Preferred Stock | I190: 827465 | K190: =+L190/I190 -> 4.83404 | L190: 3999998.9 | N190: =K190 -> 4.83404 | O190: =+I190*N190 -> 3999998.9 | S190: =IFERROR(C190,0) -> 44707 | T190: =-L190 -> -3999998.9
E192: =B190 -> Mosey | F192: Total | L192: =SUM(L190:L191) -> 3999998.9 | O192: =SUM(O190:O191) -> 3999998.9 | Q192: =O192/L192 -> 1 | R192: =XIRR(T190:T192,S190:S192,0) -> 4.8828125e-09 | S192: =$C$1 -> 46022 | T192: =O192 -> 3999998.9
B194: Violet | C194: 44722 | F194: Series Seed | I194: 2308091 | K194: =+L194/I194 -> 1.12647 | L194: 2599995.3 | N194: =K194 -> 1.12647 | O194: =+I194*N194 -> 2599995.3 | S194: =IFERROR(C194,0) -> 44722 | T194: =-L194 -> -2599995.3
E196: =B194 -> Violet | F196: Total | L196: =SUM(L194:L195) -> 2599995.3 | O196: =SUM(O194:O195) -> 2599995.3 | Q196: =O196/L196 -> 1 | R196: =XIRR(T194:T196,S194:S196,0) -> 4.8828125e-09 | S196: =$C$1 -> 46022 | T196: =O196 -> 2599995.3
B198: Gable | C198: 44848 | F198: Series A Preferred Stock | I198: 2323150 | K198: =L198/I198 -> 1.7218001 | L198: =4*10^6 -> 4000000 | N198: =K198 -> 1.7218001 | O198: =+I198*N198 -> 4000000 | S198: =IFERROR(C198,0) -> 44848 | T198: =-L198 -> -4000000
E200: =B198 -> Gable | F200: Total | L200: =SUM(L198:L199) -> 4000000 | O200: =SUM(O198:O199) -> 4000000 | Q200: =O200/L200 -> 1 | R200: =XIRR(T198:T200,S198:S200,0) -> -4.8828125e-09 | S200: =$C$1 -> 46022 | T200: =O200 -> 4000000
B202: Patch Caregiving | C202: 44879 | F202: Common Shares | I202: 85967 | K202: =L202/I202 -> 4.7837641 | L202: 411245.85 | N202: 6.8214 | O202: =I202*N202 -> 586415.29 | S202: =IFERROR(C202,0) -> 44879 | T202: =-L202 -> -411245.85 | U202: 675000
B204: (Wellthy Merger) | E204: =B202 -> Patch Caregiving | F204: Total | L204: =SUM(L202:L203) -> 411245.85 | O204: =SUM(O202:O203) -> 586415.29 | Q204: =O204/L204 -> 1.4259482 | R204: =XIRR(T202:T204,S202:S204,0) -> 0.11998122 | S204: =$C$1 -> 46022 | T204: =O204 -> 586415.29
B206: Formally | C206: 45006 | F206: SAFE | L206: =1*10^6 -> 1000000 | O206: =L206 -> 1000000 | S206: =IFERROR(C206,0) -> 45006 | T206: =-L206 -> -1000000
E208: =B206 -> Formally | F208: Total | L208: =SUM(L206:L207) -> 1000000 | O208: =SUM(O206:O207) -> 1000000 | Q208: =O208/L208 -> 1 | R208: =XIRR(T206:T208,S206:S208,0) -> 4.8828125e-09 | S208: =$C$1 -> 46022 | T208: =O208 -> 1000000
B210: Liftoff | C210: 45064 | F210: Series Seed 1 | I210: 713877 | K210: =+L210/I210 -> 0.70040077 | L210: 500000 | N210: =+K211 -> 2.1149 | O210: =+I210*N210 -> 1509778.5 | S210: =IFERROR(C210,0) -> 45064 | T210: =-L210 -> -500000
C211: 45517 | F211: Series Seed | I211: 182782 | K211: =L211/I211 -> 2.1149 | L211: 386565.66 | N211: =N210 -> 2.1149 | O211: =+I211*N211 -> 386565.66 | S211: =IFERROR(C211,0) -> 45517 | T211: =-L211 -> -386565.66
...

Sheet Portfolio Construction
D1: =20600000 -> 20600000 | F1: 73000000
D2: Fund I | F2: Fund II | G2: % change
B3: Seed | C3: # of Deals | D3: 14 | F3: ='Investment Characteristics'!C72 -> 12 | G3: =F3/D3-1 -> -0.14285714
C4: % of Portfolio | D4: =D3/$D$30 -> 0.5 | F4: =F3/$F$30 -> 0.4137931 | G4: =F4/D4-1 -> -0.17241379
C5: Avg. Initital Inv. | D5: 258412.48 | F5: ='Investment Characteristics'!C69 -> 688344.2 | G5: =F5/D5-1 -> 1.6637421
C6: Inv. % of Fund Size | D6: =D5/$D$1 -> 0.012544295 | F6: =F5/$F$1 -> 0.0094293726 | G6: =F6/D6-1 -> -0.24831388
C7: Median FD% | D7: 0.0104 | F7: ='Investment Characteristics'!C81 -> 0.045 | G7: =F7/D7-1 -> 3.3269231
C8: Avg. FD% | D8: 0.014 | F8: ='Investment Characteristics'!C80 -> 0.043795119 | G8: =F8/D8-1 -> 2.1282228
C9: Median Valuation | D9: 16000000 | F9: ='Investment Characteristics'!C78 -> 15000000 | G9: =F9/D9-1 -> -0.0625
C10: Avg. Valuation | D10: 16642857 | F10: ='Investment Characteristics'!C77 -> 16583333 | G10: =F10/D10-1 -> -0.0035765379
B12: A | C12: # of Deals | D12: 7 | F12: ='Investment Characteristics'!D72 -> 12 | G12: =F12/D12-1 -> 0.71428571
C13: % of Portfolio | D13: =D12/$D$30 -> 0.25 | F13: =F12/$F$30 -> 0.4137931 | G13: =F13/D13-1 -> 0.65517241
C14: Avg. Initital Inv. | D14: 492857.33 | F14: ='Investment Characteristics'!D69 -> 1579164.8 | G14: =F14/D14-1 -> 2.2041012
C15: Inv. % of Fund Size | D15: =D14/D1 -> 0.023925113 | F15: =F14/F1 -> 0.021632394 | G15: =F15/D15-1 -> -0.095828969
C16: Median FD% | D16: 0.0079999296 | F16: ='Investment Characteristics'!D81 -> 0.017592499 | G16: =F16/D16-1 -> 1.1990817
C17: Avg. FD% | D17: 0.0084 | F17: ='Investment Characteristics'!D80 -> 0.02963664 | G17: =F17/D17-1 -> 2.5281714
C18: Median Valuation | D18: 39000000 | F18: ='Investment Characteristics'!D78 -> 73750000 | G18: =F18/D18-1 -> 0.89102564
C19: Avg. Valuation | D19: 62571429 | F19: ='Investment Characteristics'!D77 -> 94866667 | G19: =F19/D19-1 -> 0.51613394
B21: B+ | C21: # of Deals | D21: 7 | F21: ='Investment Characteristics'!E72 -> 5 | G21: =F21/D21-1 -> -0.28571429
C22: % of Portfolio | D22: =D21/$D$30 -> 0.25 | F22: =F21/$F$30 -> 0.17241379 | G22: =F22/D22-1 -> -0.31034483
C23: Avg. Initital Inv. | D23: 611474.83 | F23: ='Investment Characteristics'!E69 -> 2019995.3 | G23: =F23/D23-1 -> 2.3034808
C24: Inv. % of Fund Size | D24: =D23/D1 -> 0.029683244 | F24: =F23/F1 -> 0.027671169 | G24: =F24/D24-1 -> -0.067784875
C25: Median FD% | D25: 0.004370656 | F25: ='Investment Characteristics'!E81 -> 0.0050633027 | G25: =F25/D25-1 -> 0.15847659
C26: Avg. FD% | D26: 0.005 | F26: ='Investment Characteristics'!E80 -> 0.0067194849 | G26: =F26/D26-1 -> 0.34389697
C27: Median Valuation | D27: 137000000 | F27: ='Investment Characteristics'!E78 -> 230000000 | G27: =F27/D27-1 -> 0.67883212
C28: Avg. Valuation | D28: 1.4014286e+08 | F28: ='Investment Characteristics'!E77 -> 383000000 | G28: =F28/D28-1 -> 1.7329256
B30: Total | C30: # of Deals | D30: 28 | F30: ='Investment Characteristics'!F72 -> 29 | G30: =F30/D30-1 -> 0.035714286
C31: Avg. Initital Inv. | D31: 405289.28 | F31: ='Investment Characteristics'!F69 -> 1286554.6 | G31: =F31/D31-1 -> 2.1744107
C32: Inv. % of Fund Size | D32: =D31/D1 -> 0.019674237 | F32: =F31/F1 -> 0.017624036 | G32: =F32/D32-1 -> -0.10420739
C33: Median FD% | D33: 0.0071 | F33: ='Investment Characteristics'!H35 -> 0.02 | G33: =F33/D33-1 -> 1.8169014
C34: Avg. FD% | D34: 0.0091946146 | F34: ='Investment Characteristics'!H34 -> 0.031544087 | G34: =F34/D34-1 -> 2.4307134
C35: Median Valuation | D35: 25500000 | F35: ='Investment Characteristics'!I35 -> 50000000 | G35: =F35/D35-1 -> 0.96078431
C36: Avg. Valuation | D36: 59000000 | F36: ='Investment Characteristics'!I34 -> 1.1215172e+08 | G36: =F36/D36-1 -> 0.90087668

Sheet Investment Characteristics
N1: Updated as of 9.30 | V1: =74*10^6 -> 74000000
B2: Initial Investment Characteristics | K2: Current Investment Characteristics | AM2: VOTING - "overall" by IC member | AU2: Avg Vote - by category | AY2: *Missing Vote | AZ2: Double-check | BD2: Scorecards - by category
B3: Company | C3: Date | D3: Series | E3: Sector | F3: $ Invested | G3: VC Syndicate | H3: FD% | I3: Avg. Cost | K3: Company | L3: Series | M3: $ Invested | N3: FD% | O3: Initital Cost | P3: Avg. Cost | Q3: Last Valuation | R3: Holding Value | S3: $ Invested | T3: Market Value | U3: Multiple | V3: RTF | X3: 44285 | Y3: 44469 | Z3: 44742 | AA3: 44926 | AB3: 45107 | AC3: 45291 | AD3: 45473 | AE3: 45565 | AF3: 45657 | AG3: 45838 | AH3: 45930 | AI3: Rationale | AJ3: Runway | AM3: ABG | AN3: CBOU | AO3: Colin | AP3: Greg | AQ3: Robby | AS3: Overall | AT3: Team | AU3: Tech | AV3: TAM | AW3: Timing | AX3: Terms | BB3: Lead | BC3: Qual. Total | BD3: Quant. Total | BE3: Deal Terms | BF3: Total | BG3: Notes
B4: Brightline | C4: =INDEX('Statement of Investments'!$C$5:$C$220,MATCH('Investment Characteristics'!$B4,'Statement of Investments'!$B$5:$B$220,0)) -> 44047 | D4: A | E4: Healthtech | F4: =INDEX('Statement of Investments'!$L$5:$L$220,MATCH('Investment Characteristics'!$B4,'Statement of Investments'!$B$5:$B$220,0)) -> 499998.47 | G4: GV, Oak HC/FT, Threshold | H4: 0.006249969 | I4: 80000000 | K4: =B4 -> Brightline | L4: C | M4: =INDEX('Statement of Investments'!$L$5:$L$220,MATCH('Investment Characteristics'!$K4,'Statement of Investments'!$E$5:$E$220,0)) -> 1499987 | N4: 0.0060300575 | O4: =I4 -> 80000000 | P4: =IFERROR(ROUND(S4/N4,-5),0) -> 248800000 | Q4: 757442906 | R4: =+Q4 -> 757442906 | S4: =INDEX('Statement of Investments'!$L$5:$L$220,MATCH(B4,'Statement of Investments'!$E$5:$E$220,0)) -> 1499987 | T4: =INDEX('Statement of Investments'!$O$5:$O$220,MATCH(B4,'Statement of Investments'!$E$5:$E$220,0)) -> 4521963.7 | U4: =T4/S4 -> 3.0146685 | V4: =+$V$1/N4/10^6 -> 12271.857 | X4: 0 | Y4: 0 | Z4: -1 | AA4: 0 | AB4: 0 | AC4: 1 | AD4: 1 | AE4: 1 | AF4: 1 | AG4: 1 | AH4: 0 | AI4: Revenue is down slightly yoy, profitable this year. Focusing on delivering care in person, opened 3rd clinic in NY, leadership change, revenue growth -ve, have they de-risked the hybrid model yet? Can it grow and scale? Valuation multiple seems high given the fact pattern | AM4: 2 | AN4: 1 | AO4: 2 | AP4: 1 | AQ4: 2 | AS4: 1.6 | AT4: 1.8 | AU4: 0.6 | AV4: 2 | AW4: 2 | AX4: 0.2 | BB4: ABG | BC4: 49.8 | BD4: 6.5 | BE4: 7 | BF4: 63.3
B5: Murmur | C5: =INDEX('Statement of Investments'!$C$5:$C$220,MATCH('Investment Characteristics'!$B5,'Statement of Investments'!$B$5:$B$220,0)) -> 44098 | D5: Seed | E5: Workforce | F5: =INDEX('Statement of Investments'!$L$5:$L$220,MATCH('Investment Characteristics'!$B5,'Statement of Investments'!$B$5:$B$220,0)) -> 225000 | G5: Lerer Hippeau, Human Ventures | H5: 0.026471511 | I5: =IFERROR(ROUND(F5/H5,-5),0) -> 8500000 | K5: Murmur | L5: Seed | M5: =INDEX('Statement of Investments'!$L$5:$L$220,MATCH('Investment Characteristics'!$K5,'Statement of Investments'!$E$5:$E$220,0)) -> 1574998 | N5: 0.064069691 | O5: =I5 -> 8500000 | P5: =IFERROR(ROUND(S5/N5,-5),0) -> 24600000 | Q5: =28*10^6 -> 28000000 | R5: 0 | S5: =INDEX('Statement of Investments'!$L$5:$L$220,MATCH(B5,'Statement of Investments'!$E$5:$E$220,0)) -> 1574998 | T5: =INDEX('Statement of Investments'!$O$5:$O$220,MATCH(B5,'Statement of Investments'!$E$5:$E$220,0)) -> 0 | U5: =T5/S5 -> 0 | V5: =+$V$1/N5/10^6 -> 1154.9923 | X5: 0 | Y5: 0 | Z5: 1 | AA5: 0 | AB5: 0 | AC5: 1 | AD5: 0 | AE5: 0 | AF5: -1 | AG5: -1 | AH5: -1 | AI5: N/A - shutdown | AM5: 1 | AN5: 1 | AO5: 1 | AP5: 1 | AQ5: 1 | AS5: 1 | AT5: 1.3 | AU5: 0.7 | AV5: 1.7 | AW5: 2 | AX5: 2 | BB5: ABG | BC5: 44 | BD5: 8 | BE5: 9 | BF5: 61
B6: Pinwheel | C6: =INDEX('Statement of Investments'!$C$5:$C$220,MATCH('Investment Characteristics'!$B6,'Statement of Investments'!$B$5:$B$220,0)) -> 44105 | D6: A | E6: Financial | F6: =INDEX('Statement of Investments'!$L$5:$L$220,MATCH('Investment Characteristics'!$B6,'Statement of Investments'!$B$5:$B$220,0)) -> 499997.04 | G6: Coatue, First Round, Upfront | H6: 0.005 | I6: =IFERROR(ROUND(F6/H6,-5),0) -> 100000000 | K6: Pinwheel | L6: B | M6: =INDEX('Statement of Investments'!$L$5:$L$220,MATCH('Investment Characteristics'!$K6,'Statement of Investments'!$E$5:$E$220,0)) -> 1453156.1 | N6: 0.0057927248 | O6: =I6 -> 100000000 | P6: =IFERROR(ROUND(S6/N6,-5),0) -> 250900000 | Q6: 5.0637434e+08 | R6: Pref Stack - $78M | S6: =INDEX('Statement of Investments'!$L$5:$L$220,MATCH(B6,'Statement of Investments'!$E$5:$E$220,0)) -> 1453156.1 | T6: =INDEX('Statement of Investments'!$O$5:$O$220,MATCH(B6,'Statement of Investments'!$E$5:$E$220,0)) -> 1453156.1 | U6: =T6/S6 -> 1 | V6: =+$V$1/N6/10^6 -> 12774.644 | X6: 0 | Y6: 1 | Z6: 1 | AA6: 1 | AB6: 0 | AC6: 0 | AD6: 0 | AE6: 0 | AF6: 0 | AG6: 0 | AH6: 0 | AI6: 30 months of runway, undergoing CEO change, written-down to cost in Q3 | AJ6: 30 months | AM6: 2 | AN6: 1 | AO6: 1 | AP6: 1 | AQ6: 1 | AS6: 1.2 | AT6: 1 | AU6: 0.6 | AV6: 2 | AW6: 1.8 | AX6: 0.2 | BB6: RP/ABG | BC6: 46.5 | BD6: 10.5 | BE6: 7 | BF6: 64
B7: Cleo | C7: =INDEX('Statement of Investments'!$C$5:$C$220,MATCH('Investment Characteristics'!$B7,'Statement of Investments'!$B$5:$B$220,0)) -> 44155 | D7: B | E7: Healthtech | F7: =INDEX('Statement of Investments'!$L$5:$L$220,MATCH('Investment Characteristics'!$B7,'Statement of Investments'!$B$5:$B$220,0)) -> 599997.84 | G7: Felicis, Forerunner, Greylock | H7: =F7/115000000 -> 0.0052173725 | I7: =IFERROR(ROUND(F7/H7,-5),0) -> 115000000 | K7: Cleo | L7: C | M7: =INDEX('Statement of Investments'!$L$5:$L$220,MATCH('Investment Characteristics'!$K7,'Statement of Investments'!$E$5:$E$220,0)) -> 599997.84 | N7: 0.0040460588 | O7: =I7 -> 115000000 | P7: =IFERROR(ROUND(S7/N7,-5),0) -> 148300000 | Q7: 231000000 | R7: 0 | S7: =INDEX('Statement of Investments'!$L$5:$L$220,MATCH(B7,'Statement of Investments'!$E$5:$E$220,0)) -> 599997.84 | T7: =INDEX('Statement of Investments'!$O$5:$O$220,MATCH(B7,'Statement of Investments'!$E$5:$E$220,0)) -> 0 | U7: =T7/S7 -> 0 | V7: =+$V$1/N7/10^6 -> 18289.403 | X7: 1 | Y7: 1 | Z7: 1 | AA7: 0 | AB7: -1 | AC7: 0 | AD7: -1 | AE7: -1 | AF7: -1 | AG7: -1 | AH7: -1 | AI7: N/A - proactive write-off | AM7: 1 | AN7: 2 | AO7: 1 | AP7: 1 | AQ7: 2 | AS7: 1.4 | AT7: 1.4 | AU7: 1 | AV7: 1.2 | AW7: 2 | AX7: 1.8 | BB7: RP | BC7: 35.3 | BD7: 12 | BE7: 7 | BF7: 54.3
B8: Rightfoot | C8: =INDEX('Statement of Investments'!$C$5:$C$220,MATCH('Investment Characteristics'!$B8,'Statement of Investments'!$B$5:$B$220,0)) -> 44175 | D8: Seed | E8: Financial | F8: =INDEX('Statement of Investments'!$L$5:$L$220,MATCH('Investment Characteristics'!$B8,'Statement of Investments'!$B$5:$B$220,0)) -> 399999.32 | G8: Bain Capital, LSVP | H8: 0.02 | I8: =IFERROR(ROUND(F8/H8,-5),0) -> 20000000 | K8: Rightfoot | L8: A | M8: =INDEX('Statement of Investments'!$L$5:$L$220,MATCH('Investment Characteristics'!$K8,'Statement of Investments'!$E$5:$E$220,0)) -> 399999.32 | N8: 0.012564741 | O8: =I8 -> 20000000 | P8: =IFERROR(ROUND(S8/N8,-5),0) -> 31800000 | Q8: =55*10^6 -> 55000000 | R8: 0 | S8: =INDEX('Statement of Investments'!$L$5:$L$220,MATCH(B8,'Statement of Investments'!$E$5:$E$220,0)) -> 399999.32 | T8: =INDEX('Statement of Investments'!$O$5:$O$220,MATCH(B8,'Statement of Investments'!$E$5:$E$220,0)) -> 0 | U8: =T8/S8 -> 0 | V8: =+$V$1/N8/10^6 -> 5889.4968 | X8: 0 | Y8: 0 | Z8: 1 | AA8: 0 | AB8: 0 | AC8: -1 | AD8: -1 | AE8: -1 | AF8: -1 | AG8: 0 | AH8: 0 | AI8: Showing signs of significant growth after undergoing pivot, monitoring to write back up to cost | AM8: 1 | AN8: 2 | AO8: 1 | AP8: 1 | AQ8: 1 | AS8: 1.2 | AT8: 1.2 | AU8: 1.4 | AV8: 1 | AW8: 1.6 | AX8: 1.8 | BB8: CH | BC8: 41 | BD8: 9.8 | BE8: 4 | BF8: 54.8
B9: Mathison | C9: =INDEX('Statement of Investments'!$C$5:$C$220,MATCH('Investment Characteristics'!$B9,'Statement of Investments'!$B$5:$B$220,0)) -> 44176 | D9: Seed | E9: Workforce | F9: =INDEX('Statement of Investments'!$L$5:$L$220,MATCH('Investment Characteristics'!$B9,'Statement of Investments'!$B$5:$B$220,0)) -> 299999.56 | G9: Bain Capital | H9: 0.020000165 | I9: =IFERROR(ROUND(F9/H9,-5),0) -> 15000000 | K9: Mathison | L9: Acq. | M9: =INDEX('Statement of Investments'!$L$5:$L$220,MATCH('Investment Characteristics'!$K9,'Statement of Investments'!$E$5:$E$220,0)) -> 2049994.2 | N9: 0.04 | O9: =I9 -> 15000000 | P9: =IFERROR(ROUND(S9/N9,-5),0) -> 51200000 | Q9: 70000000 | R9: =+Q9 -> 70000000 | S9: =INDEX('Statement of Investments'!$L$5:$L$220,MATCH(B9,'Statement of Investments'!$E$5:$E$220,0)) -> 2049994.2 | T9: =INDEX('Statement of Investments'!$O$5:$O$220,MATCH(B9,'Statement of Investments'!$E$5:$E$220,0)) -> 272298.82 | U9: =T9/S9 -> 0.13282907 | V9: =+$V$1/N9/10^6 -> 1850 | X9: 1 | Y9: 1 | Z9: 1 | AA9: -1 | AB9: -1 | AC9: -1 | AM9: 2 | AN9: 2 | AO9: 2 | AP9: 1 | AQ9: 1 | AS9: 1.6 | AT9: 0.8 | AU9: 1 | AV9: 1.2 | AW9: 2 | AX9: 1.8 | BB9: ABG | BC9: 46 | BD9: 15 | BE9: 4 | BF9: 65
B10: Galileo | C10: =INDEX('Statement of Investments'!$C$5:$C$220,MATCH('Investment Characteristics'!$B10,'Statement of Investments'!$B$5:$B$220,0)) -> 44232 | D10: C | E10: Healthtech | F10: =INDEX('Statement of Investments'!$L$5:$L$220,MATCH('Investment Characteristics'!$B10,'Statement of Investments'!$B$5:$B$220,0)) -> 1999999.2 | G10: Foresite Capital, Oak HC/FT, 8VC | H10: 0.0050633027 | I10: =IFERROR(ROUND(F10/H10,-5),0) -> 395000000 | K10: Galileo | L10: E | M10: =INDEX('Statement of Investments'!$L$5:$L$220,MATCH('Investment Characteristics'!$K10,'Statement of Investments'!$E$5:$E$220,0)) -> 2163901.7 | N10: 0.0041856851 | O10: =I10 -> 395000000 | P10: =IFERROR(ROUND(S10/N10,-5),0) -> 517000000 | Q10: 361500000 | R10: =+Q10 -> 361500000 | S10: =INDEX('Statement of Investments'!$L$5:$L$220,MATCH(B10,'Statement of Investments'!$E$5:$E$220,0)) -> 2163901.7 | T10: =INDEX('Statement of Investments'!$O$5:$O$220,MATCH(B10,'Statement of Investments'!$E$5:$E$220,0)) -> 1724878.8 | U10: =T10/S10 -> 0.79711515 | V10: =+$V$1/N10/10^6 -> 17679.304 | X10: 1 | Y10: 0 | Z10: 0 | AA10: 2 | AB10: 0 | AC10: -1 | AD10: -1 | AE10: -1 | AF10: -1 | AG10: -1 | AH10: 0 | AI10: Completed recap in Q3, completing transition away from shared savings to FFS / Capitated | AM10: 1 | AN10: 1 | AO10: 1 | AP10: 2 | AQ10: 2 | AS10: 1.4 | AT10: 2 | AU10: 1.2 | AV10: 2 | AW10: 1.8 | AX10: -0.4 | BB10: GG | BC10: 45.5 | BD10: 10.5 | BE10: 7 | BF10: 63
B11: Cocoon | C11: =INDEX('Statement of Investments'!$C$5:$C$220,MATCH('Investment Characteristics'!$B11,'Statement of Investments'!$B$5:$B$220,0)) -> 44232 | D11: Seed | E11: Workforce | F11: =INDEX('Statement of Investments'!$L$5:$L$220,MATCH('Investment Characteristics'!$B11,'Statement of Investments'!$B$5:$B$220,0)) -> 224999.42 | G11: Index Ventures, XYZ Capital | H11: 0.0073744678 | I11: =IFERROR(ROUND(F11/H11,-5),0) -> 30500000 | K11: Cocoon | L11: A | M11: =INDEX('Statement of Investments'!$L$5:$L$220,MATCH('Investment Characteristics'!$K11,'Statement of Investments'!$E$5:$E$220,0)) -> 4224996.6 | N11: 0.027242491 | O11: =I11 -> 30500000 | P11: =IFERROR(ROUND(S11/N11,-5),0) -> 155100000 | Q11: 1.6250158e+08 | R11: Pref Stack - $26M | S11: =INDEX('Statement of Investments'!$L$5:$L$220,MATCH(B11,'Statement of Investments'!$E$5:$E$220,0)) -> 4224996.6 | T11: =INDEX('Statement of Investments'!$O$5:$O$220,MATCH(B11,'Statement of Investments'!$E$5:$E$220,0)) -> 4224996.6 | U11: =T11/S11 -> 1 | V11: =+$V$1/N11/10^6 -> 2716.3448 | X11: 1 | Y11: 1 | Z11: 1 | AA11: 1 | AB11: 1 | AC11: 1 | AD11: 0 | AE11: 0 | AF11: 0 | AG11: 0 | AH11: 0 | AI11: Contracted ARR at ~$10M, strong product expansion and channel traction with Gurdian/Sedgewick moving into enterprises, moved into variable hourly workers market (increased TAM?). Increased distribution scale + partner validation should move this into green? Rev multiple seems high | AJ11: 8 months | AM11: 1 | AN11: 1 | AO11: 1 | AQ11: 1 | AS11: 1 | AT11: 1.5 | AU11: 0.8 | AV11: 1.5 | AW11: 1.5 | AX11: 1 | BB11: RP | BC11: 48.5 | BD11: 11.3 | BF11: 59.8
A12: x | B12: Rula | C12: =INDEX('Statement of Investments'!$C$5:$C$220,MATCH('Investment Characteristics'!$B12,'Statement of Investments'!$B$5:$B$220,0)) -> 44265 | D12: A | E12: Healthtech | F12: =INDEX('Statement of Investments'!$L$5:$L$220,MATCH('Investment Characteristics'!$B12,'Statement of Investments'!$B$5:$B$220,0)) -> 1500000 | G12: Wing Ventures, Upfront Ventures | H12: 0.023774266 | I12: =IFERROR(ROUND(F12/H12,-5),0) -> 63100000 | K12: Rula | L12: C | M12: =INDEX('Statement of Investments'!$L$5:$L$220,MATCH('Investment Characteristics'!$K12,'Statement of Investments'!$E$5:$E$220,0)) -> 4500000 | N12: 0.0207 | O12: =I12 -> 63100000 | P12: =IFERROR(ROUND(S12/N12,-5),0) -> 217400000 | Q12: 1250000000 | R12: =+Q12 -> 1250000000 | S12: =INDEX('Statement of Investments'!$L$5:$L$220,MATCH(B12,'Statement of Investments'!$E$5:$E$220,0)) -> 4500000 | T12: =INDEX('Statement of Investments'!$O$5:$O$220,MATCH(B12,'Statement of Investments'!$E$5:$E$220,0)) -> 25285301 | U12: =T12/S12 -> 5.6189558 | V12: =+$V$1/N12/10^6 -> 3574.8792 | X12: 1 | Y12: 1 | Z12: 1 | AA12: 1 | AB12: 1 | AC12: 1 | AD12: 1 | AE12: 1 | AF12: 1 | AG12: 1 | AH12: 1 | AI12: Forecasting 2x y/y growth with revenue run rate above $200M by year end | AM12: 1 | AN12: 1 | AP12: 1 | AQ12: 2 | AS12: 1.3 | AT12: 1.3 | AU12: 0 | AV12: 1.5 | AW12: 2 | AX12: 1 | BB12: RP | BC12: 45.5 | BD12: 10 | BE12: 7 | BF12: 62.5
B13: Origin | C13: =INDEX('Statement of Investments'!$C$5:$C$220,MATCH('Investment Characteristics'!$B13,'Statement of Investments'!$B$5:$B$220,0)) -> 44307 | D13: A | E13: Financial | F13: =INDEX('Statement of Investments'!$L$5:$L$220,MATCH('Investment Characteristics'!$B13,'Statement of Investments'!$B$5:$B$220,0)) -> 1699997.1 | G13: Felicis, 01 Advisors, General Catalyst | H13: 0.013599977 | I13: =IFERROR(ROUND(F13/H13,-5),0) -> 125000000 | K13: Origin | L13: B | M13: =INDEX('Statement of Investments'!$L$5:$L$220,MATCH('Investment Characteristics'!$K13,'Statement of Investments'!$E$5:$E$220,0)) -> 3699992.1 | N13: 0.027099272 | O13: =I13 -> 125000000 | P13: =IFERROR(ROUND(S13/N13,-5),0) -> 136500000 | Q13: 401250000 | R13: =P13 -> 136500000 | S13: =INDEX('Statement of Investments'!$L$5:$L$220,MATCH(B13,'Statement of Investments'!$E$5:$E$220,0)) -> 3699992.1 | T13: =INDEX('Statement of Investments'!$O$5:$O$220,MATCH(B13,'Statement of Investments'!$E$5:$E$220,0)) -> 3699992.1 | U13: =T13/S13 -> 1 | V13: =+$V$1/N13/10^6 -> 2730.7007 | X13: 1 | Y13: 1 | Z13: 1 | AA13: 0 | AB13: 0 | AC13: 0 | AD13: 0 | AE13: 0 | AF13: 0 | AG13: 0 | AH13: 0 | AI13: Wrote down to preference stack, undergoing pivot away from B2B model | AJ13: 19 months | AM13: 1 | AN13: 2 | AQ13: 2 | AS13: 1.7 | AT13: 2 | AU13: 1 | AV13: 1.7 | AW13: 1.3 | AX13: 1 | BB13: CH/RP | BC13: 50.5 | BD13: 8 | BE13: 6.5 | BF13: 65
B14: Nayya | C14: =INDEX('Statement of Investments'!$C$5:$C$220,MATCH('Investment Characteristics'!$B14,'Statement of Investments'!$B$5:$B$220,0)) -> 44344 | D14: B | E14: Healthtech | F14: =INDEX('Statement of Investments'!$L$5:$L$220,MATCH('Investment Characteristics'!$B14,'Statement of Investments'!$B$5:$B$220,0)) -> 500000 | G14: Felicis, Iconiq, SVB Capital | H14: 0.002173913 | I14: =IFERROR(ROUND(F14/H14,-5),0) -> 230000000 | K14: Nayya | L14: C | M14: =INDEX('Statement of Investments'!$L$5:$L$220,MATCH('Investment Characteristics'!$K14,'Statement of Investments'!$E$5:$E$220,0)) -> 2699987.1 | N14: 0.0076636442 | O14: =I14 -> 230000000 | P14: =IFERROR(ROUND(S14/N14,-5),0) -> 352300000 | Q14: 5.049535e+08 | R14: =+Q14 -> 5.049535e+08 | S14: =INDEX('Statement of Investments'!$L$5:$L$220,MATCH(B14,'Statement of Investments'!$E$5:$E$220,0)) -> 2699987.1 | T14: =INDEX('Statement of Investments'!$O$5:$O$220,MATCH(B14,'Statement of Investments'!$E$5:$E$220,0)) -> 3853385.4 | U14: =T14/S14 -> 1.4271866 | V14: =+$V$1/N14/10^6 -> 9655.9806 | X14: 1 | Y14: 1 | Z14: 0 | AA14: 0 | AB14: 0 | AC14: 1 | AD14: 1 | AE14: 1 | AF14: 1 | AG14: 1 | AH14: 0 | AI14: Reduced ARR forecast by 20%, reduced growth <2x, strong partnerships are encouraging but needs to convert to ARR contribution and signed deployments. Would suggest yellow. | AJ14: 17 months | AM14: 1 | AN14: 1 | AP14: 1 | AQ14: 1 | AS14: 1 | AT14: 1 | AU14: 1.5 | AV14: 1.8 | AW14: 1.5 | AX14: 0.3 | BB14: RP | BC14: 47.5 | BF14: 47.5
B15: Praisidio | C15: =INDEX('Statement of Investments'!$C$5:$C$220,MATCH('Investment Characteristics'!$B15,'Statement of Investments'!$B$5:$B$220,0)) -> 44370 | D15: Seed | E15: Workforce | F15: =INDEX('Statement of Investments'!$L$5:$L$220,MATCH('Investment Characteristics'!$B15,'Statement of Investments'!$B$5:$B$220,0)) -> 200000 | G15: Signal Fire, Storm Ventures | H15: 0.01 | I15: =IFERROR(ROUND(F15/H15,-5),0) -> 20000000 | K15: Praisidio | L15: Seed | M15: =INDEX('Statement of Investments'!$L$5:$L$220,MATCH('Investment Characteristics'!$K15,'Statement of Investments'!$E$5:$E$220,0)) -> 200000 | N15: 0.01 | O15: =I15 -> 20000000 | P15: =IFERROR(ROUND(S15/N15,-5),0) -> 20000000 | Q15: 20000000 | R15: 0 | S15: =INDEX('Statement of Investments'!$L$5:$L$220,MATCH(B15,'Statement of Investments'!$E$5:$E$220,0)) -> 200000 | T15: =INDEX('Statement of Investments'!$O$5:$O$220,MATCH(B15,'Statement of Investments'!$E$5:$E$220,0)) -> 0 | U15: =T15/S15 -> 0 | V15: =+$V$1/N15/10^6 -> 7400 | X15: 1 | Y15: 1 | Z15: 0 | AA15: 0 | AB15: 0 | AC15: 0 | AD15: 0 | AE15: 0 | AF15: -1 | AG15: -1 | AH15: -1 | AI15: N/A - proactive write-off | AM15: 2 | AN15: 2 | AP15: 1 | AQ15: 1 | AS15: 1.5 | AT15: 1.5 | AU15: 1 | AV15: 1 | AW15: 2 | AX15: 1.8 | BB15: ABG | BC15: 46.5 | BD15: 13 | BE15: 9 | BF15: 68.5
B16: Bravely | C16: =INDEX('Statement of Investments'!$C$5:$C$220,MATCH('Investment Characteristics'!$B16,'Statement of Investments'!$B$5:$B$220,0)) -> 44379 | D16: A | E16: Workforce | F16: =INDEX('Statement of Investments'!$L$5:$L$220,MATCH('Investment Characteristics'!$B16,'Statement of Investments'!$B$5:$B$220,0)) -> 1249999.6 | G16: Telescope Partners, Primary Venture Partners | H16: 0.018518542 | I16: =IFERROR(ROUND(F16/H16,-5),0) -> 67500000 | K16: Bravely | L16: A | M16: =INDEX('Statement of Investments'!$L$5:$L$220,MATCH('Investment Characteristics'!$K16,'Statement of Investments'!$E$5:$E$220,0)) -> 1249999.6 | N16: 0.018518542 | O16: =I16 -> 67500000 | P16: =IFERROR(ROUND(S16/N16,-5),0) -> 67500000 | Q16: 67500000 | R16: =+Q16 -> 67500000 | S16: =INDEX('Statement of Investments'!$L$5:$L$220,MATCH(B16,'Statement of Investments'!$E$5:$E$220,0)) -> 1249999.6 | T16: =INDEX('Statement of Investments'!$O$5:$O$220,MATCH(B16,'Statement of Investments'!$E$5:$E$220,0)) -> 1249999.6 | U16: =T16/S16 -> 1 | V16: =+$V$1/N16/10^6 -> 3995.995 | X16: 1 | Y16: 1 | Z16: 0 | AA16: -1 | AB16: -1 | AC16: -1 | AD16: -1 | AE16: -1 | AF16: -1 | AG16: -1 | AH16: -1 | AI16: Looking to capture AI tailwinds with a $5M+ install base | AM16: 2 | AN16: 1 | AO16: 1 | AP16: 1 | AQ16: 1 | AS16: 1.2 | AT16: 1.2 | AU16: 0.4 | AV16: 1.4 | AW16: 2 | AX16: 1.6 | BB16: ABG | BC16: 45 | BD16: 13.5 | BF16: 58.5 | BG16: No scorecard, pulled from Investment Diligence
A17: x | B17: Remote | C17: =INDEX('Statement of Investments'!$C$5:$C$220,MATCH('Investment Characteristics'!$B17,'Statement of Investments'!$B$5:$B$220,0)) -> 44398 | D17: B | E17: Workforce | F17: =INDEX('Statement of Investments'!$L$5:$L$220,MATCH('Investment Characteristics'!$B17,'Statement of Investments'!$B$5:$B$220,0)) -> 3999979.6 | G17: Accel, General Catalyst, Index, Sequoia | H17: 0.0039999789 | I17: =IFERROR(ROUND(F17/H17,-5),0) -> 1000000000 | K17: Remote | L17: C | M17: =INDEX('Statement of Investments'!$L$5:$L$220,MATCH('Investment Characteristics'!$K17,'Statement of Investments'!$E$5:$E$220,0)) -> 4781446 | N17: 0.003599981 | O17: =I17 -> 1000000000 | P17: =IFERROR(ROUND(S17/N17,-5),0) -> 1328200000 | Q17: 3000000000 | R17: =+Q17 -> 3000000000 | S17: =INDEX('Statement of Investments'!$L$5:$L$220,MATCH(B17,'Statement of Investments'!$E$5:$E$220,0)) -> 4781446 | T17: =INDEX('Statement of Investments'!$O$5:$O$220,MATCH(B17,'Statement of Investments'!$E$5:$E$220,0)) -> 10354762 | U17: =T17/S17 -> 2.165613 | V17: =+$V$1/N17/10^6 -> 20555.664 | X17: 1 | Y17: 1 | Z17: 0 | AA17: 0 | AB17: 1 | AC17: 1 | AD17: 1 | AE17: 1 | AF17: 1 | AG17: 1 | AH17: 1 | AI17: Forecasting to accelerate above $350M ARR, continued tailwinds from global workforce | AM17: 2 | AN17: 1 | AP17: 1 | AQ17: 2 | AS17: 1.5 | AT17: 2 | AU17: 1.8 | AV17: 2 | AW17: 1.8 | AX17: 0.3 | BB17: RP | BC17: 52.5 | BD17: 14.3 | BF17: 66.8
B18: Finch | C18: =INDEX('Statement of Investments'!$C$5:$C$220,MATCH('Investment Characteristics'!$B18,'Statement of Investments'!$B$5:$B$220,0)) -> 44435 | D18: A | E18: Financial | F18: =INDEX('Statement of Investments'!$L$5:$L$220,MATCH('Investment Characteristics'!$B18,'Statement of Investments'!$B$5:$B$220,0)) -> 500003.42 | G18: Menlo, General Catalyst, Box Group | H18: 0.0043467434 | I18: =IFERROR(ROUND(F18/H18,-5),0) -> 115000000 | K18: Finch | L18: B | M18: =INDEX('Statement of Investments'!$L$5:$L$220,MATCH('Investment Characteristics'!$K18,'Statement of Investments'!$E$5:$E$220,0)) -> 500003.42 | N18: 0.0032205422 | O18: =I18 -> 115000000 | P18: =IFERROR(ROUND(S18/N18,-5),0) -> 155300000 | Q18: 230000392 | R18: =+Q18 -> 230000392 | S18: =INDEX('Statement of Investments'!$L$5:$L$220,MATCH(B18,'Statement of Investments'!$E$5:$E$220,0)) -> 500003.42 | T18: =INDEX('Statement of Investments'!$O$5:$O$220,MATCH(B18,'Statement of Investments'!$E$5:$E$220,0)) -> 740862.12 | U18: =T18/S18 -> 1.4817141 | V18: =+$V$1/N18/10^6 -> 22977.498 | X18: 1 | Y18: 1 | Z18: 1 | AA18: 1 | AB18: 1 | AC18: 1 | AD18: 1 | AE18: 1 | AF18: 1 | AG18: 1 | AH18: 0 | AI18: HR Tech API, Modest growth in Rev, ARR is down ~10% when compared to product traction (seems substantial), high growth margins ~80%, val multiples seem high when compared to industry (peaking at ~20x), retention/churn metrics and high val multiple would suggest yellow (high yellow - cautious but positive) | AJ18: 34 months | AM18: 1 | AN18: 1 | AQ18: 1 | AS18: 1 | AT18: 1 | AU18: 1.7 | AV18: 1.3 | AW18: 1.7 | AX18: 0.3 | BB18: RP | BC18: 46.5 | BD18: 14 | BE18: 2 | BF18: 62.5
A19: x | B19: Midi | C19: =INDEX('Statement of Investments'!$C$5:$C$220,MATCH('Investment Characteristics'!$B19,'Statement of Investments'!$B$5:$B$220,0)) -> 44455 | D19: Seed | E19: Healthtech | F19: =INDEX('Statement of Investments'!$L$5:$L$220,MATCH('Investment Characteristics'!$B19,'Statement of Investments'!$B$5:$B$220,0)) -> 510137 | G19: Icon Ventures | H19: =F19/10000000 -> 0.0510137 | I19: =IFERROR(ROUND(F19/H19,-5),0) -> 10000000 | K19: Midi | L19: D | M19: =INDEX('Statement of Investments'!$L$5:$L$220,MATCH('Investment Characteristics'!$K19,'Statement of Investments'!$E$5:$E$220,0)) -> 5531507 | N19: 0.0483 | O19: =I19 -> 10000000 | P19: =IFERROR(ROUND(S19/N19,-5),0) -> 114500000 | Q19: 1150000000 | R19: =+Q19 -> 1150000000 | S19: =INDEX('Statement of Investments'!$L$5:$L$220,MATCH(B19,'Statement of Investments'!$E$5:$E$220,0)) -> 5531507 | T19: =INDEX('Statement of Investments'!$O$5:$O$220,MATCH(B19,'Statement of Investments'!$E$5:$E$220,0)) -> 48185999 | U19: =T19/S19 -> 8.7111883 | V19: =+$V$1/N19/10^6 -> 1532.0911 | X19: 1 | Y19: 1 | Z19: 1 | AA19: 1 | AB19: 1 | AC19: 1 | AD19: 1 | AE19: 1 | AF19: 1 | AG19: 1 | AH19: 1 | AI19: Beating and raising, ~$190M in revenue growing ~5x y/y | AM19: 2 | AN19: 2 | AO19: 1 | AP19: 1 | AQ19: 1 | AS19: 1.4 | AT19: 1.6 | AU19: 0.2 | AV19: 1.8 | AW19: 1.4 | AX19: 1.8 | BB19: ABG | BC19: 41.5 | BD19: 8 | BF19: 49.5 | BG19: No scorecard, pulled from Investment Diligence
B20: ianacare | C20: =INDEX('Statement of Investments'!$C$5:$C$220,MATCH('Investment Characteristics'!$B20,'Statement of Investments'!$B$5:$B$220,0)) -> 44547 | D20: A | E20: Healthtech | F20: =INDEX('Statement of Investments'!$L$5:$L$220,MATCH('Investment Characteristics'!$B20,'Statement of Investments'!$B$5:$B$220,0)) -> 999984.87 | G20: Greycroft, 8VC | H20: 0.016666456 | I20: =IFERROR(ROUND(F20/H20,-5),0) -> 60000000 | K20: ianacare | L20: A | M20: =INDEX('Statement of Investments'!$L$5:$L$220,MATCH('Investment Characteristics'!$K20,'Statement of Investments'!$E$5:$E$220,0)) -> 2999984.9 | N20: 0.01664562 | O20: =I20 -> 60000000 | P20: =+O20 -> 60000000 | Q20: =P20 -> 60000000 | R20: =+Q20 -> 60000000 | S20: =INDEX('Statement of Investments'!$L$5:$L$220,MATCH(B20,'Statement of Investments'!$E$5:$E$220,0)) -> 2999984.9 | T20: =INDEX('Statement of Investments'!$O$5:$O$220,MATCH(B20,'Statement of Investments'!$E$5:$E$220,0)) -> 2999984.9 | U20: =T20/S20 -> 1 | V20: =+$V$1/N20/10^6 -> 4445.6139 | Y20: 1 | Z20: 1 | AA20: 1 | AB20: 1 | AC20: 0 | AD20: -1 | AE20: -1 | AF20: 0 | AG20: 0 | AH20: 0 | AI20: Regulatory tailwinds from GUIDE program driving growth as company shifts away from employer. Expect GUIDE revenue to ramp from 6 digit ARR to 7 digit ARR in the next 6-9 months. They revised 2025E ARR projectons down by 25% but expect visibility into GUIDE related ARR to dramatically increase over next 12 months. | AJ20: 12 months | AM20: 2 | AN20: 1 | AO20: 2 | AP20: 1 | AQ20: 1 | AS20: 1.4 | AT20: 2 | AU20: 1.4 | AV20: 1 | AW20: 1.8 | AX20: 1 | BB20: ABG | BC20: 47.8 | BD20: 15 | BF20: 62.8
B21: Vivante | C21: =INDEX('Statement of Investments'!$C$5:$C$220,MATCH('Investment Characteristics'!$B21,'Statement of Investments'!$B$5:$B$220,0)) -> 44552 | D21: A | E21: Healthtech | F21: =INDEX('Statement of Investments'!$L$5:$L$220,MATCH('Investment Characteristics'!$B21,'Statement of Investments'!$B$5:$B$220,0)) -> 999999 | G21: 7Wire, NFP | H21: 0.045928552 | I21: =IFERROR(ROUND(F21/H21,-5),0) -> 21800000 | K21: Vivante | L21: B | M21: =INDEX('Statement of Investments'!$L$5:$L$220,MATCH('Investment Characteristics'!$K21,'Statement of Investments'!$E$5:$E$220,0)) -> 2204142.3 | N21: 0.037179658 | O21: =I21 -> 21800000 | P21: =IFERROR(ROUND(S21/N21,-5),0) -> 59300000 | Q21: 84077296 | R21: =+Q21 -> 84077296 | S21: =INDEX('Statement of Investments'!$L$5:$L$220,MATCH(B21,'Statement of Investments'!$E$5:$E$220,0)) -> 2204142.3 | T21: =INDEX('Statement of Investments'!$O$5:$O$220,MATCH(B21,'Statement of Investments'!$E$5:$E$220,0)) -> 3130662 | U21: =T21/S21 -> 1.4203538 | V21: =+$V$1/N21/10^6 -> 1990.3357 | Y21: 1 | Z21: 1 | AA21: -1 | AB21: 1 | AC21: 1 | AD21: 1 | AE21: 1 | AF21: 1 | AG21: 1 | AH21: -1 | AI21: Down round, strucured pay to play with punitive provisions | AM21: 1 | AN21: 2 | AP21: 1 | AQ21: 2 | AS21: 1.5 | AT21: 1.3 | AU21: 1 | AV21: 1.8 | AW21: 1.5 | AX21: 2 | BB21: RP | BC21: 49.5 | BF21: 49.5
B22: a.team | C22: =INDEX('Statement of Investments'!$C$5:$C$220,MATCH('Investment Characteristics'!$B22,'Statement of Investments'!$B$5:$B$220,0)) -> 44567 | D22: A | E22: Workforce | F22: =INDEX('Statement of Investments'!$L$5:$L$220,MATCH('Investment Characteristics'!$B22,'Statement of Investments'!$B$5:$B$220,0)) -> 999998.86 | G22: Spruce, Tiger, Insight, BoxGroup | H22: 0.003076922 | I22: =IFERROR(ROUND(F22/H22,-5),0) -> 325000000 | K22: a.team | L22: A | M22: =INDEX('Statement of Investments'!$L$5:$L$220,MATCH('Investment Characteristics'!$K22,'Statement of Investments'!$E$5:$E$220,0)) -> 999998.86 | N22: 0.0030769253 | O22: =I22 -> 325000000 | P22: =IFERROR(ROUND(S22/N22,-5),0) -> 325000000 | Q22: =P22 -> 325000000 | R22: =+Q22 -> 325000000 | S22: =INDEX('Statement of Investments'!$L$5:$L$220,MATCH(B22,'Statement of Investments'!$E$5:$E$220,0)) -> 999998.86 | T22: =INDEX('Statement of Investments'!$O$5:$O$220,MATCH(B22,'Statement of Investments'!$E$5:$E$220,0)) -> 999998.86 | U22: =T22/S22 -> 1 | V22: =+$V$1/N22/10^6 -> 24049.983 | Y22: 1 | Z22: 1 | AA22: 1 | AB22: 0 | AC22: 1 | AD22: 0 | AE22: 0 | AF22: 0 | AG22: 0 | AH22: 0 | AI22: Over 2 years of runway, $10M+ ARR, Company is running talent marketplace and the model is aligned with usage based model, rather than classic ARR | AY22: Double-check | BB22: ABG | BC22: 51.5 | BD22: 17.8 | BF22: 69.3
B23: CoverGo | C23: =INDEX('Statement of Investments'!$C$5:$C$220,MATCH('Investment Characteristics'!$B23,'Statement of Investments'!$B$5:$B$220,0)) -> 44621 | D23: A | E23: Financial | F23: =INDEX('Statement of Investments'!$L$5:$L$220,MATCH('Investment Characteristics'!$B23,'Statement of Investments'!$B$5:$B$220,0)) -> 2000000 | G23: N/A | H23: =(F23+2*10^6)/I23 -> 0.093023256 | I23: 43000000 | K23: CoverGo | L23: A | M23: =INDEX('Statement of Investments'!$L$5:$L$220,MATCH('Investment Characteristics'!$K23,'Statement of Investments'!$E$5:$E$220,0)) -> 4000000 | N23: 0.093023256 | O23: =I23 -> 43000000 | P23: =O23 -> 43000000 | Q23: =P23 -> 43000000 | R23: =+Q23 -> 43000000 | S23: =INDEX('Statement of Investments'!$L$5:$L$220,MATCH(B23,'Statement of Investments'!$E$5:$E$220,0)) -> 4000000 | T23: =INDEX('Statement of Investments'!$O$5:$O$220,MATCH(B23,'Statement of Investments'!$E$5:$E$220,0)) -> 5294506.9 | U23: =T23/S23 -> 1.3236267 | V23: =+$V$1/N23/10^6 -> 795.5 | Y23: 1 | Z23: 1 | AA23: 1 | AB23: 1 | AC23: 1 | AD23: 0 | AE23: 0 | AF23: 0 | AG23: 0 | AH23: 0 | AI23: Reaccelerated growth, forecasting 2x y/y growth and close to breakeven, yellow for now, will see how the raise goes | AJ23: 6 months, starting B raise in Q4/Q1'26 | AM23: 1 | AN23: 2 | AQ23: 2 | AS23: 1.7 | AT23: 1 | AU23: 2 | AV23: 1.3 | AW23: 1.7 | AX23: 2 | BB23: CH | BC23: 45.5 | BD23: 14.8 | BE23: 3.5 | BF23: 63.8
B24: Delfina | C24: =INDEX('Statement of Investments'!$C$5:$C$220,MATCH('Investment Characteristics'!$B24,'Statement of Investments'!$B$5:$B$220,0)) -> 44621 | D24: Seed | E24: Healthtech | F24: =INDEX('Statement of Investments'!$L$5:$L$220,MATCH('Investment Characteristics'!$B24,'Statement of Investments'!$B$5:$B$220,0)) -> 800000 | G24: Story Ventures | H24: =F24/I24 -> 0.053333333 | I24: =15*10^6 -> 15000000 | K24: Delfina | L24: A | M24: =INDEX('Statement of Investments'!$L$5:$L$220,MATCH('Investment Characteristics'!$K24,'Statement of Investments'!$E$5:$E$220,0)) -> 1549999.9 | N24: 0.041920188 | O24: =I24 -> 15000000 | P24: =O24 -> 15000000 | Q24: 52000000 | R24: =+Q24 -> 52000000 | S24: =INDEX('Statement of Investments'!$L$5:$L$220,MATCH(B24,'Statement of Investments'!$E$5:$E$220,0)) -> 1549999.9 | T24: =INDEX('Statement of Investments'!$O$5:$O$220,MATCH(B24,'Statement of Investments'!$E$5:$E$220,0)) -> 2097344.6 | U24: =T24/S24 -> 1.3531256 | V24: =+$V$1/N24/10^6 -> 1765.2593 | Z24: 1 | AA24: 1 | AB24: 1 | AC24: 1 | AD24: 0 | AE24: 0 | AF24: 1 | AG24: 0 | AH24: 0 | AI24: Didn't provide revenue projections but taking a hit due to Medicaid budget cuts. Actuals down from projections | AM24: 2 | AN24: 2 | AO24: 2 | AP24: 1 | AQ24: 2 | AS24: 1.8 | AT24: 1.8 | AU24: 1.2 | AV24: 1.4 | AW24: 1.4 | AX24: 2 | BB24: RP | BC24: 45 | BD24: 9.5 | BF24: 54.5
B25: Ashby | C25: =INDEX('Statement of Investments'!$C$5:$C$220,MATCH('Investment Characteristics'!$B25,'Statement of Investments'!$B$5:$B$220,0)) -> 44599 | D25: B | E25: Workforce | F25: =INDEX('Statement of Investments'!$L$5:$L$220,MATCH('Investment Characteristics'!$B25,'Statement of Investments'!$B$5:$B$220,0)) -> 3000000 | G25: F-Prime, Elad Gil | H25: =F25/I25 -> 0.017142857 | I25: 175000000 | K25: Ashby | L25: D | M25: =INDEX('Statement of Investments'!$L$5:$L$220,MATCH('Investment Characteristics'!$K25,'Statement of Investments'!$E$5:$E$220,0)) -> 5000000 | N25: 0.020715715 | O25: =I25 -> 175000000 | P25: =O25 -> 175000000 | Q25: 500000000 | R25: =+Q25 -> 500000000 | S25: =INDEX('Statement of Investments'!$L$5:$L$220,MATCH(B25,'Statement of Investments'!$E$5:$E$220,0)) -> 5000000 | T25: =INDEX('Statement of Investments'!$O$5:$O$220,MATCH(B25,'Statement of Investments'!$E$5:$E$220,0)) -> 10135319 | U25: =T25/S25 -> 2.0270638 | V25: =+$V$1/N25/10^6 -> 3572.1674 | Y25: 1 | Z25: 1 | AA25: 1 | AB25: 1 | AC25: 1 | AD25: 1 | AE25: 1 | AF25: 1 | AG25: 1 | AH25: 1 | AI25: Closed a $50M Series D at a ~2x step-up from previous round, strong growth | AM25: 1 | AN25: 1 | AP25: 2 | AQ25: 2 | AS25: 1.5 | AT25: 1 | AU25: 1.5 | AV25: 1.5 | AW25: 1.3 | AX25: 0.8 | BB25: RP | BC25: 53.3 | BD25: 13 | BF25: 66.3 | BG25: No scorecard, pulled from Investment Diligence
B26: Mosey | C26: =INDEX('Statement of Investments'!$C$5:$C$220,MATCH('Investment Characteristics'!$B26,'Statement of Investments'!$B$5:$B$220,0)) -> 44707 | D26: A | E26: Workforce | F26: =INDEX('Statement of Investments'!$L$5:$L$220,MATCH('Investment Characteristics'!$B26,'Statement of Investments'!$B$5:$B$220,0)) -> 3999998.9 | G26: Canaan | H26: 0.045455 | I26: 88000000 | K26: Mosey | L26: A | M26: =INDEX('Statement of Investments'!$L$5:$L$220,MATCH('Investment Characteristics'!$K26,'Statement of Investments'!$E$5:$E$220,0)) -> 3999998.9 | N26: 0.045455 | O26: =I26 -> 88000000 | P26: =O26 -> 88000000 | Q26: =P26 -> 88000000 | R26: =+Q26 -> 88000000 | S26: =INDEX('Statement of Investments'!$L$5:$L$220,MATCH(B26,'Statement of Investments'!$E$5:$E$220,0)) -> 3999998.9 | T26: =INDEX('Statement of Investments'!$O$5:$O$220,MATCH(B26,'Statement of Investments'!$E$5:$E$220,0)) -> 3999998.9 | U26: =T26/S26 -> 1 | V26: =+$V$1/N26/10^6 -> 1627.9837 | Z26: 1 | AA26: 1 | AB26: 1 | AC26: 0 | AD26: 0 | AE26: 0 | AF26: 0 | AG26: 0 | AH26: 0 | AI26: Revenue growing ~46% y/y and significant integrations into payroll providers, val multiple too high | AJ26: 24 months | AM26: 2 | AN26: 1 | AO26: 2 | AP26: 2 | AQ26: 2 | AS26: 1.8 | AT26: 1.8 | AU26: 1.4 | AV26: 1.8 | AW26: 2 | AX26: 0.6 | BB26: RP | BC26: 45.5 | BF26: 45.5
B27: Violet | C27: =INDEX('Statement of Investments'!$C$5:$C$220,MATCH('Investment Characteristics'!$B27,'Statement of Investments'!$B$5:$B$220,0)) -> 44722 | D27: Seed | E27: Healthtech | F27: =INDEX('Statement of Investments'!$L$5:$L$220,MATCH('Investment Characteristics'!$B27,'Statement of Investments'!$B$5:$B$220,0)) -> 2599995.3 | G27: The Venture Collective, Northwell | H27: =F27/I27 -> 0.1181816 | I27: =22*10^6 -> 22000000 | K27: Violet | L27: Seed | M27: =INDEX('Statement of Investments'!$L$5:$L$220,MATCH('Investment Characteristics'!$K27,'Statement of Investments'!$E$5:$E$220,0)) -> 2599995.3 | N27: 0.12409 | O27: =I27 -> 22000000 | P27: =O27 -> 22000000 | Q27: =P27 -> 22000000 | R27: =+Q27 -> 22000000 | S27: =INDEX('Statement of Investments'!$L$5:$L$220,MATCH(B27,'Statement of Investments'!$E$5:$E$220,0)) -> 2599995.3 | T27: =INDEX('Statement of Investments'!$O$5:$O$220,MATCH(B27,'Statement of Investments'!$E$5:$E$220,0)) -> 2599995.3 | U27: =T27/S27 -> 1 | V27: =+$V$1/N27/10^6 -> 596.34137 | Z27: 1 | AA27: 0 | AB27: 0 | AC27: 1 | AD27: 0 | AE27: 0 | AF27: 1 | AG27: 0 | AH27: -1 | AI27: Modest growth yoy (1.53x) Actively pursuing M&A, UCare contract cancelled as Medicaid related churn coming to fruition, $2.7M ARR Churn (230k/month) | AJ27: Cash & AR: $592k ($395k cash + $197k AR) Additional guaranteed Rev til EOM Jan: $287k Total: $879k Burn: $230k / month = 3.82 months cash out date | AM27: 2 | AN27: 2 | AO27: 2 | AP27: 2 | AQ27: 2 | AS27: 2 | AT27: 1.2 | AU27: 0.8 | AV27: 1.2 | AW27: 2 | AX27: 2 | BB27: ABG | BC27: 37 | BF27: 37
B28: Gable | C28: =INDEX('Statement of Investments'!$C$5:$C$220,MATCH('Investment Characteristics'!$B28,'Statement of Investments'!$B$5:$B$220,0)) -> 44848 | D28: A | E28: Workforce | F28: =INDEX('Statement of Investments'!$L$5:$L$220,MATCH('Investment Characteristics'!$B28,'Statement of Investments'!$B$5:$B$220,0)) -> 4000000 | G28: Foundation Capital | H28: 0.08 | I28: =F28/H28 -> 50000000 | K28: Gable | L28: A | M28: =INDEX('Statement of Investments'!$L$5:$L$220,MATCH('Investment Characteristics'!$K28,'Statement of Investments'!$E$5:$E$220,0)) -> 4000000 | N28: 0.08 | O28: =I28 -> 50000000 | P28: =O28 -> 50000000 | Q28: =P28 -> 50000000 | R28: =+Q28 -> 50000000 | S28: =INDEX('Statement of Investments'!$L$5:$L$220,MATCH(B28,'Statement of Investments'!$E$5:$E$220,0)) -> 4000000 | T28: =INDEX('Statement of Investments'!$O$5:$O$220,MATCH(B28,'Statement of Investments'!$E$5:$E$220,0)) -> 4000000 | U28: =T28/S28 -> 1 | V28: =+$V$1/N28/10^6 -> 925 | AA28: 1 | AB28: 0 | AC28: 0 | AD28: 0 | AE28: 0 | AF28: 1 | AG28: 0 | AH28: 0 | AI28: Forecasting $7.8M ARR by end of Q1'26. Sep run rate at $3.6M. Raised internal bridge round, forecasting ~3x growth and scale appropriate for Series B. Reduced burn, have reduced costs and improved EBITDA. Rev multiple seems high, would want to keep this at yellow. | AJ28: 13 months | AM28: 1 | AN28: 2 | AO28: 2 | AP28: 2 | AQ28: 2 | BB28: RP/CT | BC28: 49 | BD28: 14 | BF28: 63
A29: Wellthy Merger | B29: Patch Caregiving | C29: =INDEX('Statement of Investments'!$C$5:$C$220,MATCH('Investment Characteristics'!$B29,'Statement of Investments'!$B$5:$B$220,0)) -> 44879 | D29: Seed | E29: Workforce | F29: =INDEX('Statement of Investments'!$L$5:$L$220,MATCH('Investment Characteristics'!$B29,'Statement of Investments'!$B$5:$B$220,0))+'Statement of Investments'!L204 -> 499999.85 | G29: AlleyCorp | H29: =F29/I29 -> 0.062499981 | I29: =8*10^6 -> 8000000 | K29: Patch Caregiving | L29: Acq. | M29: =INDEX('Statement of Investments'!$L$79:$L$220,MATCH('Investment Characteristics'!$K29,'Statement of Investments'!$E$79:$E$220,0)) -> 411245.85 | N29: 0.0018 | O29: =I29 -> 8000000 | P29: =O29 -> 8000000 | Q29: =P29 -> 8000000 | R29: =+Q29 -> 8000000 | S29: =INDEX('Statement of Investments'!$L$79:$L$220,MATCH(B29,'Statement of Investments'!$E$79:$E$220,0)) -> 411245.85 | T29: =INDEX('Statement of Investments'!$O$79:$O$220,MATCH(B29,'Statement of Investments'!$E$79:$E$220,0)) -> 586415.29 | U29: =T29/S29 -> 1.4259482 | V29: =+$V$1/N29/10^6 -> 41111.111 | AA29: 1 | AB29: 1 | AC29: 1 | AD29: 1 | AE29: 1 | AF29: 1 | AG29: 1 | AH29: 0 | AI29: Acquired by Wellthy, our share is valued at ~600k. No access to FI | AM29: 1 | AN29: 2 | AO29: 2 | AP29: 1 | AQ29: 2 | BB29: RP/CT | BC29: 45.5 | BD29: 15 | BF29: 60.5
B30: Formally | C30: =INDEX('Statement of Investments'!$C$5:$C$220,MATCH('Investment Characteristics'!$B30,'Statement of Investments'!$B$5:$B$220,0)) -> 45006 | D30: Seed | E30: Workforce | F30: =INDEX('Statement of Investments'!$L$5:$L$220,MATCH('Investment Characteristics'!$B30,'Statement of Investments'!$B$5:$B$220,0)) -> 1000000 | G30: Bessemer | H30: =F30/I30 -> 0.04 | I30: =25*10^6 -> 25000000 | K30: Formally | L30: Seed | M30: =INDEX('Statement of Investments'!$L$5:$L$220,MATCH('Investment Characteristics'!$K30,'Statement of Investments'!$E$5:$E$220,0)) -> 1000000 | N30: 0.04 | O30: =I30 -> 25000000 | P30: =O30 -> 25000000 | Q30: =P30 -> 25000000 | R30: =+Q30 -> 25000000 | S30: =INDEX('Statement of Investments'!$L$5:$L$220,MATCH(B30,'Statement of Investments'!$E$5:$E$220,0)) -> 1000000 | T30: =INDEX('Statement of Investments'!$O$5:$O$220,MATCH(B30,'Statement of Investments'!$E$5:$E$220,0)) -> 1000000 | U30: =T30/S30 -> 1 | V30: =+$V$1/N30/10^6 -> 1850 | AB30: 1 | AC30: 1 | AD30: 0 | AE30: 0 | AF30: 0 | AG30: 0 | AH30: 0 | AI30: Legal AI is driving renewed interest and company continues to sell well into legal firms | AM30: 1* | AN30: 1 | AO30: 2 | AP30: 0 | AQ30: 2 | AS30: 1.2 | AT30: 1 | AU30: 0.6 | AV30: 0.4 | AW30: 1.4 | AX30: 0 | BB30: ABG | BC30: 41.5
B31: Liftoff | C31: =INDEX('Statement of Investments'!$C$5:$C$220,MATCH('Investment Characteristics'!$B31,'Statement of Investments'!$B$5:$B$220,0)) -> 45064 | D31: Seed | E31: Workforce | F31: =INDEX('Statement of Investments'!$L$5:$L$220,MATCH('Investment Characteristics'!$B31,'Statement of Investments'!$B$5:$B$220,0)) -> 500000 | G31: Torch Capital, Kleiner Perkins Spark Fund | H31: =F31/I31 -> 0.05 | I31: =10*10^6 -> 10000000 | K31: Liftoff | L31: Seed | M31: =INDEX('Statement of Investments'!$L$5:$L$220,MATCH('Investment Characteristics'!$K31,'Statement of Investments'!$E$5:$E$220,0)) -> 886565.66 | N31: 0.0486 | O31: =I31 -> 10000000 | P31: =O31 -> 10000000 | Q31: =39*10^6 -> 39000000 | R31: =+Q31 -> 39000000 | S31: =INDEX('Statement of Investments'!$L$5:$L$220,MATCH(B31,'Statement of Investments'!$E$5:$E$220,0)) -> 886565.66 | T31: =INDEX('Statement of Investments'!$O$5:$O$220,MATCH(B31,'Statement of Investments'!$E$5:$E$220,0)) -> 1896344.2 | U31: =T31/S31 -> 2.1389777 | V31: =+$V$1/N31/10^6 -> 1522.6337 | AB31: 1 | AC31: 1 | AD31: 1 | AE31: 1 | AF31: 1 | AG31: 1 | AH31: 1 | AI31: Came out of stealth in Oct 25, good organic growth, no real monetization yet, positive for now but will need to watch the story unfold from here | AJ31: 30 months | AM31: 2 | AN31: 1 | AO31: 1 | AP31: 1 | AQ31: 1 | AS31: 1.2 | AT31: 1.6 | AU31: 0.8 | AV31: 1.8 | AW31: 1 | AX31: 1.6 | BB31: ABG | BC31: 38 | BF31: 41.5
B32: Easop | C32: =INDEX('Statement of Investments'!$C$5:$C$220,MATCH('Investment Characteristics'!$B32,'Statement of Investments'!$B$5:$B$220,0)) -> 45065 | D32: Seed | E32: Workforce | F32: 1000000 | G32: Partech Ventures, Boldstart Ventures | H32: =F32/I32 -> 0.066666667 | I32: =15*10^6 -> 15000000 | K32: Easop | L32: Acq. | M32: =+F32 -> 1000000 | N32: 0.066666667 | O32: =I32 -> 15000000 | P32: =O32 -> 15000000 | Q32: =P32 -> 15000000 | R32: =+Q32 -> 15000000 | S32: =+M32 -> 1000000 | T32: =+'Statement of Investments'!O7+'Statement of Investments'!O143 -> 1068916.9 | U32: =T32/S32 -> 1.0689169 | V32: =+$V$1/N32/10^6 -> 1110 | AB32: 1 | AC32: 1 | AM32: 1 | AN32: 1 | AO32: 2 | AP32: 2 | AQ32: 2 | AS32: 1.6 | AT32: 1 | AU32: 0.6 | AV32: 0.6 | AW32: 1.6 | AX32: 1.6 | BB32: CT | BC32: 47 | BF32: 47
B34: Average | F34: =AVERAGE(F4:F33) -> 1286554.6 | H34: =AVERAGE(H4:H33) -> 0.031544087 | I34: =AVERAGE(I4:I33) -> 1.1215172e+08 | K34: Average | M34: =AVERAGE(M4:M33) -> 2337306.8 | N34: =AVERAGE(N4:N33) -> 0.031800223 | O34: =AVERAGE(O4:O33) -> 1.1215172e+08 | P34: =AVERAGE(P4:P33) -> 1.6257586e+08 | Q34: =AVERAGE(Q4:Q33) -> 3.4850345e+08 | S34: =AVERAGE(S4:S33) -> 2337306.8 | T34: =AVERAGE(T4:T33) -> 5013002.8
B35: Median | F35: =MEDIAN(F4:F33) -> 999984.87 | H35: =MEDIAN(H4:H33) -> 0.02 | I35: =MEDIAN(I4:I33) -> 50000000 | K35: Median | M35: =MEDIAN(M4:M33) -> 2049994.2 | N35: =MEDIAN(N4:N33) -> 0.020715715 | O35: =MEDIAN(O4:O33) -> 50000000 | P35: =MEDIAN(P4:P33) -> 67500000 | Q35: =MEDIAN(Q4:Q33) -> 84077296 | S35: =MEDIAN(S4:S33) -> 2049994.2 | T35: =MEDIAN(T4:T33) -> 2097344.6
B36: Dollar Weighted | H36: =SUMPRODUCT(H$4:H$33,$F$4:$F$33)/SUM($F$4:$F$33) -> 0.039869451 | I36: =SUMPRODUCT(I$4:I$33,$F$4:$F$33)/SUM($F$4:$F$33) -> 1.9381834e+08 | K36: Dollar Weighted | N36: =SUMPRODUCT(N$4:N$33,$S$4:$S$33)/SUM($S$4:$S$33) -> 0.036997972 | O36: =SUMPRODUCT(O$4:O$33,$F$4:$F$33)/SUM($F$4:$F$33) -> 1.9381834e+08 | P36: =SUMPRODUCT(P$4:P$33,$S$4:$S$33)/SUM($S$4:$S$33) -> 2.1700773e+08 | Q36: =SUMPRODUCT(Q$4:Q$33,$S$4:$S$33)/SUM($S$4:$S$33) -> 5.4883287e+08
N40: =AVERAGE(N19,N17,N12) -> 0.024199994 | Q40: =280/3.2% -> 8750
B41: Fund II Sector Summary | P41: =280/(3%*6) -> 1555.5556
C42: Workforce | D42: Healthtech | E42: Financial | F42: Total
B43: Deals:
B44: # of Deals | C44: =COUNTIF($E$4:$E$35,C$42) -> 14 | D44: =COUNTIF($E$4:$E$35,D$42) -> 10 | E44: =COUNTIF($E$4:$E$35,E$42) -> 5 | F44: =SUM(C44:E44) -> 29
B45: % of Deals | C45: =C44/$F$44 -> 0.48275862 | D45: =D44/$F$44 -> 0.34482759 | E45: =E44/$F$44 -> 0.17241379 | F45: =F44/$F$44 -> 1
B46: Invested Capital:
B47: Initial Investment | C47: =SUMIF($E$4:$E$35,C$42,$F$4:$F$35) -> 21199976 | D47: =SUMIF($E$4:$E$35,D$42,$F$4:$F$35) -> 11010112 | E47: =SUMIF($E$4:$E$35,E$42,$F$4:$F$35) -> 5099996.9 | F47: =SUM(C47:E47) -> 37310084
B48: % of Invested Cap | C48: =C47/$F$47 -> 0.56821034 | D48: =D47/$F$47 -> 0.29509747 | E48: =E47/$F$47 -> 0.13669218 | F48: =F47/$F$47 -> 1
B49: Current Investment | C49: =SUMIF($E$4:$E$35,C$42,$M$4:$M$35) -> 31379244 | D49: =SUMIF($E$4:$E$35,D$42,$M$4:$M$35) -> 26349503 | E49: =SUMIF($E$4:$E$35,E$42,$M$4:$M$35) -> 10053151 | F49: =SUM(C49:E49) -> 67781898
B50: % of Invested Cap | C50: =C49/$F$49 -> 0.46294431 | D50: =D49/$F$49 -> 0.38873953 | E50: =E49/$F$49 -> 0.14831616 | F50: =F49/$F$49 -> 1
B51: Current Mark
B52: Total Value | C52: =SUMIF($E$4:$E$35,C$42,$T$4:$T$35) -> 39789050 | D52: =SUMIF($E$4:$E$35,D$42,$T$4:$T$35) -> 94399515 | E52: =SUMIF($E$4:$E$35,E$42,$T$4:$T$35) -> 11188517 | F52: =SUM(C52:E52) -> 1.4537708e+08
B53: MOIC | C53: =C52/C49 -> 1.2680054 | D53: =D52/D49 -> 3.5825918 | E53: =E52/E49 -> 1.1129364 | F53: =F52/F49 -> 2.1447774
B54: Average Investment:
B55: Initial Avg. Inv. | C55: =AVERAGEIF($E$4:$E$35,C$42,$F$4:$F$35) -> 1514284 | D55: =AVERAGEIF($E$4:$E$35,D$42,$F$4:$F$35) -> 1101011.2 | E55: =AVERAGEIF($E$4:$E$35,E$42,$F$4:$F$35) -> 1019999.4 | F55: =F34 -> 1286554.6
B56: Current Avg. Inv. | C56: =AVERAGEIF($E$4:$E$35,C$42,$M$4:$M$35) -> 2241374.5 | D56: =AVERAGEIF($E$4:$E$35,D$42,$M$4:$M$35) -> 2634950.3 | E56: =AVERAGEIF($E$4:$E$35,E$42,$M$4:$M$35) -> 2010630.2 | F56: =M34 -> 2337306.8
B57: Average Cost:
B58: Initial Avg. Cost | C58: =AVERAGEIF($E$4:$E$35,C$42,$I$4:$I$35) -> 131250000 | D58: =AVERAGEIF($E$4:$E$35,D$42,$I$4:$I$35) -> 101190000 | E58: =AVERAGEIF($E$4:$E$35,E$42,$I$4:$I$35) -> 80600000 | F58: =I34 -> 1.1215172e+08
B59: Current Avg. Inv. | C59: =AVERAGEIF($E$4:$E$35,C$42,$P$4:$P$35) -> 1.6732857e+08 | D59: =AVERAGEIF($E$4:$E$35,D$42,$P$4:$P$35) -> 175460000 | E59: =AVERAGEIF($E$4:$E$35,E$42,$P$4:$P$35) -> 123500000 | F59: =P34 -> 1.6257586e+08
B60: Round
B61: Seed | C61: =COUNTIFS($D$4:$D$35,$B61,$E$4:$E$35,C$42) -> 8 | D61: =COUNTIFS($D$4:$D$35,$B61,$E$4:$E$35,D$42) -> 3 | E61: =COUNTIFS($D$4:$D$35,$B61,$E$4:$E$35,E$42) -> 1 | F61: =SUM(C61:E61) -> 12
B62: A | C62: =COUNTIFS($D$4:$D$35,$B62,$E$4:$E$35,C$42) -> 4 | D62: =COUNTIFS($D$4:$D$35,$B62,$E$4:$E$35,D$42) -> 4 | E62: =COUNTIFS($D$4:$D$35,$B62,$E$4:$E$35,E$42) -> 4 | F62: =SUM(C62:E62) -> 12
B63: B+ | C63: =COUNTIFS($D$4:$D$35,"B",$E$4:$E$35,C$42)+COUNTIFS($D$4:$D$35,"C",$E$4:$E$35,C$42) -> 2 | D63: =COUNTIFS($D$4:$D$35,"B",$E$4:$E$35,D$42)+COUNTIFS($D$4:$D$35,"C",$E$4:$E$35,D$42) -> 3 | E63: =COUNTIFS($D$4:$D$35,"B",$E$4:$E$35,E$42)+COUNTIFS($D$4:$D$35,"C",$E$4:$E$35,E$42) -> 0 | F63: =SUM(C63:E63) -> 5
B66: Fund II Stage Summary
C67: Seed | D67: A | E67: B | F67: Total
B68: Average Investment:
B69: Initial Avg. Inv. | C69: =AVERAGEIF($D$4:$D$33,C$67,$F$4:$F$33) -> 688344.2 | D69: =AVERAGEIF($D$4:$D$33,D$67,$F$4:$F$33) -> 1579164.8 | E69: =AVERAGEIFS($F$4:$F$33,$D$4:$D$33,"<>Seed",$D$4:$D$33,"<>A") -> 2019995.3 | F69: =F34 -> 1286554.6
B70: Current Avg. Inv. | C70: =AVERAGEIF($D$4:$D$33,C$67,$M$4:$M$33) -> 1785775.1 | D70: =AVERAGEIF($D$4:$D$33,D$67,$M$4:$M$33) -> 2592271.9 | E70: =AVERAGEIFS($M$4:$M$33,$D$4:$D$33,"<>Seed",$D$4:$D$33,"<>A") -> 3049066.5 | F70: =M34 -> 2337306.8
B71: Deals
B72: # of Deals | C72: =COUNTIF($D$4:$D$35,C$67) -> 12 | D72: =COUNTIF($D$4:$D$35,D$67) -> 12 | E72: =COUNTIF($D$4:$D$33,"B")+COUNTIF($D$4:$D$33,"C") -> 5 | F72: =SUM(C72:E72) -> 29
B73: % of Deals | C73: =C72/$F$72 -> 0.4137931 | D73: =D72/$F$72 -> 0.4137931 | E73: =E72/$F$72 -> 0.17241379 | F73: =F72/$F$72 -> 1
B74: # of Deals | C74: =COUNTIF($L$4:$L$35,C$67) -> 5 | D74: =COUNTIF($L$4:$L$35,D$67) -> 9 | E74: =F72-SUM(C74:D74) -> 15 | F74: =SUM(C74:E74) -> 29
B75: % of Deals | C75: =C74/$F$72 -> 0.17241379 | D75: =D74/$F$72 -> 0.31034483 | E75: =E74/$F$72 -> 0.51724138 | F75: =F74/$F$72 -> 1
B76: Valuation
B77: Initial Avg. Cost | C77: =AVERAGEIF($D$4:$D$33,C$67,$I$4:$I$33) -> 16583333 | D77: =AVERAGEIF($D$4:$D$33,D$67,$I$4:$I$33) -> 94866667 | E77: =AVERAGEIFS($I$4:$I$33,$D$4:$D$33,"<>Seed",$D$4:$D$33,"<>A") -> 383000000 | F77: =I34 -> 1.1215172e+08
B78: Initial Median Cost | C78: {=MEDIAN(IF($D$4:$D$33=C67,$I$4:$I$33))} -> 15000000 | D78: {=MEDIAN(IF($D$4:$D$33=D67,$I$4:$I$33))} -> 73750000 | E78: =MEDIAN(I7,I10,I14,I25,I17) -> 230000000 | F78: =I35 -> 50000000
B79: Ownership
B80: Initial Avg. FD% | C80: =AVERAGEIF($D$4:$D$33,C$67,$H$4:$H$33) -> 0.043795119 | D80: =AVERAGEIF($D$4:$D$33,D$67,$H$4:$H$33) -> 0.02963664 | E80: =AVERAGEIFS($H$4:$H$33,$D$4:$D$33,"<>Seed",$D$4:$D$33,"<>A") -> 0.0067194849 | F80: =H34 -> 0.031544087
B81: Initial Median FD% | C81: {=MEDIAN(IF($D$4:$D$33=C$67,$H$4:$H$33))} -> 0.045 | D81: {=MEDIAN(IF($D$4:$D$33=D$67,$H$4:$H$33))} -> 0.017592499 | E81: =MEDIAN(H25,H17,H14,H10,H7) -> 0.0050633027 | F81: =H35 -> 0.02
B82: Invested Capital:
B83: Initial Investment | C83: =SUMIF($D$4:$D$33,C$67,$F$4:$F$33) -> 8260130.4 | D83: =SUMIF($D$4:$D$33,D$67,$F$4:$F$33) -> 18949977 | E83: =SUMIF($D$4:$D$33,"B",$F$4:$F$33)+F10 -> 10099977 | F83: =SUM(C83:E83) -> 37310084
C84: =C83/$F$83 -> 0.22139136 | D84: =D83/$F$83 -> 0.50790497 | E84: =E83/$F$83 -> 0.27070367
B85: Current Investment | C85: =SUMIF($L$4:$L$33,C$67,$M$4:$M$33) -> 6261558.9 | D85: =SUMIF($L$4:$L$33,D$67,$M$4:$M$33) -> 23424978 | E85: =SUM(M4:M30)-SUM(C85:D85) -> 36208795 | F85: =SUM(C85:E85) -> 65895332
C86: =C85/$F$85 -> 0.0950228 | D86: =D85/$F$85 -> 0.35548767 | E86: =E85/$F$85 -> 0.54948953
C94: `

Sheet Investment Rollover
B2: Cost | H2: Carrying Value
B3: Company | C3: 6/30/2025 Value | D3: Additions | E3: Dispositions | F3: 9/30/2025 Value | H3: Company | I3: =C3 -> 6/30/2025 Value | J3: Additions | K3: Dispositions | L3: Writeup/Down | M3: =F3 -> 9/30/2025 Value | N3: MOIC
B4: Brightline | C4: 1499987 | D4: =IF(F4>C4,F4-C4,0) -> 0 | E4: =IF(F4<C4,F4-C4,0) -> 0 | F4: =INDEX('Statement of Investments'!$L$5:$L$220,MATCH('Investment Rollover'!$B4,'Statement of Investments'!$E$5:$E$220,0)) -> 1499987 | H4: =B4 -> Brightline | I4: 4521963.7 | J4: =D4 -> 0 | K4: =E4 -> 0 | L4: =M4-SUM(I4:K4) -> 0 | M4: =INDEX('Statement of Investments'!$O$5:$O$220,MATCH('Investment Rollover'!$H4,'Statement of Investments'!$E$5:$E$220,0)) -> 4521963.7 | N4: =M4/F4 -> 3.0146685
B5: Murmur | C5: 1574998 | D5: =IF(F5>C5,F5-C5,0) -> 0 | E5: =IF(F5<C5,F5-C5,0) -> 0 | F5: =INDEX('Statement of Investments'!$L$5:$L$220,MATCH('Investment Rollover'!$B5,'Statement of Investments'!$E$5:$E$220,0)) -> 1574998 | H5: =B5 -> Murmur | I5: 1574998 | J5: =D5 -> 0 | K5: =E5 -> 0 | L5: =M5-SUM(I5:K5) -> -1574998 | M5: =INDEX('Statement of Investments'!$O$5:$O$220,MATCH('Investment Rollover'!$H5,'Statement of Investments'!$E$5:$E$220,0)) -> 0 | N5: =M5/F5 -> 0
B6: Pinwheel | C6: 1453156.1 | D6: =IF(F6>C6,F6-C6,0) -> 0 | E6: =IF(F6<C6,F6-C6,0) -> 0 | F6: =INDEX('Statement of Investments'!$L$5:$L$220,MATCH('Investment Rollover'!$B6,'Statement of Investments'!$E$5:$E$220,0)) -> 1453156.1 | H6: =B6 -> Pinwheel | I6: 3035952.2 | J6: =D6 -> 0 | K6: =E6 -> 0 | L6: =M6-SUM(I6:K6) -> -1582796.1 | M6: =INDEX('Statement of Investments'!$O$5:$O$220,MATCH('Investment Rollover'!$H6,'Statement of Investments'!$E$5:$E$220,0)) -> 1453156.1 | N6: =M6/F6 -> 1
B7: Cleo | C7: 599997.84 | D7: =IF(F7>C7,F7-C7,0) -> 0 | E7: =IF(F7<C7,F7-C7,0) -> 0 | F7: =INDEX('Statement of Investments'!$L$5:$L$220,MATCH('Investment Rollover'!$B7,'Statement of Investments'!$E$5:$E$220,0)) -> 599997.84 | H7: =B7 -> Cleo | I7: 0 | J7: =D7 -> 0 | K7: =E7 -> 0 | L7: =M7-SUM(I7:K7) -> 0 | M7: =INDEX('Statement of Investments'!$O$5:$O$220,MATCH('Investment Rollover'!$H7,'Statement of Investments'!$E$5:$E$220,0)) -> 0 | N7: =M7/F7 -> 0
B8: Rightfoot | C8: 399999.32 | D8: =IF(F8>C8,F8-C8,0) -> 0 | E8: =IF(F8<C8,F8-C8,0) -> 0 | F8: =INDEX('Statement of Investments'!$L$5:$L$220,MATCH('Investment Rollover'!$B8,'Statement of Investments'!$E$5:$E$220,0)) -> 399999.32 | H8: =B8 -> Rightfoot | I8: 0 | J8: =D8 -> 0 | K8: =E8 -> 0 | L8: =M8-SUM(I8:K8) -> 0 | M8: =INDEX('Statement of Investments'!$O$5:$O$220,MATCH('Investment Rollover'!$H8,'Statement of Investments'!$E$5:$E$220,0)) -> 0 | N8: =M8/F8 -> 0
B9: Galileo | C9: 1999999.2 | D9: =IF(F9>C9,F9-C9,0) -> 163902.45 | E9: =IF(F9<C9,F9-C9,0) -> 0 | F9: =INDEX('Statement of Investments'!$L$5:$L$220,MATCH('Investment Rollover'!$B9,'Statement of Investments'!$E$5:$E$220,0)) -> 2163901.7 | H9: =B9 -> Galileo | I9: 2604941.4 | J9: =D9 -> 163902.45 | K9: =E9 -> 0 | L9: =M9-SUM(I9:K9) -> -1043965.1 | M9: =INDEX('Statement of Investments'!$O$5:$O$220,MATCH('Investment Rollover'!$H9,'Statement of Investments'!$E$5:$E$220,0)) -> 1724878.8 | N9: =M9/F9 -> 0.79711515
B10: Cocoon | C10: 4224996.6 | D10: =IF(F10>C10,F10-C10,0) -> 0 | E10: =IF(F10<C10,F10-C10,0) -> 0 | F10: =INDEX('Statement of Investments'!$L$5:$L$220,MATCH('Investment Rollover'!$B10,'Statement of Investments'!$E$5:$E$220,0)) -> 4224996.6 | H10: =B10 -> Cocoon | I10: 4224996.6 | J10: =D10 -> 0 | K10: =E10 -> 0 | L10: =M10-SUM(I10:K10) -> 0 | M10: =INDEX('Statement of Investments'!$O$5:$O$220,MATCH('Investment Rollover'!$H10,'Statement of Investments'!$E$5:$E$220,0)) -> 4224996.6 | N10: =M10/F10 -> 1
B11: Rula | C11: 4500000 | D11: =IF(F11>C11,F11-C11,0) -> 0 | E11: =IF(F11<C11,F11-C11,0) -> 0 | F11: =INDEX('Statement of Investments'!$L$5:$L$220,MATCH('Investment Rollover'!$B11,'Statement of Investments'!$E$5:$E$220,0)) -> 4500000 | H11: =B11 -> Rula | I11: 25285301 | J11: =D11 -> 0 | K11: =E11 -> 0 | L11: =M11-SUM(I11:K11) -> 0 | M11: =INDEX('Statement of Investments'!$O$5:$O$220,MATCH('Investment Rollover'!$H11,'Statement of Investments'!$E$5:$E$220,0)) -> 25285301 | N11: =M11/F11 -> 5.6189558
B12: Origin | C12: 3699992.1 | D12: =IF(F12>C12,F12-C12,0) -> 0 | E12: =IF(F12<C12,F12-C12,0) -> 0 | F12: =INDEX('Statement of Investments'!$L$5:$L$220,MATCH('Investment Rollover'!$B12,'Statement of Investments'!$E$5:$E$220,0)) -> 3699992.1 | H12: =B12 -> Origin | I12: 3699992.1 | J12: =D12 -> 0 | K12: =E12 -> 0 | L12: =M12-SUM(I12:K12) -> 0 | M12: =INDEX('Statement of Investments'!$O$5:$O$220,MATCH('Investment Rollover'!$H12,'Statement of Investments'!$E$5:$E$220,0)) -> 3699992.1 | N12: =M12/F12 -> 1
B13: Nayya | C13: 2699987.1 | D13: =IF(F13>C13,F13-C13,0) -> 0 | E13: =IF(F13<C13,F13-C13,0) -> 0 | F13: =INDEX('Statement of Investments'!$L$5:$L$220,MATCH('Investment Rollover'!$B13,'Statement of Investments'!$E$5:$E$220,0)) -> 2699987.1 | H13: =B13 -> Nayya | I13: 3853385.4 | J13: =D13 -> 0 | K13: =E13 -> 0 | L13: =M13-SUM(I13:K13) -> 0 | M13: =INDEX('Statement of Investments'!$O$5:$O$220,MATCH('Investment Rollover'!$H13,'Statement of Investments'!$E$5:$E$220,0)) -> 3853385.4 | N13: =M13/F13 -> 1.4271866
B14: Praisidio | C14: 200000 | D14: =IF(F14>C14,F14-C14,0) -> 0 | E14: =IF(F14<C14,F14-C14,0) -> 0 | F14: =INDEX('Statement of Investments'!$L$5:$L$220,MATCH('Investment Rollover'!$B14,'Statement of Investments'!$E$5:$E$220,0)) -> 200000 | H14: =B14 -> Praisidio | I14: 0 | J14: =D14 -> 0 | K14: =E14 -> 0 | L14: =M14-SUM(I14:K14) -> 0 | M14: =INDEX('Statement of Investments'!$O$5:$O$220,MATCH('Investment Rollover'!$H14,'Statement of Investments'!$E$5:$E$220,0)) -> 0 | N14: =M14/F14 -> 0
B15: Bravely | C15: 1249999.6 | D15: =IF(F15>C15,F15-C15,0) -> 0 | E15: =IF(F15<C15,F15-C15,0) -> 0 | F15: =INDEX('Statement of Investments'!$L$5:$L$220,MATCH('Investment Rollover'!$B15,'Statement of Investments'!$E$5:$E$220,0)) -> 1249999.6 | H15: =B15 -> Bravely | I15: 1249999.6 | J15: =D15 -> 0 | K15: =E15 -> 0 | L15: =M15-SUM(I15:K15) -> 0 | M15: =INDEX('Statement of Investments'!$O$5:$O$220,MATCH('Investment Rollover'!$H15,'Statement of Investments'!$E$5:$E$220,0)) -> 1249999.6 | N15: =M15/F15 -> 1
... B27: Gable | C27: 4000000 | D27: =IF(F27>C27,F27-C27,0) -> 0 | E27: =IF(F27<C27,F27-C27,0) -> 0 | F27: =INDEX('Statement of Investments'!$L$5:$L$220,MATCH('Investment Rollover'!$B27,'Statement of Investments'!$E$5:$E$220,0)) -> 4000000 | H27: =B27 -> Gable | I27: 4000000 | J27: =D27 -> 0 | K27: =E27 -> 0 | L27: =M27-SUM(I27:K27) -> 0 | M27: =INDEX('Statement of Investments'!$O$5:$O$220,MATCH('Investment Rollover'!$H27,'Statement of Investments'!$E$5:$E$220,0)) -> 4000000 | N27: =M27/F27 -> 1
B28: Patch Caregiving | C28: 500000 | D28: =IF(F28>C28,F28-C28,0) -> 0 | E28: =IF(F28<C28,F28-C28,0) -> -88754.15 | F28: ='Statement of Investments'!L204 -> 411245.85 | H28: =B28 -> Patch Caregiving | I28: 500000 | J28: =D28 -> 0 | K28: =E28 -> -88754.15 | L28: =M28-SUM(I28:K28) -> 175169.44 | M28: ='Statement of Investments'!O204 -> 586415.29 | N28: =M28/F28 -> 1.4259482
B29: Formally | C29: 1000000 | D29: =IF(F29>C29,F29-C29,0) -> 0 | E29: =IF(F29<C29,F29-C29,0) -> 0 | F29: =INDEX('Statement of Investments'!$L$5:$L$220,MATCH('Investment Rollover'!$B29,'Statement of Investments'!$E$5:$E$220,0)) -> 1000000 | H29: =B29 -> Formally | I29: 1000000 | J29: =D29 -> 0 | K29: =E29 -> 0 | L29: =M29-SUM(I29:K29) -> 0 | M29: =INDEX('Statement of Investments'!$O$5:$O$220,MATCH('Investment Rollover'!$H29,'Statement of Investments'!$E$5:$E$220,0)) -> 1000000 | N29: =M29/F29 -> 1
B30: Liftoff | C30: 886565.66 | D30: =IF(F30>C30,F30-C30,0) -> 0 | E30: =IF(F30<C30,F30-C30,0) -> 0 | F30: =INDEX('Statement of Investments'!$L$5:$L$220,MATCH('Investment Rollover'!$B30,'Statement of Investments'!$E$5:$E$220,0)) -> 886565.66 | H30: =B30 -> Liftoff | I30: 1896344.2 | J30: =D30 -> 0 | K30: =E30 -> 0 | L30: =M30-SUM(I30:K30) -> 0 | M30: =INDEX('Statement of Investments'!$O$5:$O$220,MATCH('Investment Rollover'!$H30,'Statement of Investments'!$E$5:$E$220,0)) -> 1896344.2 | N30: =M30/F30 -> 2.1389777
B32: Unrealized Total | C32: =SUM(C4:C31) -> 64656755 | D32: =SUM(D4:D31) -> 163902.45 | E32: =SUM(E4:E31) -> -88754.15 | F32: =SUM(F4:F31) -> 64731903 | H32: Unrealized Total | I32: =SUM(I4:I31) -> 1.2394434e+08 | J32: =SUM(J4:J31) -> 163902.45 | K32: =SUM(K4:K31) -> -88754.15 | L32: =SUM(L4:L31) -> 20016380 | M32: =SUM(M4:M31) -> 1.4403587e+08 | N32: =M32/F32 -> 2.225114
B35: Realized Cost | H35: Realized Carrying Value
B36: Easop | C36: 218533.69 | D36: =IF(F36>C36,F36-C36,0) -> 0 | E36: =IF(F36<C36,F36-C36,0) -> 0 | F36: =INDEX('Statement of Investments'!$L$5:$L$220,MATCH('Investment Rollover'!$B36,'Statement of Investments'!$E$5:$E$220,0)) -> 218533.69 | H36: =B36 -> Easop | I36: 204077.51 | J36: =D36 -> 0 | K36: =E36 -> 0 | L36: =M36-SUM(I36:K36) -> 59246.994 | M36: =INDEX('Statement of Investments'!$O$5:$O$220,MATCH('Investment Rollover'!$H36,'Statement of Investments'!$E$5:$E$220,0)) -> 263324.5 | N36: =M36/F36 -> 1.2049607
B37: Mathison | C37: 2049994.2 | D37: =IF(F37>C37,F37-C37,0) -> 0 | E37: =IF(F37<C37,F37-C37,0) -> 0 | F37: =INDEX('Statement of Investments'!$L$5:$L$220,MATCH('Investment Rollover'!$B37,'Statement of Investments'!$E$5:$E$220,0)) -> 2049994.2 | H37: =B37 -> Mathison | I37: 272298.82 | J37: =D37 -> 0 | K37: =E37 -> 0 | L37: =M37-SUM(I37:K37) -> 0 | M37: =INDEX('Statement of Investments'!$O$5:$O$220,MATCH('Investment Rollover'!$H37,'Statement of Investments'!$E$5:$E$220,0)) -> 272298.82 | N37: =M37/F37 -> 0.13282907
B38: Realized Total | C38: =SUM(C36:C37) -> 2268527.9 | D38: =SUM(D36:D37) -> 0 | E38: =SUM(E36:E37) -> 0 | F38: =SUM(F36:F37) -> 2268527.9 | H38: Realized Total | I38: =SUM(I36:I37) -> 476376.33 | J38: =SUM(J36:J37) -> 0 | K38: =SUM(K36:K37) -> 0 | L38: =SUM(L36:L37) -> 59246.994 | M38: =SUM(M36:M37) -> 535623.32 | N38: =M38/F38 -> 0.23611053
B39: Total | C39: =C38+C32 -> 66925283 | D39: =D38+D32 -> 163902.45 | E39: =E38+E32 -> -88754.15 | F39: =F38+F32 -> 67000431 | H39: Total | I39: =I38+I32 -> 1.2442071e+08 | J39: =J38+J32 -> 163902.45 | K39: =K38+K32 -> -88754.15 | L39: =L38+L32 -> 20075627 | M39: =M38+M32 -> 1.4457149e+08 | N39: =M39/F39 -> 2.1577695

Sheet Reserves old2
G2: Total Remaining Cash | H2: =8383280 -> 8383280
G3: 3 Yrs. Management Fees | H3: -3359850
G4: Net Investable Cash | H4: =H2+H3 -> 5023430
G5: Total Reserves | H5: =-SUM(H11:H45) -> -8500000
G6: Net Remaining | H6: =SUM(H4:H5) -> -3476570
O7: 74000000
B8: Company | C8: Sector | D8: $ Invested | E8: Follow-Ons | F8: $ Invested | H8: Reserves | I8: Total+Reserves | K8: Current Stage | L8: Last Valuation | M8: Avg. Cost | N8: RTF | O8: RTF + Warrants | P8: Reasoning
B10: Seed
B11: Murmur | C11: Workforce | D11: =INDEX('Investment Characteristics'!$F$4:$F$35,MATCH('Reserves old2'!$B11,'Investment Characteristics'!$B$4:$B$35,0)) -> 225000 | E11: =F11-D11 -> 1349998 | F11: =INDEX('Statement of Investments'!$L$5:$L$226,MATCH(B11,'Statement of Investments'!$E$5:$E$226,0)) -> 1574998 | H11: 0 | I11: =H11+F11 -> 1574998 | K11: =+INDEX('Investment Characteristics'!$L$4:$L$30,MATCH('Reserves old2'!$B11,'Investment Characteristics'!$K$4:$K$30,0)) -> Seed | L11: =+INDEX('Investment Characteristics'!$Q$4:$Q$24,MATCH('Reserves old2'!$B11,'Investment Characteristics'!$K$4:$K$24,0)) -> 28000000 | M11: =+INDEX('Investment Characteristics'!$P$4:$P$27,MATCH('Reserves old2'!B11,'Investment Characteristics'!$K$4:$K$27,0)) -> 24600000 | N11: =+INDEX('Investment Characteristics'!$V$4:$V$27,MATCH('Reserves old2'!B11,'Investment Characteristics'!$K$4:$K$27,0)) -> 1154.9923 | O11: =+N11 -> 1154.9923 | P11: "interested"
B12: Midi | C12: Healthtech | D12: =INDEX('Investment Characteristics'!$F$4:$F$35,MATCH('Reserves old2'!$B12,'Investment Characteristics'!$B$4:$B$35,0)) -> 510137 | E12: =F12-D12 -> 5021370 | F12: =INDEX('Statement of Investments'!$L$5:$L$226,MATCH(B12,'Statement of Investments'!$E$5:$E$226,0)) -> 5531507 | H12: 2000000 | I12: =H12+F12 -> 7531507 | K12: =+INDEX('Investment Characteristics'!$L$4:$L$30,MATCH('Reserves old2'!$B12,'Investment Characteristics'!$K$4:$K$30,0)) -> D | L12: =+INDEX('Investment Characteristics'!$Q$4:$Q$24,MATCH('Reserves old2'!$B12,'Investment Characteristics'!$K$4:$K$24,0)) -> 1150000000 | M12: =+INDEX('Investment Characteristics'!$P$4:$P$27,MATCH('Reserves old2'!B12,'Investment Characteristics'!$K$4:$K$27,0)) -> 114500000 | N12: =+INDEX('Investment Characteristics'!$V$4:$V$27,MATCH('Reserves old2'!B12,'Investment Characteristics'!$K$4:$K$27,0)) -> 1532.0911 | O12: =+O7/0.1495/10^6 -> 494.98328
B13: Delfina | D13: =INDEX('Investment Characteristics'!$F$4:$F$35,MATCH('Reserves old2'!$B13,'Investment Characteristics'!$B$4:$B$35,0)) -> 800000 | E13: =F13-D13 -> 749999.92 | F13: =INDEX('Statement of Investments'!$L$5:$L$226,MATCH(B13,'Statement of Investments'!$E$5:$E$226,0)) -> 1549999.9 | H13: =1.5*10^6 -> 1500000 | I13: =H13+F13 -> 3049999.9 | K13: =+INDEX('Investment Characteristics'!$L$4:$L$30,MATCH('Reserves old2'!$B13,'Investment Characteristics'!$K$4:$K$30,0)) -> A | L13: =+INDEX('Investment Characteristics'!$Q$4:$Q$24,MATCH('Reserves old2'!$B13,'Investment Characteristics'!$K$4:$K$24,0)) -> 52000000 | M13: =+INDEX('Investment Characteristics'!$P$4:$P$27,MATCH('Reserves old2'!B13,'Investment Characteristics'!$K$4:$K$27,0)) -> 15000000 | N13: =+INDEX('Investment Characteristics'!$V$4:$V$27,MATCH('Reserves old2'!B13,'Investment Characteristics'!$K$4:$K$27,0)) -> 1765.2593 | O13: =+N13 -> 1765.2593
B14: Praisidio | C14: Workforce | D14: =INDEX('Investment Characteristics'!$F$4:$F$35,MATCH('Reserves old2'!$B14,'Investment Characteristics'!$B$4:$B$35,0)) -> 200000 | E14: =F14-D14 -> 0 | F14: =INDEX('Statement of Investments'!$L$5:$L$226,MATCH(B14,'Statement of Investments'!$E$5:$E$226,0)) -> 200000 | H14: 0 | I14: =H14+F14 -> 200000 | K14: =+INDEX('Investment Characteristics'!$L$4:$L$30,MATCH('Reserves old2'!$B14,'Investment Characteristics'!$K$4:$K$30,0)) -> Seed | L14: =+INDEX('Investment Characteristics'!$Q$4:$Q$24,MATCH('Reserves old2'!$B14,'Investment Characteristics'!$K$4:$K$24,0)) -> 20000000 | M14: =+INDEX('Investment Characteristics'!$P$4:$P$27,MATCH('Reserves old2'!B14,'Investment Characteristics'!$K$4:$K$27,0)) -> 20000000 | N14: =+INDEX('Investment Characteristics'!$V$4:$V$27,MATCH('Reserves old2'!B14,'Investment Characteristics'!$K$4:$K$27,0)) -> 7400 | O14: =+O7/0.025/10^6 -> 2960 | P14: "not seeing evidence they are breaking out"
B15: Violet | D15: =INDEX('Investment Characteristics'!$F$4:$F$35,MATCH('Reserves old2'!$B15,'Investment Characteristics'!$B$4:$B$35,0)) -> 2599995.3 | E15: =F15-D15 -> 0 | F15: =INDEX('Statement of Investments'!$L$5:$L$226,MATCH(B15,'Statement of Investments'!$E$5:$E$226,0)) -> 2599995.3 | H15: 500000 | I15: =H15+F15 -> 3099995.3 | K15: =+INDEX('Investment Characteristics'!$L$4:$L$30,MATCH('Reserves old2'!$B15,'Investment Characteristics'!$K$4:$K$30,0)) -> Seed | L15: =+INDEX('Investment Characteristics'!$Q$4:$Q$27,MATCH('Reserves old2'!$B15,'Investment Characteristics'!$K$4:$K$27,0)) -> 22000000 | M15: =+INDEX('Investment Characteristics'!$P$4:$P$27,MATCH('Reserves old2'!B15,'Investment Characteristics'!$K$4:$K$27,0)) -> 22000000 | N15: =+INDEX('Investment Characteristics'!$V$4:$V$27,MATCH('Reserves old2'!B15,'Investment Characteristics'!$K$4:$K$27,0)) -> 596.34137 | O15: =+N15 -> 596.34137 | P15: Led the round, need to reserve
B16: Patch Caregiving | D16: =INDEX('Investment Characteristics'!$F$4:$F$35,MATCH('Reserves old2'!$B16,'Investment Characteristics'!$B$4:$B$35,0)) -> 499999.85 | E16: =F16-D16 -> -411245.85 | F16: =INDEX('Statement of Investments'!$L$5:$L$226,MATCH(B16,'Statement of Investments'!$E$5:$E$226,0)) -> 88754 | H16: 500000 | I16: =H16+F16 -> 588754 | K16: =+INDEX('Investment Characteristics'!$L$4:$L$30,MATCH('Reserves old2'!$B16,'Investment Characteristics'!$K$4:$K$30,0)) -> Acq. | L16: ='Investment Characteristics'!Q29 -> 8000000 | M16: ='Investment Characteristics'!P29 -> 8000000 | N16: ='Investment Characteristics'!V29 -> 41111.111 | O16: =+N16 -> 41111.111
B17: Formally | D17: =INDEX('Investment Characteristics'!$F$4:$F$35,MATCH('Reserves old2'!$B17,'Investment Characteristics'!$B$4:$B$35,0)) -> 1000000 | E17: =F17-D17 -> 0 | F17: =INDEX('Statement of Investments'!$L$5:$L$226,MATCH(B17,'Statement of Investments'!$E$5:$E$226,0)) -> 1000000 | H17: =1*10^6 -> 1000000 | I17: =H17+F17 -> 2000000 | K17: =+INDEX('Investment Characteristics'!$L$4:$L$30,MATCH('Reserves old2'!$B17,'Investment Characteristics'!$K$4:$K$30,0)) -> Seed | L17: =+INDEX('Investment Characteristics'!$Q$4:$Q$30,MATCH('Reserves old2'!$B17,'Investment Characteristics'!$K$4:$K$30,0)) -> 25000000 | M17: =+INDEX('Investment Characteristics'!$P$4:$P$30,MATCH('Reserves old2'!B17,'Investment Characteristics'!$K$4:$K$30,0)) -> 25000000 | N17: =+INDEX('Investment Characteristics'!$V$4:$V$30,MATCH('Reserves old2'!B17,'Investment Characteristics'!$K$4:$K$30,0)) -> 1850 | O17: =+N17 -> 1850 | P17: Led the round, need to reserve
B18: Liftoff | D18: =INDEX('Investment Characteristics'!$F$4:$F$35,MATCH('Reserves old2'!$B18,'Investment Characteristics'!$B$4:$B$35,0)) -> 500000 | E18: =F18-D18 -> 386565.66 | F18: =INDEX('Statement of Investments'!$L$5:$L$226,MATCH(B18,'Statement of Investments'!$E$5:$E$226,0)) -> 886565.66 | H18: 1000000 | I18: =H18+F18 -> 1886565.7 | K18: =+INDEX('Investment Characteristics'!$L$4:$L$31,MATCH('Reserves old2'!$B18,'Investment Characteristics'!$K$4:$K$31,0)) -> Seed | L18: ='Investment Characteristics'!Q31 -> 39000000 | M18: ='Investment Characteristics'!P31 -> 10000000 | N18: ='Investment Characteristics'!V31 -> 1522.6337 | O18: =+N18 -> 1522.6337
B19: Easop | D19: =INDEX('Investment Characteristics'!$F$4:$F$35,MATCH('Reserves old2'!$B19,'Investment Characteristics'!$B$4:$B$35,0)) -> 1000000 | E19: =F19-D19 -> -781466.31 | F19: =INDEX('Statement of Investments'!$L$5:$L$226,MATCH(B19,'Statement of Investments'!$E$5:$E$226,0)) -> 218533.69 | H19: =1*10^6 -> 1000000 | I19: =H19+F19 -> 1218533.7 | K19: =+INDEX('Investment Characteristics'!$L$4:$L$32,MATCH('Reserves old2'!$B19,'Investment Characteristics'!$K$4:$K$32,0)) -> Acq. | L19: =+INDEX('Investment Characteristics'!$Q$4:$Q$32,MATCH('Reserves old2'!$B19,'Investment Characteristics'!$K$4:$K$32,0)) -> 15000000 | M19: =+INDEX('Investment Characteristics'!$P$4:$P$32,MATCH('Reserves old2'!B19,'Investment Characteristics'!$K$4:$K$32,0)) -> 15000000 | N19: =+INDEX('Investment Characteristics'!$V$4:$V$32,MATCH('Reserves old2'!B19,'Investment Characteristics'!$K$4:$K$32,0)) -> 1110 | O19: =+N19 -> 1110
B21: Series A
B22: Gable | D22: =4*10^6 -> 4000000 | E22: =F22-D22 -> 0 | F22: =4*10^6 -> 4000000 | H22: 500000 | I22: =+F22 -> 4000000 | K22: =+INDEX('Investment Characteristics'!$L$4:$L$30,MATCH('Reserves old2'!$B22,'Investment Characteristics'!$K$4:$K$30,0)) -> A | L22: =+M22 -> 50000000 | M22: =50*10^6 -> 50000000 | N22: =+'Investment Characteristics'!V1/0.08/10^6 -> 925 | O22: =+N22 -> 925
B23: Vivante | D23: =INDEX('Investment Characteristics'!$F$4:$F$35,MATCH('Reserves old2'!$B23,'Investment Characteristics'!$B$4:$B$35,0)) -> 999999 | E23: =F23-D23 -> 1204143.3 | F23: =INDEX('Statement of Investments'!$L$5:$L$226,MATCH(B23,'Statement of Investments'!$E$5:$E$226,0)) -> 2204142.3 | H23: 0 | I23: =H23+F23 -> 2204142.3 | K23: =+INDEX('Investment Characteristics'!$L$4:$L$30,MATCH('Reserves old2'!$B23,'Investment Characteristics'!$K$4:$K$30,0)) -> B | L23: =+INDEX('Investment Characteristics'!$Q$4:$Q$24,MATCH('Reserves old2'!$B23,'Investment Characteristics'!$K$4:$K$24,0)) -> 84077296 | M23: =+INDEX('Investment Characteristics'!$P$4:$P$27,MATCH('Reserves old2'!B23,'Investment Characteristics'!$K$4:$K$27,0)) -> 59300000 | N23: =+INDEX('Investment Characteristics'!$V$4:$V$27,MATCH('Reserves old2'!B23,'Investment Characteristics'!$K$4:$K$27,0)) -> 1990.3357 | O23: =+N23 -> 1990.3357
B24: CoverGo | D24: =INDEX('Investment Characteristics'!$F$4:$F$35,MATCH('Reserves old2'!$B24,'Investment Characteristics'!$B$4:$B$35,0)) -> 2000000 | E24: =F24-D24 -> 2000000 | F24: =INDEX('Statement of Investments'!$L$5:$L$226,MATCH(B24,'Statement of Investments'!$E$5:$E$226,0)) -> 4000000 | H24: 500000 | I24: =H24+F24 -> 4500000 | K24: =+INDEX('Investment Characteristics'!$L$4:$L$30,MATCH('Reserves old2'!$B24,'Investment Characteristics'!$K$4:$K$30,0)) -> A | L24: =+INDEX('Investment Characteristics'!$Q$4:$Q$24,MATCH('Reserves old2'!$B24,'Investment Characteristics'!$K$4:$K$24,0)) -> 43000000 | M24: =+INDEX('Investment Characteristics'!$P$4:$P$27,MATCH('Reserves old2'!B24,'Investment Characteristics'!$K$4:$K$27,0)) -> 43000000 | N24: =+INDEX('Investment Characteristics'!$V$4:$V$27,MATCH('Reserves old2'!B24,'Investment Characteristics'!$K$4:$K$27,0)) -> 795.5 | O24: =+N24 -> 795.5 | P24: $2M committed if CoverGo reaches ARR target
B25: ianacare | D25: =INDEX('Investment Characteristics'!$F$4:$F$35,MATCH('Reserves old2'!$B25,'Investment Characteristics'!$B$4:$B$35,0)) -> 999984.87 | E25: =F25-D25 -> 2000000 | F25: =INDEX('Statement of Investments'!$L$5:$L$226,MATCH(B25,'Statement of Investments'!$E$5:$E$226,0)) -> 2999984.9 | H25: 0 | I25: =H25+F25 -> 2999984.9 | K25: =+INDEX('Investment Characteristics'!$L$4:$L$30,MATCH('Reserves old2'!$B25,'Investment Characteristics'!$K$4:$K$30,0)) -> A | L25: =+INDEX('Investment Characteristics'!$Q$4:$Q$24,MATCH('Reserves old2'!$B25,'Investment Characteristics'!$K$4:$K$24,0)) -> 60000000 | M25: =+INDEX('Investment Characteristics'!$P$4:$P$27,MATCH('Reserves old2'!B25,'Investment Characteristics'!$K$4:$K$27,0)) -> 60000000 | N25: =+O7/0.035/10^6 -> 2114.2857 | O25: =+N25 -> 2114.2857 | P25: "allison: we should def reserve" / might do (more) in GOF2
B26: Bravely | C26: Workforce | D26: =INDEX('Investment Characteristics'!$F$4:$F$35,MATCH('Reserves old2'!$B26,'Investment Characteristics'!$B$4:$B$35,0)) -> 1249999.6 | E26: =F26-D26 -> 0 | F26: =INDEX('Statement of Investments'!$L$5:$L$226,MATCH(B26,'Statement of Investments'!$E$5:$E$226,0)) -> 1249999.6 | H26: 0 | I26: =H26+F26 -> 1249999.6 | K26: =+INDEX('Investment Characteristics'!$L$4:$L$30,MATCH('Reserves old2'!$B26,'Investment Characteristics'!$K$4:$K$30,0)) -> A | L26: =+INDEX('Investment Characteristics'!$Q$4:$Q$24,MATCH('Reserves old2'!$B26,'Investment Characteristics'!$K$4:$K$24,0)) -> 67500000 | M26: =+INDEX('Investment Characteristics'!$P$4:$P$27,MATCH('Reserves old2'!B26,'Investment Characteristics'!$K$4:$K$27,0)) -> 67500000 | N26: =+INDEX('Investment Characteristics'!$V$4:$V$27,MATCH('Reserves old2'!B26,'Investment Characteristics'!$K$4:$K$27,0)) -> 3995.995 | O26: =+N26 -> 3995.995 | P26: "nope"
B27: Mathison | C27: Workforce | D27: =INDEX('Investment Characteristics'!$F$4:$F$35,MATCH('Reserves old2'!$B27,'Investment Characteristics'!$B$4:$B$35,0)) -> 299999.56 | E27: =F27-D27 -> 1749994.6 | F27: =INDEX('Statement of Investments'!$L$5:$L$226,MATCH(B27,'Statement of Investments'!$E$5:$E$226,0)) -> 2049994.2 | H27: 0 | I27: =H27+F27 -> 2049994.2 | K27: =+INDEX('Investment Characteristics'!$L$4:$L$30,MATCH('Reserves old2'!$B27,'Investment Characteristics'!$K$4:$K$30,0)) -> Acq. | L27: =+INDEX('Investment Characteristics'!$Q$4:$Q$24,MATCH('Reserves old2'!$B27,'Investment Characteristics'!$K$4:$K$24,0)) -> 70000000 | M27: =+INDEX('Investment Characteristics'!$P$4:$P$27,MATCH('Reserves old2'!B27,'Investment Characteristics'!$K$4:$K$27,0)) -> 51200000 | N27: =+INDEX('Investment Characteristics'!$V$4:$V$27,MATCH('Reserves old2'!B27,'Investment Characteristics'!$K$4:$K$27,0)) -> 1850 | O27: =O7/0.0485/10^6 -> 1525.7732
B28: Finch | C28: Financial | D28: =INDEX('Investment Characteristics'!$F$4:$F$35,MATCH('Reserves old2'!$B28,'Investment Characteristics'!$B$4:$B$35,0)) -> 500003.42 | E28: =F28-D28 -> 0 | F28: =INDEX('Statement of Investments'!$L$5:$L$226,MATCH(B28,'Statement of Investments'!$E$5:$E$226,0)) -> 500003.42 | H28: 0 | I28: =H28+F28 -> 500003.42 | K28: =+INDEX('Investment Characteristics'!$L$4:$L$30,MATCH('Reserves old2'!$B28,'Investment Characteristics'!$K$4:$K$30,0)) -> B | L28: =+INDEX('Investment Characteristics'!$Q$4:$Q$24,MATCH('Reserves old2'!$B28,'Investment Characteristics'!$K$4:$K$24,0)) -> 230000392 | M28: =+INDEX('Investment Characteristics'!$P$4:$P$27,MATCH('Reserves old2'!B28,'Investment Characteristics'!$K$4:$K$27,0)) -> 155300000 | N28: =+INDEX('Investment Characteristics'!$V$4:$V$27,MATCH('Reserves old2'!B28,'Investment Characteristics'!$K$4:$K$27,0)) -> 22977.498 | O28: =+N28 -> 22977.498 | P28: Low ownership to date and high-upside
B29: Cocoon | C29: Workforce | D29: =INDEX('Investment Characteristics'!$F$4:$F$35,MATCH('Reserves old2'!$B29,'Investment Characteristics'!$B$4:$B$35,0)) -> 224999.42 | E29: =F29-D29 -> 3999997.2 | F29: =INDEX('Statement of Investments'!$L$5:$L$226,MATCH(B29,'Statement of Investments'!$E$5:$E$226,0)) -> 4224996.6 | H29: 0 | I29: =H29+F29 -> 4224996.6 | K29: =+INDEX('Investment Characteristics'!$L$4:$L$30,MATCH('Reserves old2'!$B29,'Investment Characteristics'!$K$4:$K$30,0)) -> A | L29: =+INDEX('Investment Characteristics'!$Q$4:$Q$24,MATCH('Reserves old2'!$B29,'Investment Characteristics'!$K$4:$K$24,0)) -> 1.6250158e+08 | M29: =+INDEX('Investment Characteristics'!$P$4:$P$27,MATCH('Reserves old2'!B29,'Investment Characteristics'!$K$4:$K$27,0)) -> 155100000 | N29: =+INDEX('Investment Characteristics'!$V$4:$V$27,MATCH('Reserves old2'!B29,'Investment Characteristics'!$K$4:$K$27,0)) -> 2716.3448 | O29: =+O7/0.0375/10^6 -> 1973.3333 | P29: Low ownership to date and high-upside
B30: a.team | D30: =INDEX('Investment Characteristics'!$F$4:$F$35,MATCH('Reserves old2'!$B30,'Investment Characteristics'!$B$4:$B$35,0)) -> 999998.86 | E30: =F30-D30 -> 0 | F30: =INDEX('Statement of Investments'!$L$5:$L$226,MATCH(B30,'Statement of Investments'!$E$5:$E$226,0)) -> 999998.86 | H30: 0 | I30: =H30+F30 -> 999998.86 | K30: =+INDEX('Investment Characteristics'!$L$4:$L$30,MATCH('Reserves old2'!$B30,'Investment Characteristics'!$K$4:$K$30,0)) -> A | L30: =+INDEX('Investment Characteristics'!$Q$4:$Q$24,MATCH('Reserves old2'!$B30,'Investment Characteristics'!$K$4:$K$24,0)) -> 325000000 | M30: =+INDEX('Investment Characteristics'!$P$4:$P$27,MATCH('Reserves old2'!B30,'Investment Characteristics'!$K$4:$K$27,0)) -> 325000000 | N30: =+INDEX('Investment Characteristics'!$V$4:$V$27,MATCH('Reserves old2'!B30,'Investment Characteristics'!$K$4:$K$27,0)) -> 24049.983 | O30: =+N30 -> 24049.983
B31: Mosey | D31: =INDEX('Investment Characteristics'!$F$4:$F$35,MATCH('Reserves old2'!$B31,'Investment Characteristics'!$B$4:$B$35,0)) -> 3999998.9 | E31: =F31-D31 -> 0 | F31: =INDEX('Statement of Investments'!$L$5:$L$226,MATCH(B31,'Statement of Investments'!$E$5:$E$226,0)) -> 3999998.9 | H31: 0 | I31: =H31+F31 -> 3999998.9 | K31: =+INDEX('Investment Characteristics'!$L$4:$L$30,MATCH('Reserves old2'!$B31,'Investment Characteristics'!$K$4:$K$30,0)) -> A | L31: =90*10^6 -> 90000000 | M31: =+INDEX('Investment Characteristics'!$P$4:$P$27,MATCH('Reserves old2'!B31,'Investment Characteristics'!$K$4:$K$27,0)) -> 88000000 | N31: =+INDEX('Investment Characteristics'!$V$4:$V$27,MATCH('Reserves old2'!B31,'Investment Characteristics'!$K$4:$K$27,0)) -> 1627.9837 | O31: =+N31 -> 1627.9837
B32: Rightfoot | C32: Financial | D32: =INDEX('Investment Characteristics'!$F$4:$F$35,MATCH('Reserves old2'!$B32,'Investment Characteristics'!$B$4:$B$35,0)) -> 399999.32 | E32: =F32-D32 -> 0 | F32: =INDEX('Statement of Investments'!$L$5:$L$226,MATCH(B32,'Statement of Investments'!$E$5:$E$226,0)) -> 399999.32 | H32: 0 | I32: =H32+F32 -> 399999.32 | K32: =+INDEX('Investment Characteristics'!$L$4:$L$30,MATCH('Reserves old2'!$B32,'Investment Characteristics'!$K$4:$K$30,0)) -> A | L32: =+INDEX('Investment Characteristics'!$Q$4:$Q$24,MATCH('Reserves old2'!$B32,'Investment Characteristics'!$K$4:$K$24,0)) -> 55000000 | M32: =+INDEX('Investment Characteristics'!$P$4:$P$27,MATCH('Reserves old2'!B32,'Investment Characteristics'!$K$4:$K$27,0)) -> 31800000 | N32: =+INDEX('Investment Characteristics'!$V$4:$V$27,MATCH('Reserves old2'!B32,'Investment Characteristics'!$K$4:$K$27,0)) -> 5889.4968 | O32: =+N32 -> 5889.4968 | P32: "lost faith"
B34: Series B
B35: Ashby | D35: =INDEX('Investment Characteristics'!$F$4:$F$35,MATCH('Reserves old2'!$B35,'Investment Characteristics'!$B$4:$B$35,0)) -> 3000000 | E35: =F35-D35 -> 2000000 | F35: =INDEX('Statement of Investments'!$L$5:$L$226,MATCH(B35,'Statement of Investments'!$E$5:$E$226,0)) -> 5000000 | I35: =H35+F35 -> 5000000 | K35: =+INDEX('Investment Characteristics'!$L$4:$L$30,MATCH('Reserves old2'!$B35,'Investment Characteristics'!$K$4:$K$30,0)) -> D | L35: =+INDEX('Investment Characteristics'!$Q$4:$Q$24,MATCH('Reserves old2'!$B35,'Investment Characteristics'!$K$4:$K$24,0)) -> #N/A | M35: =+INDEX('Investment Characteristics'!$P$4:$P$27,MATCH('Reserves old2'!B35,'Investment Characteristics'!$K$4:$K$27,0)) -> 175000000 | N35: =+INDEX('Investment Characteristics'!$V$4:$V$27,MATCH('Reserves old2'!B35,'Investment Characteristics'!$K$4:$K$27,0)) -> 3572.1674 | O35: =+O7/0.039/10^6 -> 1897.4359
B36: Origin | C36: Financial | D36: =INDEX('Investment Characteristics'!$F$4:$F$35,MATCH('Reserves old2'!$B36,'Investment Characteristics'!$B$4:$B$35,0)) -> 1699997.1 | E36: =F36-D36 -> 1999995 | F36: =INDEX('Statement of Investments'!$L$5:$L$226,MATCH(B36,'Statement of Investments'!$E$5:$E$226,0)) -> 3699992.1 | H36: 0 | I36: =H36+F36 -> 3699992.1 | K36: =+INDEX('Investment Characteristics'!$L$4:$L$30,MATCH('Reserves old2'!$B36,'Investment Characteristics'!$K$4:$K$30,0)) -> B | L36: =+INDEX('Investment Characteristics'!$Q$4:$Q$24,MATCH('Reserves old2'!$B36,'Investment Characteristics'!$K$4:$K$24,0)) -> 401250000 | M36: =+INDEX('Investment Characteristics'!$P$4:$P$27,MATCH('Reserves old2'!B36,'Investment Characteristics'!$K$4:$K$27,0)) -> 136500000 | N36: =+INDEX('Investment Characteristics'!$V$4:$V$27,MATCH('Reserves old2'!B36,'Investment Characteristics'!$K$4:$K$27,0)) -> 2730.7007 | O36: =O7/0.0225/10^6 -> 3288.8889 | P36: Valuation / stage
B37: Pinwheel | C37: Financial | D37: =INDEX('Investment Characteristics'!$F$4:$F$35,MATCH('Reserves old2'!$B37,'Investment Characteristics'!$B$4:$B$35,0)) -> 499997.04 | E37: =F37-D37 -> 953159.03 | F37: =INDEX('Statement of Investments'!$L$5:$L$226,MATCH(B37,'Statement of Investments'!$E$5:$E$226,0)) -> 1453156.1 | H37: 0 | I37: =H37+F37 -> 1453156.1 | K37: =+INDEX('Investment Characteristics'!$L$4:$L$30,MATCH('Reserves old2'!$B37,'Investment Characteristics'!$K$4:$K$30,0)) -> B | L37: =+INDEX('Investment Characteristics'!$Q$4:$Q$24,MATCH('Reserves old2'!$B37,'Investment Characteristics'!$K$4:$K$24,0)) -> 5.0637434e+08 | M37: =+INDEX('Investment Characteristics'!$P$4:$P$27,MATCH('Reserves old2'!B37,'Investment Characteristics'!$K$4:$K$27,0)) -> 250900000 | N37: =+INDEX('Investment Characteristics'!$V$4:$V$27,MATCH('Reserves old2'!B37,'Investment Characteristics'!$K$4:$K$27,0)) -> 12774.644 | O37: =+N37 -> 12774.644 | P37: Valuation / stage
B38: Path | C38: Healthtech | D38: =INDEX('Investment Characteristics'!$F$4:$F$35,MATCH('Reserves old2'!$B38,'Investment Characteristics'!$B$4:$B$35,0)) -> #N/A | E38: =F38-D38 -> #N/A | F38: =INDEX('Statement of Investments'!$L$5:$L$226,MATCH(B38,'Statement of Investments'!$E$5:$E$226,0)) -> #N/A | H38: 0 | I38: =H38+F38 -> #N/A | K38: =+INDEX('Investment Characteristics'!$L$4:$L$30,MATCH('Reserves old2'!$B38,'Investment Characteristics'!$K$4:$K$30,0)) -> #N/A | L38: =+INDEX('Investment Characteristics'!$Q$4:$Q$24,MATCH('Reserves old2'!$B38,'Investment Characteristics'!$K$4:$K$24,0)) -> #N/A | M38: =+INDEX('Investment Characteristics'!$P$4:$P$27,MATCH('Reserves old2'!B38,'Investment Characteristics'!$K$4:$K$27,0)) -> #N/A | N38: =+INDEX('Investment Characteristics'!$V$4:$V$27,MATCH('Reserves old2'!B38,'Investment Characteristics'!$K$4:$K$27,0)) -> #N/A | O38: =+N38 -> #N/A | P38: Valuation / stage
B40: Series C
B41: Brightline | C41: Healthtech | D41: =INDEX('Investment Characteristics'!$F$4:$F$35,MATCH('Reserves old2'!$B41,'Investment Characteristics'!$B$4:$B$35,0)) -> 499998.47 | E41: =F41-D41 -> 999988.57 | F41: =INDEX('Statement of Investments'!$L$5:$L$226,MATCH(B41,'Statement of Investments'!$E$5:$E$226,0)) -> 1499987 | H41: 0 | I41: =H41+F41 -> 1499987 | K41: =+INDEX('Investment Characteristics'!$L$4:$L$30,MATCH('Reserves old2'!$B41,'Investment Characteristics'!$K$4:$K$30,0)) -> C | L41: =+INDEX('Investment Characteristics'!$Q$4:$Q$24,MATCH('Reserves old2'!$B41,'Investment Characteristics'!$K$4:$K$24,0)) -> 757442906 | M41: =+INDEX('Investment Characteristics'!$P$4:$P$27,MATCH('Reserves old2'!B41,'Investment Characteristics'!$K$4:$K$27,0)) -> 248800000 | N41: =+INDEX('Investment Characteristics'!$V$4:$V$27,MATCH('Reserves old2'!B41,'Investment Characteristics'!$K$4:$K$27,0)) -> 12271.857 | O41: =+N41 -> 12271.857 | P41: Valuation / stage
B42: Cleo | C42: Healthtech | D42: =INDEX('Investment Characteristics'!$F$4:$F$35,MATCH('Reserves old2'!$B42,'Investment Characteristics'!$B$4:$B$35,0)) -> 599997.84 | E42: =F42-D42 -> 0 | F42: =INDEX('Statement of Investments'!$L$5:$L$226,MATCH(B42,'Statement of Investments'!$E$5:$E$226,0)) -> 599997.84 | H42: 0 | I42: =H42+F42 -> 599997.84 | K42: =+INDEX('Investment Characteristics'!$L$4:$L$30,MATCH('Reserves old2'!$B42,'Investment Characteristics'!$K$4:$K$30,0)) -> C | L42: =+INDEX('Investment Characteristics'!$Q$4:$Q$24,MATCH('Reserves old2'!$B42,'Investment Characteristics'!$K$4:$K$24,0)) -> 231000000 | M42: =+INDEX('Investment Characteristics'!$P$4:$P$27,MATCH('Reserves old2'!B42,'Investment Characteristics'!$K$4:$K$27,0)) -> 148300000 | N42: =+INDEX('Investment Characteristics'!$V$4:$V$27,MATCH('Reserves old2'!B42,'Investment Characteristics'!$K$4:$K$27,0)) -> 18289.403 | O42: =+N42 -> 18289.403 | P42: Valuation / stage
B43: Galileo | C43: Healthtech | D43: =INDEX('Investment Characteristics'!$F$4:$F$35,MATCH('Reserves old2'!$B43,'Investment Characteristics'!$B$4:$B$35,0)) -> 1999999.2 | E43: =F43-D43 -> 163902.45 | F43: =INDEX('Statement of Investments'!$L$5:$L$226,MATCH(B43,'Statement of Investments'!$E$5:$E$226,0)) -> 2163901.7 | H43: 0 | I43: =H43+F43 -> 2163901.7 | K43: =+INDEX('Investment Characteristics'!$L$4:$L$30,MATCH('Reserves old2'!$B43,'Investment Characteristics'!$K$4:$K$30,0)) -> E | L43: =+INDEX('Investment Characteristics'!$Q$4:$Q$24,MATCH('Reserves old2'!$B43,'Investment Characteristics'!$K$4:$K$24,0)) -> 361500000 | M43: =+INDEX('Investment Characteristics'!$P$4:$P$27,MATCH('Reserves old2'!B43,'Investment Characteristics'!$K$4:$K$27,0)) -> 517000000 | N43: =+INDEX('Investment Characteristics'!$V$4:$V$27,MATCH('Reserves old2'!B43,'Investment Characteristics'!$K$4:$K$27,0)) -> 17679.304 | O43: =+N43 -> 17679.304 | P43: Valuation / stage
B44: Nayya | C44: Healthtech | D44: =INDEX('Investment Characteristics'!$F$4:$F$35,MATCH('Reserves old2'!$B44,'Investment Characteristics'!$B$4:$B$35,0)) -> 500000 | E44: =F44-D44 -> 2199987.1 | F44: =INDEX('Statement of Investments'!$L$5:$L$226,MATCH(B44,'Statement of Investments'!$E$5:$E$226,0)) -> 2699987.1 | H44: 0 | I44: =H44+F44 -> 2699987.1 | K44: =+INDEX('Investment Characteristics'!$L$4:$L$30,MATCH('Reserves old2'!$B44,'Investment Characteristics'!$K$4:$K$30,0)) -> C | L44: =+INDEX('Investment Characteristics'!$Q$4:$Q$24,MATCH('Reserves old2'!$B44,'Investment Characteristics'!$K$4:$K$24,0)) -> 5.049535e+08 | M44: =+INDEX('Investment Characteristics'!$P$4:$P$27,MATCH('Reserves old2'!B44,'Investment Characteristics'!$K$4:$K$27,0)) -> 352300000 | N44: =+INDEX('Investment Characteristics'!$V$4:$V$27,MATCH('Reserves old2'!B44,'Investment Characteristics'!$K$4:$K$27,0)) -> 9655.9806 | O44: =+N44 -> 9655.9806 | P44: Valuation / stage
B45: Remote | C45: Workforce | D45: =INDEX('Investment Characteristics'!$F$4:$F$35,MATCH('Reserves old2'!$B45,'Investment Characteristics'!$B$4:$B$35,0)) -> 3999979.6 | E45: =F45-D45 -> 781466.31 | F45: =INDEX('Statement of Investments'!$L$5:$L$226,MATCH(B45,'Statement of Investments'!$E$5:$E$226,0)) -> 4781446 | H45: 0 | I45: =H45+F45 -> 4781446 | K45: =+INDEX('Investment Characteristics'!$L$4:$L$30,MATCH('Reserves old2'!$B45,'Investment Characteristics'!$K$4:$K$30,0)) -> C | L45: =+INDEX('Investment Characteristics'!$Q$4:$Q$24,MATCH('Reserves old2'!$B45,'Investment Characteristics'!$K$4:$K$24,0)) -> 3000000000 | M45: =+INDEX('Investment Characteristics'!$P$4:$P$27,MATCH('Reserves old2'!B45,'Investment Characteristics'!$K$4:$K$27,0)) -> 1328200000 | N45: =+INDEX('Investment Characteristics'!$V$4:$V$27,MATCH('Reserves old2'!B45,'Investment Characteristics'!$K$4:$K$27,0)) -> 20555.664 | O45: =+N45 -> 20555.664 | P45: Valuation / stage
B47: Total | D47: =SUM(D11:D46) -> #N/A | E47: =SUM(E11:E46) -> #N/A | F47: =SUM(F11:F46) -> #N/A | H47: =SUM(H11:H46) -> 8500000 | I47: =SUM(I11:I46) -> #N/A
D48: =+D47/F47 -> #N/A | E48: =+E47/F47 -> #N/A

Sheet Reserves
G3: Initial | I3: Total
B4: Company | C4: Current Stage | D4: Ownership | E4: Last Valuation | G4: $ Invested | H4: Follow-Ons | I4: $ Invested | K4: Reserves | L4: Inv. and Reserved
B5: Brightline | C5: =INDEX('Investment Characteristics'!$L$4:$L$32,MATCH(Reserves!$B5,'Investment Characteristics'!$K$4:$K$32,0)) -> C | D5: =INDEX('Investment Characteristics'!$N$4:$N$32,MATCH(Reserves!$B5,'Investment Characteristics'!$K$4:$K$32,0)) -> 0.0060300575 | E5: =INDEX('Investment Characteristics'!$Q$4:$Q$32,MATCH(Reserves!$B5,'Investment Characteristics'!$K$4:$K$32,0)) -> 757442906 | G5: =INDEX('Investment Characteristics'!$F$4:$F$32,MATCH(Reserves!$B5,'Investment Characteristics'!$B$4:$B$32,0)) -> 499998.47 | H5: =I5-G5 -> 999988.57 | I5: =INDEX('Investment Characteristics'!$S$4:$S$32,MATCH(Reserves!$B5,'Investment Characteristics'!$B$4:$B$32,0)) -> 1499987 | K5: 0 | L5: =I5+K5 -> 1499987
B6: Murmur | C6: =INDEX('Investment Characteristics'!$L$4:$L$32,MATCH(Reserves!$B6,'Investment Characteristics'!$K$4:$K$32,0)) -> Seed | D6: =INDEX('Investment Characteristics'!$N$4:$N$32,MATCH(Reserves!$B6,'Investment Characteristics'!$K$4:$K$32,0)) -> 0.064069691 | E6: =INDEX('Investment Characteristics'!$Q$4:$Q$32,MATCH(Reserves!$B6,'Investment Characteristics'!$K$4:$K$32,0)) -> 28000000 | G6: =INDEX('Investment Characteristics'!$F$4:$F$32,MATCH(Reserves!$B6,'Investment Characteristics'!$B$4:$B$32,0)) -> 225000 | H6: =I6-G6 -> 1349998 | I6: =INDEX('Investment Characteristics'!$S$4:$S$32,MATCH(Reserves!$B6,'Investment Characteristics'!$B$4:$B$32,0)) -> 1574998 | K6: 0 | L6: =I6+K6 -> 1574998
B7: Pinwheel | C7: =INDEX('Investment Characteristics'!$L$4:$L$32,MATCH(Reserves!$B7,'Investment Characteristics'!$K$4:$K$32,0)) -> B | D7: =INDEX('Investment Characteristics'!$N$4:$N$32,MATCH(Reserves!$B7,'Investment Characteristics'!$K$4:$K$32,0)) -> 0.0057927248 | E7: =INDEX('Investment Characteristics'!$Q$4:$Q$32,MATCH(Reserves!$B7,'Investment Characteristics'!$K$4:$K$32,0)) -> 5.0637434e+08 | G7: =INDEX('Investment Characteristics'!$F$4:$F$32,MATCH(Reserves!$B7,'Investment Characteristics'!$B$4:$B$32,0)) -> 499997.04 | H7: =I7-G7 -> 953159.03 | I7: =INDEX('Investment Characteristics'!$S$4:$S$32,MATCH(Reserves!$B7,'Investment Characteristics'!$B$4:$B$32,0)) -> 1453156.1 | K7: 0 | L7: =I7+K7 -> 1453156.1
B8: Cleo | C8: =INDEX('Investment Characteristics'!$L$4:$L$32,MATCH(Reserves!$B8,'Investment Characteristics'!$K$4:$K$32,0)) -> C | D8: =INDEX('Investment Characteristics'!$N$4:$N$32,MATCH(Reserves!$B8,'Investment Characteristics'!$K$4:$K$32,0)) -> 0.0040460588 | E8: =INDEX('Investment Characteristics'!$Q$4:$Q$32,MATCH(Reserves!$B8,'Investment Characteristics'!$K$4:$K$32,0)) -> 231000000 | G8: =INDEX('Investment Characteristics'!$F$4:$F$32,MATCH(Reserves!$B8,'Investment Characteristics'!$B$4:$B$32,0)) -> 599997.84 | H8: =I8-G8 -> 0 | I8: =INDEX('Investment Characteristics'!$S$4:$S$32,MATCH(Reserves!$B8,'Investment Characteristics'!$B$4:$B$32,0)) -> 599997.84 | K8: 0 | L8: =I8+K8 -> 599997.84
B9: Rightfoot | C9: =INDEX('Investment Characteristics'!$L$4:$L$32,MATCH(Reserves!$B9,'Investment Characteristics'!$K$4:$K$32,0)) -> A | D9: =INDEX('Investment Characteristics'!$N$4:$N$32,MATCH(Reserves!$B9,'Investment Characteristics'!$K$4:$K$32,0)) -> 0.012564741 | E9: =INDEX('Investment Characteristics'!$Q$4:$Q$32,MATCH(Reserves!$B9,'Investment Characteristics'!$K$4:$K$32,0)) -> 55000000 | G9: =INDEX('Investment Characteristics'!$F$4:$F$32,MATCH(Reserves!$B9,'Investment Characteristics'!$B$4:$B$32,0)) -> 399999.32 | H9: =I9-G9 -> 0 | I9: =INDEX('Investment Characteristics'!$S$4:$S$32,MATCH(Reserves!$B9,'Investment Characteristics'!$B$4:$B$32,0)) -> 399999.32 | K9: 0 | L9: =I9+K9 -> 399999.32
B10: Mathison | C10: =INDEX('Investment Characteristics'!$L$4:$L$32,MATCH(Reserves!$B10,'Investment Characteristics'!$K$4:$K$32,0)) -> Acq. | D10: =INDEX('Investment Characteristics'!$N$4:$N$32,MATCH(Reserves!$B10,'Investment Characteristics'!$K$4:$K$32,0)) -> 0.04 | E10: =INDEX('Investment Characteristics'!$Q$4:$Q$32,MATCH(Reserves!$B10,'Investment Characteristics'!$K$4:$K$32,0)) -> 70000000 | G10: =INDEX('Investment Characteristics'!$F$4:$F$32,MATCH(Reserves!$B10,'Investment Characteristics'!$B$4:$B$32,0)) -> 299999.56 | H10: =I10-G10 -> 1749994.6 | I10: =INDEX('Investment Characteristics'!$S$4:$S$32,MATCH(Reserves!$B10,'Investment Characteristics'!$B$4:$B$32,0)) -> 2049994.2 | K10: 0 | L10: =I10+K10 -> 2049994.2
B11: Galileo | C11: =INDEX('Investment Characteristics'!$L$4:$L$32,MATCH(Reserves!$B11,'Investment Characteristics'!$K$4:$K$32,0)) -> E | D11: =INDEX('Investment Characteristics'!$N$4:$N$32,MATCH(Reserves!$B11,'Investment Characteristics'!$K$4:$K$32,0)) -> 0.0041856851 | E11: =INDEX('Investment Characteristics'!$Q$4:$Q$32,MATCH(Reserves!$B11,'Investment Characteristics'!$K$4:$K$32,0)) -> 361500000 | G11: =INDEX('Investment Characteristics'!$F$4:$F$32,MATCH(Reserves!$B11,'Investment Characteristics'!$B$4:$B$32,0)) -> 1999999.2 | H11: =I11-G11 -> 163902.45 | I11: =INDEX('Investment Characteristics'!$S$4:$S$32,MATCH(Reserves!$B11,'Investment Characteristics'!$B$4:$B$32,0)) -> 2163901.7 | K11: 0 | L11: =I11+K11 -> 2163901.7
B12: Cocoon | C12: =INDEX('Investment Characteristics'!$L$4:$L$32,MATCH(Reserves!$B12,'Investment Characteristics'!$K$4:$K$32,0)) -> A | D12: =INDEX('Investment Characteristics'!$N$4:$N$32,MATCH(Reserves!$B12,'Investment Characteristics'!$K$4:$K$32,0)) -> 0.027242491 | E12: =INDEX('Investment Characteristics'!$Q$4:$Q$32,MATCH(Reserves!$B12,'Investment Characteristics'!$K$4:$K$32,0)) -> 1.6250158e+08 | G12: =INDEX('Investment Characteristics'!$F$4:$F$32,MATCH(Reserves!$B12,'Investment Characteristics'!$B$4:$B$32,0)) -> 224999.42 | H12: =I12-G12 -> 3999997.2 | I12: =INDEX('Investment Characteristics'!$S$4:$S$32,MATCH(Reserves!$B12,'Investment Characteristics'!$B$4:$B$32,0)) -> 4224996.6 | K12: 0 | L12: =I12+K12 -> 4224996.6
B13: Rula | C13: =INDEX('Investment Characteristics'!$L$4:$L$32,MATCH(Reserves!$B13,'Investment Characteristics'!$K$4:$K$32,0)) -> C | D13: =INDEX('Investment Characteristics'!$N$4:$N$32,MATCH(Reserves!$B13,'Investment Characteristics'!$K$4:$K$32,0)) -> 0.0207 | E13: =INDEX('Investment Characteristics'!$Q$4:$Q$32,MATCH(Reserves!$B13,'Investment Characteristics'!$K$4:$K$32,0)) -> 1250000000 | G13: =INDEX('Investment Characteristics'!$F$4:$F$32,MATCH(Reserves!$B13,'Investment Characteristics'!$B$4:$B$32,0)) -> 1500000 | H13: =I13-G13 -> 3000000 | I13: =INDEX('Investment Characteristics'!$S$4:$S$32,MATCH(Reserves!$B13,'Investment Characteristics'!$B$4:$B$32,0)) -> 4500000 | K13: 0 | L13: =I13+K13 -> 4500000
B14: Origin | C14: =INDEX('Investment Characteristics'!$L$4:$L$32,MATCH(Reserves!$B14,'Investment Characteristics'!$K$4:$K$32,0)) -> B | D14: =INDEX('Investment Characteristics'!$N$4:$N$32,MATCH(Reserves!$B14,'Investment Characteristics'!$K$4:$K$32,0)) -> 0.027099272 | E14: =INDEX('Investment Characteristics'!$Q$4:$Q$32,MATCH(Reserves!$B14,'Investment Characteristics'!$K$4:$K$32,0)) -> 401250000 | G14: =INDEX('Investment Characteristics'!$F$4:$F$32,MATCH(Reserves!$B14,'Investment Characteristics'!$B$4:$B$32,0)) -> 1699997.1 | H14: =I14-G14 -> 1999995 | I14: =INDEX('Investment Characteristics'!$S$4:$S$32,MATCH(Reserves!$B14,'Investment Characteristics'!$B$4:$B$32,0)) -> 3699992.1 | K14: 0 | L14: =I14+K14 -> 3699992.1
B15: Nayya | C15: =INDEX('Investment Characteristics'!$L$4:$L$32,MATCH(Reserves!$B15,'Investment Characteristics'!$K$4:$K$32,0)) -> C | D15: =INDEX('Investment Characteristics'!$N$4:$N$32,MATCH(Reserves!$B15,'Investment Characteristics'!$K$4:$K$32,0)) -> 0.0076636442 | E15: =INDEX('Investment Characteristics'!$Q$4:$Q$32,MATCH(Reserves!$B15,'Investment Characteristics'!$K$4:$K$32,0)) -> 5.049535e+08 | G15: =INDEX('Investment Characteristics'!$F$4:$F$32,MATCH(Reserves!$B15,'Investment Characteristics'!$B$4:$B$32,0)) -> 500000 | H15: =I15-G15 -> 2199987.1 | I15: =INDEX('Investment Characteristics'!$S$4:$S$32,MATCH(Reserves!$B15,'Investment Characteristics'!$B$4:$B$32,0)) -> 2699987.1 | K15: 0 | L15: =I15+K15 -> 2699987.1
B16: Praisidio | C16: =INDEX('Investment Characteristics'!$L$4:$L$32,MATCH(Reserves!$B16,'Investment Characteristics'!$K$4:$K$32,0)) -> Seed | D16: =INDEX('Investment Characteristics'!$N$4:$N$32,MATCH(Reserves!$B16,'Investment Characteristics'!$K$4:$K$32,0)) -> 0.01 | E16: =INDEX('Investment Characteristics'!$Q$4:$Q$32,MATCH(Reserves!$B16,'Investment Characteristics'!$K$4:$K$32,0)) -> 20000000 | G16: =INDEX('Investment Characteristics'!$F$4:$F$32,MATCH(Reserves!$B16,'Investment Characteristics'!$B$4:$B$32,0)) -> 200000 | H16: =I16-G16 -> 0 | I16: =INDEX('Investment Characteristics'!$S$4:$S$32,MATCH(Reserves!$B16,'Investment Characteristics'!$B$4:$B$32,0)) -> 200000 | K16: 0 | L16: =I16+K16 -> 200000
... B33: Easop | C33: =INDEX('Investment Characteristics'!$L$4:$L$32,MATCH(Reserves!$B33,'Investment Characteristics'!$K$4:$K$32,0)) -> Acq. | D33: =INDEX('Investment Characteristics'!$N$4:$N$32,MATCH(Reserves!$B33,'Investment Characteristics'!$K$4:$K$32,0)) -> 0.066666667 | E33: =INDEX('Investment Characteristics'!$Q$4:$Q$32,MATCH(Reserves!$B33,'Investment Characteristics'!$K$4:$K$32,0)) -> 15000000 | G33: =INDEX('Investment Characteristics'!$F$4:$F$32,MATCH(Reserves!$B33,'Investment Characteristics'!$B$4:$B$32,0)) -> 1000000 | H33: =I33-G33 -> 0 | I33: =INDEX('Investment Characteristics'!$S$4:$S$32,MATCH(Reserves!$B33,'Investment Characteristics'!$B$4:$B$32,0)) -> 1000000 | K33: 0 | L33: =I33+K33 -> 1000000
G34: =SUM(G5:G32) -> 36310084 | H34: =SUM(H5:H32) -> 30471813 | I34: =SUM(I5:I32) -> 66781898 | K34: =SUM(K5:K32) -> 0 | L34: =SUM(L5:L32) -> 66781898
N64: =3/5 -> 0.6

Sheet Reserves old
D2: Initial | F2: Total | G2: Portfolio | I2: =J38 -> 6277500 | K2: Portfolio
B3: Company | C3: Sector | D3: $ Invested | E3: Follow-Ons | F3: $ Invested | G3: Allocation | I3: Reserves | J3: Total+Reserves | K3: Allocation | M3: Current Stage | N3: Avg. Cost | O3: Last Valuation
B4: Brightline | C4: Healthtech | D4: =INDEX('Investment Characteristics'!$F$4:$F$35,MATCH('Reserves old'!$B4,'Investment Characteristics'!$B$4:$B$35,0)) -> 499998.47 | E4: =F4-D4 -> 999988.57 | F4: =INDEX('Statement of Investments'!$L$5:$L$226,MATCH(B4,'Statement of Investments'!$E$5:$E$226,0)) -> 1499987 | G4: =F4/$F$31 -> #N/A | I4: 0 | J4: =I4+F4 -> 1499987 | K4: =J4/$J$32 -> 0.020270095 | M4: =INDEX('Investment Characteristics'!$L$4:$L$33,MATCH('Reserves old'!$B4,'Investment Characteristics'!$K$4:$K$33,0)) -> C | N4: =INDEX('Investment Characteristics'!$P$4:$P$33,MATCH('Reserves old'!$B4,'Investment Characteristics'!$K$4:$K$33,0)) -> 248800000 | O4: =INDEX('Investment Characteristics'!$Q$4:$Q$33,MATCH('Reserves old'!$B4,'Investment Characteristics'!$K$4:$K$33,0)) -> 757442906
B5: Murmur | C5: Workforce | D5: =INDEX('Investment Characteristics'!$F$4:$F$35,MATCH('Reserves old'!$B5,'Investment Characteristics'!$B$4:$B$35,0)) -> 225000 | E5: =F5-D5 -> 1349998 | F5: =INDEX('Statement of Investments'!$L$5:$L$226,MATCH(B5,'Statement of Investments'!$E$5:$E$226,0)) -> 1574998 | G5: =F5/$F$31 -> #N/A | I5: 0 | J5: =I5+F5 -> 1574998 | K5: =J5/$J$32 -> 0.021283757 | M5: =INDEX('Investment Characteristics'!$L$4:$L$33,MATCH('Reserves old'!$B5,'Investment Characteristics'!$K$4:$K$33,0)) -> Seed | N5: =O5 -> 28000000 | O5: =INDEX('Investment Characteristics'!$Q$4:$Q$33,MATCH('Reserves old'!$B5,'Investment Characteristics'!$K$4:$K$33,0)) -> 28000000
B6: Pinwheel | C6: Financial | D6: =INDEX('Investment Characteristics'!$F$4:$F$35,MATCH('Reserves old'!$B6,'Investment Characteristics'!$B$4:$B$35,0)) -> 499997.04 | E6: =F6-D6 -> 953159.03 | F6: =INDEX('Statement of Investments'!$L$5:$L$226,MATCH(B6,'Statement of Investments'!$E$5:$E$226,0)) -> 1453156.1 | G6: =F6/$F$31 -> #N/A | I6: 0 | J6: =I6+F6 -> 1453156.1 | K6: =J6/$J$32 -> 0.019637244 | M6: =INDEX('Investment Characteristics'!$L$4:$L$33,MATCH('Reserves old'!$B6,'Investment Characteristics'!$K$4:$K$33,0)) -> B | N6: =INDEX('Investment Characteristics'!$P$4:$P$33,MATCH('Reserves old'!$B6,'Investment Characteristics'!$K$4:$K$33,0)) -> 250900000 | O6: =INDEX('Investment Characteristics'!$Q$4:$Q$33,MATCH('Reserves old'!$B6,'Investment Characteristics'!$K$4:$K$33,0)) -> 5.0637434e+08
B7: Cleo | C7: Healthtech | D7: =INDEX('Investment Characteristics'!$F$4:$F$35,MATCH('Reserves old'!$B7,'Investment Characteristics'!$B$4:$B$35,0)) -> 599997.84 | E7: =F7-D7 -> 0 | F7: =INDEX('Statement of Investments'!$L$5:$L$226,MATCH(B7,'Statement of Investments'!$E$5:$E$226,0)) -> 599997.84 | G7: =F7/$F$31 -> #N/A | I7: 0 | J7: =I7+F7 -> 599997.84 | K7: =J7/$J$32 -> 0.0081080789 | M7: =INDEX('Investment Characteristics'!$L$4:$L$33,MATCH('Reserves old'!$B7,'Investment Characteristics'!$K$4:$K$33,0)) -> C | N7: =INDEX('Investment Characteristics'!$P$4:$P$33,MATCH('Reserves old'!$B7,'Investment Characteristics'!$K$4:$K$33,0)) -> 148300000 | O7: =INDEX('Investment Characteristics'!$Q$4:$Q$33,MATCH('Reserves old'!$B7,'Investment Characteristics'!$K$4:$K$33,0)) -> 231000000
B8: Rightfoot | C8: Financial | D8: =INDEX('Investment Characteristics'!$F$4:$F$35,MATCH('Reserves old'!$B8,'Investment Characteristics'!$B$4:$B$35,0)) -> 399999.32 | E8: =F8-D8 -> 0 | F8: =INDEX('Statement of Investments'!$L$5:$L$226,MATCH(B8,'Statement of Investments'!$E$5:$E$226,0)) -> 399999.32 | G8: =F8/$F$31 -> #N/A | I8: 0 | J8: =I8+F8 -> 399999.32 | K8: =J8/$J$32 -> 0.0054053962 | M8: =INDEX('Investment Characteristics'!$L$4:$L$33,MATCH('Reserves old'!$B8,'Investment Characteristics'!$K$4:$K$33,0)) -> A | N8: =INDEX('Investment Characteristics'!$P$4:$P$33,MATCH('Reserves old'!$B8,'Investment Characteristics'!$K$4:$K$33,0)) -> 31800000 | O8: =INDEX('Investment Characteristics'!$Q$4:$Q$33,MATCH('Reserves old'!$B8,'Investment Characteristics'!$K$4:$K$33,0)) -> 55000000
B9: Mathison | C9: Workforce | D9: =INDEX('Investment Characteristics'!$F$4:$F$35,MATCH('Reserves old'!$B9,'Investment Characteristics'!$B$4:$B$35,0)) -> 299999.56 | E9: =F9-D9 -> 1749994.6 | F9: =INDEX('Statement of Investments'!$L$5:$L$226,MATCH(B9,'Statement of Investments'!$E$5:$E$226,0)) -> 2049994.2 | G9: =F9/$F$31 -> #N/A | I9: 0 | J9: =I9+F9 -> 2049994.2 | K9: =J9/$J$32 -> 0.027702624 | M9: =INDEX('Investment Characteristics'!$L$4:$L$33,MATCH('Reserves old'!$B9,'Investment Characteristics'!$K$4:$K$33,0)) -> Acq. | N9: =INDEX('Investment Characteristics'!$P$4:$P$33,MATCH('Reserves old'!$B9,'Investment Characteristics'!$K$4:$K$33,0)) -> 51200000 | O9: =INDEX('Investment Characteristics'!$Q$4:$Q$33,MATCH('Reserves old'!$B9,'Investment Characteristics'!$K$4:$K$33,0)) -> 70000000
B10: Galileo | C10: Healthtech | D10: =INDEX('Investment Characteristics'!$F$4:$F$35,MATCH('Reserves old'!$B10,'Investment Characteristics'!$B$4:$B$35,0)) -> 1999999.2 | E10: =F10-D10 -> 163902.45 | F10: =INDEX('Statement of Investments'!$L$5:$L$226,MATCH(B10,'Statement of Investments'!$E$5:$E$226,0)) -> 2163901.7 | G10: =F10/$F$31 -> #N/A | I10: 0 | J10: =I10+F10 -> 2163901.7 | K10: =J10/$J$32 -> 0.029241914 | M10: =INDEX('Investment Characteristics'!$L$4:$L$33,MATCH('Reserves old'!$B10,'Investment Characteristics'!$K$4:$K$33,0)) -> E | N10: =INDEX('Investment Characteristics'!$P$4:$P$33,MATCH('Reserves old'!$B10,'Investment Characteristics'!$K$4:$K$33,0)) -> 517000000 | O10: =INDEX('Investment Characteristics'!$Q$4:$Q$33,MATCH('Reserves old'!$B10,'Investment Characteristics'!$K$4:$K$33,0)) -> 361500000
B11: Cocoon | C11: Workforce | D11: =INDEX('Investment Characteristics'!$F$4:$F$35,MATCH('Reserves old'!$B11,'Investment Characteristics'!$B$4:$B$35,0)) -> 224999.42 | E11: =F11-D11 -> 3999997.2 | F11: =INDEX('Statement of Investments'!$L$5:$L$226,MATCH(B11,'Statement of Investments'!$E$5:$E$226,0)) -> 4224996.6 | G11: =F11/$F$31 -> #N/A | I11: =3*10^6 -> 3000000 | J11: =I11+F11 -> 7224996.6 | K11: =J11/$J$32 -> 0.097635089 | M11: =INDEX('Investment Characteristics'!$L$4:$L$33,MATCH('Reserves old'!$B11,'Investment Characteristics'!$K$4:$K$33,0)) -> A | N11: =INDEX('Investment Characteristics'!$P$4:$P$33,MATCH('Reserves old'!$B11,'Investment Characteristics'!$K$4:$K$33,0)) -> 155100000 | O11: =INDEX('Investment Characteristics'!$Q$4:$Q$33,MATCH('Reserves old'!$B11,'Investment Characteristics'!$K$4:$K$33,0)) -> 1.6250158e+08
B12: Path | C12: Healthtech | D12: =INDEX('Investment Characteristics'!$F$4:$F$35,MATCH('Reserves old'!$B12,'Investment Characteristics'!$B$4:$B$35,0)) -> #N/A | E12: =F12-D12 -> #N/A | F12: =INDEX('Statement of Investments'!$L$5:$L$226,MATCH(B12,'Statement of Investments'!$E$5:$E$226,0)) -> #N/A | G12: =F12/$F$31 -> #N/A | I12: 0 | J12: =I12+F12 -> #N/A | K12: =J12/$J$32 -> #N/A | M12: =INDEX('Investment Characteristics'!$L$4:$L$33,MATCH('Reserves old'!$B12,'Investment Characteristics'!$K$4:$K$33,0)) -> #N/A | N12: =INDEX('Investment Characteristics'!$P$4:$P$33,MATCH('Reserves old'!$B12,'Investment Characteristics'!$K$4:$K$33,0)) -> #N/A | O12: =INDEX('Investment Characteristics'!$Q$4:$Q$33,MATCH('Reserves old'!$B12,'Investment Characteristics'!$K$4:$K$33,0)) -> #N/A
B13: Origin | C13: Financial | D13: =INDEX('Investment Characteristics'!$F$4:$F$35,MATCH('Reserves old'!$B13,'Investment Characteristics'!$B$4:$B$35,0)) -> 1699997.1 | E13: =F13-D13 -> 1999995 | F13: =INDEX('Statement of Investments'!$L$5:$L$226,MATCH(B13,'Statement of Investments'!$E$5:$E$226,0)) -> 3699992.1 | G13: =F13/$F$31 -> #N/A | I13: 0 | J13: =I13+F13 -> 3699992.1 | K13: =J13/$J$32 -> 0.049999893 | M13: =INDEX('Investment Characteristics'!$L$4:$L$33,MATCH('Reserves old'!$B13,'Investment Characteristics'!$K$4:$K$33,0)) -> B | N13: =INDEX('Investment Characteristics'!$P$4:$P$33,MATCH('Reserves old'!$B13,'Investment Characteristics'!$K$4:$K$33,0)) -> 136500000 | O13: =INDEX('Investment Characteristics'!$Q$4:$Q$33,MATCH('Reserves old'!$B13,'Investment Characteristics'!$K$4:$K$33,0)) -> 401250000
B14: Nayya | C14: Healthtech | D14: =INDEX('Investment Characteristics'!$F$4:$F$35,MATCH('Reserves old'!$B14,'Investment Characteristics'!$B$4:$B$35,0)) -> 500000 | E14: =F14-D14 -> 2199987.1 | F14: =INDEX('Statement of Investments'!$L$5:$L$226,MATCH(B14,'Statement of Investments'!$E$5:$E$226,0)) -> 2699987.1 | G14: =F14/$F$31 -> #N/A | I14: 0 | J14: =I14+F14 -> 2699987.1 | K14: =J14/$J$32 -> 0.036486312 | M14: =INDEX('Investment Characteristics'!$L$4:$L$33,MATCH('Reserves old'!$B14,'Investment Characteristics'!$K$4:$K$33,0)) -> C | N14: =O14 -> 5.049535e+08 | O14: =INDEX('Investment Characteristics'!$Q$4:$Q$33,MATCH('Reserves old'!$B14,'Investment Characteristics'!$K$4:$K$33,0)) -> 5.049535e+08
B15: Praisidio | C15: Workforce | D15: =INDEX('Investment Characteristics'!$F$4:$F$35,MATCH('Reserves old'!$B15,'Investment Characteristics'!$B$4:$B$35,0)) -> 200000 | E15: =F15-D15 -> 0 | F15: =INDEX('Statement of Investments'!$L$5:$L$226,MATCH(B15,'Statement of Investments'!$E$5:$E$226,0)) -> 200000 | G15: =F15/$F$31 -> #N/A | I15: 0 | J15: =I15+F15 -> 200000 | K15: =J15/$J$32 -> 0.0027027027 | M15: =INDEX('Investment Characteristics'!$L$4:$L$33,MATCH('Reserves old'!$B15,'Investment Characteristics'!$K$4:$K$33,0)) -> Seed | N15: =INDEX('Investment Characteristics'!$P$4:$P$33,MATCH('Reserves old'!$B15,'Investment Characteristics'!$K$4:$K$33,0)) -> 20000000 | O15: =INDEX('Investment Characteristics'!$Q$4:$Q$33,MATCH('Reserves old'!$B15,'Investment Characteristics'!$K$4:$K$33,0)) -> 20000000
B16: Bravely | C16: Workforce | D16: =INDEX('Investment Characteristics'!$F$4:$F$35,MATCH('Reserves old'!$B16,'Investment Characteristics'!$B$4:$B$35,0)) -> 1249999.6 | E16: =F16-D16 -> 0 | F16: =INDEX('Statement of Investments'!$L$5:$L$226,MATCH(B16,'Statement of Investments'!$E$5:$E$226,0)) -> 1249999.6 | G16: =F16/$F$31 -> #N/A | I16: =1.75*10^6 -> 1750000 | J16: =I16+F16 -> 2999999.5 | K16: =J16/$J$32 -> 0.040540534 | M16: =INDEX('Investment Characteristics'!$L$4:$L$33,MATCH('Reserves old'!$B16,'Investment Characteristics'!$K$4:$K$33,0)) -> A | N16: =INDEX('Investment Characteristics'!$P$4:$P$33,MATCH('Reserves old'!$B16,'Investment Characteristics'!$K$4:$K$33,0)) -> 67500000 | O16: =INDEX('Investment Characteristics'!$Q$4:$Q$33,MATCH('Reserves old'!$B16,'Investment Characteristics'!$K$4:$K$33,0)) -> 67500000
B17: Remote | C17: Workforce | D17: =INDEX('Investment Characteristics'!$F$4:$F$35,MATCH('Reserves old'!$B17,'Investment Characteristics'!$B$4:$B$35,0)) -> 3999979.6 | E17: =F17-D17 -> 781466.31 | F17: =INDEX('Statement of Investments'!$L$5:$L$226,MATCH(B17,'Statement of Investments'!$E$5:$E$226,0)) -> 4781446 | G17: =F17/$F$31 -> #N/A | I17: 0 | J17: =I17+F17 -> 4781446 | K17: =J17/$J$32 -> 0.064614135 | M17: =INDEX('Investment Characteristics'!$L$4:$L$33,MATCH('Reserves old'!$B17,'Investment Characteristics'!$K$4:$K$33,0)) -> C | N17: =INDEX('Investment Characteristics'!$P$4:$P$33,MATCH('Reserves old'!$B17,'Investment Characteristics'!$K$4:$K$33,0)) -> 1328200000 | O17: =INDEX('Investment Characteristics'!$Q$4:$Q$33,MATCH('Reserves old'!$B17,'Investment Characteristics'!$K$4:$K$33,0)) -> 3000000000
B18: Finch | C18: Financial | D18: =INDEX('Investment Characteristics'!$F$4:$F$35,MATCH('Reserves old'!$B18,'Investment Characteristics'!$B$4:$B$35,0)) -> 500003.42 | E18: =F18-D18 -> 0 | F18: =INDEX('Statement of Investments'!$L$5:$L$226,MATCH(B18,'Statement of Investments'!$E$5:$E$226,0)) -> 500003.42 | G18: =F18/$F$31 -> #N/A | I18: =2*10^6 -> 2000000 | J18: =I18+F18 -> 2500003.4 | K18: =J18/$J$32 -> 0.03378383 | M18: =INDEX('Investment Characteristics'!$L$4:$L$33,MATCH('Reserves old'!$B18,'Investment Characteristics'!$K$4:$K$33,0)) -> B | N18: =INDEX('Investment Characteristics'!$P$4:$P$33,MATCH('Reserves old'!$B18,'Investment Characteristics'!$K$4:$K$33,0)) -> 155300000 | O18: =INDEX('Investment Characteristics'!$Q$4:$Q$33,MATCH('Reserves old'!$B18,'Investment Characteristics'!$K$4:$K$33,0)) -> 230000392
B19: Plenish | C19: Healthtech | D19: =INDEX('Investment Characteristics'!$F$4:$F$35,MATCH('Reserves old'!$B19,'Investment Characteristics'!$B$4:$B$35,0)) -> #N/A | E19: =F19-D19 -> #N/A | F19: =INDEX('Statement of Investments'!$L$5:$L$226,MATCH(B19,'Statement of Investments'!$E$5:$E$226,0)) -> #N/A | G19: =F19/$F$31 -> #N/A | I19: =2.5*10^6 -> 2500000 | J19: =I19+F19 -> #N/A | K19: =J19/$J$32 -> #N/A | M19: =INDEX('Investment Characteristics'!$L$4:$L$33,MATCH('Reserves old'!$B19,'Investment Characteristics'!$K$4:$K$33,0)) -> #N/A | N19: =INDEX('Investment Characteristics'!$P$4:$P$33,MATCH('Reserves old'!$B19,'Investment Characteristics'!$K$4:$K$33,0)) -> #N/A | O19: =INDEX('Investment Characteristics'!$Q$4:$Q$33,MATCH('Reserves old'!$B19,'Investment Characteristics'!$K$4:$K$33,0)) -> #N/A
B20: ianacare | D20: =INDEX('Investment Characteristics'!$F$4:$F$35,MATCH('Reserves old'!$B20,'Investment Characteristics'!$B$4:$B$35,0)) -> 999984.87 | E20: =F20-D20 -> 2000000 | F20: =INDEX('Statement of Investments'!$L$5:$L$226,MATCH(B20,'Statement of Investments'!$E$5:$E$226,0)) -> 2999984.9 | G20: =F20/$F$31 -> #N/A | I20: 2000000 | J20: =I20+F20 -> 4999984.9 | K20: =J20/$J$32 -> 0.067567363 | M20: =INDEX('Investment Characteristics'!$L$4:$L$33,MATCH('Reserves old'!$B20,'Investment Characteristics'!$K$4:$K$33,0)) -> A | N20: =INDEX('Investment Characteristics'!$P$4:$P$33,MATCH('Reserves old'!$B20,'Investment Characteristics'!$K$4:$K$33,0)) -> 60000000 | O20: =INDEX('Investment Characteristics'!$Q$4:$Q$33,MATCH('Reserves old'!$B20,'Investment Characteristics'!$K$4:$K$33,0)) -> 60000000
B21: Vivante | D21: =INDEX('Investment Characteristics'!$F$4:$F$35,MATCH('Reserves old'!$B21,'Investment Characteristics'!$B$4:$B$35,0)) -> 999999 | E21: =F21-D21 -> 1204143.3 | F21: =INDEX('Statement of Investments'!$L$5:$L$226,MATCH(B21,'Statement of Investments'!$E$5:$E$226,0)) -> 2204142.3 | G21: =F21/$F$31 -> #N/A | I21: =2*10^6 -> 2000000 | J21: =I21+F21 -> 4204142.3 | K21: =J21/$J$32 -> 0.056812734 | M21: =INDEX('Investment Characteristics'!$L$4:$L$33,MATCH('Reserves old'!$B21,'Investment Characteristics'!$K$4:$K$33,0)) -> B | N21: =INDEX('Investment Characteristics'!$P$4:$P$33,MATCH('Reserves old'!$B21,'Investment Characteristics'!$K$4:$K$33,0)) -> 59300000 | O21: =INDEX('Investment Characteristics'!$Q$4:$Q$33,MATCH('Reserves old'!$B21,'Investment Characteristics'!$K$4:$K$33,0)) -> 84077296
B22: a.team | D22: =INDEX('Investment Characteristics'!$F$4:$F$35,MATCH('Reserves old'!$B22,'Investment Characteristics'!$B$4:$B$35,0)) -> 999998.86 | E22: =F22-D22 -> 0 | F22: =INDEX('Statement of Investments'!$L$5:$L$226,MATCH(B22,'Statement of Investments'!$E$5:$E$226,0)) -> 999998.86 | G22: =F22/$F$31 -> #N/A | I22: 0 | J22: =I22+F22 -> 999998.86 | K22: =J22/$J$32 -> 0.013513498 | M22: =INDEX('Investment Characteristics'!$L$4:$L$33,MATCH('Reserves old'!$B22,'Investment Characteristics'!$K$4:$K$33,0)) -> A | N22: =INDEX('Investment Characteristics'!$P$4:$P$33,MATCH('Reserves old'!$B22,'Investment Characteristics'!$K$4:$K$33,0)) -> 325000000 | O22: =INDEX('Investment Characteristics'!$Q$4:$Q$33,MATCH('Reserves old'!$B22,'Investment Characteristics'!$K$4:$K$33,0)) -> 325000000
B23: CoverGo | D23: =INDEX('Investment Characteristics'!$F$4:$F$35,MATCH('Reserves old'!$B23,'Investment Characteristics'!$B$4:$B$35,0)) -> 2000000 | E23: =F23-D23 -> 2000000 | F23: =INDEX('Statement of Investments'!$L$5:$L$226,MATCH(B23,'Statement of Investments'!$E$5:$E$226,0)) -> 4000000 | G23: =F23/$F$31 -> #N/A | I23: =F23 -> 4000000 | J23: =I23+F23 -> 8000000 | K23: =J23/$J$32 -> 0.10810811 | M23: =INDEX('Investment Characteristics'!$L$4:$L$33,MATCH('Reserves old'!$B23,'Investment Characteristics'!$K$4:$K$33,0)) -> A | N23: =INDEX('Investment Characteristics'!$P$4:$P$33,MATCH('Reserves old'!$B23,'Investment Characteristics'!$K$4:$K$33,0)) -> 43000000 | O23: =INDEX('Investment Characteristics'!$Q$4:$Q$33,MATCH('Reserves old'!$B23,'Investment Characteristics'!$K$4:$K$33,0)) -> 43000000
B24: Ashby | D24: =INDEX('Investment Characteristics'!$F$4:$F$35,MATCH('Reserves old'!$B24,'Investment Characteristics'!$B$4:$B$35,0)) -> 3000000 | E24: =F24-D24 -> 2000000 | F24: =INDEX('Statement of Investments'!$L$5:$L$226,MATCH(B24,'Statement of Investments'!$E$5:$E$226,0)) -> 5000000 | G24: =F24/$F$31 -> #N/A | I24: 0 | J24: =I24+F24 -> 5000000 | K24: =J24/$J$32 -> 0.067567568 | M24: =INDEX('Investment Characteristics'!$L$4:$L$33,MATCH('Reserves old'!$B24,'Investment Characteristics'!$K$4:$K$33,0)) -> D | N24: =INDEX('Investment Characteristics'!$P$4:$P$33,MATCH('Reserves old'!$B24,'Investment Characteristics'!$K$4:$K$33,0)) -> 175000000 | O24: =INDEX('Investment Characteristics'!$Q$4:$Q$33,MATCH('Reserves old'!$B24,'Investment Characteristics'!$K$4:$K$33,0)) -> 500000000
B25: Delfina | D25: =INDEX('Investment Characteristics'!$F$4:$F$35,MATCH('Reserves old'!$B25,'Investment Characteristics'!$B$4:$B$35,0)) -> 800000 | E25: =F25-D25 -> 749999.92 | F25: =INDEX('Statement of Investments'!$L$5:$L$226,MATCH(B25,'Statement of Investments'!$E$5:$E$226,0)) -> 1549999.9 | G25: =F25/$F$31 -> #N/A | I25: =2*10^6 -> 2000000 | J25: =I25+F25 -> 3549999.9 | K25: =J25/$J$32 -> 0.047972972 | M25: =INDEX('Investment Characteristics'!$L$4:$L$33,MATCH('Reserves old'!$B25,'Investment Characteristics'!$K$4:$K$33,0)) -> A | N25: =INDEX('Investment Characteristics'!$P$4:$P$33,MATCH('Reserves old'!$B25,'Investment Characteristics'!$K$4:$K$33,0)) -> 15000000 | O25: =INDEX('Investment Characteristics'!$Q$4:$Q$33,MATCH('Reserves old'!$B25,'Investment Characteristics'!$K$4:$K$33,0)) -> 52000000
B31: Total | D31: =SUM(D4:D29) -> #N/A | E31: =SUM(E4:E29) -> #N/A | F31: =SUM(F4:F30) -> #N/A | G31: =SUM(G4:G30) -> #N/A | I31: =SUM(I4:I30) -> 19250000 | J31: =SUM(J4:J30) -> #N/A
I32: Fund Size | J32: =74*10^6 -> 74000000
I33: Invested+Reserved | J33: =J31/J32 -> #N/A
I34: Amt. Remainig | J34: =J32-J31 -> #N/A
I35: Avg Deal Size | J35: =J41 -> 3000000
I36: Deals Remaining | J36: =(J32-J31)/J35 -> #N/A
I38: 5 Yrs. Mgmt Fees | J38: =(J32-11225000)*0.02*5 -> 6277500
I39: I + R net of 3yr fees | J39: =J31/(J32-J38) -> #N/A
I40: Amt. Remainig | J40: =J32-J38-J31 -> #N/A
I41: Avg Deal Size | J41: =3*10^6 -> 3000000
I42: Deals Remaining | J42: =(J32-J31-J38)/J41 -> #N/A
B49: Company | C49: Sector | D49: $ Invested | E49: Follow-Ons | F49: $ Invested | G49: Allocation | I49: Reserves | J49: Total+Reserves | K49: Allocation | M49: Current Stage | N49: Avg. Cost | O49: Last Valuation | P49: Reasoning
B51: Seed
B52: Murmur | C52: Workforce | D52: =INDEX('Investment Characteristics'!$F$4:$F$35,MATCH('Reserves old'!$B52,'Investment Characteristics'!$B$4:$B$35,0)) -> 225000 | E52: =F52-D52 -> 1349998 | F52: =INDEX('Statement of Investments'!$L$5:$L$226,MATCH(B52,'Statement of Investments'!$E$5:$E$226,0)) -> 1574998 | G52: 0.0091028574 | I52: 0 | J52: =I52+F52 -> 1574998 | K52: 0.0043918919 | M52: =+INDEX('Investment Characteristics'!$L$4:$L$24,MATCH('Reserves old'!$B52,'Investment Characteristics'!$K$4:$K$24,0)) -> Seed | N52: 8500000 | O52: =+INDEX('Investment Characteristics'!$Q$4:$Q$24,MATCH('Reserves old'!$B52,'Investment Characteristics'!$K$4:$K$24,0)) -> 28000000 | P52: "interested"
B53: Midi | C53: Healthtech | D53: =INDEX('Investment Characteristics'!$F$4:$F$35,MATCH('Reserves old'!$B53,'Investment Characteristics'!$B$4:$B$35,0)) -> 510137 | E53: =F53-D53 -> 5021370 | F53: =INDEX('Statement of Investments'!$L$5:$L$226,MATCH(B53,'Statement of Investments'!$E$5:$E$226,0)) -> 5531507 | G53: 0.014004396 | I53: 3000000 | J53: =I53+F53 -> 8531507 | K53: 0.040540541 | M53: =+INDEX('Investment Characteristics'!$L$4:$L$24,MATCH('Reserves old'!$B53,'Investment Characteristics'!$K$4:$K$24,0)) -> D | N53: 10000000 | O53: =+INDEX('Investment Characteristics'!$Q$4:$Q$24,MATCH('Reserves old'!$B53,'Investment Characteristics'!$K$4:$K$24,0)) -> 1150000000 | P53: "Greg getting crazy"
B54: Delfina | D54: =INDEX('Investment Characteristics'!$F$4:$F$35,MATCH('Reserves old'!$B54,'Investment Characteristics'!$B$4:$B$35,0)) -> 800000 | E54: =F54-D54 -> 749999.92 | F54: =INDEX('Statement of Investments'!$L$5:$L$226,MATCH(B54,'Statement of Investments'!$E$5:$E$226,0)) -> 1549999.9 | G54: 0.022407034 | I54: 2000000 | J54: =I54+F54 -> 3549999.9 | K54: 0.037837838 | M54: =+INDEX('Investment Characteristics'!$L$4:$L$24,MATCH('Reserves old'!$B54,'Investment Characteristics'!$K$4:$K$24,0)) -> A | N54: 15000000 | O54: =+INDEX('Investment Characteristics'!$Q$4:$Q$24,MATCH('Reserves old'!$B54,'Investment Characteristics'!$K$4:$K$24,0)) -> 52000000
B55: Praisidio | C55: Workforce | D55: =INDEX('Investment Characteristics'!$F$4:$F$35,MATCH('Reserves old'!$B55,'Investment Characteristics'!$B$4:$B$35,0)) -> 200000 | E55: =F55-D55 -> 0 | F55: =INDEX('Statement of Investments'!$L$5:$L$226,MATCH(B55,'Statement of Investments'!$E$5:$E$226,0)) -> 200000 | G55: 0.0056017584 | I55: 0 | J55: =I55+F55 -> 200000 | K55: 0.0027027027 | M55: =+INDEX('Investment Characteristics'!$L$4:$L$24,MATCH('Reserves old'!$B55,'Investment Characteristics'!$K$4:$K$24,0)) -> Seed | N55: 20000000 | O55: =+INDEX('Investment Characteristics'!$Q$4:$Q$24,MATCH('Reserves old'!$B55,'Investment Characteristics'!$K$4:$K$24,0)) -> 20000000 | P55: "not seeing evidence they are breaking out"
B56: Violet | D56: =INDEX('Investment Characteristics'!$F$4:$F$35,MATCH('Reserves old'!$B56,'Investment Characteristics'!$B$4:$B$35,0)) -> 2599995.3 | E56: =F56-D56 -> 0 | F56: =INDEX('Statement of Investments'!$L$5:$L$226,MATCH(B56,'Statement of Investments'!$E$5:$E$226,0)) -> 2599995.3 | G56: 0.011203498 | I56: =+F56 -> 2599995.3 | J56: =I56+F56 -> 5199990.5 | K56: 0.0054053962 | M56: =+INDEX('Investment Characteristics'!$L$4:$L$27,MATCH('Reserves old'!$B56,'Investment Characteristics'!$K$4:$K$27,0)) -> Seed | N56: 20000000 | O56: =+INDEX('Investment Characteristics'!$Q$4:$Q$27,MATCH('Reserves old'!$B56,'Investment Characteristics'!$K$4:$K$27,0)) -> 22000000 | P56: Led the round, need to reserve
B58: Series A
B59: Vivante | D59: =INDEX('Investment Characteristics'!$F$4:$F$35,MATCH('Reserves old'!$B59,'Investment Characteristics'!$B$4:$B$35,0)) -> 999999 | E59: =F59-D59 -> 1204143.3 | F59: =INDEX('Statement of Investments'!$L$5:$L$226,MATCH(B59,'Statement of Investments'!$E$5:$E$226,0)) -> 2204142.3 | G59: 0.028008764 | I59: 2000000 | J59: =I59+F59 -> 4204142.3 | K59: 0.040540527 | M59: =+INDEX('Investment Characteristics'!$L$4:$L$24,MATCH('Reserves old'!$B59,'Investment Characteristics'!$K$4:$K$24,0)) -> B | N59: 21800000 | O59: =+INDEX('Investment Characteristics'!$Q$4:$Q$24,MATCH('Reserves old'!$B59,'Investment Characteristics'!$K$4:$K$24,0)) -> 84077296
B60: CoverGo | D60: =INDEX('Investment Characteristics'!$F$4:$F$35,MATCH('Reserves old'!$B60,'Investment Characteristics'!$B$4:$B$35,0)) -> 2000000 | E60: =F60-D60 -> 2000000 | F60: =INDEX('Statement of Investments'!$L$5:$L$226,MATCH(B60,'Statement of Investments'!$E$5:$E$226,0)) -> 4000000 | G60: 0.056017584 | I60: 2000000 | J60: =I60+F60 -> 6000000 | K60: 0.054054054 | M60: =+INDEX('Investment Characteristics'!$L$4:$L$24,MATCH('Reserves old'!$B60,'Investment Characteristics'!$K$4:$K$24,0)) -> A | N60: 35000000 | O60: =+INDEX('Investment Characteristics'!$Q$4:$Q$24,MATCH('Reserves old'!$B60,'Investment Characteristics'!$K$4:$K$24,0)) -> 43000000 | P60: $2M committed if CoverGo reaches ARR target
B61: ianacare | D61: =INDEX('Investment Characteristics'!$F$4:$F$35,MATCH('Reserves old'!$B61,'Investment Characteristics'!$B$4:$B$35,0)) -> 999984.87 | E61: =F61-D61 -> 2000000 | F61: =INDEX('Statement of Investments'!$L$5:$L$226,MATCH(B61,'Statement of Investments'!$E$5:$E$226,0)) -> 2999984.9 | G61: 0.028008368 | I61: 2000000 | J61: =I61+F61 -> 4999984.9 | K61: 0.040540336 | M61: =+INDEX('Investment Characteristics'!$L$4:$L$24,MATCH('Reserves old'!$B61,'Investment Characteristics'!$K$4:$K$24,0)) -> A | N61: 60000000 | O61: =+INDEX('Investment Characteristics'!$Q$4:$Q$24,MATCH('Reserves old'!$B61,'Investment Characteristics'!$K$4:$K$24,0)) -> 60000000 | P61: "allison: we should def reserve" / might do (more) in GOF2
B62: Bravely | C62: Workforce | D62: =INDEX('Investment Characteristics'!$F$4:$F$35,MATCH('Reserves old'!$B62,'Investment Characteristics'!$B$4:$B$35,0)) -> 1249999.6 | E62: =F62-D62 -> 0 | F62: =INDEX('Statement of Investments'!$L$5:$L$226,MATCH(B62,'Statement of Investments'!$E$5:$E$226,0)) -> 1249999.6 | G62: 0.035010977 | I62: 0 | J62: =I62+F62 -> 1249999.6 | K62: 0.040540534 | M62: =+INDEX('Investment Characteristics'!$L$4:$L$24,MATCH('Reserves old'!$B62,'Investment Characteristics'!$K$4:$K$24,0)) -> A | N62: 67500000 | O62: =+INDEX('Investment Characteristics'!$Q$4:$Q$24,MATCH('Reserves old'!$B62,'Investment Characteristics'!$K$4:$K$24,0)) -> 67500000 | P62: "nope"
B63: Mathison | C63: Workforce | D63: =INDEX('Investment Characteristics'!$F$4:$F$35,MATCH('Reserves old'!$B63,'Investment Characteristics'!$B$4:$B$35,0)) -> 299999.56 | E63: =F63-D63 -> 1749994.6 | F63: =INDEX('Statement of Investments'!$L$5:$L$226,MATCH(B63,'Statement of Investments'!$E$5:$E$226,0)) -> 2049994.2 | G63: 0.057417861 | I63: 0 | J63: =I63+F63 -> 2049994.2 | K63: 0.027702624 | M63: =+INDEX('Investment Characteristics'!$L$4:$L$24,MATCH('Reserves old'!$B63,'Investment Characteristics'!$K$4:$K$24,0)) -> Acq. | N63: 69200000 | O63: =+INDEX('Investment Characteristics'!$Q$4:$Q$24,MATCH('Reserves old'!$B63,'Investment Characteristics'!$K$4:$K$24,0)) -> 70000000
B64: Finch | C64: Financial | D64: =INDEX('Investment Characteristics'!$F$4:$F$35,MATCH('Reserves old'!$B64,'Investment Characteristics'!$B$4:$B$35,0)) -> 500003.42 | E64: =F64-D64 -> 0 | F64: =INDEX('Statement of Investments'!$L$5:$L$226,MATCH(B64,'Statement of Investments'!$E$5:$E$226,0)) -> 500003.42 | G64: 0.014004492 | I64: 0 | J64: =I64+F64 -> 500003.42 | K64: 0.03378383 | M64: =+INDEX('Investment Characteristics'!$L$4:$L$24,MATCH('Reserves old'!$B64,'Investment Characteristics'!$K$4:$K$24,0)) -> B | N64: 115000000 | O64: =+INDEX('Investment Characteristics'!$Q$4:$Q$24,MATCH('Reserves old'!$B64,'Investment Characteristics'!$K$4:$K$24,0)) -> 230000392 | P64: Low ownership to date and high-upside
B65: Cocoon | C65: Workforce | D65: =INDEX('Investment Characteristics'!$F$4:$F$35,MATCH('Reserves old'!$B65,'Investment Characteristics'!$B$4:$B$35,0)) -> 224999.42 | E65: =F65-D65 -> 3999997.2 | F65: =INDEX('Statement of Investments'!$L$5:$L$226,MATCH(B65,'Statement of Investments'!$E$5:$E$226,0)) -> 4224996.6 | G65: 0.034310679 | I65: 2000000 | J65: =I65+F65 -> 6224996.6 | K65: 0.05709455 | M65: =+INDEX('Investment Characteristics'!$L$4:$L$24,MATCH('Reserves old'!$B65,'Investment Characteristics'!$K$4:$K$24,0)) -> A | N65: 97900000 | O65: =+INDEX('Investment Characteristics'!$Q$4:$Q$24,MATCH('Reserves old'!$B65,'Investment Characteristics'!$K$4:$K$24,0)) -> 1.6250158e+08 | P65: Low ownership to date and high-upside
B66: a.team | D66: =INDEX('Investment Characteristics'!$F$4:$F$35,MATCH('Reserves old'!$B66,'Investment Characteristics'!$B$4:$B$35,0)) -> 999998.86 | E66: =F66-D66 -> 0 | F66: =INDEX('Statement of Investments'!$L$5:$L$226,MATCH(B66,'Statement of Investments'!$E$5:$E$226,0)) -> 999998.86 | G66: 0.02800876 | I66: 0 | J66: =I66+F66 -> 999998.86 | K66: 0.013513498 | M66: =+INDEX('Investment Characteristics'!$L$4:$L$24,MATCH('Reserves old'!$B66,'Investment Characteristics'!$K$4:$K$24,0)) -> A | N66: 325000000 | O66: =+INDEX('Investment Characteristics'!$Q$4:$Q$24,MATCH('Reserves old'!$B66,'Investment Characteristics'!$K$4:$K$24,0)) -> 325000000
B67: Mosey | D67: =INDEX('Investment Characteristics'!$F$4:$F$35,MATCH('Reserves old'!$B67,'Investment Characteristics'!$B$4:$B$35,0)) -> 3999998.9 | E67: =F67-D67 -> 0 | F67: =INDEX('Statement of Investments'!$L$5:$L$226,MATCH(B67,'Statement of Investments'!$E$5:$E$226,0)) -> 3999998.9 | I67: 0 | J67: =I67+F67 -> 3999998.9 | M67: A | O67: =90*10^6 -> 90000000
B68: Rightfoot | C68: Financial | D68: =INDEX('Investment Characteristics'!$F$4:$F$35,MATCH('Reserves old'!$B68,'Investment Characteristics'!$B$4:$B$35,0)) -> 399999.32 | E68: =F68-D68 -> 0 | F68: =INDEX('Statement of Investments'!$L$5:$L$226,MATCH(B68,'Statement of Investments'!$E$5:$E$226,0)) -> 399999.32 | G68: 0.011203498 | I68: 0 | J68: =I68+F68 -> 399999.32 | K68: 0.0054053962 | M68: =+INDEX('Investment Characteristics'!$L$4:$L$24,MATCH('Reserves old'!$B68,'Investment Characteristics'!$K$4:$K$24,0)) -> A | N68: 20000000 | O68: =+INDEX('Investment Characteristics'!$Q$4:$Q$24,MATCH('Reserves old'!$B68,'Investment Characteristics'!$K$4:$K$24,0)) -> 55000000 | P68: "lost faith"
B70: Series B
B71: Ashby | D71: =INDEX('Investment Characteristics'!$F$4:$F$35,MATCH('Reserves old'!$B71,'Investment Characteristics'!$B$4:$B$35,0)) -> 3000000 | E71: =F71-D71 -> 2000000 | F71: =INDEX('Statement of Investments'!$L$5:$L$226,MATCH(B71,'Statement of Investments'!$E$5:$E$226,0)) -> 5000000 | G71: 0.084026376 | I71: 0 | J71: =I71+F71 -> 5000000 | K71: 0.040540541 | M71: =+INDEX('Investment Characteristics'!$L$4:$L$24,MATCH('Reserves old'!$B71,'Investment Characteristics'!$K$4:$K$24,0)) -> #N/A | N71: 175000000 | O71: =+INDEX('Investment Characteristics'!$Q$4:$Q$24,MATCH('Reserves old'!$B71,'Investment Characteristics'!$K$4:$K$24,0)) -> #N/A
B72: Origin | C72: Financial | D72: =INDEX('Investment Characteristics'!$F$4:$F$35,MATCH('Reserves old'!$B72,'Investment Characteristics'!$B$4:$B$35,0)) -> 1699997.1 | E72: =F72-D72 -> 1999995 | F72: =INDEX('Statement of Investments'!$L$5:$L$226,MATCH(B72,'Statement of Investments'!$E$5:$E$226,0)) -> 3699992.1 | G72: 0.10363231 | I72: 0 | J72: =I72+F72 -> 3699992.1 | K72: 0.049999893 | M72: =+INDEX('Investment Characteristics'!$L$4:$L$24,MATCH('Reserves old'!$B72,'Investment Characteristics'!$K$4:$K$24,0)) -> B | N72: 228200000 | O72: =+INDEX('Investment Characteristics'!$Q$4:$Q$24,MATCH('Reserves old'!$B72,'Investment Characteristics'!$K$4:$K$24,0)) -> 401250000 | P72: Valuation / stage
B73: Pinwheel | C73: Financial | D73: =INDEX('Investment Characteristics'!$F$4:$F$35,MATCH('Reserves old'!$B73,'Investment Characteristics'!$B$4:$B$35,0)) -> 499997.04 | E73: =F73-D73 -> 953159.03 | F73: =INDEX('Statement of Investments'!$L$5:$L$226,MATCH(B73,'Statement of Investments'!$E$5:$E$226,0)) -> 1453156.1 | G73: 0.040701146 | I73: 0 | J73: =I73+F73 -> 1453156.1 | K73: 0.019637244 | M73: =+INDEX('Investment Characteristics'!$L$4:$L$24,MATCH('Reserves old'!$B73,'Investment Characteristics'!$K$4:$K$24,0)) -> B | N73: 237600000 | O73: =+INDEX('Investment Characteristics'!$Q$4:$Q$24,MATCH('Reserves old'!$B73,'Investment Characteristics'!$K$4:$K$24,0)) -> 5.0637434e+08 | P73: Valuation / stage
B74: Path | C74: Healthtech | D74: =INDEX('Investment Characteristics'!$F$4:$F$35,MATCH('Reserves old'!$B74,'Investment Characteristics'!$B$4:$B$35,0)) -> #N/A | E74: =F74-D74 -> #N/A | F74: =INDEX('Statement of Investments'!$L$5:$L$226,MATCH(B74,'Statement of Investments'!$E$5:$E$226,0)) -> #N/A | G74: 0.12603956 | I74: 0 | J74: =I74+F74 -> #N/A | K74: 0.060810811 | M74: =+INDEX('Investment Characteristics'!$L$4:$L$24,MATCH('Reserves old'!$B74,'Investment Characteristics'!$K$4:$K$24,0)) -> #N/A | N74: 171000000 | O74: =+INDEX('Investment Characteristics'!$Q$4:$Q$24,MATCH('Reserves old'!$B74,'Investment Characteristics'!$K$4:$K$24,0)) -> #N/A | P74: Valuation / stage
B76: Series C
B77: Brightline | C77: Healthtech | D77: =INDEX('Investment Characteristics'!$F$4:$F$35,MATCH('Reserves old'!$B77,'Investment Characteristics'!$B$4:$B$35,0)) -> 499998.47 | E77: =F77-D77 -> 999988.57 | F77: =INDEX('Statement of Investments'!$L$5:$L$226,MATCH(B77,'Statement of Investments'!$E$5:$E$226,0)) -> 1499987 | G77: 0.042012825 | I77: 0 | J77: =I77+F77 -> 1499987 | K77: 0.020270095 | M77: =+INDEX('Investment Characteristics'!$L$4:$L$24,MATCH('Reserves old'!$B77,'Investment Characteristics'!$K$4:$K$24,0)) -> C | N77: 193600000 | O77: =+INDEX('Investment Characteristics'!$Q$4:$Q$24,MATCH('Reserves old'!$B77,'Investment Characteristics'!$K$4:$K$24,0)) -> 757442906 | P77: Valuation / stage
B78: Cleo | C78: Healthtech | D78: =INDEX('Investment Characteristics'!$F$4:$F$35,MATCH('Reserves old'!$B78,'Investment Characteristics'!$B$4:$B$35,0)) -> 599997.84 | E78: =F78-D78 -> 0 | F78: =INDEX('Statement of Investments'!$L$5:$L$226,MATCH(B78,'Statement of Investments'!$E$5:$E$226,0)) -> 599997.84 | G78: 0.016805215 | I78: 0 | J78: =I78+F78 -> 599997.84 | K78: 0.0081080789 | M78: =+INDEX('Investment Characteristics'!$L$4:$L$24,MATCH('Reserves old'!$B78,'Investment Characteristics'!$K$4:$K$24,0)) -> C | N78: 148300000 | O78: =+INDEX('Investment Characteristics'!$Q$4:$Q$24,MATCH('Reserves old'!$B78,'Investment Characteristics'!$K$4:$K$24,0)) -> 231000000 | P78: Valuation / stage
B79: Galileo | C79: Healthtech | D79: =INDEX('Investment Characteristics'!$F$4:$F$35,MATCH('Reserves old'!$B79,'Investment Characteristics'!$B$4:$B$35,0)) -> 1999999.2 | E79: =F79-D79 -> 163902.45 | F79: =INDEX('Statement of Investments'!$L$5:$L$226,MATCH(B79,'Statement of Investments'!$E$5:$E$226,0)) -> 2163901.7 | G79: 0.056017562 | I79: 0 | J79: =I79+F79 -> 2163901.7 | K79: 0.027027016 | M79: =+INDEX('Investment Characteristics'!$L$4:$L$24,MATCH('Reserves old'!$B79,'Investment Characteristics'!$K$4:$K$24,0)) -> E | N79: 395000000 | O79: =+INDEX('Investment Characteristics'!$Q$4:$Q$24,MATCH('Reserves old'!$B79,'Investment Characteristics'!$K$4:$K$24,0)) -> 361500000 | P79: Valuation / stage
B80: Nayya | C80: Healthtech | D80: =INDEX('Investment Characteristics'!$F$4:$F$35,MATCH('Reserves old'!$B80,'Investment Characteristics'!$B$4:$B$35,0)) -> 500000 | E80: =F80-D80 -> 2199987.1 | F80: =INDEX('Statement of Investments'!$L$5:$L$226,MATCH(B80,'Statement of Investments'!$E$5:$E$226,0)) -> 2699987.1 | G80: 0.075623378 | I80: 0 | J80: =I80+F80 -> 2699987.1 | K80: 0.036486312 | M80: =+INDEX('Investment Characteristics'!$L$4:$L$24,MATCH('Reserves old'!$B80,'Investment Characteristics'!$K$4:$K$24,0)) -> C | N80: 4.8781374e+08 | O80: =+INDEX('Investment Characteristics'!$Q$4:$Q$24,MATCH('Reserves old'!$B80,'Investment Characteristics'!$K$4:$K$24,0)) -> 5.049535e+08 | P80: Valuation / stage
B81: Remote | C81: Workforce | D81: =INDEX('Investment Characteristics'!$F$4:$F$35,MATCH('Reserves old'!$B81,'Investment Characteristics'!$B$4:$B$35,0)) -> 3999979.6 | E81: =F81-D81 -> 781466.31 | F81: =INDEX('Statement of Investments'!$L$5:$L$226,MATCH(B81,'Statement of Investments'!$E$5:$E$226,0)) -> 4781446 | G81: 0.1120346 | I81: 0 | J81: =I81+F81 -> 4781446 | K81: 0.054053779 | M81: =+INDEX('Investment Characteristics'!$L$4:$L$24,MATCH('Reserves old'!$B81,'Investment Characteristics'!$K$4:$K$24,0)) -> C | N81: 1111100000 | O81: =+INDEX('Investment Characteristics'!$Q$4:$Q$24,MATCH('Reserves old'!$B81,'Investment Characteristics'!$K$4:$K$24,0)) -> 3000000000 | P81: Valuation / stage
D83: =SUM(D52:D82) -> #N/A | E83: =SUM(E52:E82) -> #N/A | F83: =SUM(F52:F82) -> #N/A | I83: =SUM(I52:I82) -> 15599995 | J83: =SUM(J52:J82) -> #N/A
I84: Fund Size | J84: 74000000
F85: 20000000 | I85: 3 Yrs. Fees | J85: 3359850
F86: =+F85/J84 -> 0.27027027 | I86: Remaining Capital | J86: =+J84-J83-J85 -> #N/A

Sheet Sheet1
B2: Invested Capital | C2: =40703070.94+2600000 -> 43303071
B4: Net Cash | C4: 11155435
B5: Callable Capital | C5: 15884916
B6: Pending New Inv.
B7: Reserved | C7: =-'Reserves old'!I83 -> -15599995
B8: 3 Yrs. Fees
B9: Net Capital | C9: =SUM(C4:C8) -> 11440356
B11: Avg. Deal | C11: =2.5*10^6 -> 2500000
B12: Deals Remaining | C12: =+C9/C11 -> 4.5761423

Sheet Fund Pacing
B2: Fund Size | C2: =50*10^6 -> 50000000
B3: Reserve % | C3: 0.5
B4: Average Total Investment | C4: =1.75*10^6 -> 1750000
B5: Investment Period (mos) | C5: 36
B6: Investment Start Date | C6: 44044
B8: Initial Capital Deployed | C8: =C2*C3 -> 25000000
B9: Number of Deals | C9: =ROUND(C2/C4,0) -> 29
B10: Investment Conclusion Date | C10: =EDATE(C6,C5) -> 45139
C14: =C6 -> 44044 | D14: =EDATE(C14,1) -> 44075 | E14: =EDATE(D14,1) -> 44105 | F14: =EDATE(E14,1) -> 44136 | G14: =EDATE(F14,1) -> 44166 | H14: =EDATE(G14,1) -> 44197 | I14: =EDATE(H14,1) -> 44228 | J14: =EDATE(I14,1) -> 44256 | K14: =EDATE(J14,1) -> 44287 | ... AL14: =EDATE(AK14,1) -> 45108
B15: Forecasted $ Invested | C15: =$C$8/$C$5 -> 694444.44 | D15: =$C$8/$C$5 -> 694444.44 | E15: =$C$8/$C$5 -> 694444.44 | F15: =$C$8/$C$5 -> 694444.44 | G15: =$C$8/$C$5 -> 694444.44 | H15: =$C$8/$C$5 -> 694444.44 | I15: =$C$8/$C$5 -> 694444.44 | J15: =$C$8/$C$5 -> 694444.44 | ... AL15: =$C$8/$C$5 -> 694444.44
B16: Forecasted Cumulative $ Invested | C16: =SUM($C$15:C15) -> 694444.44 | D16: =SUM($C$15:D15) -> 1388888.9 | E16: =SUM($C$15:E15) -> 2083333.3 | F16: =SUM($C$15:F15) -> 2777777.8 | G16: =SUM($C$15:G15) -> 3472222.2 | H16: =SUM($C$15:H15) -> 4166666.7 | I16: =SUM($C$15:I15) -> 4861111.1 | J16: =SUM($C$15:J15) -> 5555555.6 | ... AL16: =SUM($C$15:AL15) -> 25000000
B17: Forecasted # Invested | C17: =$C$9/$C$5 -> 0.80555556 | D17: =$C$9/$C$5 -> 0.80555556 | E17: =$C$9/$C$5 -> 0.80555556 | F17: =$C$9/$C$5 -> 0.80555556 | G17: =$C$9/$C$5 -> 0.80555556 | H17: =$C$9/$C$5 -> 0.80555556 | I17: =$C$9/$C$5 -> 0.80555556 | J17: =$C$9/$C$5 -> 0.80555556 | ... AL17: =$C$9/$C$5 -> 0.80555556
B18: Forecasted Cumulative # Invested | C18: =SUM($C$17:C17) -> 0.80555556 | D18: =SUM($C$17:D17) -> 1.6111111 | E18: =SUM($C$17:E17) -> 2.4166667 | F18: =SUM($C$17:F17) -> 3.2222222 | G18: =SUM($C$17:G17) -> 4.0277778 | H18: =SUM($C$17:H17) -> 4.8333333 | I18: =SUM($C$17:I17) -> 5.6388889 | J18: =SUM($C$17:J17) -> 6.4444444 | ... AL18: =SUM($C$17:AL17) -> 29
B20: Actual $ Invested | C20: 499998.47 | D20: 225000 | E20: 499997.04 | F20: =600000+C31+C32 -> 1350000
B21: Actual Cumulative $ Invested | C21: =SUM($C$20:C20) -> 499998.47 | D21: =SUM($C$20:D20) -> 724998.47 | E21: =SUM($C$20:E20) -> 1224995.5 | F21: =SUM($C$20:F20) -> 2574995.5
B22: Actual # Invested | C22: 1 | D22: 1 | E22: 1 | F22: 3
B23: Actual Cumulative # Invested | C23: =SUM($C$22:C22) -> 1 | D23: =SUM($C$22:D22) -> 2 | E23: =SUM($C$22:E22) -> 3 | F23: =SUM($C$22:F22) -> 6
B25: $ Pacing | C25: =IF(C21=0,"",C21-C16) -> -194445.97 | D25: =IF(D21=0,"",D21-D16) -> -663890.42 | E25: =IF(E21=0,"",E21-E16) -> -858337.82 | F25: =IF(F21=0,"",F21-F16) -> -202782.27 | G25: =IF(G21=0,"",G21-G16) | H25: =IF(H21=0,"",H21-H16) | I25: =IF(I21=0,"",I21-I16) | J25: =IF(J21=0,"",J21-J16) | ... AM25: =IF(AM21=0,"",AM21-AM16)
B26: # Pacing | C26: =IF(C23=0,"",C23-C18) -> 0.19444444 | D26: =IF(D23=0,"",D23-D18) -> 0.38888889 | E26: =IF(E23=0,"",E23-E18) -> 0.58333333 | F26: =IF(F23=0,"",F23-F18) -> 2.7777778 | G26: =IF(G23=0,"",G23-G18) | H26: =IF(H23=0,"",H23-H18) | I26: =IF(I23=0,"",I23-I18) | J26: =IF(J23=0,"",J23-J18) | ... AM26: =IF(AM23=0,"",AM23-AM18)
B29: Prospective Investments
B30: Company | C30: Amount | D30: Estimated Date
B31: Rightfoot | C31: =0.4*10^6 -> 400000 | D31: 44136
B32: Mathison | C32: =0.35*10^6 -> 350000 | D32: 44136

Sheet Exit Forecast
B1: 9.30.2025
B3: Exit Forecast
H4: Revenue | N4: 0.25 | O4: 0.5 | P4: 0.25
B5: Company | C5: Partner | D5: Current Stage | E5: Ownership | F5: Total Inv. | G5: Mkt. Value | H5: 2023A | I5: 2024A | J5: 2025E | K5: ARR as of Q2 25 | L5: 3 Yr CAGR | M5: Holding Value | N5: Bear | O5: Base | P5: Bull | Q5: Weighted Exit | R5: Exit Ownership | S5: Exit Proceeds | T5: Exit MOIC
B6: Rula | C6: CT | D6: C | E6: 0.022 | F6: =INDEX('Statement of Investments'!$L$5:$L$220,MATCH($B6,'Statement of Investments'!$E$5:$E$220,0)) -> 4500000 | G6: =INDEX('Statement of Investments'!$O$5:$O$220,MATCH($B6,'Statement of Investments'!$E$5:$E$220,0)) -> 25285301 | H6: 56849444 | I6: 121610895 | J6: 224398598 | K6: 6.6489927e+08 | L6: 0.99 | M6: 1250000000 | N6: 1250000000 | O6: 2000000000 | P6: 5000000000 | Q6: =(N6*$N$4)+(O6*$O$4)+(P6*$P$4) -> 2562500000 | R6: 0.01979 | S6: =Q6*R6 -> 50711875 | T6: =S6/F6 -> 11.269306
B7: Midi | C7: ABG | D7: B | E7: 0.059 | F7: =INDEX('Statement of Investments'!$L$5:$L$220,MATCH($B7,'Statement of Investments'!$E$5:$E$220,0)) -> 5531507 | G7: =INDEX('Statement of Investments'!$O$5:$O$220,MATCH($B7,'Statement of Investments'!$E$5:$E$220,0)) -> 48185999 | H7: 6973971 | I7: 37586650 | J7: 110174020 | K7: 125604000 | L7: 2.97 | M7: 1150000000 | N7: 750000000 | O7: 3000000000 | P7: 6000000000 | Q7: =(N7*$N$4)+(O7*$O$4)+(P7*$P$4) -> 3187500000 | R7: 0.04681 | S7: =Q7*R7 -> 149206875 | T7: =S7/F7 -> 26.974001
B8: Remote | C8: RP | D8: C | E8: 0.004 | F8: =INDEX('Statement of Investments'!$L$5:$L$220,MATCH($B8,'Statement of Investments'!$E$5:$E$220,0)) -> 4781446 | G8: =INDEX('Statement of Investments'!$O$5:$O$220,MATCH($B8,'Statement of Investments'!$E$5:$E$220,0)) -> 10354762 | H8: – | I8: – | J8: – | K8: - | L8: - | M8: 3000000000 | N8: =+M8*0.8 -> 2400000000 | O8: 5000000000 | P8: 7000000000 | Q8: =(N8*$N$4)+(O8*$O$4)+(P8*$P$4) -> 4850000000 | R8: 0.0037 | S8: =Q8*R8 -> 17945000 | T8: =S8/F8 -> 3.7530488
B9: Origin | C9: CT | D9: B | E9: 0.027 | F9: =INDEX('Statement of Investments'!$L$5:$L$220,MATCH($B9,'Statement of Investments'!$E$5:$E$220,0)) -> 3699992.1 | G9: =INDEX('Statement of Investments'!$O$5:$O$220,MATCH($B9,'Statement of Investments'!$E$5:$E$220,0)) -> 3699992.1 | H9: 8368169 | I9: 8864627 | J9: 12000000 | K9: Pending | L9: 0.2 | M9: Pref Stack- $65,000,000 | N9: 0 | O9: 150000000 | P9: 300000000 | Q9: =(N9*$N$4)+(O9*$O$4)+(P9*$P$4) -> 150000000 | R9: 0.02168 | S9: =Q9*R9 -> 3252000 | T9: =S9/F9 -> 0.87892079
B10: Ashby | C10: RP | D10: C | E10: 0.023 | F10: =INDEX('Statement of Investments'!$L$5:$L$220,MATCH($B10,'Statement of Investments'!$E$5:$E$220,0)) -> 5000000 | G10: =INDEX('Statement of Investments'!$O$5:$O$220,MATCH($B10,'Statement of Investments'!$E$5:$E$220,0)) -> 10135319 | H10: 6708725 | I10: 14028342 | J10: 30461554 | K10: 31905531 | L10: 1.13 | M10: 500000000 | N10: =M10 -> 500000000 | O10: 2000000000 | P10: 3000000000 | Q10: =(N10*$N$4)+(O10*$O$4)+(P10*$P$4) -> 1875000000 | R10: 0.02062 | S10: =Q10*R10 -> 38662500 | T10: =S10/F10 -> 7.7325
B11: CoverGo | C11: CH | D11: A | E11: 0.093 | F11: =INDEX('Statement of Investments'!$L$5:$L$220,MATCH($B11,'Statement of Investments'!$E$5:$E$220,0)) -> 4000000 | G11: =INDEX('Statement of Investments'!$O$5:$O$220,MATCH($B11,'Statement of Investments'!$E$5:$E$220,0)) -> 5294506.9 | H11: 6122812 | I11: 7131378 | J11: 11012469 | K11: 6146557 | L11: 0.34 | M11: 43000000 | N11: 0 | O11: 43000000 | P11: 250000000 | Q11: =(N11*$N$4)+(O11*$O$4)+(P11*$P$4) -> 84000000 | R11: 0.06512 | S11: =Q11*R11 -> 5470080 | T11: =S11/F11 -> 1.36752
B12: Brightline | C12: CT | D12: C | E12: 0.006 | F12: =INDEX('Statement of Investments'!$L$5:$L$220,MATCH($B12,'Statement of Investments'!$E$5:$E$220,0)) -> 1499987 | G12: =INDEX('Statement of Investments'!$O$5:$O$220,MATCH($B12,'Statement of Investments'!$E$5:$E$220,0)) -> 4521963.7 | H12: 6923323 | I12: 52238905 | J12: 46580844 | K12: Pending | L12: 1.59 | M12: 705200000 | N12: 300000000 | O12: 500000000 | P12: 1000000000 | Q12: =(N12*$N$4)+(O12*$O$4)+(P12*$P$4) -> 575000000 | R12: 0.00543 | S12: =Q12*R12 -> 3122250 | T12: =S12/F12 -> 2.081518
B13: Cocoon | C13: RP | D13: A | E13: 0.028 | F13: =INDEX('Statement of Investments'!$L$5:$L$220,MATCH($B13,'Statement of Investments'!$E$5:$E$220,0)) -> 4224996.6 | G13: =INDEX('Statement of Investments'!$O$5:$O$220,MATCH($B13,'Statement of Investments'!$E$5:$E$220,0)) -> 4224996.6 | H13: 4364276 | I13: 4222643 | J13: 6822643 | K13: 5339358 | L13: 0.25 | M13: 26000000 | N13: 0 | O13: 26000000 | P13: 100000000 | Q13: =(N13*$N$4)+(O13*$O$4)+(P13*$P$4) -> 38000000 | R13: 0.0195 | S13: =Q13*R13 -> 741000 | T13: =S13/F13 -> 0.17538476
B14: Gable | C14: CH | D14: A | E14: 0.08 | F14: =INDEX('Statement of Investments'!$L$5:$L$220,MATCH($B14,'Statement of Investments'!$E$5:$E$220,0)) -> 4000000 | G14: =INDEX('Statement of Investments'!$O$5:$O$220,MATCH($B14,'Statement of Investments'!$E$5:$E$220,0)) -> 4000000 | H14: 309959 | I14: 1423910 | J14: 3785746 | K14: 3040239 | L14: 2.49 | M14: 50000000 | N14: 50000000 | O14: 75000000 | P14: 200000000 | Q14: =(N14*$N$4)+(O14*$O$4)+(P14*$P$4) -> 100000000 | R14: 0.056 | S14: =Q14*R14 -> 5600000 | T14: =S14/F14 -> 1.4
B15: Mosey | C15: CT | D15: A | E15: 0.045 | F15: =INDEX('Statement of Investments'!$L$5:$L$220,MATCH($B15,'Statement of Investments'!$E$5:$E$220,0)) -> 3999998.9 | G15: =INDEX('Statement of Investments'!$O$5:$O$220,MATCH($B15,'Statement of Investments'!$E$5:$E$220,0)) -> 3999998.9 | H15: 438617 | I15: 938232 | J15: 2000000 | K15: Pending | L15: 1.14 | M15: 88000000 | N15: 0 | O15: 88000000 | P15: 88000000 | Q15: =(N15*$N$4)+(O15*$O$4)+(P15*$P$4) -> 66000000 | R15: 0.03182 | S15: =Q15*R15 -> 2100120 | T15: =S15/F15 -> 0.52503014
B16: Nayya | C16: RP | D16: C | E16: 0.008 | F16: =INDEX('Statement of Investments'!$L$5:$L$220,MATCH($B16,'Statement of Investments'!$E$5:$E$220,0)) -> 2699987.1 | G16: =INDEX('Statement of Investments'!$O$5:$O$220,MATCH($B16,'Statement of Investments'!$E$5:$E$220,0)) -> 3853385.4 | H16: 8931989 | I16: 16060000 | J16: 33370000 | K16: 30864589 | L16: 0.93 | M16: 487813742 | N16: =300*10^6 -> 300000000 | O16: 500000000 | P16: 1000000000 | Q16: =(N16*$N$4)+(O16*$O$4)+(P16*$P$4) -> 575000000 | R16: 0.007 | S16: =Q16*R16 -> 4025000 | T16: =S16/F16 -> 1.4907479
B17: Vivante | C17: CH | D17: B | E17: 0.037 | F17: =INDEX('Statement of Investments'!$L$5:$L$220,MATCH($B17,'Statement of Investments'!$E$5:$E$220,0)) -> 2204142.3 | G17: =INDEX('Statement of Investments'!$O$5:$O$220,MATCH($B17,'Statement of Investments'!$E$5:$E$220,0)) -> 3130662 | H17: 10804903 | I17: 17442388 | J17: 25024329 | K17: 26574195 | L17: 0.52 | M17: 84077296 | N17: 0 | O17: 150000000 | P17: 300000000 | Q17: =(N17*$N$4)+(O17*$O$4)+(P17*$P$4) -> 150000000 | R17: 0.02974 | S17: =Q17*R17 -> 4461000 | T17: =S17/F17 -> 2.0239165
B18: Pinwheel | C18: CH | D18: B | E18: 0.006 | F18: =INDEX('Statement of Investments'!$L$5:$L$220,MATCH($B18,'Statement of Investments'!$E$5:$E$220,0)) -> 1453156.1 | G18: =INDEX('Statement of Investments'!$O$5:$O$220,MATCH($B18,'Statement of Investments'!$E$5:$E$220,0)) -> 1453156.1 | H18: 7228254 | I18: 8972963 | J18: 13125000 | K18: 10297233 | L18: 0.35 | M18: 496500100 | N18: 100000000 | O18: 250000000 | P18: 500000000 | Q18: =(N18*$N$4)+(O18*$O$4)+(P18*$P$4) -> 275000000 | R18: 0.00463 | S18: =Q18*R18 -> 1273250 | T18: =S18/F18 -> 0.87619632
B19: ianacare | C19: CT | D19: A | E19: 0.017 | F19: =INDEX('Statement of Investments'!$L$5:$L$220,MATCH($B19,'Statement of Investments'!$E$5:$E$220,0)) -> 2999984.9 | G19: =INDEX('Statement of Investments'!$O$5:$O$220,MATCH($B19,'Statement of Investments'!$E$5:$E$220,0)) -> 2999984.9 | H19: 791959 | I19: 1044591 | J19: 1500000 | K19: 1201303 | L19: 0.38 | M19: 60000000 | N19: 0 | O19: 60000000 | P19: 100000000 | Q19: =(N19*$N$4)+(O19*$O$4)+(P19*$P$4) -> 55000000 | R19: 0.01165 | S19: =Q19*R19 -> 640750 | T19: =S19/F19 -> 0.21358441
B20: Galileo | C20: CT | D20: C | E20: 0.004 | F20: =INDEX('Statement of Investments'!$L$5:$L$220,MATCH($B20,'Statement of Investments'!$E$5:$E$220,0)) -> 2163901.7 | G20: =INDEX('Statement of Investments'!$O$5:$O$220,MATCH($B20,'Statement of Investments'!$E$5:$E$220,0)) -> 1724878.8 | H20: 28533461 | I20: 39582209 | J20: 65878599 | K20: 14500000 | L20: 0.52 | M20: 600000000 | N20: 100000000 | O20: 300000000 | P20: 500000000 | Q20: =(N20*$N$4)+(O20*$O$4)+(P20*$P$4) -> 300000000 | R20: 0.00377 | S20: =Q20*R20 -> 1131000 | T20: =S20/F20 -> 0.52266701
B21: Violet | C21: ABG | D21: Seed | E21: 0.118 | F21: =INDEX('Statement of Investments'!$L$5:$L$220,MATCH($B21,'Statement of Investments'!$E$5:$E$220,0)) -> 2599995.3 | G21: =INDEX('Statement of Investments'!$O$5:$O$220,MATCH($B21,'Statement of Investments'!$E$5:$E$220,0)) -> 2599995.3 | H21: 634000 | I21: 1453192 | J21: 4175473 | K21: 1622758 | L21: 1.57 | M21: 22000000 | N21: 0 | O21: 0 | P21: =50*10^6 -> 50000000 | Q21: =(N21*$N$4)+(O21*$O$4)+(P21*$P$4) -> 12500000 | R21: 0.07091 | S21: =Q21*R21 -> 886375 | T21: =S21/F21 -> 0.34091408
B22: Delfina | C22: CT | D22: Seed | E22: 0.053 | F22: =INDEX('Statement of Investments'!$L$5:$L$220,MATCH($B22,'Statement of Investments'!$E$5:$E$220,0)) -> 1549999.9 | G22: =INDEX('Statement of Investments'!$O$5:$O$220,MATCH($B22,'Statement of Investments'!$E$5:$E$220,0)) -> 2097344.6 | H22: 712540 | I22: 1333980 | J22: 5161125 | K22: Pending | L22: - | M22: 15000000 | N22: 15000000 | O22: 100000000 | P22: 200000000 | Q22: =(N22*$N$4)+(O22*$O$4)+(P22*$P$4) -> 103750000 | R22: 0.03157 | S22: =Q22*R22 -> 3275387.5 | T22: =S22/F22 -> 2.1131533
B23: Murmur | C23: ABG | D23: Seed | E23: 0.064 | F23: =INDEX('Statement of Investments'!$L$5:$L$220,MATCH($B23,'Statement of Investments'!$E$5:$E$220,0)) -> 1574998 | G23: =INDEX('Statement of Investments'!$O$5:$O$220,MATCH($B23,'Statement of Investments'!$E$5:$E$220,0)) -> 0 | H23: – | I23: 4925 | J23: – | K23: Pending | L23: - | M23: 28000000 | N23: 0 | O23: 0 | P23: 0 | Q23: =(N23*$N$4)+(O23*$O$4)+(P23*$P$4) -> 0 | R23: 0.03844 | S23: =Q23*R23 -> 0 | T23: =S23/F23 -> 0
B24: Liftoff | C24: ABG | D24: Seed | E24: 0.05 | F24: =INDEX('Statement of Investments'!$L$5:$L$220,MATCH($B24,'Statement of Investments'!$E$5:$E$220,0)) -> 886565.66 | G24: =INDEX('Statement of Investments'!$O$5:$O$220,MATCH($B24,'Statement of Investments'!$E$5:$E$220,0)) -> 1896344.2 | H24: – | I24: 6081 | J24: 14000 | K24: 0 | L24: - | M24: 39000000 | N24: =+M24 -> 39000000 | O24: =65*10^6 -> 65000000 | P24: =200*10^6 -> 200000000 | Q24: =(N24*$N$4)+(O24*$O$4)+(P24*$P$4) -> 92250000 | R24: 0.03 | S24: =Q24*R24 -> 2767500 | T24: =S24/F24 -> 3.1215962
B25: Bravely | C25: ABG | D25: A | E25: 0.019 | F25: =INDEX('Statement of Investments'!$L$5:$L$220,MATCH($B25,'Statement of Investments'!$E$5:$E$220,0)) -> 1249999.6 | G25: =INDEX('Statement of Investments'!$O$5:$O$220,MATCH($B25,'Statement of Investments'!$E$5:$E$220,0)) -> 1249999.6 | H25: 7797202 | I25: 7328653 | J25: 8460985 | K25: Pending | L25: 0.04 | M25: 67500000 | N25: 0 | O25: 67500000 | P25: 100000000 | Q25: =(N25*$N$4)+(O25*$O$4)+(P25*$P$4) -> 58750000 | R25: 0.01296 | S25: =Q25*R25 -> 761400 | T25: =S25/F25 -> 0.60912022
B26: Formally | C26: CH | D26: Seed | E26: 0.04 | F26: =INDEX('Statement of Investments'!$L$5:$L$220,MATCH($B26,'Statement of Investments'!$E$5:$E$220,0)) -> 1000000 | G26: =INDEX('Statement of Investments'!$O$5:$O$220,MATCH($B26,'Statement of Investments'!$E$5:$E$220,0)) -> 1000000 | H26: – | I26: – | J26: – | K26: Pending | L26: - | M26: 25000000 | N26: 0 | O26: 25000000 | P26: 75000000 | Q26: =(N26*$N$4)+(O26*$O$4)+(P26*$P$4) -> 31250000 | R26: 0.024 | S26: =Q26*R26 -> 750000 | T26: =S26/F26 -> 0.75
B27: a.team | C27: ABG | D27: A | E27: 0.003 | F27: =INDEX('Statement of Investments'!$L$5:$L$220,MATCH($B27,'Statement of Investments'!$E$5:$E$220,0)) -> 999998.86 | G27: =INDEX('Statement of Investments'!$O$5:$O$220,MATCH($B27,'Statement of Investments'!$E$5:$E$220,0)) -> 999998.86 | H27: 9283145 | I27: 8860819 | J27: 11144446 | K27: Pending | L27: 0.1 | M27: 325000000 | N27: 0 | O27: 325000000 | P27: 500000000 | Q27: =(N27*$N$4)+(O27*$O$4)+(P27*$P$4) -> 287500000 | R27: 0.00215 | S27: =Q27*R27 -> 618125 | T27: =S27/F27 -> 0.6181257
B28: Finch | C28: CT | D28: B | E28: 0.003 | F28: =INDEX('Statement of Investments'!$L$5:$L$220,MATCH($B28,'Statement of Investments'!$E$5:$E$220,0)) -> 500003.42 | G28: =INDEX('Statement of Investments'!$O$5:$O$220,MATCH($B28,'Statement of Investments'!$E$5:$E$220,0)) -> 740862.12 | H28: – | I28: 6847796 | J28: – | K28: Pending | L28: - | M28: 200000000 | N28: 200000000 | O28: 300000000 | P28: 500000000 | Q28: =(N28*$N$4)+(O28*$O$4)+(P28*$P$4) -> 325000000 | R28: 0.0024 | S28: =Q28*R28 -> 780000 | T28: =S28/F28 -> 1.5599893
B29: Patch Caregiving | C29: RP | D29: Seed | E29: 0.063 | F29: =INDEX('Statement of Investments'!$L$5:$L$220,MATCH($B29,'Statement of Investments'!$E$5:$E$220,0)) -> 88754 | G29: =INDEX('Statement of Investments'!$O$5:$O$220,MATCH($B29,'Statement of Investments'!$E$5:$E$220,0)) -> 88754 | H29: 381112 | I29: 1613100 | J29: 3300000 | K29: 3000000 | L29: 1.94 | M29: 8000000 | N29: 0 | O29: 10000000 | P29: 50000000 | Q29: =(N29*$N$4)+(O29*$O$4)+(P29*$P$4) -> 17500000 | R29: 0.0375 | S29: =Q29*R29 -> 656250 | T29: =S29/F29 -> 7.3940329
B30: Praisidio | C30: ABG | D30: Seed | E30: 0.01 | F30: =INDEX('Statement of Investments'!$L$5:$L$220,MATCH($B30,'Statement of Investments'!$E$5:$E$220,0)) -> 200000 | G30: =INDEX('Statement of Investments'!$O$5:$O$220,MATCH($B30,'Statement of Investments'!$E$5:$E$220,0)) -> 0 | H30: – | I30: – | J30: – | K30: Pending | L30: - | M30: 0 | N30: 0 | O30: 0 | P30: 0 | Q30: =(N30*$N$4)+(O30*$O$4)+(P30*$P$4) -> 0 | R30: 0.006 | S30: =Q30*R30 -> 0 | T30: =S30/F30 -> 0
B31: Cleo | C31: CT | D31: C | E31: 0.004 | F31: =INDEX('Statement of Investments'!$L$5:$L$220,MATCH($B31,'Statement of Investments'!$E$5:$E$220,0)) -> 599997.84 | G31: =INDEX('Statement of Investments'!$O$5:$O$220,MATCH($B31,'Statement of Investments'!$E$5:$E$220,0)) -> 0 | H31: 17867474 | I31: – | J31: – | K31: Pending | L31: - | M31: 0 | N31: 0 | O31: 0 | P31: 0 | Q31: =(N31*$N$4)+(O31*$O$4)+(P31*$P$4) -> 0 | R31: 0.00364 | S31: =Q31*R31 -> 0 | T31: =S31/F31 -> 0
B32: Rightfoot | C32: CH | D32: A | E32: 0.013 | F32: =INDEX('Statement of Investments'!$L$5:$L$220,MATCH($B32,'Statement of Investments'!$E$5:$E$220,0)) -> 399999.32 | G32: =INDEX('Statement of Investments'!$O$5:$O$220,MATCH($B32,'Statement of Investments'!$E$5:$E$220,0)) -> 0 | H32: 546970 | I32: 19200 | J32: – | K32: 246000 | L32: -1 | M32: 0 | N32: 0 | O32: 0 | P32: 0 | Q32: =(N32*$N$4)+(O32*$O$4)+(P32*$P$4) -> 0 | R32: 0.0088 | S32: =Q32*R32 -> 0 | T32: =S32/F32 -> 0
F34: =SUM(F6:F32) -> 64409411 | G34: =SUM(G6:G32) -> 1.435382e+08 | S34: =SUM(S6:S33) -> 2.9883774e+08 | T34: =S34/F34 -> 4.6396595
