Workbook

Sheet Summary

Sheet Fund Dashboard
B2: SemperVirens Fund I Summary
C3: ="As of "&TEXT('Statement of Investments'!$C$1,"mm/dd/yyyy") -> As of 09/30/2025 | F3: ="As of "&TEXT('Statement of Investments'!$C$1,"mm/dd/yyyy") -> As of 09/30/2025
B5: Fund Capital: | E5: Quarterly Invested Capital:
B6: Committed Capital | C6: 20730000 | E6: New Investments | F6: =SUMIF('Investment Rollover'!$C$4:$C$26,"=0",'Investment Rollover'!$D$4:$D$26) -> 0
B7: Capital Called | C7: =-SUM('Net IRR'!C8:C13) -> 13681800 | E7: Follow-Ons | F7: =SUMIF('Investment Rollover'!$C$4:$C$26,">0",'Investment Rollover'!$D$4:$D$26) -> 252260.58
B8: Percent Called | C8: =C7/C6 -> 0.66 | E8: Total New Investments | F8: =SUM(F6:F7) -> 252260.58
B10: Investment Summary: | E10: Pro-Forma Net Peformance:
B11: Invested Capital | C11: ='Investment Performance Summary'!E47 -> 19553337 | E11: Contributions | F11: =-'Net IRR'!C39 -> 13681800
B12: Total Value | C12: ='Investment Performance Summary'!H47 -> 1.0394943e+08 | E12: Distributions | F12: ='Net IRR'!D39 -> 0
B13: MOIC | C13: =C12/C11 -> 5.3161987 | E13: NAV | F13: ='Net IRR'!F38 -> 90671203
B14: Gross IRR | C14: ='Investment Performance Summary'!J47 -> 0.35434995 | E14: TVPI | F14: =(F13+F12)/F11 -> 6.62714
E15: DPI | F15: =F12/F11 -> 0
E16: Net IRR | F16: ='Net IRR'!F39 -> 0.35763722

Sheet Investment Performance Summary
B2: SemperVirens Fund I Investment Summary
B4: ="As of "&TEXT('Statement of Investments'!$C$1,"mm/dd/yyyy") -> As of 09/30/2025 | C4: Initial Inv. | D4: Initial Exit | E4: Dollars | F4: Unrealized | G4: Realized | H4: Total | I4: Gross | J4: Gross
B5: Company | C5: Date | D5: Date | E5: Invested | F5: Value | G5: Value | H5: Value | I5: Multiple | J5: IRR
B6: Realized Portfolio
B8: Physera | C8: =INDEX('Statement of Investments'!$C$5:$C$204,MATCH('Investment Performance Summary'!$B8,'Statement of Investments'!$B$5:$B$204,0)) -> 43440 | D8: =INDEX('Statement of Investments'!$D$5:$D$204,MATCH('Investment Performance Summary'!$B8,'Statement of Investments'!$B$5:$B$204,0)) -> 43969 | E8: =INDEX('Statement of Investments'!$L$5:$L$204,MATCH($B8,'Statement of Investments'!$E$5:$E$204,0)) -> 208014.11 | F8: 0 | G8: =INDEX('Statement of Investments'!$O$5:$O$204,MATCH($B8,'Statement of Investments'!$E$5:$E$204,0)) -> 366088.28 | H8: =F8+G8 -> 366088.28 | I8: =H8/E8 -> 1.7599205 | J8: =INDEX('Statement of Investments'!$R$5:$R$204,MATCH($B8,'Statement of Investments'!$E$5:$E$204,0)) -> 0.47701722
B9: Fountain - Realized | C9: =INDEX('Statement of Investments'!$C$5:$C$204,MATCH('Investment Performance Summary'!$B9,'Statement of Investments'!$B$5:$B$204,0)) -> 43789 | D9: =INDEX('Statement of Investments'!$D$5:$D$204,MATCH('Investment Performance Summary'!$B9,'Statement of Investments'!$B$5:$B$204,0)) -> 44054 | E9: =INDEX('Statement of Investments'!$L$5:$L$204,MATCH($B9,'Statement of Investments'!$E$5:$E$204,0)) -> 94663.1 | F9: 0 | G9: =INDEX('Statement of Investments'!$O$5:$O$204,MATCH($B9,'Statement of Investments'!$E$5:$E$204,0)) -> 94663.1 | H9: =F9+G9 -> 94663.1 | I9: =H9/E9 -> 1 | J9: =INDEX('Statement of Investments'!$R$5:$R$204,MATCH($B9,'Statement of Investments'!$E$5:$E$204,0)) -> 4.8828125e-09
B10: Sapling | C10: =INDEX('Statement of Investments'!$C$5:$C$204,MATCH('Investment Performance Summary'!$B10,'Statement of Investments'!$B$5:$B$204,0)) -> 43728 | D10: =INDEX('Statement of Investments'!$D$5:$D$204,MATCH('Investment Performance Summary'!$B10,'Statement of Investments'!$B$5:$B$204,0)) -> 44188 | E10: =INDEX('Statement of Investments'!$L$5:$L$204,MATCH($B10,'Statement of Investments'!$E$5:$E$204,0)) -> 129007.89 | F10: 0 | G10: =INDEX('Statement of Investments'!$O$5:$O$204,MATCH($B10,'Statement of Investments'!$E$5:$E$204,0)) -> 203127.39 | H10: =F10+G10 -> 203127.39 | I10: =H10/E10 -> 1.5745346 | J10: =INDEX('Statement of Investments'!$R$5:$R$204,MATCH($B10,'Statement of Investments'!$E$5:$E$204,0)) -> 0.43362643
B11: Alice | C11: =INDEX('Statement of Investments'!$C$5:$C$204,MATCH('Investment Performance Summary'!$B11,'Statement of Investments'!$B$5:$B$204,0)) -> 43705 | D11: =INDEX('Statement of Investments'!$D$5:$D$204,MATCH('Investment Performance Summary'!$B11,'Statement of Investments'!$B$5:$B$204,0)) -> 45008 | E11: =INDEX('Statement of Investments'!$L$5:$L$204,MATCH($B11,'Statement of Investments'!$E$5:$E$204,0)) -> 600000.08 | F11: 0 | G11: =INDEX('Statement of Investments'!$O$5:$O$204,MATCH($B11,'Statement of Investments'!$E$5:$E$204,0)) -> 0 | H11: =F11+G11 -> 0 | I11: =H11/E11 -> 0 | J11: =INDEX('Statement of Investments'!$R$5:$R$204,MATCH($B11,'Statement of Investments'!$E$5:$E$204,0)) -> -1
B12: Pill Club | C12: =INDEX('Statement of Investments'!$C$5:$C$204,MATCH('Investment Performance Summary'!$B12,'Statement of Investments'!$B$5:$B$204,0)) -> 43473 | D12: =INDEX('Statement of Investments'!$D$5:$D$204,MATCH('Investment Performance Summary'!$B12,'Statement of Investments'!$B$5:$B$204,0)) -> 45381 | E12: =INDEX('Statement of Investments'!$L$5:$L$204,MATCH($B12,'Statement of Investments'!$E$5:$E$204,0)) -> 999998.53 | F12: 0 | G12: =INDEX('Statement of Investments'!$O$5:$O$204,MATCH($B12,'Statement of Investments'!$E$5:$E$204,0)) -> 0 | H12: =F12+G12 -> 0 | I12: =H12/E12 -> 0 | J12: =INDEX('Statement of Investments'!$R$5:$R$204,MATCH($B12,'Statement of Investments'!$E$5:$E$204,0)) -> -1
B13: Forage | C13: =INDEX('Statement of Investments'!$C$5:$C$204,MATCH('Investment Performance Summary'!$B13,'Statement of Investments'!$B$5:$B$204,0)) -> 44014 | D13: =INDEX('Statement of Investments'!$D$5:$D$204,MATCH('Investment Performance Summary'!$B13,'Statement of Investments'!$B$5:$B$204,0)) -> 45425 | E13: =INDEX('Statement of Investments'!$L$5:$L$204,MATCH($B13,'Statement of Investments'!$E$5:$E$204,0)) -> 249999.58 | F13: 0 | G13: =INDEX('Statement of Investments'!$O$5:$O$204,MATCH($B13,'Statement of Investments'!$E$5:$E$204,0)) -> 222162.45 | H13: =F13+G13 -> 222162.45 | I13: =H13/E13 -> 0.88865129 | J13: =INDEX('Statement of Investments'!$R$5:$R$204,MATCH($B13,'Statement of Investments'!$E$5:$E$204,0)) -> -0.030075918
B14: Shift | C14: =INDEX('Statement of Investments'!$C$5:$C$204,MATCH('Investment Performance Summary'!$B14,'Statement of Investments'!$B$5:$B$204,0)) -> 43390 | D14: ='Statement of Investments'!D37 -> 45631 | E14: =INDEX('Statement of Investments'!$L$5:$L$204,MATCH($B14,'Statement of Investments'!$E$5:$E$204,0)) -> 223873.41 | F14: 0 | G14: =INDEX('Statement of Investments'!$O$5:$O$204,MATCH($B14,'Statement of Investments'!$E$5:$E$204,0)) -> 8128.52 | H14: =F14+G14 -> 8128.52 | I14: =H14/E14 -> 0.036308555 | J14: =INDEX('Statement of Investments'!$R$5:$R$204,MATCH($B14,'Statement of Investments'!$E$5:$E$204,0)) -> -1
B15: Rula - Realized | C15: =INDEX('Statement of Investments'!$C$5:$C$204,MATCH('Investment Performance Summary'!$B15,'Statement of Investments'!$B$5:$B$204,0)) -> 43719 | D15: =INDEX('Statement of Investments'!$D$5:$D$204,MATCH('Investment Performance Summary'!$B15,'Statement of Investments'!$B$5:$B$204,0)) -> 45611 | E15: =INDEX('Statement of Investments'!$L$5:$L$204,MATCH($B15,'Statement of Investments'!$E$5:$E$204,0)) -> 259445.38 | F15: 0 | G15: =INDEX('Statement of Investments'!$O$5:$O$204,MATCH($B15,'Statement of Investments'!$E$5:$E$204,0)) -> 10236410 | H15: =F15+G15 -> 10236410 | I15: =H15/E15 -> 39.454972 | J15: =INDEX('Statement of Investments'!$R$5:$R$204,MATCH($B15,'Statement of Investments'!$E$5:$E$204,0)) -> 0.96135892
B16: Level | C16: =INDEX('Statement of Investments'!$C$5:$C$204,MATCH('Investment Performance Summary'!$B16,'Statement of Investments'!$B$5:$B$204,0)) -> 04/17/2020 | D16: - | E16: =INDEX('Statement of Investments'!$L$5:$L$204,MATCH($B16,'Statement of Investments'!$E$5:$E$204,0)) -> 1000002.7 | F16: =INDEX('Statement of Investments'!$O$5:$O$204,MATCH($B16,'Statement of Investments'!$E$5:$E$204,0)) -> 0 | G16: 0 | H16: =F16+G16 -> 0 | I16: =H16/E16 -> 0 | J16: =INDEX('Statement of Investments'!$R$5:$R$204,MATCH($B16,'Statement of Investments'!$E$5:$E$204,0)) -> -1
B17: Valence | C17: =INDEX('Statement of Investments'!$C$5:$C$204,MATCH('Investment Performance Summary'!$B17,'Statement of Investments'!$B$5:$B$204,0)) -> 43721 | E17: =INDEX('Statement of Investments'!$L$5:$L$204,MATCH($B17,'Statement of Investments'!$E$5:$E$204,0)) -> 249999.49 | F17: 0 | G17: =INDEX('Statement of Investments'!$O$5:$O$204,MATCH($B17,'Statement of Investments'!$E$5:$E$204,0)) -> 1997507.1 | H17: =F17+G17 -> 1997507.1 | I17: =H17/E17 -> 7.9900445 | J17: =INDEX('Statement of Investments'!$R$5:$R$204,MATCH($B17,'Statement of Investments'!$E$5:$E$204,0)) -> 0.41844098
B18: Total Realized Portfolio | E18: =SUM(E8:E17) -> 4015004.2 | F18: =SUM(F8:F17) -> 0 | G18: =SUM(G8:G17) -> 13128087 | H18: =SUM(H8:H17) -> 13128087 | I18: =H18/E18 -> 3.2697567 | J18: ='Statement of Investments'!R78 -> 0.25423873
B20: Unrealized Portfolio
B22: Spring | C22: =INDEX('Statement of Investments'!$C$5:$C$204,MATCH('Investment Performance Summary'!$B22,'Statement of Investments'!$B$5:$B$204,0)) -> 43244 | D22: - | E22: =INDEX('Statement of Investments'!$L$5:$L$204,MATCH($B22,'Statement of Investments'!$E$5:$E$204,0)) -> 1449990.3 | F22: =INDEX('Statement of Investments'!$O$5:$O$204,MATCH($B22,'Statement of Investments'!$E$5:$E$204,0)) -> 28841289 | G22: 0 | H22: =F22+G22 -> 28841289 | I22: =H22/E22 -> 19.890677 | J22: =INDEX('Statement of Investments'!$R$5:$R$204,MATCH($B22,'Statement of Investments'!$E$5:$E$204,0)) -> 0.68471499
B23: Hone | C23: =INDEX('Statement of Investments'!$C$5:$C$204,MATCH('Investment Performance Summary'!$B23,'Statement of Investments'!$B$5:$B$204,0)) -> 43262 | D23: - | E23: =INDEX('Statement of Investments'!$L$5:$L$204,MATCH($B23,'Statement of Investments'!$E$5:$E$204,0)) -> 682666.27 | F23: =INDEX('Statement of Investments'!$O$5:$O$204,MATCH($B23,'Statement of Investments'!$E$5:$E$204,0)) -> 1756737.3 | G23: 0 | H23: =F23+G23 -> 1756737.3 | I23: =H23/E23 -> 2.5733472 | J23: =INDEX('Statement of Investments'!$R$5:$R$204,MATCH($B23,'Statement of Investments'!$E$5:$E$204,0)) -> 0.19311117
B24: Cleo | C24: =INDEX('Statement of Investments'!$C$5:$C$204,MATCH('Investment Performance Summary'!$B24,'Statement of Investments'!$B$5:$B$204,0)) -> 43328 | D24: - | E24: =INDEX('Statement of Investments'!$L$5:$L$204,MATCH($B24,'Statement of Investments'!$E$5:$E$204,0)) -> 100000 | F24: =INDEX('Statement of Investments'!$O$5:$O$204,MATCH($B24,'Statement of Investments'!$E$5:$E$204,0)) -> 0 | G24: 0 | H24: =F24+G24 -> 0 | I24: =H24/E24 -> 0 | J24: =INDEX('Statement of Investments'!$R$5:$R$204,MATCH($B24,'Statement of Investments'!$E$5:$E$204,0)) -> -1
B25: Carrot | C25: =INDEX('Statement of Investments'!$C$5:$C$204,MATCH('Investment Performance Summary'!$B25,'Statement of Investments'!$B$5:$B$204,0)) -> 43333 | D25: - | E25: =INDEX('Statement of Investments'!$L$5:$L$204,MATCH($B25,'Statement of Investments'!$E$5:$E$204,0)) -> 999996.37 | F25: =INDEX('Statement of Investments'!$O$5:$O$204,MATCH($B25,'Statement of Investments'!$E$5:$E$204,0)) -> 5663568.2 | G25: 0 | H25: =F25+G25 -> 5663568.2 | I25: =H25/E25 -> 5.6635888 | J25: =INDEX('Statement of Investments'!$R$5:$R$204,MATCH($B25,'Statement of Investments'!$E$5:$E$204,0)) -> 0.35356258
B26: Multiverse | C26: =INDEX('Statement of Investments'!$C$5:$C$204,MATCH('Investment Performance Summary'!$B26,'Statement of Investments'!$B$5:$B$204,0)) -> 43395 | D26: - | E26: =INDEX('Statement of Investments'!$L$5:$L$204,MATCH($B26,'Statement of Investments'!$E$5:$E$204,0)) -> 834995.61 | F26: =INDEX('Statement of Investments'!$O$5:$O$204,MATCH($B26,'Statement of Investments'!$E$5:$E$204,0)) -> 9377802.2 | G26: 0 | H26: =F26+G26 -> 9377802.2 | I26: =H26/E26 -> 11.23096 | J26: =INDEX('Statement of Investments'!$R$5:$R$204,MATCH($B26,'Statement of Investments'!$E$5:$E$204,0)) -> 0.54692257
B27: Pelago | C27: =INDEX('Statement of Investments'!$C$5:$C$204,MATCH('Investment Performance Summary'!$B27,'Statement of Investments'!$B$5:$B$204,0)) -> 43558 | D27: - | E27: =INDEX('Statement of Investments'!$L$5:$L$204,MATCH($B27,'Statement of Investments'!$E$5:$E$204,0)) -> 549993.11 | F27: =INDEX('Statement of Investments'!$O$5:$O$204,MATCH($B27,'Statement of Investments'!$E$5:$E$204,0)) -> 4289097.2 | G27: 0 | H27: =F27+G27 -> 4289097.2 | I27: =H27/E27 -> 7.7984561 | J27: =INDEX('Statement of Investments'!$R$5:$R$204,MATCH($B27,'Statement of Investments'!$E$5:$E$204,0)) -> 0.43548993
B28: Karat | C28: =INDEX('Statement of Investments'!$C$5:$C$204,MATCH('Investment Performance Summary'!$B28,'Statement of Investments'!$B$5:$B$204,0)) -> 43592 | D28: - | E28: =INDEX('Statement of Investments'!$L$5:$L$204,MATCH($B28,'Statement of Investments'!$E$5:$E$204,0)) -> 999994.83 | F28: =INDEX('Statement of Investments'!$O$5:$O$204,MATCH($B28,'Statement of Investments'!$E$5:$E$204,0)) -> 999994.83 | G28: 0 | H28: =F28+G28 -> 999994.83 | I28: =H28/E28 -> 1 | J28: =INDEX('Statement of Investments'!$R$5:$R$204,MATCH($B28,'Statement of Investments'!$E$5:$E$204,0)) -> 4.8828125e-09
B29: Omada Health | C29: =INDEX('Statement of Investments'!$C$5:$C$204,MATCH('Investment Performance Summary'!$B29,'Statement of Investments'!$B$5:$B$204,0)) -> 43969 | D29: - | E29: =INDEX('Statement of Investments'!$L$5:$L$204,MATCH($B29,'Statement of Investments'!$E$5:$E$204,0)) -> 291986.05 | F29: =INDEX('Statement of Investments'!$O$5:$O$204,MATCH($B29,'Statement of Investments'!$E$5:$E$204,0)) -> 475335.52 | G29: 0 | H29: =F29+G29 -> 475335.52 | I29: =H29/E29 -> 1.6279391 | J29: =INDEX('Statement of Investments'!$R$5:$R$204,MATCH($B29,'Statement of Investments'!$E$5:$E$204,0)) -> 0.094944517
B30: Hatch | C30: =INDEX('Statement of Investments'!$C$5:$C$204,MATCH('Investment Performance Summary'!$B30,'Statement of Investments'!$B$5:$B$204,0)) -> 43665 | D30: - | E30: =INDEX('Statement of Investments'!$L$5:$L$204,MATCH($B30,'Statement of Investments'!$E$5:$E$204,0)) -> 258903.8 | F30: =INDEX('Statement of Investments'!$O$5:$O$204,MATCH($B30,'Statement of Investments'!$E$5:$E$204,0)) -> 133950.81 | G30: 0 | H30: =F30+G30 -> 133950.81 | I30: =H30/E30 -> 0.51737674 | J30: =INDEX('Statement of Investments'!$R$5:$R$204,MATCH($B30,'Statement of Investments'!$E$5:$E$204,0)) -> 4.8828125e-09
B31: Human Interest | C31: =INDEX('Statement of Investments'!$C$5:$C$204,MATCH('Investment Performance Summary'!$B31,'Statement of Investments'!$B$5:$B$204,0)) -> 43670 | D31: - | E31: =INDEX('Statement of Investments'!$L$5:$L$204,MATCH($B31,'Statement of Investments'!$E$5:$E$204,0)) -> 1090002.1 | F31: =INDEX('Statement of Investments'!$O$5:$O$204,MATCH($B31,'Statement of Investments'!$E$5:$E$204,0)) -> 10743747 | G31: 0 | H31: =F31+G31 -> 10743747 | I31: =H31/E31 -> 9.8566302 | J31: =INDEX('Statement of Investments'!$R$5:$R$204,MATCH($B31,'Statement of Investments'!$E$5:$E$204,0)) -> 0.50923417
B32: Rula | C32: =INDEX('Statement of Investments'!$C$5:$C$204,MATCH('Investment Performance Summary'!$B32,'Statement of Investments'!$B$5:$B$204,0)) -> 0 | D32: - | E32: =INDEX('Statement of Investments'!$L$5:$L$204,MATCH($B32,'Statement of Investments'!$E$5:$E$204,0)) -> 496199.35 | F32: =INDEX('Statement of Investments'!$O$5:$O$204,MATCH($B32,'Statement of Investments'!$E$5:$E$204,0)) -> 6277910.6 | G32: 0 | H32: =F32+G32 -> 6277910.6 | I32: =H32/E32 -> 12.651993 | J32: =INDEX('Statement of Investments'!$R$5:$R$204,MATCH($B32,'Statement of Investments'!$E$5:$E$204,0)) -> 0.74427286
B33: Terminal | C33: =INDEX('Statement of Investments'!$C$5:$C$204,MATCH('Investment Performance Summary'!$B33,'Statement of Investments'!$B$5:$B$204,0)) -> 43727 | D33: - | E33: =INDEX('Statement of Investments'!$L$5:$L$204,MATCH($B33,'Statement of Investments'!$E$5:$E$204,0)) -> 599999.73 | F33: =INDEX('Statement of Investments'!$O$5:$O$204,MATCH($B33,'Statement of Investments'!$E$5:$E$204,0)) -> 0 | G33: 0 | H33: =F33+G33 -> 0 | I33: =H33/E33 -> 0 | J33: =INDEX('Statement of Investments'!$R$5:$R$204,MATCH($B33,'Statement of Investments'!$E$5:$E$204,0)) -> -1
... B43: Ladder | C43: =INDEX('Statement of Investments'!$C$5:$C$204,MATCH('Investment Performance Summary'!$B43,'Statement of Investments'!$B$5:$B$204,0)) -> 43866 | D43: - | E43: =INDEX('Statement of Investments'!$L$5:$L$204,MATCH($B43,'Statement of Investments'!$E$5:$E$204,0)) -> 749994.59 | F43: =INDEX('Statement of Investments'!$O$5:$O$204,MATCH($B43,'Statement of Investments'!$E$5:$E$204,0)) -> 759917.21 | G43: 0 | H43: =F43+G43 -> 759917.21 | I43: =H43/E43 -> 1.0132302 | J43: =INDEX('Statement of Investments'!$R$5:$R$204,MATCH($B43,'Statement of Investments'!$E$5:$E$204,0)) -> 0.0023270166
B45: Total Unrealized Portfolio | E45: =SUM(E22:E44) -> 15538333 | F45: =SUM(F22:F44) -> 90821339 | G45: =SUM(G22:G44) -> 0 | H45: =SUM(H22:H44) -> 90821339 | I45: =H45/E45 -> 5.844986 | J45: ='Statement of Investments'!R202 -> 0.37722788
B47: Total Portfolio | E47: =E45+E18 -> 19553337 | F47: =F45+F18 -> 90821339 | G47: =G45+G18 -> 13128087 | H47: =H45+H18 -> 1.0394943e+08 | I47: =H47/E47 -> 5.3161987 | J47: ='Statement of Investments'!R204 -> 0.35434995
H52: =2*10^6 -> 2000000
H53: =+H52*0.0125 -> 25000

Sheet Warrant Summary
C2: Shift | D2: Pill Club | E2: Digithera | F2: Alice
B3: Overall Status | C3: =INDEX('Warrant Detail'!$C$3:$Y$3,MATCH('Warrant Summary'!C$2,'Warrant Detail'!$C$2:$Y$2,0)) -> 0 | D3: =INDEX('Warrant Detail'!$C$3:$Y$3,MATCH('Warrant Summary'!D$2,'Warrant Detail'!$C$2:$Y$2,0)) -> 0 | E3: =INDEX('Warrant Detail'!$C$3:$Y$3,MATCH('Warrant Summary'!E$2,'Warrant Detail'!$C$2:$Y$2,0)) -> 0.99998984 | F3: =INDEX('Warrant Detail'!$C$3:$Y$3,MATCH('Warrant Summary'!F$2,'Warrant Detail'!$C$2:$Y$2,0)) -> 0
B4: Next Steps | C4: Continue intros, get reporting doc | D4: Set up biweekly meetings | E4: Figure out how to intro more | F4: Get reporting
B5: Owner | C5: =INDEX('Warrant Detail'!$C$4:$Y$4,MATCH('Warrant Summary'!C$2,'Warrant Detail'!$C$2:$Y$2,0)) -> Robby | D5: =INDEX('Warrant Detail'!$C$4:$Y$4,MATCH('Warrant Summary'!D$2,'Warrant Detail'!$C$2:$Y$2,0)) -> Kaleana | E5: =INDEX('Warrant Detail'!$C$4:$Y$4,MATCH('Warrant Summary'!E$2,'Warrant Detail'!$C$2:$Y$2,0)) -> Robby | F5: =INDEX('Warrant Detail'!$C$4:$Y$4,MATCH('Warrant Summary'!F$2,'Warrant Detail'!$C$2:$Y$2,0)) -> Robby/Colin
B6: Reporting | C6: =INDEX('Warrant Detail'!$C$5:$Y$5,MATCH('Warrant Summary'!C$2,'Warrant Detail'!$C$2:$Y$2,0)) -> Montly report from Shift | D6: =INDEX('Warrant Detail'!$C$5:$Y$5,MATCH('Warrant Summary'!D$2,'Warrant Detail'!$C$2:$Y$2,0)) -> Quarterly Basis | E6: =INDEX('Warrant Detail'!$C$5:$Y$5,MATCH('Warrant Summary'!E$2,'Warrant Detail'!$C$2:$Y$2,0)) -> Quarterly Report | F6: =INDEX('Warrant Detail'!$C$5:$Y$5,MATCH('Warrant Summary'!F$2,'Warrant Detail'!$C$2:$Y$2,0)) -> Monthly Report
B7: Deadline | C7: ='Warrant Detail'!C10 -> 44470 | D7: ='Warrant Detail'!G10 -> 44926 | E7: ='Warrant Detail'!K10 -> 47209 | F7: ='Warrant Detail'!O10 -> 44824
B8: Remaining Needed for Trigger | C8: 7 Employers | D8: 15 fully insured employers 20 self-insured employers 90k client employees with 30k women | F8: $1M ARR
C10: Rightway Health | D10: Vetty | E10: Level Dental | F10: InsideSherpa
B11: Overall Status | C11: =INDEX('Warrant Detail'!$C$3:$Y$3,MATCH('Warrant Summary'!C$10,'Warrant Detail'!$C$2:$Y$2,0)) -> #N/A | D11: =INDEX('Warrant Detail'!$C$3:$Y$3,MATCH('Warrant Summary'!D$10,'Warrant Detail'!$C$2:$Y$2,0)) -> 0 | E11: =INDEX('Warrant Detail'!$C$3:$Y$3,MATCH('Warrant Summary'!E$10,'Warrant Detail'!$C$2:$Y$2,0)) -> 0 | F11: =INDEX('Warrant Detail'!$C$3:$AC$3,MATCH('Warrant Summary'!F$10,'Warrant Detail'!$C$2:$AC$2,0)) -> #N/A
B12: Next Steps | C12: Get all Sequoia clients on Rightway | D12: Get reporting | E12: Get reporting, get level funding and FSA | F12: Continue introducing customers
B13: Owner | C13: =INDEX('Warrant Detail'!$C$4:$Y$4,MATCH('Warrant Summary'!C$10,'Warrant Detail'!$C$2:$Y$2,0)) -> #N/A | D13: =INDEX('Warrant Detail'!$C$4:$Y$4,MATCH('Warrant Summary'!D$10,'Warrant Detail'!$C$2:$Y$2,0)) -> Colin | E13: =INDEX('Warrant Detail'!$C$4:$Y$4,MATCH('Warrant Summary'!E$10,'Warrant Detail'!$C$2:$Y$2,0)) -> Greg | F13: =INDEX('Warrant Detail'!$C$4:$AC$4,MATCH('Warrant Summary'!F$10,'Warrant Detail'!$C$2:$AC$2,0)) -> #N/A
B14: Reporting | C14: =INDEX('Warrant Detail'!$C$5:$Y$5,MATCH('Warrant Summary'!C$10,'Warrant Detail'!$C$2:$Y$2,0)) -> #N/A | D14: =INDEX('Warrant Detail'!$C$5:$Y$5,MATCH('Warrant Summary'!D$10,'Warrant Detail'!$C$2:$Y$2,0)) -> Monthly Report | E14: =INDEX('Warrant Detail'!$C$5:$Y$5,MATCH('Warrant Summary'!E$10,'Warrant Detail'!$C$2:$Y$2,0)) -> Quarterly report within 10 business days | F14: =INDEX('Warrant Detail'!$C$5:$AC$5,MATCH('Warrant Summary'!F$10,'Warrant Detail'!$C$2:$AC$2,0)) -> #N/A
B15: Deadline | C15: ='Warrant Detail'!AE10 -> 44470 | D15: ='Warrant Detail'!S10 -> 47484 | E15: ='Warrant Detail'!W10 -> 45292 | F15: ='Warrant Detail'!AA10 -> 44805
B16: Remaining Needed for Trigger | C16: Hit 75k users | D16: $250k ARR | E16: 7,500 enrolled employees | F16: 5 customers

Sheet Supporting Worksheets -->

Sheet Statement of Investments
A1: 45930 | B1: As of | C1: =IF(TODAY()<$A$1,TODAY(),A1) -> 45930
C2: Investment | D2: Liquidity | K2: Original Cost | N2: Current Value | Q2: Gross
C3: Date | D3: Date | F3: Security | G3: Stock Certificate | I3: Shares | K3: Per Share | L3: Total Dollars | N3: Per Share | O3: Total Dollars | Q3: MOIC | R3: IRR
S4: 43101 | T4: -0.1
A5: REALIZED | U5: Commentary
B7: Physera | C7: 43440 | D7: 43969 | F7: Series A Preferred Stock | I7: 128586 | K7: 1.6177042 | L7: =I7*K7 -> 208014.11 | O7: 326186 | S7: =IFERROR(C7,0) -> 43440 | T7: =-L7 -> -208014.11
C8: 43440 | D8: 44426 | F8: Escrow release | K8: 0 | L8: 0 | O8: =39451.47+450.81 -> 39902.28 | S8: =IFERROR(C8,0) -> 43440 | T8: =-L8 -> 0
E10: =B7 -> Physera | F10: Total | I10: =SUM(I7:I9) -> 128586 | K10: =L10/I10 -> 1.6177042 | L10: =SUM(L7:L9) -> 208014.11 | N10: =O10/$I10 -> 2.8470306 | O10: =SUM(O7:O9) -> 366088.28 | Q10: =O10/L10 -> 1.7599205 | R10: =XIRR(T7:T10,S7:S10,0) -> 0.47701722 | S10: =D7 -> 43969 | T10: =O10 -> 366088.28
B12: Fountain - Realized | C12: 43789 | D12: 44054 | F12: Series B Preferred Stock | I12: 13403 | K12: =L12/I12 -> 7.0628292 | L12: 94663.1 | N12: =K12 -> 7.0628292 | O12: =$I12*N12 -> 94663.1 | S12: =IFERROR(C12,0) -> 43789 | T12: =-L12 -> -94663.1
E14: =B12 -> Fountain - Realized | F14: Total | I14: =SUM(I12:I13) -> 13403 | K14: =L14/$I14 -> 7.0628292 | L14: =SUM(L12:L13) -> 94663.1 | N14: =O14/$I14 -> 7.0628292 | O14: =SUM(O12:O13) -> 94663.1 | Q14: =O14/L14 -> 1 | R14: =XIRR(T12:T14,S12:S14,0) -> 4.8828125e-09 | S14: =D12 -> 44054 | T14: =O14 -> 94663.1
B16: Sapling | C16: 43728 | D16: 44188 | F16: Series Seed Extension Preferred Stock | I16: 144159 | K16: 0.8949 | L16: =I16*K16 -> 129007.89 | N16: =O16/I16 -> 1.2483653 | O16: 179963.1 | S16: =IFERROR(C16,0) -> 43728 | T16: =-L16 -> -129007.89
C17: 44813 | D17: 44426 | F17: Escrow release | K17: 0 | L17: 0 | O17: 23164.29 | S17: =IFERROR(C17,0) -> 44813 | T17: =-L17 -> 0
E19: =B16 -> Sapling | F19: Total | I19: =SUM(I16:I18) -> 144159 | K19: 0 | L19: =SUM(L16:L18) -> 129007.89 | N19: 0 | O19: =SUM(O16:O18) -> 203127.39 | Q19: =O19/L19 -> 1.5745346 | R19: =XIRR(T16:T19,S16:S19,0) -> 0.43362643 | S19: =D16 -> 44188 | T19: =O19 -> 203127.39
B21: Alice | C21: 43705 | D21: 45008 | F21: Series A Preferred Stock | G21: PA-8 | I21: 191902 | K21: =+L21/$I$21 -> 3.1265963 | L21: 600000.08 | N21: =+O21/$I$21 -> 0 | O21: 0 | S21: =IFERROR(C21,0) -> 43705 | T21: =-L21 -> -600000.08
F22: Series A Warrants - Expired Sep 2022
E24: =B21 -> Alice | F24: Total | I24: =SUM(I21:I23) -> 191902 | K24: =+L24/$I$24 -> 3.1265963 | L24: =SUM(L21:L23) -> 600000.08 | N24: =+O24/$I$24 -> 0 | O24: =SUM(O21:O23) -> 0 | Q24: =O24/L24 -> 0 | R24: -1 | S24: =D21 -> 45008 | T24: =O24 -> 0
B26: Pill Club | C26: 43473 | D26: 45381 | F26: Series B Preferred Stock | G26: PB-7 | I26: 579911.85 | K26: =L26/I26 -> 1.7243975 | L26: 999998.53 | N26: 2.189 | O26: 0 | S26: =IFERROR(C26,0) -> 43473 | T26: =-L26 -> -999998.53
F27: Series B Warrants
E29: =B26 -> Pill Club | F29: Total | I29: =SUM(I26:I28) -> 579911.85 | K29: =L29/$I29 -> 1.7243975 | L29: =SUM(L26:L28) -> 999998.53 | N29: =O29/$I29 -> 0 | O29: =SUM(O26:O28) -> 0 | Q29: =O29/L29 -> 0 | R29: -1 | S29: =$C$1 -> 45930 | T29: =O29 -> 0
B31: Forage | C31: 44014 | D31: 45425 | F31: Series A Preferred Stock | G31: UPA1-5 | I31: 119119 | K31: =L31/I31 -> 2.0987381 | L31: 249999.58 | N31: =+O31/I31 -> 1.8650463 | O31: 222162.45 | S31: =IFERROR(C31,0) -> 44014 | T31: =-L31 -> -249999.58
F32: Series A Warrants - Expired Sep 2022
E34: =B31 -> Forage | F34: Total | I34: =SUM(I31:I33) -> 119119 | K34: =L34/$I34 -> 2.0987381 | L34: =SUM(L31:L33) -> 249999.58 | N34: =O34/$I34 -> 1.8650463 | O34: =SUM(O31:O33) -> 222162.45 | Q34: =O34/L34 -> 0.88865129 | R34: =XIRR(T31:T34,S31:S34,0) -> -0.030075918 | S34: =D31 -> 45425 | T34: =O34 -> 222162.45
B36: Shift | C36: 43390 | F36: Series Seed Preferred Stock | G36: PS-18 | I36: 151225 | K36: =L36/I36 -> 0.4885 | L36: 73873.412 | N36: =K36 -> 0.4885 | O36: 0 | S36: =IFERROR(C36,0) -> 43390 | T36: =-L36 -> -73873.412
C37: 43450 | D37: 45631 | F37: Convertible Note | G37: CPN-11 | I37: 0 | K37: 0 | L37: 150000 | N37: 0 | O37: 8128.52 | S37: =IFERROR(C37,0) -> 43450 | T37: =-L37 -> -150000
E39: =B36 -> Shift | F39: Total | L39: =SUM(L36:L38) -> 223873.41 | O39: =SUM(O36:O38) -> 8128.52 | Q39: =O39/L39 -> 0.036308555 | R39: -1 | S39: =+D37 -> 45631 | T39: =O39 -> 8128.52
B41: Rula - Realized | C41: 43719 | D41: 45611 | F41: Series Seed Preferred Stock | G41: SS-04 | I41: 386815 | K41: 0.14065434 | L41: =+I41*K41 -> 54407.207 | N41: =+O41/I41 -> 5.7816101 | O41: =2236413.5 -> 2236413.5 | S41: =IFERROR(C41,0) -> 43719 | T41: =-L41 -> -54407.207
C42: 43719 | D42: 45723 | F42: Series Seed Preferred Stock | I42: 1390592 | K42: 0.14065434 | L42: =+I42*K42 -> 195592.79 | N42: =+O42/I42 -> 5.6660177 | O42: 7879118.8 | S42: =IFERROR(C42,0) -> 43719 | T42: =-L42 -> -195592.79 | U42: Q1'25 Secondary Sale
C43: 44265 | D43: 45723 | F43: Series A-1 Preferred Stock | I43: 21334 | K43: 0.44273843 | L43: =+I43*K43 -> 9445.3816 | N43: =+O43/I43 -> 5.6659792 | O43: 120878 | S43: =IFERROR(C43,0) -> 44265 | T43: =-L43 -> -9445.3816 | U43: Q1'25 Secondary Sale
E44: =B41 -> Rula - Realized | F44: Total | I44: =SUM(I41:I43) -> 1798741 | K44: =+L44/$I$141 -> 0.23415627 | L44: =SUM(L41:L43) -> 259445.38 | N44: =+O44/$I$141 -> 9.2386291 | O44: =SUM(O41:O43) -> 10236410 | Q44: =O44/L44 -> 39.454972 | R44: =XIRR(T41:T44,S41:S44,0) -> 0.96135892 | S44: =+D42 -> 45723 | T44: =O44 -> 10236410
B46: Level | C46: 04/17/2020 | D46: 45747 | F46: Series A Preferred Stock | G46: PA-10 | I46: 163613 | K46: =L46/I46 -> 6.112 | L46: 1000002.7 | N46: 0 | O46: =$I46*N46 -> 0 | S46: =IFERROR(C46,0) -> 04/17/2020 | T46: =-L46 -> -1000002.7 | U46: Level Q1 write off
C47: 04/17/2020 | D47: 45747 | F47: Series A Warrants | I47: 163612 | K47: 0 | L47: 0.01
E49: =B46 -> Level | F49: Total | I49: =SUM(I46:I48) -> 327225 | K49: =L49/$I49 -> 3.0560094 | L49: =SUM(L46:L48) -> 1000002.7 | N49: =O49/$I49 -> 0 | O49: =SUM(O46:O48) -> 0 | Q49: =O49/L49 -> 0 | R49: -1 | S49: =$C$1 -> 45930 | T49: =O49 -> 0
B51: Valence | C51: 43721 | F51: Series Seed-3 Preferred Stock | G51: PS3-10 | I51: 214555 | K51: =+L51/#REF! -> #REF! | L51: 249999.49 | N51: 9.31 | O51: =N51*I51 -> 1997507.1 | S51: =IFERROR(C51,0) -> 43721 | T51: =-L51 -> -249999.49 | U51: Q3'25 Secondary Sale
E53: =B51 -> Valence | F53: Total | I53: =SUM(I51:I52) -> 214555 | K53: =+L53/#REF! -> #REF! | L53: =SUM(L51:L52) -> 249999.49 | N53: =+O53/#REF! -> #REF! | O53: =SUM(O51:O52) -> 1997507.1 | Q53: =O53/L53 -> 7.9900445 | R53: =XIRR(T51:T53,S51:S53,) -> 0.41844098 | S53: 45891 | T53: =O53 -> 1997507.1
U77: =O53-L53 -> 1747507.6
B78: Total Realized Portfolio | L78: =SUMIF($F$6:$F$77,"Total",L6:L77) -> 4015004.2 | O78: =SUMIF($F$6:$F$77,"Total",O6:O77) -> 13128087 | Q78: =IFERROR(O78/L78,0) -> 3.2697567 | R78: =XIRR(T7:T77,S7:S77,) -> 0.25423873
A80: UNREALIZED
S81: 43101 | T81: -0.1
B82: Carrot | C82: 43333 | F82: Series A-3 Preferred Stock (SAFE Conversion) | G82: PA3-4 | I82: 114210 | K82: =L82/I82 -> 0.87558007 | L82: 100000 | N82: 9.7426 | O82: =$I82*N82 -> 1112702.3 | S82: =IFERROR(C82,0) -> 43333 | T82: =-L82 -> -100000
C83: 43536 | F83: Series A Preferred Stock | G83: PA-13 | I83: 184604 | K83: =L83/I83 -> 1.6251001 | L83: 299999.97 | N83: =N82 -> 9.7426 | O83: =$I83*N83 -> 1798522.9 | S83: =IFERROR(C83,0) -> 43536 | T83: =-L83 -> -299999.97
C84: 44060 | F84: Series B Preferred Stock | G84: PB-11 | I84: 241120 | K84: =L84/I84 -> 1.658919 | L84: 399998.55 | N84: =N83 -> 9.7426 | O84: =$I84*N84 -> 2349135.7 | S84: =IFERROR(C84,0) -> 44060 | T84: =-L84 -> -399998.55
C85: 44369 | F85: Series C Preferred Stock | G85: PC-1 | I85: 41386 | K85: =L85/I85 -> 4.8325001 | L85: 199997.85 | N85: =N84 -> 9.7426 | O85: =$I85*N85 -> 403207.24 | S85: =IFERROR(C85,0) -> 44369 | T85: =-L85 -> -199997.85
E87: =B82 -> Carrot | F87: Total | I87: =SUM(I82:I85) -> 581320 | K87: =+L87/$I$87 -> 1.7202167 | L87: =SUM(L82:L85) -> 999996.37 | N87: =+O87/$I$87 -> 9.7426 | O87: =SUM(O82:O86) -> 5663568.2 | Q87: =O87/L87 -> 5.6635888 | R87: =XIRR(T82:T87,S82:S87,0) -> 0.35356258 | S87: =$C$1 -> 45930 | T87: =O87 -> 5663568.2 | V87: =O87/$O$202 -> 0.062359444
B89: Cleo | C89: 43328 | F89: Common Stock | G89: PA-15 | I89: 59171 | K89: =L89/I89 -> 1.6900171 | L89: 100000 | N89: 0 | O89: =$I89*N89 -> 0 | S89: =IFERROR(C89,0) -> 43328 | T89: =-L89 -> -100000
E91: =B89 -> Cleo | F91: Total | I91: =SUM(I89:I90) -> 59171 | K91: =L91/I91 -> 1.6900171 | L91: =SUM(L89:L90) -> 100000 | N91: =O91/$I91 -> 0 | O91: =SUM(O89:O90) -> 0 | Q91: =O91/L91 -> 0 | R91: -1 | S91: =$C$1 -> 45930 | T91: =O91 -> 0
B93: Hone | C93: 43262 | F93: Series Seed Preferred Stock (SAFE Conversion) | G93: PSEED-009 | I93: 70422.4 | K93: =L93/I93 -> 0.71000136 | L93: 50000 | N93: 3.0288 | O93: =+I93*N93 -> 213295.37 | S93: =IFERROR(C93,0) -> 43262 | T93: =-L93 -> -50000
C94: 43418 | F94: Series Seed Preferred Stock (SAFE Conversion) | G94: PSEED-009 | I94: 281689.6 | K94: =L94/I94 -> 0.71000136 | L94: 200000 | N94: =+N93 -> 3.0288 | O94: =+I94*N94 -> 853181.46 | S94: =IFERROR(C94,0) -> 43418 | T94: =-L94 -> -200000
C95: 44414 | F95: Series A Preferred Stock | G95: PA-2 | I95: 227899 | K95: =L95/I95 -> 1.8985001 | L95: 432666.27 | N95: =+N94 -> 3.0288 | O95: =+I95*N95 -> 690260.49 | S95: =IFERROR(C95,0) -> 44414 | T95: =-L95 -> -432666.27
E97: =B93 -> Hone | F97: Total | I97: =SUM(I93:I96) -> 580011 | K97: =+L97/$I$97 -> 1.1769885 | L97: =SUM(L93:L96) -> 682666.27 | N97: =+O97/$I$97 -> 3.0288 | O97: =SUM(O93:O96) -> 1756737.3 | Q97: =O97/L97 -> 2.5733472 | R97: =XIRR(T93:T97,S93:S97,0) -> 0.19311117 | S97: =$C$1 -> 45930 | T97: =O97 -> 1756737.3
B99: Spring | C99: 43244 | F99: Series Seed 4 Preferred Stock | G99: PS4-11 | I99: 175146 | K99: =L99/I99 -> 1.1419045 | L99: 200000 | N99: =67.87 -> 67.87 | O99: =$I99*N99 -> 11887159 | S99: =IFERROR(C99,0) -> 43244 | T99: =-L99 -> -200000
C100: 43838 | F100: Series A-2 Preferred Stock | G100: PA2-8 | I100: 174535 | K100: =L100/I100 -> 2.86474 | L100: 499997.4 | N100: =N99 -> 67.87 | O100: =$I100*N100 -> 11845690 | S100: =IFERROR(C100,0) -> 43838 | T100: =-L100 -> -499997.4
C101: 44145 | F101: Class B Common Stock | G101: CSB-4 | I101: 75268 | K101: 9.9643 | L101: =I101*K101 -> 749992.93 | N101: =N100 -> 67.87 | O101: =$I101*N101 -> 5108439.2 | S101: =IFERROR(C101,0) -> 44145 | T101: =-L101 -> -749992.93
E103: =B99 -> Spring | F103: Total | I103: =SUM(I99:I102) -> 424949 | K103: =L103/I103 -> 3.4121514 | L103: =SUM(L99:L102) -> 1449990.3 | N103: =O103/$I103 -> 67.87 | O103: =SUM(O99:O102) -> 28841289 | Q103: =O103/L103 -> 19.890677 | R103: =XIRR(T99:T103,S99:S103,0) -> 0.68471499 | S103: =$C$1 -> 45930 | T103: =O103 -> 28841289 | U103: =3.3*0.95 -> 3.135 | V103: =O103/O202 -> 0.31756071
B105: Multiverse | C105: 43395 | F105: Series Seed Preferred Stock | I105: 60300 | K105: =L105/I105 -> 2.2388 | L105: 134999.64 | N105: 56.1932 | O105: =$I105*N105 -> 3388450 | S105: =IFERROR(C105,0) -> 43395 | T105: =-L105 -> -134999.64
C106: 43719 | F106: Series A Preferred Stock | I106: 49573 | K106: =L106/I106 -> 4.0344 | L106: 199997.31 | N106: =N105 -> 56.1932 | O106: =$I106*N106 -> 2785665.5 | S106: =IFERROR(C106,0) -> 43719 | T106: =-L106 -> -199997.31
C107: 44239 | F107: Series B Preferred Stock | I107: 57012 | K107: =L107/I107 -> 8.77006 | L107: 499998.66 | N107: =N106 -> 56.1932 | O107: =I107*N107 -> 3203686.7 | S107: =IFERROR(C107,0) -> 44239 | T107: =-L107 -> -499998.66
K108: `
E109: =B105 -> Multiverse | F109: Total | I109: =SUM(I105:I108) -> 166885 | K109: =L109/I109 -> 5.0034192 | L109: =SUM(L105:L108) -> 834995.61 | N109: =O109/$I109 -> 56.1932 | O109: =SUM(O105:O108) -> 9377802.2 | Q109: =O109/L109 -> 11.23096 | R109: =XIRR(T105:T109,S105:S109,0) -> 0.54692257 | S109: =$C$1 -> 45930 | T109: =O109 -> 9377802.2 | V109: =O109/$O$202 -> 0.10325549
B111: Omada Health | C111: 43969 | F111: Common Stock | G111: CS-279 | I111: =57974/3-1 -> 19323.667 | K111: =L111/I111 -> 15.110282 | L111: 291986.05 | N111: 22.11 | O111: =$I111*N111 -> 427246.27 | S111: =IFERROR(C111,0) -> 43969 | T111: =-L111 -> -291986.05
C112: 44426 | F112: Common Stock | G112: CS-741 | I112: =2175 -> 2175 | K112: 0 | L112: 0 | N112: =N111 -> 22.11 | O112: =$I112*N112 -> 48089.25 | S112: =IFERROR(C112,0) -> 44426 | T112: =-L112 -> 0
E114: =B111 -> Omada Health | F114: Total | I114: =SUM(I111:I113) -> 21498.667 | K114: =L114/I114 -> 13.581589 | L114: =SUM(L111:L113) -> 291986.05 | N114: =O114/$I114 -> 22.11 | O114: =SUM(O111:O113) -> 475335.52 | Q114: =O114/L114 -> 1.6279391 | R114: =XIRR(T111:T114,S111:S114,0) -> 0.094944517 | S114: =$C$1 -> 45930 | T114: =O114 -> 475335.52
B117: Pelago | C117: 43558 | F117: Series A-3 Preferred Stock (SAFE Conversion) | G117: PSA3-4 | I117: 130864 | K117: =L117/I117 -> 2.2924563 | L117: 300000 | N117: 17.55 | O117: =I117*N117 -> 2296663.2 | S117: =IFERROR(C117,0) -> 43558 | T117: =-L117 -> -300000
C118: 44309 | F118: Common Stock Warrants | G118: CS-39 | I118: 98465 | K118: 0 | L118: 0 | N118: =N117 -> 17.55 | O118: =I118*N118 -> 1728060.8 | S118: =IFERROR(C118,0) -> 44309 | T118: =-L118 -> 0
C119: 44393 | F119: Series B Preferred Stock | G119: PB-6 | I119: 15064 | K119: =L119/I119 -> 16.5954 | L119: 249993.11 | N119: =N118 -> 17.55 | O119: =I119*N119 -> 264373.2 | S119: =IFERROR(C119,0) -> 44393 | T119: =-L119 -> -249993.11
E121: =B117 -> Pelago | F121: Total | I121: =SUM(I117:I118) -> 229329 | K121: =L121/$I121 -> 2.3982711 | L121: =SUM(L117:L120) -> 549993.11 | N121: =O121/$I121 -> 18.702812 | O121: =SUM(O117:O120) -> 4289097.2 | Q121: =O121/L121 -> 7.7984561 | R121: =XIRR(T117:T121,S117:S121,0) -> 0.43548993 | S121: =$C$1 -> 45930 | T121: =O121 -> 4289097.2
B123: Karat | C123: 43592 | F123: Series B Preferred Stock | G123: PB-15 | I123: 256686 | K123: =+L123/$I$123 -> 1.9479 | L123: 499998.66 | N123: =+K123 -> 1.9479 | O123: =I123*N123 -> 499998.66 | S123: =IFERROR(C123,0) -> 43592 | T123: =-L123 -> -499998.66
C124: 44132 | F124: Series B-1 Preferred Stock | G124: PB1-6 | I124: 177111 | K124: =+L124/$I$124 -> 2.8230667 | L124: 499996.17 | N124: =+K124 -> 2.8230667 | O124: =I124*N124 -> 499996.17 | S124: =IFERROR(C124,0) -> 44132 | T124: =-L124 -> -499996.17
E126: =B123 -> Karat | F126: Total | I126: =SUM(I123:I125) -> 433797 | K126: =+L126/$I$126 -> 2.3052138 | L126: =SUM(L123:L125) -> 999994.83 | N126: =+O126/$I$126 -> 2.3052138 | O126: =SUM(O123:O125) -> 999994.83 | Q126: =O126/L126 -> 1 | R126: =XIRR(T123:T126,S123:S126,0) -> 4.8828125e-09 | S126: =$C$1 -> 45930 | T126: =O126 -> 999994.83
B128: Hatch | C128: 43665 | F128: Ordinary Class B | I128: 1486 | K128: =+L128/$I$128 -> 174.22867 | L128: 258903.8 | N128: 90.141861 | O128: =I128*N128 -> 133950.81 | S128: =IFERROR(C128,0) -> 43665 | T128: =-L128 -> -258903.8
E130: =B128 -> Hatch | F130: Total | I130: =SUM(I128:I129) -> 1486 | K130: =+L130/$I$130 -> 174.22867 | L130: =SUM(L128:L129) -> 258903.8 | N130: =+O130/$I$130 -> 90.141861 | O130: =SUM(O128:O129) -> 133950.81 | Q130: =O130/L130 -> 0.51737674 | R130: =XIRR(T127:T130,S127:S130,0) -> 4.8828125e-09 | S130: =$C$1 -> 45930 | T130: =O130 -> 133950.81
B132: Human Interest | C132: 43670 | F132: Series B Preferred Stock | G132: PB-27 | I132: 406564 | K132: =+L132/I132 -> 0.6764 | L132: 274999.89 | N132: 15.53 | O132: =I132*N132 -> 6313938.9 | S132: =IFERROR(C132,0) -> 43670 | T132: =-L132 -> -274999.89 | X132: 150000 | Y132: 64588 | Z132: =+X132/Y132 -> 2.3224128 | AA132: =+N132/Z132 -> 6.6870109
C133: 43892 | F133: Series C Preferred Stock | G133: PC-11 | I133: 210793 | K133: =+L133/$I$133 -> 2.372 | L133: 500001 | N133: =N132 -> 15.53 | O133: =I133*N133 -> 3273615.3 | S133: =IFERROR(C133,0) -> 43892 | T133: =-L133 -> -500001 | Y133: =+Y132*1.5 -> 96882 | Z133: =+Y133*N132 -> 1504577.5 | AA133: =+Z133/150000 -> 10.030516
C134: 44187 | F134: Series C-1 Preferred Stock | G134: PC1-16 | I134: 74449 | K134: =+L134/I134 -> 4.2311001 | L134: 315001.17 | N134: =N133 -> 15.53 | O134: =I134*N134 -> 1156193 | S134: =IFERROR(C134,0) -> 44187 | T134: =-L134 -> -315001.17
E136: =B132 -> Human Interest | F136: Total | I136: =SUM(I132:I135) -> 691806 | K136: =+L136/$I$136 -> 1.5755892 | L136: =SUM(L132:L135) -> 1090002.1 | N136: =+O136/$I$136 -> 15.53 | O136: =SUM(O132:O135) -> 10743747 | Q136: =O136/L136 -> 9.8566302 | R136: =XIRR(T132:T136,S132:S136,0) -> 0.50923417 | S136: =$C$1 -> 45930 | T136: =O136 -> 10743747 | V136: =O136/$O$202 -> 0.11829541
B138: Rula
C139: 44265 | F139: Series A-1 Preferred Stock | G139: PA1-1 | I139: =1129335-21334 -> 1108001 | K139: =L139/I139 -> 0.44783294 | L139: 496199.35 | N139: =N43 -> 5.6659792 | O139: =I139*N139 -> 6277910.6 | S139: =IFERROR(C139,0) -> 44265 | T139: =-L139 -> -496199.35
E141: =B138 -> Rula | F141: Total | I141: =SUM(I138:I140) -> 1108001 | K141: =+L141/$I$141 -> 0.44783294 | L141: =SUM(L138:L140) -> 496199.35 | N141: =+O141/$I$141 -> 5.6659792 | O141: =SUM(O138:O140) -> 6277910.6 | Q141: =O141/L141 -> 12.651993 | R141: =XIRR(T139:T141,S139:S141,0) -> 0.74427286 | S141: =$C$1 -> 45930 | T141: =O141 -> 6277910.6 | V141: =O141/O202 -> 0.069123739
B144: Terminal | C144: 43727 | F144: Series A Preferred Stock | G144: PA-23 | I144: 1163918 | K144: =+L144/$I$144 -> 0.5155 | L144: 599999.73 | N144: 0 | O144: =+I144*N144 -> 0 | S144: =IFERROR(C144,0) -> 43727 | T144: =-L144 -> -599999.73
E146: =B144 -> Terminal | F146: Total | I146: =SUM(I144:I145) -> 1163918 | K146: 0 | L146: =SUM(L144:L145) -> 599999.73 | N146: 0 | O146: =SUM(O144:O145) -> 0 | Q146: =O146/L146 -> 0 | R146: -1 | S146: =$C$1 -> 45930 | T146: =O146 -> 0
B148: Kaladius | C148: 44186 | F148: Ordinary shares (Common Stock) | I148: 1500 | K148: 0.1997 | L148: =I148*K148 -> 299.55 | N148: =K148 -> 0.1997 | O148: =I148*N148 -> 299.55 | S148: =IFERROR(C148,0) -> 44186 | T148: =-L148 -> -299.55
C149: 44186 | F149: Preference Shares | I149: 60415 | K149: =120991/(1500*0.1+60415*1) -> 1.9977049 | L149: =I149*K149 -> 120691.34 | N149: =K149 -> 1.9977049 | O149: =I149*N149 -> 120691.34 | S149: =IFERROR(C149,0) -> 44186 | T149: =-L149 -> -120691.34
E151: =B148 -> Kaladius | F151: Total | I151: =SUM(I148:I150) -> 61915 | K151: 0 | L151: =SUM(L148:L150) -> 120990.89 | N151: 0 | O151: =SUM(O148:O150) -> 120990.89 | Q151: =O151/L151 -> 1 | R151: =XIRR(T148:T151,S148:S151,0) -> 4.8828125e-09 | S151: =$C$1 -> 45930 | T151: =O151 -> 120990.89
B153: Charthop | C153: 43740 | F153: Series Seed Preferred Stock | G153: PS-19 | I153: 59411 | K153: =+L153/I153 -> 1.6832001 | L153: 100000.6 | N153: =+K153 -> 1.6832001 | O153: =+I153*N153 -> 100000.6 | S153: =IFERROR(C153,0) -> 43740 | T153: =-L153 -> -100000.6
C154: 43970 | F154: Series A Preferred Stock | G154: PA-16 | I154: 127251 | K154: =+L154/I154 -> 4.7151001 | L154: 600001.2 | N154: =+K154 -> 4.7151001 | O154: =+I154*N154 -> 600001.2 | S154: =IFERROR(C154,0) -> 43970 | T154: =-L154 -> -600001.2
C155: 44351 | F155: Series B Preferred Stock | G155: PB-5 | I155: 33316 | K155: =+L155/I155 -> 15.0078 | L155: 499999.87 | N155: =+K155 -> 15.0078 | O155: =+I155*N155 -> 499999.87 | S155: =IFERROR(C155,0) -> 44351 | T155: =-L155 -> -499999.87
E157: =B153 -> Charthop | F157: Total | I157: =SUM(I153:I156) -> 219978 | K157: =+L157/I157 -> 5.4550986 | L157: =SUM(L153:L156) -> 1200001.7 | N157: =+O157/$I$157 -> 5.4550986 | O157: =SUM(O153:O156) -> 1200001.7 | Q157: =O157/L157 -> 1 | R157: =XIRR(T153:T157,S153:S157,0) -> 4.8828125e-09 | S157: =$C$1 -> 45930 | T157: =O157 -> 1200001.7
B159: Rightway Health | C159: 43768 | F159: Series A Preferred Stock | G159: PS-55 | I159: 242471 | K159: =L159/I159 -> 2.0621 | L159: 499999.45 | N159: 20.7765 | O159: =$I159*N159 -> 5037698.7 | S159: =IFERROR(C159,0) -> 43768 | T159: =-L159 -> -499999.45
C160: 44102 | F160: Series A Preferred Stock | G160: PS-56/PS-57 | I160: 39781 | K160: =L160/I160 -> 4.0039 | L160: 159279.15 | N160: =N159 -> 20.7765 | O160: =$I160*N160 -> 826509.95 | S160: =IFERROR(C160,0) -> 44102 | T160: =-L160 -> -159279.15
C161: 44102 | F161: Common Stock | G161: CS-43/CS-45/CS-46 | I161: 85097 | K161: =L161/I161 -> 4.0039 | L161: 340719.88 | N161: =N160 -> 20.7765 | O161: =$I161*N161 -> 1768017.8 | S161: =IFERROR(C161,0) -> 44102 | T161: =-L161 -> -340719.88
C162: =C1 -> 45930 | F162: Series A Warrants | G162: W-A-1 | I162: =I159 -> 242471 | K162: 0 | L162: 0 | N162: =(N159-K159) -> 18.7144 | O162: =+I162*N162 -> 4537699.3 | S162: =IFERROR(C162,0) -> 45930 | T162: =-L162 -> 0
C163: =C1 -> 45930 | F163: Series B Warrants | I163: =24976*3 -> 74928 | K163: 0 | L163: 0 | N163: =(N160-K160) -> 16.7726 | O163: =+I163*N163 -> 1256737.4 | S163: =IFERROR(C163,0) -> 45930 | T163: =-L163 -> 0
E165: =B159 -> Rightway Health | F165: Total | I165: =SUM(I159:I164) -> 684748 | K165: =L165/$I165 -> 1.460389 | L165: =SUM(L159:L164) -> 999998.47 | N165: =O165/$I165 -> 19.608182 | O165: =SUM(O159:O164) -> 13426663 | Q165: =O165/L165 -> 13.426684 | R165: =XIRR(T159:T165,S159:S165,0) -> 0.60154655 | S165: =$C$1 -> 45930 | T165: =O165 -> 13426663 | V165: =O165/O202 -> 0.147836
B167: Brightside Benefit | C167: 43775 | F167: Series A Preferred Stock | G167: PA-11 | I167: 398406 | K167: =L167/I167 -> 1.255 | L167: 499999.53 | N167: 1.1015 | O167: =$I167*N167 -> 438844.21 | S167: =IFERROR(C167,0) -> 43775 | T167: =-L167 -> -499999.53
E169: =B167 -> Brightside Benefit | F169: Total | I169: =SUM(I167:I168) -> 398406 | K169: =L169/$I169 -> 1.255 | L169: =SUM(L167:L168) -> 499999.53 | N169: =O169/$I169 -> 1.1015 | O169: =SUM(O167:O168) -> 438844.21 | Q169: =O169/L169 -> 0.87768924 | R169: =XIRR(T167:T169,S167:S169,0) -> -0.021854582 | S169: =$C$1 -> 45930 | T169: =O169 -> 438844.21
B171: Fountain | C171: 43789 | F171: Series B Preferred Stock | G171: PSB-21 | I171: 57389 | K171: =L171/I171 -> 7.0629166 | L171: 405333.72 | N171: 29.2344 | O171: =$I171*N171 -> 1677733 | S171: =IFERROR(C171,0) -> 43789 | T171: =-L171 -> -405333.72
E173: =B171 -> Fountain | F173: Total | I173: =SUM(I171:I172) -> 57389 | K173: =L173/$I173 -> 7.0629166 | L173: =SUM(L171:L172) -> 405333.72 | N173: =O173/$I173 -> 29.2344 | O173: =SUM(O171:O172) -> 1677733 | Q173: =O173/L173 -> 4.1391399 | R173: =XIRR(T171:T173,S171:S173,0) -> 0.27400609 | S173: =$C$1 -> 45930 | T173: =O173 -> 1677733
B175: XP | C175: 43817 | F175: Series A-2 Preferred Stock | I175: 407269 | K175: =L175/I175 -> 1.9643037 | L175: 800000 | N175: 4.8649 | O175: =$I175*N175 -> 1981323 | S175: =IFERROR(C175,0) -> 43817 | T175: =-L175 -> -800000
E177: =B175 -> XP | F177: Total | I177: =SUM(I175:I176) -> 407269 | K177: 0 | L177: =SUM(L175:L176) -> 800000 | N177: 0 | O177: =SUM(O175:O176) -> 1981323 | Q177: =O177/L177 -> 2.4766537 | R177: =XIRR(T175:T177,S175:S177,0) -> 0.16959731 | S177: =$C$1 -> 45930 | T177: =O177 -> 1981323
B179: Enrich | C179: 43829 | F179: Series Seed Preferred Stock | G179: UPS2-3 | I179: 612369 | K179: =L179/I179 -> 0.65320002 | L179: 399999.44 | N179: =K179 -> 0.65320002 | O179: 0 | S179: =IFERROR(C179,0) -> 43829 | T179: =-L179 -> -399999.44
E181: =B179 -> Enrich | F181: Total | I181: =SUM(I179:I180) -> 612369 | K181: =L181/$I181 -> 0.65320002 | L181: =SUM(L179:L180) -> 399999.44 | N181: =O181/$I181 -> 0 | O181: =SUM(O179:O180) -> 0 | Q181: =O181/L181 -> 0 | R181: -1 | S181: =$C$1 -> 45930 | T181: =O181 -> 0
...

Sheet Investment Characteristics
V1: =21*10^6 -> 21000000
B2: Initial Investment Characteristics | L2: Current Investment Characteristics
B3: Company | C3: Date | D3: Series | E3: Sector | F3: $ Invested | G3: VC Syndicate | H3: FD% | I3: PFD% | J3: Initial Cost | L3: Company | M3: Series | N3: FD% | O3: Initital Cost | P3: Avg. Cost | Q3: Last Valuation | R3: Holding Value | S3: $ Invested | T3: Market Value | U3: Multiple | W3: 2025E Revenue | X3: Holding Value Implied Mult. | Y3: EV at 10x | Z3: 10x EV> Holding Value | AB3: 44285 | AC3: 44469 | AD3: 44742 | AE3: 44925 | AF3: 45107 | AG3: 45290 | AH3: 45473 | AI3: 45565 | AJ3: 45657 | AK3: 45838 | AL3: 45930 | AM3: Comments | AN3: Runway
B4: Shift | C4: =INDEX('Statement of Investments'!$C$5:$C$204,MATCH('Investment Characteristics'!$B4,'Statement of Investments'!$B$5:$B$204,0)) -> 43390 | D4: Seed | E4: Workforce | F4: =INDEX('Statement of Investments'!$L$5:$L$204,MATCH('Investment Characteristics'!$B4,'Statement of Investments'!$B$5:$B$204,0)) -> 73873.412 | G4: a16z, Expa Capital, Structure Capital | H4: 0.006008 | I4: 0.0113 | J4: =IFERROR(ROUND(F4/H4,-6),0) -> 12000000 | L4: =B4 -> Shift | M4: Seed | N4: 0.0060080358 | O4: =J4 -> 12000000 | P4: =IFERROR(ROUND(S4/N4,-6),0) -> 37000000 | Q4: N/A | R4: N/A | S4: =INDEX('Statement of Investments'!$L$5:$L$204,MATCH('Investment Characteristics'!$L4,'Statement of Investments'!$E$5:$E$204,0)) -> 223873.41 | T4: =INDEX('Statement of Investments'!$O$5:$O$204,MATCH($L4,'Statement of Investments'!$E$5:$E$204,0)) -> 8128.52 | U4: =T4/S4 -> 0.036308555 | V4: =+$V$1/N4/10^6 -> 3495.3187 | AB4: -1 | AC4: -1 | AD4: -1 | AE4: -1 | AF4: -1 | AG4: -1
B5: Carrot | C5: =INDEX('Statement of Investments'!$C$5:$C$204,MATCH('Investment Characteristics'!$B5,'Statement of Investments'!$B$5:$B$204,0)) -> 43333 | D5: Seed | E5: Healthtech | F5: =INDEX('Statement of Investments'!$L$5:$L$204,MATCH('Investment Characteristics'!$B5,'Statement of Investments'!$B$5:$B$204,0)) -> 100000 | G5: USVP, CRV, Precursor Ventures, Maven Ventures, SoftTech, Y Combinator | H5: N/A | I5: N/A | J5: 10000000 | L5: =B5 -> Carrot | M5: D | N5: 0.0094339757 | O5: =J5 -> 10000000 | P5: =IFERROR(ROUND(S5/N5,-6),0) -> 106000000 | Q5: 600000000 | R5: 600000000 | S5: =INDEX('Statement of Investments'!$L$5:$L$204,MATCH('Investment Characteristics'!$L5,'Statement of Investments'!$E$5:$E$204,0)) -> 999996.37 | T5: =INDEX('Statement of Investments'!$O$5:$O$204,MATCH($L5,'Statement of Investments'!$E$5:$E$204,0)) -> 5663568.2 | U5: =T5/S5 -> 5.6635888 | V5: =+$V$1/N5/10^6 -> 2225.9968 | W5: =VLOOKUP(B5,'[1]Fund I RYG'!$B$4:N$23,13,0) -> No FS | AB5: 1 | AC5: 1 | AD5: 1 | AE5: 1 | AF5: 1 | AG5: 1 | AH5: 1 | AI5: 1 | AJ5: 1 | AK5: 1 | AL5: 1 | AM5: Scaling well with significant partnerships helping cover over 17,000 providers nationwide, expanded its U.S provider network significantly: adding ~4,200 new clinics/providers across all 50 states | AN5: -
B6: Cleo | C6: =INDEX('Statement of Investments'!$C$5:$C$204,MATCH('Investment Characteristics'!$B6,'Statement of Investments'!$B$5:$B$204,0)) -> 43328 | D6: A | E6: Healthtech | F6: =INDEX('Statement of Investments'!$L$5:$L$204,MATCH('Investment Characteristics'!$B6,'Statement of Investments'!$B$5:$B$204,0)) -> 100000 | G6: Felicis, Forerunner, Greylock | H6: 0.003 | I6: 0.0062 | J6: =IFERROR(ROUND(F6/H6,-6),0) -> 33000000 | L6: =B6 -> Cleo | M6: C | N6: ='Statement of Investments'!I91/35358112 -> 0.0016734774 | O6: =J6 -> 33000000 | P6: =IFERROR(ROUND(S6/N6,-6),0) -> 60000000 | Q6: =231*10^6 -> 231000000 | R6: 0 | S6: =INDEX('Statement of Investments'!$L$5:$L$204,MATCH('Investment Characteristics'!$L6,'Statement of Investments'!$E$5:$E$204,0)) -> 100000 | T6: =INDEX('Statement of Investments'!$O$5:$O$204,MATCH($L6,'Statement of Investments'!$E$5:$E$204,0)) -> 0 | U6: =T6/S6 -> 0 | V6: =+$V$1/N6/10^6 -> 12548.721 | W6: =VLOOKUP(B6,'[1]Fund I RYG'!$B$4:N$23,13,0) -> No FS | AB6: 1 | AC6: 1 | AD6: 1 | AE6: 0 | AF6: -1 | AG6: 0 | AH6: -1 | AI6: -1 | AJ6: -1 | AK6: -1 | AL6: -1 | AM6: Written off | AN6: -
B7: Hone | C7: =INDEX('Statement of Investments'!$C$5:$C$204,MATCH('Investment Characteristics'!$B7,'Statement of Investments'!$B$5:$B$204,0)) -> 43262 | D7: Seed | E7: Workforce | F7: =('Statement of Investments'!L93+'Statement of Investments'!L94) -> 250000 | G7: F-Prime, Cowboy, Slack Fund, Day One Ventures | H7: N/A | I7: N/A | J7: =8*10^6 -> 8000000 | L7: =B7 -> Hone | M7: B | N7: 0.013943702 | O7: =J7 -> 8000000 | P7: =IFERROR(ROUND(S7/N7,-6),0) -> 49000000 | Q7: 126200000 | R7: 126200000 | S7: =INDEX('Statement of Investments'!$L$5:$L$204,MATCH('Investment Characteristics'!$L7,'Statement of Investments'!$E$5:$E$204,0)) -> 682666.27 | T7: =INDEX('Statement of Investments'!$O$5:$O$204,MATCH($L7,'Statement of Investments'!$E$5:$E$204,0)) -> 1756737.3 | U7: =T7/S7 -> 2.5733472 | V7: =+$V$1/N7/10^6 -> 1506.0563 | W7: =VLOOKUP(B7,'[1]Fund I RYG'!$B$4:N$23,13,0) -> 7921721 | X7: =Q7/W7 -> 15.930882 | Y7: =W7*10 -> 79217210 | Z7: =IF(Y7>Q7,"Yes", "No") -> No | AB7: 1 | AC7: 1 | AD7: 1 | AE7: 1 | AF7: 0 | AG7: 0 | AH7: 0 | AI7: 0 | AJ7: 0 | AK7: 0 | AL7: -1 | AM7: Revenue is flat, opportunity to reinvigorate growth via AI automation? 8 month runway left | AN7: <1 year
B8: Spring | C8: =INDEX('Statement of Investments'!$C$5:$C$204,MATCH('Investment Characteristics'!$B8,'Statement of Investments'!$B$5:$B$204,0)) -> 43244 | D8: Seed | E8: Healthtech | F8: =INDEX('Statement of Investments'!$L$5:$L$204,MATCH('Investment Characteristics'!$B8,'Statement of Investments'!$B$5:$B$204,0)) -> 200000 | G8: Tiger Global, Northzone, RRE Ventures, Saddlefire Ventures | H8: 0.0088877053 | I8: 0.021434587 | J8: =IFERROR(ROUND(F8/H8,-6),0) -> 23000000 | L8: =B8 -> Spring | M8: E | N8: ='Statement of Investments'!I103/48624741 -> 0.0087393576 | O8: =J8 -> 23000000 | P8: =IFERROR(ROUND(S8/N8,-6),0) -> 166000000 | Q8: =3.3*10^9 -> 3300000000 | R8: 3300000000 | S8: =INDEX('Statement of Investments'!$L$5:$L$204,MATCH('Investment Characteristics'!$L8,'Statement of Investments'!$E$5:$E$204,0)) -> 1449990.3 | T8: =INDEX('Statement of Investments'!$O$5:$O$204,MATCH($L8,'Statement of Investments'!$E$5:$E$204,0)) -> 28841289 | U8: =T8/S8 -> 19.890677 | V8: =+$V$1/N8/10^6 -> 2402.9226 | W8: =VLOOKUP(B8,'[1]Fund I RYG'!$B$4:N$23,13,0) -> No FS | AB8: 1 | AC8: 1 | AD8: 1 | AE8: 1 | AF8: 1 | AG8: 1 | AH8: 1 | AI8: 1 | AJ8: 1 | AK8: 1 | AL8: 1 | AM8: Continues to beat plan and is approaching profitability | AN8: Potential IPO Candidate
B9: Multiverse | C9: =INDEX('Statement of Investments'!$C$5:$C$204,MATCH('Investment Characteristics'!$B9,'Statement of Investments'!$B$5:$B$204,0)) -> 43395 | D9: Seed | E9: Workforce | F9: =INDEX('Statement of Investments'!$L$5:$L$204,MATCH('Investment Characteristics'!$B9,'Statement of Investments'!$B$5:$B$204,0)) -> 134999.64 | G9: Index, LSVP, Village Global, General Catalyst | H9: 0.0051 | I9: 0.027396302 | J9: =IFERROR(ROUND(F9/H9,-6),0) -> 26000000 | L9: =B9 -> Multiverse | M9: D | N9: ='Statement of Investments'!I109/31006821 -> 0.0053822028 | O9: =J9 -> 26000000 | P9: =IFERROR(ROUND(S9/N9,-6),0) -> 155000000 | Q9: 1700000000 | R9: 1700000000 | S9: =INDEX('Statement of Investments'!$L$5:$L$204,MATCH('Investment Characteristics'!$L9,'Statement of Investments'!$E$5:$E$204,0)) -> 834995.61 | T9: =INDEX('Statement of Investments'!$O$5:$O$204,MATCH($L9,'Statement of Investments'!$E$5:$E$204,0)) -> 9377802.2 | U9: =T9/S9 -> 11.23096 | V9: =+$V$1/N9/10^6 -> 3901.7482 | W9: =VLOOKUP(B9,'[1]Fund I RYG'!$B$4:N$23,13,0) -> 100000000 | X9: =Q9/W9 -> 17 | Y9: =W9*10 -> 1000000000 | Z9: =IF(Y9>Q9,"Yes", "No") -> No | AB9: 1 | AC9: 1 | AD9: 1 | AE9: 0 | AF9: 0 | AG9: 0 | AH9: 1 | AI9: 1 | AJ9: 1 | AK9: 1 | AL9: 1 | AM9: AI retraining and upskilling providing tailwind, will finish Q4 with just over $70m of bookings, exceeding $62m forecast. Reported revenue was over $100m. Finished the year with Q4 growth YoY at 100%​, GM in Q4 reached 84%, +8pp YoY. Added > 250 new logos to customer list, launched in US, $38M Revenue in Q3 | AN9: 44 months
B10: Physera | C10: 43440 | D10: A | E10: Healthtech | F10: 500000 | G10: Slow Ventures, Blue Cross, Expa Capital, ID Ventures | H10: 0.0102 | I10: 0.021646627 | J10: 25000000 | L10: Physera | M10: Acquired | N10: Acquired | O10: Acquired | P10: Acquired | Q10: Acquired | R10: Acquired | S10: 500000 | T10: =INDEX('Statement of Investments'!$O$5:$O$204,MATCH($L10,'Statement of Investments'!$E$5:$E$204,0))+'Statement of Investments'!O114 -> 841423.8 | U10: =T10/S10 -> 1.6828476 | V10: =+$V$1/N10/10^6 -> #VALUE!
B11: Pill Club | C11: =INDEX('Statement of Investments'!$C$5:$C$204,MATCH('Investment Characteristics'!$B11,'Statement of Investments'!$B$5:$B$204,0)) -> 43473 | D11: B | E11: Healthtech | F11: =INDEX('Statement of Investments'!$L$5:$L$204,MATCH('Investment Characteristics'!$B11,'Statement of Investments'!$B$5:$B$204,0)) -> 999998.53 | G11: GV, Shasta Ventures, 500 Startups, VMG | H11: 0.004 | I11: 0.006 | J11: =IFERROR(ROUND(F11/H11,-6),0) -> 250000000 | L11: =B11 -> Pill Club | M11: N/A | N11: 0.004 | O11: =J11 -> 250000000 | P11: =IFERROR(ROUND(S11/N11,-6),0) -> 250000000 | Q11: 250000000 | R11: N/A | S11: =INDEX('Statement of Investments'!$L$5:$L$204,MATCH('Investment Characteristics'!$L11,'Statement of Investments'!$E$5:$E$204,0)) -> 999998.53 | T11: =INDEX('Statement of Investments'!$O$5:$O$204,MATCH($L11,'Statement of Investments'!$E$5:$E$204,0)) -> 0 | U11: =T11/S11 -> 0 | V11: =+$V$1/N11/10^6 -> 5250 | AB11: -1 | AC11: -1 | AD11: -1 | AE11: -1
B12: Pelago | C12: =INDEX('Statement of Investments'!$C$5:$C$204,MATCH('Investment Characteristics'!$B12,'Statement of Investments'!$B$5:$B$204,0)) -> 43558 | D12: Seed | E12: Healthtech | F12: =INDEX('Statement of Investments'!$L$5:$L$204,MATCH('Investment Characteristics'!$B12,'Statement of Investments'!$B$5:$B$204,0)) -> 300000 | G12: Village Global, EQT Ventures, Pioneer Fund, Y Combinator | H12: N/A | I12: N/A | J12: 18000000 | K12: Digital Therapeutic, Quit Genius | L12: =B12 -> Pelago | M12: C | N12: ='Statement of Investments'!I121/20022002 -> 0.01145385 | O12: =J12 -> 18000000 | P12: =IFERROR(ROUND(S12/N12,-6),0) -> 48000000 | Q12: =365*10^6 -> 365000000 | R12: 365000000 | S12: =INDEX('Statement of Investments'!$L$5:$L$204,MATCH('Investment Characteristics'!$L12,'Statement of Investments'!$E$5:$E$204,0)) -> 549993.11 | T12: =INDEX('Statement of Investments'!$O$5:$O$204,MATCH($L12,'Statement of Investments'!$E$5:$E$204,0)) -> 4289097.2 | U12: =T12/S12 -> 7.7984561 | V12: =+$V$1/N12/10^6 -> 1833.4447 | W12: =VLOOKUP(B12,'[1]Fund I RYG'!$B$4:N$23,13,0) -> 21150000 | X12: =Q12/W12 -> 17.257683 | Y12: =W12*10 -> 211500000 | Z12: =IF(Y12>Q12,"Yes", "No") -> No | AB12: 1 | AC12: 1 | AD12: 1 | AE12: 0 | AF12: 0 | AG12: 1 | AH12: 1 | AI12: 1 | AJ12: 1 | AK12: 1 | AL12: 0 | AM12: Revenue is down slightly, sig decrease in 2025 ARR but forecasted ARR $10M in H1 2026 | AN12: 13 months
B13: Karat | C13: =INDEX('Statement of Investments'!$C$5:$C$204,MATCH('Investment Characteristics'!$B13,'Statement of Investments'!$B$5:$B$204,0)) -> 43592 | D13: B | E13: Workforce | F13: =INDEX('Statement of Investments'!$L$5:$L$204,MATCH('Investment Characteristics'!$B13,'Statement of Investments'!$B$5:$B$204,0)) -> 499998.66 | G13: Tiger Global, Norwest VP, 8VC, Founder Collective | H13: 0.0036231999 | I13: 0.0074791174 | J13: =IFERROR(ROUND(F13/H13,-6),0) -> 138000000 | L13: =B13 -> Karat | M13: C | N13: ='Statement of Investments'!I126/92143512 -> 0.004707841 | O13: =J13 -> 138000000 | P13: =IFERROR(ROUND(S13/N13,-6),0) -> 212000000 | Q13: 1111200000 | R13: Preference Stack - $168M | S13: =INDEX('Statement of Investments'!$L$5:$L$204,MATCH('Investment Characteristics'!$L13,'Statement of Investments'!$E$5:$E$204,0)) -> 999994.83 | T13: =INDEX('Statement of Investments'!$O$5:$O$204,MATCH($L13,'Statement of Investments'!$E$5:$E$204,0)) -> 999994.83 | U13: =T13/S13 -> 1 | V13: =+$V$1/N13/10^6 -> 4460.6435 | W13: =VLOOKUP(B13,'[1]Fund I RYG'!$B$4:N$23,13,0) -> 23560937 | X13: =Q13/W13 -> 47.16281 | Y13: =W13*10 -> 235609370 | Z13: =IF(Y13>Q13,"Yes", "No") -> No | AB13: 1 | AC13: 1 | AD13: 0 | AE13: 0 | AF13: -1 | AG13: -1 | AH13: -1 | AI13: -1 | AJ13: 0 | AK13: 0 | AL13: 0 | AM13: Holding at preference stack, modest growth (1.4x) but 2+ years of runway. | AN13: 24 months
B14: Hatch | C14: =INDEX('Statement of Investments'!$C$5:$C$204,MATCH('Investment Characteristics'!$B14,'Statement of Investments'!$B$5:$B$204,0)) -> 43665 | D14: Seed | E14: Workforce | F14: =INDEX('Statement of Investments'!$L$5:$L$204,MATCH('Investment Characteristics'!$B14,'Statement of Investments'!$B$5:$B$204,0)) -> 258903.8 | G14: N/A | H14: 0.0104337 | I14: N/A | J14: =IFERROR(ROUND(F14/H14,-6),0) -> 25000000 | L14: =B14 -> Hatch | M14: Seed | N14: ='Statement of Investments'!I130/255154 -> 0.0058239338 | O14: =J14 -> 25000000 | P14: =IFERROR(ROUND(S14/N14,-6),0) -> 44000000 | Q14: 25000000 | R14: 25000000 | S14: =INDEX('Statement of Investments'!$L$5:$L$204,MATCH('Investment Characteristics'!$L14,'Statement of Investments'!$E$5:$E$204,0)) -> 258903.8 | T14: =INDEX('Statement of Investments'!$O$5:$O$204,MATCH($L14,'Statement of Investments'!$E$5:$E$204,0)) -> 133950.81 | U14: =T14/S14 -> 0.51737674 | V14: =+$V$1/N14/10^6 -> 3605.8102 | W14: =VLOOKUP(B14,'[1]Fund I RYG'!$B$4:N$23,13,0) -> 2974911 | X14: =Q14/W14 -> 8.4036127 | Y14: =W14*10 -> 29749110 | Z14: =IF(Y14>Q14,"Yes", "No") -> Yes | AB14: -1 | AC14: -1 | AD14: -1 | AE14: -1 | AF14: -1 | AG14: 0 | AH14: -1 | AI14: -1 | AJ14: 0 | AK14: 0 | AL14: -1 | AM14: Strong rev growth, ARR seems stalled ~$1M, not much info
B15: Human Interest | C15: =INDEX('Statement of Investments'!$C$5:$C$204,MATCH('Investment Characteristics'!$B15,'Statement of Investments'!$B$5:$B$204,0)) -> 43670 | D15: B | E15: Financial | F15: =INDEX('Statement of Investments'!$L$5:$L$204,MATCH('Investment Characteristics'!$B15,'Statement of Investments'!$B$5:$B$204,0)) -> 274999.89 | G15: Wing VP, Y Combinator, Softtech, Slow Ventures | H15: 0.007353 | I15: 0.0114 | J15: =IFERROR(ROUND(F15/H15,-6),0) -> 37000000 | L15: =B15 -> Human Interest | M15: D | N15: ='Statement of Investments'!I136/164819311 -> 0.0041973601 | O15: =J15 -> 37000000 | P15: =IFERROR(ROUND(S15/N15,-6),0) -> 260000000 | Q15: 3000000000 | R15: 3000000000 | S15: =INDEX('Statement of Investments'!$L$5:$L$204,MATCH('Investment Characteristics'!$L15,'Statement of Investments'!$E$5:$E$204,0)) -> 1090002.1 | T15: =INDEX('Statement of Investments'!$O$5:$O$204,MATCH($L15,'Statement of Investments'!$E$5:$E$204,0)) -> 10743747 | U15: =T15/S15 -> 9.8566302 | V15: =+$V$1/N15/10^6 -> 5003.1447 | W15: =VLOOKUP(B15,'[1]Fund I RYG'!$B$4:N$23,13,0) -> 144536000 | X15: =Q15/W15 -> 20.756075 | Y15: =W15*10 -> 1445360000 | Z15: =IF(Y15>Q15,"Yes", "No") -> No | AB15: 1 | AC15: 0 | AD15: 0 | AE15: 1 | AF15: 1 | AG15: 1 | AH15: 0 | AI15: 0 | AJ15: 0 | AK15: 0 | AL15: 1 | AM15: Strong revenue growth, working with 37% of all new 401(k) plans. Recent regulatory push to bring alternatives into plans. Q3 ARR at ~$162M
B16: Alice | C16: =INDEX('Statement of Investments'!$C$5:$C$204,MATCH('Investment Characteristics'!$B16,'Statement of Investments'!$B$5:$B$204,0)) -> 43705 | D16: A | E16: Financial | F16: =INDEX('Statement of Investments'!$L$5:$L$204,MATCH('Investment Characteristics'!$B16,'Statement of Investments'!$B$5:$B$204,0)) -> 600000.08 | G16: Trinity Ventures, Bain Capital, Bespoke | H16: 0.013036473 | I16: 0.02402046 | J16: =IFERROR(ROUND(F16/H16,-6),0) -> 46000000 | L16: =B16 -> Alice | M16: N/A | N16: N/A | O16: N/A | P16: N/A | Q16: N/A | R16: N/A | S16: =INDEX('Statement of Investments'!$L$5:$L$204,MATCH('Investment Characteristics'!$L16,'Statement of Investments'!$E$5:$E$204,0)) -> 600000.08 | T16: =INDEX('Statement of Investments'!$O$5:$O$204,MATCH($L16,'Statement of Investments'!$E$5:$E$204,0)) -> 0 | U16: =T16/S16 -> 0 | V16: =+$V$1/N16/10^6 -> #VALUE! | AB16: 0 | AC16: -1 | AD16: -1 | AE16: -1 | AF16: -1 | AG16: -1 | AH16: -1
B17: Rula | C17: =INDEX('Statement of Investments'!$C$5:$C$204,MATCH('Investment Characteristics'!$B17,'Statement of Investments'!$B$5:$B$204,0)) -> 0 | D17: Seed | E17: Healthtech | F17: 250000 | G17: Wing, Upfront VP | H17: 0.0161 | I17: 0.04572245 | J17: =IFERROR(ROUND(F17/H17,-6),0) -> 16000000 | L17: =B17 -> Rula | M17: C | N17: ='Statement of Investments'!I141/210804936 -> 0.0052560487 | O17: =J17 -> 16000000 | P17: =IFERROR(ROUND(S17/N17,-6),0) -> 144000000 | Q17: =1250*10^6 -> 1250000000 | R17: 1250000000 | S17: =INDEX('Statement of Investments'!$L$5:$L$204,MATCH('Investment Characteristics'!$L17,'Statement of Investments'!$E$5:$E$204,0))+'Statement of Investments'!L44 -> 755644.73 | T17: =INDEX('Statement of Investments'!$O$5:$O$204,MATCH($L17,'Statement of Investments'!$E$5:$E$204,0)) -> 6277910.6 | U17: =T17/S17 -> 8.3080188 | V17: =+$V$1/N17/10^6 -> 3995.3968 | W17: =VLOOKUP(B17,'[1]Fund I RYG'!$B$4:N$23,13,0) -> 236000000 | X17: =Q17/W17 -> 5.2966102 | Y17: =W17*10 -> 2360000000 | Z17: =IF(Y17>Q17,"Yes", "No") -> Yes | AB17: 1 | AC17: 1 | AD17: 1 | AE17: 1 | AF17: 1 | AG17: 1 | AH17: 1 | AI17: 1 | AJ17: 1 | AK17: 1 | AL17: 1 | AM17: Forecasting ~2x y/y growth with revenue run rate above $200M by year end
B18: Valence | C18: =INDEX('Statement of Investments'!$C$5:$C$204,MATCH('Investment Characteristics'!$B18,'Statement of Investments'!$B$5:$B$204,0)) -> 43721 | D18: Seed | E18: Workforce | F18: =INDEX('Statement of Investments'!$L$5:$L$204,MATCH('Investment Characteristics'!$B18,'Statement of Investments'!$B$5:$B$204,0)) -> 249999.49 | G18: IVP, Resolute, Magnetico Ventures | H18: 0.0141 | I18: 0.034148284 | J18: =IFERROR(ROUND(F18/H18,-6),0) -> 18000000 | L18: =B18 -> Valence | M18: Realized | N18: 0.0098479775 | O18: =J18 -> 18000000 | P18: =IFERROR(ROUND(S18/N18,-6),0) -> 25000000 | Q18: 265000000 | R18: 265000000 | S18: =INDEX('Statement of Investments'!$L$5:$L$204,MATCH('Investment Characteristics'!$L18,'Statement of Investments'!$E$5:$E$204,0)) -> 249999.49 | T18: =INDEX('Statement of Investments'!$O$5:$O$204,MATCH($L18,'Statement of Investments'!$E$5:$E$204,0)) -> 1997507.1 | U18: =T18/S18 -> 7.9900445 | V18: =+$V$1/N18/10^6 -> 2132.4175 | X18: =Q18/W18 -> #DIV/0! | Y18: =W18*10 -> 0 | Z18: =IF(Y18>Q18,"Yes", "No") -> No | AB18: -1 | AC18: 1 | AD18: 1 | AE18: 2 | AF18: 1 | AG18: 0 | AH18: 0 | AI18: 0 | AJ18: 1 | AK18: 1 | AM18: Fully Realized - Secondary at Series B
B19: Terminal | C19: =INDEX('Statement of Investments'!$C$5:$C$204,MATCH('Investment Characteristics'!$B19,'Statement of Investments'!$B$5:$B$204,0)) -> 43727 | D19: B | E19: Workforce | F19: =INDEX('Statement of Investments'!$L$5:$L$204,MATCH('Investment Characteristics'!$B19,'Statement of Investments'!$B$5:$B$204,0)) -> 599999.73 | G19: KPCB, LSVP, 8VC, Craft Ventures | H19: 0.004370656 | I19: 0.011327246 | J19: =IFERROR(ROUND(F19/H19,-6),0) -> 137000000 | L19: =B19 -> Terminal | M19: B | N19: ='Statement of Investments'!I146/278640874 -> 0.0041771259 | O19: =J19 -> 137000000 | P19: =IFERROR(ROUND(S19/N19,-6),0) -> 144000000 | Q19: 137000000 | R19: 0 | S19: =INDEX('Statement of Investments'!$L$5:$L$204,MATCH('Investment Characteristics'!$L19,'Statement of Investments'!$E$5:$E$204,0)) -> 599999.73 | T19: =INDEX('Statement of Investments'!$O$5:$O$204,MATCH($L19,'Statement of Investments'!$E$5:$E$204,0)) -> 0 | U19: =T19/S19 -> 0 | V19: =+$V$1/N19/10^6 -> 5027.3802 | W19: =VLOOKUP(B19,'[1]Fund I RYG'!$B$4:N$23,13,0) -> 47509757 | X19: =Q19/W19 -> 2.8836182 | Y19: =W19*10 -> 475097570 | Z19: =IF(Y19>Q19,"Yes", "No") -> Yes | AB19: 1 | AC19: 1 | AD19: 0 | AE19: -1 | AF19: -1 | AG19: -1 | AH19: 0 | AI19: 0 | AJ19: -1 | AK19: -1 | AL19: -1 | AM19: Cash flow positive mid-next year, revenue is flat
B20: Sapling | C20: =INDEX('Statement of Investments'!$C$5:$C$204,MATCH('Investment Characteristics'!$B20,'Statement of Investments'!$B$5:$B$204,0)) -> 43728 | D20: Seed | E20: Workforce | F20: 249998.37 | G20: Gradient Ventures, TuesdayVC | H20: 0.015179095 | I20: 0.029675863 | J20: =IFERROR(ROUND(F20/H20,-6),0) -> 16000000 | L20: =B20 -> Sapling | M20: Acquired | N20: Acquired | O20: Acquired | P20: Acquired | Q20: Acquired | R20: Acquired | S20: 249998.37 | T20: =INDEX('Statement of Investments'!$O$5:$O$204,MATCH($L20,'Statement of Investments'!$E$5:$E$204,0))+'Statement of Investments'!O151 -> 324118.28 | U20: =T20/S20 -> 1.2964816 | V20: =+$V$1/N20/10^6 -> #VALUE!
B21: Charthop | C21: =INDEX('Statement of Investments'!$C$5:$C$204,MATCH('Investment Characteristics'!$B21,'Statement of Investments'!$B$5:$B$204,0)) -> 43740 | D21: Seed | E21: Workforce | F21: =INDEX('Statement of Investments'!$L$5:$L$204,MATCH('Investment Characteristics'!$B21,'Statement of Investments'!$B$5:$B$204,0)) -> 100000.6 | G21: a16z, Cowboy, Flybridge | H21: 0.004 | I21: 0.020000121 | J21: =IFERROR(ROUND(F21/H21,-6),0) -> 25000000 | L21: =B21 -> Charthop | M21: C | N21: ='Statement of Investments'!I157/26710961 -> 0.0082354955 | O21: =J21 -> 25000000 | P21: =IFERROR(ROUND(S21/N21,-6),0) -> 146000000 | Q21: 270000000 | R21: Preference Stack - $74M | S21: =INDEX('Statement of Investments'!$L$5:$L$204,MATCH('Investment Characteristics'!$L21,'Statement of Investments'!$E$5:$E$204,0)) -> 1200001.7 | T21: =INDEX('Statement of Investments'!$O$5:$O$204,MATCH($L21,'Statement of Investments'!$E$5:$E$204,0)) -> 1200001.7 | U21: =T21/S21 -> 1 | V21: =+$V$1/N21/10^6 -> 2549.9376 | W21: =VLOOKUP(B21,'[1]Fund I RYG'!$B$4:N$23,13,0) -> 8668373 | X21: =Q21/W21 -> 31.147714 | Y21: =W21*10 -> 86683730 | Z21: =IF(Y21>Q21,"Yes", "No") -> No | AB21: 1 | AC21: 1 | AD21: 0 | AE21: 1 | AF21: 0 | AG21: -1 | AH21: -1 | AI21: -1 | AJ21: -1 | AK21: 0 | AL21: -1 | AM21: Revenue forecast is up ~9%, signed new business with Kraken, ~1.5 yrs of runway, holding at preference stack, forecasting ~12M by end of 2026. ARR up 7% YOY | AN21: 16 months
B22: Rightway Health | C22: =INDEX('Statement of Investments'!$C$5:$C$204,MATCH('Investment Characteristics'!$B22,'Statement of Investments'!$B$5:$B$204,0)) -> 43768 | D22: A | E22: Healthtech | F22: =INDEX('Statement of Investments'!$L$5:$L$204,MATCH('Investment Characteristics'!$B22,'Statement of Investments'!$B$5:$B$204,0)) -> 499999.45 | G22: Khosla Ventures, Tiger Global, Thrive Capital, Rizk Ventures | H22: 0.014478246 | I22: 0.050139539 | J22: =IFERROR(ROUND(F22/H22,-6),0) -> 35000000 | L22: =B22 -> Rightway Health | M22: D | N22: ='Statement of Investments'!I165/29998005 -> 0.022826451 | O22: =J22 -> 35000000 | P22: =IFERROR(ROUND(S22/N22,-6),0) -> 44000000 | Q22: =625*10^6 -> 625000000 | R22: 625000000 | S22: =INDEX('Statement of Investments'!$L$5:$L$204,MATCH('Investment Characteristics'!$L22,'Statement of Investments'!$E$5:$E$204,0)) -> 999998.47 | T22: =INDEX('Statement of Investments'!$O$5:$O$204,MATCH($L22,'Statement of Investments'!$E$5:$E$204,0)) -> 13426663 | U22: =T22/S22 -> 13.426684 | V22: =+$V$1/N22/10^6 -> 919.98532 | W22: =VLOOKUP(B22,'[1]Fund I RYG'!$B$4:N$23,13,0) -> 45000000 | X22: =Q22/W22 -> 13.888889 | Y22: =W22*10 -> 450000000 | Z22: =IF(Y22>Q22,"Yes", "No") -> No | AB22: 1 | AC22: 1 | AD22: 1 | AE22: 0 | AF22: 1 | AG22: 1 | AH22: 1 | AI22: 1 | AJ22: 1 | AK22: 1 | AL22: 1 | AM22: ARR is projected to to grow to $132M or by 60% by H12026. Strong retention and growth metrics | AN22: 36 months
B23: Brightside Benefit | C23: =INDEX('Statement of Investments'!$C$5:$C$204,MATCH('Investment Characteristics'!$B23,'Statement of Investments'!$B$5:$B$204,0)) -> 43775 | D23: A | E23: Financial | F23: =INDEX('Statement of Investments'!$L$5:$L$204,MATCH('Investment Characteristics'!$B23,'Statement of Investments'!$B$5:$B$204,0)) -> 499999.53 | G23: a16z, Comcast Ventures, Trinity Ventures | H23: 0.0037 | I23: 0.0065 | J23: =IFERROR(ROUND(F23/H23,-6),0) -> 135000000 | L23: =B23 -> Brightside Benefit | M23: B | N23: ='Statement of Investments'!I169/200417480 -> 0.0019878805 | O23: =J23 -> 135000000 | P23: =IFERROR(ROUND(S23/N23,-6),0) -> 252000000 | Q23: 195000000 | R23: 195000000 | S23: =INDEX('Statement of Investments'!$L$5:$L$204,MATCH('Investment Characteristics'!$L23,'Statement of Investments'!$E$5:$E$204,0)) -> 499999.53 | T23: =INDEX('Statement of Investments'!$O$5:$O$204,MATCH($L23,'Statement of Investments'!$E$5:$E$204,0)) -> 438844.21 | U23: =T23/S23 -> 0.87768924 | V23: =+$V$1/N23/10^6 -> 10564.015 | W23: =VLOOKUP(B23,'[1]Fund I RYG'!$B$4:N$23,13,0) -> 29602894 | X23: =Q23/W23 -> 6.5871938 | Y23: =W23*10 -> 296028940 | Z23: =IF(Y23>Q23,"Yes", "No") -> Yes | AB23: -1 | AC23: 0 | AD23: 0 | AE23: 1 | AF23: 1 | AG23: 0 | AH23: 0 | AI23: 0 | AJ23: -1 | AK23: 0 | AL23: 0 | AM23: Closed a round and scaled to $30M ARR with major partnerships
B24: Fountain | C24: =INDEX('Statement of Investments'!$C$5:$C$204,MATCH('Investment Characteristics'!$B24,'Statement of Investments'!$B$5:$B$204,0)) -> 43789 | D24: B | E24: Workforce | F24: =INDEX('Statement of Investments'!$L$5:$L$204,MATCH('Investment Characteristics'!$B24,'Statement of Investments'!$B$5:$B$204,0)) -> 405333.72 | G24: Softtech, Crosslink Ventures, Slow Ventures, DCM, Y Combinator | H24: 0.0051 | I24: 0.009029578 | J24: =IFERROR(ROUND(F24/H24,-6),0) -> 79000000 | L24: =B24 -> Fountain | M24: C | N24: 0.0019508497 | O24: =J24 -> 79000000 | P24: =IFERROR(ROUND(S24/N24,-6),0) -> 256000000 | Q24: 860000000 | R24: 860000000 | S24: 499996.82 | T24: =INDEX('Statement of Investments'!$O$5:$O$204,MATCH($L24,'Statement of Investments'!$E$5:$E$204,0))+'Statement of Investments'!O14 -> 1772396.1 | U24: =T24/S24 -> 3.5448147 | V24: =+$V$1/N24/10^6 -> 10764.54 | W24: =VLOOKUP(B24,'[1]Fund I RYG'!$B$4:N$23,13,0) -> 32719597 | X24: =Q24/W24 -> 26.283942 | Y24: =W24*10 -> 327195970 | Z24: =IF(Y24>Q24,"Yes", "No") -> No | AB24: 1 | AC24: 1 | AD24: 1 | AE24: 0 | AF24: 0 | AG24: 0 | AH24: 0 | AI24: 0 | AJ24: 0 | AK24: 0 | AL24: 0 | AM24: Revenue is down, ARR forecasts revised down from ~41M to $34M | AN24: 34 months
B25: XP | C25: =INDEX('Statement of Investments'!$C$5:$C$204,MATCH('Investment Characteristics'!$B25,'Statement of Investments'!$B$5:$B$204,0)) -> 43817 | D25: Seed | E25: Financial | F25: =INDEX('Statement of Investments'!$L$5:$L$204,MATCH('Investment Characteristics'!$B25,'Statement of Investments'!$B$5:$B$204,0)) -> 800000 | G25: Valor Capital, Village Global | H25: N/A | I25: N/A | J25: =12*10^6 -> 12000000 | L25: =B25 -> XP | M25: B | N25: ='Statement of Investments'!I177/24666608 -> 0.016510945 | O25: =J25 -> 12000000 | P25: =IFERROR(ROUND(S25/N25,-6),0) -> 48000000 | Q25: =120000000 -> 120000000 | R25: 120000000 | S25: =INDEX('Statement of Investments'!$L$5:$L$204,MATCH('Investment Characteristics'!$L25,'Statement of Investments'!$E$5:$E$204,0)) -> 800000 | T25: =INDEX('Statement of Investments'!$O$5:$O$204,MATCH($L25,'Statement of Investments'!$E$5:$E$204,0)) -> 1981323 | U25: =T25/S25 -> 2.4766537 | V25: =+$V$1/N25/10^6 -> 1271.8836 | W25: =VLOOKUP(B25,'[1]Fund I RYG'!$B$4:N$23,13,0) -> 12542758 | X25: =Q25/W25 -> 9.5672738 | Y25: =W25*10 -> 125427580 | Z25: =IF(Y25>Q25,"Yes", "No") -> Yes | AB25: 1 | AC25: 0 | AD25: 0 | AE25: 1 | AF25: 1 | AG25: 1 | AH25: 1 | AI25: 1 | AJ25: 1 | AK25: 1 | AL25: 0 | AM25: Slight ARR growth in Q3/25 with the launch of a few smaller clients, followed by material growth in Q4/25 . Based upon the implemented expense reductions, included a substantial reduction of our staff, we expect to reach breakeven without the need for external capital | AN25: -
B26: Enrich | C26: =INDEX('Statement of Investments'!$C$5:$C$204,MATCH('Investment Characteristics'!$B26,'Statement of Investments'!$B$5:$B$204,0)) -> 43829 | D26: Seed | E26: Workforce | F26: =INDEX('Statement of Investments'!$L$5:$L$204,MATCH('Investment Characteristics'!$B26,'Statement of Investments'!$B$5:$B$204,0)) -> 399999.44 | G26: Cowboy Ventures, Bloomberg Beta, Slow Ventures | H26: 0.038095113 | I26: 0.098002278 | J26: =IFERROR(ROUND(F26/H26,-6),0) -> 11000000 | L26: =B26 -> Enrich | M26: Seed | N26: 0.038095113 | O26: =J26 -> 11000000 | P26: =IFERROR(ROUND(S26/N26,-6),0) -> 11000000 | Q26: 11000000 | R26: 0 | S26: =INDEX('Statement of Investments'!$L$5:$L$204,MATCH('Investment Characteristics'!$L26,'Statement of Investments'!$E$5:$E$204,0)) -> 399999.44 | T26: =INDEX('Statement of Investments'!$O$5:$O$204,MATCH($L26,'Statement of Investments'!$E$5:$E$204,0)) -> 0 | U26: =T26/S26 -> 0 | V26: =+$V$1/N26/10^6 -> 551.25181 | W26: =VLOOKUP(B26,'[1]Fund I RYG'!$B$4:N$23,13,0) -> 1038000 | X26: =Q26/W26 -> 10.597303 | Y26: =W26*10 -> 10380000 | Z26: =IF(Y26>Q26,"Yes", "No") -> No | AB26: -1 | AC26: -1 | AD26: -1 | AE26: -1 | AF26: -1 | AG26: -1 | AH26: -1 | AI26: -1 | AJ26: -1 | AK26: -1 | AL26: -1 | AM26: N/A - write-off | AN26: 30 months
B27: Vetty | C27: =INDEX('Statement of Investments'!$C$5:$C$204,MATCH('Investment Characteristics'!$B27,'Statement of Investments'!$B$5:$B$204,0)) -> 43857 | D27: Seed | E27: Workforce | F27: =INDEX('Statement of Investments'!$L$5:$L$204,MATCH('Investment Characteristics'!$B27,'Statement of Investments'!$B$5:$B$204,0)) -> 255034 | G27: Quake Capital, Plug & Play Ventures, Newark Ventures | H27: N/A | I27: N/A | J27: =13*10^6 -> 13000000 | L27: =B27 -> Vetty | M27: A | N27: N/A | O27: =J27 -> 13000000 | P27: =J27 -> 13000000 | Q27: 13000000 | R27: 0 | S27: =INDEX('Statement of Investments'!$L$5:$L$204,MATCH('Investment Characteristics'!$L27,'Statement of Investments'!$E$5:$E$204,0)) -> 255034 | T27: =INDEX('Statement of Investments'!$O$5:$O$204,MATCH($L27,'Statement of Investments'!$E$5:$E$204,0)) -> 0 | U27: =T27/S27 -> 0 | V27: =+$V$1/N27/10^6 -> #VALUE! | W27: =VLOOKUP(B27,'[1]Fund I RYG'!$B$4:N$23,13,0) -> 10707807 | X27: =Q27/W27 -> 1.2140675 | Y27: =W27*10 -> 107078070 | Z27: =IF(Y27>Q27,"Yes", "No") -> Yes | AB27: 0 | AC27: 0 | AD27: 0 | AE27: -1 | AF27: -1 | AG27: -1 | AH27: 0 | AI27: 0 | AJ27: 0 | AK27: -1 | AL27: -1 | AM27: N/A - proactive write-off, ARR revised down from $14M to $12M, 4 months of runway | AN27: 4 months
B28: Ladder | C28: =INDEX('Statement of Investments'!$C$5:$C$204,MATCH('Investment Characteristics'!$B28,'Statement of Investments'!$B$5:$B$204,0)) -> 43866 | D28: C | E28: Financial | F28: =INDEX('Statement of Investments'!$L$5:$L$204,MATCH('Investment Characteristics'!$B28,'Statement of Investments'!$B$5:$B$204,0)) -> 749994.59 | G28: Canaan Partners, LSVP, RRE Ventures | H28: 0.0032007724 | I28: 0.0053509755 | J28: =IFERROR(ROUND(F28/H28,-6),0) -> 234000000 | L28: =B28 -> Ladder | M28: D | N28: 0.0024800544 | O28: =J28 -> 234000000 | P28: =IFERROR(ROUND(S28/N28,-6),0) -> 302000000 | Q28: =330*10^6 -> 330000000 | R28: 330000000 | S28: =INDEX('Statement of Investments'!$L$5:$L$204,MATCH('Investment Characteristics'!$L28,'Statement of Investments'!$E$5:$E$204,0)) -> 749994.59 | T28: =INDEX('Statement of Investments'!$O$5:$O$204,MATCH($L28,'Statement of Investments'!$E$5:$E$204,0)) -> 759917.21 | U28: =T28/S28 -> 1.0132302 | V28: =+$V$1/N28/10^6 -> 8467.5563 | W28: =VLOOKUP(B28,'[1]Fund I RYG'!$B$4:N$23,13,0) -> 52027760 | X28: =Q28/W28 -> 6.3427678 | Y28: =W28*10 -> 520277600 | Z28: =IF(Y28>Q28,"Yes", "No") -> Yes | AB28: 1 | AC28: 1 | AD28: 1 | AE28: 2 | AF28: 0 | AG28: 0 | AH28: 0 | AI28: 0 | AJ28: 0 | AK28: 0 | AL28: 0 | AM28: Recapitalized business, at $50M revenue run rate
B29: Galileo | C29: =INDEX('Statement of Investments'!$C$5:$C$204,MATCH('Investment Characteristics'!$B29,'Statement of Investments'!$B$5:$B$204,0)) -> 43866 | D29: B | E29: Healthtech | F29: =INDEX('Statement of Investments'!$L$5:$L$204,MATCH('Investment Characteristics'!$B29,'Statement of Investments'!$B$5:$B$204,0)) -> 749998.67 | G29: 8VC, Obvious Ventures, Oak HC/FT | H29: 0.0071 | I29: 0.0142 | J29: =IFERROR(ROUND(F29/H29,-6),0) -> 106000000 | L29: =B29 -> Galileo | M29: C | N29: ='Statement of Investments'!I196/755343150 -> 0.0076985619 | O29: =J29 -> 106000000 | P29: =IFERROR(ROUND(S29/N29,-6),0) -> 228000000 | Q29: 361500000 | R29: 361500000 | S29: =INDEX('Statement of Investments'!$L$5:$L$204,MATCH('Investment Characteristics'!$L29,'Statement of Investments'!$E$5:$E$204,0)) -> 1752253.3 | T29: =INDEX('Statement of Investments'!$O$5:$O$204,MATCH($L29,'Statement of Investments'!$E$5:$E$204,0)) -> 2656434 | U29: =T29/S29 -> 1.5160103 | V29: =+$V$1/N29/10^6 -> 2727.7822 | W29: =VLOOKUP(B29,'[1]Fund I RYG'!$B$4:N$23,13,0) -> 47000000 | X29: =Q29/W29 -> 7.6914894 | Y29: =W29*10 -> 470000000 | Z29: =IF(Y29>Q29,"Yes", "No") -> Yes | AB29: 1 | AC29: 0 | AD29: 0 | AE29: 1 | AF29: 0 | AG29: -1 | AH29: -1 | AI29: -1 | AJ29: -1 | AK29: -1 | AL29: 0 | AM29: Completed recap in Q3, completing transition away from shared savings to FFS / Capitated, $16M loan from SVB | AN29: Budget in flux
B30: Level | C30: =INDEX('Statement of Investments'!$C$5:$C$204,MATCH('Investment Characteristics'!$B30,'Statement of Investments'!$B$5:$B$204,0)) -> 04/17/2020 | D30: A | E30: Financial | F30: =INDEX('Statement of Investments'!$L$5:$L$204,MATCH('Investment Characteristics'!$B30,'Statement of Investments'!$B$5:$B$204,0)) -> 1000002.7 | G30: Khosla, LSVP, First Round, Homebrew | H30: ='Statement of Investments'!$I$46/20451805 -> 0.0079999296 | I30: N/A | J30: =IFERROR(ROUND(F30/H30,-6),0) -> 125000000 | L30: =B30 -> Level | M30: B | N30: =H30*0.9 -> 0.0071999366 | O30: =J30 -> 125000000 | P30: =IFERROR(ROUND(S30/N30,-6),0) -> 139000000 | Q30: =70*10^6 -> 70000000 | R30: 0 | S30: =INDEX('Statement of Investments'!$L$5:$L$204,MATCH('Investment Characteristics'!$L30,'Statement of Investments'!$E$5:$E$204,0)) -> 1000002.7 | T30: =INDEX('Statement of Investments'!$O$5:$O$204,MATCH($L30,'Statement of Investments'!$E$5:$E$204,0)) -> 0 | U30: =T30/S30 -> 0 | V30: =+$V$1/N30/10^6 -> 2916.6923 | AB30: 1 | AC30: 1 | AD30: 0 | AE30: 0 | AF30: 0 | AG30: 0 | AH30: 0 | AI30: 0 | AJ30: -1 | AK30: -1 | AM30: Written off
B31: Forage | C31: =INDEX('Statement of Investments'!$C$5:$C$204,MATCH('Investment Characteristics'!$B31,'Statement of Investments'!$B$5:$B$204,0)) -> 44014 | D31: A | E31: Workforce | F31: =INDEX('Statement of Investments'!$L$5:$L$204,MATCH('Investment Characteristics'!$B31,'Statement of Investments'!$B$5:$B$204,0)) -> 249999.58 | G31: LSVP, Y Combinator | H31: =F31/J31 -> 0.0064102456 | I31: N/A | J31: =39*10^6 -> 39000000 | L31: =B31 -> Forage | M31: B | N31: 0.00479 | O31: =J31 -> 39000000 | P31: =IFERROR(ROUND(S31/N31,-6),0) -> 52000000 | Q31: 115000000 | R31: Acquired | S31: =INDEX('Statement of Investments'!$L$5:$L$204,MATCH('Investment Characteristics'!$L31,'Statement of Investments'!$E$5:$E$204,0)) -> 249999.58 | T31: =INDEX('Statement of Investments'!$O$5:$O$204,MATCH($L31,'Statement of Investments'!$E$5:$E$204,0)) -> 222162.45 | U31: =T31/S31 -> 0.88865129 | V31: =+$V$1/N31/10^6 -> 4384.1336 | AB31: 0 | AC31: 1 | AD31: 1 | AE31: 1 | AF31: 0 | AG31: 0 | AH31: 0 | AI31: 0 | AM31: Written off
B33: Average | F33: =AVERAGE(F4:F32) -> 405469.07 | H33: =AVERAGE(H4:H32) -> 0.0091946146 | I33: =AVERAGE(I4:I32) -> 0.023048671 | J33: =AVERAGE(J4:J32) -> 59000000 | L33: Average | N33: =AVERAGE(N4:N32) -> 0.0086008406 | O33: =AVERAGE(O4:O32) -> 62600000 | P33: =AVERAGE(P4:P32) -> 127640000 | Q33: =AVERAGE(Q4:Q32) -> 638787500 | S33: =AVERAGE(S4:S32) -> 698333.46 | T33: =AVERAGE(T4:T32) -> 3346893.4
B34: Median | F34: =MEDIAN(F4:F32) -> 287499.95 | H34: =MEDIAN(H4:H32) -> 0.0071 | I34: =MEDIAN(I4:I32) -> 0.017100061 | J34: =MEDIAN(J4:J32) -> 25500000 | L34: Median | N34: =MEDIAN(N4:N32) -> 0.0059159848 | O34: =MEDIAN(O4:O32) -> 26000000 | P34: =MEDIAN(P4:P32) -> 139000000 | Q34: =MEDIAN(Q4:Q32) -> 267500000 | S34: =MEDIAN(S4:S32) -> 641333.18 | T34: =MEDIAN(T4:T32) -> 920709.31
B35: Dollar Weighted | H35: =SUMPRODUCT($F$4:$F$31,H$4:H$31)/SUM($F$4:$F$31) -> 0.0074654525 | I35: =SUMPRODUCT($F$4:$F$31,I$4:I$31)/SUM($F$4:$F$31) -> 0.014936583 | J35: =SUMPRODUCT($F$4:$F$31,J$4:J$31)/SUM($F$4:$F$31) -> 89643009 | L35: Dollar Weighted | N35: =SUMPRODUCT(N$4:N$31,$S$4:$S$31)/SUM($S$4:$S$31) -> 0.0079032079 | O35: =SUMPRODUCT(O$4:O$31,$S$4:$S$31)/SUM($S$4:$S$31) -> 66755981 | P35: =SUMPRODUCT(P$4:P$31,$S$4:$S$31)/SUM($S$4:$S$31) -> 1.4349657e+08 | Q35: =SUMPRODUCT(Q$4:Q$31,$S$4:$S$31)/SUM($S$4:$S$31) -> 7.8784696e+08 | T35: =SUM(T4:T31) -> 93713016
D38: =COUNTIF(D4:D31,D31) -> 7
B39: Fund I - Performance Summary
C40: Workforce | D40: Healthtech | E40: Financial | F40: Total
B41: Deals:
B42: # of Deals | C42: =COUNTIF($E$4:$E$32,C$40) -> 13 | D42: =COUNTIF($E$4:$E$32,D$40) -> 9 | E42: =COUNTIF($E$4:$E$32,E$40) -> 6 | F42: =SUM(C42:E42) -> 28
B43: % of Deals | C43: =C42/$F$42 -> 0.46428571 | D43: =D42/$F$42 -> 0.32142857 | E43: =E42/$F$42 -> 0.21428571 | F43: =F42/$F$42 -> 1
B44: Invested Capital:
B45: Initial Investment | C45: =SUMIF($E$4:$E$32,C$40,$F$4:$F$32) -> 3728140.4 | D45: =SUMIF($E$4:$E$32,D$40,$F$4:$F$32) -> 3699996.7 | E45: =SUMIF($E$4:$E$32,E$40,$F$4:$F$32) -> 3924996.7 | F45: =SUM(C45:E45) -> 11353134
B46: % of Invested Cap | C46: =C45/$F$45 -> 0.32837986 | D46: =D45/$F$45 -> 0.32590091 | E46: =E45/$F$45 -> 0.34571923 | F46: =F45/$F$45 -> 1
B47: Current Investment | C47: =SUMIF($E$4:$E$32,C$40,$S$4:$S$32) -> 6705463 | D47: =SUMIF($E$4:$E$32,D$40,$S$4:$S$32) -> 8107874.8 | E47: =SUMIF($E$4:$E$32,E$40,$S$4:$S$32) -> 4739998.9 | F47: =SUM(C47:E47) -> 19553337
B48: % of Invested Cap | C48: =C47/$F$47 -> 0.3429319 | D48: =D47/$F$47 -> 0.41465428 | E48: =E47/$F$47 -> 0.24241381 | F48: =F47/$F$47 -> 1
B49: Current Mark
B50: Total Value | C50: =SUMIF($E$4:$E$32,C$40,$T$4:$T$32) -> 17792799 | D50: =SUMIF($E$4:$E$32,D$40,$T$4:$T$32) -> 61996386 | E50: =SUMIF($E$4:$E$32,E$40,$T$4:$T$32) -> 13923832 | F50: =SUM(C50:E50) -> 93713016
B51: MOIC | C51: =C50/C47 -> 2.6534781 | D51: =D50/D47 -> 7.6464409 | E51: =E50/E47 -> 2.9375179 | F51: =F50/F47 -> 4.7926867
B52: Average Investment:
B53: Initial Avg. Inv. | C53: =AVERAGEIF($E$4:$E$32,C$40,$F$4:$F$32) -> 286780.03 | D53: =AVERAGEIF($E$4:$E$32,D$40,$F$4:$F$32) -> 411110.74 | E53: =AVERAGEIF($E$4:$E$32,E$40,$F$4:$F$32) -> 654166.12 | F53: =F33 -> 405469.07
B54: Current Avg. Inv. | C54: =AVERAGEIF($E$4:$E$32,C$40,$S$4:$S$32) -> 515804.85 | D54: =AVERAGEIF($E$4:$E$32,D$40,$S$4:$S$32) -> 900874.98 | E54: =AVERAGEIF($E$4:$E$32,E$40,$S$4:$S$32) -> 789999.82 | F54: =S33 -> 698333.46
B55: Average Cost:
B56: Initial Avg. Cost | C56: =AVERAGEIF($E$4:$E$32,C$40,$J$4:$J$32) -> 42076923 | D56: =AVERAGEIF($E$4:$E$32,D$40,$J$4:$J$32) -> 57333333 | E56: =AVERAGEIF($E$4:$E$32,E$40,$J$4:$J$32) -> 98166667 | F56: =J33 -> 59000000
B57: Current Avg. Inv. | C57: =AVERAGEIF($E$4:$E$32,C$40,$P$4:$P$32) -> 95333333 | D57: =AVERAGEIF($E$4:$E$32,D$40,$P$4:$P$32) -> 130750000 | E57: =AVERAGEIF($E$4:$E$32,E$40,$P$4:$P$32) -> 200200000 | F57: =P33 -> 127640000
B58: Round
B59: Seed | C59: =COUNTIFS($D$4:$D$32,$B59,$E$4:$E$32,C$40) -> 9 | D59: =COUNTIFS($D$4:$D$32,$B59,$E$4:$E$32,D$40) -> 4 | E59: =COUNTIFS($D$4:$D$32,$B59,$E$4:$E$32,E$40) -> 1 | F59: =SUM(C59:E59) -> 14
B60: A | C60: =COUNTIFS($D$4:$D$32,$B60,$E$4:$E$32,C$40) -> 1 | D60: =COUNTIFS($D$4:$D$32,$B60,$E$4:$E$32,D$40) -> 3 | E60: =COUNTIFS($D$4:$D$32,$B60,$E$4:$E$32,E$40) -> 3 | F60: =SUM(C60:E60) -> 7
B61: B+ | C61: =COUNTIFS($D$4:$D$32,"B",$E$4:$E$32,C$40)+COUNTIFS($D$4:$D$32,"C",$E$4:$E$32,C$40) -> 3 | D61: =COUNTIFS($D$4:$D$32,"B",$E$4:$E$32,D$40)+COUNTIFS($D$4:$D$32,"C",$E$4:$E$32,D$40) -> 2 | E61: =COUNTIFS($D$4:$D$32,"B",$E$4:$E$32,E$40)+COUNTIFS($D$4:$D$32,"C",$E$4:$E$32,E$40) -> 2 | F61: =SUM(C61:E61) -> 7
B64: Stage Summary
C65: Seed | D65: A | E65: B | F65: Total
B66: Average Investment:
B67: Initial Avg. Inv. | C67: =AVERAGEIF($D$4:$D$31,C$65,$F$4:$F$31) -> 258772.05 | D67: =AVERAGEIF($D$4:$D$31,D$65,$F$4:$F$31) -> 492857.33 | E67: =AVERAGE(F11,F13,F24,F15,F28,F29,F19) -> 611474.83 | F67: =F33 -> 405469.07
B68: Current Avg. Inv. | C68: =AVERAGEIF($D$4:$D$31,C$65,$S$4:$S$31) -> 636506.9 | D68: =AVERAGEIF($D$4:$D$31,D$65,$S$4:$S$31) -> 564285.76 | E68: =AVERAGE(S28:S29,S24,S22,S19,S15,S13,S11,S8,S5:S6) -> 931111.36 | F68: =S33 -> 698333.46
B69: Deals
B70: Initial # of Deals | C70: =COUNTIF($D$4:$D$32,C$65) -> 14 | D70: =COUNTIF($D$4:$D$32,D$65) -> 7 | E70: =COUNTIF($D$4:$D$31,"B")+COUNTIF($D$4:$D$31,"C") -> 7 | F70: =SUM(C70:E70) -> 28
B71: % of Deals | C71: =C70/$F$70 -> 0.5 | D71: =D70/$F$70 -> 0.25 | E71: =E70/$F$70 -> 0.25 | F71: =F70/$F$42 -> 1
B72: Current # of Deals | C72: =COUNTIF($M$4:$M$32,C$65) -> 3 | D72: =COUNTIF($M$4:$M$32,D$65) -> 1 | E72: =F70-SUM(C72:D72)-4 -> 20 | F72: =SUM(C72:E72) -> 24
B73: % of Deals | C73: =C72/$F$72 -> 0.125 | D73: =D72/$F$72 -> 0.041666667 | E73: =E72/$F$72 -> 0.83333333 | F73: =F72/$F$42 -> 0.85714286
B74: Valuation
B75: Initial Avg. Cost | C75: =AVERAGEIF($D$4:$D$32,C$65,$J$4:$J$32) -> 16642857 | D75: =AVERAGEIF($D$4:$D$32,D$65,$J$4:$J$32) -> 62571429 | E75: =AVERAGE(J11,J13,J24,J28,J29,J15,J19) -> 1.4014286e+08 | F75: =J33 -> 59000000
B76: Initial Median Cost | C76: {=MEDIAN(IF($D$4:$D$31=C65,$J$4:$J$31))} -> 16000000 | D76: {=MEDIAN(IF($D$4:$D$31=D65,$J$4:$J$31))} -> 39000000 | E76: =MEDIAN(J11,J13,J24,J28,J29,J15,J19) -> 137000000 | F76: =J34 -> 25500000
B78: Initial Investment | C78: =SUMIF($D$4:$D$31,C65,$F$4:$F$31) -> 3622808.8 | D78: =SUMIF($D$4:$D$31,D65,$F$4:$F$31) -> 3450001.3 | E78: =SUMIF($D$4:$D$31,E65,$F$4:$F$31) -> 3530329.2 | F78: =SUM(C78:E78) -> 10603139
B79: Current Investment
B80: Current Valuation | C80: =SUMIF($D$4:$D$32,C65,$T$4:$T$32) -> 61851433 | D80: =SUMIF($D$4:$D$32,D65,$T$4:$T$32) -> 14929094 | E80: =SUMIF($D$4:$D$32,E65,$T$4:$T$32) -> 16172572 | F80: =SUM(C80:E80) -> 92953099
C81: Seed | D81: A | E81: B | F81: C
B82: Initial # of Deals | C82: =COUNTIF($D$4:$D$32,C$81) -> 14 | D82: =COUNTIF($D$4:$D$32,D$81) -> 7 | E82: =COUNTIF($D$4:$D$32,E$81) -> 6 | F82: =COUNTIF($D$4:$D$32,F$81) -> 1
B83: Current # of Deals | C83: =COUNTIF($M$4:$M$32,C$81)-1 -> 2 | D83: =COUNTIF($M$4:$M$32,D$81) -> 1 | E83: =COUNTIF($M$4:$M$32,E$81) -> 6 | F83: =COUNTIF($M$4:$M$32,F$81)+2 -> 9
C85: Workforce | D85: Healthtech | E85: Financial | F85: Total
C86: =SUMIF($E$4:$E$32,C$40,$T$4:$T$32) -> 17792799 | D86: =SUMIF($E$4:$E$32,D$40,$T$4:$T$32) -> 61996386 | E86: =SUMIF($E$4:$E$32,E$40,$T$4:$T$32) -> 13923832 | F86: =SUM(C86:E86) -> 93713016
C87: =C86/$F$86 -> 0.18986476 | D87: =D86/$F$86 -> 0.66155576 | E87: =E86/$F$86 -> 0.14857948 | F87: =SUM(C87:E87) -> 1

Sheet Sheet2

Sheet Investment Rollover
B2: Unrealized Cost | H2: Unrealized Carrying Value
B3: Company | C3: 6/30/2025 Value | D3: Additions | E3: Dispositions | F3: 9/30/2025 Cost | H3: Company | I3: 6/30/2025 Value | J3: Additions | K3: Dispositions | L3: Net Writeup | M3: 9/30/2025 Value | N3: MOIC
B4: Carrot | C4: 999996.37 | D4: =IF(F4>C4,F4-C4,0) -> 0 | E4: =IF(F4<C4,F4-C4,0) -> 0 | F4: =INDEX('Statement of Investments'!$L$5:$L$204,MATCH('Investment Rollover'!$H4,'Statement of Investments'!$E$5:$E$204,0)) -> 999996.37 | H4: =B4 -> Carrot | I4: 5663568.2 | J4: =D4 -> 0 | K4: =E4 -> 0 | L4: =M4-SUM(I4:K4) -> 0 | M4: =INDEX('Statement of Investments'!$O$5:$O$204,MATCH('Investment Rollover'!$H4,'Statement of Investments'!$E$5:$E$204,0)) -> 5663568.2 | N4: =M4/F4 -> 5.6635888
B5: Cleo | C5: 100000 | D5: =IF(F5>C5,F5-C5,0) -> 0 | E5: =IF(F5<C5,F5-C5,0) -> 0 | F5: =INDEX('Statement of Investments'!$L$5:$L$204,MATCH('Investment Rollover'!$H5,'Statement of Investments'!$E$5:$E$204,0)) -> 100000 | H5: =B5 -> Cleo | I5: 0 | J5: =D5 -> 0 | K5: =E5 -> 0 | L5: =M5-SUM(I5:K5) -> 0 | M5: =INDEX('Statement of Investments'!$O$5:$O$204,MATCH('Investment Rollover'!$H5,'Statement of Investments'!$E$5:$E$204,0)) -> 0 | N5: =M5/F5 -> 0
B6: Hone | C6: 682666.27 | D6: =IF(F6>C6,F6-C6,0) -> 0 | E6: =IF(F6<C6,F6-C6,0) -> 0 | F6: =INDEX('Statement of Investments'!$L$5:$L$204,MATCH('Investment Rollover'!$H6,'Statement of Investments'!$E$5:$E$204,0)) -> 682666.27 | H6: =B6 -> Hone | I6: 1756737.3 | J6: =D6 -> 0 | K6: =E6 -> 0 | L6: =M6-SUM(I6:K6) -> 0 | M6: =INDEX('Statement of Investments'!$O$5:$O$204,MATCH('Investment Rollover'!$H6,'Statement of Investments'!$E$5:$E$204,0)) -> 1756737.3 | N6: =M6/F6 -> 2.5733472
B7: Spring | C7: 1449990.3 | D7: =IF(F7>C7,F7-C7,0) -> 0 | E7: =IF(F7<C7,F7-C7,0) -> 0 | F7: =INDEX('Statement of Investments'!$L$5:$L$204,MATCH('Investment Rollover'!$H7,'Statement of Investments'!$E$5:$E$204,0)) -> 1449990.3 | H7: =B7 -> Spring | I7: 28841289 | J7: =D7 -> 0 | K7: =E7 -> 0 | L7: =M7-SUM(I7:K7) -> 0 | M7: =INDEX('Statement of Investments'!$O$5:$O$204,MATCH('Investment Rollover'!$H7,'Statement of Investments'!$E$5:$E$204,0)) -> 28841289 | N7: =M7/F7 -> 19.890677
B8: Multiverse | C8: 834995.61 | D8: =IF(F8>C8,F8-C8,0) -> 0 | E8: =IF(F8<C8,F8-C8,0) -> 0 | F8: =INDEX('Statement of Investments'!$L$5:$L$204,MATCH('Investment Rollover'!$H8,'Statement of Investments'!$E$5:$E$204,0)) -> 834995.61 | H8: =B8 -> Multiverse | I8: 9377802.2 | J8: =D8 -> 0 | K8: =E8 -> 0 | L8: =M8-SUM(I8:K8) -> 0 | M8: =INDEX('Statement of Investments'!$O$5:$O$204,MATCH('Investment Rollover'!$H8,'Statement of Investments'!$E$5:$E$204,0)) -> 9377802.2 | N8: =M8/F8 -> 11.23096
B9: Omada Health | C9: 291986.05 | D9: =IF(F9>C9,F9-C9,0) -> 0 | E9: =IF(F9<C9,F9-C9,0) -> 0 | F9: =INDEX('Statement of Investments'!$L$5:$L$204,MATCH('Investment Rollover'!$H9,'Statement of Investments'!$E$5:$E$204,0)) -> 291986.05 | H9: =B9 -> Omada Health | I9: 393425.6 | J9: =D9 -> 0 | K9: =E9 -> 0 | L9: =M9-SUM(I9:K9) -> 81909.92 | M9: =INDEX('Statement of Investments'!$O$5:$O$204,MATCH('Investment Rollover'!$H9,'Statement of Investments'!$E$5:$E$204,0)) -> 475335.52 | N9: =M9/F9 -> 1.6279391
B10: Pelago | C10: 549993.11 | D10: =IF(F10>C10,F10-C10,0) -> 0 | E10: =IF(F10<C10,F10-C10,0) -> 0 | F10: =INDEX('Statement of Investments'!$L$5:$L$204,MATCH('Investment Rollover'!$H10,'Statement of Investments'!$E$5:$E$204,0)) -> 549993.11 | H10: =B10 -> Pelago | I10: 4289097.2 | J10: =D10 -> 0 | K10: =E10 -> 0 | L10: =M10-SUM(I10:K10) -> 0 | M10: =INDEX('Statement of Investments'!$O$5:$O$204,MATCH('Investment Rollover'!$H10,'Statement of Investments'!$E$5:$E$204,0)) -> 4289097.2 | N10: =M10/F10 -> 7.7984561
B11: Karat | C11: 999994.83 | D11: =IF(F11>C11,F11-C11,0) -> 0 | E11: =IF(F11<C11,F11-C11,0) -> 0 | F11: =INDEX('Statement of Investments'!$L$5:$L$204,MATCH('Investment Rollover'!$H11,'Statement of Investments'!$E$5:$E$204,0)) -> 999994.83 | H11: =B11 -> Karat | I11: 999994.83 | J11: =D11 -> 0 | K11: =E11 -> 0 | L11: =M11-SUM(I11:K11) -> 0 | M11: =INDEX('Statement of Investments'!$O$5:$O$204,MATCH('Investment Rollover'!$H11,'Statement of Investments'!$E$5:$E$204,0)) -> 999994.83 | N11: =M11/F11 -> 1
B12: Hatch | C12: 258903.8 | D12: =IF(F12>C12,F12-C12,0) -> 0 | E12: =IF(F12<C12,F12-C12,0) -> 0 | F12: =INDEX('Statement of Investments'!$L$5:$L$204,MATCH('Investment Rollover'!$H12,'Statement of Investments'!$E$5:$E$204,0)) -> 258903.8 | H12: =B12 -> Hatch | I12: 133950.81 | J12: =D12 -> 0 | K12: =E12 -> 0 | L12: =M12-SUM(I12:K12) -> 0 | M12: =INDEX('Statement of Investments'!$O$5:$O$204,MATCH('Investment Rollover'!$H12,'Statement of Investments'!$E$5:$E$204,0)) -> 133950.81 | N12: =M12/F12 -> 0.51737674
B13: Human Interest | C13: 1090002.1 | D13: =IF(F13>C13,F13-C13,0) -> 0 | E13: =IF(F13<C13,F13-C13,0) -> 0 | F13: =INDEX('Statement of Investments'!$L$5:$L$204,MATCH('Investment Rollover'!$H13,'Statement of Investments'!$E$5:$E$204,0)) -> 1090002.1 | H13: =B13 -> Human Interest | I13: 5589792.5 | J13: =D13 -> 0 | K13: =E13 -> 0 | L13: =M13-SUM(I13:K13) -> 5153954.7 | M13: =INDEX('Statement of Investments'!$O$5:$O$204,MATCH('Investment Rollover'!$H13,'Statement of Investments'!$E$5:$E$204,0)) -> 10743747 | N13: =M13/F13 -> 9.8566302
B14: Rula | C14: 496199.35 | D14: =IF(F14>C14,F14-C14,0) -> 0 | E14: =IF(F14<C14,F14-C14,0) -> 0 | F14: =INDEX('Statement of Investments'!$L$5:$L$204,MATCH('Investment Rollover'!$H14,'Statement of Investments'!$E$5:$E$204,0)) -> 496199.35 | H14: =B14 -> Rula | I14: 6277910.6 | J14: =D14 -> 0 | K14: =E14 -> 0 | L14: =M14-SUM(I14:K14) -> 0 | M14: =INDEX('Statement of Investments'!$O$5:$O$204,MATCH('Investment Rollover'!$H14,'Statement of Investments'!$E$5:$E$204,0)) -> 6277910.6 | N14: =M14/F14 -> 12.651993
B15: Terminal | C15: 599999.73 | D15: =IF(F15>C15,F15-C15,0) -> 0 | E15: =IF(F15<C15,F15-C15,0) -> 0 | F15: =INDEX('Statement of Investments'!$L$5:$L$204,MATCH('Investment Rollover'!$H15,'Statement of Investments'!$E$5:$E$204,0)) -> 599999.73 | H15: =B15 -> Terminal | I15: 0 | J15: =D15 -> 0 | K15: =E15 -> 0 | L15: =M15-SUM(I15:K15) -> 0 | M15: =INDEX('Statement of Investments'!$O$5:$O$204,MATCH('Investment Rollover'!$H15,'Statement of Investments'!$E$5:$E$204,0)) -> 0 | N15: =M15/F15 -> 0
... B25: Galileo | C25: 1499992.7 | D25: =IF(F25>C25,F25-C25,0) -> 252260.58 | E25: =IF(F25<C25,F25-C25,0) -> 0 | F25: =INDEX('Statement of Investments'!$L$5:$L$204,MATCH('Investment Rollover'!$H25,'Statement of Investments'!$E$5:$E$204,0)) -> 1752253.3 | H25: =B25 -> Galileo | I25: 4040579.9 | J25: =D25 -> 252260.58 | K25: =E25 -> 0 | L25: =M25-SUM(I25:K25) -> -1636406.5 | M25: =INDEX('Statement of Investments'!$O$5:$O$204,MATCH('Investment Rollover'!$H25,'Statement of Investments'!$E$5:$E$204,0)) -> 2656434 | N25: =M25/F25 -> 1.5160103
N26: =M26/F26 -> #DIV/0!
B27: Unrealized Total | C27: =SUM(C4:C26) -> 15286073 | D27: =SUM(D4:D26) -> 252260.58 | E27: =SUM(E4:E26) -> 0 | F27: =SUM(F4:F26) -> 15538333 | H27: Unrealized Total | I27: =SUM(I4:I26) -> 86969621 | J27: =SUM(J4:J26) -> 252260.58 | K27: =SUM(K4:K26) -> 0 | L27: =SUM(L4:L26) -> 3599458.1 | M27: =SUM(M4:M26) -> 90821339 | N27: =M27/F27 -> 5.844986
B28: Realized Cost | H28: Realized Carrying Value
B29: Physera | C29: 208014.11 | D29: =IF(F29>C29,F29-C29,0) -> 0 | E29: =IF(F29<C29,F29-C29,0) -> 0 | F29: =INDEX('Statement of Investments'!$L$5:$L$204,MATCH('Investment Rollover'!$B29,'Statement of Investments'!$E$5:$E$204,0)) -> 208014.11 | H29: =B29 -> Physera | I29: 366088.28 | J29: =D29 -> 0 | K29: =E29 -> 0 | L29: =M29-SUM(I29:K29) -> 0 | M29: =INDEX('Statement of Investments'!$O$5:$O$204,MATCH('Investment Rollover'!$H29,'Statement of Investments'!$E$5:$E$204,0)) -> 366088.28 | N29: =M29/F29 -> 1.7599205
B30: Fountain - Realized | C30: 94663.1 | D30: =IF(F30>C30,F30-C30,0) -> 0 | E30: =IF(F30<C30,F30-C30,0) -> 0 | F30: =INDEX('Statement of Investments'!$L$5:$L$204,MATCH('Investment Rollover'!$B30,'Statement of Investments'!$E$5:$E$204,0)) -> 94663.1 | H30: Fountain - Realized | I30: 94663.1 | J30: =D30 -> 0 | K30: =E30 -> 0 | L30: =M30-SUM(I30:K30) -> 0 | M30: =INDEX('Statement of Investments'!$O$5:$O$204,MATCH('Investment Rollover'!$H30,'Statement of Investments'!$E$5:$E$204,0)) -> 94663.1 | N30: =M30/F30 -> 1
B31: Sapling | C31: 129007.89 | D31: =IF(F31>C31,F31-C31,0) -> 0 | E31: =IF(F31<C31,F31-C31,0) -> 0 | F31: =INDEX('Statement of Investments'!$L$5:$L$204,MATCH('Investment Rollover'!$B31,'Statement of Investments'!$E$5:$E$204,0)) -> 129007.89 | H31: =B31 -> Sapling | I31: 203127.39 | J31: =D31 -> 0 | K31: =E31 -> 0 | L31: =M31-SUM(I31:K31) -> 0 | M31: =INDEX('Statement of Investments'!$O$5:$O$204,MATCH('Investment Rollover'!$H31,'Statement of Investments'!$E$5:$E$204,0)) -> 203127.39 | N31: =M31/F31 -> 1.5745346
B32: Alice | C32: 600000.08 | D32: =IF(F32>C32,F32-C32,0) -> 0 | E32: =IF(F32<C32,F32-C32,0) -> 0 | F32: =INDEX('Statement of Investments'!$L$5:$L$204,MATCH('Investment Rollover'!$H32,'Statement of Investments'!$E$5:$E$204,0)) -> 600000.08 | H32: =B32 -> Alice | I32: 0 | J32: =D32 -> 0 | K32: =E32 -> 0 | L32: =M32-SUM(I32:K32) -> 0 | M32: =INDEX('Statement of Investments'!$O$5:$O$204,MATCH('Investment Rollover'!$H32,'Statement of Investments'!$E$5:$E$204,0)) -> 0 | N32: =M32/F32 -> 0
B33: Pill Club | C33: 999998.53 | D33: =IF(F33>C33,F33-C33,0) -> 0 | E33: =IF(F33<C33,F33-C33,0) -> 0 | F33: =INDEX('Statement of Investments'!$L$5:$L$204,MATCH('Investment Rollover'!$B33,'Statement of Investments'!$E$5:$E$204,0)) -> 999998.53 | H33: Pill Club | I33: 0 | J33: 0 | K33: =E33 -> 0 | L33: =M33-SUM(I33:K33) -> 0 | M33: =INDEX('Statement of Investments'!$O$5:$O$204,MATCH('Investment Rollover'!$H33,'Statement of Investments'!$E$5:$E$204,0)) -> 0 | N33: =M33/F33 -> 0
B34: Shift | C34: 223873.41 | D34: =IF(F34>C34,F34-C34,0) -> 0 | E34: =IF(F34<C34,F34-C34,0) -> 0 | F34: =INDEX('Statement of Investments'!$L$5:$L$204,MATCH('Investment Rollover'!$H34,'Statement of Investments'!$E$5:$E$204,0)) -> 223873.41 | H34: =B34 -> Shift | I34: 8128.52 | J34: =D34 -> 0 | K34: =E34 -> 0 | L34: =M34-SUM(I34:K34) -> 0 | M34: =INDEX('Statement of Investments'!$O$5:$O$204,MATCH('Investment Rollover'!$H34,'Statement of Investments'!$E$5:$E$204,0)) -> 8128.52 | N34: =M34/F34 -> 0.036308555
B35: Forage | C35: 249999.58 | D35: =IF(F35>C35,F35-C35,0) -> 0 | E35: =IF(F35<C35,F35-C35,0) -> 0 | F35: =INDEX('Statement of Investments'!$L$5:$L$204,MATCH('Investment Rollover'!$H35,'Statement of Investments'!$E$5:$E$204,0)) -> 249999.58 | H35: =B35 -> Forage | I35: 222162.45 | J35: =D35 -> 0 | K35: =E35 -> 0 | L35: =M35-SUM(I35:K35) -> 0 | M35: =INDEX('Statement of Investments'!$O$5:$O$204,MATCH('Investment Rollover'!$H35,'Statement of Investments'!$E$5:$E$204,0)) -> 222162.45 | N35: =M35/F35 -> 0.88865129
B36: Rula - Realized | C36: 259445.38 | D36: =IF(F36>C36,F36-C36,0) -> 0 | E36: =IF(F36<C36,F36-C36,0) -> 0 | F36: =INDEX('Statement of Investments'!$L$5:$L$204,MATCH('Investment Rollover'!$B36,'Statement of Investments'!$E$5:$E$204,0)) -> 259445.38 | H36: Rula - Realized | I36: 10236410 | J36: =D36 -> 0 | K36: =E36 -> 0 | L36: =M36-SUM(I36:K36) -> 0 | M36: =INDEX('Statement of Investments'!$O$5:$O$204,MATCH('Investment Rollover'!$H36,'Statement of Investments'!$E$5:$E$204,0)) -> 10236410 | N36: =M36/F36 -> 39.454972
N37: =M37/F37 -> #DIV/0!
B38: Level | C38: 1000002.7 | D38: =IF(F38>C38,F38-C38,0) -> 0 | E38: =IF(F38<C38,F38-C38,0) -> 0 | F38: =INDEX('Statement of Investments'!$L$5:$L$204,MATCH('Investment Rollover'!$H38,'Statement of Investments'!$E$5:$E$204,0)) -> 1000002.7 | H38: =B38 -> Level | I38: 0 | J38: =D38 -> 0 | K38: =E38 -> 0 | L38: =M38-SUM(I38:K38) -> 0 | M38: =INDEX('Statement of Investments'!$O$5:$O$204,MATCH('Investment Rollover'!$H38,'Statement of Investments'!$E$5:$E$204,0)) -> 0 | N38: =M38/F38 -> 0
B39: Valence | C39: 249999.49 | E39: =IF(F39<C39,F39-C39,0) -> 0 | F39: =INDEX('Statement of Investments'!$L$5:$L$204,MATCH('Investment Rollover'!$H39,'Statement of Investments'!$E$5:$E$204,0)) -> 249999.49 | H39: Valence | I39: 0 | M39: =INDEX('Statement of Investments'!$O$5:$O$204,MATCH('Investment Rollover'!$H39,'Statement of Investments'!$E$5:$E$204,0)) -> 1997507.1 | N39: =M39/F39 -> 7.9900445
B40: Realized Total | C40: =SUM(C29:C39) -> 4015004.2 | D40: =SUM(D29:D38) -> 0 | E40: =SUM(E29:E38) -> 0 | F40: =SUM(F29:F39) -> 4015004.2 | H40: Realized Total | I40: =SUM(I29:I38) -> 11130580 | J40: =SUM(J29:J38) -> 0 | K40: =SUM(K29:K38) -> 0 | L40: =SUM(L29:L38) -> 0 | M40: =SUM(M29:M39) -> 13128087 | N40: =M40/F40 -> 3.2697567
N41: =M41/F41 -> #DIV/0!
B42: Total | C42: =C40+C27 -> 19301077 | D42: =D40+D27 -> 252260.58 | E42: =E40+E27 -> 0 | F42: =F40+F27 -> 19553337 | H42: Total | I42: =I40+I27 -> 98100201 | J42: =J40+J27 -> 252260.58 | K42: =K40+K27 -> 0 | L42: =L40+L27 -> 3599458.1 | M42: =M40+M27 -> 1.0394943e+08 | N42: =M42/F42 -> 5.3161987
B44: Check | F44: =F27-'Statement of Investments'!L202 -> 0 | M44: =M27-'Statement of Investments'!O202 -> 0
B45: Check | F45: =F42-'Statement of Investments'!L204 -> 0 | M45: =M42-'Statement of Investments'!O204 -> 0

Sheet Warrant Detail
C2: Shift | G2: Pill Club | K2: Digithera | O2: Alice | S2: Vetty | W2: Level Dental | AA2: Forage | AE2: Rightway Health - Series A | AI2: Rightway Health - Series B
B3: Overall Status: | C3: 0 | G3: 0 | K3: =M18/L18 -> 0.99998984 | O3: 0 | S3: 0 | W3: 0 | AA3: 0 | AE3: =AG18/AF18 -> 1 | AI3: 0
B4: Owner: | C4: Robby | G4: Kaleana | K4: Robby | O4: Robby/Colin | S4: Colin | W4: Greg | AA4: Allison | AE4: Greg | AI4: Greg
B5: Reporting: | C5: Montly report from Shift | G5: Quarterly Basis | K5: Quarterly Report | O5: Monthly Report | S5: Monthly Report | W5: Quarterly report within 10 business days | AA5: Monthly Report | AE5: Monthly Report | AI5: Monthly Report
B6: As of Date: | C6: 43780 | G6: 43780 | K6: 43780 | O6: N/A | S6: N/A | W6: N/A | AA6: N/A | AE6: N/A | AI6: N/A
C8: Transaction Details | D8: Amount | E8: Status | G8: Transaction Details | H8: Amount | I8: Status | K8: Transaction Details | L8: Amount | M8: Status | O8: Transaction Details | P8: Amount | Q8: Status | S8: Transaction Details | T8: Amount | U8: Status | W8: Transaction Details | X8: Amount | Y8: Status | AA8: Transaction Details | AB8: Amount | AC8: Status | AE8: Transaction Details | AF8: Amount | AG8: Status | AI8: Transaction Details | AJ8: Amount | AK8: Status
B9: Warrant Security: | C9: Common Shares | D9: 240000 | E9: — | G9: Series B | H9: 579911 | I9: — | K9: Common Shares | L9: 98465 | M9: — | O9: Series A | P9: 127934 | Q9: — | S9: Common/Preferred | T9: 1.2% FD | U9: — | W9: Series A | X9: 163612 | Y9: ` | AA9: Series A | AB9: 238238 | AC9: ` | AE9: Series A | AF9: 242471 | AG9: =AG18 -> 242471 | AI9: Series B | AJ9: 124878 | AK9: =AK18 -> 0
B10: Deadline: | C10: 44470 | D10: — | E10: — | G10: 44926 | H10: — | I10: — | K10: 47209 | L10: — | M10: — | O10: 44824 | P10: — | Q10: — | S10: 47484 | T10: — | U10: — | W10: 45292 | X10: — | Y10: — | AA10: 44805 | AB10: — | AC10: — | AE10: 44470 | AF10: — | AG10: — | AI10: 44378 | AJ10: — | AK10: —
B11: Notes | C11: — | D11: — | E11: — | G11: 9/4/25 to exercise | H11: — | I11: — | K11: Provide leads to Digithera; 5 days to reject | L11: — | M11: — | O11: 4 months to exercise after each vest | P11: — | Q11: — | S11: — | T11: — | U11: — | W11: April 2025 to exercise | X11: — | Y11: — | AA11: Sep 2030 to exercise | AB11: — | AC11: — | AE11: April 2023 to exercise | AF11: — | AG11: — | AI11: July 1, 2022 is second vesting date | AJ11: — | AK11: —
B12: Vest Trigger 1 | C12: 10 Employers | D12: 80000 | E12: 3 Employers | G12: 15 fully insured employers 20 self-insured employers 90k client employees with 30k women | H12: — | I12: — | K12: 300 new members + 5 employers | L12: 24616 | M12: =L12 -> 24616 | O12: $1M ARR | P12: 31983 | Q12: — | S12: $250k ARR | T12: 50% of the warrant | U12: $2k ARR | W12: Measure on 1/1/21: Min # of enrolled employees: 7,500 yields 20,451 shares Max: 15,000 yields 40,903 shares | X12: 40903 | Y12: 0 | AA12: 5 Customers who reach $20k ACV each | AB12: 119119 | AC12: 1 customer in closing | AE12: 15k users by 1st anniversary | AF12: 48495 | AG12: =AF12 -> 48495 | AI12: 25,000 Rightway RX Users | AJ12: 24976
B13: Vest Trigger 2 | C13: 10 Employers | D13: 80000 | E13: — | G13: FI and SI employers have to be "Qualified", i.e. complete the promotional activities listed in Ex. B. | H13: =H9 -> 579911 | I13: — | K13: 300 new members + 5 employers | L13: 24616 | M13: 24616 | O13: $1M ARR | P13: 31983 | Q13: — | S13: $250k ARR | T13: 50% of the warrant | U13: — | W13: Measure on 1/1/22: Min # of enrolled employees: 15,000 yields 20,451 shares Max: 50,000 yields 40,903 shares | X13: 40903 | Y13: 4,500 employees | AA13: 5 Customers who reach $20k ACV each | AB13: 119119 | AC13: — | AE13: 30k users by 1st anniversary | AF13: 48494 | AG13: =AF13 -> 48494 | AI13: 50,000 Rightway RX Users | AJ13: 24976
B14: Vest Trigger 3 | C14: 10 Employers | D14: 80000 | E14: — | G14: — | H14: — | I14: — | K14: 300 new members + 5 employers | L14: 24616 | M14: 24616 | O14: $1M ARR | P14: 63968 | Q14: — | S14: — | T14: — | U14: — | W14: Measure on 1/1/23: Min # of enrolled employees: 50,000 yields 20,451 shares Max: 75,000 yields 40,903 shares | X14: 40903 | Y14: — | AA14: — | AB14: — | AC14: — | AE14: 50k users by 2nd anniversary | AF14: 48494 | AG14: =AF14 -> 48494 | AI14: 75,000 Rightway RX Users | AJ14: 24976
B15: Vest Trigger 4 | C15: — | D15: — | E15: — | G15: — | H15: — | I15: — | K15: 300 new members + 5 employers | L15: 24616 | M15: 24616 | O15: — | P15: — | Q15: — | S15: — | T15: — | U15: — | W15: Measure on 1/1/24: Min # of enrolled employees: 75,000 yields 20,451 shares Max: 100,000 yields 40,903 shares | X15: 40903 | Y15: — | AA15: — | AB15: — | AC15: — | AE15: 75k users by 2nd anniversary | AF15: 48494 | AG15: =AF15 -> 48494 | AI15: 100,000 Rightway RX Users | AJ15: 24975
B16: Vest Trigger 5 | C16: — | D16: — | E16: — | G16: — | H16: — | I16: — | K16: — | L16: — | M16: — | O16: — | P16: — | Q16: — | S16: — | T16: — | U16: — | W16: "Other Notes: 1. In any year after 1st year, if we hit the Max #, then we will vest in 50% of whatever didn't vest in prior year. 2. For companies whom we refer but are not our clients, we count 33% of their employees" | Y16: — | AA16: — | AB16: — | AC16: — | AE16: 100k users by 2nd anniversary | AF16: 48494 | AG16: =AF16 -> 48494 | AI16: 150,000 Rightway RX Users | AJ16: 24975
B18: Total Trigger | C18: 30 | D18: 240000 | E18: 3 | G18: — | H18: =H9 -> 579911 | I18: — | L18: =L9 -> 98465 | M18: =SUM(M12:M16) -> 98464 | O18: $3M ARR | P18: =P9 -> 127934 | Q18: — | S18: $500k ARR | T18: =T9 -> 1.2% FD | U18: — | X18: =X9 -> 163612 | Y18: — | AB18: =AB9 -> 238238 | AC18: — | AE18: 100k users by 2nd anniversary | AF18: =AF9 -> 242471 | AG18: =SUM(AG12:AG16) -> 242471 | AI18: 150k users by 2nd anniversary | AJ18: =AJ9 -> 124878 | AK18: =SUM(AK12:AK16) -> 0

Sheet Sheet1
C4: type | D4: date | E4: amount | G4: =XIRR($E$5:$E$479,$C$5:$C$479) -> #VALUE! | I4: xirr
C5: contrib | D5: 43777 | E5: -165000
C6: contrib | D6: 44084 | E6: -41675 | G6: =SUMIF($C$5:$C$479,I6,$E$5:$E$479) -> -20730000 | I6: contrib
C7: contrib | D7: 44272 | E7: -43325 | G7: =SUMIF($C$5:$C$479,I7,$E$5:$E$479) -> 107744921 | I7: total val
C8: contrib | D8: 43559 | E8: -24750 | G8: =SUMIF($C$5:$C$479,I8,$E$5:$E$479) -> -363684 | I8: mgmt
C9: contrib | D9: 43777 | E9: -24750 | G9: =SUMIF($C$5:$C$479,I9,$E$5:$E$479) -> -16248 | I9: accr exp
C10: contrib | D10: 44084 | E10: -12503 | G10: =SUMIF($C$5:$C$479,I10,$E$5:$E$479) -> 53284 | I10: int recvble
C11: contrib | D11: 44271 | E11: -12997 | G11: =SUMIF($C$5:$C$479,I11,$E$5:$E$479) -> 70473 | I11: cash
C12: contrib | D12: 43763 | E12: -165000 | G12: =-(88222331*0.196) -> -17291577 | I12: est. carry
C13: contrib | D13: 43770 | E13: -33000
C14: contrib | D14: 43397 | E14: -16500
C15: contrib | D15: 43777 | E15: -16500
C16: contrib | D16: 44090 | E16: -8335
C17: contrib | D17: 44281 | E17: -8665
C18: contrib | D18: 43578 | E18: -49500
C19: contrib | D19: 43761 | E19: -49500
C20: contrib | D20: 44074 | E20: -25005
C21: contrib | D21: 44256 | E21: -25995
C22: contrib | D22: 43725 | E22: -8250
C23: contrib | D23: 43762 | E23: -8250
C24: contrib | D24: 44088 | E24: -4168
... C414: total val | D414: 44926 | E414: 23164
C415: total val | D415: 44926 | E415: -
C416: total val | D416: 44926 | E416: -
C417: total val | D417: 44926 | E417: 1112074
C418: total val | D418: 44926 | E418: 1797508
C419: total val | D419: 44926 | E419: 2347810
C420: total val | D420: 44926 | E420: 402980
C421: total val | D421: 44926 | E421: 386501
C422: total val | D422: 44926 | E422: 213295
C423: total val | D423: 44926 | E423: 853181
C424: total val | D424: 44926 | E424: 690260
C425: total val | D425: 44926 | E425: 8039977
C426: total val | D426: 44926 | E426: 8011930
C427: total val | D427: 44926 | E427: 3455135
C428: total val | D428: 44926 | E428: 3388478
... C438: total val | D438: 44926 | E438: 2137730
C439: total val | D439: 44926 | E439: -
C440: total val | D440: 44926 | E440: 3340045
C441: total val | D441: 44926 | E441: 1731728
C442: total val | D442: 44926 | E442: 611621
C443: total val | D443: 44926 | E443: -
C444: total val | D444: 44926 | E444: 5411362
C445: total val | D445: 44926 | E445: 3438290
C446: total val | D446: 44926 | E446: 963352
C447: total val | D447: 44926 | E447: 600000
C448: total val | D448: 44926 | E448: 300
C449: total val | D449: 44926 | E449: 120691
C450: total val | D450: 44926 | E450: 601637
C451: total val | D451: 44926 | E451: 1288633
C452: total val | D452: 44926 | E452: 337381
C453: total val | D453: 44926 | E453: 10435952
C454: total val | D454: 44926 | E454: 1712174
C455: total val | D455: 44926 | E455: 3662575
... C459: total val | D459: 44926 | E459: 1190569
C460: total val | D460: 44926 | E460: -
C461: total val | D461: 44926 | E461: 250000
C462: total val | D462: 44926 | E462: 2046049
C463: total val | D463: 44926 | E463: 2828652
C464: total val | D464: 44926 | E464: 901892
C465: total val | D465: 44926 | E465: 5430904
C466: total val | D466: 44926 | E466: 551521
C467: mgmt | D467: 44470 | E467: -73844
C468: mgmt | D468: 44564 | E468: -72460
C469: mgmt | D469: 44652 | E469: -72460
C470: mgmt | D470: 44743 | E470: -72460
C471: mgmt | D471: 44837 | E471: -72460
C472: accr exp | D472: 44834 | E472: -2691
... C479: int recvble | D479: 44926 | E479: 53284

Sheet Reserves
E1: Initial | G1: Total | K1: 6/30 | L1: 3/31 | M1: ROBBY
B2: Company | C2: Current Stage | D2: Sector | E2: $ Invested | F2: Follow-Ons | G2: $ Invested | I2: Reserves | J2: Total+Reserves | K2: Health | L2: Health | M2: Reserves | N2: Total+Reserves | P2: Notes
B3: Shift | C3: =INDEX('Investment Characteristics'!$M$4:$M$30,MATCH(Reserves!$B3,'Investment Characteristics'!$L$4:$L$30,0)) -> Seed | D3: Workforce | E3: =INDEX('Investment Characteristics'!$F$4:$F$32,MATCH(Reserves!$B3,'Investment Characteristics'!$B$4:$B$32,0)) -> 73873.412 | F3: =G3-E3 -> 150000 | G3: =INDEX('Statement of Investments'!$L$5:$L$204,MATCH(B3,'Statement of Investments'!$E$5:$E$204,0)) -> 223873.41 | I3: 0 | J3: =I3+G3 -> 223873.41 | K3: Y | L3: G | N3: =G3+M3 -> 223873.41
B4: Carrot | C4: =INDEX('Investment Characteristics'!$M$4:$M$30,MATCH(Reserves!$B4,'Investment Characteristics'!$L$4:$L$30,0)) -> D | D4: Healthtech | E4: =INDEX('Investment Characteristics'!$F$4:$F$32,MATCH(Reserves!$B4,'Investment Characteristics'!$B$4:$B$32,0)) -> 100000 | F4: =G4-E4 -> 899996.37 | G4: =INDEX('Statement of Investments'!$L$5:$L$204,MATCH(B4,'Statement of Investments'!$E$5:$E$204,0)) -> 999996.37 | I4: 0 | J4: =I4+G4 -> 999996.37 | K4: Y | L4: G | M4: 250000 | N4: =G4+M4 -> 1249996.4
B5: Cleo | C5: =INDEX('Investment Characteristics'!$M$4:$M$30,MATCH(Reserves!$B5,'Investment Characteristics'!$L$4:$L$30,0)) -> C | D5: Healthtech | E5: =INDEX('Investment Characteristics'!$F$4:$F$32,MATCH(Reserves!$B5,'Investment Characteristics'!$B$4:$B$32,0)) -> 100000 | F5: =G5-E5 -> 0 | G5: =INDEX('Statement of Investments'!$L$5:$L$204,MATCH(B5,'Statement of Investments'!$E$5:$E$204,0)) -> 100000 | I5: 0 | J5: =I5+G5 -> 100000 | K5: Y | L5: Y | N5: =G5+M5 -> 100000
B6: Hone | C6: =INDEX('Investment Characteristics'!$M$4:$M$30,MATCH(Reserves!$B6,'Investment Characteristics'!$L$4:$L$30,0)) -> B | D6: Workforce | E6: =INDEX('Investment Characteristics'!$F$4:$F$32,MATCH(Reserves!$B6,'Investment Characteristics'!$B$4:$B$32,0)) -> 250000 | F6: =G6-E6 -> 432666.27 | G6: =INDEX('Statement of Investments'!$L$5:$L$204,MATCH(B6,'Statement of Investments'!$E$5:$E$204,0)) -> 682666.27 | I6: =0.5*10^6 -> 500000 | J6: =I6+G6 -> 1182666.3 | K6: R | L6: Y | M6: 500000 | N6: =G6+M6 -> 1182666.3
B7: Spring | C7: =INDEX('Investment Characteristics'!$M$4:$M$30,MATCH(Reserves!$B7,'Investment Characteristics'!$L$4:$L$30,0)) -> E | D7: Healthtech | E7: =INDEX('Investment Characteristics'!$F$4:$F$32,MATCH(Reserves!$B7,'Investment Characteristics'!$B$4:$B$32,0)) -> 200000 | F7: =G7-E7 -> 1249990.3 | G7: =INDEX('Statement of Investments'!$L$5:$L$204,MATCH(B7,'Statement of Investments'!$E$5:$E$204,0)) -> 1449990.3 | I7: 0 | J7: =I7+G7 -> 1449990.3 | K7: G | L7: G | N7: =G7+M7 -> 1449990.3
B8: Multiverse | C8: =INDEX('Investment Characteristics'!$M$4:$M$30,MATCH(Reserves!$B8,'Investment Characteristics'!$L$4:$L$30,0)) -> D | D8: Workforce | E8: =INDEX('Investment Characteristics'!$F$4:$F$32,MATCH(Reserves!$B8,'Investment Characteristics'!$B$4:$B$32,0)) -> 134999.64 | F8: =G8-E8 -> 699995.97 | G8: =INDEX('Statement of Investments'!$L$5:$L$204,MATCH(B8,'Statement of Investments'!$E$5:$E$204,0)) -> 834995.61 | I8: 0 | J8: =I8+G8 -> 834995.61 | K8: G | L8: G | M8: 500000 | N8: =G8+M8 -> 1334995.6
B9: Physera | C9: =INDEX('Investment Characteristics'!$M$4:$M$30,MATCH(Reserves!$B9,'Investment Characteristics'!$L$4:$L$30,0)) -> Acquired | D9: Healthtech | E9: =INDEX('Investment Characteristics'!$F$4:$F$32,MATCH(Reserves!$B9,'Investment Characteristics'!$B$4:$B$32,0)) -> 500000 | F9: =G9-E9 -> 0 | G9: =E9 -> 500000 | I9: 0 | J9: =I9+G9 -> 500000 | K9: - | L9: Y | N9: =G9+M9 -> 500000
B10: Pill Club | C10: =INDEX('Investment Characteristics'!$M$4:$M$30,MATCH(Reserves!$B10,'Investment Characteristics'!$L$4:$L$30,0)) -> N/A | D10: Healthtech | E10: =INDEX('Investment Characteristics'!$F$4:$F$32,MATCH(Reserves!$B10,'Investment Characteristics'!$B$4:$B$32,0)) -> 999998.53 | F10: =G10-E10 -> 0 | G10: =INDEX('Statement of Investments'!$L$5:$L$204,MATCH(B10,'Statement of Investments'!$E$5:$E$204,0)) -> 999998.53 | I10: 0 | J10: =I10+G10 -> 999998.53 | K10: G | L10: Y | N10: =G10+M10 -> 999998.53
B11: QuitGenius | C11: =INDEX('Investment Characteristics'!$M$4:$M$30,MATCH(Reserves!$B11,'Investment Characteristics'!$L$4:$L$30,0)) -> #N/A | D11: Healthtech | E11: =INDEX('Investment Characteristics'!$F$4:$F$32,MATCH(Reserves!$B11,'Investment Characteristics'!$B$4:$B$32,0)) -> #N/A | F11: =G11-E11 -> #N/A | G11: =INDEX('Statement of Investments'!$L$5:$L$204,MATCH(B11,'Statement of Investments'!$E$5:$E$204,0)) -> #N/A | I11: 0 | J11: =I11+G11 -> #N/A | K11: G | L11: Y | M11: 500000 | N11: =G11+M11 -> #N/A
B12: Karat | C12: =INDEX('Investment Characteristics'!$M$4:$M$30,MATCH(Reserves!$B12,'Investment Characteristics'!$L$4:$L$30,0)) -> C | D12: Workforce | E12: =INDEX('Investment Characteristics'!$F$4:$F$32,MATCH(Reserves!$B12,'Investment Characteristics'!$B$4:$B$32,0)) -> 499998.66 | F12: =G12-E12 -> 499996.17 | G12: =INDEX('Statement of Investments'!$L$5:$L$204,MATCH(B12,'Statement of Investments'!$E$5:$E$204,0)) -> 999994.83 | I12: 0 | J12: =I12+G12 -> 999994.83 | K12: G | L12: Y | N12: =G12+M12 -> 999994.83
B13: Hatch | C13: =INDEX('Investment Characteristics'!$M$4:$M$30,MATCH(Reserves!$B13,'Investment Characteristics'!$L$4:$L$30,0)) -> Seed | D13: Workforce | E13: =INDEX('Investment Characteristics'!$F$4:$F$32,MATCH(Reserves!$B13,'Investment Characteristics'!$B$4:$B$32,0)) -> 258903.8 | F13: =G13-E13 -> 0 | G13: =INDEX('Statement of Investments'!$L$5:$L$204,MATCH(B13,'Statement of Investments'!$E$5:$E$204,0)) -> 258903.8 | I13: =250000 -> 250000 | J13: =I13+G13 -> 508903.8 | K13: Y | L13: G | N13: =G13+M13 -> 258903.8
B14: Human Interest | C14: =INDEX('Investment Characteristics'!$M$4:$M$30,MATCH(Reserves!$B14,'Investment Characteristics'!$L$4:$L$30,0)) -> D | D14: Financial | E14: =INDEX('Investment Characteristics'!$F$4:$F$32,MATCH(Reserves!$B14,'Investment Characteristics'!$B$4:$B$32,0)) -> 274999.89 | F14: =G14-E14 -> 815002.17 | G14: =INDEX('Statement of Investments'!$L$5:$L$204,MATCH(B14,'Statement of Investments'!$E$5:$E$204,0)) -> 1090002.1 | I14: 0 | J14: =I14+G14 -> 1090002.1 | K14: G | L14: G | N14: =G14+M14 -> 1090002.1
B15: Alice | C15: =INDEX('Investment Characteristics'!$M$4:$M$30,MATCH(Reserves!$B15,'Investment Characteristics'!$L$4:$L$30,0)) -> N/A | D15: Financial | E15: =INDEX('Investment Characteristics'!$F$4:$F$32,MATCH(Reserves!$B15,'Investment Characteristics'!$B$4:$B$32,0)) -> 600000.08 | F15: =G15-E15 -> 0 | G15: =INDEX('Statement of Investments'!$L$5:$L$204,MATCH(B15,'Statement of Investments'!$E$5:$E$204,0)) -> 600000.08 | I15: 250000 | J15: =I15+G15 -> 850000.08 | K15: R | L15: Y | N15: =G15+M15 -> 600000.08
B16: Path | C16: =INDEX('Investment Characteristics'!$M$4:$M$30,MATCH(Reserves!$B16,'Investment Characteristics'!$L$4:$L$30,0)) -> #N/A | D16: Healthtech | E16: =INDEX('Investment Characteristics'!$F$4:$F$32,MATCH(Reserves!$B16,'Investment Characteristics'!$B$4:$B$32,0)) -> #N/A | F16: =G16-E16 -> #N/A | G16: =INDEX('Statement of Investments'!$L$5:$L$204,MATCH(B16,'Statement of Investments'!$E$5:$E$204,0)) -> #N/A | I16: 0 | J16: =I16+G16 -> #N/A | K16: Y | L16: Y | N16: =G16+M16 -> #N/A
B17: Valence | C17: =INDEX('Investment Characteristics'!$M$4:$M$30,MATCH(Reserves!$B17,'Investment Characteristics'!$L$4:$L$30,0)) -> Realized | D17: Workforce | E17: =INDEX('Investment Characteristics'!$F$4:$F$32,MATCH(Reserves!$B17,'Investment Characteristics'!$B$4:$B$32,0)) -> 249999.49 | F17: =G17-E17 -> 0 | G17: =INDEX('Statement of Investments'!$L$5:$L$204,MATCH(B17,'Statement of Investments'!$E$5:$E$204,0)) -> 249999.49 | I17: 0 | J17: =I17+G17 -> 249999.49 | K17: Y | L17: G | N17: =G17+M17 -> 249999.49
B18: Terminal | C18: =INDEX('Investment Characteristics'!$M$4:$M$30,MATCH(Reserves!$B18,'Investment Characteristics'!$L$4:$L$30,0)) -> B | D18: Workforce | E18: =INDEX('Investment Characteristics'!$F$4:$F$32,MATCH(Reserves!$B18,'Investment Characteristics'!$B$4:$B$32,0)) -> 599999.73 | F18: =G18-E18 -> 0 | G18: =INDEX('Statement of Investments'!$L$5:$L$204,MATCH(B18,'Statement of Investments'!$E$5:$E$204,0)) -> 599999.73 | I18: 0 | J18: =I18+G18 -> 599999.73 | K18: Y | L18: G | N18: =G18+M18 -> 599999.73
B19: Sapling | C19: =INDEX('Investment Characteristics'!$M$4:$M$30,MATCH(Reserves!$B19,'Investment Characteristics'!$L$4:$L$30,0)) -> Acquired | D19: Workforce | E19: =INDEX('Investment Characteristics'!$F$4:$F$32,MATCH(Reserves!$B19,'Investment Characteristics'!$B$4:$B$32,0)) -> 249998.37 | F19: =G19-E19 -> 0 | G19: 249998.37 | I19: 0 | J19: =I19+G19 -> 249998.37 | K19: Y | L19: Y | N19: =G19+M19 -> 249998.37
B20: Charthop | C20: =INDEX('Investment Characteristics'!$M$4:$M$30,MATCH(Reserves!$B20,'Investment Characteristics'!$L$4:$L$30,0)) -> C | D20: Workforce | E20: =INDEX('Investment Characteristics'!$F$4:$F$32,MATCH(Reserves!$B20,'Investment Characteristics'!$B$4:$B$32,0)) -> 100000.6 | F20: =G20-E20 -> 1100001.1 | G20: =INDEX('Statement of Investments'!$L$5:$L$204,MATCH(B20,'Statement of Investments'!$E$5:$E$204,0)) -> 1200001.7 | I20: 0 | J20: =I20+G20 -> 1200001.7 | K20: G | L20: G | M20: 750000 | N20: =G20+M20 -> 1950001.7
B21: Rightway Health | C21: =INDEX('Investment Characteristics'!$M$4:$M$30,MATCH(Reserves!$B21,'Investment Characteristics'!$L$4:$L$30,0)) -> D | D21: Healthtech | E21: =INDEX('Investment Characteristics'!$F$4:$F$32,MATCH(Reserves!$B21,'Investment Characteristics'!$B$4:$B$32,0)) -> 499999.45 | F21: =G21-E21 -> 499999.02 | G21: =INDEX('Statement of Investments'!$L$5:$L$204,MATCH(B21,'Statement of Investments'!$E$5:$E$204,0)) -> 999998.47 | I21: 0 | J21: =I21+G21 -> 999998.47 | K21: G | L21: G | N21: =G21+M21 -> 999998.47
B22: Brightside Benefit | C22: =INDEX('Investment Characteristics'!$M$4:$M$30,MATCH(Reserves!$B22,'Investment Characteristics'!$L$4:$L$30,0)) -> B | D22: Financial | E22: =INDEX('Investment Characteristics'!$F$4:$F$32,MATCH(Reserves!$B22,'Investment Characteristics'!$B$4:$B$32,0)) -> 499999.53 | F22: =G22-E22 -> 0 | G22: =INDEX('Statement of Investments'!$L$5:$L$204,MATCH(B22,'Statement of Investments'!$E$5:$E$204,0)) -> 499999.53 | I22: 250000 | J22: =I22+G22 -> 749999.53 | K22: R | L22: Y | N22: =G22+M22 -> 499999.53
B23: Fountain | C23: =INDEX('Investment Characteristics'!$M$4:$M$30,MATCH(Reserves!$B23,'Investment Characteristics'!$L$4:$L$30,0)) -> C | D23: Workforce | E23: =INDEX('Investment Characteristics'!$F$4:$F$32,MATCH(Reserves!$B23,'Investment Characteristics'!$B$4:$B$32,0)) -> 405333.72 | F23: =G23-E23 -> 0 | G23: =INDEX('Statement of Investments'!$L$5:$L$204,MATCH(B23,'Statement of Investments'!$E$5:$E$204,0)) -> 405333.72 | I23: 0 | J23: =I23+G23 -> 405333.72 | K23: Y | L23: Y | N23: =G23+M23 -> 405333.72
B24: XP | C24: =INDEX('Investment Characteristics'!$M$4:$M$30,MATCH(Reserves!$B24,'Investment Characteristics'!$L$4:$L$30,0)) -> B | D24: Healthtech | E24: =INDEX('Investment Characteristics'!$F$4:$F$32,MATCH(Reserves!$B24,'Investment Characteristics'!$B$4:$B$32,0)) -> 800000 | F24: =G24-E24 -> 0 | G24: =INDEX('Statement of Investments'!$L$5:$L$204,MATCH(B24,'Statement of Investments'!$E$5:$E$204,0)) -> 800000 | I24: 400000 | J24: =I24+G24 -> 1200000 | K24: R | L24: G | M24: 500000 | N24: =G24+M24 -> 1300000
B25: Enrich | C25: =INDEX('Investment Characteristics'!$M$4:$M$30,MATCH(Reserves!$B25,'Investment Characteristics'!$L$4:$L$30,0)) -> Seed | D25: Workforce | E25: =INDEX('Investment Characteristics'!$F$4:$F$32,MATCH(Reserves!$B25,'Investment Characteristics'!$B$4:$B$32,0)) -> 399999.44 | F25: =G25-E25 -> 0 | G25: =INDEX('Statement of Investments'!$L$5:$L$204,MATCH(B25,'Statement of Investments'!$E$5:$E$204,0)) -> 399999.44 | I25: 0 | J25: =I25+G25 -> 399999.44 | K25: Y | L25: G | N25: =G25+M25 -> 399999.44
B26: Vetty | C26: =INDEX('Investment Characteristics'!$M$4:$M$30,MATCH(Reserves!$B26,'Investment Characteristics'!$L$4:$L$30,0)) -> A | D26: Workforce | E26: =INDEX('Investment Characteristics'!$F$4:$F$32,MATCH(Reserves!$B26,'Investment Characteristics'!$B$4:$B$32,0)) -> 255034 | F26: =G26-E26 -> 0 | G26: =INDEX('Statement of Investments'!$L$5:$L$204,MATCH(B26,'Statement of Investments'!$E$5:$E$204,0)) -> 255034 | I26: 0 | J26: =I26+G26 -> 255034 | K26: G | L26: G | M26: 250000 | N26: =G26+M26 -> 505034
B27: Ladder | C27: =INDEX('Investment Characteristics'!$M$4:$M$30,MATCH(Reserves!$B27,'Investment Characteristics'!$L$4:$L$30,0)) -> D | D27: Financial | E27: =INDEX('Investment Characteristics'!$F$4:$F$32,MATCH(Reserves!$B27,'Investment Characteristics'!$B$4:$B$32,0)) -> 749994.59 | F27: =G27-E27 -> 0 | G27: =INDEX('Statement of Investments'!$L$5:$L$204,MATCH(B27,'Statement of Investments'!$E$5:$E$204,0)) -> 749994.59 | I27: 0 | J27: =I27+G27 -> 749994.59 | K27: G | L27: G | N27: =G27+M27 -> 749994.59
B28: Galileo | C28: =INDEX('Investment Characteristics'!$M$4:$M$30,MATCH(Reserves!$B28,'Investment Characteristics'!$L$4:$L$30,0)) -> C | D28: Healthtech | E28: =INDEX('Investment Characteristics'!$F$4:$F$32,MATCH(Reserves!$B28,'Investment Characteristics'!$B$4:$B$32,0)) -> 749998.67 | F28: =G28-E28 -> 1002254.6 | G28: =INDEX('Statement of Investments'!$L$5:$L$204,MATCH(B28,'Statement of Investments'!$E$5:$E$204,0)) -> 1752253.3 | I28: 0 | J28: =I28+G28 -> 1752253.3 | K28: G | L28: Y | N28: =G28+M28 -> 1752253.3
B29: Level | C29: =INDEX('Investment Characteristics'!$M$4:$M$30,MATCH(Reserves!$B29,'Investment Characteristics'!$L$4:$L$30,0)) -> B | D29: Healthtech | E29: =INDEX('Investment Characteristics'!$F$4:$F$32,MATCH(Reserves!$B29,'Investment Characteristics'!$B$4:$B$32,0)) -> 1000002.7 | F29: =G29-E29 -> 0.01 | G29: =INDEX('Statement of Investments'!$L$5:$L$204,MATCH(B29,'Statement of Investments'!$E$5:$E$204,0)) -> 1000002.7 | I29: 0 | J29: =I29+G29 -> 1000002.7 | K29: G | L29: Y | N29: =G29+M29 -> 1000002.7
B30: Forage | C30: =INDEX('Investment Characteristics'!$M$4:$M$32,MATCH(Reserves!$B30,'Investment Characteristics'!$L$4:$L$32,0)) -> B | D30: Workforce | E30: =INDEX('Investment Characteristics'!$F$4:$F$32,MATCH(Reserves!$B30,'Investment Characteristics'!$B$4:$B$32,0)) -> 249999.58 | F30: =G30-E30 -> 0 | G30: =INDEX('Statement of Investments'!$L$5:$L$204,MATCH(B30,'Statement of Investments'!$E$5:$E$204,0)) -> 249999.58 | I30: 500000 | J30: =I30+G30 -> 749999.58 | M30: 750000 | N30: =G30+M30 -> 999999.58
E31: =SUM(E3:E30) -> #N/A | F31: =SUM(F3:F30) -> #N/A | G31: =SUM(G3:G30) -> #N/A | I31: =SUM(I3:I30) -> 2150000 | J31: =SUM(J3:J30) -> #N/A | M31: =SUM(M3:M30) -> 4000000 | N31: =SUM(N3:N30) -> #N/A
I32: Total Investment % | J32: =J31/(20.7*10^6) -> #N/A | M32: Total Investment % | N32: =N31/(20.7*10^6) -> #N/A
E34: =+E31/G31 -> #N/A
G35: =12/28 -> 0.42857143
E37: =E3/G3 -> 0.3299785 | F37: =F3/G3 -> 0.6700215
E38: =E4/G4 -> 0.10000036 | F38: =F4/G4 -> 0.89999964
E39: =E6/G6 -> 0.36621115 | F39: =F6/G6 -> 0.63378885
E40: =E7/G7 -> 0.13793195 | F40: =F7/G7 -> 0.86206805
E41: =E8/G8 -> 0.16167707 | F41: =F8/G8 -> 0.83832293
E42: =E11/G11 -> #N/A | F42: =F11/G11 -> #N/A
E43: =E12/G12 -> 0.50000125 | F43: =F12/G12 -> 0.49999875
E44: =E14/G14 -> 0.252293 | F44: =F14/G14 -> 0.747707
E45: =E16/G16 -> #N/A | F45: =F16/G16 -> #N/A
E46: =E20/G20 -> 0.083333717 | F46: =F20/G20 -> 0.91666628
E47: =E21/G21 -> 0.50000021 | F47: =F21/G21 -> 0.49999979
E48: =E28/G28 -> 0.42801956 | F48: =F28/G28 -> 0.57198044

Sheet Exit Forecast
B1: IN PROGRESS
B5: Exit Forecast
H6: Revenue | N6: 0.25 | O6: 0.5 | P6: 0.25
B7: Company | C7: Partner | D7: Current Stage | E7: Ownership | F7: Total Inv. | G7: Mkt. Value | H7: 2023A | I7: 2024A | J7: 2025E | K7: 3 Yr CAGR | L7: ARR as of 6.30 | M7: Holding Value | N7: Bear | O7: Base | P7: Bull | R7: Weighted Exit | S7: Exit Ownership | T7: Exit Proceeds | U7: Exit MOIC
B8: Spring | C8: RP | D8: E | E8: 0.01 | F8: =INDEX('Statement of Investments'!$L$5:$L$204,MATCH(B8,'Statement of Investments'!$E$5:$E$204,0)) -> 1449990.3 | G8: =INDEX('Statement of Investments'!$O$5:$O$204,MATCH(B8,'Statement of Investments'!$E$5:$E$204,0)) -> 28841289 | H8: – | I8: – | J8: – | K8: - | L8: – | M8: 3300000000 | N8: 3300000000 | O8: 5000000000 | P8: 7000000000 | R8: =(N8*$N$6)+(O8*$O$6)+(P8*$P$6) -> 5075000000 | S8: 0.00878 | T8: =R8*S8 -> 44558500 | U8: =T8/F8 -> 30.730205
B9: Rula | C9: CT | D9: C | E9: 0.013 | F9: =INDEX('Statement of Investments'!$L$5:$L$204,MATCH(B9,'Statement of Investments'!$E$5:$E$204,0)) -> 496199.35 | G9: =INDEX('Statement of Investments'!$O$5:$O$204,MATCH(B9,'Statement of Investments'!$E$5:$E$204,0)) -> 6277910.6 | H9: 60415684 | I9: 121610895 | J9: 224398598 | K9: 0.93 | L9: 6.6489927e+08 | M9: 1250000000 | N9: =+M9 -> 1250000000 | O9: 2000000000 | P9: 5000000000 | R9: =(N9*$N$6)+(O9*$O$6)+(P9*$P$6) -> 2562500000 | S9: 0.01143 | T9: =R9*S9 -> 29289375 | U9: =T9/F9 -> 59.027435
B10: Rightway Health | C10: CT | D10: C | E10: 0.022 | F10: =INDEX('Statement of Investments'!$L$5:$L$204,MATCH(B10,'Statement of Investments'!$E$5:$E$204,0)) -> 999998.47 | G10: =INDEX('Statement of Investments'!$O$5:$O$204,MATCH(B10,'Statement of Investments'!$E$5:$E$204,0)) -> 13426663 | H10: 21546850 | I10: 47074859 | J10: 69679639 | K10: 0.8 | L10: Pending | M10: 625000000 | N10: 625000000 | O10: 1500000000 | P10: 3000000000 | R10: =(N10*$N$6)+(O10*$O$6)+(P10*$P$6) -> 1656250000 | S10: 0.01957 | T10: =R10*S10 -> 32412812 | U10: =T10/F10 -> 32.412862
B11: Multiverse | C11: RP | D11: D | E11: 0.005 | F11: =INDEX('Statement of Investments'!$L$5:$L$204,MATCH(B11,'Statement of Investments'!$E$5:$E$204,0)) -> 834995.61 | G11: =INDEX('Statement of Investments'!$O$5:$O$204,MATCH(B11,'Statement of Investments'!$E$5:$E$204,0)) -> 9377802.2 | H11: 75025357 | I11: – | J11: – | K11: - | L11: Pending | M11: 1700000000 | N11: 700000000 | O11: 1700000000 | P11: 2000000000 | R11: =(N11*$N$6)+(O11*$O$6)+(P11*$P$6) -> 1525000000 | S11: 0.0045 | T11: =R11*S11 -> 6862500 | U11: =T11/F11 -> 8.2186061
B12: Carrot | C12: RP | D12: D | E12: 0.009 | F12: =INDEX('Statement of Investments'!$L$5:$L$204,MATCH(B12,'Statement of Investments'!$E$5:$E$204,0)) -> 999996.37 | G12: =INDEX('Statement of Investments'!$O$5:$O$204,MATCH(B12,'Statement of Investments'!$E$5:$E$204,0)) -> 5663568.2 | H12: – | I12: – | J12: – | K12: - | L12: Pending | M12: 600000000 | N12: 600000000 | O12: 1000000000 | P12: 2000000000 | R12: =(N12*$N$6)+(O12*$O$6)+(P12*$P$6) -> 1150000000 | S12: 0.00849 | T12: =R12*S12 -> 9763500 | U12: =T12/F12 -> 9.7635354
B13: Human Interest | C13: CH | D13: D | E13: 0.004 | F13: =INDEX('Statement of Investments'!$L$5:$L$204,MATCH(B13,'Statement of Investments'!$E$5:$E$204,0)) -> 1090002.1 | G13: =INDEX('Statement of Investments'!$O$5:$O$204,MATCH(B13,'Statement of Investments'!$E$5:$E$204,0)) -> 10743747 | H13: 60172052 | I13: 105094000 | J13: – | K13: - | L13: 147664441 | M13: 3000000000 | N13: =+M13*0.8 -> 2400000000 | O13: =+M13 -> 3000000000 | P13: 4000000000 | R13: =(N13*$N$6)+(O13*$O$6)+(P13*$P$6) -> 3100000000 | S13: 0.00378 | T13: =R13*S13 -> 11718000 | U13: =T13/F13 -> 10.750438
B14: Pelago | C14: RP | D14: C | E14: 0.011 | F14: =INDEX('Statement of Investments'!$L$5:$L$204,MATCH(B14,'Statement of Investments'!$E$5:$E$204,0)) -> 549993.11 | G14: =INDEX('Statement of Investments'!$O$5:$O$204,MATCH(B14,'Statement of Investments'!$E$5:$E$204,0)) -> 4289097.2 | H14: 6127072 | I14: 12579516 | J14: – | K14: - | L14: 6629713 | M14: 365000000 | N14: 100000000 | O14: 365000000 | P14: 500000000 | R14: =(N14*$N$6)+(O14*$O$6)+(P14*$P$6) -> 332500000 | S14: 0.01 | T14: =R14*S14 -> 3325000 | U14: =T14/F14 -> 6.0455303
B15: Galileo | C15: CT | D15: C | E15: 0.006 | F15: =INDEX('Statement of Investments'!$L$5:$L$204,MATCH(B15,'Statement of Investments'!$E$5:$E$204,0)) -> 1752253.3 | G15: =INDEX('Statement of Investments'!$O$5:$O$204,MATCH(B15,'Statement of Investments'!$E$5:$E$204,0)) -> 2656434 | H15: 16648369 | I15: 39582209 | J15: 65878599 | K15: 0.99 | L15: 14500000 | M15: 600000000 | N15: 100000000 | O15: 300000000 | P15: 500000000 | R15: =(N15*$N$6)+(O15*$O$6)+(P15*$P$6) -> 300000000 | S15: 0.00584 | T15: =R15*S15 -> 1752000 | U15: =T15/F15 -> 0.99985546
B16: XP | C16: CH | D16: B | E16: 0.017 | F16: =INDEX('Statement of Investments'!$L$5:$L$204,MATCH(B16,'Statement of Investments'!$E$5:$E$204,0)) -> 800000 | G16: =INDEX('Statement of Investments'!$O$5:$O$204,MATCH(B16,'Statement of Investments'!$E$5:$E$204,0)) -> 1981323 | H16: 5578000 | I16: 9100000 | J16: – | K16: - | L16: Pending | M16: 120000000 | N16: =M16 -> 120000000 | O16: 500000000 | P16: 1000000000 | R16: =(N16*$N$6)+(O16*$O$6)+(P16*$P$6) -> 530000000 | S16: 0.01321 | T16: =R16*S16 -> 7001300 | U16: =T16/F16 -> 8.751625
B17: Fountain | C17: ABG | D17: C | E17: 0.002 | F17: =INDEX('Statement of Investments'!$L$5:$L$204,MATCH(B17,'Statement of Investments'!$E$5:$E$204,0)) -> 405333.72 | G17: =INDEX('Statement of Investments'!$O$5:$O$204,MATCH(B17,'Statement of Investments'!$E$5:$E$204,0)) -> 1677733 | H17: 32636880 | I17: 32000000 | J17: – | K17: - | L17: Pending | M17: 860000000 | N17: 300000000 | O17: 500000000 | P17: 1000000000 | R17: =(N17*$N$6)+(O17*$O$6)+(P17*$P$6) -> 575000000 | S17: 0.00176 | T17: =R17*S17 -> 1012000 | U17: =T17/F17 -> 2.4967081
B18: Hone | C18: RP | D18: B | E18: 0.014 | F18: =INDEX('Statement of Investments'!$L$5:$L$204,MATCH(B18,'Statement of Investments'!$E$5:$E$204,0)) -> 682666.27 | G18: =INDEX('Statement of Investments'!$O$5:$O$204,MATCH(B18,'Statement of Investments'!$E$5:$E$204,0)) -> 1756737.3 | H18: 7750413 | I18: 7590763 | J18: 8673501 | K18: 0.06 | L18: Pending | M18: 126200000 | N18: 75000000 | O18: 126200000 | P18: 250000000 | R18: =(N18*$N$6)+(O18*$O$6)+(P18*$P$6) -> 144350000 | S18: 0.01115 | T18: =R18*S18 -> 1609502.5 | U18: =T18/F18 -> 2.357671
B19: Charthop | C19: RP | D19: C | E19: 0.008 | F19: =INDEX('Statement of Investments'!$L$5:$L$204,MATCH(B19,'Statement of Investments'!$E$5:$E$204,0)) -> 1200001.7 | G19: =INDEX('Statement of Investments'!$O$5:$O$204,MATCH(B19,'Statement of Investments'!$E$5:$E$204,0)) -> 1200001.7 | H19: 11787745 | I19: 7936981 | J19: 9193161 | K19: -0.12 | L19: 8359314 | M19: 74000000 | N19: 0 | O19: 74000000 | P19: 150000000 | R19: =(N19*$N$6)+(O19*$O$6)+(P19*$P$6) -> 74500000 | S19: 0.00741 | T19: =R19*S19 -> 552045 | U19: =T19/F19 -> 0.46003686
B20: Karat | C20: CH | D20: C | E20: 0.005 | F20: =INDEX('Statement of Investments'!$L$5:$L$204,MATCH(B20,'Statement of Investments'!$E$5:$E$204,0)) -> 999994.83 | G20: =INDEX('Statement of Investments'!$O$5:$O$204,MATCH(B20,'Statement of Investments'!$E$5:$E$204,0)) -> 999994.83 | H20: 17900000 | I20: 16800000 | J20: 21900000 | K20: 0.11 | L20: 23000000 | M20: 168000000 | N20: 0 | O20: 168000000 | P20: 500000000 | R20: =(N20*$N$6)+(O20*$O$6)+(P20*$P$6) -> 209000000 | S20: 0.00424 | T20: =R20*S20 -> 886160 | U20: =T20/F20 -> 0.88616458
B21: Valence | C21: ABG | D21: A | E21: 0.01 | F21: =INDEX('Statement of Investments'!$L$5:$L$204,MATCH(B21,'Statement of Investments'!$E$5:$E$204,0)) -> 249999.49 | G21: =INDEX('Statement of Investments'!$O$5:$O$204,MATCH(B21,'Statement of Investments'!$E$5:$E$204,0)) -> 1997507.1 | H21: – | I21: – | J21: – | K21: - | L21: Pending | M21: 265000000 | N21: =M21 -> 265000000 | O21: 500000000 | P21: 1000000000 | R21: =(N21*$N$6)+(O21*$O$6)+(P21*$P$6) -> 566250000 | S21: 0.00689 | T21: =G21 -> 1997507.1 | U21: =T21/F21 -> 7.9900445
B22: Ladder | C22: CH | D22: D | E22: 0.002 | F22: =INDEX('Statement of Investments'!$L$5:$L$204,MATCH(B22,'Statement of Investments'!$E$5:$E$204,0)) -> 749994.59 | G22: =INDEX('Statement of Investments'!$O$5:$O$204,MATCH(B22,'Statement of Investments'!$E$5:$E$204,0)) -> 759917.21 | H22: – | I22: 49313412 | J22: – | K22: - | L22: $26M (H1'25 Rev) | M22: 330000000 | N22: 0 | O22: 330000000 | P22: 500000000 | R22: =(N22*$N$6)+(O22*$O$6)+(P22*$P$6) -> 290000000 | S22: 0.00223 | T22: =R22*S22 -> 646700 | U22: =T22/F22 -> 0.86227289
B23: Brightside Benefit | C23: CH | D23: B | E23: 0.001 | F23: =INDEX('Statement of Investments'!$L$5:$L$204,MATCH(B23,'Statement of Investments'!$E$5:$E$204,0)) -> 499999.53 | G23: =INDEX('Statement of Investments'!$O$5:$O$204,MATCH(B23,'Statement of Investments'!$E$5:$E$204,0)) -> 438844.21 | H23: 5535433 | I23: 19460501 | J23: 33268745 | K23: 1.45 | L23: 32861386 | M23: 170000000 | N23: 0 | O23: 170000000 | P23: 200000000 | R23: =(N23*$N$6)+(O23*$O$6)+(P23*$P$6) -> 135000000 | S23: 0.00089 | T23: =R23*S23 -> 120150 | U23: =T23/F23 -> 0.24030023
B24: Vetty | C24: RP | D24: A | E24: 0.019 | F24: =INDEX('Statement of Investments'!$L$5:$L$204,MATCH(B24,'Statement of Investments'!$E$5:$E$204,0)) -> 255034 | G24: 0 | H24: 6346968 | I24: – | J24: – | K24: - | L24: Pending | M24: 13000000 | N24: 0 | O24: 13000000 | P24: 50000000 | R24: =(N24*$N$6)+(O24*$O$6)+(P24*$P$6) -> 19000000 | S24: 0.01346 | T24: =R24*S24 -> 255740 | U24: =T24/F24 -> 1.0027683
B25: Hatch | C25: RP | D25: Seed | E25: 0.006 | F25: =INDEX('Statement of Investments'!$L$5:$L$204,MATCH(B25,'Statement of Investments'!$E$5:$E$204,0)) -> 258903.8 | G25: =INDEX('Statement of Investments'!$O$5:$O$204,MATCH(B25,'Statement of Investments'!$E$5:$E$204,0)) -> 133950.81 | H25: 4725281 | I25: 760642 | J25: 1550352 | K25: -0.43 | L25: 1059932 | M25: 25000000 | N25: 0 | O25: 25000000 | P25: 50000000 | R25: =(N25*$N$6)+(O25*$O$6)+(P25*$P$6) -> 25000000 | S25: 0.00349 | T25: =R25*S25 -> 87250 | U25: =T25/F25 -> 0.33699776
B26: Cleo | C26: CT | D26: C | E26: 0.002 | F26: =INDEX('Statement of Investments'!$L$5:$L$204,MATCH(B26,'Statement of Investments'!$E$5:$E$204,0)) -> 100000 | G26: =INDEX('Statement of Investments'!$O$5:$O$204,MATCH(B26,'Statement of Investments'!$E$5:$E$204,0)) -> 0 | H26: – | I26: – | J26: – | K26: - | L26: – | M26: – | N26: 0 | O26: 0 | P26: 0 | R26: =(N26*$N$6)+(O26*$O$6)+(P26*$P$6) -> 0 | S26: 0.00151 | T26: =R26*S26 -> 0 | U26: =T26/F26 -> 0
B27: Terminal | C27: ABG | D27: B | E27: 0.004 | F27: =INDEX('Statement of Investments'!$L$5:$L$204,MATCH(B27,'Statement of Investments'!$E$5:$E$204,0)) -> 599999.73 | G27: =INDEX('Statement of Investments'!$O$5:$O$204,MATCH(B27,'Statement of Investments'!$E$5:$E$204,0)) -> 0 | H27: 55223893 | I27: 47067203 | J27: 42655885 | K27: -0.12 | L27: 45347986 | M27: – | N27: 0 | O27: 0 | P27: 0 | R27: =(N27*$N$6)+(O27*$O$6)+(P27*$P$6) -> 0 | S27: 0.00334 | T27: =R27*S27 -> 0 | U27: =T27/F27 -> 0
B28: Enrich | C28: ABG | D28: Seed | E28: 0.038 | F28: =INDEX('Statement of Investments'!$L$5:$L$204,MATCH(B28,'Statement of Investments'!$E$5:$E$204,0)) -> 399999.44 | G28: =INDEX('Statement of Investments'!$O$5:$O$204,MATCH(B28,'Statement of Investments'!$E$5:$E$204,0)) -> 0 | H28: – | I28: 622164 | J28: 1038000 | K28: - | L28: Pending | M28: – | N28: 0 | O28: 0 | P28: 0 | R28: =(N28*$N$6)+(O28*$O$6)+(P28*$P$6) -> 0 | S28: 0.02286 | T28: =R28*S28 -> 0 | U28: =T28/F28 -> 0
B29: Omada Health | D29: IPO | F29: =INDEX('Statement of Investments'!$L$5:$L$204,MATCH(B29,'Statement of Investments'!$E$5:$E$204,0)) -> 291986.05 | G29: =INDEX('Statement of Investments'!$O$5:$O$204,MATCH(B29,'Statement of Investments'!$E$5:$E$204,0)) -> 475335.52 | T29: =G29 -> 475335.52 | U29: =T29/F29 -> 1.6279391
F30: ='Statement of Investments'!L204 -> 19553337 | G30: =SUM(G8:G29) -> 92697856 | T30: =SUM(T8:T29) -> 1.5432538e+08 | U30: =T30/F30 -> 7.8925339

Sheet Net IRR
A1: Actual
B3: As of | C3: 43830
B4: Fund Commit | C4: 20730000
B6: LP Net Performance | H6: NAV Reconciliation
B7: Date | C7: Contributions | D7: Distributions | E7: NAV | F7: CF | H7: Assets
B8: 43404 | C8: -2575650 | D8: 0 | E8: 0 | F8: =SUM(C8:E8) -> -2575650 | H8: Cash | I8: 3909832
B9: 43489 | C9: -463650 | D9: 0 | E9: 0 | F9: =SUM(C9:E9) -> -463650 | H9: Contributions receivable | I9: 0
B10: 43616 | C10: -1478400 | D10: 0 | E10: 0 | F10: =SUM(C10:E10) -> -1478400 | H10: Portfolio interest receivable | I10: 4140
B11: 43781 | C11: -2323200 | D11: 0 | E11: 0 | F11: =SUM(C11:E11) -> -2323200 | H11: Investments at Cost | I11: 9092764
B12: 43781 | C12: -6840900 | D12: 0 | E12: 0 | F12: =SUM(C12:E12) -> -6840900 | H12: Estimate of Unrealized Gain on Investments | I12: =I13-I11 -> 2086099
B13: =C3 -> 43830 | C13: 0 | D13: 0 | E13: =I23 -> 15046453 | F13: =SUM(C13:E13) -> 15046453 | H13: Investments at Fair Value | I13: 11178863
B14: Net IRR | C14: =SUM(C8:C13) -> -13681800 | D14: =SUM(D8:D13) -> 0 | E14: =SUM(E8:E13) -> 15046453 | F14: =XIRR(F8:F13,B8:B13) -> 0.25105039 | H14: Assets | I14: =I13+SUM(I8:I10) -> 15092835
H16: Liabilities
H17: Accounts Payable | I17: 12382
H18: Notes payable | I18: 0
H19: Management fee payable | I19: 0
H20: Prefunded contributions | I20: 34000
H21: Liabilities | I21: =SUM(I17:I20) -> 46382
H23: NAV | I23: =I14-I21 -> 15046453
A28: Pro-Forma
B30: As of | C30: ='Statement of Investments'!C1 -> 45930 | I30: Pro-forma
B31: LP Net Performance | H31: NAV Reconciliation | K31: Fund Commit: | L31: =C4 -> 20730000
B32: Date | C32: Contributions | D32: Distributions | E32: NAV | F32: CF | H32: Assets | K32: Waived Fees: | L32: -4800000
B33: 43404 | C33: -2575650 | D33: 0 | E33: 0 | F33: =SUM(C33:E33) -> -2575650 | H33: Cash | I33: =971756-'Investment Rollover'!D17 -> 971756 | K33: Net Commit | L33: =SUM(L31:L32) -> 15930000 | M33: =L33/L31 -> 0.76845152
B34: 43489 | C34: -463650 | D34: 0 | E34: 0 | F34: =SUM(C34:E34) -> -463650 | H34: Contributions receivable | I34: 0 | K34: Annual Mgmt Fees | L34: =L33*0.02 -> 318600
B35: 43616 | C35: -1478400 | D35: 0 | E35: 0 | F35: =SUM(C35:E35) -> -1478400 | H35: Portfolio interest receivable | I35: 4140
B36: 43781 | C36: -2323200 | D36: 0 | E36: 0 | F36: =SUM(C36:E36) -> -2323200 | H36: Investments at Cost | I36: ='Investment Rollover'!F27 -> 15538333
B37: 43781 | C37: -6840900 | D37: 0 | E37: 0 | F37: =SUM(C37:E37) -> -6840900 | H37: Estimate of Unrealized Gain on Investments | I37: =I38-I36 -> 75283006
B38: =C30 -> 45930 | C38: 0 | D38: 0 | E38: =I48 -> 90671203 | F38: =SUM(C38:E38) -> 90671203 | H38: Investments at Fair Value | I38: ='Investment Rollover'!M27 -> 90821339
B39: Net IRR | C39: =SUM(C33:C38) -> -13681800 | D39: =SUM(D33:D38) -> 0 | E39: =SUM(E33:E38) -> 90671203 | F39: =XIRR(F33:F38,B33:B38) -> 0.35763722 | H39: Assets | I39: =I38+SUM(I33:I35) -> 91797235
H41: Liabilities
H42: Accounts Payable | I42: 12382
H43: Notes payable | I43: 1000000
H44: Management fee payable | I44: =L34/4 -> 79650
H45: Prefunded contributions | I45: 34000
H46: Liabilities | I46: =SUM(I42:I45) -> 1126032
H48: NAV | I48: =I39-I46 -> 90671203
